Workbook
Name \0: #REF!
Name \a: #N/A
Name \a: #N/A
Name \a: #N/A
Name \a: #N/A
Name \a: #N/A
Name \a: #N/A
Name \a: #N/A
Name \a: #N/A
Name \a: #N/A
Name \a: #N/A
Name \a: #N/A
Name \a: #N/A
Name \a: #N/A
Name \a: #N/A
Name \a: #N/A
Name \a: #REF!
Name \b: #N/A
Name \c: #N/A
Name \d: #N/A
Name \e: #N/A
Name \f: #N/A
Name \g: #N/A
Name \h: [1]PP!$IC$5
Name \h: #N/A
Name \h: #N/A
Name \h: #N/A
Name \h: #N/A
Name \h: #N/A
Name \h: #N/A
Name \h: #N/A
Name \h: #N/A
Name \h: #N/A
Name \h: #N/A
Name \h: #N/A
Name \h: #N/A
Name \h: #N/A
Name \h: #N/A
Name \h: #N/A
Name \h: #REF!
Name \i: [1]PP!$IP$7844
Name \i: #N/A
Name \i: #N/A
Name \i: #N/A
Name \i: #N/A
Name \i: #N/A
Name \i: #N/A
Name \i: #N/A
Name \i: #N/A
Name \i: #N/A
Name \i: #N/A
Name \i: #N/A
Name \i: #N/A
Name \i: #N/A
Name \i: #N/A
Name \i: #N/A
Name \i: #REF!
Name \j: #N/A
Name \k: #N/A
Name \KWS123: #N/A

Sheet IBSHI đơn 5 (4)
B1: C¤NG TY tnhh tm ngäc hiÕu | D1: céng hoµ x· héi chñ nghÜa viÖt nam
B2: Sè 8 M¸y T¬ - Ng« QuyÒn - H¶i Phßng | D2: §éc LËp - Tù Do - H¹nh Phóc
A3: -----J----- | D3: ---------o0o--------
D4: H¶i Phßng, Ngµy 05 th¸ng 11 n¨m 2025
C6: b¸o gi¸
B7: Kính gửi: CÔNG TY IBSHI
A8: Theo yªu cÇu cña Quý C«ng ty. Chóng t«i cã thÓ cung cÊp cho C«ng ty c¸c mÆt hµng sau: | L8: =L5+L6 -> 0
A10: STT | B10: Quy cách | C10: Số lượng (cây) | D10: Trọng lượng | E10: Đơn Giá | F10: Thành tiền | G10: bazem
A11: I90-C5 | B11: Thép tấm 10*2000*12000 | C11: 1 | D11: =ROUND(10*2*12*7.85*C11,0) -> 1884 | E11: =ROUND(G11/1.1,2) -> 13636.36 | F11: =ROUND(E11*D11,0) -> 25690902 | G11: 15000 | H11: oke
A12: I90-C6 | B12: Thép tấm 12*2000*12000 | C12: 1 | D12: =ROUND(12*2*12*7.85*C12,0) -> 2261 | E12: =ROUND(G12/1.1,2) -> 13636.36 | F12: =ROUND(E12*D12,0) -> 30831810 | G12: 15000 | H12: oke
A13: I90-C7 | B13: Thép tấm 16*2000*6000 | C13: 1 | D13: =ROUND(16*2*6*7.85*C13,0) -> 1507 | E13: =ROUND(G13/1.1,2) -> 14000 | F13: =ROUND(E13*D13,0) -> 21098000 | G13: 15400 | H13: oke
A14: I90-C8 | B14: Thép tấm 20*2000*12000 | C14: 1 | D14: =ROUND(20*2*12*7.85*C14,0) -> 3768 | E14: =ROUND(G14/1.1,2) -> 14181.82 | F14: =ROUND(E14*D14,0) -> 53437098 | G14: 15600 | H14: oke
A15: I90-C12 | B15: Thép H125*125*6,5*9*12000 | C15: 6 | D15: =ROUND(23.6*12*C15,0) -> 1699 | E15: =ROUND(G15/1.1,2) -> 17545.45 | F15: =ROUND(E15*D15,0) -> 29809720 | G15: 19300 | H15: oke | I15: =C15*12 -> 72 | J15: 74 | K15: H125x125x6.5x9
A16: I90-C13 | B16: Thép H200*200*8*12*12000 | C16: 12 | D16: =ROUND(49.9*12*C16,0) -> 7186 | E16: =ROUND(G16/1.1,2) -> 17545.45 | F16: =ROUND(E16*D16,0) -> 126081604 | G16: 19300 | H16: oke | I16: =C16*12 -> 144 | J16: 139.26525 | K16: H200x200x8x12 | L16: H200x200x8x12
A17: I90-C15 | B17: Thép H250*250*9*14*12000 | C17: 3 | D17: =ROUND(71.8*12*C17,0) -> 2585 | E17: =ROUND(G17/1.1,2) -> 17545.45 | F17: =ROUND(E17*D17,0) -> 45354988 | G17: 19300 | H17: oke | I17: =C17*12 -> 36 | J17: 25.68 | K17: H250x250x9x14 | L17: H250x250x9x14
A18: I90-C16 | B18: Thép H150*150*7*10*12000 | C18: 3.5 | D18: =ROUND(31.1*12*C18,0) -> 1306 | E18: =ROUND(G18/1.1,2) -> 17545.45 | F18: =ROUND(E18*D18,0) -> 22914358 | G18: 19300 | H18: oke | I18: =C18*12 -> 42 | J18: 42 | K18: H150x150x7x10 | L18: H150x150x7x10
A19: I90-C21 | B19: Thép U200*90*8*13,5*12000 | C19: 8 | D19: =ROUND(30.3*12*C19,0) -> 2909 | E19: =ROUND(G19/1.1,2) -> 17545.45 | F19: =ROUND(E19*D19,0) -> 51039714 | G19: 19300 | H19: oke | I19: =C19*12 -> 96 | J19: 93.5 | K19: U200x90x8.5x13.5 | L19: Thép U200x90x8x13.5x12000 | M19: U200x90x8.5x13.5
A20: I90-C22 | B20: Thép U250*90*9*13*12000 | C20: 35 | D20: =ROUND(34.6*12*C20,0) -> 14532 | E20: =ROUND(G20/1.1,2) -> 17545.45 | F20: =ROUND(E20*D20,0) -> 254970479 | G20: 19300 | H20: oke | I20: =C20*12 -> 420 | J20: 420.7574 | K20: U250x90x9x13x120000 | L20: Thép U250x90x9x13x120000 | M20: U250x90x9x13x120000
A21: I90-C24 | B21: Thép U300x90x9x13 x120000 | C21: 1 | D21: =ROUND(38.1*12*C21,0) -> 457 | E21: =ROUND(G21/1.1,2) -> 17545.45 | F21: =ROUND(E21*D21,0) -> 8018271 | G21: 19300 | H21: oke | I21: =C21*12 -> 12 | J21: 12 | K21: U300x90x9x12 x120000 | L21: U280x100x9x13 | M21: U300x90x9x12 x120000
A22: I90-C26 | B22: Thép U125*65*6*8*12000 | C22: 11 | D22: =ROUND(13.4*12*C22,0) -> 1769 | E22: =ROUND(G22/1.1,2) -> 17545.45 | F22: =ROUND(E22*D22,0) -> 31037901 | G22: 19300 | H22: oke | I22: =C22*12 -> 132 | J22: 127 | K22: U125x65x6x8 | L22: Hùng Nguyên 4 cây (U125x65x6x8) | M22: U125x65x6x8
A23: I90-C28 | B23: Thép V150*150*10*6000 | C23: 1 | D23: =ROUND(23*6*C23,0) -> 138 | E23: =ROUND(G23/1.1,2) -> 15909.09 | F23: =ROUND(E23*D23,0) -> 2195454 | G23: 17500 | H23: oke | I23: =C23*12 -> 12 | J23: 3
A24: I90-C29 | B24: Thép V80*80*8*6000 | C24: 3 | D24: =ROUND(9.63*6*C24,0) -> 173 | E24: =ROUND(G24/1.1,2) -> 13909.09 | F24: =ROUND(E24*D24,0) -> 2406273 | G24: 15300 | H24: oke | I24: =C24*12 -> 36 | J24: 32.406312 | K24: Thép góc V75x75x7x6000
A25: I90-C30 | B25: Thép V75*75*6*12000 | C25: 3 | D25: =ROUND(6.85*12*C25,0) -> 247 | E25: =ROUND(G25/1.1,2) -> 13909.09 | F25: =ROUND(E25*D25,0) -> 3435545 | G25: 15300 | H25: oke | I25: =C25*12 -> 36 | J25: 15.84 | K25: Thép góc V80x80x8x6000
A26: 16 | F26: =ROUND(SUM(F11:F25),0) -> 708322117 | I26: =C26*12 -> 0
A27: 17 | B27: VAT 10% | F27: =ROUND(F26*10%,0) -> 70832212
A29: Tæng Céng | D29: =SUM(D11:D28) -> 42421 | F29: =F26+F27 -> 779154329
B30: - Hiệu lực báo giá: báo giá có giá trị hết ngày 10/11/2025 , giá đã bao gồm VAT 10% | H30: 1 | K30: hoan
B31: - Điều kiện giao hàng: hàng giao theo bazem kho bên bán trên phương tiện bên mua.
B32: - Thời hạn thanh toán: trước khi nhận hàng.
B33: - Nếu quý công ty chấp nhận xin vui lòng fax lại số: 0313.528921
B34: Xin trân trọng cảm ơn.
B35: XÁC NHẬN CỦA BÊN MUA | D35: CÔNG TY TNHH TM NGỌC HIẾU

Sheet Máy hàn
A1: BID ANALYSIS - GIẢI TRÌNH MUA SẮM/ĐẤU THẦU
A3: Project | B3: PROJECT No/ Dự án: Phục Vụ Sản Xuất
A4: Dự án
A5: Subject | B5: Cung cấp máy hàn
A6: Chủ đề
A8: No. | B8: CONTENT | D8: Dự toán | G8: Đã mua/Đã đặt | H8: Đơn vị cung cấp chào giá (vnđ) | K8: Lựa chọn | L8: Ghi chú
A9: Item | B9: Description/ Chi tiết | C9: Số lượng (PSC) | D9: Khối lượng/ Số lượng | E9: Đơn giá (vnd) | F9: Thành tiền (vnd) | G9: Thành tiền (vnd) | H9: C.Ty C.Phần Công Nghiệp WELDCOM
C10: Số lượng (cây) | H10: Phạm vi | I10: Đơn giá chưa VAT (VND) | J10: Thành Tiền ( có VAT 8%)
A11: Tổng | D11: N/A | E11: N/A | J11: =SUM(J12:J12) -> 600000000 | L11: =F11-G11-J11 -> -600000000
A12: 1 | B12: M01M-011437 Máy hàn bán tự động MIG500 N388- Jassic (TP5) Bảo hành: 18 tháng (Phụ kiện theo máy bao gồm: Cấp dây 15M cáp 50, súng QTB-500 3M, đồng hồ 36V) | C12: 20 | D12: N/A | E12: N/A | F12: N/A | G12: N/A | H12: V | I12: 27777778 | J12: 600000000 | K12: WELDCOM
B13: Đơn giá tổng hợp
A14: II | B14: Khối lượng dự kiến giao (Kg )/ Estimated weight (Kg):
A15: 1 | B15: …
A16: 2 | B16: …
A17: III | B17: Tiến độ/ Schedule
A18: 1 | B18: ….
A20: IV | B20: Nhân lực/ ManPower
A21: 1 | B21: Thợ Pha cắt / Thợ sắt / Thợ hàn / …
B22: ….
A23: V | B23: Yêu cầu kỹ thuật: Tham chiếu các tài liệu đính kèm/ Technical requirement – refer to document attached
B24: Xếp hạng | I24: 1
A25: Ghi Chú: PTM tiến hành ngay công tác mua hàng
A26: NGƯỜI ĐỀ NGHỊ/ RECOMMENDATION BY: | C26: NGƯỜI KIỂM TRA/ DEPARTMENT HEAD CHECK BY: | G26: APPROVED BY: PHÊ DUYỆT
G27: Nguyễn Quang Vinh | I27: Hoàng Ngọc Bằng | K27: Đoàn Văn Toàn
H30: Nguyễn Quang Vinh | J30: Hoàng Ngọc Bằng | M30: Đoàn Văn Toàn

Sheet Sàn nhựa Đại Việt
A1: BID ANALYSIS - GIẢI TRÌNH MUA SẮM/ĐẤU THẦU
A3: Project | B3: PROJECT No/ Dự án: 25-BRA-I-090
A4: Dự án
A5: Subject | B5: Cung cấp vật tư GRATING dự án 090
A6: Chủ đề
A8: No. | B8: CONTENT | G8: Dự toán | J8: Đã mua/Đã đặt | K8: Đơn vị cung cấp chào giá (vnđ) | N8: Lựa chọn | O8: Ghi chú
A9: Chủng loại | B9: Bản vẽ | C9: Length | D9: Width | E9: Thickness | F9: ĐVT | G9: Số lượng | H9: Đơn giá (vnd) | I9: Thành tiền (vnd) | J9: Thành tiền (vnd) | K9: CÔNG TY CỔ PHẦN ĐẠI PHÁT COMPOSITE
E10: Số lượng (cây) | F10: Trọng lượng | K10: Phạm vi | L10: Đơn giá (VND) | M10: Thành Tiền (Không có VAT)
M11: =SUM(M12:M89) -> 255444000 | O11: =I11-J11-M11 -> -255444000
A12: Tấm sàn grating ô 38*38*30mm | B12: 13105R-R001-Z301-000 | C12: 790 | D12: 600 | E12: 30 | F12: Tấm | G12: 10 | H12: N/A | I12: N/A | J12: N/A | K12: V | L12: 690000 | M12: 6900000 | N12: Đại Phát | O12: 13105R-R001-Z302-000 Đã giao
A13: Tấm sàn grating ô 38*38*30mm | B13: 13105R-R001-Z302-000 | C13: 790 | D13: 425 | E13: 30 | F13: Tấm | G13: 4 | H13: N/A | I13: N/A | J13: N/A | K13: V | L13: 590000 | M13: 2360000 | N13: Đại Phát
A14: Tấm sàn grating ô 38*38*30mm | B14: 13105R-R001-Z305-000 | C14: 790 | D14: 600 | E14: 30 | F14: Tấm | G14: 2 | H14: N/A | I14: N/A | J14: N/A | K14: V | L14: 690000 | M14: 1380000 | N14: Đại Phát
A15: Tấm sàn grating ô 38*38*30mm | B15: 13105R-R001-Z306-000 | C15: 679 | D15: 425 | E15: 30 | F15: Tấm | G15: 4 | H15: N/A | I15: N/A | J15: N/A | K15: V | L15: 510000 | M15: 2040000 | N15: Đại Phát
A16: Tấm sàn grating ô 38*38*30mm | B16: 13105R-R001-Z307-000 | C16: 679 | D16: 425 | E16: 30 | F16: Tấm | G16: 4 | H16: N/A | I16: N/A | J16: N/A | K16: V | L16: 510000 | M16: 2040000 | N16: Đại Phát
A17: GRP-Grating-thk 30mm | B17: 13164R-R001-Z301-000 | C17: 790 | D17: 600 | E17: 30 | F17: Tấm | G17: 15 | H17: N/A | I17: N/A | J17: N/A | K17: V | L17: 690000 | M17: 10350000 | N17: Đại Phát | O17: I90-Grating-Type H30mm-13164 (3units)-Rev00
A18: GRP-Grating-thk 30mm | B18: 13164R-R001-Z302-000 | C18: 790 | D18: 425 | E18: 30 | F18: Tấm | G18: 6 | H18: N/A | I18: N/A | J18: N/A | K18: V | L18: 590000 | M18: 3540000 | N18: Đại Phát
A19: GRP-Grating-thk 30mm | B19: 13164R-R001-Z303-000 | C19: 830 | D19: 425 | E19: 30 | F19: Tấm | G19: 6 | H19: N/A | I19: N/A | J19: N/A | K19: V | L19: 670000 | M19: 4020000 | N19: Đại Phát
A20: GRP-Grating-thk 30mm | B20: 13164R-R001-Z304-000 | C20: 860 | D20: 425 | E20: 30 | F20: Tấm | G20: 6 | H20: N/A | I20: N/A | J20: N/A | K20: V | L20: 670000 | M20: 4020000 | N20: Đại Phát
A21: GRP-Grating-thk 30mm | B21: 13164R-R001-Z305-000 | C21: 790 | D21: 600 | E21: 30 | F21: Tấm | G21: 3 | H21: N/A | I21: N/A | J21: N/A | K21: V | L21: 690000 | M21: 2070000 | N21: Đại Phát
A22: GRP-Grating-thk 50mm | B22: 13105R-R001-S116-005A | C22: 1172 | D22: 610 | E22: 50 | F22: Tấm | G22: 8 | H22: N/A | I22: N/A | J22: N/A | K22: V | L22: 1500000 | M22: 12000000 | N22: Đại Phát | O22: I90-Grating H50mm-BO SUNG (U1+U2)-REV00 Đã giao
A23: GRP-Grating-thk 50mm | B23: 13105R-R001-S117-005A | C23: 568 | D23: 610 | E23: 50 | F23: Tấm | G23: 8 | H23: N/A | I23: N/A | J23: N/A | K23: V | L23: 800000 | M23: 6400000 | N23: Đại Phát
A24: GRP-Grating-thk 50mm | B24: 13164R-R001-S108-000 | C24: 1485 | D24: 490 | E24: 50 | F24: Tấm | G24: 2 | H24: N/A | I24: N/A | J24: N/A | K24: V | L24: 1364000 | M24: 2728000 | N24: Đại Phát | O24: I090-Grating partlist-H50mm-U3
A25: GRP-Grating-thk 50mm | B25: 13164R-R001-S109-000 | C25: 1485 | D25: 299 | E25: 50 | F25: Tấm | G25: 1 | H25: N/A | I25: N/A | J25: N/A | K25: V | L25: 855000 | M25: 855000 | N25: Đại Phát
A26: GRP-Grating-thk 50mm | B26: 13164R-R001-S110-000 | C26: 1485 | D26: 259 | E26: 50 | F26: Tấm | G26: 1 | H26: N/A | I26: N/A | J26: N/A | L26: 770000 | M26: 770000 | N26: Đại Phát
A27: GRP-Grating-thk 50mm | B27: 13164R-R001-S112-000 | C27: 1750 | D27: 428.5 | E27: 50 | F27: Tấm | G27: 1 | H27: N/A | I27: N/A | J27: N/A | L27: 1350000 | M27: 1350000 | N27: Đại Phát
A28: GRP-Grating-thk 50mm | B28: 13164R-R001-S116-000 | C28: 1290 | D28: 660 | E28: 50 | F28: Tấm | G28: 1 | H28: N/A | I28: N/A | J28: N/A | L28: 1565000 | M28: 1565000 | N28: Đại Phát
A29: GRP-Grating-thk 50mm | B29: 13164R-R001-S118-000 | C29: 1750 | D29: 610 | E29: 50 | F29: Tấm | G29: 15 | H29: N/A | I29: N/A | J29: N/A | L29: 1905000 | M29: 28575000 | N29: Đại Phát
A30: GRP-Grating-thk 50mm | B30: 13164R-R001-S118-001 | C30: 1750 | D30: 396 | E30: 50 | F30: Tấm | G30: 1 | H30: N/A | I30: N/A | J30: N/A | L30: 1305000 | M30: 1305000 | N30: Đại Phát
A31: GRP-Grating-thk 50mm | B31: 13164R-R001-S118-002 | C31: 779 | D31: 642,5 | E31: 50 | F31: Tấm | G31: 1 | H31: N/A | I31: N/A | J31: N/A | L31: 955000 | M31: 955000 | N31: Đại Phát
A32: GRP-Grating-thk 50mm | B32: 13164R-R001-S118-003 | C32: 961 | D32: 643 | E32: 50 | F32: Tấm | G32: 1 | H32: N/A | I32: N/A | J32: N/A | L32: 1250000 | M32: 1250000 | N32: Đại Phát
A33: GRP-Grating-thk 50mm | B33: 13164R-R001-S119-000 | C33: 1243 | D33: 305 | E33: 50 | F33: Tấm | G33: 2 | H33: N/A | I33: N/A | J33: N/A | L33: 755000 | M33: 1510000 | N33: Đại Phát
A34: GRP-Grating-thk 50mm | B34: 13164R-R001-S120-000 | C34: 850 | D34: 738.5 | E34: 50 | F34: Tấm | G34: 1 | H34: N/A | I34: N/A | J34: N/A | L34: 1255000 | M34: 1255000 | N34: Đại Phát
A35: GRP-Grating-thk 50mm | B35: 13164R-R001-S120-005 | C35: 850 | D35: 738.5 | E35: 50 | F35: Tấm | G35: 1 | H35: N/A | I35: N/A | J35: N/A | L35: 1255000 | M35: 1255000 | N35: Đại Phát
A36: GRP-Grating-thk 50mm | B36: 13164R-R001-S127-001 | C36: 1610 | D36: 600 | E36: 50 | F36: Tấm | G36: 3 | H36: N/A | I36: N/A | J36: N/A | L36: 1750000 | M36: 5250000 | N36: Đại Phát
A37: GRP-Grating-thk 50mm | B37: 13164R-R001-S118-004 | C37: 1750 | D37: 565 | E37: 50 | F37: Tấm | G37: 2 | H37: N/A | I37: N/A | J37: N/A | L37: 1750000 | M37: 3500000 | N37: Đại Phát
A38: GRP-Grating-thk 50mm | B38: 13164R-R001-S127-000 | C38: 2695 | D38: 1220 | E38: 50 | F38: Tấm | G38: 1 | H38: N/A | I38: N/A | J38: N/A | L38: 5550000 | M38: 5550000 | N38: Đại Phát
A39: GRP-Grating-thk 50mm | B39: 13164R-R001-S127-002 | C39: 600 | D39: 501 | E39: 50 | F39: Tấm | G39: 1 | H39: N/A | I39: N/A | J39: N/A | L39: 615000 | M39: 615000 | N39: Đại Phát
A40: GRP-Grating-thk 50mm | B40: 13164R-R001-S127-003 | C40: 1109 | D40: 600 | E40: 50 | F40: Tấm | G40: 1 | H40: N/A | I40: N/A | J40: N/A | L40: 1265000 | M40: 1265000 | N40: Đại Phát
A41: GRP-Grating-thk 50mm | B41: 13164R-R001-S128-000 | C41: 1750 | D41: 517 | E41: 50 | F41: Tấm | G41: 1 | H41: N/A | I41: N/A | J41: N/A | L41: 1650000 | M41: 1650000 | N41: Đại Phát
A42: GRP-Grating-thk 50mm | B42: 13164R-R001-S128-002 | C42: 1750 | D42: 653 | E42: 50 | F42: Tấm | G42: 1 | H42: N/A | I42: N/A | J42: N/A | L42: 2250000 | M42: 2250000 | N42: Đại Phát
A43: GRP-Grating-thk 50mm | B43: 13164R-R001-S131-000 | C43: 1290 | D43: 610 | E43: 50 | F43: Tấm | G43: 1 | H43: N/A | I43: N/A | J43: N/A | L43: 1450000 | M43: 1450000 | N43: Đại Phát
... A45: GRP-Grating-thk 50mm | B45: 13164R-R001-S132-000 | C45: 660 | D45: 450 | E45: 50 | F45: Tấm | G45: 1 | H45: N/A | I45: N/A | J45: N/A | L45: 605000 | M45: 605000 | N45: Đại Phát
A46: GRP-Grating-thk 50mm | B46: 13164R-R001-S108-000 | C46: 1485 | D46: 490 | E46: 50 | F46: Tấm | G46: 2 | H46: N/A | I46: N/A | J46: N/A | L46: 1364000 | M46: 2728000 | N46: Đại Phát | O46: I090-Grating partlist-H50mm-U4
A47: GRP-Grating-thk 50mm | B47: 13164R-R001-S109-000 | C47: 1485 | D47: 299 | E47: 50 | F47: Tấm | G47: 1 | H47: N/A | I47: N/A | J47: N/A | L47: 855000 | M47: 855000 | N47: Đại Phát
A48: GRP-Grating-thk 50mm | B48: 13164R-R001-S110-000 | C48: 1485 | D48: 259 | E48: 50 | F48: Tấm | G48: 1 | H48: N/A | I48: N/A | J48: N/A | L48: 770000 | M48: 770000 | N48: Đại Phát
A49: GRP-Grating-thk 50mm | B49: 13164R-R001-S112-000 | C49: 1750 | D49: 428.5 | E49: 50 | F49: Tấm | G49: 1 | H49: N/A | I49: N/A | J49: N/A | L49: 1350000 | M49: 1350000 | N49: Đại Phát
A50: GRP-Grating-thk 50mm | B50: 13164R-R001-S116-000 | C50: 1290 | D50: 660 | E50: 50 | F50: Tấm | G50: 1 | H50: N/A | I50: N/A | J50: N/A | L50: 1565000 | M50: 1565000 | N50: Đại Phát
A51: GRP-Grating-thk 50mm | B51: 13164R-R001-S118-000 | C51: 1750 | D51: 610 | E51: 50 | F51: Tấm | G51: 15 | H51: N/A | I51: N/A | J51: N/A | L51: 1905000 | M51: 28575000 | N51: Đại Phát
A52: GRP-Grating-thk 50mm | B52: 13164R-R001-S118-001 | C52: 1750 | D52: 396 | E52: 50 | F52: Tấm | G52: 1 | H52: N/A | I52: N/A | J52: N/A | L52: 1305000 | M52: 1305000 | N52: Đại Phát
A53: GRP-Grating-thk 50mm | B53: 13164R-R001-S118-002 | C53: 779 | D53: 642,5 | E53: 50 | F53: Tấm | G53: 1 | H53: N/A | I53: N/A | J53: N/A | L53: 955000 | M53: 955000 | N53: Đại Phát
A54: GRP-Grating-thk 50mm | B54: 13164R-R001-S118-003 | C54: 961 | D54: 643 | E54: 50 | F54: Tấm | G54: 1 | H54: N/A | I54: N/A | J54: N/A | L54: 1250000 | M54: 1250000 | N54: Đại Phát
A55: GRP-Grating-thk 50mm | B55: 13164R-R001-S119-000 | C55: 1243 | D55: 305 | E55: 50 | F55: Tấm | G55: 2 | H55: N/A | I55: N/A | J55: N/A | L55: 755000 | M55: 1510000 | N55: Đại Phát
A56: GRP-Grating-thk 50mm | B56: 13164R-R001-S120-000 | C56: 850 | D56: 738.5 | E56: 50 | F56: Tấm | G56: 1 | H56: N/A | I56: N/A | J56: N/A | L56: 1255000 | M56: 1255000 | N56: Đại Phát
A57: GRP-Grating-thk 50mm | B57: 13164R-R001-S120-005 | C57: 850 | D57: 738.5 | E57: 50 | F57: Tấm | G57: 1 | H57: N/A | I57: N/A | J57: N/A | L57: 1255000 | M57: 1255000 | N57: Đại Phát
A58: GRP-Grating-thk 50mm | B58: 13164R-R001-S127-001 | C58: 1610 | D58: 600 | E58: 50 | F58: Tấm | G58: 3 | H58: N/A | I58: N/A | J58: N/A | L58: 1750000 | M58: 5250000 | N58: Đại Phát
A59: GRP-Grating-thk 50mm | B59: 13164R-R001-S118-004 | C59: 1750 | D59: 565 | E59: 50 | F59: Tấm | G59: 2 | H59: N/A | I59: N/A | J59: N/A | L59: 1750000 | M59: 3500000 | N59: Đại Phát
A60: GRP-Grating-thk 50mm | B60: 13164R-R001-S127-000 | C60: 2695 | D60: 1220 | E60: 50 | F60: Tấm | G60: 1 | H60: N/A | I60: N/A | J60: N/A | L60: 5550000 | M60: 5550000 | N60: Đại Phát
A61: GRP-Grating-thk 50mm | B61: 13164R-R001-S127-002 | C61: 600 | D61: 501 | E61: 50 | F61: Tấm | G61: 1 | H61: N/A | I61: N/A | J61: N/A | L61: 615000 | M61: 615000 | N61: Đại Phát
A62: GRP-Grating-thk 50mm | B62: 13164R-R001-S127-003 | C62: 1109 | D62: 600 | E62: 50 | F62: Tấm | G62: 1 | H62: N/A | I62: N/A | J62: N/A | L62: 1265000 | M62: 1265000 | N62: Đại Phát
A63: GRP-Grating-thk 50mm | B63: 13164R-R001-S128-000 | C63: 1750 | D63: 517 | E63: 50 | F63: Tấm | G63: 1 | H63: N/A | I63: N/A | J63: N/A | L63: 1650000 | M63: 1650000 | N63: Đại Phát
A64: GRP-Grating-thk 50mm | B64: 13164R-R001-S128-002 | C64: 1750 | D64: 653 | E64: 50 | F64: Tấm | G64: 1 | H64: N/A | I64: N/A | J64: N/A | L64: 2250000 | M64: 2250000 | N64: Đại Phát
A65: GRP-Grating-thk 50mm | B65: 13164R-R001-S131-000 | C65: 1290 | D65: 610 | E65: 50 | F65: Tấm | G65: 1 | H65: N/A | I65: N/A | J65: N/A | L65: 1450000 | M65: 1450000 | N65: Đại Phát
... A67: GRP-Grating-thk 50mm | B67: 13164R-R001-S132-000 | C67: 660 | D67: 450 | E67: 50 | F67: Tấm | G67: 1 | H67: N/A | I67: N/A | J67: N/A | L67: 605000 | M67: 605000 | N67: Đại Phát
A68: GRP-Grating-thk 50mm | B68: 13164R-R001-S108-000 | C68: 1485 | D68: 490 | E68: 50 | F68: Tấm | G68: 2 | H68: N/A | I68: N/A | J68: N/A | L68: 1364000 | M68: 2728000 | N68: Đại Phát | O68: I090-Grating partlist-H50mm-U5
A69: GRP-Grating-thk 50mm | B69: 13164R-R001-S109-000 | C69: 1485 | D69: 299 | E69: 50 | F69: Tấm | G69: 1 | H69: N/A | I69: N/A | J69: N/A | L69: 855000 | M69: 855000 | N69: Đại Phát
A70: GRP-Grating-thk 50mm | B70: 13164R-R001-S110-000 | C70: 1485 | D70: 259 | E70: 50 | F70: Tấm | G70: 1 | H70: N/A | I70: N/A | J70: N/A | L70: 770000 | M70: 770000 | N70: Đại Phát
A71: GRP-Grating-thk 50mm | B71: 13164R-R001-S112-000 | C71: 1750 | D71: 428.5 | E71: 50 | F71: Tấm | G71: 1 | H71: N/A | I71: N/A | J71: N/A | L71: 1350000 | M71: 1350000 | N71: Đại Phát
A72: GRP-Grating-thk 50mm | B72: 13164R-R001-S116-000 | C72: 1290 | D72: 660 | E72: 50 | F72: Tấm | G72: 1 | H72: N/A | I72: N/A | J72: N/A | L72: 1565000 | M72: 1565000 | N72: Đại Phát
A73: GRP-Grating-thk 50mm | B73: 13164R-R001-S118-000 | C73: 1750 | D73: 610 | E73: 50 | F73: Tấm | G73: 15 | H73: N/A | I73: N/A | J73: N/A | L73: 1905000 | M73: 28575000 | N73: Đại Phát
A74: GRP-Grating-thk 50mm | B74: 13164R-R001-S118-001 | C74: 1750 | D74: 396 | E74: 50 | F74: Tấm | G74: 1 | H74: N/A | I74: N/A | J74: N/A | L74: 1305000 | M74: 1305000 | N74: Đại Phát
A75: GRP-Grating-thk 50mm | B75: 13164R-R001-S118-002 | C75: 779 | D75: 642,5 | E75: 50 | F75: Tấm | G75: 1 | H75: N/A | I75: N/A | J75: N/A | L75: 955000 | M75: 955000 | N75: Đại Phát
A76: GRP-Grating-thk 50mm | B76: 13164R-R001-S118-003 | C76: 961 | D76: 643 | E76: 50 | F76: Tấm | G76: 1 | H76: N/A | I76: N/A | J76: N/A | L76: 1250000 | M76: 1250000 | N76: Đại Phát
A77: GRP-Grating-thk 50mm | B77: 13164R-R001-S119-000 | C77: 1243 | D77: 305 | E77: 50 | F77: Tấm | G77: 2 | H77: N/A | I77: N/A | J77: N/A | L77: 755000 | M77: 1510000 | N77: Đại Phát
A78: GRP-Grating-thk 50mm | B78: 13164R-R001-S120-000 | C78: 850 | D78: 738.5 | E78: 50 | F78: Tấm | G78: 1 | H78: N/A | I78: N/A | J78: N/A | L78: 1255000 | M78: 1255000 | N78: Đại Phát
A79: GRP-Grating-thk 50mm | B79: 13164R-R001-S120-005 | C79: 850 | D79: 738.5 | E79: 50 | F79: Tấm | G79: 1 | H79: N/A | I79: N/A | J79: N/A | L79: 1255000 | M79: 1255000 | N79: Đại Phát
A80: GRP-Grating-thk 50mm | B80: 13164R-R001-S127-001 | C80: 1610 | D80: 600 | E80: 50 | F80: Tấm | G80: 3 | H80: N/A | I80: N/A | J80: N/A | L80: 1750000 | M80: 5250000 | N80: Đại Phát
A81: GRP-Grating-thk 50mm | B81: 13164R-R001-S118-004 | C81: 1750 | D81: 565 | E81: 50 | F81: Tấm | G81: 2 | H81: N/A | I81: N/A | J81: N/A | L81: 1750000 | M81: 3500000 | N81: Đại Phát
A82: GRP-Grating-thk 50mm | B82: 13164R-R001-S127-000 | C82: 2695 | D82: 1220 | E82: 50 | F82: Tấm | G82: 1 | H82: N/A | I82: N/A | J82: N/A | L82: 5550000 | M82: 5550000 | N82: Đại Phát
A83: GRP-Grating-thk 50mm | B83: 13164R-R001-S127-002 | C83: 600 | D83: 501 | E83: 50 | F83: Tấm | G83: 1 | H83: N/A | I83: N/A | J83: N/A | L83: 615000 | M83: 615000 | N83: Đại Phát
A84: GRP-Grating-thk 50mm | B84: 13164R-R001-S127-003 | C84: 1109 | D84: 600 | E84: 50 | F84: Tấm | G84: 1 | H84: N/A | I84: N/A | J84: N/A | L84: 1265000 | M84: 1265000 | N84: Đại Phát
A85: GRP-Grating-thk 50mm | B85: 13164R-R001-S128-000 | C85: 1750 | D85: 517 | E85: 50 | F85: Tấm | G85: 1 | H85: N/A | I85: N/A | J85: N/A | L85: 1650000 | M85: 1650000 | N85: Đại Phát
A86: GRP-Grating-thk 50mm | B86: 13164R-R001-S128-002 | C86: 1750 | D86: 653 | E86: 50 | F86: Tấm | G86: 1 | H86: N/A | I86: N/A | J86: N/A | L86: 2250000 | M86: 2250000 | N86: Đại Phát
A87: GRP-Grating-thk 50mm | B87: 13164R-R001-S131-000 | C87: 1290 | D87: 610 | E87: 50 | F87: Tấm | G87: 1 | H87: N/A | I87: N/A | J87: N/A | L87: 1450000 | M87: 1450000 | N87: Đại Phát
... A89: GRP-Grating-thk 50mm | B89: 13164R-R001-S132-000 | C89: 660 | D89: 450 | E89: 50 | F89: Tấm | G89: 1 | H89: N/A | I89: N/A | J89: N/A | L89: 605000 | M89: 605000 | N89: Đại Phát
B90: Đơn giá tổng hợp
A91: II | B91: Khối lượng dự kiến giao (Kg )/ Estimated weight (Kg):
A92: 1 | B92: … | C92: kg
A93: 2 | B93: …
A94: III | B94: Tiến độ/ Schedule | C94: Bắt đầu/ Start | D94: Kết thúc/ Finish
A95: 1 | B95: ….
A97: IV | B97: Nhân lực/ ManPower
A98: 1 | B98: Thợ Pha cắt / Thợ sắt / Thợ hàn / …
B99: ….
A100: V | B100: Yêu cầu kỹ thuật: Tham chiếu các tài liệu đính kèm/ Technical requirement – refer to document attached
B101: Xếp hạng | L101: 1
A102: Ghi Chú: PTM tiến hành mua hàng để đảm bảo tiến độ
A103: NGƯỜI ĐỀ NGHỊ/ RECOMMENDATION BY: | C103: NGƯỜI KIỂM TRA/ DEPARTMENT HEAD CHECK BY: | F103: APPROVED BY: PHÊ DUYỆT
F104: Nguyễn Quang Vinh | J104: Hoàng Ngọc Bằng | M104: Đoàn Văn Toàn

Sheet Vật tư đóng kiện Trân toàn
A1: BID ANALYSIS - GIẢI TRÌNH MUA SẮM/ĐẤU THẦU
A3: Project | B3: PROJECT No/ Dự án: 25-BRA-I-090
A4: Dự án
A5: Subject | B5: Cung cấp vật tư đóng kiện dự án 090
A6: Chủ đề
A8: No. | B8: CONTENT | C8: Phạm vi công việc | G8: Dự toán | J8: Đã mua/Đã đặt | K8: Đơn vị cung cấp chào giá (vnđ) | N8: Lựa chọn | O8: Ghi chú
A9: Item | B9: Description/ Chi tiết | C9: Profile/ Vật tư | D9: Grade/ Mác vật liệu | E9: Số lượng (M2) | F9: Trọng lượng (KG) | G9: Khối lượng/ Số lượng | H9: Đơn giá (vnd) | I9: Thành tiền (vnd) | J9: Thành tiền (vnd) | K9: Trần Toàn
E10: Số lượng (cây) | F10: Trọng lượng | K10: Phạm vi | L10: Đơn giá (VND) | M10: Thành Tiền (Không có VAT)
A11: Tổng | G11: N/A | H11: N/A | I11: ='DT04 (TM) 1 '!L17 -> 2538751590 | J11: ='Vật tư đóng kiện Ngọc hiếu 090'!K11+'Vật tư đóng kiện Ngọc hiếu 090'!N11 -> 4.994165e+09 | M11: =SUM(M12:M25) -> 262257375 | O11: =I11-J11-M11 -> -2.7176708e+09
A12: I90-C140 | B12: I90-C140 (10500 x 6500) x 3 tấm | D12: Bạt da | E12: 204.75 | F12: N/A | G12: N/A | H12: N/A | I12: N/A | J12: N/A | K12: V | L12: 50500 | M12: =L12*E12 -> 10339875 | N12: Trần Toàn | O12: -Giá trí mua đang vượt dự toán - PTM không nắm được vật tư phụ kiện còn phát sinh hàng không - Thông báo tới SALE để khách hàng hỗ trợ thêm chi phí
A13: I90-C141 | B13: I90-C141 (12000 x 8000) x 3 tấm | D13: Bạt da | E13: 288 | F13: N/A | G13: N/A | H13: N/A | I13: N/A | J13: N/A | K13: V | L13: 50500 | M13: =L13*E13 -> 14544000 | N13: Trần Toàn
A14: I90-C142 | B14: I90-C142 (1200 x 9500) x 1 tấm | D14: Bạt da | E14: 114 | F14: N/A | G14: N/A | H14: N/A | I14: N/A | J14: N/A | K14: V | L14: 50500 | M14: =L14*E14 -> 5757000 | N14: Trần Toàn
A15: I90-C143 | B15: I90-C143 (14000 x 7000) x 4 tấm | D15: Bạt da | E15: =392+196 -> 588 | F15: N/A | G15: N/A | H15: N/A | I15: N/A | J15: N/A | K15: V | L15: 50500 | M15: =L15*E15 -> 29694000 | N15: Trần Toàn
A16: I90-C144 | B16: I90-C144 (15000 x 11000) x 1 tấm | D16: Bạt da | E16: 165 | F16: N/A | G16: N/A | H16: N/A | I16: N/A | J16: N/A | K16: V | L16: 50500 | M16: =L16*E16 -> 8332500 | N16: Trần Toàn
A17: I90-C145 | B17: I90-C145 (15000 x 7000) x 3 tấm | D17: Bạt da | E17: 315 | F17: N/A | G17: N/A | H17: N/A | I17: N/A | J17: N/A | K17: V | L17: 50500 | M17: =L17*E17 -> 15907500 | N17: Trần Toàn
A18: I90-C146 | B18: I90-C146 (15500 x 9500) x 1 tấm | D18: Bạt da | E18: 147.25 | F18: N/A | G18: N/A | H18: N/A | I18: N/A | J18: N/A | K18: V | L18: 50500 | M18: =L18*E18 -> 7436125 | N18: Trần Toàn
A19: I90-C147 | B19: I90-C147 (15500 x 10000) x 1 tấm | D19: Bạt da | E19: 155 | F19: N/A | G19: N/A | H19: N/A | I19: N/A | J19: N/A | K19: V | L19: 50500 | M19: =L19*E19 -> 7827500 | N19: Trần Toàn
A20: I90-C148 | B20: I90-C148 (17000 x 12000) x 4 tấm | D20: Bạt da | E20: 816 | F20: N/A | G20: N/A | H20: N/A | I20: N/A | J20: N/A | K20: V | L20: 50500 | M20: =L20*E20 -> 41208000 | N20: Trần Toàn
A21: I90-C149 | B21: I90-C149 (16500 x 9000) x 3 tấm | D21: Bạt da | E21: 445.5 | F21: N/A | G21: N/A | H21: N/A | I21: N/A | J21: N/A | K21: V | L21: 50500 | M21: =L21*E21 -> 22497750 | N21: Trần Toàn
A22: I90-C150 | B22: I90-C150 (16500 x 10000) x 3 tấm | D22: Bạt da | E22: 495 | F22: N/A | G22: N/A | H22: N/A | I22: N/A | J22: N/A | K22: V | L22: 50500 | M22: =L22*E22 -> 24997500 | N22: Trần Toàn
A23: I90-C151 | B23: I90-C151 (17500 x 11500) x 3 tấm | D23: Bạt da | E23: 603.75 | F23: N/A | G23: N/A | H23: N/A | I23: N/A | J23: N/A | K23: V | L23: 50500 | M23: =L23*E23 -> 30489375 | N23: Trần Toàn
A24: I90-C152 | B24: I90-C152 (9000 x 7500) x 3 tấm | D24: Bạt da | E24: 202.5 | F24: N/A | G24: N/A | H24: N/A | I24: N/A | J24: N/A | K24: V | L24: 50500 | M24: =L24*E24 -> 10226250 | N24: Trần Toàn
A25: I90-C154 | B25: Bạt dứa I90 - C 154 ( 15000 x 20000 ) x 10 tấm | D25: Bạt dứa | E25: 3000 | F25: N/A | G25: N/A | H25: N/A | I25: N/A | J25: N/A | K25: V | L25: 11000 | M25: =L25*E25 -> 33000000 | N25: Trần Toàn
B26: Đơn giá tổng hợp
A27: II | B27: Khối lượng dự kiến giao (Kg )/ Estimated weight (Kg):
A28: 1 | B28: … | C28: kg
A29: 2 | B29: …
A30: III | B30: Tiến độ/ Schedule | C30: Bắt đầu/ Start | D30: Kết thúc/ Finish
A31: 1 | B31: ….
A33: IV | B33: Nhân lực/ ManPower
A34: 1 | B34: Thợ Pha cắt / Thợ sắt / Thợ hàn / …
B35: ….
A36: V | B36: Yêu cầu kỹ thuật: Tham chiếu các tài liệu đính kèm/ Technical requirement – refer to document attached
B37: Xếp hạng | L37: 1
A38: Ghi Chú: Vật tư đóng kiện dự án 090 tính tiền theo khối lượng thực tế, PTM tiến hành mua hàng
A39: NGƯỜI ĐỀ NGHỊ/ RECOMMENDATION BY: | C39: NGƯỜI KIỂM TRA/ DEPARTMENT HEAD CHECK BY: | F39: APPROVED BY: PHÊ DUYỆT
F40: Nguyễn Quang Vinh | H40: Hoàng Ngọc Bằng | K40: Đoàn Văn Toàn

Sheet Vật tư 
A1: BID ANALYSIS - GIẢI TRÌNH MUA SẮM/ĐẤU THẦU
A3: Project | B3: PROJECT No/ Dự án: 25-BRA-I-090
A4: Dự án
A5: Subject | B5: Cung cấp vật tư phục vụ dự án 090
A6: Chủ đề
A8: No. | B8: CONTENT | C8: Phạm vi công việc | F8: Dự toán | I8: Đã mua/Đã đặt | J8: Đơn vị cung cấp chào giá (vnđ) | M8: Lựa chọn | N8: Ghi chú
A9: Item | B9: Description/ Chi tiết | C9: Số thùng | D9: Đóng gói | E9: Trọng lượng (Lít) | F9: Khối lượng/ Số lượng | G9: Đơn giá (vnd) | H9: Thành tiền (vnd) | I9: Thành tiền (vnd) | J9: Phúc Châu
E10: Trọng lượng | J10: Phạm vi | K10: Đơn giá (VND) | L10: Thành Tiền (Không có VAT)
A11: Tổng | B11: Vật tư phục vụ sản xuất 090 | F11: N/A | G11: N/A | L11: =SUM(L12:L12) -> 79800000 | N11: =H11-I11-L11 -> -79800000
A12: 1 | B12: VPCI-386 (19L/Thùng) | C12: 7 | D12: 19L/Thùng | E12: 133 | F12: N/A | G12: N/A | H12: N/A | I12: N/A | J12: V | K12: 600000 | L12: =E12*K12 -> 79800000 | M12: Phúc Châu
A13: II | B13: Khối lượng dự kiến giao (Kg )/ Estimated weight (Kg):
A14: 1 | B14: … | C14: kg
A15: 2 | B15: …
A16: III | B16: Tiến độ/ Schedule | C16: Bắt đầu/ Start | D16: Kết thúc/ Finish
A17: 1 | B17: ….
A19: IV | B19: Nhân lực/ ManPower
A20: 1 | B20: Thợ Pha cắt / Thợ sắt / Thợ hàn / …
B21: ….
A22: V | B22: Yêu cầu kỹ thuật: Tham chiếu các tài liệu đính kèm/ Technical requirement – refer to document attached
B23: Xếp hạng | K23: 1
A24: Ghi Chú: Vật tư phục vụ sản xuất, PTM tiến hành mua hàng ngay để đảm bảo tiến độ
A25: NGƯỜI ĐỀ NGHỊ/ RECOMMENDATION BY: | C25: NGƯỜI KIỂM TRA/ DEPARTMENT HEAD CHECK BY: | E25: APPROVED BY: PHÊ DUYỆT
E26: Nguyễn Quang Vinh | G26: Hoàng Ngọc Bằng | J26: Đoàn Văn Toàn

Sheet Vật tư sơn 090
A1: BID ANALYSIS - GIẢI TRÌNH MUA SẮM/ĐẤU THẦU
A3: Project | B3: PROJECT No/ Dự án: 25-BRA-I-090
A4: Dự án
A5: Subject | B5: Cung cấp vật tư phục vụ dự án 090
A6: Chủ đề
A8: No. | B8: CONTENT | C8: Phạm vi công việc | F8: Dự toán | I8: Đã mua/Đã đặt | J8: Đơn vị cung cấp chào giá (vnđ) | M8: Lựa chọn | N8: Ghi chú
A9: Item | B9: Description/ Chi tiết | C9: Profile/ Vật tư | D9: Grade/ Mác vật liệu | E9: Trọng lượng (KG) | F9: Khối lượng/ Số lượng | G9: Đơn giá (vnd) | H9: Thành tiền (vnd) | I9: Thành tiền (vnd) | J9: Nguyên Hanh
E10: Trọng lượng | J10: Phạm vi | K10: Đơn giá (VND) | L10: Thành Tiền (Không có VAT)
A11: Tổng | B11: Vật tư phục vụ sản xuất 090 | F11: N/A | G11: N/A | L11: =SUM(L12:L12) -> 17400000 | N11: =H11-I11-L11 -> -17400000
A12: 1 | B12: Hạt Garmet 30/60 | C12: Hạt Garmet 30/60 | D12: N/A | E12: 2000 | F12: N/A | G12: N/A | H12: N/A | I12: N/A | J12: V | K12: 8700000 | L12: =K12*2 -> 17400000 | M12: Nguyên hanh
A13: II | B13: Khối lượng dự kiến giao (Kg )/ Estimated weight (Kg):
A14: 1 | B14: … | C14: kg
A15: 2 | B15: …
A16: III | B16: Tiến độ/ Schedule | C16: Bắt đầu/ Start | D16: Kết thúc/ Finish
A17: 1 | B17: ….
A19: IV | B19: Nhân lực/ ManPower
A20: 1 | B20: Thợ Pha cắt / Thợ sắt / Thợ hàn / …
B21: ….
A22: V | B22: Yêu cầu kỹ thuật: Tham chiếu các tài liệu đính kèm/ Technical requirement – refer to document attached
B23: Xếp hạng | K23: 1
A24: Ghi Chú: Vật tư phục vụ sản xuất, PTM tiến hành mua hàng ngay để đảm bảo tiến độ
A25: NGƯỜI ĐỀ NGHỊ/ RECOMMENDATION BY: | C25: NGƯỜI KIỂM TRA/ DEPARTMENT HEAD CHECK BY: | E25: APPROVED BY: PHÊ DUYỆT
E26: Nguyễn Quang Vinh | G26: Hoàng Ngọc Bằng | J26: Đoàn Văn Toàn

Sheet Vật tư Hùng Nguyên
A1: BID ANALYSIS - GIẢI TRÌNH MUA SẮM/ĐẤU THẦU
A3: Project | B3: PROJECT No/ Dự án: 25-BRA-I-090
A4: Dự án
A5: Subject | B5: Cung cấp vật tư chính và vật tư đóng kiện dự án 090
A6: Chủ đề
A8: No. | B8: CONTENT | C8: Phạm vi công việc | G8: Dự toán | J8: Đã mua/Đã đặt | K8: Đơn vị cung cấp chào giá (vnđ) | N8: Đơn vị cung cấp chào giá (vnđ) | Q8: Lựa chọn | R8: Ghi chú
A9: Item | B9: Description/ Chi tiết | C9: Profile/ Vật tư | D9: Grade/ Mác vật liệu | E9: Số lượng (mua) (M) | F9: Số lượng (PR) (M) | G9: Khối lượng/ Số lượng | H9: Đơn giá (vnd) | I9: Thành tiền (vnd) | J9: Thành tiền (vnd) | K9: Ngọc Hiếu | N9: Hùng Nguyên
E10: Số lượng (cây) | F10: Số lượng (cây) | K10: Phạm vi | L10: Đơn giá (VND) | M10: Thành Tiền (Không có VAT) | N10: Phạm vi | O10: Đơn giá (VND) | P10: Thành Tiền (Không có VAT)
A11: Tổng | G11: N/A | H11: N/A | I11: ='DT04 (TM) 1 '!L8 -> 2.6838359e+10 | J11: ='DT04 (TM) 1 '!Q8 -> 2.8199693e+10 | P11: =SUM(P12:P12) -> 6401319 | R11: =I11-J11-M11-P11 -> -1.3677356e+09
A12: I90-A5 | B12: PL5x1500x6000 | C12: PL5x200x6000 | D12: SS400 | E12: 12 | F12: 9 | G12: N/A | H12: N/A | I12: N/A | J12: N/A | K12: V | L12: 13636.36 | M12: N/A | N12: V | O12: 13727.27 | P12: 6401319 | Q12: Hùng Nguyên | R12: -Giá trí mua đang vượt dự toán
A13: Tổng | G13: N/A | H13: N/A | I13: ='DT04 (TM) 1 '!L17 -> 2538751590 | J13: ='Tổng hợp'!J16 -> 4.2279793e+09 | M13: =SUM(M14:M14) -> 0 | P13: =SUM(P14:P14) -> 156776769 | R13: =I13-J13-M13-P13 -> -1.8460045e+09
A14: I90-C100 | B14: HEA200(H190x200x6.5x10)-L12000 | C14: Thép hình H200x200x6x8x12000 | D14: SS400 | E14: 170 | F14: 170 | G14: N/A | H14: N/A | I14: N/A | J14: N/A | K14: V | L14: =19300/1.1 -> 17545.455 | M14: N/A | N14: V | O14: =19200/1.1 -> 17454.545 | P14: =3*52258923 -> 156776769 | Q14: Hùng Nguyên | R14: -Giá trí mua đang vượt dự toán
B15: Đơn giá tổng hợp
A16: II | B16: Khối lượng dự kiến giao (Kg )/ Estimated weight (Kg):
A17: 1 | B17: … | C17: kg
A18: 2 | B18: …
A19: III | B19: Tiến độ/ Schedule | C19: Bắt đầu/ Start | D19: Kết thúc/ Finish
A20: 1 | B20: ….
A22: IV | B22: Nhân lực/ ManPower
A23: 1 | B23: Thợ Pha cắt / Thợ sắt / Thợ hàn / …
B24: ….
A25: V | B25: Yêu cầu kỹ thuật: Tham chiếu các tài liệu đính kèm/ Technical requirement – refer to document attached
B26: Xếp hạng | L26: 2 | O26: 1
A27: Ghi Chú: PTM tiến hành mua hàng để đảm bảo tiến độ
A28: NGƯỜI ĐỀ NGHỊ/ RECOMMENDATION BY: | C28: NGƯỜI KIỂM TRA/ DEPARTMENT HEAD CHECK BY: | K28: APPROVED BY: PHÊ DUYỆT
J29: Nguyễn Quang Vinh | M29: Hoàng Ngọc Bằng | P29: Đoàn Văn Toàn

Sheet Vật tư Quang Thịnh Phát
A1: BID ANALYSIS - GIẢI TRÌNH MUA SẮM/ĐẤU THẦU
A3: Project | B3: PROJECT No/ Dự án: 25-BRA-I-090
A4: Dự án
A5: Subject | B5: Cung cấp vật tư hộp A36/SS400
A6: Chủ đề
A8: No. | B8: CONTENT | C8: Phạm vi công việc | H8: Dự toán | K8: Đã mua/Đã đặt | L8: Đơn vị cung cấp chào giá (vnđ) | O8: Đơn vị cung cấp chào giá (vnđ) | R8: Lựa chọn | S8: Ghi chú
A9: Item | B9: Description/ Chi tiết | C9: Profile/ Vật tư | D9: Grade/ Mác vật liệu | E9: Số lượng mua (M) | F9: Số lượng PR (M) | G9: Trọng lượng (KG) | H9: Khối lượng/ Số lượng | I9: Đơn giá (vnd) | J9: Thành tiền (vnd) | K9: Thành tiền (vnd) | L9: QUANG THỊNH PHÁT | O9: Hùng Nguyên
E10: Số lượng (cây) | F10: Số lượng (cây) | G10: Trọng lượng | L10: Phạm vi | M10: Đơn giá (VND) | N10: Thành Tiền (Không có VAT) | O10: Phạm vi | P10: Đơn giá (VND) | Q10: Thành Tiền (Không có VAT)
A11: Tổng | H11: N/A | I11: N/A | J11: ='Tổng hợp'!K14 -> 2.7375767e+10 | K11: ='Tổng hợp'!J14 -> 2.8199693e+10 | N11: =SUM(N12:N12) -> 31690449 | Q11: =SUM(Q12:Q12) -> 0 | S11: =J11-K11-N11 -> -8.5561675e+08
A12: I90-A127 | B12: SHS 40x40x3-L6000 | C12: Thép hộp đen 40 x 40 x 3,0 x 6.000 mm | D12: A36/SS400 | E12: =6*98 -> 588 | F12: 582 | G12: 2015 | H12: N/A | I12: N/A | J12: N/A | K12: N/A | L12: V | M12: 15727.27 | N12: 31690449 | O12: V | P12: =18000/1.1 -> 16363.636 | Q12: N/A | R12: Quang Thịnh Phát | S12: -Giá trí mua đang vượt dự toán - PTM không nắm được vật tư phụ kiện còn phát sinh hàng không - Thông báo tới SALE để khách hàng hỗ trợ thêm chi phí
B13: Đơn giá tổng hợp
A14: II | B14: Khối lượng dự kiến giao (Kg )/ Estimated weight (Kg):
A15: 1 | B15: … | C15: kg
A16: 2 | B16: …
A17: III | B17: Tiến độ/ Schedule | C17: Bắt đầu/ Start | D17: Kết thúc/ Finish
A18: 1 | B18: ….
A20: IV | B20: Nhân lực/ ManPower
A21: 1 | B21: Thợ Pha cắt / Thợ sắt / Thợ hàn / …
B22: ….
A23: V | B23: Yêu cầu kỹ thuật: Tham chiếu các tài liệu đính kèm/ Technical requirement – refer to document attached
B24: Xếp hạng | M24: 1 | P24: 2
A25: Ghi Chú: PTM tiến hành mua hàng để đảm bảo tiến độ
A26: NGƯỜI ĐỀ NGHỊ/ RECOMMENDATION BY: | C26: NGƯỜI KIỂM TRA/ DEPARTMENT HEAD CHECK BY: | K26: APPROVED BY: PHÊ DUYỆT
K27: Nguyễn Quang Vinh | M27: Hoàng Ngọc Bằng | P27: Đoàn Văn Toàn

Sheet Vật tư đóng kiện Ngọc hiếu 090
A1: BID ANALYSIS - GIẢI TRÌNH MUA SẮM/ĐẤU THẦU
A3: Project | B3: PROJECT No/ Dự án: 25-BRA-I-090
A4: Dự án
A5: Subject | B5: Cung cấp vật tư đóng kiện dự án 090
A6: Chủ đề
A8: No. | B8: CONTENT | C8: Phạm vi công việc | H8: Dự toán | K8: Đã mua/Đã đặt | L8: Đơn vị cung cấp chào giá (vnđ) | O8: Đơn vị cung cấp chào giá (vnđ) | R8: Lựa chọn | S8: Ghi chú
A9: Item | B9: Description/ Chi tiết | C9: Profile/ Vật tư | D9: Grade/ Mác vật liệu | E9: Số lượng (cây) | G9: Trọng lượng (KG) | H9: Khối lượng/ Số lượng | I9: Đơn giá (vnd) | J9: Thành tiền (vnd) | K9: Thành tiền (vnd) | L9: Ngọc Hiếu | O9: Hùng Nguyên
E10: Số lượng (cây) | G10: Trọng lượng | L10: Phạm vi | M10: Đơn giá (VND) | N10: Thành Tiền (Không có VAT) | O10: Phạm vi | P10: Đơn giá (VND) | Q10: Thành Tiền (Không có VAT)
A11: Tổng | H11: N/A | I11: N/A | J11: ='DT04 (TM) 1 '!L17 -> 2538751590 | K11: ='Tổng hợp'!J16+'Vật tư đóng kiện Hoàng hà 090'!N11 -> 4.2858429e+09 | N11: =SUM(N12:N26) -> 708322117 | Q11: =SUM(Q12:Q26) -> 0 | S11: =J11-K11-N11 -> -2.4554134e+09
A12: I90-C5 | B12: PL10x2000x12000 | C12: Thép tấm 10*2000*12000 | D12: SS400 | E12: 1 | F12: 24 | G12: 1884 | H12: N/A | I12: N/A | J12: N/A | K12: N/A | L12: V | M12: 13636.36 | N12: 25690902 | O12: V | P12: 13727.27 | Q12: N/A | R12: Ngọc Hiếu | S12: -Giá trí mua đang vượt dự toán - PTM không nắm được vật tư phụ kiện còn phát sinh hàng không - Thông báo tới SALE để khách hàng hỗ trợ thêm chi phí
A13: I90-C6 | B13: PL12x2000x12000 | C13: Thép tấm 12*2000*12000 | D13: SS400 | E13: 1 | F13: 24 | G13: 2261 | H13: N/A | I13: N/A | J13: N/A | K13: N/A | L13: V | M13: 13636.36 | N13: 30831810 | O13: V | P13: 13727.27 | Q13: N/A | R13: Ngọc Hiếu
A14: I90-C7 | B14: PL15x2000x12000 | C14: Thép tấm 16*2000*6000 | D14: SS400 | E14: 1 | F14: 12 | G14: 1507 | H14: N/A | I14: N/A | J14: N/A | K14: N/A | L14: V | M14: 14000 | N14: 21098000 | O14: V | P14: 14000 | Q14: N/A | R14: Ngọc Hiếu
A15: I90-C8 | B15: PL20x2000x12000 | C15: Thép tấm 20*2000*12000 | D15: SS400 | E15: 1 | F15: 24 | G15: 3768 | H15: N/A | I15: N/A | J15: N/A | K15: N/A | L15: V | M15: 14181.82 | N15: 53437098 | O15: V | P15: 14545.45 | Q15: N/A | R15: Ngọc Hiếu
A16: I90-C12 | B16: HEA120(H114x120x5x8)-L12000 | C16: Thép H125*125*6,5*9*12000 | D16: SS400 | E16: 6 | F16: 72 | G16: 1699 | H16: N/A | I16: N/A | J16: N/A | K16: N/A | L16: V | M16: 17545.45 | N16: 29809720 | O16: V | P16: 17636.36 | Q16: N/A | R16: Ngọc Hiếu
A17: I90-C13 | B17: HEA180(171x180x6x9.5)-L12000 | C17: Thép H200*200*8*12*12000 | D17: SS400 | E17: 12 | F17: =E17*12 -> 144 | G17: 7186 | H17: N/A | I17: N/A | J17: N/A | K17: N/A | L17: V | M17: 17545.45 | N17: 126081604 | O17: V | P17: 17636.36 | Q17: N/A | R17: Ngọc Hiếu
A18: I90-C15 | B18: HEA260(H250x260x7.5x12.5)-L12000 | C18: Thép H250*250*9*14*12000 | D18: SS400 | E18: 3 | F18: =E18*12 -> 36 | G18: 2585 | H18: N/A | I18: N/A | J18: N/A | K18: N/A | L18: V | M18: 17545.45 | N18: 45354988 | O18: V | P18: 17636.36 | Q18: N/A | R18: Ngọc Hiếu
A19: I90-C16 | B19: HEB140(H140x140x7x12)-L12000 | C19: Thép H150*150*7*10*12000 | D19: SS400 | E19: 3.5 | F19: =E19*12 -> 42 | G19: 1306 | H19: N/A | I19: N/A | J19: N/A | K19: N/A | L19: V | M19: 17545.45 | N19: 22914358 | O19: V | P19: 17636.36 | Q19: N/A | R19: Ngọc Hiếu
A20: I90-C21 | B20: UNP200(C200x75x8.5x11.5)-L12000 | C20: Thép U200*90*8*13,5*12000 | D20: SS400 | E20: 8 | F20: 96 | G20: 2909 | H20: N/A | I20: N/A | J20: N/A | K20: N/A | L20: V | M20: 17545.45 | N20: 51039714 | O20: V | P20: 17500 | Q20: N/A | R20: Ngọc Hiếu
A21: I90-C22 | B21: UNP220(C220x80x9x12.5)-L12000 | C21: Thép U250*90*9*13*12000 | D21: SS400 | E21: 35 | F21: 420 | G21: 14532 | H21: N/A | I21: N/A | J21: N/A | K21: N/A | L21: V | M21: 17545.45 | N21: 254970479 | O21: X | P21: N/A | Q21: N/A | R21: Ngọc Hiếu
A22: I90-C24 | B22: UNP260(C260x90x10x14)-L12000 | C22: Thép U300x90x9x13 x120000 | D22: SS400 | E22: 1 | F22: 12 | G22: 457 | H22: N/A | I22: N/A | J22: N/A | K22: N/A | L22: V | M22: 17545.45 | N22: 8018271 | O22: V | P22: 17772.73 | Q22: N/A | R22: Ngọc Hiếu
A23: I90-C26 | B23: UPN120(C120x55x7x9)-L12000 | C23: Thép U125*65*6*8*12000 | D23: SS400 | E23: 11 | F23: 132 | G23: 1769 | H23: N/A | I23: N/A | J23: N/A | K23: N/A | L23: V | M23: 17545.45 | N23: 31037901 | O23: X | P23: N/A | Q23: N/A | R23: Ngọc Hiếu
A24: I90-C28 | B24: L150x150x10-L6000 | C24: Thép V150*150*10*6000 | D24: SS400 | E24: 1 | F24: 6 | G24: 138 | H24: N/A | I24: N/A | J24: N/A | K24: N/A | L24: V | M24: 15909.09 | N24: 2195454 | O24: X | P24: N/A | Q24: N/A | R24: Ngọc Hiếu
A25: I90-C29 | B25: L75x75x6-L12000 | C25: Thép V80*80*8*6000 | D25: SS400 | E25: 3 | F25: 18 | G25: 173 | H25: N/A | I25: N/A | J25: N/A | K25: N/A | L25: V | M25: 13909.09 | N25: 2406273 | O25: V | P25: 14181.82 | Q25: N/A | R25: Ngọc Hiếu
A26: I90-C30 | B26: L80x80x8-L12000 | C26: Thép V75*75*6*12000 | D26: SS400 | E26: 3 | F26: 36 | G26: 247 | H26: N/A | I26: N/A | J26: N/A | K26: N/A | L26: V | M26: 13909.09 | N26: 3435545 | O26: V | P26: 14181.82 | Q26: N/A | R26: Ngọc Hiếu
B27: Đơn giá tổng hợp
A28: II | B28: Khối lượng dự kiến giao (Kg )/ Estimated weight (Kg):
A29: 1 | B29: … | C29: kg
A30: 2 | B30: …
A31: III | B31: Tiến độ/ Schedule | C31: Bắt đầu/ Start | D31: Kết thúc/ Finish
A32: 1 | B32: ….
A34: IV | B34: Nhân lực/ ManPower
A35: 1 | B35: Thợ Pha cắt / Thợ sắt / Thợ hàn / …
B36: ….
A37: V | B37: Yêu cầu kỹ thuật: Tham chiếu các tài liệu đính kèm/ Technical requirement – refer to document attached
B38: Xếp hạng | M38: 1 | P38: 2
A39: Ghi Chú: Vật tư đóng kiện dự án 090 tính tiền theo khối lượng thực tế, PTM tiến hành mua hàng
A40: NGƯỜI ĐỀ NGHỊ/ RECOMMENDATION BY: | C40: NGƯỜI KIỂM TRA/ DEPARTMENT HEAD CHECK BY: | G40: APPROVED BY: PHÊ DUYỆT
G41: Nguyễn Quang Vinh | I41: Hoàng Ngọc Bằng | L41: Đoàn Văn Toàn

Sheet Vật tư đóng kiện Hoàng hà2
A1: BID ANALYSIS - GIẢI TRÌNH MUA SẮM/ĐẤU THẦU
A3: Project | B3: PROJECT No/ Dự án: 25-BRA-I-090
A4: Dự án
A5: Subject | B5: Cung cấp vật tư đóng kiện dự án 090
A6: Chủ đề
A8: No. | B8: CONTENT | C8: Phạm vi công việc | H8: Dự toán | K8: Đã mua | L8: Đơn vị cung cấp chào giá (vnđ) | O8: Lựa chọn | P8: Ghi chú
A9: Item | B9: Description/ Chi tiết | C9: Profile/ Vật tư | D9: Grade/ Mác vật liệu | E9: Mặt hàng | F9: ĐVT | G9: Số lượng | H9: Khối lượng/ Số lượng | I9: Đơn giá (vnd) | J9: Thành tiền (vnd) | K9: Thành tiền (vnd) | L9: Hoàng Hà
L10: Phạm vi | M10: Đơn giá (VND) | N10: Thành Tiền (Không có VAT)
A11: Tổng | H11: N/A | I11: N/A | J11: ='DT04 (TM) 1 '!L17 -> 2538751590 | K11: ='Tổng hợp'!J16-N11 -> 4.2034457e+09 | N11: =SUM(N12:N21) -> 24533600 | P11: =J11-K11-N11 -> -1.6892277e+09
A12: I90-C107 | B12: Bu lông ren suốt | C12: M20*85 | D12: Mạ kẽm 8.8 | E12: Bulong M8x30 | F12: cái | G12: 8 | H12: N/A | I12: N/A | J12: N/A | L12: V | M12: 12000 | N12: 96000 | O12: Hoàng Hà | P12: -Giá trí mua đang vượt dự toán - PTM không nắm được vật tư phụ kiện còn phát sinh hàng không - Thông báo tới SALE để khách hàng hỗ trợ thêm chi phí
A13: I90-C116 | B13: Ecu | C13: M20 | D13: Mạ kẽm 8.8 | E13: Bulong M8x50 | F13: cái | G13: 8 | H13: N/A | I13: N/A | J13: N/A | L13: V | M13: 2900 | N13: 23200 | O13: Hoàng Hà
A14: I90-C127 | B14: Long đen phẳng | C14: M20 | D14: Mạ kẽm 8.8 | E14: Bulong M10x20 | F14: cái | G14: 16 | H14: N/A | I14: N/A | J14: N/A | L14: V | M14: 1050 | N14: 16800 | O14: Hoàng Hà
A15: I90-C50 | B15: Bu lông ren suốt | C15: M24*110 | D15: Mạ kẽm 8.8 | E15: Bulong M10x30 | F15: cái | G15: 24 | H15: N/A | I15: N/A | J15: N/A | L15: V | M15: 20800 | N15: 499200 | O15: Hoàng Hà
A16: I90-C60 | B16: Ecu | C16: M24 | D16: Mạ kẽm 8.8 | E16: Bulong M10x40 | F16: cái | G16: 24 | H16: N/A | I16: N/A | J16: N/A | L16: V | M16: 4800 | N16: 115200 | O16: Hoàng Hà
A17: I90-C72 | B17: Long đen phẳng | C17: M24 | D17: Mạ kẽm 8.8 | E17: Bulong M10x50 | F17: cái | G17: 48 | H17: N/A | I17: N/A | J17: N/A | L17: V | M17: 1150 | N17: 55200 | O17: Hoàng Hà
A18: I90-C93 | B18: Dây chằng hàng | C18: D50 | D18: Vải | E18: Bulong M12x40 | F18: met | G18: 1000 | H18: N/A | I18: N/A | J18: N/A | L18: V | M18: 5830 | N18: 5830000 | O18: Hoàng Hà
A19: I90-C93 | B19: Dây chằng hàng | C19: D50 | D19: Vải | E19: Bulong M12x40 | F19: cái | G19: 600 | H19: N/A | I19: N/A | J19: N/A | L19: V | M19: 5830 | N19: 3498000 | O19: Hoàng Hà
A20: I90-C94 | B20: Khóa dây chằng hàng | C20: D50 | D20: Thép mạ | E20: Bulong M12x70 | F20: cái | G20: 200 | H20: N/A | I20: N/A | J20: N/A | L20: V | M20: 36000 | N20: 7200000 | O20: Hoàng Hà
A21: I90-C94 | B21: Khóa dây chằng hàng | C21: D50 | D21: Thép mạ | E21: Bulong M12x80 | F21: cái | G21: 200 | H21: N/A | I21: N/A | J21: N/A | L21: V | M21: 36000 | N21: 7200000 | O21: Hoàng Hà
B22: Đơn giá tổng hợp
A23: II | B23: Khối lượng dự kiến giao (Kg )/ Estimated weight (Kg):
A24: 1 | B24: … | C24: kg
A25: 2 | B25: …
A26: III | B26: Tiến độ/ Schedule | C26: Bắt đầu/ Start | D26: Kết thúc/ Finish
A27: 1 | B27: ….
A29: IV | B29: Nhân lực/ ManPower
A30: 1 | B30: Thợ Pha cắt / Thợ sắt / Thợ hàn / …
B31: ….
A32: V | B32: Yêu cầu kỹ thuật: Tham chiếu các tài liệu đính kèm/ Technical requirement – refer to document attached
B33: Xếp hạng | M33: 1
A34: Ghi Chú: Vật tư đóng kiện dự án 090 tính tiền theo khối lượng thực tế, PTM tiến hành mua hàng
A35: NGƯỜI ĐỀ NGHỊ/ RECOMMENDATION BY: | C35: NGƯỜI KIỂM TRA/ DEPARTMENT HEAD CHECK BY: | G35: APPROVED BY: PHÊ DUYỆT
G36: Nguyễn Quang Vinh | I36: Hoàng Ngọc Bằng | L36: Đoàn Văn Toàn

Sheet Vật tư VSAN 21-3-
A1: BID ANALYSIS - GIẢI TRÌNH MUA SẮM/ĐẤU THẦU
A3: Project | B3: PROJECT No/ Dự án: 25-BRA-I-090
A4: Dự án
A5: Subject | B5: Cung cấp vật tư phụ kiện VSAN ngày 21-3
A6: Chủ đề
A8: No. | B8: CONTENT | C8: Phạm vi công việc | I8: Dự toán | L8: Đã mua | M8: Đơn vị cung cấp chào giá (vnđ) | P8: Lựa chọn | Q8: Ghi chú
A9: Item | B9: Description/ Chi tiết | C9: Profile/ Vật tư | D9: Số lượng PR PSC | E9: Grade/ Mác vật liệu | F9: Mặt hàng | G9: ĐVT | H9: Số lượng | I9: Khối lượng/ Số lượng | J9: Đơn giá (vnd) | K9: Thành tiền (vnd) | L9: Thành tiền (vnd) | M9: VSAN
M10: Phạm vi | N10: Đơn giá (VND) | O10: Thành Tiền (Không có VAT)
A11: Tổng | I11: N/A | J11: N/A | K11: ='Tổng hợp'!K14 -> 2.7375767e+10 | L11: ='Tổng hợp'!J14 -> 2.8199693e+10 | O11: =SUM(O12) -> 306000 | Q11: =K11-L11-O11 -> -8.242323e+08
A12: I90-A133 | B12: =VLOOKUP(A12,'25-BRA-I-090'!I:L,3,0) -> chốt chẻ D8x90-ISO 1234 | C12: =VLOOKUP(A12,'25-BRA-I-090'!I:L,4,0) -> Steel-hot dip gal'v or SUS304 | D12: =VLOOKUP(A12,'25-BRA-I-090'!I:FF,149,0) -> 0 | E12: Chốt chẻ M8x90 inox | F12: inox 304 | G12: PSC | H12: 6 | I12: N/A | J12: N/A | K12: N/A | M12: V | N12: 51000 | O12: =N12*H12 -> 306000 | P12: VSAN
A13: Tổng | I13: N/A | J13: N/A | K13: ='Tổng hợp'!K15 -> 1.703349e+09 | L13: ='Tổng hợp'!J15 -> 4.9994399e+09 | O13: =SUM(O14:O24) -> 8960150 | Q13: =K13-L13-O13 -> -3.305051e+09
A14: I90-B9 | B14: =VLOOKUP(A14,'25-BRA-I-090'!I:L,3,0) -> Bolt-M12x45-ISO4017-8.8-Galv | C14: =VLOOKUP(A14,'25-BRA-I-090'!I:L,4,0) -> 8.8-Galv | D14: =VLOOKUP(A14,'25-BRA-I-090'!I:FF,149,0) -> 0 | E14: Bulong M12x50 | F14: Gr 8.8 ISO 4017 HDG | G14: PSC | H14: 79 | I14: N/A | J14: N/A | K14: N/A | M14: V | N14: 3640 | O14: =N14*H14 -> 287560 | P14: VSAN
A15: I90-B17 | B15: =VLOOKUP(A15,'25-BRA-I-090'!I:L,3,0) -> Bolt-M16x70-DIN186B-8.8-Galv | C15: =VLOOKUP(A15,'25-BRA-I-090'!I:L,4,0) -> 8.8-Galv | D15: =VLOOKUP(A15,'25-BRA-I-090'!I:FF,149,0) -> -112 | E15: Bulong đầu búa M16x70 | F15: DIN186B-8.8-HDG | G15: PSC | H15: 154 | I15: N/A | J15: N/A | K15: N/A | M15: V | N15: 44000 | O15: =N15*H15 -> 6776000 | P15: VSAN
A16: I90-B40 | B16: =VLOOKUP(A16,'25-BRA-I-090'!I:L,3,0) -> Bolt-M5x16-DIN912-8.8-Galv | C16: =VLOOKUP(A16,'25-BRA-I-090'!I:L,4,0) -> 8.8-Galv | D16: =VLOOKUP(A16,'25-BRA-I-090'!I:FF,149,0) -> 0 | E16: Bulong LGC M5x16 | F16: Gr 10.9/ Gr 12.9 DIN 912 Geomet | G16: PSC | H16: 9 | I16: N/A | J16: N/A | K16: N/A | M16: V | N16: 3000 | O16: =N16*H16 -> 27000 | P16: VSAN
A17: I90-B43 | B17: =VLOOKUP(A17,'25-BRA-I-090'!I:L,3,0) -> Bolt-M6x12-ISO4017-8.8-Galv | C17: =VLOOKUP(A17,'25-BRA-I-090'!I:L,4,0) -> 8.8-Galv | D17: =VLOOKUP(A17,'25-BRA-I-090'!I:FF,149,0) -> 0 | E17: Bulong M6x12 | F17: Gr 8.8 ISO 4017 Geomet | G17: PSC | H17: 2 | I17: N/A | J17: N/A | K17: N/A | M17: V | N17: 4200 | O17: =N17*H17 -> 8400 | P17: VSAN
A18: I90-B49 | B18: =VLOOKUP(A18,'25-BRA-I-090'!I:L,3,0) -> BOLT-M8x20-ISO4017-8.8-Galv | C18: =VLOOKUP(A18,'25-BRA-I-090'!I:L,4,0) -> 8.8-Galv | D18: =VLOOKUP(A18,'25-BRA-I-090'!I:FF,149,0) -> 0 | E18: Bulong M8x20 | F18: Gr 8.8 ISO 4017 Geomet | G18: PSC | H18: 2 | I18: N/A | J18: N/A | K18: N/A | M18: V | N18: 860 | O18: =N18*H18 -> 1720 | P18: VSAN
A19: I90-B54 | B19: =VLOOKUP(A19,'25-BRA-I-090'!I:L,3,0) -> Nut-M10-ISO4032-8-Galv | C19: =VLOOKUP(A19,'25-BRA-I-090'!I:L,4,0) -> 8-Galv | D19: =VLOOKUP(A19,'25-BRA-I-090'!I:FF,149,0) -> 0 | E19: Ecu M10 | F19: Gr 8 ISO 4032 HDG | G19: PSC | H19: 860 | I19: N/A | J19: N/A | K19: N/A | M19: V | N19: 810 | O19: =N19*H19 -> 696600 | P19: VSAN
A20: I90-B73 | B20: =VLOOKUP(A20,'25-BRA-I-090'!I:L,3,0) -> NUT-M5-ISO4032-8-Galv | C20: =VLOOKUP(A20,'25-BRA-I-090'!I:L,4,0) -> 8-Galv | D20: =VLOOKUP(A20,'25-BRA-I-090'!I:FF,149,0) -> 0 | E20: Ecu M5 | F20: Gr 8 ISO 4032 Geomet | G20: PSC | H20: 11 | I20: N/A | J20: N/A | K20: N/A | M20: V | N20: 90 | O20: =N20*H20 -> 990 | P20: VSAN
A21: I90-B85 | B21: =VLOOKUP(A21,'25-BRA-I-090'!I:L,3,0) -> Washer-M10-ISO7089-St-200 HV-Galv | C21: =VLOOKUP(A21,'25-BRA-I-090'!I:L,4,0) -> St-200 HV-Galv | D21: =VLOOKUP(A21,'25-BRA-I-090'!I:FF,149,0) -> 0 | E21: Vòng đệm phẳng M10 | F21: 200HV ISO 7089 HDG | G21: PSC | H21: 738 | I21: N/A | J21: N/A | K21: N/A | M21: V | N21: 450 | O21: =N21*H21 -> 332100 | P21: VSAN
A22: I90-B105 | B22: =VLOOKUP(A22,'25-BRA-I-090'!I:L,3,0) -> Washer-M5-ISO7089-St-200 HV-tZn | C22: =VLOOKUP(A22,'25-BRA-I-090'!I:L,4,0) -> St-200 HV-tZn | D22: =VLOOKUP(A22,'25-BRA-I-090'!I:FF,149,0) -> 0 | E22: Vòng đệm phẳng M5 | F22: 200HV ISO 7089 Geomet | G22: PSC | H22: 7 | I22: N/A | J22: N/A | K22: N/A | M22: V | N22: 1000 | O22: =N22*H22 -> 7000 | P22: VSAN
A23: I90-B112 | B23: =VLOOKUP(A23,'25-BRA-I-090'!I:L,3,0) -> Washer-M8-ISO7093-St-Galv | C23: =VLOOKUP(A23,'25-BRA-I-090'!I:L,4,0) -> St-Galv | D23: =VLOOKUP(A23,'25-BRA-I-090'!I:FF,149,0) -> 0 | E23: Vòng đệm phẳng rộng M8 | F23: 200HV DIN 9021 Geomet | G23: PSC | H23: 8 | I23: N/A | J23: N/A | K23: N/A | M23: V | N23: 1560 | O23: =N23*H23 -> 12480 | P23: VSAN
A24: I90-B119 | B24: =VLOOKUP(A24,'25-BRA-I-090'!I:L,3,0) -> Washer M12-St-200 HV-ISO7093A-tZn | C24: =VLOOKUP(A24,'25-BRA-I-090'!I:L,4,0) -> St-Galv | D24: =VLOOKUP(A24,'25-BRA-I-090'!I:FF,149,0) -> 0 | E24: Vòng đệm phẳng rộng M12 | F24: 200HV DIN 9021 HDG | G24: PSC | H24: 146 | I24: N/A | J24: N/A | K24: N/A | M24: V | N24: 5550 | O24: =N24*H24 -> 810300 | P24: VSAN
B25: Xếp hạng | N25: 1
A26: Ghi Chú: PTM tiến hành mua hàng để đảm bảo tiến độ
A27: NGƯỜI ĐỀ NGHỊ/ RECOMMENDATION BY: | C27: NGƯỜI KIỂM TRA/ DEPARTMENT HEAD CHECK BY: | H27: APPROVED BY: PHÊ DUYỆT
H28: Nguyễn Quang Vinh | K28: Hoàng Ngọc Bằng | M28: Đoàn Văn Toàn

Sheet Vật tư Hoàng Hà 20-3
A1: BID ANALYSIS - GIẢI TRÌNH MUA SẮM/ĐẤU THẦU
A3: Project | B3: PROJECT No/ Dự án: 25-BRA-I-090
A4: Dự án
A5: Subject | B5: Cung cấp vật tư phụ kiện Hoàng Hà ngày 15-3
A6: Chủ đề
A8: No. | B8: CONTENT | C8: Phạm vi công việc | H8: Dự toán | K8: Đã mua | L8: Đơn vị cung cấp chào giá (vnđ) | O8: Lựa chọn | P8: Ghi chú
A9: Item | B9: Description/ Chi tiết | C9: Profile/ Vật tư | D9: Grade/ Mác vật liệu | E9: Mặt hàng | F9: ĐVT | G9: Số lượng | H9: Khối lượng/ Số lượng | I9: Đơn giá (vnd) | J9: Thành tiền (vnd) | K9: Thành tiền (vnd) | L9: Hoàng Hà
L10: Phạm vi | M10: Đơn giá (VND) | N10: Thành Tiền (Không có VAT)
A11: Tổng | H11: N/A | I11: N/A | J11: ='Tổng hợp'!K15 -> 1.703349e+09 | K11: ='Tổng hợp'!J15 -> 4.9994399e+09 | N11: =SUM(N12:N14) -> 35715600 | P11: =J11-K11-N11 -> -3.3318065e+09
A12: I90-B30 | B12: Bolt-M20x65-ISO4017-8.8-Galv | C12: 8.8-Galv | D12: Bulong M20x70 | E12: 8.8-Galv | F12: PSC | G12: 1539 | H12: N/A | I12: N/A | J12: N/A | L12: V | M12: 18000 | N12: =M12*G12 -> 27702000 | O12: Hoàng Hà
A13: I90-B63 | B13: Nut-M20-ISO4032-8-Galv | C13: 8.8-Galv | D13: Ecu M20 | E13: 8-Galv | F13: PSC | G13: 1364 | H13: N/A | I13: N/A | J13: N/A | L13: V | M13: 4000 | N13: =M13*G13 -> 5456000 | O13: Hoàng Hà
A14: I90-B98 | B14: Washer-M20-ISO7089-St-Galv | C14: St-Galv | D14: Vòng đệm phẳng M20 | E14: St-Galv | F14: PSC | G14: 3197 | H14: N/A | I14: N/A | J14: N/A | L14: V | M14: 800 | N14: =M14*G14 -> 2557600 | O14: Hoàng Hà
B15: Xếp hạng | M15: 1
A16: Ghi Chú: PTM tiến hành mua hàng để đảm bảo tiến độ
A17: NGƯỜI ĐỀ NGHỊ/ RECOMMENDATION BY: | C17: NGƯỜI KIỂM TRA/ DEPARTMENT HEAD CHECK BY: | G17: APPROVED BY: PHÊ DUYỆT
G18: Nguyễn Quang Vinh | J18: Hoàng Ngọc Bằng | L18: Đoàn Văn Toàn

Sheet Vật tư VSAN 9-3 
A1: BID ANALYSIS - GIẢI TRÌNH MUA SẮM/ĐẤU THẦU
A3: Project | B3: PROJECT No/ Dự án: 25-BRA-I-090
A4: Dự án
A5: Subject | B5: Cung cấp vật tư phụ kiện VSAN ngày 9-3
A6: Chủ đề
A8: No. | B8: CONTENT | C8: Phạm vi công việc | H8: Dự toán | K8: Đã mua | L8: Đơn vị cung cấp chào giá (vnđ) | O8: Lựa chọn | P8: Ghi chú
A9: Item | B9: Description/ Chi tiết | C9: Profile/ Vật tư | D9: Grade/ Mác vật liệu | E9: Mặt hàng | F9: ĐVT | G9: Số lượng | H9: Khối lượng/ Số lượng | I9: Đơn giá (vnd) | J9: Thành tiền (vnd) | K9: Thành tiền (vnd) | L9: VSAN
L10: Phạm vi | M10: Đơn giá (VND) | N10: Thành Tiền (Không có VAT)
A11: Tổng | H11: N/A | I11: N/A | J11: ='Tổng hợp'!K14 -> 2.7375767e+10 | K11: ='Tổng hợp'!J14-N11 -> 2.8198943e+10 | N11: =SUM(N12) -> 750000 | P11: =J11-K11-N11 -> -8.239263e+08
A12: I90-A131 | B12: Spring D2.2 | C12: Steel | D12: Lò xo D3 inox | E12: SS 304 | F12: PSC | G12: 5 | H12: N/A | I12: N/A | J12: N/A | L12: V | M12: 150000 | N12: =M12*G12 -> 750000 | O12: VSAN
B13: Xếp hạng | M13: 1
A14: Ghi Chú: PTM tiến hành mua hàng để đảm bảo tiến độ
A15: NGƯỜI ĐỀ NGHỊ/ RECOMMENDATION BY: | C15: NGƯỜI KIỂM TRA/ DEPARTMENT HEAD CHECK BY: | G15: APPROVED BY: PHÊ DUYỆT
G16: Nguyễn Quang Vinh | J16: Hoàng Ngọc Bằng | L16: Đoàn Văn Toàn

Sheet Vật tư VSAN 5-3
A1: BID ANALYSIS - GIẢI TRÌNH MUA SẮM/ĐẤU THẦU
A3: Project | B3: PROJECT No/ Dự án: 25-BRA-I-090
A4: Dự án
A5: Subject | B5: Cung cấp vật tư phụ kiện VSAN ngày 5-3
A6: Chủ đề
A8: No. | B8: CONTENT | C8: Phạm vi công việc | H8: Dự toán | K8: Đã mua | L8: Đơn vị cung cấp chào giá (vnđ) | O8: Lựa chọn | P8: Ghi chú
A9: Item | B9: Description/ Chi tiết | C9: Profile/ Vật tư | D9: Grade/ Mác vật liệu | E9: Mặt hàng | F9: ĐVT | G9: Số lượng | H9: Khối lượng/ Số lượng | I9: Đơn giá (vnd) | J9: Thành tiền (vnd) | K9: Thành tiền (vnd) | L9: VSAN
L10: Phạm vi | M10: Đơn giá (VND) | N10: Thành Tiền (Không có VAT)
A11: Tổng | H11: N/A | I11: N/A | J11: ='Tổng hợp'!K14 -> 2.7375767e+10 | K11: ='Tổng hợp'!J14-N11 -> 2.8199093e+10 | N11: =SUM(N12) -> 600000 | P11: =J11-K11-N11 -> -8.239263e+08
A12: I90-A131 | B12: Spring D2.2 | C12: Steel | D12: Lò xo D3 inox | E12: SS 304 | F12: PSC | G12: 3 | H12: N/A | I12: N/A | J12: N/A | L12: V | M12: 200000 | N12: =M12*G12 -> 600000 | O12: VSAN
A13: Tổng | H13: N/A | I13: N/A | J13: ='Tổng hợp'!K15 -> 1.703349e+09 | K13: ='Tổng hợp'!J15-N13 -> 4.9940097e+09 | N13: =SUM(N14:N25) -> 5430170 | P13: =J13-K13-N13 -> -3.2960909e+09
A14: I90-B8 | B14: Bolt-M12x40-ISO4017-8.8-Galv | C14: 8.8-Galv | D14: Bulong M12x40 | E14: Gr 8.8 ISO 4017 HDG | F14: PSC | G14: 70 | H14: N/A | I14: N/A | J14: N/A | L14: V | M14: 3140 | N14: =M14*G14 -> 219800 | O14: VSAN
A15: I90-B29 | B15: Bolt-M20x55-ISO4017-8.8-Galv | C15: 8.8-Galv | D15: Bulong M20x60 | E15: Gr 8.8 ISO 4017 HDG | F15: PSC | G15: 55 | H15: N/A | I15: N/A | J15: N/A | L15: V | M15: 13720 | N15: =M15*G15 -> 754600 | O15: VSAN
A16: I90-B42 | B16: Bolt-M6x12-DIN7500-St-Galv | C16: St-Galv | D16: Bulong M6x12 | E16: DIN7500-St Geomet | F16: PSC | G16: 125 | H16: N/A | I16: N/A | J16: N/A | L16: V | M16: 8200 | N16: =M16*G16 -> 1025000 | O16: VSAN
A17: I90-B46 | B17: Bolt-M6x20-DIN7500-St-Galv | C17: St-Galv | D17: Bulong M6x20 | E17: DIN7500-St Geomet | F17: PSC | G17: 8 | H17: N/A | I17: N/A | J17: N/A | L17: V | M17: 8400 | N17: =M17*G17 -> 67200 | O17: VSAN
A18: I90-B48 | B18: Bolt-M6x25-ISO4017-8.8-Galv | C18: 8.8-Galv | D18: Bulong M6x25 | E18: Gr 8.8 ISO 4017 Geomet | F18: PSC | G18: 80 | H18: N/A | I18: N/A | J18: N/A | L18: V | M18: 5500 | N18: =M18*G18 -> 440000 | O18: VSAN
A19: I90-B74 | B19: Nut-M6-ISO4032-8-Galv | C19: 8-Galv | D19: Ecu M6 | E19: Gr 8 ISO 4032 Geomet | F19: PSC | G19: 80 | H19: N/A | I19: N/A | J19: N/A | L19: V | M19: 180 | N19: =M19*G19 -> 14400 | O19: VSAN
A20: I90-B76 | B20: Nut-M8-ISO4032-8-Galv | C20: 8-Galv | D20: Ecu M8 | E20: Gr 8 ISO 4032 Geomet | F20: PSC | G20: 120 | H20: N/A | I20: N/A | J20: N/A | L20: V | M20: 360 | N20: =M20*G20 -> 43200 | O20: VSAN
A21: I90-B108 | B21: Washer-M6-ISO7089-St-200 HV-tZn | C21: St-200 HV-tZn | D21: Vòng đệm phẳng M6 | E21: 200HV ISO 7089 Geomet | F21: PSC | G21: 160 | H21: N/A | I21: N/A | J21: N/A | L21: V | M21: 1000 | N21: =M21*G21 -> 160000 | O21: VSAN
A22: I90-B119 | B22: Washer-M12-ISO7093-St-200 HV-Galv | C22: St-300 HV-Galv | D22: Vòng đệm phẳng rộng M12 | E22: 200HV DIN 9021 HDG | F22: PSC | G22: 103 | H22: N/A | I22: N/A | J22: N/A | L22: V | M22: 5550 | N22: =M22*G22 -> 571650 | O22: VSAN
A23: I90-B132 | B23: Bolt-M16x90-ISO4017-8.8-Galv | C23: 8.8-Galv | D23: Bulong M16x90 | E23: Gr 8.8 ISO 4017 HDG | F23: PSC | G23: 16 | H23: N/A | I23: N/A | J23: N/A | L23: V | M23: 9420 | N23: =M23*G23 -> 150720 | O23: VSAN
A24: I90-B133 | B24: Bolt-M20x60-ISO4017-8.8-Galv | C24: 8.8-Galv | D24: Bulong M20x60 | E24: Gr 8.8 ISO 4017 HDG | F24: PSC | G24: 160 | H24: N/A | I24: N/A | J24: N/A | L24: V | M24: 11760 | N24: =M24*G24 -> 1881600 | O24: VSAN
A25: I90-B134 | B25: Bolt-M6x25-DIN7500-St-Galv | C25: St-Galv | D25: Bulong M6x25 | E25: DIN7500-St Geomet | F25: PSC | G25: 10 | H25: N/A | I25: N/A | J25: N/A | L25: V | M25: 10200 | N25: =M25*G25 -> 102000 | O25: VSAN
B26: Xếp hạng | M26: 1
A27: Ghi Chú: PTM tiến hành mua hàng để đảm bảo tiến độ
A28: NGƯỜI ĐỀ NGHỊ/ RECOMMENDATION BY: | C28: NGƯỜI KIỂM TRA/ DEPARTMENT HEAD CHECK BY: | G28: APPROVED BY: PHÊ DUYỆT
G29: Nguyễn Quang Vinh | J29: Hoàng Ngọc Bằng | L29: Đoàn Văn Toàn

Sheet Vật tư đóng kiện Hoàng hà 090
A1: BID ANALYSIS - GIẢI TRÌNH MUA SẮM/ĐẤU THẦU
A3: Project | B3: PROJECT No/ Dự án: 25-BRA-I-090
A4: Dự án
A5: Subject | B5: Cung cấp vật tư đóng kiện dự án 090
A6: Chủ đề
A8: No. | B8: CONTENT | C8: Phạm vi công việc | H8: Dự toán | K8: Đã mua | L8: Đơn vị cung cấp chào giá (vnđ) | O8: Lựa chọn | P8: Ghi chú
A9: Item | B9: Description/ Chi tiết | C9: Profile/ Vật tư | D9: Grade/ Mác vật liệu | E9: Mặt hàng | F9: ĐVT | G9: Số lượng | H9: Khối lượng/ Số lượng | I9: Đơn giá (vnd) | J9: Thành tiền (vnd) | K9: Thành tiền (vnd) | L9: Hoàng Hà
L10: Phạm vi | M10: Đơn giá (VND) | N10: Thành Tiền (Không có VAT)
A11: Tổng | H11: N/A | I11: N/A | J11: ='DT04 (TM) 1 '!L17 -> 2538751590 | K11: ='Tổng hợp'!J16 -> 4.2279793e+09 | N11: =SUM(N12:N66) -> 57863610 | P11: =J11-K11-N11 -> -1.7470913e+09
A12: I90-C32 | B12: Bu lông ren suốt | C12: M16*50 | D12: Mạ kẽm 8.8 | E12: Bulong M8x30 | F12: PSC | G12: 788 | H12: N/A | I12: N/A | J12: N/A | L12: V | M12: 4600 | N12: =M12*G12 -> 3624800 | O12: Hoàng Hà | P12: -Giá trí mua đang vượt dự toán - PTM không nắm được vật tư phụ kiện còn phát sinh hàng không - Thông báo tới SALE để khách hàng hỗ trợ thêm chi phí
A13: I90-C33 | B13: Bu lông ren suốt | C13: M16*60 | D13: Mạ kẽm 8.8 | E13: Bulong M8x50 | F13: PSC | G13: 372 | H13: N/A | I13: N/A | J13: N/A | L13: V | M13: 5250 | N13: =M13*G13 -> 1953000 | O13: Hoàng Hà
A14: I90-C35 | B14: Bu lông ren suốt | C14: M16*70 | D14: Mạ kẽm 8.8 | E14: Bulong M10x20 | F14: PSC | G14: 48 | H14: N/A | I14: N/A | J14: N/A | L14: V | M14: 5850 | N14: =M14*G14 -> 280800 | O14: Hoàng Hà
A15: I90-C36 | B15: Bu lông ren suốt | C15: M16*80 | D15: Mạ kẽm 8.8 | E15: Bulong M10x30 | F15: PSC | G15: 36 | H15: N/A | I15: N/A | J15: N/A | L15: V | M15: 6500 | N15: =M15*G15 -> 234000 | O15: Hoàng Hà
A16: I90-C37 | B16: Bu lông ren suốt | C16: M16*90 | D16: Mạ kẽm 8.8 | E16: Bulong M10x40 | F16: PSC | G16: 24 | H16: N/A | I16: N/A | J16: N/A | L16: V | M16: 7100 | N16: =M16*G16 -> 170400 | O16: Hoàng Hà
A17: I90-C41 | B17: Bu lông ren suốt | C17: M20*50 | D17: Mạ kẽm 8.8 | E17: Bulong M10x50 | F17: PSC | G17: 48 | H17: N/A | I17: N/A | J17: N/A | L17: V | M17: 8150 | N17: =M17*G17 -> 391200 | O17: Hoàng Hà
A18: I90-C42 | B18: Bu lông ren suốt | C18: M20*55 | D18: Mạ kẽm 8.8 | E18: Bulong M12x40 | F18: PSC | G18: 213 | H18: N/A | I18: N/A | J18: N/A | L18: V | M18: 9000 | N18: =M18*G18 -> 1917000 | O18: Hoàng Hà
A19: I90-C44 | B19: Bu lông ren suốt | C19: M20*60 | D19: Mạ kẽm 8.8 | E19: Bulong M12x40 | F19: PSC | G19: 272 | H19: N/A | I19: N/A | J19: N/A | L19: V | M19: 9000 | N19: =M19*G19 -> 2448000 | O19: Hoàng Hà
A20: I90-C46 | B20: Bu lông ren suốt | C20: M20*70 | D20: Mạ kẽm 8.8 | E20: Bulong M12x70 | F20: PSC | G20: 192 | H20: N/A | I20: N/A | J20: N/A | L20: V | M20: 9900 | N20: =M20*G20 -> 1900800 | O20: Hoàng Hà
A21: I90-C48 | B21: Bu lông ren suốt | C21: M24*100 | D21: Mạ kẽm 8.8 | E21: Bulong M12x80 | F21: PSC | G21: 120 | H21: N/A | I21: N/A | J21: N/A | L21: V | M21: 19400 | N21: =M21*G21 -> 2328000 | O21: Hoàng Hà
A22: I90-C50 | B22: Bu lông ren suốt | C22: M24*110 | D22: Mạ kẽm 8.8 | E22: Bulong M16x40 | F22: PSC | G22: 48 | H22: N/A | I22: N/A | J22: N/A | L22: V | M22: 20800 | N22: =M22*G22 -> 998400 | O22: Hoàng Hà
A23: I90-C52 | B23: Bu lông ren suốt | C23: M24*90 | D23: Mạ kẽm 8.8 | E23: Bulong M16x50 | F23: PSC | G23: 120 | H23: N/A | I23: N/A | J23: N/A | L23: V | M23: 17900 | N23: =M23*G23 -> 2148000 | O23: Hoàng Hà
A24: I90-C54 | B24: Bu lông ren suốt | C24: M30*120 | D24: Mạ kẽm 8.8 | E24: Bulong M16x50 | F24: PSC | G24: 96 | H24: N/A | I24: N/A | J24: N/A | L24: V | M24: 46000 | N24: =M24*G24 -> 4416000 | O24: Hoàng Hà
... A66: I90-C139 | B66: Thanh ren | C66: M20*1000 | D66: Mạ kẽm 8.8 | E66: Vòng đệm phẳng rộng M20 | F66: PSC | G66: 12 | H66: N/A | I66: N/A | J66: N/A | L66: V | M66: 13700 | N66: =M66*G66 -> 164400 | O66: Hoàng Hà
B67: Đơn giá tổng hợp
A68: II | B68: Khối lượng dự kiến giao (Kg )/ Estimated weight (Kg):
A69: 1 | B69: … | C69: kg
A70: 2 | B70: …
A71: III | B71: Tiến độ/ Schedule | C71: Bắt đầu/ Start | D71: Kết thúc/ Finish
A72: 1 | B72: ….
A74: IV | B74: Nhân lực/ ManPower
A75: 1 | B75: Thợ Pha cắt / Thợ sắt / Thợ hàn / …
B76: ….
A77: V | B77: Yêu cầu kỹ thuật: Tham chiếu các tài liệu đính kèm/ Technical requirement – refer to document attached
B78: Xếp hạng | M78: 1
A79: Ghi Chú: Vật tư đóng kiện dự án 090 tính tiền theo khối lượng thực tế, PTM tiến hành mua hàng
A80: NGƯỜI ĐỀ NGHỊ/ RECOMMENDATION BY: | C80: NGƯỜI KIỂM TRA/ DEPARTMENT HEAD CHECK BY: | G80: APPROVED BY: PHÊ DUYỆT
G81: Nguyễn Quang Vinh | I81: Hoàng Ngọc Bằng | L81: Đoàn Văn Toàn

Sheet DT04 (TM) 1 
D1: CÔNG TY CỔ PHẦN CÔNG NGHIỆP NẶNG IBS IBS HEAVY INDUSTRY JOINT STOCK COMPANY Add.: KM6, Quốc lộ 5, Phường Hồng Bàng, Thành phố Hải Phòng
A2: BẢNG DỰ TOÁN CHI TIẾT VẬT TƯ
A3: Mẫu số: QT30-DT04 | M3: Mua sắm/ Ordered, Puchased (Đến hiện tại/ Up to now) | U3: THIẾT KẾ/ MUA SẮM THỰC TẾ
A4: STT | B4: Nhóm vật tư | C4: Mã vật tư | D4: Danh mục vật tư | E4: Đơn vị tính | F4: Mác vật liệu | G4: Quy cách | J4: Khối lượng/ Số lượng | K4: Đơn giá (vnd) | L4: Thành tiền (vnd) | M4: Hàng mua thêm | O4: Hàng tồn | Q4: Tổng Giá trị đã mua/ Total Cost (VND) | R4: Đânh giá | S4: Tỷ lệ | T4: Ghi chú | U4: Khối lượng | V4: Giá trị | W4: Chênh lệch | X4: Ghi chú
G5: Dài | H5: Rộng | I5: Dày | M5: Khối lượng/ Weight (Kg) | N5: Số lượng/ Q'ty (M/M2//PSC) | O5: Khối lượng/ Weight (Kg/N/A) Materials available at the factory | P5: Số lượng/ Q'ty (M/M2/PSC) Materials available at the factory
A6: A | B6: VTC | D6: Vật tư | L6: =SUM(L7:L26) -> 3.9012967e+10 | R6: =IF(L6>Q6," OKE MUA TIẾP","BÁO CÁO BOM") -> OKE MUA TIẾP
A7: 1 | D7: Vật tư chính | E7: kg | R7: =IF(L7>Q7," OKE MUA TIẾP","BÁO CÁO BOM") -> BÁO CÁO BOM
A8: 1.1 | D8: Thép carbon | E8: kg | J8: 1225.166 | L8: 2.6838359e+10 | M8: ='Tổng hợp'!F14 -> 1371496.8 | N8: ='Tổng hợp'!G14 -> 33225.763 | O8: ='Tổng hợp'!H14 -> 11796.06 | P8: ='Tổng hợp'!I14 -> 141.9749 | Q8: ='Tổng hợp'!J14 -> 2.8199693e+10 | R8: =IF(L8>Q8," OKE MUA TIẾP","BÁO CÁO BOM") -> BÁO CÁO BOM
A9: 1.2 | D9: Thép stainless | E9: kg | J9: 241.912
A10: 1.3 | D10: Tấm gratting nhựa | E10: kg | J10: 120 | L10: 537408000
A11: 1.4 | D11: Bảo ôn | J11: 10245.516
A12: 1.5 | D12: Các loại vật tư thép khác (cấp công trường | E12: kg
A13: 1.6 | D13: Bolt các loại, phụ kiện, gioăng,... | E13: kg | L13: 1.703349e+09 | M13: ='Tổng hợp'!F15 -> 174616.5 | N13: ='Tổng hợp'!G15 -> 178599.55 | O13: ='Tổng hợp'!H15 -> 6861.4896 | P13: ='Tổng hợp'!I15 -> 14559.671 | Q13: ='Tổng hợp'!J15 -> 4.9994399e+09 | R13: =IF(L13>Q13," OKE MUA TIẾP","BÁO CÁO BOM") -> BÁO CÁO BOM
A14: 2 | D14: Vật tư sơn
A15: 2.1 | D15: Vật tư sơn các loại. dung môi | J15: 8766.274 | L15: 1.615417e+09 | O15: ='Vật tư sơn BRA090'!AE7 -> 8374.56 | Q15: ='Vật tư sơn BRA090'!AH7 -> 2346421600 | R15: =IF(L15>Q15," OKE MUA TIẾP","BÁO CÁO BOM") -> BÁO CÁO BOM
A17: 3 | D17: Vật tư đóng kiện, biện pháp | E17: kg | L17: =SUM(L18:L20) -> 2538751590 | M17: ='Tổng hợp'!F16 -> 174616.5 | N17: ='Tổng hợp'!G16 -> 48456.55 | O17: ='Tổng hợp'!H16 -> 6861.4896 | P17: ='Tổng hợp'!I16 -> 14559.671 | Q17: ='Tổng hợp'!J16 -> 4.2279793e+09 | R17: =IF(L17>Q17," OKE MUA TIẾP","BÁO CÁO BOM") -> BÁO CÁO BOM
A18: 3.1 | D18: Vật tư biện pháp | L18: 839587140
A19: 3.2 | D19: Vật tư đóng kiện | L19: 3.998034e+08
A20: 3.3 | D20: Bạt che phủ các loại | E20: kg | L20: 1299361050
A21: 4 | D21: Vật tư tiêu hao
A22: 4.1 | D22: Vật liệu hàn | L22: 1652821140 | O22: ='Vat lieu han -BRA090'!AI7 -> 12225 | Q22: ='Vat lieu han -BRA090'!AL7 -> 775765000 | R22: =IF(L22>Q22," OKE MUA TIẾP","BÁO CÁO BOM") -> OKE MUA TIẾP | S22: lấy giữ liệu của kho xuất cho chính xác
A23: 4.2 | D23: Vật tư phụ (hàn), khí công nghiệp | L23: 1.1033447e+09
A24: 4.3 | D24: Đá mài các loại | L24: 1.6345848e+08
A25: 4.4 | D25: Hạt mài | L25: 175325480
A26: 5 | D26: Vật tư khác | L26: 145981218
A27: B | D27: Nhân công trực tiếp | J27: =SUM(J28:J36) -> 21590.066 | L27: =SUM(L28:L36) -> 2.3676403e+10
A28: 1 | D28: Pha cắt | J28: 1362.154 | L28: 1572005500
A29: 2 | D29: Lốc, sấn | J29: 573.388 | L29: 997070000
A30: 3 | D30: Gá hàn hoàn thiện | J30: 1362.154 | L30: 13134527000
A31: 4 | D31: Tổ hợp thử | J31: 1332.678 | L31: 3314816000
A32: 5 | D32: Thử chức năng | J32: 824.062 | L32: 1150986000
A33: 6 | D33: Làm sạch, sơn, rửa axit | J33: 13470.274 | L33: 869150550
A34: 7 | D34: Đóng kiện, giao hàng | J34: 1332.678 | L34: 9.328746e+08
A35: 8 | D35: Vận chuyển | J35: 1332.678 | L35: 1.999017e+08
A36: 9 | D36: Nhân công dự phòng | L36: 1.5050721e+09
A37: C | D37: Thầu phụ, dịch vụ thuê ngoài | L37: =SUM(L38:L45) -> 10721526300
A38: 1 | D38: Kiểm tra NDT, kiểm tra mẫu, quy trình | L38: 732972900
A39: 2 | D39: Mạ kẽm nhúng nóng | J39: 74 | L39: 888000000
A40: 3 | D40: Gia công cơ khí | J40: 602.062 | L40: 2500000000
A41: 4 | D41: Bảo ôn | J41: 10245.516 | L41: 4610482200
A42: 5 | D42: Chi phí thông quan và vận chuyển container hàng hóa KH cấp | L42: 9.75e+08
A43: 6 | D43: Chằng buộc, hun trùng | L43: 200000000
A44: 7 | D44: Chi phí khác và dự phòng | L44: 282000000
A45: 8 | D45: Engineering | L45: 533071200
D46: TỔNG CỘNG (A+B+C+D) | L46: =SUM(L38:L45)+SUM(L28:L36)+SUM(L22:L26)+SUM(L18:L20)+SUM(L8:L16) -> 7.0872145e+10 | Q46: =SUM(Q38:Q45)+SUM(Q28:Q36)+SUM(Q22:Q26)+SUM(Q18:Q20)+SUM(Q8:Q16) -> 3.6321319e+10 | R46: =IF(L46>Q46," OKE MUA TIẾP","BÁO CÁO BOM") -> OKE MUA TIẾP
J48: Ngày…...tháng…...năm 2025
J49: PHỎNG THƯƠNG MẠI

Sheet Vat lieu han -BRA090
A1: THEO DÕI VẬT TƯ DỰ ÁN/ MATERIAL CONTROL LOG | E1: Thời gian nộp bảng cập nhật:
A2: Tên dự án/ Project no.:25-SHI-I-084 | E2: - Trong ngày khi có biến động.
A3: Cập nhật ngày/ Update to: | E3: - Báo cáo hàng tuần vào 16:30 mỗi chiều thứ 2.
A4: Item/ STT | B4: Description/ Chi tiết | C4: Unit/ Đơn vị | D4: Current Ordered/Dự trù lần 1 (Ngà 2/6/2025 ) | F4: Current Ordered/Dự trù lần 2 (Ngày 11/8/2025 ) | H4: Current Ordered/Dự trù lần 3 (Ngày 19/8/2025 | J4: Current Ordered/Dự trù lần 3 (Ngày6/9/2025 | L4: Current Ordered/Dự trù lần 4 (Ngày 25/9/2025 | N4: Current Ordered/Dự trù lần 5 (Ngày 26/9/2025 | P4: Current Ordered/Dự trù lần 6 (Ngày 4/10/2025 | R4: Total Ordered/Tổng dự trù | T4: Remarks/ Ghi chú | U4: Tận dụng tồn kho/ Remain | Z4: Khối lượng phải mua sắm/ total order | AB4: Ngày bàn giao vật tư/ Material avaiable for hand over date | AC4: VẬT TƯ TRONG NƯỚC | AN4: ĐÃ MUA TRONG NƯỚC | AP4: QC Nghiệm thu | AT4: Remarks/ Ghi chú
D5: Q.Ty/ S.Lượng | E5: Weight/ K.Lượng (Kg) | F5: Q.Ty/ S.Lượng | G5: Weight/ K.Lượng (Kg) | H5: Q.Ty/ S.Lượng | I5: Weight/ K.Lượng (Kg) | J5: Q.Ty/ S.Lượng | K5: Weight/ K.Lượng (Kg) | L5: Q.Ty/ S.Lượng | M5: Weight/ K.Lượng (Kg) | N5: Q.Ty/ S.Lượng | O5: Weight/ K.Lượng (Kg) | P5: Q.Ty/ S.Lượng | Q5: Weight/ K.Lượng (Kg) | R5: Q.Ty/ S.Lượng | S5: Weight/ K.Lượng (Kg) | U5: Report No. | V5: Q.Ty/ S.Lượng | W5: Weight/ K.Lượng (Kg) | X5: Ngày nghiệm thu ACC | Y5: Remarks/ Ghi chú | Z5: Q.Ty/ S.Lượng | AA5: Weight/ K.Lượng (Kg) | AC5: Số Hợp đồng / Contract No | AD5: Nhà cung cấp/ Vendor | AE5: Profile/ Vật tư | AF5: Grade/ Mác vật liệu | AG5: Contract weight ( K.Lượng theo HĐ) | AH5: Ngày ký HD/ Contract date | AI5: S.Lượng giao hàng thực tế/ Handover Q'ty | AJ5: K.Lượng giao hàng thực tế// Handover weight | AK5: Đơn giá / Unit Price (Not VAT) | AL5: Tổng tiền (VNĐ) | AM5: Bàn giao sản xuất/ Handover to Product | AN5: Q.Ty/ S.Lượng | AO5: Weight/ K.Lượng (Kg) | AP5: Report No. | AQ5: Inspection date | AR5: Khối lượng nghiệm thu đạt/ Weight Acc. Inspection | AS5: Results
A6: 1 | B6: =A6+1 -> 2 | C6: 2 | D6: =C6+1 -> 3 | E6: 3 | F6: =E6+1 -> 4 | G6: 4 | H6: =G6+1 -> 5 | I6: 5 | J6: =I6+1 -> 6 | K6: 5 | L6: =K6+1 -> 6 | M6: 5 | N6: =M6+1 -> 6 | O6: 5 | P6: =O6+1 -> 6 | Q6: 5 | R6: =I6+1 -> 6 | S6: 6 | T6: =S6+1 -> 7 | U6: 7 | V6: =U6+1 -> 8 | W6: 8 | X6: =W6+1 -> 9 | Y6: 9 | Z6: =Y6+1 -> 10 | AA6: 10 | AB6: =AA6+1 -> 11 | AC6: 11 | AD6: =AC6+1 -> 12 | AE6: 12 | AF6: =AE6+1 -> 13 | AG6: 13 | AH6: =AG6+1 -> 14 | AI6: 14 | AJ6: =AI6+1 -> 15 | AK6: 15 | AL6: =AK6+1 -> 16 | AM6: 16 | AN6: =AM6+1 -> 17 | AO6: 17 | AP6: =AO6+1 -> 18 | AQ6: 18 | AR6: =AQ6+1 -> 19 | AS6: 19 | AT6: 34
A7: A. | B7: Main-Material / Vật tư chính | F7: =SUM(F8:F32) -> 1950 | G7: =SUM(G8:G32) -> 0 | H7: =SUM(H8:H32) -> 200 | I7: =SUM(I8:I32) -> 0 | J7: =SUM(J8:J32) -> 40 | K7: =SUM(K8:K32) -> 0 | L7: =SUM(L8:L32) -> 70 | M7: =SUM(M8:M32) -> 0 | ... S7: =SUM(S8:S32) -> 0 | V7: =SUM(V8:V32) -> 0 | W7: =SUM(W8:W32) -> 0 | Z7: =SUM(Z8:Z32) -> 13855 | AA7: =SUM(AA8:AA32) -> 0 | AC7: =SUM(AC8:AC32) -> 0 | AD7: =SUM(AD8:AD32) -> 0 | AE7: =SUM(AE8:AE32) -> 0 | AF7: =SUM(AF8:AF32) -> 0 | AG7: =SUM(AG8:AG32) -> 30435 | AI7: =SUM(AI8:AI32) -> 12225 | AJ7: =SUM(AJ8:AJ32) -> 0 | AL7: =SUM(AL8:AL32) -> 775765000 | AN7: =SUM(AN8:AN32) -> 11184 | AO7: =SUM(AO8:AO32) -> 15 | AP7: =SUM(AP8:AP32) -> 0 | AQ7: =SUM(AQ8:AQ32) -> 0 | AR7: =SUM(AR8:AR32) -> 0 | AS7: =SUM(AS8:AS32) -> 0 | AT7: =SUM(AT8:AT32) -> 0
A8: 1 | B8: Dây hàn E71T-1C( AWS A5.20) F1~1.2 | C8: kg | D8: 10000 | F8: 1500 | R8: =D8+F8+H8+J8+L8+N8+P8 -> 11500 | S8: =E8+G8 -> 0 | T8: Hyundai/Lincoln | Z8: =IF(R8>V8,R8-V8,"0") -> 11500 | AA8: =IF(S8>W8,S8-W8,"0") -> 0 | AB8: 17/05/2025, 27/5/20525 | AC8: Po/2025-05-16-0001 | AD8: Hai Tốt | AE8: COLC71CE21-1: Dây hàn lõi thuốc / Flux Wire Trade name: Lincoln 71C (AWS A5.20 E71T-1C) Dia: 1.2mm x 15kg/cuộn | AG8: =1065+23760 -> 24825 | AH8: 45793 | AI8: 10000 | AK8: 33000 | AL8: =+AI8*AK8 -> 330000000 | AN8: =SUMIF($A:$A,A8,$AI:$AI) -> 10014 | AO8: =SUMIF($A:$A,A8,$AJ:$AJ) -> 15
A9: 2 | B9: Dây hàn E308LT1-1 (AWS A5.22) F1~1.2 | C9: kg | D9: 100 | F9: 50 | R9: =D9+F9+H9+J9+L9+N9+P9 -> 150 | S9: =E9+G9 -> 0 | Z9: =IF(R9>V9,R9-V9,"0") -> 150 | AA9: =IF(S9>W9,S9-W9,"0") -> 0 | AB9: 45784 | AC9: HĐKT số. 02042025/HĐKT/IBSHI-TMV | AD9: Thương mại Việt | AE9: Dây hàn SW-309L Cored | AG9: 960 | AH9: 45793 | AI9: 500 | AK9: 240000 | AL9: =+AI9*AK9 -> 120000000 | AN9: =SUMIF($A:$A,A9,$AI:$AI) -> 500 | AO9: =SUMIF($A:$A,A9,$AJ:$AJ) -> 0
A10: 3 | B10: Dây hàn E309LT1-1 (AWS A5.22) F1~1.2 | C10: kg | D10: 500 | R10: =D10+F10+H10+J10+L10+N10+P10 -> 500 | S10: =E10+G10 -> 0 | Z10: =IF(R10>V10,R10-V10,"0") -> 500 | AA10: =IF(S10>W10,S10-W10,"0") -> 0 | AB10: 45784 | AC10: HĐKT số. 02042025/HĐKT/IBSHI-TMV | AD10: Thương mại Việt | AE10: Dây hàn SW-308L Cored | AG10: 240 | AH10: 45793 | AI10: 100 | AK10: 200000 | AL10: =+AI10*AK10 -> 20000000 | AN10: =SUMIF($A:$A,A10,$AI:$AI) -> 100 | AO10: =SUMIF($A:$A,A10,$AJ:$AJ) -> 0
A11: 4 | B11: Dây hàn E347T1-1/4 (AWS A5.22) F1~1.2 | C11: kg | D11: 500 | F11: 250 | R11: =D11+F11+H11+J11+L11+N11+P11 -> 750 | S11: =E11+G11 -> 0 | Z11: =IF(R11>V11,R11-V11,"0") -> 750 | AA11: =IF(S11>W11,S11-W11,"0") -> 0 | AB11: 45769 | AC11: HĐKT số. 03042025/HĐKT/IBSHI-NG | AD11: Nguyễn Gia | AG11: 3600 | AH11: 45750 | AI11: 500 | AK11: 260000 | AL11: =+AI11*AK11 -> 130000000 | AN11: =SUMIF($A:$A,A11,$AI:$AI) -> 500 | AO11: =SUMIF($A:$A,A11,$AJ:$AJ) -> 0
A12: 5 | B12: Que hàn Tig ER308L (AWS A5.9) F2~2.4 | C12: kg | D12: 20 | R12: =D12+F12+H12+J12+L12+N12+P12 -> 20 | S12: =E12+G12 -> 0 | Z12: =IF(R12>V12,R12-V12,"0") -> 20 | AA12: =IF(S12>W12,S12-W12,"0") -> 0 | AB12: 45784 | AC12: HĐKT số. 02042025/HĐKT/IBSHI-TMV | AD12: Thương mại Việt | AE12: Que hàn SMT-308L | AG12: 200 | AH12: 45793 | AI12: 20 | AK12: 200000 | AL12: =+AI12*AK12 -> 4000000 | AN12: =SUMIF($A:$A,A12,$AI:$AI) -> 20 | AO12: =SUMIF($A:$A,A12,$AJ:$AJ) -> 0
A13: 6 | B13: Que hàn Tig ER309L (AWS A5.9) F2~2.4 | C13: kg | D13: 50 | R13: =D13+F13+H13+J13+L13+N13+P13 -> 50 | S13: =E13+G13 -> 0 | Z13: =IF(R13>V13,R13-V13,"0") -> 50 | AA13: =IF(S13>W13,S13-W13,"0") -> 0 | AB13: 45784 | AC13: HĐKT số. 02042025/HĐKT/IBSHI-TMV | AD13: Thương mại Việt | AE13: Que hàn SMT-309L | AG13: 150 | AH13: 45793 | AI13: 50 | AK13: 252000 | AL13: =+AI13*AK13 -> 12600000 | AN13: =SUMIF($A:$A,A13,$AI:$AI) -> 50 | AO13: =SUMIF($A:$A,A13,$AJ:$AJ) -> 0
B14: Que hàn E7018A1 (AWS A5.5) F3.2 (Que CM78) | C14: kg | F14: 150 | P14: 110 | R14: =D14+F14+H14+J14+L14+N14+P14 -> 260 | S14: =E14+G14 -> 0 | Z14: =IF(R14>V14,R14-V14,"0") -> 260 | AA14: =IF(S14>W14,S14-W14,"0") -> 0 | AB14: 45912 | AC14: Nguyễn Gia | AD14: Nguyễn Gia | AE14: Que hàn T-347 2.4mm | AG14: 260 | AH14: 45894 | AI14: =60+200 -> 260 | AK14: 280000 | AL14: =+AI14*AK14 -> 72800000 | AN14: =SUMIF($A:$A,A14,$AI:$AI) -> 0 | AO14: =SUMIF($A:$A,A14,$AJ:$AJ) -> 0
B15: Que hàn KT421 (J), D3.2 | H15: 200 | R15: =D15+F15+H15+J15+L15+N15+P15 -> 200 | S15: =E15+G15 -> 0 | Z15: =IF(R15>V15,R15-V15,"0") -> 200 | AA15: =IF(S15>W15,S15-W15,"0") -> 0 | AB15: 45890 | AC15: Nguyễn Gia | AD15: Nguyễn Gia | AE15: Que hàn J-421 3.2mm | AG15: 200 | AH15: 45894 | AI15: 200 | AK15: 26000 | AL15: =+AI15*AK15 -> 5200000 | AN15: =SUMIF($A:$A,A15,$AI:$AI) -> 0 | AO15: =SUMIF($A:$A,A15,$AJ:$AJ) -> 0
B16: Que hàn Tig Inox Kiswwel T-347T ER (AWS A5.9) F2-2.4 | J16: 40 | R16: =D16+F16+H16+J16+L16+N16+P16 -> 40 | S16: =E16+G16 -> 0 | Z16: =IF(R16>V16,R16-V16,"0") -> 40 | AA16: =IF(S16>W16,S16-W16,"0") -> 0 | AB16: Về ngày 21/8/2025 và 12/9/2025 | AC16: Nguyễn Gia | AI16: 40 | AK16: 280000 | AL16: =+AI16*AK16 -> 11200000 | AN16: =SUMIF($A:$A,A16,$AI:$AI) -> 0 | AO16: =SUMIF($A:$A,A16,$AJ:$AJ) -> 0
B17: Que CM78 (chưa có PR) | R17: =D17+F17+H17+J17+L17+N17+P17 -> 0 | S17: =E17+G17 -> 0 | Z17: =IF(R17>V17,R17-V17,"0") -> 0 | AA17: =IF(S17>W17,S17-W17,"0") -> 0 | AB17: Về ngày 12/9/2025 | AC17: Nguyễn Gia | AI17: 200 | AK17: 135000 | AL17: =+AI17*AK17 -> 27000000 | AN17: =SUMIF($A:$A,A17,$AI:$AI) -> 0 | AO17: =SUMIF($A:$A,A17,$AJ:$AJ) -> 0
B18: Dây hàn lõi thuôc SC81B2 F1.2mm (chưa có PR) | N18: 315 | R18: =D18+F18+H18+J18+L18+N18+P18 -> 315 | S18: =E18+G18 -> 0 | Z18: =IF(R18>V18,R18-V18,"0") -> 315 | AA18: =IF(S18>W18,S18-W18,"0") -> 0 | AB18: Về ngày 20/9/2025 và 22/9/2025 | AC18: Thương Mại Việt | AI18: =105+210 -> 315 | AK18: 125000 | AL18: =+AI18*AK18 -> 39375000 | AN18: =SUMIF($A:$A,A18,$AI:$AI) -> 0 | AO18: =SUMIF($A:$A,A18,$AJ:$AJ) -> 0
B19: Dây hàn Mig SM -80G F1.2mm | C19: Hyundai | L19: 30 | R19: =D19+F19+H19+J19+L19+N19+P19 -> 30 | S19: =E19+G19 -> 0 | Z19: =IF(R19>V19,R19-V19,"0") -> 30 | AA19: =IF(S19>W19,S19-W19,"0") -> 0 | AB19: Về ngày 20/9/2025 | AC19: Thương Mại Việt | AI19: 30 | AK19: 78000 | AL19: =+AI19*AK19 -> 2340000 | AN19: =SUMIF($A:$A,A19,$AI:$AI) -> 0 | AO19: =SUMIF($A:$A,A19,$AJ:$AJ) -> 0
B20: Que hàn Tig T-80SB2 F2.4mm | C20: Hyundai | L20: 40 | R20: =D20+F20+H20+J20+L20+N20+P20 -> 40 | S20: =E20+G20 -> 0 | Z20: =IF(R20>V20,R20-V20,"0") -> 40 | AA20: =IF(S20>W20,S20-W20,"0") -> 0 | AB20: Về ngày 20/9/2025 | AC20: Thương Mại Việt | AI20: 10 | AK20: 125000 | AL20: =+AI20*AK20 -> 1250000 | AN20: =SUMIF($A:$A,A20,$AI:$AI) -> 0 | AO20: =SUMIF($A:$A,A20,$AJ:$AJ) -> 0
R21: =D21+F21+H21+J21+L21+N21+P21 -> 0 | S21: =E21+G21 -> 0 | Z21: =IF(R21>V21,R21-V21,"0") -> 0 | AA21: =IF(S21>W21,S21-W21,"0") -> 0 | AN21: =SUMIF($A:$A,A21,$AI:$AI) -> 0 | AO21: =SUMIF($A:$A,A21,$AJ:$AJ) -> 0
R22: =D22+F22+H22+J22+L22+N22+P22 -> 0 | S22: =E22+G22 -> 0 | Z22: =IF(R22>V22,R22-V22,"0") -> 0 | AA22: =IF(S22>W22,S22-W22,"0") -> 0 | AN22: =SUMIF($A:$A,A22,$AI:$AI) -> 0 | AO22: =SUMIF($A:$A,A22,$AJ:$AJ) -> 0
R23: =D23+F23+H23+J23+L23 -> 0 | S23: =E23+G23 -> 0 | Z23: =IF(R23>V23,R23-V23,"0") -> 0 | AA23: =IF(S23>W23,S23-W23,"0") -> 0 | AN23: =SUMIF($A:$A,A23,$AI:$AI) -> 0 | AO23: =SUMIF($A:$A,A23,$AJ:$AJ) -> 0
R24: =D24+F24+H24+J24+L24 -> 0 | S24: =E24+G24 -> 0 | Z24: =IF(R24>V24,R24-V24,"0") -> 0 | AA24: =IF(S24>W24,S24-W24,"0") -> 0 | AN24: =SUMIF($A:$A,A24,$AI:$AI) -> 0 | AO24: =SUMIF($A:$A,A24,$AJ:$AJ) -> 0
R25: =D25+F25+H25+J25+L25 -> 0 | S25: =E25+G25 -> 0 | Z25: =IF(R25>V25,R25-V25,"0") -> 0 | AA25: =IF(S25>W25,S25-W25,"0") -> 0 | AN25: =SUMIF($A:$A,A25,$AI:$AI) -> 0 | AO25: =SUMIF($A:$A,A25,$AJ:$AJ) -> 0
R26: =D26+F26+H26+J26+L26 -> 0 | S26: =E26+G26 -> 0 | Z26: =IF(R26>V26,R26-V26,"0") -> 0 | AA26: =IF(S26>W26,S26-W26,"0") -> 0 | AN26: =SUMIF($A:$A,A26,$AI:$AI) -> 0 | AO26: =SUMIF($A:$A,A26,$AJ:$AJ) -> 0
R27: =D27+F27+H27+J27+L27 -> 0 | S27: =E27+G27 -> 0 | Z27: =IF(R27>V27,R27-V27,"0") -> 0 | AA27: =IF(S27>W27,S27-W27,"0") -> 0 | AN27: =SUMIF($A:$A,A27,$AI:$AI) -> 0 | AO27: =SUMIF($A:$A,A27,$AJ:$AJ) -> 0
R28: =D28+F28+H28+J28+L28 -> 0 | S28: =E28+G28 -> 0 | Z28: =IF(R28>V28,R28-V28,"0") -> 0 | AA28: =IF(S28>W28,S28-W28,"0") -> 0 | AN28: =SUMIF($A:$A,A28,$AI:$AI) -> 0 | AO28: =SUMIF($A:$A,A28,$AJ:$AJ) -> 0
R29: =D29+F29+H29+J29+L29 -> 0 | S29: =E29+G29 -> 0 | Z29: =IF(R29>V29,R29-V29,"0") -> 0 | AA29: =IF(S29>W29,S29-W29,"0") -> 0 | AN29: =SUMIF($A:$A,A29,$AI:$AI) -> 0 | AO29: =SUMIF($A:$A,A29,$AJ:$AJ) -> 0
R30: =D30+F30+H30+J30+L30 -> 0 | S30: =E30+G30 -> 0 | Z30: =IF(R30>V30,R30-V30,"0") -> 0 | AA30: =IF(S30>W30,S30-W30,"0") -> 0 | AN30: =SUMIF($A:$A,A30,$AI:$AI) -> 0 | AO30: =SUMIF($A:$A,A30,$AJ:$AJ) -> 0
R31: =D31+F31+H31+J31+L31 -> 0 | S31: =E31+G31 -> 0 | Z31: =IF(R31>V31,R31-V31,"0") -> 0 | AA31: =IF(S31>W31,S31-W31,"0") -> 0 | AN31: =SUMIF($A:$A,A31,$AI:$AI) -> 0 | AO31: =SUMIF($A:$A,A31,$AJ:$AJ) -> 0
R32: =D32+F32+H32+J32+L32 -> 0 | S32: =E32+G32 -> 0 | Z32: =IF(R32>V32,R32-V32,"0") -> 0 | AA32: =IF(S32>W32,S32-W32,"0") -> 0 | AN32: =SUMIF($A:$A,A32,$AI:$AI) -> 0 | AO32: =SUMIF($A:$A,A32,$AJ:$AJ) -> 0

Sheet Vật tư sơn BRA090
A1: THEO DÕI VẬT TƯ DỰ ÁN/ MATERIAL CONTROL LOG | E1: Thời gian nộp bảng cập nhật:
A2: Tên dự án/ Project no.:25-SHI-I-084 | E2: - Trong ngày khi có biến động.
A3: Cập nhật ngày/ Update to: | E3: - Báo cáo hàng tuần vào 16:30 mỗi chiều thứ 2.
A4: Item/ STT | B4: Description/ Chi tiết | C4: Unit/ Đơn vị | D4: Current Ordered/Dự trù lần 1 (Ngày29/7/2025) | F4: Current Ordered/Dự trù lần 2 (Ngày 16/8/2025 | H4: Current Ordered/Dự trù lần 3 (Ngày 8/11/2025) | J4: Current Ordered/Dự trù nagyf 15/11/2025 | L4: Current Ordered/Dự trù lần 4 (Ngày 10/12/2025) | N4: Total Ordered/Tổng dự trù | P4: Remarks/ Ghi chú | Q4: Tận dụng tồn kho/ Remain | V4: Khối lượng phải mua sắm/ total order | X4: Ngày bàn giao vật tư/ Material avaiable for hand over date | Y4: VẬT TƯ TRONG NƯỚC | AJ4: ĐÃ MUA TRONG NƯỚC | AL4: QC Nghiệm thu | AP4: Remarks/ Ghi chú
D5: Q.Ty/ S.Lượng | E5: Weight/ K.Lượng (Kg) | F5: Q.Ty/ S.Lượng | G5: Weight/ K.Lượng (Kg) | H5: Q.Ty/ S.Lượng | I5: Weight/ K.Lượng (Kg) | J5: Q.Ty/ S.Lượng | K5: Weight/ K.Lượng (Kg) | L5: Q.Ty/ S.Lượng | M5: Weight/ K.Lượng (Kg) | N5: Q.Ty/ S.Lượng | O5: Weight/ K.Lượng (Kg) | Q5: Report No. | R5: Q.Ty/ S.Lượng | S5: Weight/ K.Lượng (Kg) | T5: Ngày nghiệm thu ACC | U5: Remarks/ Ghi chú | V5: Q.Ty/ S.Lượng | W5: Weight/ K.Lượng (Kg) | Y5: Số Hợp đồng / Contract No | Z5: Nhà cung cấp/ Vendor | AA5: Profile/ Vật tư | AB5: Grade/ Mác vật liệu | AC5: Contract weight ( K.Lượng theo HĐ) | AD5: Ngày ký HD/ Contract date | AE5: S.Lượng giao hàng thực tế/ Handover Q'ty | AF5: K.Lượng giao hàng thực tế// Handover weight | AG5: Đơn giá / Unit Price (Not VAT) | AH5: Tổng tiền (VNĐ) | AI5: Bàn giao sản xuất/ Handover to Product | AJ5: Q.Ty/ S.Lượng | AK5: Weight/ K.Lượng (Kg) | AL5: Report No. | AM5: Inspection date | AN5: Khối lượng nghiệm thu đạt/ Weight Acc. Inspection | AO5: Results
A6: 1 | B6: =A6+1 -> 2 | C6: 2 | D6: =C6+1 -> 3 | E6: 3 | F6: =E6+1 -> 4 | G6: 4 | H6: =G6+1 -> 5 | I6: 5 | J6: =G6+1 -> 5 | K6: 5 | L6: =I6+1 -> 6 | M6: 5 | N6: =I6+1 -> 6 | O6: 6 | P6: =O6+1 -> 7 | Q6: 7 | R6: =Q6+1 -> 8 | S6: 8 | T6: =S6+1 -> 9 | U6: 9 | V6: =U6+1 -> 10 | W6: 10 | X6: =W6+1 -> 11 | Y6: 11 | Z6: =Y6+1 -> 12 | AA6: 12 | AB6: =AA6+1 -> 13 | AC6: 13 | AD6: =AC6+1 -> 14 | AE6: 14 | AF6: =AE6+1 -> 15 | AG6: 15 | AH6: =AG6+1 -> 16 | AI6: 16 | AJ6: =AI6+1 -> 17 | AK6: 17 | AL6: =AK6+1 -> 18 | AM6: 18 | AN6: =AM6+1 -> 19 | AO6: 19 | AP6: 34
A7: A. | B7: Main-Material / Vật tư chính | F7: =SUM(F8:F33) -> 1315 | G7: =SUM(G8:G33) -> 0 | H7: =SUM(H8:H33) -> 492 | I7: =SUM(I8:I33) -> 0 | J7: =SUM(J8:J33) -> 1000 | K7: =SUM(K8:K33) -> 0 | L7: =SUM(L8:L33) -> 1490 | M7: =SUM(M8:M33) -> 0 | ... O7: =SUM(O8:O33) -> 0 | R7: =SUM(R8:R33) -> 0 | S7: =SUM(S8:S33) -> 0 | V7: =SUM(V8:V33) -> 11522 | W7: =SUM(W8:W33) -> 0 | Y7: =SUM(Y8:Y33) -> 0 | Z7: =SUM(Z8:Z33) -> 0 | AA7: =SUM(AA8:AA33) -> 0 | AB7: =SUM(AB8:AB33) -> 0 | AC7: =SUM(AC8:AC33) -> 8789.06 | AE7: =SUM(AE8:AE33) -> 8374.56 | AF7: =SUM(AF8:AF33) -> 0 | AH7: =SUM(AH8:AH33) -> 2346421600 | AJ7: =SUM(AJ8:AJ33) -> 4881.48 | AK7: =SUM(AK8:AK33) -> 15 | AL7: =SUM(AL8:AL33) -> 0 | AM7: =SUM(AM8:AM33) -> 0 | AN7: =SUM(AN8:AN33) -> 0 | AO7: =SUM(AO8:AO33) -> 0 | AP7: =SUM(AP8:AP33) -> 0
A8: 1 | B8: RESIST 86,GREY | C8: Lít | D8: 1965 | H8: 130 | L8: 540 | N8: =+D8+F8+H8+L8+J8 -> 2635 | O8: =E8+G8 -> 0 | V8: =IF(N8>R8,N8-R8,"0") -> 2635 | W8: =IF(O8>S8,O8-S8,"0") -> 0 | X8: 26/08/2025 và 20/9/2025 và 3/10/2025 và 31/10/2025 và 8/11/2025 và 22/11/2025 và 22/11/2025 | Y8: A241/IBS HI-PHUCCHAU | Z8: Phúc Châu | AC8: 1971.6 | AD8: 45888 | AE8: =208+67.6+74.2+455.8+275.6+95.4+795 -> 1971.6 | AG8: 325000 | AH8: =+AG8*AE8 -> 640770000 | AJ8: =SUMIF($A:$A,A8,$AE:$AE) -> 1985.6 | AK8: =SUMIF($A:$A,A8,$AF:$AF) -> 15
A9: 2 | B9: Thinner No. 25 | C9: Lít | D9: 240 | H9: 15 | L9: 60 | N9: =+D9+F9+H9+L9+J9 -> 315 | O9: =E9+G9 -> 0 | V9: =IF(N9>R9,N9-R9,"0") -> 315 | W9: =IF(O9>S9,O9-S9,"0") -> 0 | X9: 26/08/2025 và 20/9/2025 và 3/10/2025 và 31/10/2025 | Y9: A241/IBS HI-PHUCCHAU | Z9: Phúc Châu | AC9: 240 | AD9: 45888 | AE9: =40+120+80 -> 240 | AG9: 67000 | AH9: =+AG9*AE9 -> 16080000 | AJ9: =SUMIF($A:$A,A9,$AE:$AE) -> 240 | AK9: =SUMIF($A:$A,A9,$AF:$AF) -> 0
A10: 3 | B10: Solvalitt,GREY (Ral 7035) | C10: Lít | D10: 2040 | H10: 135 | L10: 890 | N10: =+D10+F10+H10+L10+J10 -> 3065 | O10: =E10+G10 -> 0 | V10: =IF(N10>R10,N10-R10,"0") -> 3065 | W10: =IF(O10>S10,O10-S10,"0") -> 0 | X10: 26/08/2025 và 20/9/2025 và 25/10/2025 và 8/11/2025 và 22/11/2025 | Y10: A241/IBS HI-PHUCCHAU | Z10: Phúc Châu | AC10: 2043.04 | AD10: 45888 | AE10: =135.6+180.8+230.52+244.08+528.84+723.2 -> 2043.04 | AG10: 440000 | AH10: =+AG10*AE10 -> 8.989376e+08 | AJ10: =SUMIF($A:$A,A10,$AE:$AE) -> 2043.04 | AK10: =SUMIF($A:$A,A10,$AF:$AF) -> 0
A11: 4 | B11: Thinner No. 10 | C11: Lít | D11: 310 | F11: 70 | N11: =+D11+F11+H11+L11+J11 -> 380 | O11: =E11+G11 -> 0 | V11: =IF(N11>R11,N11-R11,"0") -> 380 | W11: =IF(O11>S11,O11-S11,"0") -> 0 | X11: 26/08/2025 và 3/9/2025 và 25/10/2025 (Thinner 7) | Y11: A241/IBS HI-PHUCCHAU | Z11: Phúc Châu | AC11: 380 | AD11: 45888 | AE11: =40+200+140 -> 380 | AG11: 60000 | AH11: =+AG11*AE11 -> 22800000 | AJ11: =SUMIF($A:$A,A11,$AE:$AE) -> 380 | AK11: =SUMIF($A:$A,A11,$AF:$AF) -> 0
A12: 5 | B12: MukiZ Series | C12: Lít | D12: 20 | N12: =+D12+F12+H12+L12+J12 -> 20 | O12: =E12+G12 -> 0 | V12: =IF(N12>R12,N12-R12,"0") -> 20 | W12: =IF(O12>S12,O12-S12,"0") -> 0 | X12: 45895 | Y12: A241/IBS HI-PHUCCHAU | Z12: Phúc Châu | AC12: 16.75 | AD12: 45888 | AE12: 16.75 | AG12: 170000 | AH12: =+AG12*AE12 -> 2847500 | AJ12: =SUMIF($A:$A,A12,$AE:$AE) -> 16.75 | AK12: =SUMIF($A:$A,A12,$AF:$AF) -> 0
A13: 6 | B13: Barrier80 | C13: Lít | D13: 545 | N13: =+D13+F13+H13+L13+J13 -> 545 | O13: =E13+G13 -> 0 | V13: =IF(N13>R13,N13-R13,"0") -> 545 | W13: =IF(O13>S13,O13-S13,"0") -> 0 | X13: 26/08/2025 và 3/9/2025 | Y13: A241/IBS HI-PHUCCHAU | Z13: Phúc Châu | AC13: 549 | AD13: 45888 | AE13: =40.5+121.5+387 -> 549 | AG13: 360000 | AH13: =+AG13*AE13 -> 197640000 | AJ13: =SUMIF($A:$A,A20,$AE:$AE) -> 6.5 | AK13: =SUMIF($A:$A,A20,$AF:$AF) -> 0
A14: 7 | B14: Thinner No. 17 | C14: Lít | D14: 165 | F14: 65 | N14: =+D14+F14+H14+L14+J14 -> 230 | O14: =E14+G14 -> 0 | V14: =IF(N14>R14,N14-R14,"0") -> 230 | W14: =IF(O14>S14,O14-S14,"0") -> 0 | X14: 26/08/2025 và 3/9/2025 và 11/11/2025 | Y14: A241/IBS HI-PHUCCHAU | Z14: Phúc Châu | AC14: 230 | AD14: 45888 | AE14: =60+160+10 -> 230 | AG14: 60000 | AH14: =+AG14*AE14 -> 13800000 | AJ14: =SUMIF($A:$A,A21,$AE:$AE) -> 209.59 | AK14: =SUMIF($A:$A,A21,$AF:$AF) -> 0
A15: 8 | B15: Penguard Express | C15: Lít | D15: 820 | N15: =+D15+F15+H15+L15+J15 -> 820 | O15: =E15+G15 -> 0 | V15: =IF(N15>R15,N15-R15,"0") -> 820 | W15: =IF(O15>S15,O15-S15,"0") -> 0 | X15: 26/08/2025 và 3/9/2025 | Y15: A241/IBS HI-PHUCCHAU | Z15: Phúc Châu | AC15: 820 | AD15: 45888 | AE15: =40+160+620 -> 820 | AG15: 125000 | AH15: =+AG15*AE15 -> 102500000 | AJ15: =SUMIF($A:$A,A22,$AE:$AE) -> 0 | AK15: =SUMIF($A:$A,A22,$AF:$AF) -> 0
A16: 9 | B16: HardtopXP,Grey (Ral 7035) | C16: Lít | D16: 530 | F16: 635 | N16: =+D16+F16+H16+L16+J16 -> 1165 | O16: =E16+G16 -> 0 | V16: =IF(N16>R16,N16-R16,"0") -> 1165 | W16: =IF(O16>S16,O16-S16,"0") -> 0 | X16: 26/08/2025 và 20/9/2025 | Y16: A241/IBS HI-PHUCCHAU | Z16: Phúc Châu | AC16: 1180 | AD16: 45888 | AE16: =145.6+14.4+600 -> 760 | AG16: 220000 | AH16: =+AG16*AE16 -> 167200000 | AJ16: =SUMIF($A:$A,A23,$AE:$AE) -> 0 | AK16: =SUMIF($A:$A,A23,$AF:$AF) -> 0
A17: 10 | B17: Penguard Primer | C17: Lít | F17: 540 | N17: =+D17+F17+H17+L17+J17 -> 540 | V17: =IF(N17>R17,N17-R17,"0") -> 540 | X17: 45903 | Y17: A241/IBS HI-PHUCCHAU | Z17: Phúc Châu | AC17: 540 | AD17: 45888 | AE17: 540 | AG17: 125000 | AH17: =+AG17*AE17 -> 67500000
A18: 11 | B18: Sơn Vàng không chì | C18: Lít | D18: 510 | N18: =+D18+F18+H18+L18+J18 -> 510 | O18: =E18+G18 -> 0 | V18: =IF(N18>R18,N18-R18,"0") -> 510 | W18: =IF(O18>S18,O18-S18,"0") -> 0 | X18: 26/08/2025 và 3/10/2025 và 11/11/2025 | Y18: A241/IBS HI-PHUCCHAU | Z18: Phúc Châu | AC18: 528.08 | AD18: 45888 | AE18: =150.88+282.9+94.3 -> 528.08 | AG18: 170000 | AH18: =+AG18*AE18 -> 89773600 | AJ18: =SUMIF($A:$A,A24,$AE:$AE) -> 0 | AK18: =SUMIF($A:$A,A24,$AF:$AF) -> 0
A19: 12 | B19: Dung môi | C19: Lít | D19: 80 | N19: =+D19+F19+H19+L19+J19 -> 80 | O19: =E19+G19 -> 0 | V19: =IF(N19>R19,N19-R19,"0") -> 80 | W19: =IF(O19>S19,O19-S19,"0") -> 0 | X19: 26/8/2025 và 03/09/2025 | Y19: A241/IBS HI-PHUCCHAU | Z19: Phúc Châu | AC19: 80 | AD19: 45888 | AE19: =40+40 -> 80 | AG19: 55000 | AH19: =+AG19*AE19 -> 4400000 | AJ19: =SUMIF($A:$A,A25,$AE:$AE) -> 0 | AK19: =SUMIF($A:$A,A25,$AF:$AF) -> 0
A20: 13 | B20: Hạt mài Garnet (Chưa có PR) | C20: tấn | F20: 5 | H20: 2 | N20: =+D20+F20+H20+L20+J20 -> 7 | O20: =E20+G20 -> 0 | V20: =IF(N20>R20,N20-R20,"0") -> 7 | W20: =IF(O20>S20,O20-S20,"0") -> 0 | X20: 45913 | Z20: Nguyên Hanh | AC20: 1 | AD20: 45915 | AE20: =1+3.5+2 -> 6.5 | AG20: 8800000 | AH20: =+AG20*AE20 -> 57200000 | AJ20: =SUMIF($A:$A,A26,$AE:$AE) -> 0 | AK20: =SUMIF($A:$A,A26,$AF:$AF) -> 0
A21: 14 | B21: HardtopXP, (Ral 1018) | H21: 210 | N21: =+D21+F21+H21+L21+J21 -> 210 | O21: =E21+G21 -> 0 | V21: =IF(N21>R21,N21-R21,"0") -> 210 | W21: =IF(O21>S21,O21-S21,"0") -> 0 | X21: 45976 | Y21: A241/IBS HI-PHUCCHAU - Phụ lục 2 | Z21: Phúc Châu | AC21: 209.59 | AD21: 45915 | AE21: 209.59 | AG21: 310000 | AH21: =+AG21*AE21 -> 64972900 | AJ21: =SUMIF($A:$A,A27,$AE:$AE) -> 0 | AK21: =SUMIF($A:$A,A27,$AF:$AF) -> 0
B22: Vpcl 385 | J22: 1000 | N22: =+D22+F22+H22+L22+J22 -> 1000 | O22: =E22+G22 -> 0 | V22: =IF(N22>R22,N22-R22,"0") -> 1000 | W22: =IF(O22>S22,O22-S22,"0") -> 0 | AJ22: =SUMIF($A:$A,A28,$AE:$AE) -> 0 | AK22: =SUMIF($A:$A,A28,$AF:$AF) -> 0
N23: =+D23+F23+H23+L23 -> 0 | O23: =E23+G23 -> 0 | V23: =IF(N23>R23,N23-R23,"0") -> 0 | W23: =IF(O23>S23,O23-S23,"0") -> 0 | AJ23: =SUMIF($A:$A,A29,$AE:$AE) -> 0 | AK23: =SUMIF($A:$A,A29,$AF:$AF) -> 0
N24: =+D24+F24+H24+L24 -> 0 | O24: =E24+G24 -> 0 | V24: =IF(N24>R24,N24-R24,"0") -> 0 | W24: =IF(O24>S24,O24-S24,"0") -> 0 | AJ24: =SUMIF($A:$A,A30,$AE:$AE) -> 0 | AK24: =SUMIF($A:$A,A30,$AF:$AF) -> 0
N25: =+D25+F25+H25+L25 -> 0 | O25: =E25+G25 -> 0 | V25: =IF(N25>R25,N25-R25,"0") -> 0 | W25: =IF(O25>S25,O25-S25,"0") -> 0 | AJ25: =SUMIF($A:$A,A31,$AE:$AE) -> 0 | AK25: =SUMIF($A:$A,A31,$AF:$AF) -> 0
N26: =+D26+F26+H26+L26 -> 0 | O26: =E26+G26 -> 0 | V26: =IF(N26>R26,N26-R26,"0") -> 0 | W26: =IF(O26>S26,O26-S26,"0") -> 0 | AJ26: =SUMIF($A:$A,A32,$AE:$AE) -> 0 | AK26: =SUMIF($A:$A,A32,$AF:$AF) -> 0
N27: =+D27+F27+H27+L27 -> 0 | O27: =E27+G27 -> 0 | V27: =IF(N27>R27,N27-R27,"0") -> 0 | W27: =IF(O27>S27,O27-S27,"0") -> 0 | AJ27: =SUMIF($A:$A,A33,$AE:$AE) -> 0 | AK27: =SUMIF($A:$A,A33,$AF:$AF) -> 0
N28: =+D28+F28+H28+L28 -> 0 | O28: =E28+G28 -> 0 | V28: =IF(N28>R28,N28-R28,"0") -> 0 | W28: =IF(O28>S28,O28-S28,"0") -> 0 | AJ28: =SUMIF($A:$A,A34,$AE:$AE) -> 0 | AK28: =SUMIF($A:$A,A34,$AF:$AF) -> 0
N29: =+D29+F29+H29+L29 -> 0 | O29: =E29+G29 -> 0 | V29: =IF(N29>R29,N29-R29,"0") -> 0 | W29: =IF(O29>S29,O29-S29,"0") -> 0 | AJ29: =SUMIF($A:$A,A35,$AE:$AE) -> 0 | AK29: =SUMIF($A:$A,A35,$AF:$AF) -> 0
N30: =+D30+F30+H30+L30 -> 0 | O30: =E30+G30 -> 0 | V30: =IF(N30>R30,N30-R30,"0") -> 0 | W30: =IF(O30>S30,O30-S30,"0") -> 0 | AJ30: =SUMIF($A:$A,A36,$AE:$AE) -> 0 | AK30: =SUMIF($A:$A,A36,$AF:$AF) -> 0
N31: =+D31+F31+H31+L31 -> 0 | O31: =E31+G31 -> 0 | V31: =IF(N31>R31,N31-R31,"0") -> 0 | W31: =IF(O31>S31,O31-S31,"0") -> 0 | AJ31: =SUMIF($A:$A,A37,$AE:$AE) -> 0 | AK31: =SUMIF($A:$A,A37,$AF:$AF) -> 0
N32: =D32+F32 -> 0 | O32: =E32+G32 -> 0 | V32: =IF(N32>R32,N32-R32,"0") -> 0 | W32: =IF(O32>S32,O32-S32,"0") -> 0 | AJ32: =SUMIF($A:$A,A38,$AE:$AE) -> 0 | AK32: =SUMIF($A:$A,A38,$AF:$AF) -> 0
N33: =D33+F33 -> 0 | O33: =E33+G33 -> 0 | V33: =IF(N33>R33,N33-R33,"0") -> 0 | W33: =IF(O33>S33,O33-S33,"0") -> 0 | AJ33: =SUMIF($A:$A,A39,$AE:$AE) -> 0 | AK33: =SUMIF($A:$A,A39,$AF:$AF) -> 0

Sheet 25-BRA-I-090
I1: THEO DÕI VẬT TƯ DỰ ÁN/ MATERIAL CONTROL LOG | N1: Hướng dẫn cập nhật thông tin: | R1: Thời gian nộp bảng cập nhật: | FE1: DỰ TOÁN
I2: Tên dự án/ Project no.:25-BRA-I-090 | N2: - Chữ tô màu xanh: | P2: Chưa cập nhật | R2: - Trong ngày khi có biến động.
I3: Cập nhật ngày/ Update to: | K3: =TODAY() -> 46108 | N3: - Chữ tô màu đỏ: | P3: Đã cập nhật mới | R3: - Báo cáo hàng tuần vào 16:30 mỗi chiều thứ 2.
B4: Đánh giá (Thiếu/ Đủ/ Thừa) | G4: Xin chuyển đổi | I4: Item/ STT | J4: Description/ Chi tiết | K4: Profile/ Vật tư | L4: Grade/ Mác vật liệu | M4: Unit/ Đơn vị | N4: U.Weight/ Đ.Trọng (Kg/m2,m,pcs) | O4: Net Quantity/Số lượng tinh | Q4: Current Ordered/Dự trù lần 1 (Ngày 24/4/2025) | S4: Current Ordered/Dự trù lần 2 (Ngày 5/5/2025) | U4: Current Ordered/Dự trù lần 3 (Ngày 14/5/2025) | W4: Current Ordered/Dự trù lần 4 (Ngày 25/5/2025) | Y4: Current Ordered/Dự trù lần 4 (Ngày 2/6/2025) | AA4: Current Ordered/Dự trù lần 5 (Ngày 13/6/2025) | AC4: Current Ordered/Dự trù lần 6 (Ngày 21/6/2025) | AE4: Current Ordered/Dự trù lần 7 (Ngày 12/7/2025) | AG4: Current Ordered/Dự trù lần 8 (Ngày 29/7/2025) | AI4: Current Ordered/Dự trù lần 9 (Ngày 2/8/2025) | AK4: Current Ordered/Dự trù lần 10 (Ngày 13/8/2025) | AM4: Current Ordered/Dự trù lần 11 (Ngày 16/8/2025) | AO4: Current Ordered/Dự trù lần 12 (Ngày 22/8/2025) | AQ4: Current Ordered/Dự trù lần 13 (Ngày 23/8/2025) | AS4: Current Ordered/Dự trù lần 14 (Ngày 28/8/2025) | AU4: Current Ordered/Dự trù lần 15 (Ngày 04/9/2025) | AW4: Current Ordered/Dự trù lần 16 (Ngày 06/9/2025) | AY4: Current Ordered/Dự trù lần 17 (Ngày 12/9/2025) | BA4: Current Ordered/Dự trù lần 18 (Ngày 13/9/2025) | BC4: Current Ordered/Dự trù lần 19 (Ngày 02/10/2025) | BE4: Current Ordered/Dự trù lần 20 (Ngày 04/10/2025) | BG4: Current Ordered/Dự trù lần 21 (Ngày 10/10/2025) | BI4: Current Ordered/Dự trù lần 22 (Ngày 16/10/2025) | BK4: Current Ordered/Dự trù lần 23 (Ngày 20/10/2025) | BM4: Current Ordered/Dự trù lần 24 (Ngày 23/10/2025) | BO4: Current Ordered/Dự trù lần 25 (Ngày 29/10/2025) | BQ4: Current Ordered/Dự trù lần 26 (Ngày 4/11/2025) | BS4: Current Ordered/Dự trù lần 27 (Ngày 9/11/2025) | BU4: Current Ordered/Dự trù lần 28 (Ngày 20/11/2025) | BW4: Current Ordered/Dự trù lần 29 (Ngày 25/11/2025) | BY4: Current Ordered/Dự trù lần 30 (Ngày 26/11/2025) | CA4: Current Ordered/Dự trù lần 31 (Ngày 04/12/2025) | CC4: Current Ordered/Dự trù lần 32 (Ngày 05/12/2025) | CE4: Current Ordered/Dự trù lần 33 (Ngày 12/12/2025) | CG4: Current Ordered/Dự trù lần 34 (Ngày 17/12/2025) | CI4: Current Ordered/Dự trù lần 35 (Ngày 17/12/2025) | CK4: Current Ordered/Dự trù lần 36 (Ngày 24/12/2025) | CM4: Current Ordered/Dự trù lần 37 (Ngày 30/1/2026) | CO4: Current Ordered/Dự trù lần 38 (Ngày 25/2/2026) | CQ4: Current Ordered/Dự trù lần 39 (Ngày 5/3/2026) | CS4: Current Ordered/Dự trù lần 40 (Ngày10/3/2026) | CU4: Current Ordered/Dự trù lần 41 (Ngày17/3/2026) | CW4: Total Ordered/Tổng dự trù | CY4: Remarks/ Ghi chú | CZ4: Tận dụng tồn kho/ Remain | DE4: Khối lượng phải mua sắm/ total order | DG4: Ngày bàn giao vật tư/ Material avaiable for hand over date | DH4: VẬT TƯ TRONG NƯỚC | DU4: ĐÃ MUA TRONG NƯỚC | DW4: QC Nghiệm thu | EA4: Mua sắm nước ngoài/ Oversea purchase | ES4: ĐÃ MUA NHẬP KHẨU | EU4: Nghiệm thu | EY4: TỔNG ĐÃ MUA TRONG VÀ NGOÀI NƯỚC | FA4: So sánh với số lượng vật tư PR | FD4: Remarks/ Ghi chú
O5: Q.Ty/ S.Lượng | P5: Weight/ K.Lượng (Kg) | Q5: Q.Ty/ S.Lượng | R5: Weight/ K.Lượng (Kg) | S5: Q.Ty/ S.Lượng | T5: Weight/ K.Lượng (Kg) | U5: Q.Ty/ S.Lượng | V5: Weight/ K.Lượng (Kg) | W5: Q.Ty/ S.Lượng | X5: Weight/ K.Lượng (Kg) | Y5: Q.Ty/ S.Lượng | Z5: Weight/ K.Lượng (Kg) | AA5: Q.Ty/ S.Lượng | AB5: Weight/ K.Lượng (Kg) | AC5: Q.Ty/ S.Lượng | AD5: Weight/ K.Lượng (Kg) | AE5: Q.Ty/ S.Lượng | AF5: Weight/ K.Lượng (Kg) | AG5: Q.Ty/ S.Lượng | AH5: Weight/ K.Lượng (Kg) | AI5: Q.Ty/ S.Lượng | AJ5: Weight/ K.Lượng (Kg) | AK5: Q.Ty/ S.Lượng | AL5: Weight/ K.Lượng (Kg) | AM5: Q.Ty/ S.Lượng | AN5: Weight/ K.Lượng (Kg) | AO5: Q.Ty/ S.Lượng | AP5: Weight/ K.Lượng (Kg) | AQ5: Q.Ty/ S.Lượng | AR5: Weight/ K.Lượng (Kg) | AS5: Q.Ty/ S.Lượng | AT5: Weight/ K.Lượng (Kg) | AU5: Q.Ty/ S.Lượng | AV5: Weight/ K.Lượng (Kg) | AW5: Q.Ty/ S.Lượng | AX5: Weight/ K.Lượng (Kg) | AY5: Q.Ty/ S.Lượng | AZ5: Weight/ K.Lượng (Kg) | BA5: Q.Ty/ S.Lượng | BB5: Weight/ K.Lượng (Kg) | BC5: Q.Ty/ S.Lượng | BD5: Weight/ K.Lượng (Kg) | BE5: Q.Ty/ S.Lượng | BF5: Weight/ K.Lượng (Kg) | BG5: Q.Ty/ S.Lượng | BH5: Weight/ K.Lượng (Kg) | BI5: Q.Ty/ S.Lượng | BJ5: Weight/ K.Lượng (Kg) | BK5: Q.Ty/ S.Lượng | BL5: Weight/ K.Lượng (Kg) | BM5: Q.Ty/ S.Lượng | BN5: Weight/ K.Lượng (Kg) | BO5: Q.Ty/ S.Lượng | BP5: Weight/ K.Lượng (Kg) | BQ5: Q.Ty/ S.Lượng | BR5: Weight/ K.Lượng (Kg) | BS5: Q.Ty/ S.Lượng | BT5: Weight/ K.Lượng (Kg) | BU5: Q.Ty/ S.Lượng | BV5: Weight/ K.Lượng (Kg) | BW5: Q.Ty/ S.Lượng | BX5: Weight/ K.Lượng (Kg) | BY5: Q.Ty/ S.Lượng | BZ5: Weight/ K.Lượng (Kg) | CA5: Q.Ty/ S.Lượng | CB5: Weight/ K.Lượng (Kg) | CC5: Q.Ty/ S.Lượng | CD5: Weight/ K.Lượng (Kg) | CE5: Q.Ty/ S.Lượng | CF5: Weight/ K.Lượng (Kg) | CG5: Q.Ty/ S.Lượng | CH5: Weight/ K.Lượng (Kg) | CI5: Q.Ty/ S.Lượng | CJ5: Weight/ K.Lượng (Kg) | CK5: Q.Ty/ S.Lượng | CL5: Weight/ K.Lượng (Kg) | CM5: Q.Ty/ S.Lượng | CN5: Weight/ K.Lượng (Kg) | CO5: Q.Ty/ S.Lượng | CP5: Weight/ K.Lượng (Kg) | CQ5: Q.Ty/ S.Lượng | CR5: Weight/ K.Lượng (Kg) | CS5: Q.Ty/ S.Lượng | CT5: Weight/ K.Lượng (Kg) | CU5: Q.Ty/ S.Lượng | CV5: Weight/ K.Lượng (Kg) | CW5: Q.Ty/ S.Lượng | CX5: Weight/ K.Lượng (Kg) | CZ5: Report No. | DA5: Q.Ty/ S.Lượng | DB5: Weight/ K.Lượng (Kg) | DC5: Ngày nghiệm thu ACC | DD5: Remarks/ Ghi chú | DE5: Q.Ty/ S.Lượng | DF5: Weight/ K.Lượng (Kg) | DH5: Số Hợp đồng / Contract No | DI5: Nhà cung cấp/ Vendor | DJ5: Profile/ Vật tư | DK5: Grade/ Mác vật liệu | DL5: Contract weight ( K.Lượng theo HĐ) | DM5: Ngày ký HD/ Contract date | DN5: S.Lượng giao hàng thực tế/ Handover Q'ty | DO5: K.Lượng giao hàng thực tế// Handover weight | DP5: Đơn giá / Unit Price (Not VAT) | DQ5: Tổng tiền đã VAT (VNĐ) | DR5: % thuế VAT | DS5: Tổng tiền chưa VAT (VNĐ) | DT5: Bàn giao sản xuất/ Handover to Product | DU5: Q.Ty/ S.Lượng | DV5: Weight/ K.Lượng (Kg) | DW5: Report No. | DX5: Inspection date | DY5: Khối lượng nghiệm thu đạt/ Weight Acc. Inspection | DZ5: Results | EA5: Số Hợp đồng / Contract No | EB5: Nhà cung cấp/ Vendor | EC5: Profile/ Vật tư | ED5: Grade/ Mác vật liệu | EE5: Weight/ Khối lượng (Kg) | EF5: Ngày ký HD/ Contract date | EG5: Số lượng giao hàng thực tế/ Handover Q'ty | EH5: Khối lượng giao hàng thực tế/ Handover Q'ty | EI5: Đơn giá / Unit Price | EJ5: Thành tiền Hợp đồng/ total | EK5: Ngày mở L/C/ LC issued date | EL5: Hàng đi từ cảng nước ngoài/ Export Port | EM5: Hàng Đến cảng HP (CIF)/ HaiPhong CIF | EN5: Ngày thanh toán / Payment date | EO5: Thủ tục hải quan, vận chuyển/ Paper work, local transportaion date | EP5: Ngày hàng về / Arived | EQ5: Ngày mời nghiệm thu / invice QC date | ER5: Bàn giao sản xuất/ Handover to Product | ES5: Q.Ty/ S.Lượng | ET5: Weight/ K.Lượng (Kg) | EU5: Report No. | EV5: Inspection date | EW5: Khối lượng nghiệm thu đạt/ Weight Acc. Inspection | EX5: Results | EY5: Q.Ty/ S.Lượng | EZ5: Weight/ K.Lượng (Kg) | FA5: Q.Ty/ S.Lượng | FB5: Weight/ K.Lượng (Kg) | FC5: Đánh giá (Thiếu/ Đủ/ Thừa) | FE5: STT | FF5: Chi tiết vật liệu | FH5: ĐVT | FI5: Định mức | FJ5: Số lượng | FK5: Khối lượng | FL5: Đơn giá (VNĐ)
B6: ` | C6: Số lượng cần (M/M2) | D6: Note | E6: Lượng kho đang lấy của Hoàng cấp | F6: Lượng lấy vượt | G6: Xin chuyển đổi | H6: Để xuất chuyển đổi | I6: 1 | J6: =I6+1 -> 2 | K6: =J6+1 -> 3 | L6: =K6+1 -> 4 | M6: =L6+1 -> 5 | N6: =M6+1 -> 6 | O6: =N6+1 -> 7 | P6: =O6+1 -> 8 | Q6: =P6+1 -> 9 | ... FD6: =FC6+1 -> 152
I7: A. | J7: Main-Material / Vật tư chính | CW7: =SUM(CW8:CW315) -> 31490.409 | CX7: =SUM(CX8:CX315) -> 1394826.7 | CY7: =SUM(CY8:CY315) -> 0 | CZ7: =SUM(CZ8:CZ315) -> 0 | DA7: =SUM(DA8:DA315) -> 141.9749 | DB7: =SUM(DB8:DB315) -> 11796.06 | DC7: =SUM(DC8:DC315) -> 0 | DD7: =SUM(DD8:DD315) -> 0 | ... FD7: =SUM(FD8:FD315) -> 0 | FE7: I
A8: =IF(I8=I7,"ok","Hiện") -> Hiện | B8: =FC8 -> Đủ | C8: =FA8 -> 0 | I8: I90-A1 | J8: Bulong móng | K8: ANCHOR BOLT M42 | M8: sets | N8: =10.405+0.93/4 -> 10.6375 | O8: 320 | P8: =+O8*N8 -> 3404 | Q8: 320 | R8: 3404 | W8: 0 | X8: 0 | Y8: 0 | Z8: 0 | AA8: 0 | AB8: 0 | AC8: 0 | AD8: 0 | AE8: 0 | AF8: 0 | AG8: 0 | AH8: 0 | AI8: =VLOOKUP(I8,'[119]MTO-rev09'!$A:$O,11,0) -> 0 | AJ8: =VLOOKUP(I8,'[119]MTO-rev09'!$A:$O,12,0) -> 0 | AK8: 0 | AL8: 0 | AO8: 0 | AP8: 0 | AQ8: 0 | AR8: 0 | AS8: 0 | AT8: 0 | AU8: 0 | AV8: 0 | AW8: 0 | AX8: 0 | AY8: 0 | AZ8: 0 | BC8: 0 | BD8: 0 | BE8: 0 | BF8: 0 | BG8: 0 | BH8: 0 | BI8: 0 | BJ8: 0 | BK8: 0 | BL8: 0 | BM8: 0 | BN8: 0 | BQ8: 0 | BR8: 0 | BS8: 0 | BT8: 0 | BU8: 0 | BV8: 0 | BY8: 0 | BZ8: 0 | CA8: 0 | CB8: 0 | CC8: 0 | CD8: 0 | CE8: =VLOOKUP(I8,[120]REV33!$A:$O,11,0) -> 0 | CF8: =VLOOKUP(I8,[120]REV33!$A:$O,12,0) -> 0 | CO8: 0 | CP8: 0 | CQ8: 0 | CR8: 0 | CS8: 0 | CT8: 0 | CU8: 0 | CV8: 0 | CW8: =Q8+S8+U8+W8+Y8+AA8+AC8+AE8+AG8+AI8+AK8+AM8+AO8+AQ8+AS8+AU8+AW8+AY8+BA8+BC8+BE8+BG8+BI8+BK8+BM8+BO8+BQ8+BS8+BU8+BW8+BY8+CA8+CC8+CE8+CG8+CI8+CK8+CM8+CO8+CQ8+CS8+CU8 -> 320 | CX8: =R8+T8+V8+X8+Z8+AB8+AD8+AF8+AH8+AJ8+AL8+AN8+AP8+AR8+AT8+AV8+AX8+AZ8+BB8+BD8+BF8+BH8+BJ8+BL8+BN8+BP8+BR8+BT8+BV8+BX8+BZ8+CB8+CD8+CF8+CH8+CJ8+CL8+CN8+CP8+CR8+CT8+CV8 -> 3404 | CY8: Thông số kỹ thuật theo bản vẽ đặt hàng "I90-13105-ANCHOR BOLT M42" | DE8: =IF(CW8>DA8,CW8-DA8,"0") -> 320 | DF8: =IF(CX8>DB8,CX8-DB8,"0") -> 3404 | DG8: 45792 | DH8: 90.1/HĐKT-2025 IBS-VSAN | DI8: VSAN | DJ8: Thanh ren M42-4.5x675 Ecu M42-4.5 Vòng đẹm phẳng OD75xID43x10mm Vòng đệm phẳng M42 | DL8: N/A | DM8: 45773 | DN8: 320 | DO8: N/A | DP8: =203497600/320 -> 635930 | DQ8: =DN8*DP8*1.1 -> 2.2384736e+08 | DR8: =(DQ8-DS8)/DS8 -> 0.1 | DS8: =DN8*DP8 -> 203497600 | DT8: 45797 | DU8: =SUMIF($I:$I,I8,$DN:$DN) -> 320 | DV8: =SUMIF($I:$I,I8,$DO:$DO) -> 0 | ES8: =SUMIF($I:$I,I8,$EG:$EG) -> 0 | ET8: =SUMIF($I:$I,I8,$EH:$EH) -> 0 | EY8: =DU8+ES8 -> 320 | EZ8: =DV8+ET8 -> 0 | FA8: =DE8-EY8 -> 0 | FB8: =DF8-EZ8 -> 3404 | FC8: =IF(FA8<0,"Thừa",IF(FA8=0,"Đủ","Thiếu")) -> Đủ
A9: =IF(I9=I8,"ok","Hiện") -> Hiện | B9: =FC9 -> Đủ | C9: =FA9 -> 0 | I9: I90-A2 | J9: Tôn tấm | K9: PL10x2000x6000 | L9: 1.0577(S355J2)/ ASTM A36 | M9: m2 | N9: =7.85*DA9 -> 0 | O9: =+P9/N9 -> #DIV/0! | P9: =30.66*80 -> 2452.8 | Q9: 48 | R9: 3768 | W9: 0 | X9: 0 | Y9: 0 | Z9: 0 | AA9: 0 | AB9: 0 | AC9: 0 | AD9: 0 | AE9: 0 | AF9: 0 | AG9: 0 | AH9: 0 | AI9: =VLOOKUP(I9,'[119]MTO-rev09'!$A:$O,11,0) -> 0 | AJ9: =VLOOKUP(I9,'[119]MTO-rev09'!$A:$O,12,0) -> 0 | AK9: 0 | AL9: 0 | AO9: 0 | AP9: 0 | AQ9: 0 | AR9: 0 | AS9: 0 | AT9: 0 | AU9: 0 | AV9: 0 | AW9: 0 | AX9: 0 | AY9: 0 | AZ9: 0 | BC9: 0 | BD9: 0 | BE9: 0 | BF9: 0 | BG9: 0 | BH9: 0 | BI9: 0 | BJ9: 0 | BK9: 0 | BL9: 0 | BM9: 0 | BN9: 0 | BQ9: 0 | BR9: 0 | BS9: 0 | BT9: 0 | BU9: 0 | BV9: 0 | BY9: 0 | BZ9: 0 | CA9: 0 | CB9: 0 | CC9: 0 | CD9: 0 | CE9: =VLOOKUP(I9,[120]REV33!$A:$O,11,0) -> 0 | CF9: =VLOOKUP(I9,[120]REV33!$A:$O,12,0) -> 0 | CO9: 0 | CP9: 0 | CQ9: 0 | CR9: 0 | CS9: 0 | CT9: 0 | CU9: 0 | CV9: 0 | CW9: =Q9+S9+U9+W9+Y9+AA9+AC9+AE9+AG9+AI9+AK9+AM9+AO9+AQ9+AS9+AU9+AW9+AY9+BA9+BC9+BE9+BG9+BI9+BK9+BM9+BO9+BQ9+BS9+BU9+BW9+BY9+CA9+CC9+CE9+CG9+CI9+CK9+CM9+CO9+CQ9+CS9+CU9 -> 48 | CX9: =R9+T9+V9+X9+Z9+AB9+AD9+AF9+AH9+AJ9+AL9+AN9+AP9+AR9+AT9+AV9+AX9+AZ9+BB9+BD9+BF9+BH9+BJ9+BL9+BN9+BP9+BR9+BT9+BV9+BX9+BZ9+CB9+CD9+CF9+CH9+CJ9+CL9+CN9+CP9+CR9+CT9+CV9 -> 3768 | CY9: Rev01-đổi khổ như thực tế đã mua PL10x2000x6000-4 tờ | DE9: =IF(CW9>DA9,CW9-DA9,"0") -> 48 | DF9: =IF(CX9>DB9,CX9-DB9,"0") -> 3768 | DG9: 45792 | DH9: 020525/HN-IBS | DI9: Hùng Nguyên | DJ9: Thép tấm 10x2000x6000 = 4 Tấm/ Cây SS400 | DK9: SS400 | DL9: 3768 | DM9: 45779 | DN9: 48 | DO9: 3768 | DP9: 13545.45 | DQ9: =DP9*DO9*1.1 -> 56143181 | DR9: =(DQ9-DS9)/DS9 -> 0.1 | DS9: =DP9*DO9 -> 51039256 | DT9: 45782 | DU9: =SUMIF($I:$I,I9,$DN:$DN) -> 48 | DV9: =SUMIF($I:$I,I9,$DO:$DO) -> 3768 | ES9: =SUMIF($I:$I,I9,$EG:$EG) -> 0 | ET9: =SUMIF($I:$I,I9,$EH:$EH) -> 0 | EY9: =DU9+ES9 -> 48 | EZ9: =DV9+ET9 -> 3768 | FA9: =DE9-EY9 -> 0 | FB9: =DF9-EZ9 -> 0 | FC9: =IF(FA9<0,"Thừa",IF(FA9=0,"Đủ","Thiếu")) -> Đủ
A10: =IF(I10=I9,"ok","Hiện") -> Hiện | B10: =FC10 -> Đủ | C10: =FA10 -> 0 | I10: I90-A3 | J10: Tôn tấm | K10: PL1.5x800x800 | L10: ASTM A36 | M10: m2 | N10: 11.775 | O10: 0.33970276 | P10: 4 | S10: 0.64 | T10: 7.536 | W10: 0 | X10: 0 | Y10: 0 | Z10: 0 | AA10: 0 | AB10: 0 | AC10: 0 | AD10: 0 | AE10: 0 | AF10: 0 | AG10: 3 | AH10: 35.325 | AI10: =VLOOKUP(I10,'[119]MTO-rev09'!$A:$O,11,0) -> 0 | AJ10: =VLOOKUP(I10,'[119]MTO-rev09'!$A:$O,12,0) -> 0 | AK10: 0 | AL10: 0 | AO10: 0 | AP10: 0 | AQ10: 0 | AR10: 0 | AS10: 0 | AT10: 0 | AU10: 0 | AV10: 0 | AW10: 0 | AX10: 0 | AY10: 0 | AZ10: 0 | BC10: 0 | BD10: 0 | BE10: 0 | BF10: 0 | BG10: 0 | BH10: 0 | BI10: 0 | BJ10: 0 | BK10: 0 | BL10: 0 | BM10: 0 | BN10: 0 | BQ10: 0 | BR10: 0 | BS10: 0 | BT10: 0 | BU10: 0 | BV10: 0 | BY10: 0 | BZ10: 0 | CA10: 0 | CB10: 0 | CC10: 0 | CD10: 0 | CE10: =VLOOKUP(I10,[120]REV33!$A:$O,11,0) -> 0 | CF10: =VLOOKUP(I10,[120]REV33!$A:$O,12,0) -> 0 | CO10: 0 | CP10: 0 | CQ10: 0 | CR10: 0 | CS10: 0 | CT10: 0 | CU10: 0 | CV10: 0 | CW10: =Q10+S10+U10+W10+Y10+AA10+AC10+AE10+AG10+AI10+AK10+AM10+AO10+AQ10+AS10+AU10+AW10+AY10+BA10+BC10+BE10+BG10+BI10+BK10+BM10+BO10+BQ10+BS10+BU10+BW10+BY10+CA10+CC10+CE10+CG10+CI10+CK10+CM10+CO10+CQ10+CS10+CU10 -> 3.64 | CX10: =R10+T10+V10+X10+Z10+AB10+AD10+AF10+AH10+AJ10+AL10+AN10+AP10+AR10+AT10+AV10+AX10+AZ10+BB10+BD10+BF10+BH10+BJ10+BL10+BN10+BP10+BR10+BT10+BV10+BX10+BZ10+CB10+CD10+CF10+CH10+CJ10+CL10+CN10+CP10+CR10+CT10+CV10 -> 42.861 | CY10: Rev08-PL1.5x1200x2500 | DA10: 3.64 | DB10: 42.861 | DD10: Mời nghiệm thu ngày 10/6 | DE10: =IF(CW10>DA10,CW10-DA10,"0") -> 0 | DF10: =IF(CX10>DB10,CX10-DB10,"0") -> 0 | DG10: 45792 | DU10: =SUMIF($I:$I,I10,$DN:$DN) -> 0 | DV10: =SUMIF($I:$I,I10,$DO:$DO) -> 0 | ES10: =SUMIF($I:$I,I10,$EG:$EG) -> 0 | ET10: =SUMIF($I:$I,I10,$EH:$EH) -> 0 | EY10: =DU10+ES10 -> 0 | EZ10: =DV10+ET10 -> 0 | FA10: =DE10-EY10 -> 0 | FB10: =DF10-EZ10 -> 0 | FC10: =IF(FA10<0,"Thừa",IF(FA10=0,"Đủ","Thiếu")) -> Đủ
A11: =IF(I11=I10,"ok","Hiện") -> Hiện | B11: =CONCATENATE(FC11," Thiết kế báo khổ 2m chỉ mua 60 tấm") -> Thiếu Thiết kế báo khổ 2m chỉ mua 60 tấm | C11: =FA11 -> 36 | E11: 63 tờ tôn PL3x 2m x 6m | I11: I90-A4 | J11: Tôn tấm | K11: PL3x1500x6000 | L11: ASTM A36 | M11: m2 | N11: 23.55 | O11: 9.2866242 | P11: 218.7 | S11: 9 | T11: 211.95 | W11: 0 | X11: 0 | Y11: 0 | Z11: 0 | AA11: 18 | AB11: 423.9 | AC11: 0 | AD11: 0 | AE11: 9 | AF11: 211.95 | AG11: 0 | AH11: 0 | AI11: =VLOOKUP(I11,'[119]MTO-rev09'!$A:$O,11,0) -> 0 | AJ11: =VLOOKUP(I11,'[119]MTO-rev09'!$A:$O,12,0) -> 0 | AK11: 0 | AL11: 0 | AO11: 0 | AP11: 0 | AQ11: 0 | AR11: 0 | AS11: 18 | AT11: 672.85605 | AU11: 0 | AV11: 0 | AW11: 0 | AX11: 0 | AY11: 0 | AZ11: 0 | BC11: 450 | BD11: 10597.5 | BE11: 0 | BF11: 0 | BG11: 0 | BH11: 0 | BI11: 0 | BJ11: 0 | BK11: 0 | BL11: 0 | BM11: 0 | BN11: 0 | BQ11: 0 | BR11: 0 | BS11: 756 | BT11: 17803.8 | BU11: 0 | BV11: 0 | BY11: 0 | BZ11: 0 | CA11: 0 | CB11: 0 | CC11: 0 | CD11: 0 | CE11: =VLOOKUP(I11,[120]REV33!$A:$O,11,0) -> 0 | CF11: =VLOOKUP(I11,[120]REV33!$A:$O,12,0) -> 0 | CO11: 0 | CP11: 0 | CQ11: 0 | CR11: 0 | CS11: 0 | CT11: 0 | CU11: 0 | CV11: 0 | CW11: =Q11+S11+U11+W11+Y11+AA11+AC11+AE11+AG11+AI11+AK11+AM11+AO11+AQ11+AS11+AU11+AW11+AY11+BA11+BC11+BE11+BG11+BI11+BK11+BM11+BO11+BQ11+BS11+BU11+BW11+BY11+CA11+CC11+CE11+CG11+CI11+CK11+CM11+CO11+CQ11+CS11+CU11 -> 1260 | CX11: =R11+T11+V11+X11+Z11+AB11+AD11+AF11+AH11+AJ11+AL11+AN11+AP11+AR11+AT11+AV11+AX11+AZ11+BB11+BD11+BF11+BH11+BJ11+BL11+BN11+BP11+BR11+BT11+BV11+BX11+BZ11+CB11+CD11+CF11+CH11+CJ11+CL11+CN11+CP11+CR11+CT11+CV11 -> 29921.956 | CY11: Rev27-Braden bổ sung PL3x1500x6000-84 tờ cho mục cover mới (tính cho U3+U4+U5) | DE11: =IF(CW11>DA11,CW11-DA11,"0") -> 1260 | DF11: =IF(CX11>DB11,CX11-DB11,"0") -> 29921.956 | DG11: 45792 | DH11: 140525HN-IBS | DI11: Hùng Nguyên | DJ11: Thép tấm 3x1500x6000 | DK11: SS400 (Team / chứng chỉ A36) | DL11: 211.95 | DM11: 45791 | DN11: 9 | DO11: 211.95 | DP11: 13090.91 | DQ11: =DP11*DO11*1.1 -> 3052080.2 | DR11: =(DQ11-DS11)/DS11 -> 0.1 | DS11: =DP11*DO11 -> 2774618.4 | DT11: 45794 | DU11: =SUMIF($I:$I,I11,$DN:$DN) -> 1224 | DV11: =SUMIF($I:$I,I11,$DO:$DO) -> 28825.2 | ES11: =SUMIF($I:$I,I11,$EG:$EG) -> 0 | ET11: =SUMIF($I:$I,I11,$EH:$EH) -> 0 | EY11: =DU11+ES11 -> 1224 | EZ11: =DV11+ET11 -> 28825.2 | FA11: =DE11-EY11 -> 36 | FB11: =DF11-EZ11 -> 1096.7561 | FC11: =IF(FA11<0,"Thừa",IF(FA11=0,"Đủ","Thiếu")) -> Thiếu
A12: =IF(I12=I11,"ok","Hiện") -> ok | I12: I90-A4 | J12: Tôn tấm | K12: PL3x1500x6000 | L12: ASTM A36 | M12: m2 | DH12: 11.11.2025/APEC | DI12: APEC | DJ12: Thép tấm 3x2000x6000mm ( 60 Tấm) | DK12: SS400/SS400B | DM12: 45972 | DN12: 720 | DO12: 16956 | DP12: 13954.55 | DQ12: =DP12*DO12*(1+DR12) -> 2.6027468e+08 | DR12: 0.1 | DS12: =DO12*DP12 -> 2.3661335e+08 | DT12: 45976
A13: =IF(I13=I12,"ok","Hiện") -> ok | I13: I90-A4 | J13: Tôn tấm | K13: PL3x1500x6000 | L13: ASTM A36 | M13: m2 | DH13: 150725/HN-IBS | DI13: Hùng Nguyên | DJ13: Thép tấm 3x1500x6000 = 1 Tấm A36 | DK13: SS400/Q235B | DL13: 211.95 | DM13: 45853 | DN13: 9 | DO13: 211.95 | DP13: 13454.55 | DQ13: =DP13*DO13*1.1 -> 3136861.1 | DR13: =(DQ13-DS13)/DS13 -> 0.1 | DS13: =DP13*DO13 -> 2851691.9 | DT13: 45856
A14: =IF(I14=I13,"ok","Hiện") -> ok | I14: I90-A4 | J14: Tôn tấm | K14: PL3x1500x6000 | L14: ASTM A36 | M14: m2 | DH14: 210625/HN-IBS | DI14: Hùng Nguyên | DJ14: Thép tấm 3x1500x6000 (2 tờ) | DK14: SS400 | DL14: 423.9 | DM14: 45829 | DN14: 18 | DO14: 423.9 | DP14: 13363.64 | DQ14: =DP14*DO14*1.1 -> 6231331.7 | DR14: =(DQ14-DS14)/DS14 -> 0.1 | DS14: =DP14*DO14 -> 5664847 | DT14: 45835
A15: =IF(I15=I14,"ok","Hiện") -> ok | I15: I90-A4 | J15: Tôn tấm | K15: PL3x1500x6000 | L15: ASTM A36 | M15: m2 | DH15: I90-0409/HN-IBS | DI15: Hùng Nguyên | DJ15: Thép tấm 3x1500x6000 ( 2 tấm) | DL15: 423.9 | DM15: 45904 | DN15: 18 | DO15: 423.9 | DP15: 13909.09 | DQ15: =DP15*DO15*1.1 -> 6485669.6 | DR15: =(DQ15-DS15)/DS15 -> 0.1 | DS15: =DP15*DO15 -> 5896063.3 | DT15: 45909
A16: =IF(I16=I15,"ok","Hiện") -> ok | I16: I90-A4 | J16: Tôn tấm | K16: PL3x1500x6000 | L16: ASTM A36 | M16: m2 | DH16: I90-0310/HN-IBS | DI16: Hùng Nguyên | DJ16: Thép tấm 3x1500x6000 SS400 ( 50 Tấm) | DK16: SS400 | DL16: 10597.5 | DM16: 45933 | DN16: 450 | DO16: 10597.5 | DP16: 14181.82 | DQ16: =DP16*DO16*1.1 -> 1.6532102e+08 | DR16: =(DQ16-DS16)/DS16 -> 0.1 | DS16: =DP16*DO16 -> 1.5029184e+08 | DT16: 45939
A17: =IF(I17=I16,"ok","Hiện") -> Hiện | B17: =FC17 -> Thừa | C17: =FA17 -> -3 | I17: I90-A5 | J17: Tôn tấm | K17: PL5x1500x6000 | L17: ASTM A36 | M17: m2 | N17: 39.25 | O17: 6.8264968 | P17: 267.94 | S17: 9 | T17: 353.25 | W17: 0 | X17: 0 | Y17: 0 | Z17: 0 | AA17: 9 | AB17: 353.25 | AC17: 0 | AD17: 0 | AE17: 0 | AF17: 0 | AG17: 0 | AH17: 0 | AI17: =VLOOKUP(I17,'[119]MTO-rev09'!$A:$O,11,0) -> 0 | AJ17: =VLOOKUP(I17,'[119]MTO-rev09'!$A:$O,12,0) -> 0 | AK17: 0 | AL17: 0 | AO17: 0 | AP17: 0 | AQ17: 0 | AR17: 0 | AS17: 0 | AT17: 0 | AU17: 0 | AV17: 0 | AW17: 0 | AX17: 0 | AY17: 0 | AZ17: 0 | BC17: 0 | BD17: 0 | BE17: 0 | BF17: 0 | BG17: 0 | BH17: 0 | BI17: 0 | BJ17: 0 | BK17: 9 | BL17: 353.25 | BM17: 0 | BN17: 0 | BQ17: 0 | BR17: 0 | BS17: 0 | BT17: 0 | BU17: 0 | BV17: 0 | BY17: 0 | BZ17: 0 | CA17: 9 | CB17: 353.25 | CC17: 0 | CD17: 0 | CE17: =VLOOKUP(I17,[120]REV33!$A:$O,11,0) -> 0 | CF17: =VLOOKUP(I17,[120]REV33!$A:$O,12,0) -> 0 | CO17: 0 | CP17: 0 | CQ17: 0 | CR17: 0 | CS17: 0 | CT17: 0 | CU17: 0 | CV17: 0 | CW17: =Q17+S17+U17+W17+Y17+AA17+AC17+AE17+AG17+AI17+AK17+AM17+AO17+AQ17+AS17+AU17+AW17+AY17+BA17+BC17+BE17+BG17+BI17+BK17+BM17+BO17+BQ17+BS17+BU17+BW17+BY17+CA17+CC17+CE17+CG17+CI17+CK17+CM17+CO17+CQ17+CS17+CU17 -> 36 | CX17: =R17+T17+V17+X17+Z17+AB17+AD17+AF17+AH17+AJ17+AL17+AN17+AP17+AR17+AT17+AV17+AX17+AZ17+BB17+BD17+BF17+BH17+BJ17+BL17+BN17+BP17+BR17+BT17+BV17+BX17+BZ17+CB17+CD17+CF17+CH17+CJ17+CL17+CN17+CP17+CR17+CT17+CV17 -> 1413 | CY17: Rev31-IBS-PL5x1500x6000-1tờ cho rev platform | DE17: =IF(CW17>DA17,CW17-DA17,"0") -> 36 | DF17: =IF(CX17>DB17,CX17-DB17,"0") -> 1413 | DG17: 45792 | DH17: 140525HN-IBS | DI17: Hùng Nguyên | DJ17: Thép tấm 5x1500x6000 | DK17: SS400 (Team / chứng chỉ A36) | DL17: 353.25 | DM17: 45791 | DN17: 9 | DO17: 353.25 | DP17: 13090.91 | DQ17: =DP17*DO17*1.1 -> 5086800.4 | DR17: =(DQ17-DS17)/DS17 -> 0.1 | DS17: =DP17*DO17 -> 4624364 | DT17: 45794 | DU17: =SUMIF($I:$I,I17,$DN:$DN) -> 39 | DV17: =SUMIF($I:$I,I17,$DO:$DO) -> 1530.75 | ES17: =SUMIF($I:$I,I17,$EG:$EG) -> 0 | ET17: =SUMIF($I:$I,I17,$EH:$EH) -> 0 | EY17: =DU17+ES17 -> 39 | EZ17: =DV17+ET17 -> 1530.75 | FA17: =DE17-EY17 -> -3 | FB17: =DF17-EZ17 -> -117.75 | FC17: =IF(FA17<0,"Thừa",IF(FA17=0,"Đủ","Thiếu")) -> Thừa
A18: =IF(I18=I17,"ok","Hiện") -> ok | I18: I90-A5 | J18: Tôn tấm | K18: PL5x1500x6000 | L18: ASTM A36 | M18: m2 | DH18: ? | DI18: Hùng Nguyên | DJ18: Thép tấm 5x2000x6000 | DL18: 471 | DM18: ? | DN18: 12 | DO18: 471 | DP18: 13727.27 | DQ18: =DP18*DO18*1.1 -> 7112098.6 | DR18: =(DQ18-DS18)/DS18 -> 0.1 | DS18: =DP18*DO18 -> 6465544.2 | DT18: 45997
A19: =IF(I19=I18,"ok","Hiện") -> ok | I19: I90-A5 | J19: Tôn tấm | K19: PL5x1500x6000 | L19: ASTM A36 | M19: m2 | DH19: 210625/HN-IBS | DI19: Hùng Nguyên | DJ19: Thép tấm 5x1500x6000 (1 tờ) | DK19: SS400 | DL19: 353.25 | DM19: 45829 | DN19: 9 | DO19: 353.25 | DP19: 13272.73 | DQ19: =DP19*DO19*1.1 -> 5157451.1 | DR19: =(DQ19-DS19)/DS19 -> 0.1 | DS19: =DP19*DO19 -> 4688591.9 | DT19: 45835
A20: =IF(I20=I19,"ok","Hiện") -> ok | I20: I90-A5 | J20: Tôn tấm | K20: PL5x1500x6000 | L20: ASTM A36 | M20: m2 | DH20: ? | DI20: Hùng Nguyên | DJ20: Thép tấm 5x1500x6000 (1 tờ) | DL20: 353.25 | DM20: ? | DN20: 9 | DO20: 353.25 | DP20: 14181.82 | DQ20: =DP20*DO20*1.1 -> 5510700.7 | DR20: =(DQ20-DS20)/DS20 -> 0.1 | DS20: =DP20*DO20 -> 5009727.9 | DT20: 45957
A21: =IF(I21=I20,"ok","Hiện") -> Hiện | B21: =FC21 -> Đủ | C21: =FA21 -> 0 | I21: I90-A5A | J21: Tôn tấm | K21: PL5x2000X12000 | L21: ASTM A36 | M21: m2 | N21: 39.25 | AC21: 192 | AD21: 7536 | AE21: 0 | AF21: 0 | AG21: 0 | AH21: 0 | AI21: =VLOOKUP(I21,'[119]MTO-rev09'!$A:$O,11,0) -> 0 | AJ21: =VLOOKUP(I21,'[119]MTO-rev09'!$A:$O,12,0) -> 0 | AK21: 0 | AL21: 0 | AO21: 0 | AP21: 0 | AQ21: 0 | AR21: 0 | AS21: 0 | AT21: 0 | AU21: 0 | AV21: 0 | AW21: 0 | AX21: 0 | AY21: 0 | AZ21: 0 | BC21: 0 | BD21: 0 | BE21: 0 | BF21: 0 | BG21: 0 | BH21: 0 | BI21: 0 | BJ21: 0 | BK21: 0 | BL21: 0 | BM21: 0 | BN21: 0 | BQ21: 0 | BR21: 0 | BS21: 0 | BT21: 0 | BU21: 0 | BV21: 0 | BY21: 0 | BZ21: 0 | CA21: 0 | CB21: 0 | CC21: 0 | CD21: 0 | CE21: =VLOOKUP(I21,[120]REV33!$A:$O,11,0) -> 0 | CF21: =VLOOKUP(I21,[120]REV33!$A:$O,12,0) -> 0 | CO21: 0 | CP21: 0 | CQ21: 0 | CR21: 0 | CS21: 0 | CT21: 0 | CU21: 0 | CV21: 0 | CW21: =Q21+S21+U21+W21+Y21+AA21+AC21+AE21+AG21+AI21+AK21+AM21+AO21+AQ21+AS21+AU21+AW21+AY21+BA21+BC21+BE21+BG21+BI21+BK21+BM21+BO21+BQ21+BS21+BU21+BW21+BY21+CA21+CC21+CE21+CG21+CI21+CK21+CM21+CO21+CQ21+CS21+CU21 -> 192 | CX21: =R21+T21+V21+X21+Z21+AB21+AD21+AF21+AH21+AJ21+AL21+AN21+AP21+AR21+AT21+AV21+AX21+AZ21+BB21+BD21+BF21+BH21+BJ21+BL21+BN21+BP21+BR21+BT21+BV21+BX21+BZ21+CB21+CD21+CF21+CH21+CJ21+CL21+CN21+CP21+CR21+CT21+CV21 -> 7536 | CY21: Rev06-BRADEN-PL5x2000x12000-8tờ | DE21: =IF(CW21>DA21,CW21-DA21,"0") -> 192 | DF21: =IF(CX21>DB21,CX21-DB21,"0") -> 7536 | DG21: 45792 | DH21: 210625/HN-IBS | DI21: Hùng Nguyên | DJ21: Thép tấm 5x2000x12000 (8 tờ) | DK21: SS400 | DL21: 7536 | DM21: 45829 | DN21: 192 | DO21: 7536 | DP21: 13181.82 | DQ21: =DP21*DO21*1.1 -> 1.0927202e+08 | DR21: =(DQ21-DS21)/DS21 -> 0.1 | DS21: =DP21*DO21 -> 99338196 | DT21: 45835 | DU21: =SUMIF($I:$I,I21,$DN:$DN) -> 192 | DV21: =SUMIF($I:$I,I21,$DO:$DO) -> 7536 | ES21: =SUMIF($I:$I,I21,$EG:$EG) -> 0 | ET21: =SUMIF($I:$I,I21,$EH:$EH) -> 0 | EY21: =DU21+ES21 -> 192 | EZ21: =DV21+ET21 -> 7536 | FA21: =DE21-EY21 -> 0 | FB21: =DF21-EZ21 -> 0 | FC21: =IF(FA21<0,"Thừa",IF(FA21=0,"Đủ","Thiếu")) -> Đủ
A22: =IF(I22=I21,"ok","Hiện") -> Hiện | B22: =FC22 -> Đủ | C22: =FA22 -> 0 | I22: I90-A6 | J22: Tôn tấm | K22: PL6x1500x12000; PL6x2000x12000 (2 tờ); PL6x2000x3000(1 tờ) | L22: ASTM A36 | M22: m2 | N22: 47.1 | O22: 120.96306 | P22: 5697.36 | S22: 126 | T22: 5934.6 | W22: 0 | X22: 0 | Y22: 0 | Z22: 0 | AA22: 54 | AB22: 2543.4 | AC22: 0 | AD22: 0 | AE22: 24 | AF22: 1130.4 | AG22: 0 | AH22: 0 | AI22: =VLOOKUP(I22,'[119]MTO-rev09'!$A:$O,11,0) -> 0 | AJ22: =VLOOKUP(I22,'[119]MTO-rev09'!$A:$O,12,0) -> 0 | AK22: 0 | AL22: 0 | AO22: 0 | AP22: 0 | AQ22: 0 | AR22: 0 | AS22: 0 | AT22: 0 | AU22: 0 | AV22: 0 | AW22: 0 | AX22: 0 | AY22: 0 | AZ22: 0 | BC22: 0 | BD22: 0 | BE22: 0 | BF22: 0 | BG22: 0 | BH22: 0 | BI22: 0 | BJ22: 0 | BK22: 0 | BL22: 0 | BM22: 0 | BN22: 0 | BQ22: 0 | BR22: 0 | BS22: 0 | BT22: 0 | BU22: 0 | BV22: 0 | BY22: 0 | BZ22: 0 | CA22: 0 | CB22: 0 | CC22: 0 | CD22: 0 | CE22: =VLOOKUP(I22,[120]REV33!$A:$O,11,0) -> 0 | CF22: =VLOOKUP(I22,[120]REV33!$A:$O,12,0) -> 0 | CO22: 0 | CP22: 0 | CQ22: 0 | CR22: 0 | CS22: 0 | CT22: 0 | CU22: 0 | CV22: 0 | CW22: =Q22+S22+U22+W22+Y22+AA22+AC22+AE22+AG22+AI22+AK22+AM22+AO22+AQ22+AS22+AU22+AW22+AY22+BA22+BC22+BE22+BG22+BI22+BK22+BM22+BO22+BQ22+BS22+BU22+BW22+BY22+CA22+CC22+CE22+CG22+CI22+CK22+CM22+CO22+CQ22+CS22+CU22 -> 204 | CX22: =R22+T22+V22+X22+Z22+AB22+AD22+AF22+AH22+AJ22+AL22+AN22+AP22+AR22+AT22+AV22+AX22+AZ22+BB22+BD22+BF22+BH22+BJ22+BL22+BN22+BP22+BR22+BT22+BV22+BX22+BZ22+CB22+CD22+CF22+CH22+CJ22+CL22+CN22+CP22+CR22+CT22+CV22 -> 9608.4 | CY22: Rev07-BRADEN-PL6x2000x12000-1tờ | DE22: =IF(CW22>DA22,CW22-DA22,"0") -> 204 | DF22: =IF(CX22>DB22,CX22-DB22,"0") -> 9608.4 | DG22: 45792 | DH22: 140525HN-IBS | DI22: Hùng Nguyên | DJ22: Thép tấm 6x1500x12000 | DK22: SS400 (Team / chứng chỉ A36) | DL22: 5934.6 | DM22: 45791 | DN22: 126 | DO22: 5934.6 | DP22: 13090.91 | DQ22: =DP22*DO22*1.1 -> 85458246 | DR22: =(DQ22-DS22)/DS22 -> 0.1 | DS22: =DP22*DO22 -> 77689314 | DT22: 45794 | DU22: =SUMIF($I:$I,I22,$DN:$DN) -> 204 | DV22: =SUMIF($I:$I,I22,$DO:$DO) -> 9608.4 | ES22: =SUMIF($I:$I,I22,$EG:$EG) -> 0 | ET22: =SUMIF($I:$I,I22,$EH:$EH) -> 0 | EY22: =DU22+ES22 -> 204 | EZ22: =DV22+ET22 -> 9608.4 | FA22: =DE22-EY22 -> 0 | FB22: =DF22-EZ22 -> 0 | FC22: =IF(FA22<0,"Thừa",IF(FA22=0,"Đủ","Thiếu")) -> Đủ
A23: =IF(I23=I22,"ok","Hiện") -> ok | I23: I90-A6 | J23: Tôn tấm | K23: PL6x1500x12000; PL6x2000x12000 (2 tờ); PL6x2000x3000(1 tờ) | L23: ASTM A36 | M23: m2 | DH23: 150725/HN-IBS | DI23: Hùng Nguyên | DJ23: Thép tấm 6x2000x12000 = 1 Tấm A36 | DK23: SS400/Q235B | DL23: 1130.4 | DM23: 45853 | DN23: 24 | DO23: 1130.4 | DP23: 13136.36 | DQ23: =DP23*DO23*1.1 -> 16334275 | DR23: =(DQ23-DS23)/DS23 -> 0.1 | DS23: =DP23*DO23 -> 14849341 | DT23: 45856
A24: =IF(I24=I23,"ok","Hiện") -> ok | I24: I90-A6 | J24: Tôn tấm | K24: PL6x1500x12000; PL6x2000x12000 (2 tờ); PL6x2000x3000(1 tờ) | L24: ASTM A36 | M24: m2 | DH24: 210625/HN-IBS | DI24: Hùng Nguyên | DJ24: Thép tấm 6x2000x12000 (2 tờ) | DK24: SS400 | DL24: 2260.8 | DM24: 45829 | DN24: 48 | DO24: 2260.8 | DP24: 13181.82 | DQ24: =DP24*DO24*1.1 -> 32781605 | DR24: =(DQ24-DS24)/DS24 -> 0.1 | DS24: =DP24*DO24 -> 29801459 | DT24: 45835
A25: =IF(I25=I24,"ok","Hiện") -> ok | I25: I90-A6 | J25: Tôn tấm | K25: PL6x1500x12000; PL6x2000x12000 (2 tờ); PL6x2000x3000(1 tờ) | L25: ASTM A36 | M25: m2 | DH25: 210625/HN-IBS | DI25: Hùng Nguyên | DJ25: Thép tấm 6x2000x3000 (1 tờ) | DK25: SS400 | DL25: 282.6 | DM25: 45829 | DN25: 6 | DO25: 282.6 | DP25: 13181.82 | DQ25: =DP25*DO25*1.1 -> 4097700.6 | DR25: =(DQ25-DS25)/DS25 -> 0.1 | DS25: =DP25*DO25 -> 3725182.3 | DT25: 45835
A26: =IF(I26=I25,"ok","Hiện") -> Hiện | B26: =FC26 -> Đủ | C26: =FA26 -> 0 | I26: I90-A7 | J26: Tôn tấm | K26: PL8x1500x9060 | L26: ASTM A36 | M26: m2 | N26: 62.8 | O26: 5004.7443 | P26: 314297.94 | S26: 163.08 | T26: 10241.424 | W26: 0 | X26: 0 | Y26: 0 | Z26: 0 | AA26: 0 | AB26: 0 | AC26: 0 | AD26: 0 | AE26: 0 | AF26: 0 | AG26: 0 | AH26: 0 | AI26: =VLOOKUP(I26,'[119]MTO-rev09'!$A:$O,11,0) -> 0 | AJ26: =VLOOKUP(I26,'[119]MTO-rev09'!$A:$O,12,0) -> 0 | AK26: 0 | AL26: 0 | AO26: 0 | AP26: 0 | AQ26: 0 | AR26: 0 | AS26: 0 | AT26: 0 | AU26: 0 | AV26: 0 | AW26: 0 | AX26: 0 | AY26: 0 | AZ26: 0 | BC26: 0 | BD26: 0 | BE26: 0 | BF26: 0 | BG26: 0 | BH26: 0 | BI26: 0 | BJ26: 0 | BK26: 0 | BL26: 0 | BM26: 0 | BN26: 0 | BQ26: 0 | BR26: 0 | BS26: 0 | BT26: 0 | BU26: 0 | BV26: 0 | BY26: 0 | BZ26: 0 | CA26: 0 | CB26: 0 | CC26: 0 | CD26: 0 | CE26: =VLOOKUP(I26,[120]REV33!$A:$O,11,0) -> 0 | CF26: =VLOOKUP(I26,[120]REV33!$A:$O,12,0) -> 0 | CO26: 0 | CP26: 0 | CQ26: 0 | CR26: 0 | CS26: 0 | CT26: 0 | CU26: 0 | CV26: 0 | CW26: =Q26+S26+U26+W26+Y26+AA26+AC26+AE26+AG26+AI26+AK26+AM26+AO26+AQ26+AS26+AU26+AW26+AY26+BA26+BC26+BE26+BG26+BI26+BK26+BM26+BO26+BQ26+BS26+BU26+BW26+BY26+CA26+CC26+CE26+CG26+CI26+CK26+CM26+CO26+CQ26+CS26+CU26 -> 163.08 | CX26: =R26+T26+V26+X26+Z26+AB26+AD26+AF26+AH26+AJ26+AL26+AN26+AP26+AR26+AT26+AV26+AX26+AZ26+BB26+BD26+BF26+BH26+BJ26+BL26+BN26+BP26+BR26+BT26+BV26+BX26+BZ26+CB26+CD26+CF26+CH26+CJ26+CL26+CN26+CP26+CR26+CT26+CV26 -> 10241.424 | CY26: Rev01-PL8x1500x9060-12-tờ | DE26: =IF(CW26>DA26,CW26-DA26,"0") -> 163.08 | DF26: =IF(CX26>DB26,CX26-DB26,"0") -> 10241.424 | DG26: 45792 | DH26: 140525HN-IBS | DI26: Hùng Nguyên | DJ26: Thép tấm 8x1500x9060 | DK26: SS400 (Team / chứng chỉ A36) | DL26: 5120.71 | DM26: 45791 | DN26: =6*1.5*9.06 -> 81.54 | DO26: 5120.71 | DP26: 13090.91 | DQ26: =DP26*DO26*1.1 -> 73738229 | DR26: =(DQ26-DS26)/DS26 -> 0.1 | DS26: =DP26*DO26 -> 67034754 | DT26: 45800 | DU26: =SUMIF($I:$I,I26,$DN:$DN) -> 163.08 | DV26: =SUMIF($I:$I,I26,$DO:$DO) -> 10241.42 | ES26: =SUMIF($I:$I,I26,$EG:$EG) -> 0 | ET26: =SUMIF($I:$I,I26,$EH:$EH) -> 0 | EY26: =DU26+ES26 -> 163.08 | EZ26: =DV26+ET26 -> 10241.42 | FA26: =DE26-EY26 -> 0 | FB26: =DF26-EZ26 -> 0.004 | FC26: =IF(FA26<0,"Thừa",IF(FA26=0,"Đủ","Thiếu")) -> Đủ
A27: =IF(I27=I26,"ok","Hiện") -> ok | I27: I90-A7 | J27: Tôn tấm | K27: PL8x1500x9060 | L27: ASTM A36 | M27: m2 | DH27: 040625HN-IBS | DI27: Hùng Nguyên | DJ27: Thép tấm 8x1500x9060 = 6 TẤm ASTM A36 | DK27: SS400 | DL27: 5120.71 | DM27: 45812 | DN27: 81.54 | DO27: 5120.71 | DP27: 13090.91 | DQ27: =DP27*DO27*1.1 -> 73738229 | DR27: =(DQ27-DS27)/DS27 -> 0.1 | DS27: =DP27*DO27 -> 67034754 | DT27: 45817
A28: =IF(I28=I27,"ok","Hiện") -> Hiện | B28: =FC28 -> Đủ | C28: =FA28 -> 0 | I28: I90-A8 | J28: Tôn tấm | K28: PL8x2000x7200 | L28: ASTM A36 | M28: m2 | N28: 62.8 | S28: 460.8 | T28: 28938.24 | W28: 0 | X28: 0 | Y28: 0 | Z28: 0 | AA28: 0 | AB28: 0 | AC28: 0 | AD28: 0 | AE28: 0 | AF28: 0 | AG28: 0 | AH28: 0 | AI28: =VLOOKUP(I28,'[119]MTO-rev09'!$A:$O,11,0) -> 0 | AJ28: =VLOOKUP(I28,'[119]MTO-rev09'!$A:$O,12,0) -> 0 | AK28: 0 | AL28: 0 | AO28: 0 | AP28: 0 | AQ28: 0 | AR28: 0 | AS28: 0 | AT28: 0 | AU28: 0 | AV28: 0 | AW28: 0 | AX28: 0 | AY28: 0 | AZ28: 0 | BC28: 0 | BD28: 0 | BE28: 0 | BF28: 0 | BG28: 0 | BH28: 0 | BI28: 0 | BJ28: 0 | BK28: 0 | BL28: 0 | BM28: 0 | BN28: 0 | BQ28: 0 | BR28: 0 | BS28: 0 | BT28: 0 | BU28: 0 | BV28: 0 | BY28: 0 | BZ28: 0 | CA28: 0 | CB28: 0 | CC28: 0 | CD28: 0 | CE28: =VLOOKUP(I28,[120]REV33!$A:$O,11,0) -> 0 | CF28: =VLOOKUP(I28,[120]REV33!$A:$O,12,0) -> 0 | CO28: 0 | CP28: 0 | CQ28: 0 | CR28: 0 | CS28: 0 | CT28: 0 | CU28: 0 | CV28: 0 | CW28: =Q28+S28+U28+W28+Y28+AA28+AC28+AE28+AG28+AI28+AK28+AM28+AO28+AQ28+AS28+AU28+AW28+AY28+BA28+BC28+BE28+BG28+BI28+BK28+BM28+BO28+BQ28+BS28+BU28+BW28+BY28+CA28+CC28+CE28+CG28+CI28+CK28+CM28+CO28+CQ28+CS28+CU28 -> 460.8 | CX28: =R28+T28+V28+X28+Z28+AB28+AD28+AF28+AH28+AJ28+AL28+AN28+AP28+AR28+AT28+AV28+AX28+AZ28+BB28+BD28+BF28+BH28+BJ28+BL28+BN28+BP28+BR28+BT28+BV28+BX28+BZ28+CB28+CD28+CF28+CH28+CJ28+CL28+CN28+CP28+CR28+CT28+CV28 -> 28938.24 | CY28: Rev01-PL8x2000x7200-32-tờ | DE28: =IF(CW28>DA28,CW28-DA28,"0") -> 460.8 | DF28: =IF(CX28>DB28,CX28-DB28,"0") -> 28938.24 | DG28: 45792 | DH28: 140525HN-IBS | DI28: Hùng Nguyên | DJ28: Thép tấm 8x2000x7200 | DK28: A36 | DL28: 19895.04 | DM28: 45791 | DN28: =22*2*7.2 -> 316.8 | DO28: 19895.04 | DP28: 13090.91 | DQ28: =DP28*DO28*1.1 -> 2.864886e+08 | DR28: =(DQ28-DS28)/DS28 -> 0.1 | DS28: =DP28*DO28 -> 2.6044418e+08 | DT28: 45800 | DU28: =SUMIF($I:$I,I28,$DN:$DN) -> 460.8 | DV28: =SUMIF($I:$I,I28,$DO:$DO) -> 28938.24 | ES28: =SUMIF($I:$I,I28,$EG:$EG) -> 0 | ET28: =SUMIF($I:$I,I28,$EH:$EH) -> 0 | EY28: =DU28+ES28 -> 460.8 | EZ28: =DV28+ET28 -> 28938.24 | FA28: =DE28-EY28 -> 0 | FB28: =DF28-EZ28 -> 0 | FC28: =IF(FA28<0,"Thừa",IF(FA28=0,"Đủ","Thiếu")) -> Đủ
A29: =IF(I29=I28,"ok","Hiện") -> ok | I29: I90-A8 | J29: Tôn tấm | K29: PL8x2000x7200 | L29: ASTM A36 | M29: m2 | DH29: 040625HN-IBS | DI29: Hùng Nguyên | DJ29: Thép tấm 8x2000x7200 = 10 TẤm ASTM A36 | DK29: SS400 | DL29: 9043.2 | DM29: 45812 | DN29: 144 | DO29: 9043.2 | DP29: 13090.91 | DQ29: =DP29*DO29*1.1 -> 1.3022209e+08 | DR29: =(DQ29-DS29)/DS29 -> 0.1 | DS29: =DP29*DO29 -> 1.1838372e+08 | DT29: 45817
A30: =IF(I30=I29,"ok","Hiện") -> Hiện | B30: =FC30 -> Đủ | C30: =FA30 -> 0 | I30: I90-A9 | J30: Tôn tấm | K30: PL8x2000x7800 | L30: ASTM A36 | M30: m2 | N30: 62.8 | S30: 748.8 | T30: 47024.64 | W30: 0 | X30: 0 | Y30: 0 | Z30: 0 | AA30: 0 | AB30: 0 | AC30: 0 | AD30: 0 | AE30: 0 | AF30: 0 | AG30: 0 | AH30: 0 | AI30: =VLOOKUP(I30,'[119]MTO-rev09'!$A:$O,11,0) -> 0 | AJ30: =VLOOKUP(I30,'[119]MTO-rev09'!$A:$O,12,0) -> 0 | AK30: 0 | AL30: 0 | AO30: 0 | AP30: 0 | AQ30: 0 | AR30: 0 | AS30: 0 | AT30: 0 | AU30: 0 | AV30: 0 | AW30: 0 | AX30: 0 | AY30: 0 | AZ30: 0 | BC30: 0 | BD30: 0 | BE30: 0 | BF30: 0 | BG30: 0 | BH30: 0 | BI30: 0 | BJ30: 0 | BK30: 0 | BL30: 0 | BM30: 0 | BN30: 0 | BQ30: 0 | BR30: 0 | BS30: 0 | BT30: 0 | BU30: 0 | BV30: 0 | BY30: 0 | BZ30: 0 | CA30: 0 | CB30: 0 | CC30: 0 | CD30: 0 | CE30: =VLOOKUP(I30,[120]REV33!$A:$O,11,0) -> 0 | CF30: =VLOOKUP(I30,[120]REV33!$A:$O,12,0) -> 0 | CO30: 0 | CP30: 0 | CQ30: 0 | CR30: 0 | CS30: 0 | CT30: 0 | CU30: 0 | CV30: 0 | CW30: =Q30+S30+U30+W30+Y30+AA30+AC30+AE30+AG30+AI30+AK30+AM30+AO30+AQ30+AS30+AU30+AW30+AY30+BA30+BC30+BE30+BG30+BI30+BK30+BM30+BO30+BQ30+BS30+BU30+BW30+BY30+CA30+CC30+CE30+CG30+CI30+CK30+CM30+CO30+CQ30+CS30+CU30 -> 748.8 | CX30: =R30+T30+V30+X30+Z30+AB30+AD30+AF30+AH30+AJ30+AL30+AN30+AP30+AR30+AT30+AV30+AX30+AZ30+BB30+BD30+BF30+BH30+BJ30+BL30+BN30+BP30+BR30+BT30+BV30+BX30+BZ30+CB30+CD30+CF30+CH30+CJ30+CL30+CN30+CP30+CR30+CT30+CV30 -> 47024.64 | CY30: Rev01-PL8x2000x7800-48-tờ | DE30: =IF(CW30>DA30,CW30-DA30,"0") -> 748.8 | DF30: =IF(CX30>DB30,CX30-DB30,"0") -> 47024.64 | DG30: 45792 | DH30: 140525HN-IBS | DI30: Hùng Nguyên | DJ30: Thép tấm 8x2000x7800 | DK30: A36 | DL30: 27431.04 | DM30: 45791 | DN30: =28*2*7.8 -> 436.8 | DO30: 27431.04 | DP30: 13090.91 | DQ30: =DP30*DO30*1.1 -> 3.95007e+08 | DR30: =(DQ30-DS30)/DS30 -> 0.1 | DS30: =DP30*DO30 -> 3.5909728e+08 | DT30: 45800 | DU30: =SUMIF($I:$I,I30,$DN:$DN) -> 748.8 | DV30: =SUMIF($I:$I,I30,$DO:$DO) -> 47024.64 | ES30: =SUMIF($I:$I,I30,$EG:$EG) -> 0 | ET30: =SUMIF($I:$I,I30,$EH:$EH) -> 0 | EY30: =DU30+ES30 -> 748.8 | EZ30: =DV30+ET30 -> 47024.64 | FA30: =DE30-EY30 -> 0 | FB30: =DF30-EZ30 -> 0 | FC30: =IF(FA30<0,"Thừa",IF(FA30=0,"Đủ","Thiếu")) -> Đủ
A31: =IF(I31=I30,"ok","Hiện") -> ok | I31: I90-A9 | J31: Tôn tấm | K31: PL8x2000x7800 | L31: ASTM A36 | M31: m2 | DH31: 040625HN-IBS | DI31: Hùng Nguyên | DJ31: Thép tấm 8x2000x7800 = 20 TẤm ASTM A36 | DK31: SS400 | DL31: 19593.6 | DM31: 45812 | DN31: 312 | DO31: 19593.6 | DP31: 13090.91 | DQ31: =DP31*DO31*1.1 -> 2.8214786e+08 | DR31: =(DQ31-DS31)/DS31 -> 0.1 | DS31: =DP31*DO31 -> 2.5649805e+08 | DT31: 45817
A32: =IF(I32=I31,"ok","Hiện") -> Hiện | B32: =FC32 -> Đủ | C32: =FA32 -> 0 | I32: I90-A10 | J32: Tôn tấm | K32: PL8x2000x9060 | L32: ASTM A36 | M32: m2 | N32: 62.8 | S32: 797.28 | T32: 50069.184 | W32: 0 | X32: 0 | Y32: 0 | Z32: 0 | AA32: 0 | AB32: 0 | AC32: 0 | AD32: 0 | AE32: 0 | AF32: 0 | AG32: 0 | AH32: 0 | AI32: =VLOOKUP(I32,'[119]MTO-rev09'!$A:$O,11,0) -> 0 | AJ32: =VLOOKUP(I32,'[119]MTO-rev09'!$A:$O,12,0) -> 0 | AK32: 0 | AL32: 0 | AO32: 0 | AP32: 0 | AQ32: 0 | AR32: 0 | AS32: 0 | AT32: 0 | AU32: 0 | AV32: 0 | AW32: 0 | AX32: 0 | AY32: 0 | AZ32: 0 | BC32: 0 | BD32: 0 | BE32: 0 | BF32: 0 | BG32: 0 | BH32: 0 | BI32: 0 | BJ32: 0 | BK32: 0 | BL32: 0 | BM32: 0 | BN32: 0 | BQ32: 0 | BR32: 0 | BS32: 0 | BT32: 0 | BU32: 0 | BV32: 0 | BY32: 0 | BZ32: 0 | CA32: 0 | CB32: 0 | CC32: 0 | CD32: 0 | CE32: =VLOOKUP(I32,[120]REV33!$A:$O,11,0) -> 0 | CF32: =VLOOKUP(I32,[120]REV33!$A:$O,12,0) -> 0 | CO32: 0 | CP32: 0 | CQ32: 0 | CR32: 0 | CS32: 0 | CT32: 0 | CU32: 0 | CV32: 0 | CW32: =Q32+S32+U32+W32+Y32+AA32+AC32+AE32+AG32+AI32+AK32+AM32+AO32+AQ32+AS32+AU32+AW32+AY32+BA32+BC32+BE32+BG32+BI32+BK32+BM32+BO32+BQ32+BS32+BU32+BW32+BY32+CA32+CC32+CE32+CG32+CI32+CK32+CM32+CO32+CQ32+CS32+CU32 -> 797.28 | CX32: =R32+T32+V32+X32+Z32+AB32+AD32+AF32+AH32+AJ32+AL32+AN32+AP32+AR32+AT32+AV32+AX32+AZ32+BB32+BD32+BF32+BH32+BJ32+BL32+BN32+BP32+BR32+BT32+BV32+BX32+BZ32+CB32+CD32+CF32+CH32+CJ32+CL32+CN32+CP32+CR32+CT32+CV32 -> 50069.184 | CY32: Rev01-PL8x2000x9060-44-tờ | DE32: =IF(CW32>DA32,CW32-DA32,"0") -> 797.28 | DF32: =IF(CX32>DB32,CX32-DB32,"0") -> 50069.184 | DG32: 45792 | DH32: 140525HN-IBS | DI32: Hùng Nguyên | DJ32: Thép tấm 8x2000x9060 | DK32: A36 | DL32: 27310.46 | DM32: 45791 | DN32: =24*2*9.06 -> 434.88 | DO32: 27310.46 | DP32: 13090.91 | DQ32: =DP32*DO32*1.1 -> 3.9327065e+08 | DR32: =(DQ32-DS32)/DS32 -> 0.1 | DS32: =DP32*DO32 -> 3.5751877e+08 | DT32: 45800 | DU32: =SUMIF($I:$I,I32,$DN:$DN) -> 797.28 | DV32: =SUMIF($I:$I,I32,$DO:$DO) -> 50069.18 | ES32: =SUMIF($I:$I,I32,$EG:$EG) -> 0 | ET32: =SUMIF($I:$I,I32,$EH:$EH) -> 0 | EY32: =DU32+ES32 -> 797.28 | EZ32: =DV32+ET32 -> 50069.18 | FA32: =DE32-EY32 -> 0 | FB32: =DF32-EZ32 -> 0.004 | FC32: =IF(FA32<0,"Thừa",IF(FA32=0,"Đủ","Thiếu")) -> Đủ
A33: =IF(I33=I32,"ok","Hiện") -> ok | I33: I90-A10 | J33: Tôn tấm | K33: PL8x2000x9060 | L33: ASTM A36 | M33: m2 | DH33: 040625HN-IBS | DI33: Hùng Nguyên | DJ33: Thép tấm 8x2000x9060 = 20 TẤm ASTM A36 | DK33: SS400 | DL33: 22758.72 | DM33: 45812 | DN33: 362.4 | DO33: 22758.72 | DP33: 13090.91 | DQ33: =DP33*DO33*1.1 -> 3.2772559e+08 | DR33: =(DQ33-DS33)/DS33 -> 0.1 | DS33: =DP33*DO33 -> 2.9793236e+08 | DT33: 45817
A34: =IF(I34=I33,"ok","Hiện") -> Hiện | B34: =FC34 -> Đủ | C34: =FA34 -> 0 | I34: I90-A11 | J34: Tôn tấm | K34: PL8x2000x12000 | L34: ASTM A36 | M34: m2 | N34: 62.8 | S34: 2880 | T34: 180864 | W34: 0 | X34: 0 | Y34: 0 | Z34: 0 | AA34: 0 | AB34: 0 | AC34: 0 | AD34: 0 | AE34: 336 | AF34: 21100.8 | AG34: 0 | AH34: 0 | AI34: =VLOOKUP(I34,'[119]MTO-rev09'!$A:$O,11,0) -> 0 | AJ34: =VLOOKUP(I34,'[119]MTO-rev09'!$A:$O,12,0) -> 0 | AK34: 0 | AL34: 0 | AO34: 0 | AP34: 0 | AQ34: 0 | AR34: 0 | AS34: 0 | AT34: 0 | AU34: 0 | AV34: 0 | AW34: 0 | AX34: 0 | AY34: 0 | AZ34: 0 | BC34: 0 | BD34: 0 | BE34: 0 | BF34: 0 | BG34: 0 | BH34: 0 | BI34: 0 | BJ34: 0 | BK34: 0 | BL34: 0 | BM34: 0 | BN34: 0 | BQ34: 0 | BR34: 0 | BS34: 0 | BT34: 0 | BU34: 0 | BV34: 0 | BY34: 0 | BZ34: 0 | CA34: 0 | CB34: 0 | CC34: 0 | CD34: 0 | CE34: =VLOOKUP(I34,[120]REV33!$A:$O,11,0) -> 0 | CF34: =VLOOKUP(I34,[120]REV33!$A:$O,12,0) -> 0 | CO34: 0 | CP34: 0 | CQ34: 0 | CR34: 0 | CS34: 0 | CT34: 0 | CU34: 0 | CV34: 0 | CW34: =Q34+S34+U34+W34+Y34+AA34+AC34+AE34+AG34+AI34+AK34+AM34+AO34+AQ34+AS34+AU34+AW34+AY34+BA34+BC34+BE34+BG34+BI34+BK34+BM34+BO34+BQ34+BS34+BU34+BW34+BY34+CA34+CC34+CE34+CG34+CI34+CK34+CM34+CO34+CQ34+CS34+CU34 -> 3216 | CX34: =R34+T34+V34+X34+Z34+AB34+AD34+AF34+AH34+AJ34+AL34+AN34+AP34+AR34+AT34+AV34+AX34+AZ34+BB34+BD34+BF34+BH34+BJ34+BL34+BN34+BP34+BR34+BT34+BV34+BX34+BZ34+CB34+CD34+CF34+CH34+CJ34+CL34+CN34+CP34+CR34+CT34+CV34 -> 201964.8 | CY34: Rev07-BRADEN-PL8x2000x12000-14tờ | DE34: =IF(CW34>DA34,CW34-DA34,"0") -> 3216 | DF34: =IF(CX34>DB34,CX34-DB34,"0") -> 201964.8 | DG34: 45792 | DH34: 140525HN-IBS | DI34: Hùng Nguyên | DJ34: Thép tấm 8x2000x12000 | DK34: A36 | DL34: =75360*55/70 -> 59211.429 | DM34: 45791 | DN34: 1200 | DO34: 75360 | DP34: 13090.91 | DQ34: =DP34*DO34*1.1 -> 1.0851841e+09 | DR34: =(DQ34-DS34)/DS34 -> 0.1 | DS34: =DP34*DO34 -> 9.8653098e+08 | DT34: 45800 | DU34: =SUMIF($I:$I,I34,$DN:$DN) -> 3216 | DV34: =SUMIF($I:$I,I34,$DO:$DO) -> 201964.8 | ES34: =SUMIF($I:$I,I34,$EG:$EG) -> 0 | ET34: =SUMIF($I:$I,I34,$EH:$EH) -> 0 | EY34: =DU34+ES34 -> 3216 | EZ34: =DV34+ET34 -> 201964.8 | FA34: =DE34-EY34 -> 0 | FB34: =DF34-EZ34 -> 0 | FC34: =IF(FA34<0,"Thừa",IF(FA34=0,"Đủ","Thiếu")) -> Đủ
A35: =IF(I35=I34,"ok","Hiện") -> ok | I35: I90-A11 | J35: Tôn tấm | K35: PL8x2000x12000 | L35: ASTM A36 | M35: m2 | DH35: 150725/HN-IBS | DI35: Hùng Nguyên | DJ35: Thép tấm 8x2000x12000 = 14 Tấm A36 | DK35: SS400/Q235B | DL35: 21100.8 | DM35: 45853 | DN35: 336 | DO35: 21100.8 | DP35: 13136.36 | DQ35: =DP35*DO35*1.1 -> 3.0490648e+08 | DR35: =(DQ35-DS35)/DS35 -> 0.1 | DS35: =DP35*DO35 -> 2.7718771e+08 | DT35: 45856
A36: =IF(I36=I35,"ok","Hiện") -> ok | I36: I90-A11 | J36: Tôn tấm | K36: PL8x2000x12000 | L36: ASTM A36 | M36: m2 | DH36: 040625HN-IBS | DI36: Hùng Nguyên | DJ36: Thép tấm 8x2000x12000 = 70 TẤm ASTM A36 | DK36: SS400 | DL36: 105504 | DM36: 45812 | DN36: 1680 | DO36: 105504 | DP36: 13090.91 | DQ36: =DP36*DO36*1.1 -> 1.5192577e+09 | DR36: =(DQ36-DS36)/DS36 -> 0.1 | DS36: =DP36*DO36 -> 1.3811434e+09 | DT36: 45819
A37: =IF(I37=I36,"ok","Hiện") -> Hiện | B37: =FC37 -> Đủ | C37: =FA37 -> 0 | I37: I90-A11A | J37: Tôn tấm | K37: PL8x2000x9650 | L37: ASTM A36 | M37: m2 | N37: 62.8 | AA37: 1737 | AB37: 109083.6 | AC37: 0 | AD37: 0 | AE37: 0 | AF37: 0 | AG37: 0 | AH37: 0 | AI37: =VLOOKUP(I37,'[119]MTO-rev09'!$A:$O,11,0) -> 0 | AJ37: =VLOOKUP(I37,'[119]MTO-rev09'!$A:$O,12,0) -> 0 | AK37: 0 | AL37: 0 | AO37: 0 | AP37: 0 | AQ37: 0 | AR37: 0 | AS37: 0 | AT37: 0 | AU37: 0 | AV37: 0 | AW37: 0 | AX37: 0 | AY37: 0 | AZ37: 0 | BC37: 0 | BD37: 0 | BE37: 0 | BF37: 0 | BG37: 0 | BH37: 0 | BI37: 0 | BJ37: 0 | BK37: 0 | BL37: 0 | BM37: 0 | BN37: 0 | BQ37: 0 | BR37: 0 | BS37: 0 | BT37: 0 | BU37: 0 | BV37: 0 | BY37: 0 | BZ37: 0 | CA37: 0 | CB37: 0 | CC37: 0 | CD37: 0 | CE37: =VLOOKUP(I37,[120]REV33!$A:$O,11,0) -> 0 | CF37: =VLOOKUP(I37,[120]REV33!$A:$O,12,0) -> 0 | CO37: 0 | CP37: 0 | CQ37: 0 | CR37: 0 | CS37: 0 | CT37: 0 | CU37: 0 | CV37: 0 | CW37: =Q37+S37+U37+W37+Y37+AA37+AC37+AE37+AG37+AI37+AK37+AM37+AO37+AQ37+AS37+AU37+AW37+AY37+BA37+BC37+BE37+BG37+BI37+BK37+BM37+BO37+BQ37+BS37+BU37+BW37+BY37+CA37+CC37+CE37+CG37+CI37+CK37+CM37+CO37+CQ37+CS37+CU37 -> 1737 | CX37: =R37+T37+V37+X37+Z37+AB37+AD37+AF37+AH37+AJ37+AL37+AN37+AP37+AR37+AT37+AV37+AX37+AZ37+BB37+BD37+BF37+BH37+BJ37+BL37+BN37+BP37+BR37+BT37+BV37+BX37+BZ37+CB37+CD37+CF37+CH37+CJ37+CL37+CN37+CP37+CR37+CT37+CV37 -> 109083.6 | CY37: Rev05-BRADEN-PL8x2000x9650-90tờ | DE37: =IF(CW37>DA37,CW37-DA37,"0") -> 1737 | DF37: =IF(CX37>DB37,CX37-DB37,"0") -> 109083.6 | DH37: 210625/HN-IBS | DI37: Hùng Nguyên | DJ37: Thép tấm 8x2000x9650 | DK37: SS400 | DL37: 109083.6 | DM37: 45829 | DN37: 1737 | DO37: 109083.6 | DP37: 13181.82 | DQ37: =DP37*DO37*1.1 -> 1.5817124e+09 | DR37: =(DQ37-DS37)/DS37 -> 0.1 | DS37: =DP37*DO37 -> 1.4379204e+09 | DT37: 45832 | DU37: =SUMIF($I:$I,I37,$DN:$DN) -> 1737 | DV37: =SUMIF($I:$I,I37,$DO:$DO) -> 109083.6 | ES37: =SUMIF($I:$I,I37,$EG:$EG) -> 0 | ET37: =SUMIF($I:$I,I37,$EH:$EH) -> 0 | EY37: =DU37+ES37 -> 1737 | EZ37: =DV37+ET37 -> 109083.6 | FA37: =DE37-EY37 -> 0 | FB37: =DF37-EZ37 -> 0 | FC37: =IF(FA37<0,"Thừa",IF(FA37=0,"Đủ","Thiếu")) -> Đủ
A38: =IF(I38=I37,"ok","Hiện") -> Hiện | B38: =FC38 -> Đủ | C38: =FA38 -> 0 | I38: I90-A12 | J38: Tôn tấm | K38: PL10x1500x12000; PL10x2000x12000 (12 tờ) | L38: ASTM A36 | M38: m2 | N38: 78.5 | O38: 189.65962 | P38: 14888.28 | S38: 198 | T38: =S38*$N$38 -> 15543 | W38: 0 | X38: 0 | Y38: 0 | Z38: 0 | AA38: 288 | AB38: =AA38*$N$38 -> 22608 | AC38: 0 | AD38: 0 | AE38: 0 | AF38: 0 | AG38: 24 | AH38: =AG38*$N$38 -> 1884 | AI38: =VLOOKUP(I38,'[119]MTO-rev09'!$A:$O,11,0) -> 0 | AJ38: =VLOOKUP(I38,'[119]MTO-rev09'!$A:$O,12,0) -> 0 | AK38: 0 | AL38: 0 | AM38: 120 | AN38: =AM38*$N$38 -> 9420 | AO38: 0 | AP38: 0 | AQ38: 0 | AR38: 0 | AS38: 0 | AT38: 0 | AU38: 0 | AV38: 0 | AW38: 0 | AX38: 0 | AY38: 0 | AZ38: 0 | BA38: 84 | BB38: =BA38*$N$38 -> 6594 | BC38: 0 | BD38: 0 | BE38: 0 | BF38: 0 | BG38: 0 | BH38: 0 | BI38: 0 | BJ38: 0 | BK38: 0 | BL38: 0 | BM38: 0 | BN38: 0 | BQ38: 0 | BR38: 0 | BS38: 0 | BT38: 0 | BU38: 0 | BV38: 0 | BY38: 0 | BZ38: 0 | CA38: 0 | CB38: 0 | CC38: 0 | CD38: 0 | CE38: =VLOOKUP(I38,[120]REV33!$A:$O,11,0) -> 0 | CF38: =VLOOKUP(I38,[120]REV33!$A:$O,12,0) -> 0 | CO38: 0 | CP38: 0 | CQ38: 0 | CR38: 0 | CS38: 0 | CT38: 0 | CU38: 0 | CV38: 0 | CW38: =Q38+S38+U38+W38+Y38+AA38+AC38+AE38+AG38+AI38+AK38+AM38+AO38+AQ38+AS38+AU38+AW38+AY38+BA38+BC38+BE38+BG38+BI38+BK38+BM38+BO38+BQ38+BS38+BU38+BW38+BY38+CA38+CC38+CE38+CG38+CI38+CK38+CM38+CO38+CQ38+CS38+CU38 -> 714 | CX38: =R38+T38+V38+X38+Z38+AB38+AD38+AF38+AH38+AJ38+AL38+AN38+AP38+AR38+AT38+AV38+AX38+AZ38+BB38+BD38+BF38+BH38+BJ38+BL38+BN38+BP38+BR38+BT38+BV38+BX38+BZ38+CB38+CD38+CF38+CH38+CJ38+CL38+CN38+CP38+CR38+CT38+CV38 -> 56049 | CY38: Rev18-BRADEN-bổ sung PL10x2000x12000-3.5 tờ | DE38: =IF(CW38>DA38,CW38-DA38,"0") -> 714 | DF38: =IF(CX38>DB38,CX38-DB38,"0") -> 56049 | DG38: 45792 | DH38: 140525HN-IBS | DI38: Hùng Nguyên | DJ38: Thép tấm 10x1500x12000 | DK38: SS400 (Team / chứng chỉ A36) | DL38: 15543 | DM38: 45791 | DN38: 198 | DO38: 15543 | DP38: 13090.91 | DQ38: =DP38*DO38*1.1 -> 2.2381922e+08 | DR38: =(DQ38-DS38)/DS38 -> 0.1 | DS38: =DP38*DO38 -> 2.0347201e+08 | DT38: 45794 | DU38: =SUMIF($I:$I,I38,$DN:$DN) -> 714 | DV38: =SUMIF($I:$I,I38,$DO:$DO) -> 56049 | ES38: =SUMIF($I:$I,I38,$EG:$EG) -> 0 | ET38: =SUMIF($I:$I,I38,$EH:$EH) -> 0 | EY38: =DU38+ES38 -> 714 | EZ38: =DV38+ET38 -> 56049 | FA38: =DE38-EY38 -> 0 | FB38: =DF38-EZ38 -> 0 | FC38: =IF(FA38<0,"Thừa",IF(FA38=0,"Đủ","Thiếu")) -> Đủ
A39: =IF(I39=I38,"ok","Hiện") -> ok | I39: I90-A12 | J39: Tôn tấm | K39: PL10x1500x12000; PL10x2000x12000 (12 tờ) | L39: ASTM A36 | M39: m2 | DH39: 210625/HN-IBS | DI39: Hùng Nguyên | DJ39: Thép tấm 10x2000x12000 (12 tờ) | DK39: SS400 | DL39: 22608 | DM39: 45829 | DN39: 288 | DO39: 22608 | DP39: 13181.82 | DQ39: =DP39*DO39*1.1 -> 3.2781605e+08 | DR39: =(DQ39-DS39)/DS39 -> 0.1 | DS39: =DP39*DO39 -> 2.9801459e+08 | DT39: 45835
A40: =IF(I40=I39,"ok","Hiện") -> ok | I40: I90-A12 | J40: Tôn tấm | K40: PL10x1500x12000; PL10x2000x12000 (12 tờ) | L40: ASTM A36 | M40: m2 | DH40: 280725/HN-IBS | DI40: Hùng Nguyên | DJ40: Thép tấm 10x2000x12000 (1 tờ) | DK40: SS400 | DL40: 1884 | DM40: 45866 | DN40: 24 | DO40: 1884 | DP40: 13636.36 | DQ40: =DP40*DO40*1.1 -> 28259992 | DR40: =(DQ40-DS40)/DS40 -> 0.1 | DS40: =DP40*DO40 -> 25690902 | DT40: 45867
A41: =IF(I41=I40,"ok","Hiện") -> ok | I41: I90-A12 | J41: Tôn tấm | K41: PL10x1500x12000; PL10x2000x12000 (12 tờ) | L41: ASTM A36 | M41: m2 | DH41: 190825/HN-IBS | DI41: Hùng Nguyên | DJ41: Thép tấm 10x2000x12000 (5 tờ) | DK41: SS400/Q235B | DL41: 9420 | DM41: 45888 | DN41: 120 | DO41: 9420 | DP41: 13090.91 | DQ41: =DP41*DO41*1.1 -> 1.3564801e+08 | DR41: =(DQ41-DS41)/DS41 -> 0.1 | DS41: =DP41*DO41 -> 1.2331637e+08 | DT41: 45891
A42: =IF(I42=I41,"ok","Hiện") -> ok | I42: I90-A12 | J42: Tôn tấm | K42: PL10x1500x12000; PL10x2000x12000 (12 tờ) | L42: ASTM A36 | M42: m2 | DH42: I90-1509/HN-IBS | DI42: Hùng Nguyên | DJ42: Thép tấm 10x2000x12000 (3.5 tờ) | DL42: 6594 | DM42: 45915 | DN42: =3.5*24 -> 84 | DO42: 6594 | DP42: =14600/1.1 -> 13272.727 | DQ42: =DP42*DO42*1.1 -> 96272400 | DR42: =(DQ42-DS42)/DS42 -> 0.1 | DS42: =DP42*DO42 -> 87520364 | DT42: 45918
A43: =IF(I43=I42,"ok","Hiện") -> Hiện | B43: =FC43 -> Đủ | C43: =FA43 -> 0 | I43: I90-A13 | J43: Tôn tấm | K43: PL12x1500x12000; PL12x2000x12000; PL12x2000x9000. | L43: ASTM A36 | M43: m2 | N43: 94.2 | O43: 61.203822 | P43: 5765.4 | S43: 54 | T43: 5086.8 | W43: 0 | X43: 0 | Y43: 0 | Z43: 0 | AA43: 90 | AB43: 8478 | AC43: 24 | AD43: 2260.8 | AE43: 48 | AF43: 4521.6 | AG43: 0 | AH43: 0 | AI43: =VLOOKUP(I43,'[119]MTO-rev09'!$A:$O,11,0) -> 0 | AJ43: =VLOOKUP(I43,'[119]MTO-rev09'!$A:$O,12,0) -> 0 | AK43: 48 | AL43: 4521.6 | AO43: 0 | AP43: 0 | AQ43: 0 | AR43: 0 | AS43: 0 | AT43: 0 | AU43: 0 | AV43: 0 | AW43: 0 | AX43: 0 | AY43: 0 | AZ43: 0 | BC43: 0 | BD43: 0 | BE43: 0 | BF43: 0 | BG43: 0 | BH43: 0 | BI43: 0 | BJ43: 0 | BK43: 0 | BL43: 0 | BM43: 0 | BN43: 0 | BQ43: 0 | BR43: 0 | BS43: 0 | BT43: 0 | BU43: 0 | BV43: 0 | BY43: 0 | BZ43: 0 | CA43: 0 | CB43: 0 | CC43: 0 | CD43: 0 | CE43: =VLOOKUP(I43,[120]REV33!$A:$O,11,0) -> 0 | CF43: =VLOOKUP(I43,[120]REV33!$A:$O,12,0) -> 0 | CO43: 0 | CP43: 0 | CQ43: 0 | CR43: 0 | CS43: 0 | CT43: 0 | CU43: 0 | CV43: 0 | CW43: =Q43+S43+U43+W43+Y43+AA43+AC43+AE43+AG43+AI43+AK43+AM43+AO43+AQ43+AS43+AU43+AW43+AY43+BA43+BC43+BE43+BG43+BI43+BK43+BM43+BO43+BQ43+BS43+BU43+BW43+BY43+CA43+CC43+CE43+CG43+CI43+CK43+CM43+CO43+CQ43+CS43+CU43 -> 264 | CX43: =R43+T43+V43+X43+Z43+AB43+AD43+AF43+AH43+AJ43+AL43+AN43+AP43+AR43+AT43+AV43+AX43+AZ43+BB43+BD43+BF43+BH43+BJ43+BL43+BN43+BP43+BR43+BT43+BV43+BX43+BZ43+CB43+CD43+CF43+CH43+CJ43+CL43+CN43+CP43+CR43+CT43+CV43 -> 24868.8 | CY43: Rev10-BRADEN-PL12x2000x12000-2tờ | DE43: =IF(CW43>DA43,CW43-DA43,"0") -> 264 | DF43: =IF(CX43>DB43,CX43-DB43,"0") -> 24868.8 | DG43: 45792 | DH43: 140525HN-IBS | DI43: Hùng Nguyên | DJ43: Thép tấm 12x1500x12000 (3 tờ) | DK43: SS400 (Team / chứng chỉ A36) | DL43: 5086.8 | DM43: 45791 | DN43: 54 | DO43: 5086.8 | DP43: 13090.91 | DQ43: =DP43*DO43*1.1 -> 73249925 | DR43: =(DQ43-DS43)/DS43 -> 0.1 | DS43: =DP43*DO43 -> 66590841 | DT43: 45794 | DU43: =SUMIF($I:$I,I43,$DN:$DN) -> 264 | DV43: =SUMIF($I:$I,I43,$DO:$DO) -> 24868.8 | ES43: =SUMIF($I:$I,I43,$EG:$EG) -> 0 | ET43: =SUMIF($I:$I,I43,$EH:$EH) -> 0 | EY43: =DU43+ES43 -> 264 | EZ43: =DV43+ET43 -> 24868.8 | FA43: =DE43-EY43 -> 0 | FB43: =DF43-EZ43 -> 0 | FC43: =IF(FA43<0,"Thừa",IF(FA43=0,"Đủ","Thiếu")) -> Đủ
A44: =IF(I44=I43,"ok","Hiện") -> ok | I44: I90-A13 | J44: Tôn tấm | K44: PL12x1500x12000; PL12x2000x12000; PL12x2000x9000. | L44: ASTM A36 | M44: m2 | DH44: 150725/HN-IBS | DI44: Hùng Nguyên | DJ44: Thép tấm 12x2000x12000 = 2 Tấm A36 | DK44: SS400/Q235B | DL44: 4521.6 | DM44: 45853 | DN44: 48 | DO44: 4521.6 | DP44: 13136.36 | DQ44: =DP44*DO44*1.1 -> 65337102 | DR44: =(DQ44-DS44)/DS44 -> 0.1 | DS44: =DP44*DO44 -> 59397365 | DT44: 45856
A45: =IF(I45=I44,"ok","Hiện") -> ok | I45: I90-A13 | J45: Tôn tấm | K45: PL12x1500x12000; PL12x2000x12000; PL12x2000x9000. | L45: ASTM A36 | M45: m2 | DH45: 210625/HN-IBS | DI45: Hùng Nguyên | DJ45: Thép tấm 12x2000x12000 (3 tờ) | DK45: SS400 | DL45: 6782.4 | DM45: 45829 | DN45: 72 | DO45: 6782.4 | DP45: 13181.82 | DQ45: =DP45*DO45*1.1 -> 98344814 | DR45: =(DQ45-DS45)/DS45 -> 0.1 | DS45: =DP45*DO45 -> 89404376 | DT45: 45832
A46: =IF(I46=I45,"ok","Hiện") -> ok | I46: I90-A13 | J46: Tôn tấm | K46: PL12x1500x12000; PL12x2000x12000; PL12x2000x9000. | L46: ASTM A36 | M46: m2 | DH46: 210625/HN-IBS | DI46: Hùng Nguyên | DJ46: Thép tấm 12x2000x9000 (1 tờ) | DK46: SS400 | DL46: 1695.6 | DM46: 45829 | DN46: 18 | DO46: 1695.6 | DP46: 13181.82 | DQ46: =DP46*DO46*1.1 -> 24586203 | DR46: =(DQ46-DS46)/DS46 -> 0.1 | DS46: =DP46*DO46 -> 22351094 | DT46: 45832
A47: =IF(I47=I46,"ok","Hiện") -> ok | I47: I90-A13 | J47: Tôn tấm | K47: PL12x1500x12000; PL12x2000x12000; PL12x2000x9000. | L47: ASTM A36 | M47: m2 | DH47: 210625/HN-IBS | DI47: Hùng Nguyên | DJ47: Thép tấm 12x2000x12000 (1 tờ) | DK47: SS400 | DL47: 2260.8 | DM47: 45829 | DN47: 24 | DO47: 2260.8 | DP47: 13181.82 | DQ47: =DP47*DO47*1.1 -> 32781605 | DR47: =(DQ47-DS47)/DS47 -> 0.1 | DS47: =DP47*DO47 -> 29801459 | DT47: 45835
A48: =IF(I48=I47,"ok","Hiện") -> ok | I48: I90-A13 | J48: Tôn tấm | K48: PL12x1500x12000; PL12x2000x12000; PL12x2000x9000. | L48: ASTM A36 | M48: m2 | DH48: 190825/HN-IBS | DI48: Hùng Nguyên | DJ48: Thép tấm 12x2000x12000 (2 tờ) | DK48: SS400/Q235B | DL48: 4521.6 | DM48: 45888 | DN48: 48 | DO48: 4521.6 | DP48: 13090.91 | DQ48: =DP48*DO48*1.1 -> 65111045 | DR48: =(DQ48-DS48)/DS48 -> 0.1 | DS48: =DP48*DO48 -> 59191859 | DT48: 45891
A49: =IF(I49=I48,"ok","Hiện") -> Hiện | B49: =CONCATENATE(FC49," Đã đủ") -> Thiếu Đã đủ | C49: =FA49 -> 12 | I49: I90-A14 | J49: Tôn tấm | K49: PL15x1500x12000 | L49: ASTM A36 | M49: m2 | N49: 117.75 | O49: 388.0569 | P49: 45693.7 | S49: 396 | T49: 46629 | W49: 0 | X49: 0 | Y49: 288 | Z49: 33912 | AA49: 126 | AB49: 14836.5 | AC49: 18 | AD49: 2119.5 | AE49: 18 | AF49: 2119.5 | AG49: 0 | AH49: 0 | AI49: =VLOOKUP(I49,'[119]MTO-rev09'!$A:$O,11,0) -> 0 | AJ49: =VLOOKUP(I49,'[119]MTO-rev09'!$A:$O,12,0) -> 0 | AK49: 0 | AL49: 0 | AM49: 36 | AN49: 4239 | AO49: 0 | AP49: 0 | AQ49: 0 | AR49: 0 | AS49: 0 | AT49: 0 | AU49: 0 | AV49: 0 | AW49: 0 | AX49: 0 | AY49: 0 | AZ49: 0 | BC49: 0 | BD49: 0 | BE49: 0 | BF49: 0 | BG49: 0 | BH49: 0 | BI49: 0 | BJ49: 0 | BK49: 0 | BL49: 0 | BM49: 0 | BN49: 0 | BQ49: 0 | BR49: 0 | BS49: 0 | BT49: 0 | BU49: 0 | BV49: 0 | BY49: 0 | BZ49: 0 | CA49: 0 | CB49: 0 | CC49: 0 | CD49: 0 | CE49: =VLOOKUP(I49,[120]REV33!$A:$O,11,0) -> 0 | CF49: =VLOOKUP(I49,[120]REV33!$A:$O,12,0) -> 0 | CO49: 0 | CP49: 0 | CQ49: 0 | CR49: 0 | CS49: 0 | CT49: 0 | CU49: 0 | CV49: 0 | CW49: =Q49+S49+U49+W49+Y49+AA49+AC49+AE49+AG49+AI49+AK49+AM49+AO49+AQ49+AS49+AU49+AW49+AY49+BA49+BC49+BE49+BG49+BI49+BK49+BM49+BO49+BQ49+BS49+BU49+BW49+BY49+CA49+CC49+CE49+CG49+CI49+CK49+CM49+CO49+CQ49+CS49+CU49 -> 882 | CX49: =R49+T49+V49+X49+Z49+AB49+AD49+AF49+AH49+AJ49+AL49+AN49+AP49+AR49+AT49+AV49+AX49+AZ49+BB49+BD49+BF49+BH49+BJ49+BL49+BN49+BP49+BR49+BT49+BV49+BX49+BZ49+CB49+CD49+CF49+CH49+CJ49+CL49+CN49+CP49+CR49+CT49+CV49 -> 103855.5 | CY49: Rev11-BRADEN-PL15x1500x12000-2tờ | DE49: =IF(CW49>DA49,CW49-DA49,"0") -> 882 | DF49: =IF(CX49>DB49,CX49-DB49,"0") -> 103855.5 | DG49: 45792 | DH49: 140525HN-IBS | DI49: Hùng Nguyên | DJ49: Thép tấm 16x1500x12000 | DK49: SS400 (Team / chứng chỉ A36) | DL49: 27129.6 | DM49: 45791 | DN49: 216 | DO49: 27129.6 | DP49: 13363.64 | DQ49: =DP49*DO49*1.1 -> 3.9880523e+08 | DR49: =(DQ49-DS49)/DS49 -> 0.1 | DS49: =DP49*DO49 -> 3.6255021e+08 | DT49: 45797 | DU49: =SUMIF($I:$I,I49,$DN:$DN) -> 870 | DV49: =SUMIF($I:$I,I49,$DO:$DO) -> 109272 | ES49: =SUMIF($I:$I,I49,$EG:$EG) -> 0 | ET49: =SUMIF($I:$I,I49,$EH:$EH) -> 0 | EY49: =DU49+ES49 -> 870 | EZ49: =DV49+ET49 -> 109272 | FA49: =DE49-EY49 -> 12 | FB49: =DF49-EZ49 -> -5416.5 | FC49: =IF(FA49<0,"Thừa",IF(FA49=0,"Đủ","Thiếu")) -> Thiếu
A50: =IF(I50=I49,"ok","Hiện") -> ok | I50: I90-A14 | J50: Tôn tấm | K50: PL15x1500x12000 | L50: ASTM A36 | M50: m2 | DH50: 040625HN-IBS | DI50: Hùng Nguyên | DJ50: Thép tấm 16x1500x12000 = 26 TẤm ASTM A36 | DK50: SS400 | DL50: 58780.8 | DM50: 45812 | DN50: 468 | DO50: 58780.8 | DP50: 13363.64 | DQ50: =DP50*DO50*1.1 -> 8.64078e+08 | DR50: =(DQ50-DS50)/DS50 -> 0.1 | DS50: =DP50*DO50 -> 7.8552545e+08 | DT50: 45817
A51: =IF(I51=I50,"ok","Hiện") -> ok | I51: I90-A14 | J51: Tôn tấm | K51: PL15x1500x12000 | L51: ASTM A36 | M51: m2 | DH51: 210625/HN-IBS | DI51: Hùng Nguyên | DJ51: Thép tấm 16x1500x12000 | DK51: SS400 | DL51: 15825.6 | DM51: 45829 | DN51: 126 | DO51: 15825.6 | DP51: 13363.64 | DQ51: =DP51*DO51*1.1 -> 2.3263638e+08 | DR51: =(DQ51-DS51)/DS51 -> 0.1 | DS51: =DP51*DO51 -> 2.1148762e+08 | DT51: 45838
A52: =IF(I52=I51,"ok","Hiện") -> ok | I52: I90-A14 | J52: Tôn tấm | K52: PL15x1500x12000 | L52: ASTM A36 | M52: m2 | DH52: 210625/HN-IBS | DI52: Hùng Nguyên | DJ52: Thép tấm 16x1500x12000 | DK52: SS400 | DL52: 4521.6 | DM52: 45829 | DN52: 36 | DO52: 4521.6 | DP52: 13363.64 | DQ52: =DP52*DO52*1.1 -> 66467538 | DR52: =(DQ52-DS52)/DS52 -> 0.1 | DS52: =DP52*DO52 -> 60425035 | DT52: 45838
A53: =IF(I53=I52,"ok","Hiện") -> ok | I53: I90-A14 | J53: Tôn tấm | K53: PL15x1500x12000 | L53: ASTM A36 | M53: m2 | DH53: 190825/HN-IBS | DI53: Hùng Nguyên | DJ53: Thép tấm 16x2000x12000 (1 tờ) | DK53: SS400/Q235B | DL53: 3014.4 | DM53: 45888 | DN53: 24 | DO53: 3014.4 | DP53: 13454.55 | DQ53: =DP53*DO53*1.1 -> 44613135 | DR53: =(DQ53-DS53)/DS53 -> 0.1 | DS53: =DP53*DO53 -> 40557396 | DT53: 45891
A54: =IF(I54=I53,"ok","Hiện") -> Hiện | B54: =FC54 -> Đủ | C54: =FA54 -> 0 | I54: I90-A15 | J54: Tôn tấm | K54: PL18x1500x6000 | L54: ASTM A36 | M54: m2 | N54: 141.3 | O54: 7.5583864 | P54: 1068 | S54: 9 | T54: 1271.7 | W54: 0 | X54: 0 | Y54: 0 | Z54: 0 | AA54: 0 | AB54: 0 | AC54: 0 | AD54: 0 | AE54: 0 | AF54: 0 | AG54: 0 | AH54: 0 | AI54: =VLOOKUP(I54,'[119]MTO-rev09'!$A:$O,11,0) -> 0 | AJ54: =VLOOKUP(I54,'[119]MTO-rev09'!$A:$O,12,0) -> 0 | AK54: 0 | AL54: 0 | AO54: 0 | AP54: 0 | AQ54: 0 | AR54: 0 | AS54: 0 | AT54: 0 | AU54: 0 | AV54: 0 | AW54: 0 | AX54: 0 | AY54: 0 | AZ54: 0 | BC54: 0 | BD54: 0 | BE54: 0 | BF54: 0 | BG54: 0 | BH54: 0 | BI54: 0 | BJ54: 0 | BK54: 0 | BL54: 0 | BM54: 0 | BN54: 0 | BQ54: 0 | BR54: 0 | BS54: 0 | BT54: 0 | BU54: 0 | BV54: 0 | BY54: 0 | BZ54: 0 | CA54: 0 | CB54: 0 | CC54: 0 | CD54: 0 | CE54: =VLOOKUP(I54,[120]REV33!$A:$O,11,0) -> 0 | CF54: =VLOOKUP(I54,[120]REV33!$A:$O,12,0) -> 0 | CO54: 0 | CP54: 0 | CQ54: 0 | CR54: 0 | CS54: 0 | CT54: 0 | CU54: 0 | CV54: 0 | CW54: =Q54+S54+U54+W54+Y54+AA54+AC54+AE54+AG54+AI54+AK54+AM54+AO54+AQ54+AS54+AU54+AW54+AY54+BA54+BC54+BE54+BG54+BI54+BK54+BM54+BO54+BQ54+BS54+BU54+BW54+BY54+CA54+CC54+CE54+CG54+CI54+CK54+CM54+CO54+CQ54+CS54+CU54 -> 9 | CX54: =R54+T54+V54+X54+Z54+AB54+AD54+AF54+AH54+AJ54+AL54+AN54+AP54+AR54+AT54+AV54+AX54+AZ54+BB54+BD54+BF54+BH54+BJ54+BL54+BN54+BP54+BR54+BT54+BV54+BX54+BZ54+CB54+CD54+CF54+CH54+CJ54+CL54+CN54+CP54+CR54+CT54+CV54 -> 1271.7 | CY54: Rev01-PL18x1500x6000-1-tờ | DE54: =IF(CW54>DA54,CW54-DA54,"0") -> 9 | DF54: =IF(CX54>DB54,CX54-DB54,"0") -> 1271.7 | DG54: 45792 | DH54: 140525HN-IBS | DI54: Hùng Nguyên | DJ54: Thép tấm 18x1500x6000 | DK54: SS400 (Team / chứng chỉ A36) | DL54: 1271.7 | DM54: 45791 | DN54: 9 | DO54: 1271.7 | DP54: 13545.45 | DQ54: =DP54*DO54*1.1 -> 18948324 | DR54: =(DQ54-DS54)/DS54 -> 0.1 | DS54: =DP54*DO54 -> 17225749 | DT54: 45794 | DU54: =SUMIF($I:$I,I54,$DN:$DN) -> 9 | DV54: =SUMIF($I:$I,I54,$DO:$DO) -> 1271.7 | ES54: =SUMIF($I:$I,I54,$EG:$EG) -> 0 | ET54: =SUMIF($I:$I,I54,$EH:$EH) -> 0 | EY54: =DU54+ES54 -> 9 | EZ54: =DV54+ET54 -> 1271.7 | FA54: =DE54-EY54 -> 0 | FB54: =DF54-EZ54 -> 0 | FC54: =IF(FA54<0,"Thừa",IF(FA54=0,"Đủ","Thiếu")) -> Đủ
A55: =IF(I55=I54,"ok","Hiện") -> Hiện | B55: =FC55 -> Thừa | C55: =FA55 -> -6 | I55: I90-A16 | J55: Tôn tấm | K55: PL20x1500x12000 | L55: ASTM A36 | M55: m2 | N55: 157 | O55: 107.17478 | P55: 16826.44 | S55: 108 | T55: 16956 | W55: 0 | X55: 0 | Y55: 0 | Z55: 0 | AA55: 72 | AB55: 11304 | AC55: 0 | AD55: 0 | AE55: 18 | AF55: 2826 | AG55: 0 | AH55: 0 | AI55: =VLOOKUP(I55,'[119]MTO-rev09'!$A:$O,11,0) -> 0 | AJ55: =VLOOKUP(I55,'[119]MTO-rev09'!$A:$O,12,0) -> 0 | AK55: 72 | AL55: 11304 | AO55: 0 | AP55: 0 | AQ55: 0 | AR55: 0 | AS55: 0 | AT55: 0 | AU55: 0 | AV55: 0 | AW55: 0 | AX55: 0 | AY55: 0 | AZ55: 0 | BC55: 0 | BD55: 0 | BE55: 0 | BF55: 0 | BG55: 0 | BH55: 0 | BI55: 0 | BJ55: 0 | BK55: 0 | BL55: 0 | BM55: 0 | BN55: 0 | BQ55: 0 | BR55: 0 | BS55: 0 | BT55: 0 | BU55: 0 | BV55: 0 | BY55: 0 | BZ55: 0 | CA55: 0 | CB55: 0 | CC55: 0 | CD55: 0 | CE55: =VLOOKUP(I55,[120]REV33!$A:$O,11,0) -> 0 | CF55: =VLOOKUP(I55,[120]REV33!$A:$O,12,0) -> 0 | CO55: 0 | CP55: 0 | CQ55: 0 | CR55: 0 | CS55: 0 | CT55: 0 | CU55: 0 | CV55: 0 | CW55: =Q55+S55+U55+W55+Y55+AA55+AC55+AE55+AG55+AI55+AK55+AM55+AO55+AQ55+AS55+AU55+AW55+AY55+BA55+BC55+BE55+BG55+BI55+BK55+BM55+BO55+BQ55+BS55+BU55+BW55+BY55+CA55+CC55+CE55+CG55+CI55+CK55+CM55+CO55+CQ55+CS55+CU55 -> 270 | CX55: =R55+T55+V55+X55+Z55+AB55+AD55+AF55+AH55+AJ55+AL55+AN55+AP55+AR55+AT55+AV55+AX55+AZ55+BB55+BD55+BF55+BH55+BJ55+BL55+BN55+BP55+BR55+BT55+BV55+BX55+BZ55+CB55+CD55+CF55+CH55+CJ55+CL55+CN55+CP55+CR55+CT55+CV55 -> 42390 | CY55: Rev10-BRADEN-PL20x1500x12000-4tờ | DE55: =IF(CW55>DA55,CW55-DA55,"0") -> 270 | DF55: =IF(CX55>DB55,CX55-DB55,"0") -> 42390 | DG55: 45792 | DH55: 140525HN-IBS | DI55: Hùng Nguyên | DJ55: Thép tấm 20x1500x12000 | DK55: SS400 (Team / chứng chỉ A36) | DL55: 8478 | DM55: 45791 | DN55: 54 | DO55: 8478 | DP55: 13545.45 | DQ55: =DP55*DO55*1.1 -> 1.2632216e+08 | DR55: =(DQ55-DS55)/DS55 -> 0.1 | DS55: =DP55*DO55 -> 1.1483833e+08 | DT55: 45794 | DU55: =SUMIF($I:$I,I55,$DN:$DN) -> 276 | DV55: =SUMIF($I:$I,I55,$DO:$DO) -> 43332 | ES55: =SUMIF($I:$I,I55,$EG:$EG) -> 0 | ET55: =SUMIF($I:$I,I55,$EH:$EH) -> 0 | EY55: =DU55+ES55 -> 276 | EZ55: =DV55+ET55 -> 43332 | FA55: =DE55-EY55 -> -6 | FB55: =DF55-EZ55 -> -942 | FC55: =IF(FA55<0,"Thừa",IF(FA55=0,"Đủ","Thiếu")) -> Thừa
A56: =IF(I56=I55,"ok","Hiện") -> ok | I56: I90-A16 | J56: Tôn tấm | K56: PL20x1500x12000 | L56: ASTM A36 | M56: m2 | DH56: 150725/HN-IBS | DI56: Hùng Nguyên | DJ56: Thép tấm 20x2000x12000 = 1 Tấm A36 | DK56: SS400/Q235B | DL56: 3768 | DM56: 45853 | DN56: 24 | DO56: 3768 | DP56: 13590.91 | DQ56: =DP56*DO56*1.1 -> 56331604 | DR56: =(DQ56-DS56)/DS56 -> 0.1 | DS56: =DP56*DO56 -> 51210549 | DT56: 45856
A57: =IF(I57=I56,"ok","Hiện") -> ok | I57: I90-A16 | J57: Tôn tấm | K57: PL20x1500x12000 | L57: ASTM A36 | M57: m2 | DH57: 210625/HN-IBS | DI57: Hùng Nguyên | DJ57: Thép tấm 20x1500x12000 | DK57: SS400 | DL57: 11304 | DM57: 45829 | DN57: 72 | DO57: 11304 | DP57: 13454.55 | DQ57: =DP57*DO57*1.1 -> 1.6729926e+08 | DR57: =(DQ57-DS57)/DS57 -> 0.1 | DS57: =DP57*DO57 -> 1.5209023e+08 | DT57: 45838
A58: =IF(I58=I57,"ok","Hiện") -> ok | I58: I90-A16 | J58: Tôn tấm | K58: PL20x1500x12000 | L58: ASTM A36 | M58: m2 | DH58: 040625HN-IBS | DI58: Hùng Nguyên | DJ58: Thép tấm 20x1500x12000 = 3 TẤm ASTM A36 | DK58: SS400 | DL58: 8478 | DM58: 45812 | DN58: 54 | DO58: 8478 | DP58: 13545.45 | DQ58: =DP58*DO58*1.1 -> 1.2632216e+08 | DR58: =(DQ58-DS58)/DS58 -> 0.1 | DS58: =DP58*DO58 -> 1.1483833e+08 | DT58: 45819
A59: =IF(I59=I58,"ok","Hiện") -> ok | I59: I90-A16 | J59: Tôn tấm | K59: PL20x1500x12000 | L59: ASTM A36 | M59: m2 | DH59: 190825/HN-IBS | DI59: Hùng Nguyên | DJ59: Thép tấm 20x1500x12000 (4 tờ) | DK59: SS400/Q235B | DL59: 11304 | DM59: 45888 | DN59: 72 | DO59: 11304 | DP59: 14090.91 | DQ59: =DP59*DO59*1.1 -> 1.7521201e+08 | DR59: =(DQ59-DS59)/DS59 -> 0.1 | DS59: =DP59*DO59 -> 1.5928365e+08 | DT59: 45891
A60: =IF(I60=I59,"ok","Hiện") -> Hiện | B60: =FC60 -> Thừa | C60: =FA60 -> -4 | D60: Dùng cùng tờ dự án 097 (khổ tồn 2mx11m) | I60: I90-A17 | J60: Tôn tấm | K60: PL25x1500x12000 | L60: ASTM A36 | M60: m2 | N60: 196.25 | O60: 16.954395 | P60: 3327.3 | S60: 18 | T60: 3532.5 | W60: 0 | X60: 0 | Y60: 0 | Z60: 0 | AA60: 18 | AB60: 3532.5 | AC60: 0 | AD60: 0 | AE60: 36 | AF60: 7065 | AG60: 0 | AH60: 0 | AI60: =VLOOKUP(I60,'[119]MTO-rev09'!$A:$O,11,0) -> 0 | AJ60: =VLOOKUP(I60,'[119]MTO-rev09'!$A:$O,12,0) -> 0 | AK60: 0 | AL60: 0 | AO60: 30 | AP60: 5887.5 | AQ60: 0 | AR60: 0 | AS60: 0 | AT60: 0 | AU60: 0 | AV60: 0 | AW60: 10 | AX60: 1962.5 | AY60: 0 | AZ60: 0 | BA60: 44 | BB60: 8635 | BC60: 0 | BD60: 0 | BE60: 0 | BF60: 0 | BG60: 0 | BH60: 0 | BI60: 0 | BJ60: 0 | BK60: 0 | BL60: 0 | BM60: 0 | BN60: 0 | BQ60: 0 | BR60: 0 | BS60: 0 | BT60: 0 | BU60: 0 | BV60: 0 | BY60: 0 | BZ60: 0 | CA60: 0 | CB60: 0 | CC60: 0 | CD60: 0 | CE60: =VLOOKUP(I60,[120]REV33!$A:$O,11,0) -> 0 | CF60: =VLOOKUP(I60,[120]REV33!$A:$O,12,0) -> 0 | CO60: 0 | CP60: 0 | CQ60: 0 | CR60: 0 | CS60: 0 | CT60: 0 | CU60: 0 | CV60: 0 | CW60: =Q60+S60+U60+W60+Y60+AA60+AC60+AE60+AG60+AI60+AK60+AM60+AO60+AQ60+AS60+AU60+AW60+AY60+BA60+BC60+BE60+BG60+BI60+BK60+BM60+BO60+BQ60+BS60+BU60+BW60+BY60+CA60+CC60+CE60+CG60+CI60+CK60+CM60+CO60+CQ60+CS60+CU60 -> 156 | CX60: =R60+T60+V60+X60+Z60+AB60+AD60+AF60+AH60+AJ60+AL60+AN60+AP60+AR60+AT60+AV60+AX60+AZ60+BB60+BD60+BF60+BH60+BJ60+BL60+BN60+BP60+BR60+BT60+BV60+BX60+BZ60+CB60+CD60+CF60+CH60+CJ60+CL60+CN60+CP60+CR60+CT60+CV60 -> 30615 | CY60: Rev18-IBS bổ sung loại khổ 2x12m | DA60: =1.5*12+2*11 -> 40 | DB60: =DA60*N60 -> 7850 | DD60: Hàng tồn/ Lấy hàng dự án 097 sáng | DE60: =IF(CW60>DA60,CW60-DA60,"0") -> 116 | DF60: =IF(CX60>DB60,CX60-DB60,"0") -> 22765 | DG60: 45792 | DH60: 214/2025/CTC-IBS | DI60: City com | DJ60: Thép tấm 25x2000x12000 (1 tờ) | DK60: A36 | DL60: 4710 | DM60: 45783 | DN60: 24 | DO60: 4710 | DP60: 13909.09 | DQ60: =DP60*DO60*1.1 -> 72062995 | DR60: =(DQ60-DS60)/DS60 -> 0.1 | DS60: =DP60*DO60 -> 65511814 | DT60: 45835 | DU60: =SUMIF($I:$I,I60,$DN:$DN) -> 120 | DV60: =SUMIF($I:$I,I60,$DO:$DO) -> 23550 | ES60: =SUMIF($I:$I,I60,$EG:$EG) -> 0 | ET60: =SUMIF($I:$I,I60,$EH:$EH) -> 0 | EY60: =DU60+ES60 -> 120 | EZ60: =DV60+ET60 -> 23550 | FA60: =DE60-EY60 -> -4 | FB60: =DF60-EZ60 -> -785 | FC60: =IF(FA60<0,"Thừa",IF(FA60=0,"Đủ","Thiếu")) -> Thừa
A61: =IF(I61=I60,"ok","Hiện") -> ok | I61: I90-A17 | J61: Tôn tấm | K61: PL25x1500x12000 | L61: ASTM A36 | M61: m2 | DH61: 150725/HN-IBS | DI61: Hùng Nguyên | DJ61: Thép tấm 25x2000x12000 = 1 Tấm A36 | DK61: SS400/Q235B | DL61: 4710 | DM61: 45853 | DN61: 24 | DO61: 4710 | DP61: 14090.91 | DQ61: =DP61*DO61*1.1 -> 73005005 | DR61: =(DQ61-DS61)/DS61 -> 0.1 | DS61: =DP61*DO61 -> 66368186 | DT61: 45856
A62: =IF(I62=I61,"ok","Hiện") -> ok | I62: I90-A17 | J62: Tôn tấm | K62: PL25x1500x12000 | L62: ASTM A36 | M62: m2 | DH62: 210625/HN-IBS | DI62: Hùng Nguyên | DJ62: Thép tấm 25x2000x12000 | DK62: A36/SS400/Q235B | DL62: 4710 | DM62: 45829 | DN62: 24 | DO62: 4710 | DP62: 14136.36 | DQ62: =DP62*DO62*1.1 -> 73240481 | DR62: =(DQ62-DS62)/DS62 -> 0.1 | DS62: =DP62*DO62 -> 66582256 | DT62: 45832
A63: =IF(I63=I62,"ok","Hiện") -> ok | I63: I90-A17 | J63: Tôn tấm | K63: PL25x1500x12000 | L63: ASTM A36 | M63: m2 | DH63: 15.09.2025/APEC-IBS | DI63: APEC | DJ63: Thép tấm 25x2000x12000 | DK63: A36 | DL63: 9420 | DM63: 45915 | DN63: 48 | DO63: 9420 | DP63: 14909.09 | DQ63: =DP63*DO63*1.1 -> 1.5448799e+08 | DR63: =(DQ63-DS63)/DS63 -> 0.1 | DS63: =DP63*DO63 -> 1.4044363e+08
A64: =IF(I64=I63,"ok","Hiện") -> Hiện | B64: =FC64 -> Đủ | C64: =FA64 -> 0 | I64: I90-A18 | J64: Tôn tấm | K64: PL30x2000x6000 | L64: ASTM A36 | M64: m2 | N64: 235.5 | O64: 27.252654 | P64: 6418 | S64: 24 | T64: 5652 | W64: 0 | X64: 0 | Y64: 84 | Z64: 19782 | AA64: 48 | AB64: 11304 | AC64: 0 | AD64: 0 | AE64: 0 | AF64: 0 | AG64: 0 | AH64: 0 | AI64: =VLOOKUP(I64,'[119]MTO-rev09'!$A:$O,11,0) -> 0 | AJ64: =VLOOKUP(I64,'[119]MTO-rev09'!$A:$O,12,0) -> 0 | AK64: 0 | AL64: 0 | AO64: 0 | AP64: 0 | AQ64: 0 | AR64: 0 | AS64: 0 | AT64: 0 | AU64: 0 | AV64: 0 | AW64: 0 | AX64: 0 | AY64: 0 | AZ64: 0 | BC64: 0 | BD64: 0 | BE64: 0 | BF64: 0 | BG64: 0 | BH64: 0 | BI64: 0 | BJ64: 0 | BK64: 0 | BL64: 0 | BM64: 0 | BN64: 0 | BQ64: 0 | BR64: 0 | BS64: 0 | BT64: 0 | BU64: 0 | BV64: 0 | BY64: 0 | BZ64: 0 | CA64: 0 | CB64: 0 | CC64: 0 | CD64: 0 | CE64: =VLOOKUP(I64,[120]REV33!$A:$O,11,0) -> 0 | CF64: =VLOOKUP(I64,[120]REV33!$A:$O,12,0) -> 0 | CO64: 0 | CP64: 0 | CQ64: 0 | CR64: 0 | CS64: 0 | CT64: 0 | CU64: 0 | CV64: 0 | CW64: =Q64+S64+U64+W64+Y64+AA64+AC64+AE64+AG64+AI64+AK64+AM64+AO64+AQ64+AS64+AU64+AW64+AY64+BA64+BC64+BE64+BG64+BI64+BK64+BM64+BO64+BQ64+BS64+BU64+BW64+BY64+CA64+CC64+CE64+CG64+CI64+CK64+CM64+CO64+CQ64+CS64+CU64 -> 156 | CX64: =R64+T64+V64+X64+Z64+AB64+AD64+AF64+AH64+AJ64+AL64+AN64+AP64+AR64+AT64+AV64+AX64+AZ64+BB64+BD64+BF64+BH64+BJ64+BL64+BN64+BP64+BR64+BT64+BV64+BX64+BZ64+CB64+CD64+CF64+CH64+CJ64+CL64+CN64+CP64+CR64+CT64+CV64 -> 36738 | CY64: Rev05-BRADEN-PL30x2000x6000-4tờ | DE64: =IF(CW64>DA64,CW64-DA64,"0") -> 156 | DF64: =IF(CX64>DB64,CX64-DB64,"0") -> 36738 | DG64: 45792 | DH64: 140525HN-IBS | DI64: Hùng Nguyên | DJ64: Thép tấm 30x2000x12000 | DK64: A36 | DL64: 5652 | DM64: 45791 | DN64: 24 | DO64: 5652 | DP64: 14090.91 | DQ64: =DP64*DO64*1.1 -> 87606006 | DR64: =(DQ64-DS64)/DS64 -> 0.1 | DS64: =DP64*DO64 -> 79641823 | DT64: 45797 | DU64: =SUMIF($I:$I,I64,$DN:$DN) -> 156 | DV64: =SUMIF($I:$I,I64,$DO:$DO) -> 36738 | ES64: =SUMIF($I:$I,I64,$EG:$EG) -> 0 | ET64: =SUMIF($I:$I,I64,$EH:$EH) -> 0 | EY64: =DU64+ES64 -> 156 | EZ64: =DV64+ET64 -> 36738 | FA64: =DE64-EY64 -> 0 | FB64: =DF64-EZ64 -> 0 | FC64: =IF(FA64<0,"Thừa",IF(FA64=0,"Đủ","Thiếu")) -> Đủ
A65: =IF(I65=I64,"ok","Hiện") -> ok | I65: I90-A18 | J65: Tôn tấm | K65: PL30x2000x6000 | L65: ASTM A36 | M65: m2 | DH65: 040625HN-IBS | DI65: Hùng Nguyên | DJ65: Thép tấm 30x2000x12000 = 3.5 TẤm ASTM A36 | DK65: Q235B/A36/SS400 | DL65: 19782 | DM65: 45812 | DN65: 84 | DO65: 19782 | DP65: 14090.91 | DQ65: =DP65*DO65*1.1 -> 3.0662102e+08 | DR65: =(DQ65-DS65)/DS65 -> 0.1 | DS65: =DP65*DO65 -> 2.7874638e+08 | DT65: 45819
A66: =IF(I66=I65,"ok","Hiện") -> ok | I66: I90-A18 | J66: Tôn tấm | K66: PL30x2000x6000 | L66: ASTM A36 | M66: m2 | DH66: 210625/HN-IBS | DI66: Hùng Nguyên | DJ66: Thép tấm 30x2000x12000 | DK66: A36/SS400/Q235B | DL66: 11304 | DM66: 45829 | DN66: 48 | DO66: 11304 | DP66: 14136.36 | DQ66: =DP66*DO66*1.1 -> 1.7577715e+08 | DR66: =(DQ66-DS66)/DS66 -> 0.1 | DS66: =DP66*DO66 -> 1.5979741e+08 | DT66: 45832
A67: =IF(I67=I66,"ok","Hiện") -> Hiện | B67: =FC67 -> Đủ | C67: =FA67 -> 0 | I67: I90-A19 | J67: Tôn tấm | K67: PL30x2000x6000; PL30x2000x12000 | L67: ASTM A36 | M67: m2 | N67: 235.5 | S67: 12 | T67: 2826 | W67: 0 | X67: 0 | Y67: 0 | Z67: 0 | AA67: 0 | AB67: 0 | AC67: 0 | AD67: 0 | AE67: 24 | AF67: 5652 | AG67: 0 | AH67: 0 | AI67: =VLOOKUP(I67,'[119]MTO-rev09'!$A:$O,11,0) -> 0 | AJ67: =VLOOKUP(I67,'[119]MTO-rev09'!$A:$O,12,0) -> 0 | AK67: 0 | AL67: 0 | AO67: 0 | AP67: 0 | AQ67: 0 | AR67: 0 | AS67: 0 | AT67: 0 | AU67: 0 | AV67: 0 | AW67: 0 | AX67: 0 | AY67: 0 | AZ67: 0 | BC67: 0 | BD67: 0 | BE67: 0 | BF67: 0 | BG67: 0 | BH67: 0 | BI67: 0 | BJ67: 0 | BK67: 0 | BL67: 0 | BM67: 0 | BN67: 0 | BQ67: 0 | BR67: 0 | BS67: 0 | BT67: 0 | BU67: 0 | BV67: 0 | BY67: 0 | BZ67: 0 | CA67: 0 | CB67: 0 | CC67: 0 | CD67: 0 | CE67: =VLOOKUP(I67,[120]REV33!$A:$O,11,0) -> 0 | CF67: =VLOOKUP(I67,[120]REV33!$A:$O,12,0) -> 0 | CO67: 0 | CP67: 0 | CQ67: 0 | CR67: 0 | CS67: 0 | CT67: 0 | CU67: 0 | CV67: 0 | CW67: =Q67+S67+U67+W67+Y67+AA67+AC67+AE67+AG67+AI67+AK67+AM67+AO67+AQ67+AS67+AU67+AW67+AY67+BA67+BC67+BE67+BG67+BI67+BK67+BM67+BO67+BQ67+BS67+BU67+BW67+BY67+CA67+CC67+CE67+CG67+CI67+CK67+CM67+CO67+CQ67+CS67+CU67 -> 36 | CX67: =R67+T67+V67+X67+Z67+AB67+AD67+AF67+AH67+AJ67+AL67+AN67+AP67+AR67+AT67+AV67+AX67+AZ67+BB67+BD67+BF67+BH67+BJ67+BL67+BN67+BP67+BR67+BT67+BV67+BX67+BZ67+CB67+CD67+CF67+CH67+CJ67+CL67+CN67+CP67+CR67+CT67+CV67 -> 8478 | CY67: Rev07-BRADEN-PL30x2000x12000-1tờ | DE67: =IF(CW67>DA67,CW67-DA67,"0") -> 36 | DF67: =IF(CX67>DB67,CX67-DB67,"0") -> 8478 | DG67: 45792 | DH67: 140525HN-IBS | DI67: Hùng Nguyên | DJ67: Thép tấm 30x2000x6000 | DK67: A36 | DL67: 2826 | DM67: 45791 | DN67: 12 | DO67: 2826 | DP67: 14090.91 | DQ67: =DP67*DO67*1.1 -> 43803003 | DR67: =(DQ67-DS67)/DS67 -> 0.1 | DS67: =DP67*DO67 -> 39820912 | DT67: 45800 | DU67: =SUMIF($I:$I,I67,$DN:$DN) -> 36 | DV67: =SUMIF($I:$I,I67,$DO:$DO) -> 8478 | ES67: =SUMIF($I:$I,I67,$EG:$EG) -> 0 | ET67: =SUMIF($I:$I,I67,$EH:$EH) -> 0 | EY67: =DU67+ES67 -> 36 | EZ67: =DV67+ET67 -> 8478 | FA67: =DE67-EY67 -> 0 | FB67: =DF67-EZ67 -> 0 | FC67: =IF(FA67<0,"Thừa",IF(FA67=0,"Đủ","Thiếu")) -> Đủ
A68: =IF(I68=I67,"ok","Hiện") -> ok | I68: I90-A19 | J68: Tôn tấm | K68: PL30x2000x6000; PL30x2000x12000 | L68: ASTM A36 | M68: m2 | DH68: 150725/HN-IBS | DI68: Hùng Nguyên | DJ68: Thép tấm 30x2000x12000 = 1 Tấm A36 | DK68: SS400/Q235B | DL68: 5652 | DM68: 45853 | DN68: 24 | DO68: 5652 | DP68: 14090.91 | DQ68: =DP68*DO68*1.1 -> 87606006 | DR68: =(DQ68-DS68)/DS68 -> 0.1 | DS68: =DP68*DO68 -> 79641823 | DT68: 45856
A69: =IF(I69=I68,"ok","Hiện") -> Hiện | B69: =FC69 -> Đủ | C69: =FA69 -> 0 | I69: I90-A20 | J69: Tôn tấm | K69: PL35x2000x6000 | L69: ASTM A36 | M69: m2 | N69: 274.75 | O69: 33.579618 | P69: 9226 | S69: 36 | T69: 9891 | W69: 0 | X69: 0 | Y69: 0 | Z69: 0 | AA69: 36 | AB69: 9891 | AC69: 0 | AD69: 0 | AE69: 0 | AF69: 0 | AG69: 0 | AH69: 0 | AI69: =VLOOKUP(I69,'[119]MTO-rev09'!$A:$O,11,0) -> 0 | AJ69: =VLOOKUP(I69,'[119]MTO-rev09'!$A:$O,12,0) -> 0 | AK69: 12 | AL69: 3297 | AO69: 0 | AP69: 0 | AQ69: 0 | AR69: 0 | AS69: 0 | AT69: 0 | AU69: 0 | AV69: 0 | AW69: 0 | AX69: 0 | AY69: 0 | AZ69: 0 | BC69: 0 | BD69: 0 | BE69: 0 | BF69: 0 | BG69: 0 | BH69: 0 | BI69: 0 | BJ69: 0 | BK69: 0 | BL69: 0 | BM69: 0 | BN69: 0 | BQ69: 0 | BR69: 0 | BS69: 0 | BT69: 0 | BU69: 0 | BV69: 0 | BY69: 0 | BZ69: 0 | CA69: 0 | CB69: 0 | CC69: 0 | CD69: 0 | CE69: =VLOOKUP(I69,[120]REV33!$A:$O,11,0) -> 0 | CF69: =VLOOKUP(I69,[120]REV33!$A:$O,12,0) -> 0 | CO69: 0 | CP69: 0 | CQ69: 0 | CR69: 0 | CS69: 0 | CT69: 0 | CU69: 0 | CV69: 0 | CW69: =Q69+S69+U69+W69+Y69+AA69+AC69+AE69+AG69+AI69+AK69+AM69+AO69+AQ69+AS69+AU69+AW69+AY69+BA69+BC69+BE69+BG69+BI69+BK69+BM69+BO69+BQ69+BS69+BU69+BW69+BY69+CA69+CC69+CE69+CG69+CI69+CK69+CM69+CO69+CQ69+CS69+CU69 -> 84 | CX69: =R69+T69+V69+X69+Z69+AB69+AD69+AF69+AH69+AJ69+AL69+AN69+AP69+AR69+AT69+AV69+AX69+AZ69+BB69+BD69+BF69+BH69+BJ69+BL69+BN69+BP69+BR69+BT69+BV69+BX69+BZ69+CB69+CD69+CF69+CH69+CJ69+CL69+CN69+CP69+CR69+CT69+CV69 -> 23079 | CY69: Rev05-BRADEN-PL35x2000x6000-4tờ | DE69: =IF(CW69>DA69,CW69-DA69,"0") -> 84 | DF69: =IF(CX69>DB69,CX69-DB69,"0") -> 23079 | DG69: 45792 | DH69: 140525HN-IBS | DI69: Hùng Nguyên | DJ69: Thép tấm 35x2000x6000 | DK69: A36 | DL69: 9891 | DM69: 45791 | DN69: 36 | DO69: 9891 | DP69: 14363.64 | DQ69: =DP69*DO69*1.1 -> 1.5627784e+08 | DR69: =(DQ69-DS69)/DS69 -> 0.1 | DS69: =DP69*DO69 -> 1.4207076e+08 | DT69: 45797 | DU69: =SUMIF($I:$I,I69,$DN:$DN) -> 84 | DV69: =SUMIF($I:$I,I69,$DO:$DO) -> 23079 | ES69: =SUMIF($I:$I,I69,$EG:$EG) -> 0 | ET69: =SUMIF($I:$I,I69,$EH:$EH) -> 0 | EY69: =DU69+ES69 -> 84 | EZ69: =DV69+ET69 -> 23079 | FA69: =DE69-EY69 -> 0 | FB69: =DF69-EZ69 -> 0 | FC69: =IF(FA69<0,"Thừa",IF(FA69=0,"Đủ","Thiếu")) -> Đủ
A70: =IF(I70=I69,"ok","Hiện") -> ok | I70: I90-A20 | J70: Tôn tấm | K70: PL35x2000x6000 | L70: ASTM A36 | M70: m2 | DH70: 210625/HN-IBS | DI70: Hùng Nguyên | DJ70: Thép tấm 35x2000x12000 | DK70: A36/SS400 | DL70: 9891 | DM70: 45829 | DN70: 36 | DO70: 9891 | DP70: 14363.64 | DQ70: =DP70*DO70*1.1 -> 1.5627784e+08 | DR70: =(DQ70-DS70)/DS70 -> 0.1 | DS70: =DP70*DO70 -> 1.4207076e+08 | DT70: 45832
A71: =IF(I71=I70,"ok","Hiện") -> ok | I71: I90-A20 | J71: Tôn tấm | K71: PL35x2000x6000 | L71: ASTM A36 | M71: m2 | DH71: 190825/HN-IBS | DI71: Hùng Nguyên | DJ71: Thép tấm 35x2000x6000 (1 tờ) | DK71: SS400/Q235B | DL71: 3297 | DM71: 45888 | DN71: 12 | DO71: 3297 | DP71: 14363.64 | DQ71: =DP71*DO71*1.1 -> 52092613 | DR71: =(DQ71-DS71)/DS71 -> 0.1 | DS71: =DP71*DO71 -> 47356921 | DT71: 45891
A72: =IF(I72=I71,"ok","Hiện") -> Hiện | B72: =FC72 -> Thừa | C72: =FA72 -> -1 | I72: I90-A21 | J72: Tôn tấm | K72: PL45x2000x4500; PL45x2000x7000 | L72: ASTM A36 | M72: m2 | N72: 353.25 | O72: 7.8303751 | P72: 2766.08 | S72: 9 | T72: 3179.25 | W72: 0 | X72: 0 | Y72: 0 | Z72: 0 | AA72: 14 | AB72: 4945.5 | AC72: 0 | AD72: 0 | AE72: 0 | AF72: 0 | AG72: 0 | AH72: 0 | AI72: =VLOOKUP(I72,'[119]MTO-rev09'!$A:$O,11,0) -> 0 | AJ72: =VLOOKUP(I72,'[119]MTO-rev09'!$A:$O,12,0) -> 0 | AK72: 0 | AL72: 0 | AO72: 0 | AP72: 0 | AQ72: 0 | AR72: 0 | AS72: 0 | AT72: 0 | AU72: 0 | AV72: 0 | AW72: 0 | AX72: 0 | AY72: 0 | AZ72: 0 | BC72: 0 | BD72: 0 | BE72: 0 | BF72: 0 | BG72: 0 | BH72: 0 | BI72: 0 | BJ72: 0 | BK72: 0 | BL72: 0 | BM72: 0 | BN72: 0 | BQ72: 0 | BR72: 0 | BS72: 0 | BT72: 0 | BU72: 0 | BV72: 0 | BY72: 0 | BZ72: 0 | CA72: 0 | CB72: 0 | CC72: 0 | CD72: 0 | CE72: =VLOOKUP(I72,[120]REV33!$A:$O,11,0) -> 0 | CF72: =VLOOKUP(I72,[120]REV33!$A:$O,12,0) -> 0 | CO72: 0 | CP72: 0 | CQ72: 0 | CR72: 0 | CS72: 0 | CT72: 0 | CU72: 0 | CV72: 0 | CW72: =Q72+S72+U72+W72+Y72+AA72+AC72+AE72+AG72+AI72+AK72+AM72+AO72+AQ72+AS72+AU72+AW72+AY72+BA72+BC72+BE72+BG72+BI72+BK72+BM72+BO72+BQ72+BS72+BU72+BW72+BY72+CA72+CC72+CE72+CG72+CI72+CK72+CM72+CO72+CQ72+CS72+CU72 -> 23 | CX72: =R72+T72+V72+X72+Z72+AB72+AD72+AF72+AH72+AJ72+AL72+AN72+AP72+AR72+AT72+AV72+AX72+AZ72+BB72+BD72+BF72+BH72+BJ72+BL72+BN72+BP72+BR72+BT72+BV72+BX72+BZ72+CB72+CD72+CF72+CH72+CJ72+CL72+CN72+CP72+CR72+CT72+CV72 -> 8124.75 | CY72: Rev05-BRADEN-PL50x2000x7000-1tờ | DE72: =IF(CW72>DA72,CW72-DA72,"0") -> 23 | DF72: =IF(CX72>DB72,CX72-DB72,"0") -> 8124.75 | DG72: 45792 | DH72: 0606.HĐKT/TCN-IBS/2025 | DI72: Thép công nghiệp Hà Nội | DJ72: Thép tấm 45x2000x12000mm | DK72: A36 | DL72: 8500 | DM72: 1 | DN72: 24 | DO72: 8500 | DP72: 14728 | DQ72: =DP72*DO72*1.1 -> 137706800 | DR72: =(DQ72-DS72)/DS72 -> 0.1 | DS72: =DP72*DO72 -> 125188000 | DT72: 45828 | DU72: =SUMIF($I:$I,I72,$DN:$DN) -> 24 | DV72: =SUMIF($I:$I,I72,$DO:$DO) -> 8500 | ES72: =SUMIF($I:$I,I72,$EG:$EG) -> 0 | ET72: =SUMIF($I:$I,I72,$EH:$EH) -> 0 | EY72: =DU72+ES72 -> 24 | EZ72: =DV72+ET72 -> 8500 | FA72: =DE72-EY72 -> -1 | FB72: =DF72-EZ72 -> -375.25 | FC72: =IF(FA72<0,"Thừa",IF(FA72=0,"Đủ","Thiếu")) -> Thừa
A73: =IF(I73=I72,"ok","Hiện") -> Hiện | B73: =FC73 -> Thừa | C73: =FA73 -> -0.8 | I73: I90-A22 | J73: Tôn tấm | K73: PL50x2000x4600; PL50x2000x7000 | L73: ASTM A36 | M73: m2 | N73: 392.5 | O73: 7.3192357 | P73: 2872.8 | S73: 0 | T73: 0 | W73: 18.2 | X73: 7143.5 | Y73: -9 | Z73: -3532.5 | AA73: 14 | AB73: 5495 | AC73: 0 | AD73: 0 | AE73: 0 | AF73: 0 | AG73: 0 | AH73: 0 | AI73: =VLOOKUP(I73,'[119]MTO-rev09'!$A:$O,11,0) -> 0 | AJ73: =VLOOKUP(I73,'[119]MTO-rev09'!$A:$O,12,0) -> 0 | AK73: 0 | AL73: 0 | AO73: 0 | AP73: 0 | AQ73: 0 | AR73: 0 | AS73: 0 | AT73: 0 | AU73: 0 | AV73: 0 | AW73: 0 | AX73: 0 | AY73: 0 | AZ73: 0 | BC73: 0 | BD73: 0 | BE73: 0 | BF73: 0 | BG73: 0 | BH73: 0 | BI73: 0 | BJ73: 0 | BK73: 0 | BL73: 0 | BM73: 0 | BN73: 0 | BQ73: 0 | BR73: 0 | BS73: 0 | BT73: 0 | BU73: 0 | BV73: 0 | BY73: 0 | BZ73: 0 | CA73: 0 | CB73: 0 | CC73: 0 | CD73: 0 | CE73: =VLOOKUP(I73,[120]REV33!$A:$O,11,0) -> 0 | CF73: =VLOOKUP(I73,[120]REV33!$A:$O,12,0) -> 0 | CO73: 0 | CP73: 0 | CQ73: 0 | CR73: 0 | CS73: 0 | CT73: 0 | CU73: 0 | CV73: 0 | CW73: =Q73+S73+U73+W73+Y73+AA73+AC73+AE73+AG73+AI73+AK73+AM73+AO73+AQ73+AS73+AU73+AW73+AY73+BA73+BC73+BE73+BG73+BI73+BK73+BM73+BO73+BQ73+BS73+BU73+BW73+BY73+CA73+CC73+CE73+CG73+CI73+CK73+CM73+CO73+CQ73+CS73+CU73 -> 23.2 | CX73: =R73+T73+V73+X73+Z73+AB73+AD73+AF73+AH73+AJ73+AL73+AN73+AP73+AR73+AT73+AV73+AX73+AZ73+BB73+BD73+BF73+BH73+BJ73+BL73+BN73+BP73+BR73+BT73+BV73+BX73+BZ73+CB73+CD73+CF73+CH73+CJ73+CL73+CN73+CP73+CR73+CT73+CV73 -> 9106 | CY73: Rev05-BRADEN-PL50x2000x7000-1tờ: Rev01-PL50x2000x4600-1tờ | DE73: =IF(CW73>DA73,CW73-DA73,"0") -> 23.2 | DF73: =IF(CX73>DB73,CX73-DB73,"0") -> 9106 | DG73: 45792 | DH73: 140525HN-IBS | DI73: Hùng Nguyên | DJ73: Thép tấm 50x2000x6000 | DK73: A36 | DL73: 4710 | DM73: 45791 | DN73: 12 | DO73: 4710 | DP73: 14363.64 | DQ73: =DP73*DO73*1.1 -> 74418019 | DR73: =(DQ73-DS73)/DS73 -> 0.1 | DS73: =DP73*DO73 -> 67652744 | DT73: 45794 | DU73: =SUMIF($I:$I,I73,$DN:$DN) -> 24 | DV73: =SUMIF($I:$I,I73,$DO:$DO) -> 9420 | ES73: =SUMIF($I:$I,I73,$EG:$EG) -> 0 | ET73: =SUMIF($I:$I,I73,$EH:$EH) -> 0 | EY73: =DU73+ES73 -> 24 | EZ73: =DV73+ET73 -> 9420 | FA73: =DE73-EY73 -> -0.8 | FB73: =DF73-EZ73 -> -314 | FC73: =IF(FA73<0,"Thừa",IF(FA73=0,"Đủ","Thiếu")) -> Thừa
A74: =IF(I74=I73,"ok","Hiện") -> ok | I74: I90-A22 | J74: Tôn tấm | K74: PL50x2000x4600; PL50x2000x7000 | L74: ASTM A36 | M74: m2 | DH74: 210625/HN-IBS | DI74: Hùng Nguyên | DJ74: Thép tấm 50x2000x6000 (1 tờ) | DK74: A36/SS400 | DL74: 4710 | DM74: 45829 | DN74: 12 | DO74: 4710 | DP74: 14545.45 | DQ74: =DP74*DO74*1.1 -> 75359976 | DR74: =(DQ74-DS74)/DS74 -> 0.1 | DS74: =DP74*DO74 -> 68509070 | DT74: 45835
A75: =IF(I75=I74,"ok","Hiện") -> Hiện | B75: =FC75 -> Đủ | C75: =FA75 -> 0 | I75: I90-A23 | J75: Tôn tấm | K75: PL20x2000x6000 | L75: ASTM A572-Gr.50 | M75: m2 | N75: 157 | O75: 11.372484 | P75: 1785.48 | S75: 12 | T75: 1884 | W75: 0 | X75: 0 | Y75: 0 | Z75: 0 | AA75: 0 | AB75: 0 | AC75: 0 | AD75: 0 | AE75: 0 | AF75: 0 | AG75: 0 | AH75: 0 | AI75: =VLOOKUP(I75,'[119]MTO-rev09'!$A:$O,11,0) -> 0 | AJ75: =VLOOKUP(I75,'[119]MTO-rev09'!$A:$O,12,0) -> 0 | AK75: 0 | AL75: 0 | AO75: 0 | AP75: 0 | AQ75: 0 | AR75: 0 | AS75: 0 | AT75: 0 | AU75: 0 | AV75: 0 | AW75: 0 | AX75: 0 | AY75: 0 | AZ75: 0 | BC75: 0 | BD75: 0 | BE75: 0 | BF75: 0 | BG75: 0 | BH75: 0 | BI75: 0 | BJ75: 0 | BK75: 0 | BL75: 0 | BM75: 0 | BN75: 0 | BQ75: 0 | BR75: 0 | BS75: 0 | BT75: 0 | BU75: 0 | BV75: 0 | BY75: 0 | BZ75: 0 | CA75: 0 | CB75: 0 | CC75: 0 | CD75: 0 | CE75: =VLOOKUP(I75,[120]REV33!$A:$O,11,0) -> 0 | CF75: =VLOOKUP(I75,[120]REV33!$A:$O,12,0) -> 0 | CO75: 0 | CP75: 0 | CQ75: 0 | CR75: 0 | CS75: 0 | CT75: 0 | CU75: 0 | CV75: 0 | CW75: =Q75+S75+U75+W75+Y75+AA75+AC75+AE75+AG75+AI75+AK75+AM75+AO75+AQ75+AS75+AU75+AW75+AY75+BA75+BC75+BE75+BG75+BI75+BK75+BM75+BO75+BQ75+BS75+BU75+BW75+BY75+CA75+CC75+CE75+CG75+CI75+CK75+CM75+CO75+CQ75+CS75+CU75 -> 12 | CX75: =R75+T75+V75+X75+Z75+AB75+AD75+AF75+AH75+AJ75+AL75+AN75+AP75+AR75+AT75+AV75+AX75+AZ75+BB75+BD75+BF75+BH75+BJ75+BL75+BN75+BP75+BR75+BT75+BV75+BX75+BZ75+CB75+CD75+CF75+CH75+CJ75+CL75+CN75+CP75+CR75+CT75+CV75 -> 1884 | CY75: Rev01-PL20x2000x6000-1-tờ | DE75: =IF(CW75>DA75,CW75-DA75,"0") -> 12 | DF75: =IF(CX75>DB75,CX75-DB75,"0") -> 1884 | DG75: 45813 | DH75: 140525HN-IBS | DI75: Hùng Nguyên | DJ75: Thép tấm 20x2000x6000 A572 | DK75: A572 Gr.B | DL75: 1884 | DM75: 45791 | DN75: 12 | DO75: 1884 | DP75: 15272.73 | DQ75: =DP75*DO75*1.1 -> 31651206 | DR75: =(DQ75-DS75)/DS75 -> 0.1 | DS75: =DP75*DO75 -> 28773823 | DT75: 45794 | DU75: =SUMIF($I:$I,I75,$DN:$DN) -> 12 | DV75: =SUMIF($I:$I,I75,$DO:$DO) -> 1884 | ES75: =SUMIF($I:$I,I75,$EG:$EG) -> 0 | ET75: =SUMIF($I:$I,I75,$EH:$EH) -> 0 | EY75: =DU75+ES75 -> 12 | EZ75: =DV75+ET75 -> 1884 | FA75: =DE75-EY75 -> 0 | FB75: =DF75-EZ75 -> 0 | FC75: =IF(FA75<0,"Thừa",IF(FA75=0,"Đủ","Thiếu")) -> Đủ
A76: =IF(I76=I75,"ok","Hiện") -> Hiện | B76: =FC76 -> Thừa | C76: =FA76 -> -10.4 | I76: I90-A24 | J76: Tôn tấm | K76: PL20x2000x800 | L76: ASTM A572-Gr.50 | M76: m2 | N76: 157 | S76: 1.6 | T76: 251.2 | W76: 0 | X76: 0 | Y76: 0 | Z76: 0 | AA76: 0 | AB76: 0 | AC76: 0 | AD76: 0 | AE76: 0 | AF76: 0 | AG76: 0 | AH76: 0 | AI76: =VLOOKUP(I76,'[119]MTO-rev09'!$A:$O,11,0) -> 0 | AJ76: =VLOOKUP(I76,'[119]MTO-rev09'!$A:$O,12,0) -> 0 | AK76: 0 | AL76: 0 | AO76: 0 | AP76: 0 | AQ76: 0 | AR76: 0 | AS76: 0 | AT76: 0 | AU76: 0 | AV76: 0 | AW76: 0 | AX76: 0 | AY76: 0 | AZ76: 0 | BC76: 0 | BD76: 0 | BE76: 0 | BF76: 0 | BG76: 0 | BH76: 0 | BI76: 0 | BJ76: 0 | BK76: 0 | BL76: 0 | BM76: 0 | BN76: 0 | BQ76: 0 | BR76: 0 | BS76: 0 | BT76: 0 | BU76: 0 | BV76: 0 | BY76: 0 | BZ76: 0 | CA76: 0 | CB76: 0 | CC76: 0 | CD76: 0 | CE76: =VLOOKUP(I76,[120]REV33!$A:$O,11,0) -> 0 | CF76: =VLOOKUP(I76,[120]REV33!$A:$O,12,0) -> 0 | CO76: 0 | CP76: 0 | CQ76: 0 | CR76: 0 | CS76: 0 | CT76: 0 | CU76: 0 | CV76: 0 | CW76: =Q76+S76+U76+W76+Y76+AA76+AC76+AE76+AG76+AI76+AK76+AM76+AO76+AQ76+AS76+AU76+AW76+AY76+BA76+BC76+BE76+BG76+BI76+BK76+BM76+BO76+BQ76+BS76+BU76+BW76+BY76+CA76+CC76+CE76+CG76+CI76+CK76+CM76+CO76+CQ76+CS76+CU76 -> 1.6 | CX76: =R76+T76+V76+X76+Z76+AB76+AD76+AF76+AH76+AJ76+AL76+AN76+AP76+AR76+AT76+AV76+AX76+AZ76+BB76+BD76+BF76+BH76+BJ76+BL76+BN76+BP76+BR76+BT76+BV76+BX76+BZ76+CB76+CD76+CF76+CH76+CJ76+CL76+CN76+CP76+CR76+CT76+CV76 -> 251.2 | CY76: Rev01-PL20x2000x800-1-tờ | DE76: =IF(CW76>DA76,CW76-DA76,"0") -> 1.6 | DF76: =IF(CX76>DB76,CX76-DB76,"0") -> 251.2 | DG76: 45813 | DH76: 140525HN-IBS | DI76: Hùng Nguyên | DJ76: Thép tấm 20x2000x6000 A572 | DK76: A572 Gr.B | DL76: 1884 | DM76: 45791 | DN76: 12 | DO76: 1884 | DP76: 15272.73 | DQ76: =DP76*DO76*1.1 -> 31651206 | DR76: =(DQ76-DS76)/DS76 -> 0.1 | DS76: =DP76*DO76 -> 28773823 | DT76: 45794 | DU76: =SUMIF($I:$I,I76,$DN:$DN) -> 12 | DV76: =SUMIF($I:$I,I76,$DO:$DO) -> 1884 | ES76: =SUMIF($I:$I,I76,$EG:$EG) -> 0 | ET76: =SUMIF($I:$I,I76,$EH:$EH) -> 0 | EY76: =DU76+ES76 -> 12 | EZ76: =DV76+ET76 -> 1884 | FA76: =DE76-EY76 -> -10.4 | FB76: =DF76-EZ76 -> -1632.8 | FC76: =IF(FA76<0,"Thừa",IF(FA76=0,"Đủ","Thiếu")) -> Thừa
A77: =IF(I77=I76,"ok","Hiện") -> Hiện | B77: =FC77 -> Đủ | C77: =FA77 -> 0 | I77: I90-A25 | J77: Tôn tấm | K77: PL40x2000x2400 | L77: ASTM A572-Gr.50 | M77: m2 | N77: 314 | O77: 3.9515924 | P77: 1240.8 | S77: 4.8 | T77: 1507.2 | W77: 0 | X77: 0 | Y77: 0 | Z77: 0 | AA77: 0 | AB77: 0 | AC77: 0 | AD77: 0 | AE77: 0 | AF77: 0 | AG77: 0 | AH77: 0 | AI77: =VLOOKUP(I77,'[119]MTO-rev09'!$A:$O,11,0) -> 0 | AJ77: =VLOOKUP(I77,'[119]MTO-rev09'!$A:$O,12,0) -> 0 | AK77: 0 | AL77: 0 | AO77: 0 | AP77: 0 | AQ77: 0 | AR77: 0 | AS77: 0 | AT77: 0 | AU77: 0 | AV77: 0 | AW77: 0 | AX77: 0 | AY77: 0 | AZ77: 0 | BC77: 0 | BD77: 0 | BE77: 0 | BF77: 0 | BG77: 0 | BH77: 0 | BI77: 0 | BJ77: 0 | BK77: 0 | BL77: 0 | BM77: 0 | BN77: 0 | BQ77: 0 | BR77: 0 | BS77: 0 | BT77: 0 | BU77: 0 | BV77: 0 | BY77: 0 | BZ77: 0 | CA77: 0 | CB77: 0 | CC77: 0 | CD77: 0 | CE77: =VLOOKUP(I77,[120]REV33!$A:$O,11,0) -> 0 | CF77: =VLOOKUP(I77,[120]REV33!$A:$O,12,0) -> 0 | CO77: 0 | CP77: 0 | CQ77: 0 | CR77: 0 | CS77: 0 | CT77: 0 | CU77: 0 | CV77: 0 | CW77: =Q77+S77+U77+W77+Y77+AA77+AC77+AE77+AG77+AI77+AK77+AM77+AO77+AQ77+AS77+AU77+AW77+AY77+BA77+BC77+BE77+BG77+BI77+BK77+BM77+BO77+BQ77+BS77+BU77+BW77+BY77+CA77+CC77+CE77+CG77+CI77+CK77+CM77+CO77+CQ77+CS77+CU77 -> 4.8 | CX77: =R77+T77+V77+X77+Z77+AB77+AD77+AF77+AH77+AJ77+AL77+AN77+AP77+AR77+AT77+AV77+AX77+AZ77+BB77+BD77+BF77+BH77+BJ77+BL77+BN77+BP77+BR77+BT77+BV77+BX77+BZ77+CB77+CD77+CF77+CH77+CJ77+CL77+CN77+CP77+CR77+CT77+CV77 -> 1507.2 | CY77: Rev01-PL40x2000x2400-1-tờ | DA77: 4.8 | DB77: 1507.2 | DD77: Đã mời ngày 5/19 | DE77: =IF(CW77>DA77,CW77-DA77,"0") -> 0 | DF77: =IF(CX77>DB77,CX77-DB77,"0") -> 0 | DG77: 45813 | DU77: =SUMIF($I:$I,I77,$DN:$DN) -> 0 | DV77: =SUMIF($I:$I,I77,$DO:$DO) -> 0 | ES77: =SUMIF($I:$I,I77,$EG:$EG) -> 0 | ET77: =SUMIF($I:$I,I77,$EH:$EH) -> 0 | EY77: =DU77+ES77 -> 0 | EZ77: =DV77+ET77 -> 0 | FA77: =DE77-EY77 -> 0 | FB77: =DF77-EZ77 -> 0 | FC77: =IF(FA77<0,"Thừa",IF(FA77=0,"Đủ","Thiếu")) -> Đủ
A78: =IF(I78=I77,"ok","Hiện") -> Hiện | B78: =FC78 -> Thừa | C78: =FA78 -> -4.7184 | I78: I90-A26 | J78: Thép hình-H | K78: HEA120(H114x120x5x8)-L12000 | L78: ASTM A36/ EN-1.0577 | M78: m | N78: 19.9 | O78: 589.792 | P78: 11730.32 | S78: 619.2816 | T78: 12323.704 | W78: 0 | X78: 0 | Y78: 0 | Z78: 0 | AA78: 0 | AB78: 0 | AC78: 0 | AD78: 0 | AE78: 0 | AF78: 0 | AG78: 0 | AH78: 0 | AI78: =VLOOKUP(I78,'[119]MTO-rev09'!$A:$O,11,0) -> 0 | AJ78: =VLOOKUP(I78,'[119]MTO-rev09'!$A:$O,12,0) -> 0 | AK78: 0 | AL78: 0 | AO78: 0 | AP78: 0 | AQ78: 0 | AR78: 0 | AS78: 0 | AT78: 0 | AU78: 0 | AV78: 0 | AW78: 0 | AX78: 0 | AY78: 0 | AZ78: 0 | BC78: 0 | BD78: 0 | BE78: 0 | BF78: 0 | BG78: 0 | BH78: 0 | BI78: 0 | BJ78: 0 | BK78: 0 | BL78: 0 | BM78: 0 | BN78: 0 | BQ78: 0 | BR78: 0 | BS78: 0 | BT78: 0 | BU78: 0 | BV78: 0 | BY78: 0 | BZ78: 0 | CA78: 0 | CB78: 0 | CC78: 0 | CD78: 0 | CE78: =VLOOKUP(I78,[120]REV33!$A:$O,11,0) -> 0 | CF78: =VLOOKUP(I78,[120]REV33!$A:$O,12,0) -> 0 | CO78: 0 | CP78: 0 | CQ78: 0 | CR78: 0 | CS78: 0 | CT78: 0 | CU78: 0 | CV78: 0 | CW78: =Q78+S78+U78+W78+Y78+AA78+AC78+AE78+AG78+AI78+AK78+AM78+AO78+AQ78+AS78+AU78+AW78+AY78+BA78+BC78+BE78+BG78+BI78+BK78+BM78+BO78+BQ78+BS78+BU78+BW78+BY78+CA78+CC78+CE78+CG78+CI78+CK78+CM78+CO78+CQ78+CS78+CU78 -> 619.2816 | CX78: =R78+T78+V78+X78+Z78+AB78+AD78+AF78+AH78+AJ78+AL78+AN78+AP78+AR78+AT78+AV78+AX78+AZ78+BB78+BD78+BF78+BH78+BJ78+BL78+BN78+BP78+BR78+BT78+BV78+BX78+BZ78+CB78+CD78+CF78+CH78+CJ78+CL78+CN78+CP78+CR78+CT78+CV78 -> 12323.704 | CY78: Rev01-IBS bổ sung mới | DE78: =IF(CW78>DA78,CW78-DA78,"0") -> 619.2816 | DF78: =IF(CX78>DB78,CX78-DB78,"0") -> 12323.704 | DG78: 45813 | DU78: =SUMIF($I:$I,I78,$DN:$DN) -> 0 | DV78: =SUMIF($I:$I,I78,$DO:$DO) -> 0 | EA78: IBSHI-GNEE/2505-07 | EB78: GNEE | EC78: HEA120(H114x120x5x8)-L12000 | EE78: 12417.6 | EF78: 45784 | EG78: 624 | EH78: 12417.6 | EI78: =0.0140000072674221+0.987 -> 1.001 | EJ78: =EI78*EH78 -> 12430.018 | EK78: 45786 | EP78: 45823 | EQ78: 45824 | ES78: =SUMIF($I:$I,I78,$EG:$EG) -> 624 | ET78: =SUMIF($I:$I,I78,$EH:$EH) -> 12417.6 | EY78: =DU78+ES78 -> 624 | EZ78: =DV78+ET78 -> 12417.6 | FA78: =DE78-EY78 -> -4.7184 | FB78: =DF78-EZ78 -> -93.89616 | FC78: =IF(FA78<0,"Thừa",IF(FA78=0,"Đủ","Thiếu")) -> Thừa
A79: =IF(I79=I78,"ok","Hiện") -> Hiện | B79: =FC79 -> Thừa | C79: =FA79 -> -8.9793 | I79: I90-A27 | J79: Thép hình-H | K79: HEA200(H190x200x6.5x10)-L12000 | L79: ASTM A36/ EN-1.0577 | M79: m | N79: 42.3 | O79: 25.734 | P79: 1087.8 | S79: 27.0207 | T79: 1142.9756 | W79: 0 | X79: 0 | Y79: 0 | Z79: 0 | AA79: 12 | AB79: 507.6 | AC79: 0 | AD79: 0 | AE79: 0 | AF79: 0 | AG79: 0 | AH79: 0 | AI79: =VLOOKUP(I79,'[119]MTO-rev09'!$A:$O,11,0) -> 0 | AJ79: =VLOOKUP(I79,'[119]MTO-rev09'!$A:$O,12,0) -> 0 | AK79: 0 | AL79: 0 | AO79: 0 | AP79: 0 | AQ79: 0 | AR79: 0 | AS79: 0 | AT79: 0 | AU79: 0 | AV79: 0 | AW79: 0 | AX79: 0 | AY79: 0 | AZ79: 0 | BC79: 0 | BD79: 0 | BE79: 0 | BF79: 0 | BG79: 0 | BH79: 0 | BI79: 0 | BJ79: 0 | BK79: 0 | BL79: 0 | BM79: 0 | BN79: 0 | BQ79: 0 | BR79: 0 | BS79: 0 | BT79: 0 | BU79: 0 | BV79: 0 | BY79: 0 | BZ79: 0 | CA79: 0 | CB79: 0 | CC79: 0 | CD79: 0 | CE79: =VLOOKUP(I79,[120]REV33!$A:$O,11,0) -> 0 | CF79: =VLOOKUP(I79,[120]REV33!$A:$O,12,0) -> 0 | CO79: 0 | CP79: 0 | CQ79: 0 | CR79: 0 | CS79: 0 | CT79: 0 | CU79: 0 | CV79: 0 | CW79: =Q79+S79+U79+W79+Y79+AA79+AC79+AE79+AG79+AI79+AK79+AM79+AO79+AQ79+AS79+AU79+AW79+AY79+BA79+BC79+BE79+BG79+BI79+BK79+BM79+BO79+BQ79+BS79+BU79+BW79+BY79+CA79+CC79+CE79+CG79+CI79+CK79+CM79+CO79+CQ79+CS79+CU79 -> 39.0207 | CX79: =R79+T79+V79+X79+Z79+AB79+AD79+AF79+AH79+AJ79+AL79+AN79+AP79+AR79+AT79+AV79+AX79+AZ79+BB79+BD79+BF79+BH79+BJ79+BL79+BN79+BP79+BR79+BT79+BV79+BX79+BZ79+CB79+CD79+CF79+CH79+CJ79+CL79+CN79+CP79+CR79+CT79+CV79 -> 1650.5756 | CY79: Rev05-BRADEN-bổ sung 12.0m | DE79: =IF(CW79>DA79,CW79-DA79,"0") -> 39.0207 | DF79: =IF(CX79>DB79,CX79-DB79,"0") -> 1650.5756 | DG79: 45813 | DU79: =SUMIF($I:$I,I79,$DN:$DN) -> 0 | DV79: =SUMIF($I:$I,I79,$DO:$DO) -> 0 | EA79: IBSHI-GNEE/2505-07 | EB79: GNEE | EC79: HEA200(H190x200x6.5x10)-L12000 | EE79: 1522.8 | EF79: 45784 | EG79: 36 | EH79: 1522.8 | EI79: =0.0140000072674221+0.981 -> 0.99500001 | EJ79: =EI79*EH79 -> 1515.186 | EK79: 45786 | EP79: 45823 | EQ79: 45824 | ES79: =SUMIF($I:$I,I79,$EG:$EG) -> 48 | ET79: =SUMIF($I:$I,I79,$EH:$EH) -> 2030.4 | EY79: =DU79+ES79 -> 48 | EZ79: =DV79+ET79 -> 2030.4 | FA79: =DE79-EY79 -> -8.9793 | FB79: =DF79-EZ79 -> -379.82439 | FC79: =IF(FA79<0,"Thừa",IF(FA79=0,"Đủ","Thiếu")) -> Thừa
A80: =IF(I80=I79,"ok","Hiện") -> ok | I80: I90-A27 | J80: Thép hình-H | K80: HEA200(H190x200x6.5x10)-L12000 | L80: ASTM A36/ EN-1.0577 | M80: m | EA80: IBSHI-GNEE/2506-25 | EB80: GNEE | EC80: 190*200*6.5*10*12000 | ED80: ASTM A36 HEA200 | EE80: 507.6 | EF80: 45833 | EG80: 12 | EH80: 507.6 | EI80: =0.113081035655641+0.994 -> 1.107081 | EJ80: =EI80*EH80 -> 561.95433 | EK80: 45846 | EQ80: 45869 | ER80: 45869
A81: =IF(I81=I80,"ok","Hiện") -> Hiện | B81: =FC81 -> Đủ | C81: =FA81 -> 0 | I81: I90-A28 | J81: Thép hình-H | K81: HEA340(H330x300x9.5x16.5)-L12000 | L81: ASTM A36/ EN-1.0577 | M81: m | N81: 105 | O81: 850.332 | P81: 89053.1 | S81: 876 | T81: 91980 | W81: 0 | X81: 0 | Y81: 72 | Z81: 7560 | AA81: 540 | AB81: 56700 | AC81: 0 | AD81: 0 | AE81: 0 | AF81: 0 | AG81: 0 | AH81: 0 | AI81: =VLOOKUP(I81,'[119]MTO-rev09'!$A:$O,11,0) -> 0 | AJ81: =VLOOKUP(I81,'[119]MTO-rev09'!$A:$O,12,0) -> 0 | AK81: 0 | AL81: 0 | AO81: 0 | AP81: 0 | AQ81: 0 | AR81: 0 | AS81: 0 | AT81: 0 | AU81: 0 | AV81: 0 | AW81: 0 | AX81: 0 | AY81: 0 | AZ81: 0 | BC81: 0 | BD81: 0 | BE81: 0 | BF81: 0 | BG81: 0 | BH81: 0 | BI81: 0 | BJ81: 0 | BK81: 0 | BL81: 0 | BM81: 0 | BN81: 0 | BQ81: 0 | BR81: 0 | BS81: 0 | BT81: 0 | BU81: 0 | BV81: 0 | BY81: 0 | BZ81: 0 | CA81: 0 | CB81: 0 | CC81: 0 | CD81: 0 | CE81: =VLOOKUP(I81,[120]REV33!$A:$O,11,0) -> 0 | CF81: =VLOOKUP(I81,[120]REV33!$A:$O,12,0) -> 0 | CO81: 0 | CP81: 0 | CQ81: 0 | CR81: 0 | CS81: 0 | CT81: 0 | CU81: 0 | CV81: 0 | CW81: =Q81+S81+U81+W81+Y81+AA81+AC81+AE81+AG81+AI81+AK81+AM81+AO81+AQ81+AS81+AU81+AW81+AY81+BA81+BC81+BE81+BG81+BI81+BK81+BM81+BO81+BQ81+BS81+BU81+BW81+BY81+CA81+CC81+CE81+CG81+CI81+CK81+CM81+CO81+CQ81+CS81+CU81 -> 1488 | CX81: =R81+T81+V81+X81+Z81+AB81+AD81+AF81+AH81+AJ81+AL81+AN81+AP81+AR81+AT81+AV81+AX81+AZ81+BB81+BD81+BF81+BH81+BJ81+BL81+BN81+BP81+BR81+BT81+BV81+BX81+BZ81+CB81+CD81+CF81+CH81+CJ81+CL81+CN81+CP81+CR81+CT81+CV81 -> 156240 | CY81: Rev05-BRADEN-bổ sung 540.0m | DE81: =IF(CW81>DA81,CW81-DA81,"0") -> 1488 | DF81: =IF(CX81>DB81,CX81-DB81,"0") -> 156240 | DG81: 45813 | DU81: =SUMIF($I:$I,I81,$DN:$DN) -> 0 | DV81: =SUMIF($I:$I,I81,$DO:$DO) -> 0 | EA81: IBSHI-GNEE/2505-07 | EB81: GNEE | EC81: HEA340(H330x300x9.5x16.5)-L12000 | EE81: 91980 | EF81: 45784 | EG81: 876 | EH81: 91980 | EI81: =0.0140000072674221+0.994 -> 1.008 | EJ81: =EI81*EH81 -> 92715.841 | EK81: 45786 | EP81: 45823 | EQ81: 45824 | ES81: =SUMIF($I:$I,I81,$EG:$EG) -> 1488 | ET81: =SUMIF($I:$I,I81,$EH:$EH) -> 156240 | EY81: =DU81+ES81 -> 1488 | EZ81: =DV81+ET81 -> 156240 | FA81: =DE81-EY81 -> 0 | FB81: =DF81-EZ81 -> 0 | FC81: =IF(FA81<0,"Thừa",IF(FA81=0,"Đủ","Thiếu")) -> Đủ
A82: =IF(I82=I81,"ok","Hiện") -> ok | I82: I90-A28 | J82: Thép hình-H | K82: HEA340(H330x300x9.5x16.5)-L12000 | L82: ASTM A36/ EN-1.0577 | M82: m | EA82: IBSHI-GNEE/2506-25 | EB82: GNEE | EC82: 330*300*9.5*16.5*12000 | ED82: ASTM A36 HEA340 | EE82: 56700 | EF82: 45833 | EG82: 540 | EH82: 56700 | EI82: =0.113081035655641+0.994 -> 1.107081 | EJ82: =EI82*EH82 -> 62771.495 | EK82: 45846 | EQ82: 45869 | ER82: 45869
A83: =IF(I83=I82,"ok","Hiện") -> ok | I83: I90-A28 | J83: Thép hình-H | K83: HEA340(H330x300x9.5x16.5)-L12000 | L83: ASTM A36/ EN-1.0577 | M83: m | EA83: BSHI-GNEE/2506-05 | EB83: GNEE2 | EC83: ASTM A36 HEA340 (H330x300x9.5x16.5)-L12000 | ED83: ASTM A36 HEA340 (H330x300x9.5x16.5)-L12000 = 6 Cây | EE83: 7560 | EF83: 45813 | EG83: 72 | EH83: 7560 | EI83: =0.0577454062236541+0.994 -> 1.0517454 | EJ83: =EI83*EH83 -> 7951.1953 | EK83: 45833 | EN83: 45851 | EO83: 45851 | EP83: 45853 | EQ83: 45853 | ER83: 45853
A84: =IF(I84=I83,"ok","Hiện") -> Hiện | B84: =FC84 -> Thừa | C84: =FA84 -> -5.5 | I84: I90-A29 | J84: Thép hình-H | K84: HEB240(H240x240x10x17)-L3000; HEB240(H240x240x10x17)-L3500 | L84: ASTM A36/ EN-1.0577 | M84: m | N84: 83.2 | O84: 2.888 | P84: 187.52 | S84: 3 | T84: 249.6 | W84: 0 | X84: 0 | Y84: 0 | Z84: 0 | AA84: 3.5 | AB84: 291.2 | AC84: 0 | AD84: 0 | AE84: 0 | AF84: 0 | AG84: 0 | AH84: 0 | AI84: =VLOOKUP(I84,'[119]MTO-rev09'!$A:$O,11,0) -> 0 | AJ84: =VLOOKUP(I84,'[119]MTO-rev09'!$A:$O,12,0) -> 0 | AK84: 0 | AL84: 0 | AO84: 0 | AP84: 0 | AQ84: 0 | AR84: 0 | AS84: 0 | AT84: 0 | AU84: 0 | AV84: 0 | AW84: 0 | AX84: 0 | AY84: 0 | AZ84: 0 | BC84: 0 | BD84: 0 | BE84: 0 | BF84: 0 | BG84: 0 | BH84: 0 | BI84: 0 | BJ84: 0 | BK84: 0 | BL84: 0 | BM84: 0 | BN84: 0 | BQ84: 0 | BR84: 0 | BS84: 0 | BT84: 0 | BU84: 0 | BV84: 0 | BY84: 0 | BZ84: 0 | CA84: 0 | CB84: 0 | CC84: 0 | CD84: 0 | CE84: =VLOOKUP(I84,[120]REV33!$A:$O,11,0) -> 0 | CF84: =VLOOKUP(I84,[120]REV33!$A:$O,12,0) -> 0 | CO84: 0 | CP84: 0 | CQ84: 0 | CR84: 0 | CS84: 0 | CT84: 0 | CU84: 0 | CV84: 0 | CW84: =Q84+S84+U84+W84+Y84+AA84+AC84+AE84+AG84+AI84+AK84+AM84+AO84+AQ84+AS84+AU84+AW84+AY84+BA84+BC84+BE84+BG84+BI84+BK84+BM84+BO84+BQ84+BS84+BU84+BW84+BY84+CA84+CC84+CE84+CG84+CI84+CK84+CM84+CO84+CQ84+CS84+CU84 -> 6.5 | CX84: =R84+T84+V84+X84+Z84+AB84+AD84+AF84+AH84+AJ84+AL84+AN84+AP84+AR84+AT84+AV84+AX84+AZ84+BB84+BD84+BF84+BH84+BJ84+BL84+BN84+BP84+BR84+BT84+BV84+BX84+BZ84+CB84+CD84+CF84+CH84+CJ84+CL84+CN84+CP84+CR84+CT84+CV84 -> 540.8 | CY84: Rev05-BRADEN-bổ sung 3.5m | DE84: =IF(CW84>DA84,CW84-DA84,"0") -> 6.5 | DF84: =IF(CX84>DB84,CX84-DB84,"0") -> 540.8 | DG84: 45813 | DU84: =SUMIF($I:$I,I84,$DN:$DN) -> 0 | DV84: =SUMIF($I:$I,I84,$DO:$DO) -> 0 | EA84: IBSHI-GNEE/2505-07 | EB84: GNEE | EC84: HEB240(H240x240x10x17)-L3000 | EE84: 998.4 | EF84: 45784 | EG84: 12 | EH84: 998.4 | EI84: =0.0140000072674221+0.977 -> 0.99100001 | EJ84: =EI84*EH84 -> 989.41441 | EK84: 45786 | EP84: 45823 | EQ84: 45824 | ES84: =SUMIF($I:$I,I84,$EG:$EG) -> 12 | ET84: =SUMIF($I:$I,I84,$EH:$EH) -> 998.4 | EY84: =DU84+ES84 -> 12 | EZ84: =DV84+ET84 -> 998.4 | FA84: =DE84-EY84 -> -5.5 | FB84: =DF84-EZ84 -> -457.6 | FC84: =IF(FA84<0,"Thừa",IF(FA84=0,"Đủ","Thiếu")) -> Thừa
A85: =IF(I85=I84,"ok","Hiện") -> Hiện | B85: =CONCATENATE(FC85," Dùng cùng I90-A43") -> Thiếu Dùng cùng I90-A43 | C85: =FA85 -> 60 | G85: Dùng cùng I90-A43 | I85: I90-A30 | J85: Thép hình-H | K85: HEB300(H300x300x11x19)-L12000 | L85: ASTM A36/ EN-1.0577 | M85: m | N85: 117 | O85: 53.576 | P85: 4285.28 | S85: 56.2548 | T85: 6581.8116 | W85: 0 | X85: 0 | Y85: 0 | Z85: 0 | AA85: 63.7452 | AB85: 7458.1884 | AC85: 0 | AD85: 0 | AE85: 0 | AF85: 0 | AG85: 0 | AH85: 0 | AI85: =VLOOKUP(I85,'[119]MTO-rev09'!$A:$O,11,0) -> 0 | AJ85: =VLOOKUP(I85,'[119]MTO-rev09'!$A:$O,12,0) -> 0 | AK85: 0 | AL85: 0 | AO85: 0 | AP85: 0 | AQ85: 0 | AR85: 0 | AS85: 0 | AT85: 0 | AU85: 0 | AV85: 0 | AW85: 0 | AX85: 0 | AY85: 0 | AZ85: 0 | BC85: 0 | BD85: 0 | BE85: 0 | BF85: 0 | BG85: 0 | BH85: 0 | BI85: 0 | BJ85: 0 | BK85: 0 | BL85: 0 | BM85: 0 | BN85: 0 | BQ85: 0 | BR85: 0 | BS85: 0 | BT85: 0 | BU85: 0 | BV85: 0 | BY85: 0 | BZ85: 0 | CA85: 0 | CB85: 0 | CC85: 0 | CD85: 0 | CE85: =VLOOKUP(I85,[120]REV33!$A:$O,11,0) -> 0 | CF85: =VLOOKUP(I85,[120]REV33!$A:$O,12,0) -> 0 | CO85: 0 | CP85: 0 | CQ85: 0 | CR85: 0 | CS85: 0 | CT85: 0 | CU85: 0 | CV85: 0 | CW85: =Q85+S85+U85+W85+Y85+AA85+AC85+AE85+AG85+AI85+AK85+AM85+AO85+AQ85+AS85+AU85+AW85+AY85+BA85+BC85+BE85+BG85+BI85+BK85+BM85+BO85+BQ85+BS85+BU85+BW85+BY85+CA85+CC85+CE85+CG85+CI85+CK85+CM85+CO85+CQ85+CS85+CU85 -> 120 | CX85: =R85+T85+V85+X85+Z85+AB85+AD85+AF85+AH85+AJ85+AL85+AN85+AP85+AR85+AT85+AV85+AX85+AZ85+BB85+BD85+BF85+BH85+BJ85+BL85+BN85+BP85+BR85+BT85+BV85+BX85+BZ85+CB85+CD85+CF85+CH85+CJ85+CL85+CN85+CP85+CR85+CT85+CV85 -> 14040 | CY85: Rev05-BRADEN-bổ sung 63.75.0m | DE85: =IF(CW85>DA85,CW85-DA85,"0") -> 120 | DF85: =IF(CX85>DB85,CX85-DB85,"0") -> 14040 | DG85: 45813 | DU85: =SUMIF($I:$I,I85,$DN:$DN) -> 0 | DV85: =SUMIF($I:$I,I85,$DO:$DO) -> 0 | EA85: IBSHI-GNEE/2505-07 | EB85: GNEE | EC85: HEB300(H300x300x11x19)-L12000 | EE85: 7020 | EF85: 45784 | EG85: 60 | EH85: 7020 | EI85: =0.0140000072674221+0.977 -> 0.99100001 | EJ85: =EI85*EH85 -> 6956.8201 | EK85: 45786 | EP85: 45823 | EQ85: 45824 | ES85: =SUMIF($I:$I,I85,$EG:$EG) -> 60 | ET85: =SUMIF($I:$I,I85,$EH:$EH) -> 7020 | EY85: =DU85+ES85 -> 60 | EZ85: =DV85+ET85 -> 7020 | FA85: =DE85-EY85 -> 60 | FB85: =DF85-EZ85 -> 7020 | FC85: =IF(FA85<0,"Thừa",IF(FA85=0,"Đủ","Thiếu")) -> Thiếu
A86: =IF(I86=I85,"ok","Hiện") -> Hiện | B86: =FC86 -> Thừa | C86: =FA86 -> -8.9124 | I86: I90-A31 | J86: Thép hình-H | K86: IPE180(H180x91x5.3x8)-L12000 | L86: ASTM A36/ EN-1.0577 | M86: m | N86: 18.8 | O86: 71.512 | P86: 1264.64 | S86: 75.0876 | T86: 1411.6469 | W86: 0 | X86: 0 | Y86: 0 | Z86: 0 | AA86: 0 | AB86: 0 | AC86: 0 | AD86: 0 | AE86: 0 | AF86: 0 | AG86: 0 | AH86: 0 | AI86: =VLOOKUP(I86,'[119]MTO-rev09'!$A:$O,11,0) -> 0 | AJ86: =VLOOKUP(I86,'[119]MTO-rev09'!$A:$O,12,0) -> 0 | AK86: 0 | AL86: 0 | AO86: 0 | AP86: 0 | AQ86: 0 | AR86: 0 | AS86: 0 | AT86: 0 | AU86: 0 | AV86: 0 | AW86: 0 | AX86: 0 | AY86: 0 | AZ86: 0 | BC86: 0 | BD86: 0 | BE86: 0 | BF86: 0 | BG86: 0 | BH86: 0 | BI86: 0 | BJ86: 0 | BK86: 0 | BL86: 0 | BM86: 0 | BN86: 0 | BQ86: 0 | BR86: 0 | BS86: 0 | BT86: 0 | BU86: 0 | BV86: 0 | BY86: 0 | BZ86: 0 | CA86: 0 | CB86: 0 | CC86: 0 | CD86: 0 | CE86: =VLOOKUP(I86,[120]REV33!$A:$O,11,0) -> 0 | CF86: =VLOOKUP(I86,[120]REV33!$A:$O,12,0) -> 0 | CO86: 0 | CP86: 0 | CQ86: 0 | CR86: 0 | CS86: 0 | CT86: 0 | CU86: 0 | CV86: 0 | CW86: =Q86+S86+U86+W86+Y86+AA86+AC86+AE86+AG86+AI86+AK86+AM86+AO86+AQ86+AS86+AU86+AW86+AY86+BA86+BC86+BE86+BG86+BI86+BK86+BM86+BO86+BQ86+BS86+BU86+BW86+BY86+CA86+CC86+CE86+CG86+CI86+CK86+CM86+CO86+CQ86+CS86+CU86 -> 75.0876 | CX86: =R86+T86+V86+X86+Z86+AB86+AD86+AF86+AH86+AJ86+AL86+AN86+AP86+AR86+AT86+AV86+AX86+AZ86+BB86+BD86+BF86+BH86+BJ86+BL86+BN86+BP86+BR86+BT86+BV86+BX86+BZ86+CB86+CD86+CF86+CH86+CJ86+CL86+CN86+CP86+CR86+CT86+CV86 -> 1411.6469 | CY86: Rev01-IBS bổ sung mới | DE86: =IF(CW86>DA86,CW86-DA86,"0") -> 75.0876 | DF86: =IF(CX86>DB86,CX86-DB86,"0") -> 1411.6469 | DG86: 45813 | DU86: =SUMIF($I:$I,I86,$DN:$DN) -> 0 | DV86: =SUMIF($I:$I,I86,$DO:$DO) -> 0 | EA86: IBSHI-GNEE/2505-07 | EB86: GNEE | EC86: IPE180(H180x91x5.3x8)-L12000 | EE86: 1579.2 | EF86: 45784 | EG86: 84 | EH86: 1579.2 | EI86: =0.0140000072674221+0.984 -> 0.99800001 | EJ86: =EI86*EH86 -> 1576.0416 | EK86: 45786 | EP86: 45823 | EQ86: 45824 | ES86: =SUMIF($I:$I,I86,$EG:$EG) -> 84 | ET86: =SUMIF($I:$I,I86,$EH:$EH) -> 1579.2 | EY86: =DU86+ES86 -> 84 | EZ86: =DV86+ET86 -> 1579.2 | FA86: =DE86-EY86 -> -8.9124 | FB86: =DF86-EZ86 -> -167.55312 | FC86: =IF(FA86<0,"Thừa",IF(FA86=0,"Đủ","Thiếu")) -> Thừa
A87: =IF(I87=I86,"ok","Hiện") -> Hiện | B87: =FC87 -> Thừa | C87: =FA87 -> -3.8172 | I87: I90-A32 | J87: Thép hình-H | K87: IPE270(H270x135x6.6x10.2)-L12000 | L87: ASTM A36/ EN-1.0577 | M87: m | N87: 36.1 | O87: 304.936 | P87: 10997.96 | S87: 320.1828 | T87: 11558.599 | W87: 0 | X87: 0 | Y87: 0 | Z87: 0 | AA87: 0 | AB87: 0 | AC87: 0 | AD87: 0 | AE87: 0 | AF87: 0 | AG87: 0 | AH87: 0 | AI87: =VLOOKUP(I87,'[119]MTO-rev09'!$A:$O,11,0) -> 0 | AJ87: =VLOOKUP(I87,'[119]MTO-rev09'!$A:$O,12,0) -> 0 | AK87: 0 | AL87: 0 | AO87: 0 | AP87: 0 | AQ87: 0 | AR87: 0 | AS87: 0 | AT87: 0 | AU87: 0 | AV87: 0 | AW87: 0 | AX87: 0 | AY87: 0 | AZ87: 0 | BC87: 0 | BD87: 0 | BE87: 0 | BF87: 0 | BG87: 0 | BH87: 0 | BI87: 0 | BJ87: 0 | BK87: 0 | BL87: 0 | BM87: 0 | BN87: 0 | BQ87: 0 | BR87: 0 | BS87: 0 | BT87: 0 | BU87: 0 | BV87: 0 | BY87: 0 | BZ87: 0 | CA87: 0 | CB87: 0 | CC87: 0 | CD87: 0 | CE87: =VLOOKUP(I87,[120]REV33!$A:$O,11,0) -> 0 | CF87: =VLOOKUP(I87,[120]REV33!$A:$O,12,0) -> 0 | CO87: 0 | CP87: 0 | CQ87: 0 | CR87: 0 | CS87: 0 | CT87: 0 | CU87: 0 | CV87: 0 | CW87: =Q87+S87+U87+W87+Y87+AA87+AC87+AE87+AG87+AI87+AK87+AM87+AO87+AQ87+AS87+AU87+AW87+AY87+BA87+BC87+BE87+BG87+BI87+BK87+BM87+BO87+BQ87+BS87+BU87+BW87+BY87+CA87+CC87+CE87+CG87+CI87+CK87+CM87+CO87+CQ87+CS87+CU87 -> 320.1828 | CX87: =R87+T87+V87+X87+Z87+AB87+AD87+AF87+AH87+AJ87+AL87+AN87+AP87+AR87+AT87+AV87+AX87+AZ87+BB87+BD87+BF87+BH87+BJ87+BL87+BN87+BP87+BR87+BT87+BV87+BX87+BZ87+CB87+CD87+CF87+CH87+CJ87+CL87+CN87+CP87+CR87+CT87+CV87 -> 11558.599 | CY87: Rev01-IBS bổ sung mới | DE87: =IF(CW87>DA87,CW87-DA87,"0") -> 320.1828 | DF87: =IF(CX87>DB87,CX87-DB87,"0") -> 11558.599 | DG87: 45813 | DU87: =SUMIF($I:$I,I87,$DN:$DN) -> 0 | DV87: =SUMIF($I:$I,I87,$DO:$DO) -> 0 | EA87: IBSHI-GNEE/2505-07 | EB87: GNEE | EC87: IPE270(H270x135x6.6x10.2)-L12000 | EE87: 11696.4 | EF87: 45784 | EG87: 324 | EH87: 11696.4 | EI87: =0.0140000072674221+0.983 -> 0.99700001 | EJ87: =EI87*EH87 -> 11661.311 | EK87: 45786 | EP87: 45823 | EQ87: 45824 | ES87: =SUMIF($I:$I,I87,$EG:$EG) -> 324 | ET87: =SUMIF($I:$I,I87,$EH:$EH) -> 11696.4 | EY87: =DU87+ES87 -> 324 | EZ87: =DV87+ET87 -> 11696.4 | FA87: =DE87-EY87 -> -3.8172 | FB87: =DF87-EZ87 -> -137.80092 | FC87: =IF(FA87<0,"Thừa",IF(FA87=0,"Đủ","Thiếu")) -> Thừa
A88: =IF(I88=I87,"ok","Hiện") -> Hiện | B88: =FC88 -> Thừa | C88: =FA88 -> -0.8646 | I88: I90-A33 | J88: Thép hình-H | K88: IPE300(H300x150x7.1x10.7)-L12000 | L88: ASTM A36/ EN-1.0577 | M88: m | N88: 42.2 | O88: 107.748 | P88: 4338.96 | S88: 113.1354 | T88: 4774.3139 | W88: 0 | X88: 0 | Y88: 0 | Z88: 0 | AA88: 102 | AB88: 4304.4 | AC88: 0 | AD88: 0 | AE88: 0 | AF88: 0 | AG88: 0 | AH88: 0 | AI88: =VLOOKUP(I88,'[119]MTO-rev09'!$A:$O,11,0) -> 0 | AJ88: =VLOOKUP(I88,'[119]MTO-rev09'!$A:$O,12,0) -> 0 | AK88: 0 | AL88: 0 | AO88: 0 | AP88: 0 | AQ88: 0 | AR88: 0 | AS88: 0 | AT88: 0 | AU88: 0 | AV88: 0 | AW88: 0 | AX88: 0 | AY88: 0 | AZ88: 0 | BC88: 0 | BD88: 0 | BE88: 0 | BF88: 0 | BG88: 0 | BH88: 0 | BI88: 0 | BJ88: 0 | BK88: 0 | BL88: 0 | BM88: 0 | BN88: 0 | BQ88: 0 | BR88: 0 | BS88: 0 | BT88: 0 | BU88: 0 | BV88: 0 | BY88: 0 | BZ88: 0 | CA88: 0 | CB88: 0 | CC88: 0 | CD88: 0 | CE88: =VLOOKUP(I88,[120]REV33!$A:$O,11,0) -> 0 | CF88: =VLOOKUP(I88,[120]REV33!$A:$O,12,0) -> 0 | CO88: 0 | CP88: 0 | CQ88: 0 | CR88: 0 | CS88: 0 | CT88: 0 | CU88: 0 | CV88: 0 | CW88: =Q88+S88+U88+W88+Y88+AA88+AC88+AE88+AG88+AI88+AK88+AM88+AO88+AQ88+AS88+AU88+AW88+AY88+BA88+BC88+BE88+BG88+BI88+BK88+BM88+BO88+BQ88+BS88+BU88+BW88+BY88+CA88+CC88+CE88+CG88+CI88+CK88+CM88+CO88+CQ88+CS88+CU88 -> 215.1354 | CX88: =R88+T88+V88+X88+Z88+AB88+AD88+AF88+AH88+AJ88+AL88+AN88+AP88+AR88+AT88+AV88+AX88+AZ88+BB88+BD88+BF88+BH88+BJ88+BL88+BN88+BP88+BR88+BT88+BV88+BX88+BZ88+CB88+CD88+CF88+CH88+CJ88+CL88+CN88+CP88+CR88+CT88+CV88 -> 9078.7139 | CY88: Rev05-BRADEN-bổ sung 102.0m | DE88: =IF(CW88>DA88,CW88-DA88,"0") -> 215.1354 | DF88: =IF(CX88>DB88,CX88-DB88,"0") -> 9078.7139 | DG88: 45813 | DU88: =SUMIF($I:$I,I88,$DN:$DN) -> 0 | DV88: =SUMIF($I:$I,I88,$DO:$DO) -> 0 | EA88: IBSHI-GNEE/2505-07 | EB88: GNEE | EC88: IPE300(H300x150x7.1x10.7)-L12000 | EE88: 5064 | EF88: 45784 | EG88: 120 | EH88: 5064 | EI88: =0.0140000072674221+0.981 -> 0.99500001 | EJ88: =EI88*EH88 -> 5038.68 | EK88: 45786 | EP88: 45823 | EQ88: 45824 | ES88: =SUMIF($I:$I,I88,$EG:$EG) -> 216 | ET88: =SUMIF($I:$I,I88,$EH:$EH) -> 9115.2 | EY88: =DU88+ES88 -> 216 | EZ88: =DV88+ET88 -> 9115.2 | FA88: =DE88-EY88 -> -0.8646 | FB88: =DF88-EZ88 -> -36.48612 | FC88: =IF(FA88<0,"Thừa",IF(FA88=0,"Đủ","Thiếu")) -> Thừa
A89: =IF(I89=I88,"ok","Hiện") -> ok | I89: I90-A33 | J89: Thép hình-H | K89: IPE300(H300x150x7.1x10.7)-L12000 | L89: ASTM A36/ EN-1.0577 | M89: m | EA89: IBSHI-GNEE/2506-25 | EB89: GNEE | EC89: 300*150*7.1*10.7*12000 | ED89: ASTM A36 IPE300 | EE89: 4051.2 | EF89: 45833 | EG89: 96 | EH89: 4051.2 | EI89: =0.113081035655641+0.981 -> 1.094081 | EJ89: =EI89*EH89 -> 4432.3411 | EK89: 45846 | EQ89: 45869 | ER89: 45869
A90: =IF(I90=I89,"ok","Hiện") -> Hiện | B90: =FC90 -> Đủ | C90: =FA90 -> 0 | I90: I90-A34 | J90: Thép hình-H | K90: IPE330(H330x160x7.5x11.5)-L12000 | L90: ASTM A36/ EN-1.0577 | M90: m | N90: 49.1 | O90: 192.784 | P90: 9334.64 | S90: 204 | T90: 10016.4 | W90: 0 | X90: 0 | Y90: 0 | Z90: 0 | AA90: 288 | AB90: 14140.8 | AC90: 0 | AD90: 0 | AE90: 0 | AF90: 0 | AG90: 0 | AH90: 0 | AI90: =VLOOKUP(I90,'[119]MTO-rev09'!$A:$O,11,0) -> 0 | AJ90: =VLOOKUP(I90,'[119]MTO-rev09'!$A:$O,12,0) -> 0 | AK90: 0 | AL90: 0 | AO90: 0 | AP90: 0 | AQ90: 0 | AR90: 0 | AS90: 0 | AT90: 0 | AU90: 0 | AV90: 0 | AW90: 0 | AX90: 0 | AY90: 0 | AZ90: 0 | BC90: 0 | BD90: 0 | BE90: 0 | BF90: 0 | BG90: 0 | BH90: 0 | BI90: 0 | BJ90: 0 | BK90: 0 | BL90: 0 | BM90: 0 | BN90: 0 | BQ90: 0 | BR90: 0 | BS90: 0 | BT90: 0 | BU90: 0 | BV90: 0 | BY90: 0 | BZ90: 0 | CA90: 0 | CB90: 0 | CC90: 0 | CD90: 0 | CE90: =VLOOKUP(I90,[120]REV33!$A:$O,11,0) -> 0 | CF90: =VLOOKUP(I90,[120]REV33!$A:$O,12,0) -> 0 | CO90: 0 | CP90: 0 | CQ90: 0 | CR90: 0 | CS90: 0 | CT90: 0 | CU90: 0 | CV90: 0 | CW90: =Q90+S90+U90+W90+Y90+AA90+AC90+AE90+AG90+AI90+AK90+AM90+AO90+AQ90+AS90+AU90+AW90+AY90+BA90+BC90+BE90+BG90+BI90+BK90+BM90+BO90+BQ90+BS90+BU90+BW90+BY90+CA90+CC90+CE90+CG90+CI90+CK90+CM90+CO90+CQ90+CS90+CU90 -> 492 | CX90: =R90+T90+V90+X90+Z90+AB90+AD90+AF90+AH90+AJ90+AL90+AN90+AP90+AR90+AT90+AV90+AX90+AZ90+BB90+BD90+BF90+BH90+BJ90+BL90+BN90+BP90+BR90+BT90+BV90+BX90+BZ90+CB90+CD90+CF90+CH90+CJ90+CL90+CN90+CP90+CR90+CT90+CV90 -> 24157.2 | CY90: Rev05-BRADEN-bổ sung 288.0m | DE90: =IF(CW90>DA90,CW90-DA90,"0") -> 492 | DF90: =IF(CX90>DB90,CX90-DB90,"0") -> 24157.2 | DG90: 45813 | DU90: =SUMIF($I:$I,I90,$DN:$DN) -> 0 | DV90: =SUMIF($I:$I,I90,$DO:$DO) -> 0 | EA90: IBSHI-GNEE/2505-07 | EB90: GNEE | EC90: IPE330(H330x160x7.5x11.5)-L12000 | EE90: 10036.8 | EF90: 45784 | EG90: 204 | EH90: 10036.8 | EI90: =0.0140000072674221+0.984 -> 0.99800001 | EJ90: =EI90*EH90 -> 10016.726 | EK90: 45786 | EP90: 45823 | EQ90: 45824 | ES90: =SUMIF($I:$I,I90,$EG:$EG) -> 492 | ET90: =SUMIF($I:$I,I90,$EH:$EH) -> 24206.4 | EY90: =DU90+ES90 -> 492 | EZ90: =DV90+ET90 -> 24206.4 | FA90: =DE90-EY90 -> 0 | FB90: =DF90-EZ90 -> -49.2 | FC90: =IF(FA90<0,"Thừa",IF(FA90=0,"Đủ","Thiếu")) -> Đủ
A91: =IF(I91=I90,"ok","Hiện") -> ok | I91: I90-A34 | J91: Thép hình-H | K91: IPE330(H330x160x7.5x11.5)-L12000 | L91: ASTM A36/ EN-1.0577 | M91: m | EA91: IBSHI-GNEE/2506-25 | EB91: GNEE | EC91: 330*160*7.5*11.5*12000 | ED91: ASTM A36 IPE330 | EE91: 14169.6 | EF91: 45833 | EG91: 288 | EH91: 14169.6 | EI91: =0.113081035655641+0.981 -> 1.094081 | EJ91: =EI91*EH91 -> 15502.691 | EK91: 45846 | EQ91: 45869 | ER91: 45869
