Workbook
Name \0: #REF!
Name \a: #N/A
Name \a: #N/A
Name \a: #N/A
Name \a: #N/A
Name \a: #N/A
Name \a: #N/A
Name \a: #N/A
Name \a: #N/A
Name \a: #REF!
Name \b: #N/A
Name \c: #N/A
Name \d: #N/A
Name \e: #N/A
Name \f: #N/A
Name \g: #N/A
Name \h: #N/A
Name \h: #N/A
Name \h: #N/A
Name \h: #N/A
Name \h: #N/A
Name \h: #N/A
Name \h: #N/A
Name \h: #N/A
Name \h: [1]PP!$IC$5
Name \i: #N/A
Name \i: #N/A
Name \i: #N/A
Name \i: #N/A
Name \i: #N/A
Name \i: #N/A
Name \i: #N/A
Name \i: #N/A
Name \i: [1]PP!$IP$7844
Name \j: #N/A
Name \k: #N/A
Name \KWS123: #N/A
Name \m: #N/A
Name \m: #N/A
Name \m: #N/A
Name \m: #N/A
Name \m: #N/A
Name \m: #N/A
Name \m: #N/A
Name \m: #N/A
Name \m: [1]PP!#REF!
Name \n: #N/A
Name \p: #REF!
Name \s: #N/A
Name \s: #N/A
Name \s: #N/A
Name \s: #N/A
Name \s: #N/A
Name \s: #N/A
Name \s: #N/A
Name \s: #N/A
Name \s: [1]PP!$HX$3
Name \t: #N/A
Name \v: #REF!
Name \w: #REF!

Sheet Giải tình Tam Đa
A1: BID ANALYSIS - GIẢI TRÌNH MUA SẮM/ĐẤU THẦU
A3: Project | B3: PROJECT No/ Dự án: 25-GEN-G-07
A4: Dự án
A5: Subject | B5: Cung cấp vật tư bu lông, phụ kiện
A6: Chủ đề
A8: No. | B8: CONTENT | C8: Phạm vi công việc | H8: Dự toán | K8: Đã mua | L8: Đơn vị cung cấp chào giá (vnđ) | O8: Lựa chọn | P8: Ghi chú
A9: Item | B9: Description/ Chi tiết | C9: Profile/ Vật tư | D9: Grade/ Mác vật liệu | E9: Số lượng Mua | F9: Số lượng PR | G9: Đơn vị | H9: Khối lượng/ Số lượng | I9: Đơn giá (vnd) | J9: Thành tiền (vnd) | K9: Thành tiền (vnd) | L9: Tam Đa
L10: Phạm vi | M10: Đơn giá (VND) | N10: Thành Tiền (Không có VAT)
A11: Tổng | B11: Bolt-Material / Vật tư bulong, phụ kiện | H11: N/A | I11: N/A | N11: =SUM(N12:N16) -> 5580000 | P11: =J11-K11-N11 -> -5580000
A12: G07-VPK-020 | B12: Threaded half coupling-không mạ | C12: 3/8" NPS Threaded half coupling #3000-ASME B16.11 | D12: ASME-SA105M | E12: 4 | F12: 4 | G12: cái | H12: N/A | I12: N/A | J12: N/A | L12: V | M12: N/A | N12: N/A | O12: Tam Đa
A13: G07-VPK-021 | B13: Threaded half coupling-không mạ | C13: 3/4" NPS Threaded half coupling #3000-ASME B16.11 | D13: ASME-SA105M | E13: 4 | F13: 4 | G13: cái | H13: N/A | I13: N/A | J13: N/A | L13: V | M13: 65000 | N13: =M13*F13 -> 260000 | O13: Tam Đa
A14: G07-VPK-022 | B14: Threaded half coupling-không mạ | C14: 1" NPS Threaded half coupling #3000-ASME B16.11 | D14: ASME-SA105M | E14: 4 | F14: 4 | G14: cái | H14: N/A | I14: N/A | J14: N/A | L14: V | M14: 95000 | N14: =M14*F14 -> 380000 | O14: Tam Đa
A15: G07-VPK-023 | B15: Threaded half coupling-không mạ | C15: 2" NPS Threaded half coupling #3000-ASME B16.11 | D15: ASME-SA105M | E15: 20 | F15: 20 | G15: cái | H15: N/A | I15: N/A | J15: N/A | L15: V | M15: 195000 | N15: =M15*F15 -> 3900000 | O15: Tam Đa
A16: G07-VPK-024 | B16: plug | C16: 2" NPS Threaded hex head plug #3000-ASME B16.11 | D16: ASME-SA105M | E16: 4 | F16: 4 | G16: cái | H16: N/A | I16: N/A | J16: N/A | L16: V | M16: 260000 | N16: =M16*F16 -> 1040000 | O16: Tam Đa
B17: Xếp hạng | M17: 1
A18: Ghi chú: Tiếp tục công tác mua sắm để đảm báo tiến độ
A19: NGƯỜI ĐỀ NGHỊ/ RECOMMENDATION BY: | C19: NGƯỜI KIỂM TRA/ DEPARTMENT HEAD CHECK BY: | G19: APPROVED BY: PHÊ DUYỆT
G20: Nguyễn Quang Vinh | K20: Hoàng Ngọc Bằng | O20: Đoàn Văn Toàn

Sheet Giải tình ngọc hiếu
A1: BID ANALYSIS - GIẢI TRÌNH MUA SẮM/ĐẤU THẦU
A3: Project | B3: PROJECT No/ Dự án: 25-GEN-G-07
A4: Dự án
A5: Subject | B5: Cung cấp vật tư thép hình
A6: Chủ đề
A8: No. | B8: CONTENT | C8: Phạm vi công việc | H8: Dự toán | K8: Đã mua | L8: Đơn vị cung cấp chào giá (vnđ) | O8: Đơn vị cung cấp chào giá (vnđ) | R8: Lựa chọn | S8: Ghi chú
A9: Item | B9: Description/ Chi tiết | C9: Profile/ Vật tư | D9: Grade/ Mác vật liệu | E9: Số lượng Mua | F9: Số lượng PR | G9: Đơn vị | H9: Khối lượng/ Số lượng | I9: Đơn giá (vnd) | J9: Thành tiền (vnd) | K9: Thành tiền (vnd) | L9: HÙNG NGUYÊN | O9: NGỌC HIẾU
L10: Phạm vi | M10: Đơn giá (VND) | N10: Thành Tiền (Không có VAT) | O10: Phạm vi | P10: Đơn giá (VND) | Q10: Thành Tiền (Không có VAT)
A11: Tổng | B11: Main-Material / Vật tư chính thép đen | H11: N/A | I11: N/A | K11: ='Tổng hợp'!J20 -> 4.3019969e+08 | Q11: =SUM(Q12:Q12) -> 45173648 | S11: =J11-K11-N11-Q11 -> -4.7537334e+08
A12: G07-VTC01-006 | B12: Thép U100*50*5*7,5*6000 | C12: C100x50x5x7.5-L6000 | D12: Q235A/SS400 | E12: =56*6 -> 336 | F12: 336 | G12: m2 | H12: N/A | I12: N/A | J12: N/A | K12: N/A | L12: V | M12: =19000/1.1 -> 17272.727 | N12: N/A | O12: V | P12: 14363.64 | Q12: 45173648 | R12: Ngọc Hiếu | S12: Chưa có dự toán
B13: Xếp hạng | M13: 2 | P13: 1
A14: Ghi chú: Tiếp tục công tác mua sắm để đảm báo tiến độ
A15: NGƯỜI ĐỀ NGHỊ/ RECOMMENDATION BY: | C15: NGƯỜI KIỂM TRA/ DEPARTMENT HEAD CHECK BY: | G15: APPROVED BY: PHÊ DUYỆT
G16: Nguyễn Quang Vinh | N16: Hoàng Ngọc Bằng | Q16: Đoàn Văn Toàn

Sheet Giải tình hùng nguyên
A1: BID ANALYSIS - GIẢI TRÌNH MUA SẮM/ĐẤU THẦU
A3: Project | B3: PROJECT No/ Dự án: 25-GEN-G-07
A4: Dự án
A5: Subject | B5: Cung cấp vật tư thép tấm
A6: Chủ đề
A8: No. | B8: CONTENT | C8: Phạm vi công việc | H8: Dự toán | K8: Đã mua | L8: Đơn vị cung cấp chào giá (vnđ) | O8: Đơn vị cung cấp chào giá (vnđ) | R8: Lựa chọn | S8: Ghi chú
A9: Item | B9: Description/ Chi tiết | C9: Profile/ Vật tư | D9: Grade/ Mác vật liệu | E9: Số lượng Mua | F9: Số lượng PR | G9: Đơn vị | H9: Khối lượng/ Số lượng | I9: Đơn giá (vnd) | J9: Thành tiền (vnd) | K9: Thành tiền (vnd) | L9: HÙNG NGUYÊN | O9: APEC
L10: Phạm vi | M10: Đơn giá (VND) | N10: Thành Tiền (Không có VAT) | O10: Phạm vi | P10: Đơn giá (VND) | Q10: Thành Tiền (Không có VAT)
A11: Tổng | B11: Main-Material / Vật tư chính thép đen | H11: N/A | I11: N/A | K11: ='Tổng hợp'!J20-N11 -> 2.1240928e+08 | N11: =SUM(N12:N13) -> 217790411 | Q11: =SUM(Q12:Q12) -> 0 | S11: =J11-K11-N11 -> -4.3019969e+08
A12: G07-VTC01-003 | B12: PL6X2000X12000 | C12: Thép tấm 6x2000x12000 | D12: Q235A/SS400 | E12: 216 | F12: 216 | G12: m2 | H12: N/A | I12: N/A | J12: N/A | K12: N/A | L12: V | M12: 13272.73 | N12: 135031446 | O12: V | P12: =14700/1.1 -> 13363.636 | Q12: N/A | R12: HÙNG NGUYÊN | S12: Chưa có dự toán
A13: G07-VTC01-005 | B13: PL16X2000X12000 | C13: Thép tấm 16x2000x12000 | D13: Q235A/SS400 | E13: 36 | F13: 36 | G13: m2 | H13: N/A | I13: N/A | J13: N/A | K13: N/A | L13: V | M13: 13727.27 | N13: 82758965 | O13: V | P13: =15400/1.1 -> 14000 | Q13: N/A | R13: HÙNG NGUYÊN
B14: Xếp hạng | M14: 1 | P14: 2
A15: Ghi chú: Tiếp tục công tác mua sắm để đảm báo tiến độ
A16: NGƯỜI ĐỀ NGHỊ/ RECOMMENDATION BY: | C16: NGƯỜI KIỂM TRA/ DEPARTMENT HEAD CHECK BY: | G16: APPROVED BY: PHÊ DUYỆT
G17: Nguyễn Quang Vinh | N17: Hoàng Ngọc Bằng | Q17: Đoàn Văn Toàn

Sheet Giải tình Quang Thịnh Phát
A1: BID ANALYSIS - GIẢI TRÌNH MUA SẮM/ĐẤU THẦU
A3: Project | B3: PROJECT No/ Dự án: 25-GEN-G-08
A4: Dự án
A5: Subject | B5: Cung cấp vật tư bu lông, phụ kiện
A6: Chủ đề
A8: No. | B8: CONTENT | C8: Phạm vi công việc | H8: Dự toán | K8: Đã mua | L8: Đơn vị cung cấp chào giá (vnđ) | O8: Lựa chọn | P8: Ghi chú
A9: Item | B9: Description/ Chi tiết | C9: Profile/ Vật tư | D9: Grade/ Mác vật liệu | E9: Số lượng Mua | F9: Số lượng PR | G9: Đơn vị | H9: Khối lượng/ Số lượng | I9: Đơn giá (vnd) | J9: Thành tiền (vnd) | K9: Thành tiền (vnd) | L9: Quang Thịnh Phát
L10: Phạm vi | M10: Đơn giá (VND) | N10: Thành Tiền (Không có VAT)
A11: Tổng | B11: Main-Material / Vật tư chính thép đen | H11: N/A | I11: N/A | N11: =SUM(N12:N12) -> 14079545 | P11: =J11-K11-N11 -> -14079545
A12: G07-VTC01-007 | B12: SHS 70x70x5-L6000 | C12: Thép hộp đen 60 x 60 x 5,5 x 6.000 mm | D12: Q235A/SS400 | E12: =16*6 -> 96 | F12: 96 | G12: m | H12: N/A | I12: N/A | J12: N/A | L12: V | M12: 15909.09 | N12: 14079545 | O12: Quang thịnh Phát | P12: Chưa có dự toán
B13: Xếp hạng | M13: 1
A14: Ghi chú: Tiếp tục công tác mua sắm để đảm báo tiến độ
A15: NGƯỜI ĐỀ NGHỊ/ RECOMMENDATION BY: | C15: NGƯỜI KIỂM TRA/ DEPARTMENT HEAD CHECK BY: | G15: APPROVED BY: PHÊ DUYỆT
G16: Nguyễn Quang Vinh | K16: Hoàng Ngọc Bằng | O16: Đoàn Văn Toàn

Sheet 25-GEN-G-07
G1: THEO DÕI VẬT TƯ DỰ ÁN/ MATERIAL CONTROL LOG | L1: Hướng dẫn cập nhật thông tin: | P1: Thời gian nộp bảng cập nhật: | CI1: DỰ TOÁN
G2: Tên dự án/ Project no.:25-GEN-G-07 | L2: - Chữ tô màu xanh: | N2: Chưa cập nhật | P2: - Trong ngày khi có biến động.
G3: Cập nhật ngày/ Update to: | I3: =TODAY() -> 46086 | L3: - Chữ tô màu đỏ: | N3: Đã cập nhật mới | P3: - Báo cáo hàng tuần vào 16:30 mỗi chiều thứ 2. | AF3: =SUBTOTAL(9,AF7:AF1148) -> 0
B4: Đánh giá (Thiếu/ Đủ/ Thừa) | G4: Item/ STT | H4: Description/ Chi tiết | I4: Profile/ Vật tư | J4: Grade/ Mác vật liệu | K4: Unit/ Đơn vị | L4: U.Weight/ Đ.Trọng (Kg/m2,m,pcs) | M4: Net Quantity/Số lượng tinh | O4: Current Ordered/Dự trù lần 0 (Ngày 20/12/2025) | Q4: Current Ordered/Dự trù lần 1 (Ngày 13/1/2026) | S4: Current Ordered/Dự trù lần 2 (Ngày 14/1/2026) | U4: Current Ordered/Dự trù lần 3 (Ngày 21/1/2026) | W4: Current Ordered/Dự trù lần 4 (Ngày 27/1/2026) | Y4: Current Ordered/Dự trù lần 5 (Ngày 11/2/2026) | AA4: Total Ordered/Tổng dự trù | AC4: Remarks/ Ghi chú | AD4: Tận dụng tồn kho/ Remain | AI4: Khối lượng phải mua sắm/ total order | AK4: Ngày bàn giao vật tư/ Material avaiable for hand over date | AL4: VẬT TƯ TRONG NƯỚC | AY4: ĐÃ MUA TRONG NƯỚC | BA4: QC Nghiệm thu | BE4: Mua sắm nước ngoài/ Oversea purchase | BW4: ĐÃ MUA NHẬP KHẨU | BY4: Nghiệm thu | CC4: TỔNG ĐÃ MUA TRONG VÀ NGOÀI NƯỚC | CE4: So sánh với số lượng vật tư PR | CH4: Remarks/ Ghi chú
M5: Q.Ty/ S.Lượng | N5: Weight/ K.Lượng (Kg) | O5: Q.Ty/ S.Lượng | P5: Weight/ K.Lượng (Kg) | Q5: Q.Ty/ S.Lượng | R5: Weight/ K.Lượng (Kg) | S5: Q.Ty/ S.Lượng | T5: Weight/ K.Lượng (Kg) | U5: Q.Ty/ S.Lượng | V5: Weight/ K.Lượng (Kg) | W5: Q.Ty/ S.Lượng | X5: Weight/ K.Lượng (Kg) | Y5: Q.Ty/ S.Lượng | Z5: Weight/ K.Lượng (Kg) | AA5: Q.Ty/ S.Lượng | AB5: Weight/ K.Lượng (Kg) | AD5: Report No. | AE5: Q.Ty/ S.Lượng | AF5: Weight/ K.Lượng (Kg) | AG5: Ngày nghiệm thu ACC | AH5: Remarks/ Ghi chú | AI5: Q.Ty/ S.Lượng | AJ5: Weight/ K.Lượng (Kg) | AL5: Số Hợp đồng / Contract No | AM5: Nhà cung cấp/ Vendor | AN5: Profile/ Vật tư | AO5: Grade/ Mác vật liệu | AP5: Contract weight ( K.Lượng theo HĐ) | AQ5: Ngày ký HD/ Contract date | AR5: S.Lượng giao hàng thực tế/ Handover Q'ty | AS5: K.Lượng giao hàng thực tế// Handover weight | AT5: Đơn giá / Unit Price (Not VAT) | AU5: Tổng tiền bao gồm cả VAT (VNĐ) | AV5: Tiền VAT | AW5: Tổng tiền chưa VAT (VNĐ) | AX5: Bàn giao sản xuất/ Handover to Product | AY5: Q.Ty/ S.Lượng | AZ5: Weight/ K.Lượng (Kg) | BA5: Report No. | BB5: Inspection date | BC5: Khối lượng nghiệm thu đạt/ Weight Acc. Inspection | BD5: Results | BE5: Số Hợp đồng / Contract No | BF5: Nhà cung cấp/ Vendor | BG5: Profile/ Vật tư | BH5: Grade/ Mác vật liệu | BI5: Weight/ Khối lượng (Kg) | BJ5: Ngày ký HD/ Contract date | BK5: Số lượng giao hàng thực tế/ Handover Q'ty | BL5: Khối lượng giao hàng thực tế/ Handover Q'ty | BM5: Đơn giá / Unit Price | BN5: Thành tiền Hợp đồng/ total | BO5: Ngày mở L/C/ LC issued date | BP5: Hàng đi từ cảng nước ngoài/ Export Port | BQ5: Hàng Đến cảng HP (CIF)/ HaiPhong CIF | BR5: Ngày thanh toán / Payment date | BS5: Thủ tục hải quan, vận chuyển/ Paper work, local transportaion date | BT5: Ngày hàng về / Arived | BU5: Ngày mời nghiệm thu / invice QC date | BV5: Bàn giao sản xuất/ Handover to Product | BW5: Q.Ty/ S.Lượng | BX5: Weight/ K.Lượng (Kg) | BY5: Report No. | BZ5: Inspection date | CA5: Khối lượng nghiệm thu đạt/ Weight Acc. Inspection | CB5: Results | CC5: Q.Ty/ S.Lượng | CD5: Weight/ K.Lượng (Kg) | CE5: Q.Ty/ S.Lượng | CF5: Weight/ K.Lượng (Kg) | CG5: Đánh giá (Thiếu/ Đủ/ Thừa) | CI5: STT | CJ5: Chi tiết vật liệu | CL5: ĐVT | CM5: Định mức | CN5: Số lượng | CO5: Khối lượng | CP5: Đơn giá (VNĐ)
C6: Số lượng cần (M/M2) | D6: Xin chuyển đổi | E6: Tiền cần cho phần hàng chưa nhận được hoặc chưa đặt hàng | F6: Kế hoạch | G6: 1 | H6: =G6+1 -> 2 | I6: =H6+1 -> 3 | J6: =I6+1 -> 4 | K6: =J6+1 -> 5 | L6: =K6+1 -> 6 | M6: =L6+1 -> 7 | N6: =M6+1 -> 8 | O6: =N6+1 -> 9 | P6: =O6+1 -> 10 | AA6: =P6+1 -> 11 | AB6: =AA6+1 -> 12 | AC6: =AB6+1 -> 13 | AD6: =AC6+1 -> 14 | AE6: =AD6+1 -> 15 | AF6: =AE6+1 -> 16 | AG6: =AF6+1 -> 17 | AH6: =AG6+1 -> 18 | AI6: =AH6+1 -> 19 | ... AT6: =AS6+1 -> 30 | AX6: =AT6+1 -> 31 | AY6: =AX6+1 -> 32 | AZ6: =AY6+1 -> 33 | BA6: =AZ6+1 -> 34 | BB6: =BA6+1 -> 35 | BC6: =BB6+1 -> 36 | BD6: =BC6+1 -> 37 | BE6: =BD6+1 -> 38 | BF6: =BE6+1 -> 39 | ... CH6: =CG6+1 -> 67
G7: VTC01 | H7: Main-Material / Vật tư chính thép đen | AA7: =SUM(AA8:AA24) -> 931.375 | AB7: =SUM(AB8:AB24) -> 31090.659 | AC7: =SUM(AC8:AC24) -> 0 | AD7: =SUM(AD8:AD24) -> 0 | AE7: =SUM(AE8:AE24) -> 40.375 | AF7: =SUM(AF8:AF24) -> 1107.6395 | AG7: =SUM(AG8:AG24) -> 0 | AH7: =SUM(AH8:AH24) -> 0 | ... CH7: =SUM(CH8:CH24) -> 0 | CI7: I
A8: =IF(G8=G7,"ok","Hiện") -> Hiện | B8: =CG8 -> Đủ | C8: =CE8 -> 0 | G8: G07-VTC01-001 | H8: Tôn tấm | I8: PL3X1500X6000 | J8: Q235A/SS400 | K8: m2 | L8: 23.55 | M8: =+N8/L8 -> 0 | N8: 0 | O8: 45 | P8: 1059.75 | Q8: -45 | R8: -1059.75 | U8: 108 | V8: 2543.4 | W8: 0 | X8: 0 | AA8: =O8+Q8+S8+U8+W8+Y8 -> 108 | AB8: =P8+R8+T8+V8+X8+Z8 -> 2543.4 | AC8: REV03-khay đựng | AI8: =IF(AA8>AE8,AA8-AE8,"0") -> 108 | AJ8: =IF(AB8>AF8,AB8-AF8,"0") -> 2543.4 | AK8: Chưa có | AY8: =SUMIF($I:$I,I8,$AR:$AR) -> 108 | AZ8: =SUMIF($I:$I,I8,$AS:$AS) -> 2543.4 | BW8: =SUMIF($I:$I,I8,$BK:$BK) -> 0 | BX8: =SUMIF($I:$I,I8,$BL:$BL) -> 0 | CC8: =AY8+BW8 -> 108 | CD8: =AZ8+BX8 -> 2543.4 | CE8: =AI8-CC8 -> 0 | CF8: =AJ8-CD8 -> 0 | CG8: =IF(CE8<0,"Thừa",IF(CE8=0,"Đủ","Thiếu")) -> Đủ
A9: =IF(G9=G8,"ok","Hiện") -> ok | G9: G07-VTC01-001 | H9: Tôn tấm | I9: PL3X1500X6000 | J9: Q235A/SS400 | K9: m2 | AL9: ? | AM9: Hùng Nguyên | AN9: Thép tấm 6x2000x12000 | AO9: SS400 | AP9: 2543.4 | AQ9: 46048 | AR9: 108 | AS9: 2543.4 | AT9: 13363.64 | AU9: =AT9*AS9*1.1 -> 37387990 | AV9: 0.1 | AW9: =AT9*AS9 -> 33989082 | AX9: 46051
A10: =IF(G10=G9,"ok","Hiện") -> Hiện | B10: =CG10 -> Đủ | C10: =CE10 -> 0 | G10: G07-VTC01-002 | H10: Tôn tấm | I10: PL5X1500X3200 | J10: Q235A/SS400 | K10: m2 | L10: 39.25 | M10: =+N10/L10 -> 3.87008 | N10: 151.90064 | O10: 4.8 | P10: 188.4 | U10: 0 | V10: 0 | W10: 0 | X10: 0 | AA10: =O10+Q10+S10+U10+W10+Y10 -> 4.8 | AB10: =P10+R10+T10+V10+X10+Z10 -> 188.4 | AE10: 4.8 | AF10: 188.4 | AH10: Hàng tồn | AI10: =IF(AA10>AE10,AA10-AE10,"0") -> 0 | AJ10: =IF(AB10>AF10,AB10-AF10,"0") -> 0 | AK10: Chưa có | AY10: =SUMIF($I:$I,I10,$AR:$AR) -> 0 | AZ10: =SUMIF($I:$I,I10,$AS:$AS) -> 0 | BW10: =SUMIF($I:$I,I10,$BK:$BK) -> 0 | BX10: =SUMIF($I:$I,I10,$BL:$BL) -> 0 | CC10: =AY10+BW10 -> 0 | CD10: =AZ10+BX10 -> 0 | CE10: =AI10-CC10 -> 0 | CF10: =AJ10-CD10 -> 0 | CG10: =IF(CE10<0,"Thừa",IF(CE10=0,"Đủ","Thiếu")) -> Đủ
A11: =IF(G11=G10,"ok","Hiện") -> Hiện | B11: =CG11 -> Đủ | C11: =CE11 -> 0 | G11: G07-VTC01-003 | H11: Tôn tấm | I11: PL6X2000X12000 | J11: Q235A/SS400 | K11: m2 | L11: 47.1 | M11: =+N11/L11 -> 196.80073 | N11: =7693.71435+1575.6 -> 9269.3144 | O11: 216 | P11: 10173.6 | U11: 0 | V11: 0 | W11: 0 | X11: 0 | AA11: =O11+Q11+S11+U11+W11+Y11 -> 216 | AB11: =P11+R11+T11+V11+X11+Z11 -> 10173.6 | AC11: REV03-tăng khối lượng tinh 201.4 kg | AI11: =IF(AA11>AE11,AA11-AE11,"0") -> 216 | AJ11: =IF(AB11>AF11,AB11-AF11,"0") -> 10173.6 | AK11: Chưa có | AL11: ? | AM11: Hùng Nguyên | AN11: Thép tấm 6x2000x12000 | AO11: SS400 | AP11: 10173.6 | AQ11: 46036 | AR11: 216 | AS11: 10173.6 | AT11: 13272.73 | AU11: =AT11*AS11*1.1 -> 1.4853459e+08 | AV11: 0.1 | AW11: =AT11*AS11 -> 1.3503145e+08 | AX11: 46041 | AY11: =SUMIF($I:$I,I11,$AR:$AR) -> 216 | AZ11: =SUMIF($I:$I,I11,$AS:$AS) -> 10173.6 | BW11: =SUMIF($I:$I,I11,$BK:$BK) -> 0 | BX11: =SUMIF($I:$I,I11,$BL:$BL) -> 0 | CC11: =AY11+BW11 -> 216 | CD11: =AZ11+BX11 -> 10173.6 | CE11: =AI11-CC11 -> 0 | CF11: =AJ11-CD11 -> 0 | CG11: =IF(CE11<0,"Thừa",IF(CE11=0,"Đủ","Thiếu")) -> Đủ
A12: =IF(G12=G11,"ok","Hiện") -> ok | B12: =CG12 -> Đủ | C12: =CE12 -> 0 | G12: G07-VTC01-003 | H12: Tôn tấm | I12: PL8X1000X1000 | J12: Q235A/SS400 | K12: m2 | L12: 62.8 | M12: =+N12/L12 -> 0.56050955 | N12: 35.2 | O12: 1 | P12: 62.8 | AA12: =O12+Q12+S12 -> 1 | AB12: =P12+R12+T12 -> 62.8 | AE12: 1 | AF12: 62.8 | AH12: Hàng tồn | AI12: =IF(AA12>AE12,AA12-AE12,"0") -> 0 | AJ12: =IF(AB12>AF12,AB12-AF12,"0") -> 0 | AK12: Chưa có | AY12: =SUMIF($I:$I,I12,$AR:$AR) -> 0 | AZ12: =SUMIF($I:$I,I12,$AS:$AS) -> 0 | BW12: =SUMIF($I:$I,I12,$BK:$BK) -> 0 | BX12: =SUMIF($I:$I,I12,$BL:$BL) -> 0 | CC12: =AY12+BW12 -> 0 | CD12: =AZ12+BX12 -> 0 | CE12: =AI12-CC12 -> 0 | CF12: =AJ12-CD12 -> 0 | CG12: =IF(CE12<0,"Thừa",IF(CE12=0,"Đủ","Thiếu")) -> Đủ
A13: =IF(G13=G12,"ok","Hiện") -> Hiện | B13: =CG13 -> Đủ | C13: =CE13 -> 0 | G13: G07-VTC01-004 | H13: Tôn tấm | I13: PL10X1500X1800 | J13: Q235A/SS400 | K13: m2 | L13: 78.5 | M13: =+N13/L13 -> 2.238 | N13: 175.683 | O13: 2.775 | P13: 217.8375 | U13: 0 | V13: 0 | W13: 0 | X13: 0 | AA13: =O13+Q13+S13+U13+W13+Y13 -> 2.775 | AB13: =P13+R13+T13+V13+X13+Z13 -> 217.8375 | AC13: REV03-tăng khối lượng tinh 488.7 kg | AE13: 2.775 | AF13: 217.8375 | AH13: Hàng tồn | AI13: =IF(AA13>AE13,AA13-AE13,"0") -> 0 | AJ13: =IF(AB13>AF13,AB13-AF13,"0") -> 0 | AK13: Chưa có | AY13: =SUMIF($I:$I,I13,$AR:$AR) -> 0 | AZ13: =SUMIF($I:$I,I13,$AS:$AS) -> 0 | BW13: =SUMIF($I:$I,I13,$BK:$BK) -> 0 | BX13: =SUMIF($I:$I,I13,$BL:$BL) -> 0 | CC13: =AY13+BW13 -> 0 | CD13: =AZ13+BX13 -> 0 | CE13: =AI13-CC13 -> 0 | CF13: =AJ13-CD13 -> 0 | CG13: =IF(CE13<0,"Thừa",IF(CE13=0,"Đủ","Thiếu")) -> Đủ
A14: =IF(G14=G13,"ok","Hiện") -> Hiện | B14: =CG14 -> Đủ | C14: =CE14 -> 0 | G14: G07-VTC01-005 | H14: Tôn tấm | I14: PL16X2000X12000 | J14: Q235A/SS400 | K14: m2 | L14: 125.6 | M14: =+N14/L14 -> 30.36668 | N14: 3814.055 | O14: 36 | P14: 4521.6 | U14: 0 | V14: 0 | W14: 0 | X14: 0 | AA14: =O14+Q14+S14+U14+W14+Y14 -> 36 | AB14: =P14+R14+T14+V14+X14+Z14 -> 4521.6 | AI14: =IF(AA14>AE14,AA14-AE14,"0") -> 36 | AJ14: =IF(AB14>AF14,AB14-AF14,"0") -> 4521.6 | AK14: Chưa có | AL14: ? | AM14: Hùng Nguyên | AN14: Thép tấm 16x2000x12000 | AO14: SS400 | AP14: 6028.8 | AQ14: 46036 | AR14: 36 | AS14: 6028.8 | AT14: 13727.27 | AU14: =AT14*AS14*1.1 -> 91034862 | AV14: 0.1 | AW14: =AT14*AS14 -> 82758965 | AX14: 46041 | AY14: =SUMIF($I:$I,I14,$AR:$AR) -> 36 | AZ14: =SUMIF($I:$I,I14,$AS:$AS) -> 6028.8 | BW14: =SUMIF($I:$I,I14,$BK:$BK) -> 0 | BX14: =SUMIF($I:$I,I14,$BL:$BL) -> 0 | CC14: =AY14+BW14 -> 36 | CD14: =AZ14+BX14 -> 6028.8 | CE14: =AI14-CC14 -> 0 | CF14: =AJ14-CD14 -> -1507.2 | CG14: =IF(CE14<0,"Thừa",IF(CE14=0,"Đủ","Thiếu")) -> Đủ
A15: =IF(G15=G14,"ok","Hiện") -> Hiện | B15: =CG15 -> Đủ | C15: =CE15 -> 0 | G15: G07-VTC01-006 | H15: Thép hình C | I15: C100x50x5x7.5-L6000 | J15: Q235A/SS400 | K15: m2 | L15: 9.36 | M15: 328.95 | N15: 3078.972 | O15: 336 | P15: 3144.96 | U15: 0 | V15: 0 | W15: 0 | X15: 0 | AA15: =O15+Q15+S15+U15+W15+Y15 -> 336 | AB15: =P15+R15+T15+V15+X15+Z15 -> 3144.96 | AC15: REV01-đổi profile | AI15: =IF(AA15>AE15,AA15-AE15,"0") -> 336 | AJ15: =IF(AB15>AF15,AB15-AF15,"0") -> 3144.96 | AK15: Chưa có | AL15: ? | AM15: Ngọc Hiếu | AN15: Thép U100*50*5*7,5*6000 (56 cây) | AO15: SS400 | AP15: 3145 | AQ15: 46036 | AR15: =56*6 -> 336 | AS15: 3145 | AT15: 14363.64 | AU15: =AT15*AS15*1.1 -> 49691013 | AV15: 0.1 | AW15: =AT15*AS15 -> 45173648 | AX15: 46045 | AY15: =SUMIF($I:$I,I15,$AR:$AR) -> 336 | AZ15: =SUMIF($I:$I,I15,$AS:$AS) -> 3145 | BW15: =SUMIF($I:$I,I15,$BK:$BK) -> 0 | BX15: =SUMIF($I:$I,I15,$BL:$BL) -> 0 | CC15: =AY15+BW15 -> 336 | CD15: =AZ15+BX15 -> 3145 | CE15: =AI15-CC15 -> 0 | CF15: =AJ15-CD15 -> -0.04 | CG15: =IF(CE15<0,"Thừa",IF(CE15=0,"Đủ","Thiếu")) -> Đủ
A16: =IF(G16=G15,"ok","Hiện") -> Hiện | B16: =CG16 -> Đủ | C16: =CE16 -> 0 | G16: G07-VTC01-007 | H16: Thép hộp | I16: SHS 60x60x5-L6000 | J16: Q235A/SS400 | K16: m2 | L16: 10.21 | M16: 86.562 | N16: 883.79802 | O16: 96 | P16: 980.16 | U16: 0 | V16: 0 | W16: 0 | X16: 0 | AA16: =O16+Q16+S16+U16+W16+Y16 -> 96 | AB16: =P16+R16+T16+V16+X16+Z16 -> 980.16 | AC16: REV01-đổi profile | AI16: =IF(AA16>AE16,AA16-AE16,"0") -> 96 | AJ16: =IF(AB16>AF16,AB16-AF16,"0") -> 980.16 | AK16: Chưa có | AL16: 1201/2026/QTP-IBS | AM16: Quang Thịnh Phát | AN16: Thép hộp đen 60 x 60 x 5,5 x 6.000 mm | AO16: SS400 | AP16: 885 | AQ16: 46034 | AR16: =16*6 -> 96 | AS16: 885 | AT16: 15909.09 | AU16: =AT16*AS16*1.1 -> 15487499 | AV16: 0.1 | AW16: =AT16*AS16 -> 14079545 | AX16: 46038 | AY16: =SUMIF($I:$I,I16,$AR:$AR) -> 96 | AZ16: =SUMIF($I:$I,I16,$AS:$AS) -> 885 | BW16: =SUMIF($I:$I,I16,$BK:$BK) -> 0 | BX16: =SUMIF($I:$I,I16,$BL:$BL) -> 0 | CC16: =AY16+BW16 -> 96 | CD16: =AZ16+BX16 -> 885 | CE16: =AI16-CC16 -> 0 | CF16: =AJ16-CD16 -> 95.16 | CG16: =IF(CE16<0,"Thừa",IF(CE16=0,"Đủ","Thiếu")) -> Đủ
A17: =IF(G17=G16,"ok","Hiện") -> Hiện | B17: =CG17 -> Thừa | C17: =CE17 -> -1.25 | G17: G07-VTC01-008 | H17: Tôn tấm | I17: PL2X1200X2500 | J17: Q235A/SS400 | K17: m2 | L17: =2*7.85 -> 15.7 | M17: =+N17/L17 -> 27.32508 | N17: 429.00376 | U17: 30 | V17: 471 | W17: 0 | X17: 0 | AA17: =O17+Q17+S17+U17+W17+Y17 -> 30 | AB17: =P17+R17+T17+V17+X17+Z17 -> 471 | AC17: REV03-khay đựng | AI17: =IF(AA17>AE17,AA17-AE17,"0") -> 30 | AJ17: =IF(AB17>AF17,AB17-AF17,"0") -> 471 | AY17: =SUMIF($I:$I,I17,$AR:$AR) -> 31.25 | AZ17: =SUMIF($I:$I,I17,$AS:$AS) -> 491 | BW17: =SUMIF($I:$I,I17,$BK:$BK) -> 0 | BX17: =SUMIF($I:$I,I17,$BL:$BL) -> 0 | CC17: =AY17+BW17 -> 31.25 | CD17: =AZ17+BX17 -> 491 | CE17: =AI17-CC17 -> -1.25 | CF17: =AJ17-CD17 -> -20 | CG17: =IF(CE17<0,"Thừa",IF(CE17=0,"Đủ","Thiếu")) -> Thừa
A18: =IF(G18=G17,"ok","Hiện") -> ok | G18: G07-VTC01-008 | H18: Tôn tấm | I18: PL2X1200X2500 | J18: Q235A/SS400 | K18: m2 | AL18: ? | AM18: Ngọc Hiếu | AN18: Thép tấm 2*1250*2500 | AO18: SS400 | AP18: 491 | AQ18: 46048 | AR18: =10*1.25*2.5 -> 31.25 | AS18: 491 | AT18: 14545.45 | AU18: =AT18*AS18*1.1 -> 7855997.5 | AV18: 0.1 | AW18: =AT18*AS18 -> 7141816 | AX18: 46051
A19: =IF(G19=G18,"ok","Hiện") -> Hiện | B19: =CG19 -> Đủ | C19: =CE19 -> 0 | G19: G07-VTC01-009 | H19: Ống | I19: Pipe D33.4x2.77 | J19: Q235A/SS400 | K19: m | L19: 2.69 | M19: 1.692 | N19: =+M19*L19 -> 4.55148 | U19: 1.8 | V19: 4.842 | W19: 0 | X19: 0 | AA19: =O19+Q19+S19+U19+W19+Y19 -> 1.8 | AB19: =P19+R19+T19+V19+X19+Z19 -> 4.842 | AC19: REV03-khay đựng | AE19: 1.8 | AF19: 4.842 | AH19: Sử dụng hàng tồn | AI19: =IF(AA19>AE19,AA19-AE19,"0") -> 0 | AJ19: =IF(AB19>AF19,AB19-AF19,"0") -> 0 | AY19: =SUMIF($I:$I,I19,$AR:$AR) -> 0 | AZ19: =SUMIF($I:$I,I19,$AS:$AS) -> 0 | BW19: =SUMIF($I:$I,I19,$BK:$BK) -> 0 | BX19: =SUMIF($I:$I,I19,$BL:$BL) -> 0 | CC19: =AY19+BW19 -> 0 | CD19: =AZ19+BX19 -> 0 | CE19: =AI19-CC19 -> 0 | CF19: =AJ19-CD19 -> 0 | CG19: =IF(CE19<0,"Thừa",IF(CE19=0,"Đủ","Thiếu")) -> Đủ
A20: =IF(G20=G19,"ok","Hiện") -> Hiện | B20: =CG20 -> Đủ | C20: =CE20 -> 0 | G20: G07-VTC01-010 | H20: Ống | I20: Pipe D42.2x2.27 | J20: Q235A/SS400 | K20: m | L20: 3.74 | M20: =0.13*27 -> 3.51 | N20: =+M20*L20 -> 13.1274 | U20: 4 | V20: 14.96 | W20: 0 | X20: 0 | AA20: =O20+Q20+S20+U20+W20+Y20 -> 4 | AB20: =P20+R20+T20+V20+X20+Z20 -> 14.96 | AC20: REV03-khay đựng | AE20: 4 | AF20: 14.96 | AH20: Sử dụng hàng tồn | AI20: =IF(AA20>AE20,AA20-AE20,"0") -> 0 | AJ20: =IF(AB20>AF20,AB20-AF20,"0") -> 0 | AY20: =SUMIF($I:$I,I20,$AR:$AR) -> 0 | AZ20: =SUMIF($I:$I,I20,$AS:$AS) -> 0 | BW20: =SUMIF($I:$I,I20,$BK:$BK) -> 0 | BX20: =SUMIF($I:$I,I20,$BL:$BL) -> 0 | CC20: =AY20+BW20 -> 0 | CD20: =AZ20+BX20 -> 0 | CE20: =AI20-CC20 -> 0 | CF20: =AJ20-CD20 -> 0 | CG20: =IF(CE20<0,"Thừa",IF(CE20=0,"Đủ","Thiếu")) -> Đủ
A21: =IF(G21=G20,"ok","Hiện") -> Hiện | B21: =CG21 -> Đủ | C21: =CE21 -> 0 | G21: G07-VTC01-011 | H21: Tôn tấm | I21: PL14x2000x12000 (2 tờ) PL14x2000x4500 (1 tầm) | J21: Q235A/SS400 | K21: m2 | L21: =7.85*14 -> 109.9 | M21: =+N21/L21 -> 47.190173 | N21: 5186.2 | W21: 57 | X21: 6264.3 | AA21: =O21+Q21+S21+U21+W21+Y21 -> 57 | AB21: =P21+R21+T21+V21+X21+Z21 -> 6264.3 | AC21: REV04-tank | AI21: =IF(AA21>AE21,AA21-AE21,"0") -> 57 | AJ21: =IF(AB21>AF21,AB21-AF21,"0") -> 6264.3 | AL21: ? | AM21: Hùng Nguyên | AN21: Thép tấm 14x2000x12000 SS400 | AO21: SS400 | AP21: 5275.2 | AQ21: 46050 | AR21: =2*(24) -> 48 | AS21: 5275.2 | AT21: 13727.27 | AU21: =AT21*AS21*1.1 -> 79655504 | AV21: 0.1 | AW21: =AT21*AS21 -> 72414095 | AX21: 46050 | AY21: =SUMIF($I:$I,I21,$AR:$AR) -> 57 | AZ21: =SUMIF($I:$I,I21,$AS:$AS) -> 6264.3 | BW21: =SUMIF($I:$I,I21,$BK:$BK) -> 0 | BX21: =SUMIF($I:$I,I21,$BL:$BL) -> 0 | CC21: =AY21+BW21 -> 57 | CD21: =AZ21+BX21 -> 6264.3 | CE21: =AI21-CC21 -> 0 | CF21: =AJ21-CD21 -> 0 | CG21: =IF(CE21<0,"Thừa",IF(CE21=0,"Đủ","Thiếu")) -> Đủ
A22: =IF(G22=G21,"ok","Hiện") -> ok | G22: G07-VTC01-011 | H22: Tôn tấm | I22: PL14x2000x12000 (2 tờ) PL14x2000x4500 (1 tầm) | J22: Q235A/SS400 | K22: m2 | AL22: ? | AM22: Hùng Nguyên | AN22: Thép tấm 14x2000x4500 SS400 | AO22: SS400 | AP22: 989.1 | AQ22: 46050 | AR22: 9 | AS22: 989.1 | AT22: 13727.27 | AU22: =AT22*AS22*1.1 -> 14935407 | AV22: 0.1 | AW22: =AT22*AS22 -> 13577643 | AX22: 46050
A23: =IF(G23=G22,"ok","Hiện") -> Hiện | B23: =CG23 -> Đủ | C23: =CE23 -> 0 | G23: G07-VTC01-012 | H23: Tôn tấm | I23: PL20x2000x6000 | J23: Q235A/SS400 | K23: m2 | L23: =7.85*20 -> 157 | M23: =+N23/L23 -> 10.34868 | N23: 1624.7428 | W23: 12 | X23: 1884 | AA23: =O23+Q23+S23+U23+W23+Y23 -> 12 | AB23: =P23+R23+T23+V23+X23+Z23 -> 1884 | AC23: REV04-support dầm chính | AI23: =IF(AA23>AE23,AA23-AE23,"0") -> 12 | AJ23: =IF(AB23>AF23,AB23-AF23,"0") -> 1884 | AL23: ? | AM23: Hùng Nguyên | AN23: Thép tấm 20x2000x6000 SS400 | AO23: SS400 | AP23: 1884 | AQ23: 46050 | AR23: 12 | AS23: 1884 | AT23: 13818.18 | AU23: =AT23*AS23*1.1 -> 28636796 | AV23: 0.1 | AW23: =AT23*AS23 -> 26033451 | AX23: 46050 | AY23: =SUMIF($I:$I,I23,$AR:$AR) -> 12 | AZ23: =SUMIF($I:$I,I23,$AS:$AS) -> 1884 | BW23: =SUMIF($I:$I,I23,$BK:$BK) -> 0 | BX23: =SUMIF($I:$I,I23,$BL:$BL) -> 0 | CC23: =AY23+BW23 -> 12 | CD23: =AZ23+BX23 -> 1884 | CE23: =AI23-CC23 -> 0 | CF23: =AJ23-CD23 -> 0 | CG23: =IF(CE23<0,"Thừa",IF(CE23=0,"Đủ","Thiếu")) -> Đủ
A24: =IF(G24=G23,"ok","Hiện") -> Hiện | B24: =CG24 -> Đủ | C24: =CE24 -> 0 | G24: G07-VTC01-013 | H24: Thép hình H | I24: H125x125x6.5.9 | J24: Q235A/SS400 | K24: m | L24: 23.8 | M24: =0.237*108 -> 25.596 | N24: =+M24*L24 -> 609.1848 | W24: 26 | X24: 618.8 | AA24: =O24+Q24+S24+U24+W24+Y24 -> 26 | AB24: =P24+R24+T24+V24+X24+Z24 -> 618.8 | AC24: REV04-support dầm chính | AE24: 26 | AF24: 618.8 | AH24: Sử dụng hàng tồn | AI24: =IF(AA24>AE24,AA24-AE24,"0") -> 0 | AJ24: =IF(AB24>AF24,AB24-AF24,"0") -> 0 | AY24: =SUMIF($I:$I,I24,$AR:$AR) -> 0 | AZ24: =SUMIF($I:$I,I24,$AS:$AS) -> 0 | BW24: =SUMIF($I:$I,I24,$BK:$BK) -> 0 | BX24: =SUMIF($I:$I,I24,$BL:$BL) -> 0 | CC24: =AY24+BW24 -> 0 | CD24: =AZ24+BX24 -> 0 | CE24: =AI24-CC24 -> 0 | CF24: =AJ24-CD24 -> 0 | CG24: =IF(CE24<0,"Thừa",IF(CE24=0,"Đủ","Thiếu")) -> Đủ
G25: VTC02 | H25: Main-Material / Vật tư chính thép trắng | AA25: =SUM(AA26:AA27) -> 0 | AB25: =SUM(AB26:AB27) -> 0 | AC25: =SUM(AC26:AC27) -> 0 | AD25: =SUM(AD26:AD27) -> 0 | AE25: =SUM(AE26:AE27) -> 0 | AF25: =SUM(AF26:AF27) -> 0 | AG25: =SUM(AG26:AG27) -> 0 | AH25: =SUM(AH26:AH27) -> 0 | ... CH25: =SUM(CH26:CH27) -> 0
G28: VTC03 | H28: Gratting-Material / Vật tư gratting | AA28: =SUM(AA29:AA30) -> 0 | AB28: =SUM(AB29:AB30) -> 0 | AC28: =SUM(AC29:AC30) -> 0 | AD28: =SUM(AD29:AD30) -> 0 | AE28: =SUM(AE29:AE30) -> 0 | AF28: =SUM(AF29:AF30) -> 0 | AG28: =SUM(AG29:AG30) -> 0 | AH28: =SUM(AH29:AH30) -> 0 | ... CH28: =SUM(CH29:CH30) -> 0
G31: VTC04 | H31: Insulation-Material / Vật tư bảo ôn | AA31: =SUM(AA32) -> 0 | AB31: =SUM(AB32) -> 0 | AC31: =SUM(AC32) -> 0 | AD31: =SUM(AD32) -> 0 | AE31: =SUM(AE32) -> 0 | AF31: =SUM(AF32) -> 0 | AG31: =SUM(AG32) -> 0 | AH31: =SUM(AH32) -> 0 | ... CH31: =SUM(CH32) -> 0
G33: VPK | H33: Bolt-Material / Vật tư bulong, phụ kiện | AA33: =SUM(AA34:AA58) -> 3981 | AB33: =SUM(AB34:AB58) -> 0 | AC33: =SUM(AC34:AC58) -> 0 | AD33: =SUM(AD34:AD58) -> 0 | AE33: =SUM(AE34:AE58) -> 0 | AF33: =SUM(AF34:AF58) -> 0 | AG33: =SUM(AG34:AG58) -> 0 | AH33: =SUM(AH34:AH58) -> 0 | ... CH33: =SUM(CH34:CH58) -> 0
A34: =IF(G34=G33,"ok","Hiện") -> Hiện | B34: =CG34 -> Đủ | C34: =CE34 -> 0 | G34: G07-VPK-001 | H34: Bolt | I34: Bolt M24x150-8.8-DIN933-HDG | J34: mạ kẽm nhúng nóng | K34: pcs | M34: 61 | O34: 61 | P34: 0 | U34: 0 | V34: 0 | W34: 0 | X34: 0 | AA34: =O34+Q34+S34+U34+W34+Y34 -> 61 | AB34: =P34+R34+T34+V34+X34+Z34 -> 0 | AC34: REV02-Sửa lại cho đúng số lượng do rev1 bi sai | AI34: =IF(AA34>AE34,AA34-AE34,"0") -> 61 | AJ34: =IF(AB34>AF34,AB34-AF34,"0") -> 0 | AK34: Chưa có | AL34: ? | AM34: VSAN | AN34: M24*150 | AO34: Mạ kẽm nhúng nóng 5.6 | AP34: N/A | AQ34: ? | AR34: 61 | AS34: N/A | AT34: 52000 | AU34: =AT34*AR34*1.08 -> 3425760 | AV34: 0.08 | AW34: =AT34*AR34 -> 3172000 | AX34: 46079 | AY34: =SUMIF($I:$I,I34,$AR:$AR) -> 61 | AZ34: =SUMIF($I:$I,I34,$AS:$AS) -> 0 | BW34: =SUMIF($I:$I,I34,$BK:$BK) -> 0 | BX34: =SUMIF($I:$I,I34,$BL:$BL) -> 0 | CC34: =AY34+BW34 -> 61 | CD34: =AZ34+BX34 -> 0 | CE34: =AI34-CC34 -> 0 | CF34: =AJ34-CD34 -> 0 | CG34: =IF(CE34<0,"Thừa",IF(CE34=0,"Đủ","Thiếu")) -> Đủ
A35: =IF(G35=G34,"ok","Hiện") -> Hiện | B35: =CG35 -> Đủ | C35: =CE35 -> 0 | G35: G07-VPK-002 | H35: Bolt | I35: Bolt M6x20-DIN912 | J35: SUS304 | K35: pcs | M35: 350 | O35: 350 | P35: 0 | U35: 0 | V35: 0 | W35: 0 | X35: 0 | AA35: =O35+Q35+S35+U35+W35+Y35 -> 350 | AB35: =P35+R35+T35+V35+X35+Z35 -> 0 | AC35: REV02-Sửa lại cho đúng số lượng do rev1 bi sai | AI35: =IF(AA35>AE35,AA35-AE35,"0") -> 350 | AJ35: =IF(AB35>AF35,AB35-AF35,"0") -> 0 | AK35: Chưa có | AL35: ? | AM35: Hoàng Hà | AN35: M6*20 | AO35: Inox 304 | AP35: N/A | AQ35: ? | AR35: 350 | AS35: N/A | AT35: 914 | AU35: =AT35*AR35*1.08 -> 345492 | AV35: 0.08 | AW35: =AT35*AR35 -> 319900 | AX35: 46062 | AY35: =SUMIF($I:$I,I35,$AR:$AR) -> 350 | AZ35: =SUMIF($I:$I,I35,$AS:$AS) -> 0 | BW35: =SUMIF($I:$I,I35,$BK:$BK) -> 0 | BX35: =SUMIF($I:$I,I35,$BL:$BL) -> 0 | CC35: =AY35+BW35 -> 350 | CD35: =AZ35+BX35 -> 0 | CE35: =AI35-CC35 -> 0 | CF35: =AJ35-CD35 -> 0 | CG35: =IF(CE35<0,"Thừa",IF(CE35=0,"Đủ","Thiếu")) -> Đủ
A36: =IF(G36=G35,"ok","Hiện") -> Hiện | B36: =CG36 -> Đủ | C36: =CE36 -> 0 | G36: G07-VPK-003 | H36: Bolt | I36: Bolt M6x50-DIN912 | J36: SUS304 | K36: pcs | M36: 380 | O36: 380 | P36: 0 | U36: 0 | V36: 0 | W36: 0 | X36: 0 | AA36: =O36+Q36+S36+U36+W36+Y36 -> 380 | AB36: =P36+R36+T36+V36+X36+Z36 -> 0 | AC36: REV01-bỏ cấp bền thừa ở profile, chuyển sang DIN912 | AI36: =IF(AA36>AE36,AA36-AE36,"0") -> 380 | AJ36: =IF(AB36>AF36,AB36-AF36,"0") -> 0 | AK36: Chưa có | AL36: ? | AM36: Hoàng Hà | AN36: M6*50 | AO36: Inox 304 | AP36: N/A | AQ36: ? | AR36: 380 | AS36: N/A | AT36: 1711 | AU36: =AT36*AR36*1.08 -> 702194.4 | AV36: 0.08 | AW36: =AT36*AR36 -> 650180 | AX36: 46062 | AY36: =SUMIF($I:$I,I36,$AR:$AR) -> 380 | AZ36: =SUMIF($I:$I,I36,$AS:$AS) -> 0 | BW36: =SUMIF($I:$I,I36,$BK:$BK) -> 0 | BX36: =SUMIF($I:$I,I36,$BL:$BL) -> 0 | CC36: =AY36+BW36 -> 380 | CD36: =AZ36+BX36 -> 0 | CE36: =AI36-CC36 -> 0 | CF36: =AJ36-CD36 -> 0 | CG36: =IF(CE36<0,"Thừa",IF(CE36=0,"Đủ","Thiếu")) -> Đủ
A37: =IF(G37=G36,"ok","Hiện") -> Hiện | B37: =CG37 -> Đủ | C37: =CE37 -> 0 | G37: G07-VPK-004 | H37: Bolt | I37: Bolt M8x30-8.8-DIN912 | J37: SUS304 | K37: pcs | M37: 120 | O37: 120 | P37: 0 | U37: 0 | V37: 0 | W37: 0 | X37: 0 | AA37: =O37+Q37+S37+U37+W37+Y37 -> 120 | AB37: =P37+R37+T37+V37+X37+Z37 -> 0 | AC37: REV01-đổi cấp bền, , chuyển sang DIN912 | AI37: =IF(AA37>AE37,AA37-AE37,"0") -> 120 | AJ37: =IF(AB37>AF37,AB37-AF37,"0") -> 0 | AK37: Chưa có | AL37: ? | AM37: Hoàng Hà | AN37: M8*30 | AO37: Inox 304 | AP37: N/A | AQ37: ? | AR37: 120 | AS37: N/A | AT37: 2277 | AU37: =AT37*AR37*1.08 -> 295099.2 | AV37: 0.08 | AW37: =AT37*AR37 -> 273240 | AX37: 46062 | AY37: =SUMIF($I:$I,I37,$AR:$AR) -> 120 | AZ37: =SUMIF($I:$I,I37,$AS:$AS) -> 0 | BW37: =SUMIF($I:$I,I37,$BK:$BK) -> 0 | BX37: =SUMIF($I:$I,I37,$BL:$BL) -> 0 | CC37: =AY37+BW37 -> 120 | CD37: =AZ37+BX37 -> 0 | CE37: =AI37-CC37 -> 0 | CF37: =AJ37-CD37 -> 0 | CG37: =IF(CE37<0,"Thừa",IF(CE37=0,"Đủ","Thiếu")) -> Đủ
A38: =IF(G38=G37,"ok","Hiện") -> Hiện | B38: =CG38 -> Đủ | C38: =CE38 -> 0 | G38: G07-VPK-005 | H38: Nut | I38: Nut M24-8.0-DIN934-HDG | J38: mạ kẽm nhúng nóng | K38: pcs | M38: 122 | O38: 122 | P38: 0 | U38: 0 | V38: 0 | W38: 0 | X38: 0 | AA38: =O38+Q38+S38+U38+W38+Y38 -> 122 | AB38: =P38+R38+T38+V38+X38+Z38 -> 0 | AI38: =IF(AA38>AE38,AA38-AE38,"0") -> 122 | AJ38: =IF(AB38>AF38,AB38-AF38,"0") -> 0 | AK38: Chưa có | AL38: ? | AM38: VSAN | AN38: M24 | AO38: Mạ kẽm nhúng nóng 5.6 | AP38: N/A | AQ38: ? | AR38: 122 | AS38: N/A | AT38: 7500 | AU38: =AT38*AR38*1.08 -> 988200 | AV38: 0.08 | AW38: =AT38*AR38 -> 915000 | AX38: 46079 | AY38: =SUMIF($I:$I,I38,$AR:$AR) -> 122 | AZ38: =SUMIF($I:$I,I38,$AS:$AS) -> 0 | BW38: =SUMIF($I:$I,I38,$BK:$BK) -> 0 | BX38: =SUMIF($I:$I,I38,$BL:$BL) -> 0 | CC38: =AY38+BW38 -> 122 | CD38: =AZ38+BX38 -> 0 | CE38: =AI38-CC38 -> 0 | CF38: =AJ38-CD38 -> 0 | CG38: =IF(CE38<0,"Thừa",IF(CE38=0,"Đủ","Thiếu")) -> Đủ
A39: =IF(G39=G38,"ok","Hiện") -> Hiện | B39: =CG39 -> Đủ | C39: =CE39 -> 0 | G39: G07-VPK-006 | H39: Washer | I39: Washer M24-8.8-DIN127-HDG | J39: mạ kẽm nhúng nóng | K39: pcs | M39: 61 | O39: 61 | P39: 0 | U39: 0 | V39: 0 | W39: 0 | X39: 0 | AA39: =O39+Q39+S39+U39+W39+Y39 -> 61 | AB39: =P39+R39+T39+V39+X39+Z39 -> 0 | AI39: =IF(AA39>AE39,AA39-AE39,"0") -> 61 | AJ39: =IF(AB39>AF39,AB39-AF39,"0") -> 0 | AK39: Chưa có | AL39: ? | AM39: VSAN | AN39: M24 | AO39: Mạ kẽm nhúng nóng | AP39: N/A | AQ39: ? | AR39: 61 | AS39: N/A | AT39: 1450 | AU39: =AT39*AR39*1.08 -> 95526 | AV39: 0.08 | AW39: =AT39*AR39 -> 88450 | AX39: 46079 | AY39: =SUMIF($I:$I,I39,$AR:$AR) -> 61 | AZ39: =SUMIF($I:$I,I39,$AS:$AS) -> 0 | BW39: =SUMIF($I:$I,I39,$BK:$BK) -> 0 | BX39: =SUMIF($I:$I,I39,$BL:$BL) -> 0 | CC39: =AY39+BW39 -> 61 | CD39: =AZ39+BX39 -> 0 | CE39: =AI39-CC39 -> 0 | CF39: =AJ39-CD39 -> 0 | CG39: =IF(CE39<0,"Thừa",IF(CE39=0,"Đủ","Thiếu")) -> Đủ
A40: =IF(G40=G39,"ok","Hiện") -> Hiện | B40: =CG40 -> Đủ | C40: =CE40 -> 0 | G40: G07-VPK-007 | H40: Washer | I40: Washer M6-DIN125A | J40: SUS304 | K40: pcs | M40: 380 | O40: 380 | P40: 0 | U40: 0 | V40: 0 | W40: 0 | X40: 0 | AA40: =O40+Q40+S40+U40+W40+Y40 -> 380 | AB40: =P40+R40+T40+V40+X40+Z40 -> 0 | AC40: REV01-bỏ cấp bền thừa ở profile | AI40: =IF(AA40>AE40,AA40-AE40,"0") -> 380 | AJ40: =IF(AB40>AF40,AB40-AF40,"0") -> 0 | AK40: Chưa có | AL40: ? | AM40: Hoàng Hà | AN40: M6 | AO40: Inox 304 | AP40: N/A | AQ40: ? | AR40: 380 | AS40: N/A | AT40: 150 | AU40: =AT40*AR40*1.08 -> 61560 | AV40: 0.08 | AW40: =AT40*AR40 -> 57000 | AX40: 46062 | AY40: =SUMIF($I:$I,I40,$AR:$AR) -> 380 | AZ40: =SUMIF($I:$I,I40,$AS:$AS) -> 0 | BW40: =SUMIF($I:$I,I40,$BK:$BK) -> 0 | BX40: =SUMIF($I:$I,I40,$BL:$BL) -> 0 | CC40: =AY40+BW40 -> 380 | CD40: =AZ40+BX40 -> 0 | CE40: =AI40-CC40 -> 0 | CF40: =AJ40-CD40 -> 0 | CG40: =IF(CE40<0,"Thừa",IF(CE40=0,"Đủ","Thiếu")) -> Đủ
A41: =IF(G41=G40,"ok","Hiện") -> Hiện | B41: =CG41 -> Đủ | C41: =CE41 -> 0 | G41: G07-VPK-008 | H41: Washer | I41: Washer M6-DIN127 | J41: SUS304 | K41: pcs | M41: 730 | O41: 730 | P41: 0 | U41: 0 | V41: 0 | W41: 0 | X41: 0 | AA41: =O41+Q41+S41+U41+W41+Y41 -> 730 | AB41: =P41+R41+T41+V41+X41+Z41 -> 0 | AC41: REV01-bỏ cấp bền thừa ở profile | AI41: =IF(AA41>AE41,AA41-AE41,"0") -> 730 | AJ41: =IF(AB41>AF41,AB41-AF41,"0") -> 0 | AK41: Chưa có | AL41: ? | AM41: Hoàng Hà | AN41: M6 | AO41: Inox 304 | AP41: N/A | AQ41: ? | AR41: 730 | AS41: N/A | AT41: 150 | AU41: =AT41*AR41*1.08 -> 118260 | AV41: 0.08 | AW41: =AT41*AR41 -> 109500 | AX41: 46062 | AY41: =SUMIF($I:$I,I41,$AR:$AR) -> 730 | AZ41: =SUMIF($I:$I,I41,$AS:$AS) -> 0 | BW41: =SUMIF($I:$I,I41,$BK:$BK) -> 0 | BX41: =SUMIF($I:$I,I41,$BL:$BL) -> 0 | CC41: =AY41+BW41 -> 730 | CD41: =AZ41+BX41 -> 0 | CE41: =AI41-CC41 -> 0 | CF41: =AJ41-CD41 -> 0 | CG41: =IF(CE41<0,"Thừa",IF(CE41=0,"Đủ","Thiếu")) -> Đủ
A42: =IF(G42=G41,"ok","Hiện") -> Hiện | B42: =CG42 -> Đủ | C42: =CE42 -> 0 | G42: G07-VPK-009 | H42: Washer | I42: Washer M8-DIN125A | J42: SUS304 | K42: pcs | M42: 120 | O42: 120 | P42: 0 | U42: 0 | V42: 0 | W42: 0 | X42: 0 | AA42: =O42+Q42+S42+U42+W42+Y42 -> 120 | AB42: =P42+R42+T42+V42+X42+Z42 -> 0 | AC42: REV01-đổi cấp bền | AI42: =IF(AA42>AE42,AA42-AE42,"0") -> 120 | AJ42: =IF(AB42>AF42,AB42-AF42,"0") -> 0 | AK42: Chưa có | AL42: ? | AM42: Hoàng Hà | AN42: M8 | AO42: Inox 304 | AP42: N/A | AQ42: ? | AR42: 120 | AS42: N/A | AT42: 300 | AU42: =AT42*AR42*1.08 -> 38880 | AV42: 0.08 | AW42: =AT42*AR42 -> 36000 | AX42: 46062 | AY42: =SUMIF($I:$I,I42,$AR:$AR) -> 120 | AZ42: =SUMIF($I:$I,I42,$AS:$AS) -> 0 | BW42: =SUMIF($I:$I,I42,$BK:$BK) -> 0 | BX42: =SUMIF($I:$I,I42,$BL:$BL) -> 0 | CC42: =AY42+BW42 -> 120 | CD42: =AZ42+BX42 -> 0 | CE42: =AI42-CC42 -> 0 | CF42: =AJ42-CD42 -> 0 | CG42: =IF(CE42<0,"Thừa",IF(CE42=0,"Đủ","Thiếu")) -> Đủ
A43: =IF(G43=G42,"ok","Hiện") -> Hiện | B43: =CG43 -> Đủ | C43: =CE43 -> 0 | G43: G07-VPK-010 | H43: Washer | I43: Washer M8-DIN127 | J43: SUS304 | K43: pcs | M43: 120 | O43: 120 | P43: 0 | U43: 0 | V43: 0 | W43: 0 | X43: 0 | AA43: =O43+Q43+S43+U43+W43+Y43 -> 120 | AB43: =P43+R43+T43+V43+X43+Z43 -> 0 | AC43: REV01-đổi cấp bền | AI43: =IF(AA43>AE43,AA43-AE43,"0") -> 120 | AJ43: =IF(AB43>AF43,AB43-AF43,"0") -> 0 | AK43: Chưa có | AL43: ? | AM43: Hoàng Hà | AN43: M8 | AO43: Inox 304 | AP43: N/A | AQ43: ? | AR43: 120 | AS43: N/A | AT43: 300 | AU43: =AT43*AR43*1.08 -> 38880 | AV43: 0.08 | AW43: =AT43*AR43 -> 36000 | AX43: 46062 | AY43: =SUMIF($I:$I,I43,$AR:$AR) -> 120 | AZ43: =SUMIF($I:$I,I43,$AS:$AS) -> 0 | BW43: =SUMIF($I:$I,I43,$BK:$BK) -> 0 | BX43: =SUMIF($I:$I,I43,$BL:$BL) -> 0 | CC43: =AY43+BW43 -> 120 | CD43: =AZ43+BX43 -> 0 | CE43: =AI43-CC43 -> 0 | CF43: =AJ43-CD43 -> 0 | CG43: =IF(CE43<0,"Thừa",IF(CE43=0,"Đủ","Thiếu")) -> Đủ
A44: =IF(G44=G43,"ok","Hiện") -> Hiện | B44: =CG44 -> Đủ | C44: =CE44 -> 0 | G44: G07-VPK-011 | H44: Tấm chống cháy SILICON-20mm | I44: PL20x190x500xSILICON COMPOSTE, 60 SHORE A | J44: SILICON COMPOSTE, 60 SHORE A | K44: pcs | M44: 330 | O44: 330 | P44: 0 | Q44: -330 | R44: 0 | U44: 0 | V44: 0 | W44: 0 | X44: 0 | AA44: =O44+Q44+S44+U44+W44+Y44 -> 0 | AB44: =P44+R44+T44+V44+X44+Z44 -> 0 | AC44: REV01-hủy không dùng | AI44: =IF(AA44>AE44,AA44-AE44,"0") -> 0 | AJ44: =IF(AB44>AF44,AB44-AF44,"0") -> 0 | AK44: Chưa có | AY44: =SUMIF($I:$I,I44,$AR:$AR) -> 0 | AZ44: =SUMIF($I:$I,I44,$AS:$AS) -> 0 | BW44: =SUMIF($I:$I,I44,$BK:$BK) -> 0 | BX44: =SUMIF($I:$I,I44,$BL:$BL) -> 0 | CC44: =AY44+BW44 -> 0 | CD44: =AZ44+BX44 -> 0 | CE44: =AI44-CC44 -> 0 | CF44: =AJ44-CD44 -> 0 | CG44: =IF(CE44<0,"Thừa",IF(CE44=0,"Đủ","Thiếu")) -> Đủ
A45: =IF(G45=G44,"ok","Hiện") -> Hiện | B45: =CG45 -> Đủ | C45: =CE45 -> 0 | G45: G07-VPK-012 | H45: Bánh xe -loại cổ quay | I45: SUPO 12J-65S-PA (loại cổ quay) | J45: Steel-mạ kẽm | K45: pcs | M45: 162 | U45: 165 | V45: 0 | W45: 0 | X45: 0 | AA45: =O45+Q45+S45+U45+W45+Y45 -> 165 | AB45: =P45+R45+T45+V45+X45+Z45 -> 0 | AC45: REV03-bổ sung mới | AI45: =IF(AA45>AE45,AA45-AE45,"0") -> 165 | AJ45: =IF(AB45>AF45,AB45-AF45,"0") -> 0 | AL45: ? | AM45: MRO | AN45: Bánh xe | AP45: N/A | AQ45: ? | AR45: 165 | AS45: N/A | AT45: =1.4*96000 -> 134400 | AU45: =AT45*AR45*1.08 -> 23950080 | AV45: 0.08 | AW45: =AT45*AR45 -> 22176000 | AX45: 46058 | AY45: =SUMIF($I:$I,I45,$AR:$AR) -> 165 | AZ45: =SUMIF($I:$I,I45,$AS:$AS) -> 0 | BW45: =SUMIF($I:$I,I45,$BK:$BK) -> 0 | BX45: =SUMIF($I:$I,I45,$BL:$BL) -> 0 | CC45: =AY45+BW45 -> 165 | CD45: =AZ45+BX45 -> 0 | CE45: =AI45-CC45 -> 0 | CF45: =AJ45-CD45 -> 0 | CG45: =IF(CE45<0,"Thừa",IF(CE45=0,"Đủ","Thiếu")) -> Đủ
A46: =IF(G46=G45,"ok","Hiện") -> Hiện | B46: =CG46 -> Đủ | C46: =CE46 -> 0 | G46: G07-VPK-013 | H46: Bulông nở | I46: Bulong nở M16x150-HDG | J46: mạ kẽm nhúng nóng | K46: pcs | M46: 174 | W46: 176 | X46: 0 | AA46: =O46+Q46+S46+U46+W46+Y46 -> 176 | AB46: =P46+R46+T46+V46+X46+Z46 -> 0 | AC46: REV04-support dầm chính + tank | AI46: =IF(AA46>AE46,AA46-AE46,"0") -> 176 | AJ46: =IF(AB46>AF46,AB46-AF46,"0") -> 0 | AL46: ? | AM46: Hoàng Hà | AN46: Bulong nở M16x150-HDG | AP46: N/A | AQ46: ? | AR46: 176 | AS46: N/A | AT46: 22500 | AU46: =AT46*AR46*1.08 -> 4276800 | AV46: 0.08 | AW46: =AT46*AR46 -> 3960000 | AX46: 46062 | AY46: =SUMIF($I:$I,I46,$AR:$AR) -> 176 | AZ46: =SUMIF($I:$I,I46,$AS:$AS) -> 0 | BW46: =SUMIF($I:$I,I46,$BK:$BK) -> 0 | BX46: =SUMIF($I:$I,I46,$BL:$BL) -> 0 | CC46: =AY46+BW46 -> 176 | CD46: =AZ46+BX46 -> 0 | CE46: =AI46-CC46 -> 0 | CF46: =AJ46-CD46 -> 0 | CG46: =IF(CE46<0,"Thừa",IF(CE46=0,"Đủ","Thiếu")) -> Đủ
A47: =IF(G47=G46,"ok","Hiện") -> Hiện | B47: =CG47 -> Đủ | C47: =CE47 -> 0 | G47: G07-VPK-014 | H47: Bolt | I47: Bolt M16x100-8.8-DIN933-HDG | J47: mạ kẽm nhúng nóng | K47: pcs | M47: 60 | W47: 65 | X47: 0 | AA47: =O47+Q47+S47+U47+W47+Y47 -> 65 | AB47: =P47+R47+T47+V47+X47+Z47 -> 0 | AC47: REV04-support dầm chính | AI47: =IF(AA47>AE47,AA47-AE47,"0") -> 65 | AJ47: =IF(AB47>AF47,AB47-AF47,"0") -> 0 | AL47: ? | AM47: Hoàng Hà | AN47: Bolt M16x100-8.8-DIN933-HDG | AP47: N/A | AQ47: ? | AR47: 65 | AS47: N/A | AT47: 14700 | AU47: =AT47*AR47*1.08 -> 1031940 | AV47: 0.08 | AW47: =AT47*AR47 -> 955500 | AX47: 46062 | AY47: =SUMIF($I:$I,I47,$AR:$AR) -> 65 | AZ47: =SUMIF($I:$I,I47,$AS:$AS) -> 0 | BW47: =SUMIF($I:$I,I47,$BK:$BK) -> 0 | BX47: =SUMIF($I:$I,I47,$BL:$BL) -> 0 | CC47: =AY47+BW47 -> 65 | CD47: =AZ47+BX47 -> 0 | CE47: =AI47-CC47 -> 0 | CF47: =AJ47-CD47 -> 0 | CG47: =IF(CE47<0,"Thừa",IF(CE47=0,"Đủ","Thiếu")) -> Đủ
A48: =IF(G48=G47,"ok","Hiện") -> Hiện | B48: =CG48 -> Đủ | C48: =CE48 -> 0 | G48: G07-VPK-015 | H48: Nut | I48: Nut M16-8.0-DIN934-HDG | J48: mạ kẽm nhúng nóng | K48: pcs | M48: 120 | W48: 130 | X48: 0 | AA48: =O48+Q48+S48+U48+W48+Y48 -> 130 | AB48: =P48+R48+T48+V48+X48+Z48 -> 0 | AC48: REV04-support dầm chính | AI48: =IF(AA48>AE48,AA48-AE48,"0") -> 130 | AJ48: =IF(AB48>AF48,AB48-AF48,"0") -> 0 | AL48: ? | AM48: Hoàng Hà | AN48: Nut M16-8.0-DIN934-HDG | AP48: N/A | AQ48: ? | AR48: 130 | AS48: N/A | AU48: =AT48*AR48*1.08 -> 0 | AV48: 0.08 | AW48: =AT48*AR48 -> 0 | AX48: 46062 | AY48: =SUMIF($I:$I,I48,$AR:$AR) -> 130 | AZ48: =SUMIF($I:$I,I48,$AS:$AS) -> 0 | BW48: =SUMIF($I:$I,I48,$BK:$BK) -> 0 | BX48: =SUMIF($I:$I,I48,$BL:$BL) -> 0 | CC48: =AY48+BW48 -> 130 | CD48: =AZ48+BX48 -> 0 | CE48: =AI48-CC48 -> 0 | CF48: =AJ48-CD48 -> 0 | CG48: =IF(CE48<0,"Thừa",IF(CE48=0,"Đủ","Thiếu")) -> Đủ
A49: =IF(G49=G48,"ok","Hiện") -> Hiện | B49: =CG49 -> Thiếu | C49: =CE49 -> 1 | E49: MRO hàng chưa về | G49: G07-VPK-016 | H49: Aptomat | I49: Aptomat 350A-loại 3 pha | K49: pcs | M49: 1 | W49: 1 | X49: 0 | AA49: =O49+Q49+S49+U49+W49+Y49 -> 1 | AB49: =P49+R49+T49+V49+X49+Z49 -> 0 | AC49: REV04-support dầm chính | AI49: =IF(AA49>AE49,AA49-AE49,"0") -> 1 | AJ49: =IF(AB49>AF49,AB49-AF49,"0") -> 0 | AY49: =SUMIF($I:$I,I49,$AR:$AR) -> 0 | AZ49: =SUMIF($I:$I,I49,$AS:$AS) -> 0 | BW49: =SUMIF($I:$I,I49,$BK:$BK) -> 0 | BX49: =SUMIF($I:$I,I49,$BL:$BL) -> 0 | CC49: =AY49+BW49 -> 0 | CD49: =AZ49+BX49 -> 0 | CE49: =AI49-CC49 -> 1 | CF49: =AJ49-CD49 -> 0 | CG49: =IF(CE49<0,"Thừa",IF(CE49=0,"Đủ","Thiếu")) -> Thiếu
A50: =IF(G50=G49,"ok","Hiện") -> Hiện | B50: =CG50 -> Thiếu | C50: =CE50 -> 1 | E50: MRO hàng chưa về | G50: G07-VPK-017 | H50: Aptomat | I50: Aptomat 100A-loại 3 pha | K50: pcs | M50: 1 | W50: 1 | X50: 0 | AA50: =O50+Q50+S50+U50+W50+Y50 -> 1 | AB50: =P50+R50+T50+V50+X50+Z50 -> 0 | AC50: REV04-support dầm chính | AI50: =IF(AA50>AE50,AA50-AE50,"0") -> 1 | AJ50: =IF(AB50>AF50,AB50-AF50,"0") -> 0 | AY50: =SUMIF($I:$I,I50,$AR:$AR) -> 0 | AZ50: =SUMIF($I:$I,I50,$AS:$AS) -> 0 | BW50: =SUMIF($I:$I,I50,$BK:$BK) -> 0 | BX50: =SUMIF($I:$I,I50,$BL:$BL) -> 0 | CC50: =AY50+BW50 -> 0 | CD50: =AZ50+BX50 -> 0 | CE50: =AI50-CC50 -> 1 | CF50: =AJ50-CD50 -> 0 | CG50: =IF(CE50<0,"Thừa",IF(CE50=0,"Đủ","Thiếu")) -> Thiếu
A51: =IF(G51=G50,"ok","Hiện") -> Hiện | B51: =CG51 -> Thừa | C51: =CE51 -> -3 | G51: G07-VPK-018 | H51: Tiếp địa | I51: Tiếp địa D16-L2000 | J51: Đồng | K51: pcs | M51: 3 | W51: 3 | X51: 0 | AA51: =O51+Q51+S51+U51+W51+Y51 -> 3 | AB51: =P51+R51+T51+V51+X51+Z51 -> 0 | AC51: REV04-support dầm chính | AI51: =IF(AA51>AE51,AA51-AE51,"0") -> 3 | AJ51: =IF(AB51>AF51,AB51-AF51,"0") -> 0 | AL51: Báo giá ngày 4/2/2026 | AM51: Mr Phong | AN51: Thanh đông D20 | AP51: N/A | AQ51: 46058 | AR51: 6 | AS51: 17.5 | AT51: 540000 | AU51: =AT51*AS51*1.1 -> 10395000 | AV51: 0.1 | AW51: =AT51*AS51 -> 9450000 | AX51: 46057 | AY51: =SUMIF($I:$I,I51,$AR:$AR) -> 6 | AZ51: =SUMIF($I:$I,I51,$AS:$AS) -> 17.5 | BW51: =SUMIF($I:$I,I51,$BK:$BK) -> 0 | BX51: =SUMIF($I:$I,I51,$BL:$BL) -> 0 | CC51: =AY51+BW51 -> 6 | CD51: =AZ51+BX51 -> 17.5 | CE51: =AI51-CC51 -> -3 | CF51: =AJ51-CD51 -> -17.5 | CG51: =IF(CE51<0,"Thừa",IF(CE51=0,"Đủ","Thiếu")) -> Thừa
A52: =IF(G52=G51,"ok","Hiện") -> Hiện | B52: =CG52 -> Đủ | C52: =CE52 -> 0 | G52: G07-VPK-019 | H52: Nước cất 2 lần | I52: Nước cất 2 lần | J52: nước cất 2 lần | K52: Liter | M52: 300 | W52: 300 | X52: 0 | AA52: =O52+Q52+S52+U52+W52+Y52 -> 300 | AB52: =P52+R52+T52+V52+X52+Z52 -> 0 | AC52: REV04-support dầm chính | AI52: =IF(AA52>AE52,AA52-AE52,"0") -> 300 | AJ52: =IF(AB52>AF52,AB52-AF52,"0") -> 0 | AL52: Báo giá ngày 28/1/2026 | AM52: CÔNG TY TNHH TMDV HÓA CHẤT VÀ THIẾT BỊ VIỆT HƯNG | AN52: Nước cất | AP52: N/a | AQ52: 46051 | AR52: 300 | AS52: N/a | AT52: 5555.558 | AU52: =AT52*AR52*1.08 -> 1800000.8 | AV52: 0.08 | AW52: =AT52*AR52 -> 1666667.4 | AX52: 46051 | AY52: =SUMIF($I:$I,I52,$AR:$AR) -> 300 | AZ52: =SUMIF($I:$I,I52,$AS:$AS) -> 0 | BW52: =SUMIF($I:$I,I52,$BK:$BK) -> 0 | BX52: =SUMIF($I:$I,I52,$BL:$BL) -> 0 | CC52: =AY52+BW52 -> 300 | CD52: =AZ52+BX52 -> 0 | CE52: =AI52-CC52 -> 0 | CF52: =AJ52-CD52 -> 0 | CG52: =IF(CE52<0,"Thừa",IF(CE52=0,"Đủ","Thiếu")) -> Đủ
A53: =IF(G53=G52,"ok","Hiện") -> Hiện | B53: =CG53 -> Đủ | C53: =CE53 -> 0 | G53: G07-VPK-020 | H53: Threaded half coupling-không mạ | I53: 3/8" NPS Threaded half coupling #3000-ASME B16.11 | J53: ASME-SA105M | K53: pcs | M53: 4 | W53: 4 | X53: 0 | AA53: =O53+Q53+S53+U53+W53+Y53 -> 4 | AB53: =P53+R53+T53+V53+X53+Z53 -> 0 | AC53: REV04-tank | AI53: =IF(AA53>AE53,AA53-AE53,"0") -> 4 | AJ53: =IF(AB53>AF53,AB53-AF53,"0") -> 0 | AL53: Báo giá ngày 2/12/2026 | AM53: Tam Đa | AN53: 3/8" NPS Threaded half coupling #3000-ASME B16.11 | AP53: N/a | AQ53: 46065 | AR53: 4 | AS53: N/a | AT53: 0 | AU53: =AT53*AR53*1.08 -> 0 | AV53: 0.08 | AW53: =AT53*AR53 -> 0 | AX53: 46065 | AY53: =SUMIF($I:$I,I53,$AR:$AR) -> 4 | AZ53: =SUMIF($I:$I,I53,$AS:$AS) -> 0 | BW53: =SUMIF($I:$I,I53,$BK:$BK) -> 0 | BX53: =SUMIF($I:$I,I53,$BL:$BL) -> 0 | CC53: =AY53+BW53 -> 4 | CD53: =AZ53+BX53 -> 0 | CE53: =AI53-CC53 -> 0 | CF53: =AJ53-CD53 -> 0 | CG53: =IF(CE53<0,"Thừa",IF(CE53=0,"Đủ","Thiếu")) -> Đủ
A54: =IF(G54=G53,"ok","Hiện") -> Hiện | B54: =CG54 -> Đủ | C54: =CE54 -> 0 | G54: G07-VPK-021 | H54: Threaded half coupling-không mạ | I54: 3/4" NPS Threaded half coupling #3000-ASME B16.11 | J54: ASME-SA105M | K54: pcs | M54: 4 | W54: 4 | X54: 0 | AA54: =O54+Q54+S54+U54+W54+Y54 -> 4 | AB54: =P54+R54+T54+V54+X54+Z54 -> 0 | AC54: REV04-tank | AI54: =IF(AA54>AE54,AA54-AE54,"0") -> 4 | AJ54: =IF(AB54>AF54,AB54-AF54,"0") -> 0 | AL54: Báo giá ngày 2/12/2026 | AM54: Tam Đa | AN54: 3/4" NPS Threaded half coupling #3000-ASME B16.11 | AP54: N/a | AQ54: 46065 | AR54: 4 | AS54: N/a | AT54: 65000 | AU54: =AT54*AR54*1.08 -> 280800 | AV54: 0.08 | AW54: =AT54*AR54 -> 260000 | AX54: 46065 | AY54: =SUMIF($I:$I,I54,$AR:$AR) -> 4 | AZ54: =SUMIF($I:$I,I54,$AS:$AS) -> 0 | BW54: =SUMIF($I:$I,I54,$BK:$BK) -> 0 | BX54: =SUMIF($I:$I,I54,$BL:$BL) -> 0 | CC54: =AY54+BW54 -> 4 | CD54: =AZ54+BX54 -> 0 | CE54: =AI54-CC54 -> 0 | CF54: =AJ54-CD54 -> 0 | CG54: =IF(CE54<0,"Thừa",IF(CE54=0,"Đủ","Thiếu")) -> Đủ
A55: =IF(G55=G54,"ok","Hiện") -> Hiện | B55: =CG55 -> Đủ | C55: =CE55 -> 0 | G55: G07-VPK-022 | H55: Threaded half coupling-không mạ | I55: 1" NPS Threaded half coupling #3000-ASME B16.11 | J55: ASME-SA105M | K55: pcs | M55: 4 | W55: 4 | X55: 0 | AA55: =O55+Q55+S55+U55+W55+Y55 -> 4 | AB55: =P55+R55+T55+V55+X55+Z55 -> 0 | AC55: REV04-tank | AI55: =IF(AA55>AE55,AA55-AE55,"0") -> 4 | AJ55: =IF(AB55>AF55,AB55-AF55,"0") -> 0 | AL55: Báo giá ngày 2/12/2026 | AM55: Tam Đa | AN55: 1" NPS Threaded half coupling #3000-ASME B16.11 | AP55: N/a | AQ55: 46065 | AR55: 4 | AS55: N/a | AT55: 95000 | AU55: =AT55*AR55*1.08 -> 410400 | AV55: 0.08 | AW55: =AT55*AR55 -> 380000 | AX55: 46065 | AY55: =SUMIF($I:$I,I55,$AR:$AR) -> 4 | AZ55: =SUMIF($I:$I,I55,$AS:$AS) -> 0 | BW55: =SUMIF($I:$I,I55,$BK:$BK) -> 0 | BX55: =SUMIF($I:$I,I55,$BL:$BL) -> 0 | CC55: =AY55+BW55 -> 4 | CD55: =AZ55+BX55 -> 0 | CE55: =AI55-CC55 -> 0 | CF55: =AJ55-CD55 -> 0 | CG55: =IF(CE55<0,"Thừa",IF(CE55=0,"Đủ","Thiếu")) -> Đủ
A56: =IF(G56=G55,"ok","Hiện") -> Hiện | B56: =CG56 -> Đủ | C56: =CE56 -> 0 | G56: G07-VPK-023 | H56: Threaded half coupling-không mạ | I56: 2" NPS Threaded half coupling #3000-ASME B16.11 | J56: ASME-SA105M | K56: pcs | M56: 20 | W56: 20 | X56: 0 | AA56: =O56+Q56+S56+U56+W56+Y56 -> 20 | AB56: =P56+R56+T56+V56+X56+Z56 -> 0 | AC56: REV04-tank | AI56: =IF(AA56>AE56,AA56-AE56,"0") -> 20 | AJ56: =IF(AB56>AF56,AB56-AF56,"0") -> 0 | AL56: Báo giá ngày 2/12/2026 | AM56: Tam Đa | AN56: 2" NPS Threaded half coupling #3000-ASME B16.11 | AP56: N/a | AQ56: 46065 | AR56: 20 | AS56: N/a | AT56: 195000 | AU56: =AT56*AR56*1.08 -> 4212000 | AV56: 0.08 | AW56: =AT56*AR56 -> 3900000 | AX56: 46065 | AY56: =SUMIF($I:$I,I56,$AR:$AR) -> 20 | AZ56: =SUMIF($I:$I,I56,$AS:$AS) -> 0 | BW56: =SUMIF($I:$I,I56,$BK:$BK) -> 0 | BX56: =SUMIF($I:$I,I56,$BL:$BL) -> 0 | CC56: =AY56+BW56 -> 20 | CD56: =AZ56+BX56 -> 0 | CE56: =AI56-CC56 -> 0 | CF56: =AJ56-CD56 -> 0 | CG56: =IF(CE56<0,"Thừa",IF(CE56=0,"Đủ","Thiếu")) -> Đủ
A57: =IF(G57=G56,"ok","Hiện") -> Hiện | B57: =CG57 -> Đủ | C57: =CE57 -> 0 | G57: G07-VPK-024 | H57: plug | I57: 2" NPS Threaded hex head plug #3000-ASME B16.11 | J57: ASME-SA105M | K57: pcs | M57: 4 | W57: 4 | X57: 0 | AA57: =O57+Q57+S57+U57+W57+Y57 -> 4 | AB57: =P57+R57+T57+V57+X57+Z57 -> 0 | AC57: REV04-tank | AI57: =IF(AA57>AE57,AA57-AE57,"0") -> 4 | AJ57: =IF(AB57>AF57,AB57-AF57,"0") -> 0 | AL57: Báo giá ngày 2/12/2026 | AM57: Tam Đa | AN57: 2" NPS Threaded hex head plug #3000-ASME B16.11 | AP57: N/a | AQ57: 46065 | AR57: 4 | AS57: N/a | AT57: 260000 | AU57: =AT57*AR57*1.08 -> 1123200 | AV57: 0.08 | AW57: =AT57*AR57 -> 1040000 | AX57: 46065 | AY57: =SUMIF($I:$I,I57,$AR:$AR) -> 4 | AZ57: =SUMIF($I:$I,I57,$AS:$AS) -> 0 | BW57: =SUMIF($I:$I,I57,$BK:$BK) -> 0 | BX57: =SUMIF($I:$I,I57,$BL:$BL) -> 0 | CC57: =AY57+BW57 -> 4 | CD57: =AZ57+BX57 -> 0 | CE57: =AI57-CC57 -> 0 | CF57: =AJ57-CD57 -> 0 | CG57: =IF(CE57<0,"Thừa",IF(CE57=0,"Đủ","Thiếu")) -> Đủ
A58: =IF(G58=G57,"ok","Hiện") -> Hiện | B58: =CG58 -> Đủ | C58: =CE58 -> 0 | E58: Hoàng Hà | G58: G07-VPK-025 | H58: Bolt | I58: Bolt M8x35-A2-DIN933 (1bolt+1nut+2 plain washer) | K58: set | M58: 648 | Y58: 660 | AA58: =O58+Q58+S58+U58+W58+Y58 -> 660 | AB58: =P58+R58+T58+V58+X58+Z58 -> 0 | AC58: REV05-khay (bắt bánh xe) | AI58: =IF(AA58>AE58,AA58-AE58,"0") -> 660 | AJ58: =IF(AB58>AF58,AB58-AF58,"0") -> 0 | AM58: Hoàng Hà | AN58: Bolt M8x35-A2-DIN933 (1bolt+1nut+2 plain washer) | AR58: 660 | AX58: 46081 | AY58: =SUMIF($I:$I,I58,$AR:$AR) -> 660 | AZ58: =SUMIF($I:$I,I58,$AS:$AS) -> 0 | BW58: =SUMIF($I:$I,I58,$BK:$BK) -> 0 | BX58: =SUMIF($I:$I,I58,$BL:$BL) -> 0 | CC58: =AY58+BW58 -> 660 | CD58: =AZ58+BX58 -> 0 | CE58: =AI58-CC58 -> 0 | CF58: =AJ58-CD58 -> 0 | CG58: =IF(CE58<0,"Thừa",IF(CE58=0,"Đủ","Thiếu")) -> Đủ
G59: VTK | H59: Packing Material / Vật tư kiện | AB59: =SUM(AB60:AB108) -> 0 | AE59: =SUM(AE60:AE108) -> 0 | AF59: =SUM(AF60:AF108) -> 0 | AI59: =SUM(AI60:AI108) -> 0 | AJ59: =SUM(AJ60:AJ108) -> 0 | AP59: =SUM(AP60:AP108) -> 0 | AR59: =SUM(AR60:AR108) -> 0 | AS59: =SUM(AS60:AS108) -> 0 | AW59: =SUM(AW60:AW108) -> 0 | AY59: =SUM(AY60:AY108) -> 0 | AZ59: =SUM(AZ60:AZ108) -> 0 | BB59: =SUM(BB60:BB108) -> 0 | BC59: =SUM(BC60:BC108) -> 0 | BI59: =SUM(BI60:BI108) -> 0 | BK59: =SUM(BK60:BK108) -> 0 | BL59: =SUM(BL60:BL108) -> 0 | BN59: =SUM(BN60:BN108) -> 0 | BW59: =SUM(BW60:BW108) -> 0 | BX59: =SUM(BX60:BX108) -> 0 | BZ59: =SUM(BZ60:BZ108) -> 0 | CA59: =SUM(CA60:CA108) -> 0 | CB59: =SUM(CB60:CB108) -> 0 | CC59: =SUM(CC60:CC108) -> 0 | CD59: =SUM(CD60:CD108) -> 0 | CE59: =SUM(CE60:CE108) -> 0 | CF59: =SUM(CF60:CF108) -> 0

Sheet Tổng hợp
A1: Item/ STT | B1: Total Ordered/Tổng dự trù | D1: Tận dụng tồn kho/ Remain | G1: Khối lượng phải mua sắm/ total order | I1: VẬT TƯ TRONG NƯỚC | L1: VẬT TƯ OVERSEA | O1: Khối lượng phải mua còn lại theo PR/ total order from PR | Q1: Khối lượng phải mua còn lại/ total order
B2: Q.Ty/S.Lượng (M/M2/Set) | C2: Weight/K.Lượng (Kg) | D2: Q.Ty/S.Lượng (M/M2/Set) | E2: Weight/K.Lượng (Kg) | F2: Đã nghiệm thu (Kg) | G2: Q.Ty/ S.Lượng | H2: Weight/ K.Lượng (Kg) | I2: S.Lượng giao hàng thực tế/ Handover Q'ty | J2: K.Lượng giao hàng thực tế// Handover weight | K2: Khối lượng nghiệm thu đạt/ Weight Acc. Inspection | L2: S.Lượng giao hàng thực tế/ Handover Q'ty | M2: K.Lượng giao hàng thực tế// Handover weight | N2: Khối lượng nghiệm thu đạt/ Weight Acc. Inspection | O2: Q.Ty/S.Lượng (M/M2/Set) | P2: Weight/ K.Lượng (Kg) | Q2: Q.Ty/S.Lượng (M/M2/Set) | R2: Weight/ K.Lượng (Kg)
A3: VTC01 | B3: Main-Material / Vật tư chính thép đen
A4: 1 | B4: ='25-GEN-G-07'!AA7 -> 931.375 | C4: ='25-GEN-G-07'!AB7 -> 31090.659 | D4: ='25-GEN-G-07'!AE7 -> 40.375 | E4: ='25-GEN-G-07'!AF7 -> 1107.6395 | F4: =E4 -> 1107.6395 | G4: ='25-GEN-G-07'!AI7 -> 891 | H4: ='25-GEN-G-07'!AJ7 -> 29983.02 | I4: ='25-GEN-G-07'!AY7 -> 892.25 | J4: ='25-GEN-G-07'!AZ7 -> 31415.1 | K4: ='25-GEN-G-07'!BC7 -> 0 | L4: ='25-GEN-G-07'!BW7 -> 0 | M4: ='25-GEN-G-07'!BX7 -> 0 | N4: ='25-GEN-G-07'!CA7 -> 0 | O4: =B4-I4-L4 -> 39.125 | P4: =C4-J4-M4 -> -324.4405 | Q4: ='25-GEN-G-07'!CE7 -> -1.25 | R4: ='25-GEN-G-07'!CF7 -> -1432.08
A5: VTC02 | B5: Main-Material / Vật tư chính thép trắng
A6: 1 | B6: ='25-GEN-G-07'!AA25 -> 0 | C6: ='25-GEN-G-07'!AB25 -> 0 | D6: ='25-GEN-G-07'!AE25 -> 0 | E6: ='25-GEN-G-07'!AF25 -> 0 | F6: =E6 -> 0 | G6: ='25-GEN-G-07'!AI25 -> 0 | H6: ='25-GEN-G-07'!AJ25 -> 0 | I6: ='25-GEN-G-07'!AY25 -> 0 | J6: ='25-GEN-G-07'!AZ25 -> 0 | K6: ='25-GEN-G-07'!BC25 -> 0 | L6: ='25-GEN-G-07'!BW25 -> 0 | M6: ='25-GEN-G-07'!BX25 -> 0 | N6: ='25-GEN-G-07'!CA25 -> 0 | O6: =B6-I6-L6 -> 0 | P6: =C6-J6-M6 -> 0 | Q6: ='25-GEN-G-07'!CE25 -> 0 | R6: ='25-GEN-G-07'!CF25 -> 0
A7: VTC03 | B7: Gratting-Material / Vật tư gratting
A8: 1 | B8: ='25-GEN-G-07'!AA28 -> 0 | C8: ='25-GEN-G-07'!AB28 -> 0 | D8: ='25-GEN-G-07'!AE28 -> 0 | E8: ='25-GEN-G-07'!AF28 -> 0 | F8: =E8 -> 0 | G8: ='25-GEN-G-07'!AI28 -> 0 | H8: ='25-GEN-G-07'!AJ28 -> 0 | I8: ='25-GEN-G-07'!AY28 -> 0 | J8: ='25-GEN-G-07'!AZ28 -> 0 | K8: ='25-GEN-G-07'!BC28 -> 0 | L8: ='25-GEN-G-07'!BW28 -> 0 | M8: ='25-GEN-G-07'!BX28 -> 0 | N8: ='25-GEN-G-07'!CA28 -> 0 | O8: =B8-I8-L8 -> 0 | P8: =C8-J8-M8 -> 0 | Q8: ='25-GEN-G-07'!CE28 -> 0 | R8: ='25-GEN-G-07'!CF28 -> 0
A9: VTC04 | B9: Insulation-Material / Vật tư bảo ôn
A10: 1 | B10: ='25-GEN-G-07'!AA31 -> 0 | C10: ='25-GEN-G-07'!AB31 -> 0 | D10: ='25-GEN-G-07'!AE31 -> 0 | E10: ='25-GEN-G-07'!AF31 -> 0 | F10: =E10 -> 0 | G10: ='25-GEN-G-07'!AI31 -> 0 | H10: ='25-GEN-G-07'!AJ31 -> 0 | I10: ='25-GEN-G-07'!AY31 -> 0 | J10: ='25-GEN-G-07'!AZ31 -> 0 | K10: ='25-GEN-G-07'!BC31 -> 0 | L10: ='25-GEN-G-07'!BW31 -> 0 | M10: ='25-GEN-G-07'!BX31 -> 0 | N10: ='25-GEN-G-07'!CA31 -> 0 | O10: =B10-I10-L10 -> 0 | P10: =C10-J10-M10 -> 0 | Q10: ='25-GEN-G-07'!CE31 -> 0 | R10: ='25-GEN-G-07'!CF31 -> 0
A11: VPK | B11: Bolt-Material / Vật tư bulong, phụ kiện
A12: 1 | B12: ='25-GEN-G-07'!AA33 -> 3981 | C12: ='25-GEN-G-07'!AB33 -> 0 | D12: ='25-GEN-G-07'!AE33 -> 0 | E12: ='25-GEN-G-07'!AF33 -> 0 | F12: =E12 -> 0 | G12: ='25-GEN-G-07'!AI33 -> 3981 | H12: ='25-GEN-G-07'!AJ33 -> 0 | I12: ='25-GEN-G-07'!AY33 -> 3982 | J12: ='25-GEN-G-07'!AZ33 -> 17.5 | K12: ='25-GEN-G-07'!BC33 -> 0 | L12: ='25-GEN-G-07'!BW33 -> 0 | M12: ='25-GEN-G-07'!BX33 -> 0 | N12: ='25-GEN-G-07'!CA33 -> 0 | O12: =B12-I12-L12 -> -1 | P12: =C12-J12-M12 -> -17.5 | Q12: ='25-GEN-G-07'!CE33 -> -1 | R12: ='25-GEN-G-07'!CF33 -> -17.5
A13: VTK | B13: Packing Material / Vật tư kiện
A14: 1 | B14: ='25-GEN-G-07'!AA59 | C14: ='25-GEN-G-07'!AB59 -> 0 | D14: ='25-GEN-G-07'!AE59 -> 0 | E14: ='25-GEN-G-07'!AF59 -> 0 | F14: =E14 -> 0 | G14: ='25-GEN-G-07'!AI59 -> 0 | H14: ='25-GEN-G-07'!AJ59 -> 0 | I14: ='25-GEN-G-07'!AY59 -> 0 | J14: ='25-GEN-G-07'!AZ59 -> 0 | K14: ='25-GEN-G-07'!BC59 -> 0 | L14: ='25-GEN-G-07'!BW59 -> 0 | M14: ='25-GEN-G-07'!BX59 -> 0 | N14: ='25-GEN-G-07'!CA59 -> 0 | O14: =B14-I14-L14 -> #VALUE! | P14: =C14-J14-M14 -> 0 | Q14: ='25-GEN-G-07'!CE59 -> 0 | R14: ='25-GEN-G-07'!CF59 -> 0
A17: STT/ No. | B17: Dự án/ Hạng mục/ Project/ Items | C17: Thiết kế, Dự toán/ Design, Estimation | F17: Mua sắm/ Ordered, Puchased (Đến hiện tại/ Up to now) | K17: Tổng Giá trị mua thêm/ Total Cost (VND)
F18: Hàng mua thêm | H18: Hàng tồn
C19: Khối lượng/ Weight (Kg) | D19: Số lượng/ Q'ty (M/M2//PSC) | E19: Tổng Giá trị/ Total Cost (VND) | F19: Khối lượng/ Weight (Kg) | G19: Số lượng/ Q'ty (M/M2//PSC) | H19: Khối lượng/ Weight (Kg/N/A) Materials available at the factory | I19: Số lượng/ Q'ty (M/M2/PSC) Materials available at the factory | J19: Tổng Giá trị mua thêm/ Total Cost (VND) | K19: DỰ TOÁN (VNĐ) | L19: GIÁ TRỊ ĐÃ ĐẶT HÀNG THÊM (VNĐ) | M19: Chênh lệch/ Diff. (VND) | N19: Ghi chú/ Remarks
A20: VTC01 | B20: Main-Material / Vật tư chính thép đen | C20: =C4 -> 31090.659 | D20: =B4 -> 931.375 | F20: =J4+M4 -> 31415.1 | G20: =I4+L4 -> 892.25 | H20: =E4 -> 1107.6395 | I20: =D4 -> 40.375 | J20: ='25-GEN-G-07'!AW7+'25-GEN-G-07'!BN7*27000 -> 4.3019969e+08 | K20: 0 | M20: =K20-J20-L20 -> -4.3019969e+08 | N20: =IF(M20<=0,"VƯỢT DỰ TOÁN","ĐẢM BẢO") -> VƯỢT DỰ TOÁN
A21: VTC02 | B21: Main-Material / Vật tư chính thép trắng | C21: =C6 -> 0 | D21: =B6 -> 0 | F21: =J6+M6 -> 0 | G21: =I6+L6 -> 0 | H21: =E6 -> 0 | I21: =D6 -> 0 | J21: ='25-GEN-G-07'!AW25+'25-GEN-G-07'!BN25*27000 -> 0 | K21: 0 | M21: =K21-J21-L21 -> 0 | N21: =IF(M21<=0,"VƯỢT DỰ TOÁN","ĐẢM BẢO") -> VƯỢT DỰ TOÁN
A22: VTC03 | B22: Gratting-Material / Vật tư gratting | C22: =C8 -> 0 | D22: =B8 -> 0 | F22: =J8+M8 -> 0 | G22: =I8+L8 -> 0 | H22: =E8 -> 0 | I22: =D8 -> 0 | J22: ='25-GEN-G-07'!AW28+'25-GEN-G-07'!BN28*27000 -> 0 | K22: 0 | M22: =K22-J22-L22 -> 0 | N22: =IF(M22<=0,"VƯỢT DỰ TOÁN","ĐẢM BẢO") -> VƯỢT DỰ TOÁN
A23: VTC04 | B23: Insulation-Material / Vật tư bảo ôn | C23: =C10 -> 0 | D23: =B10 -> 0 | F23: =J10+M10 -> 0 | G23: =I10+L10 -> 0 | H23: =E10 -> 0 | I23: =D10 -> 0 | J23: ='25-GEN-G-07'!AW31+'25-GEN-G-07'!BN31*27000 -> 0 | K23: 0 | M23: =K23-J23-L23 -> 0 | N23: =IF(M23<=0,"VƯỢT DỰ TOÁN","ĐẢM BẢO") -> VƯỢT DỰ TOÁN
A24: VPK | B24: Bolt-Material / Vật tư bulong, phụ kiện | C24: =C12 -> 0 | D24: =B12 -> 3981 | F24: =J12+M12 -> 17.5 | G24: =I12+L12 -> 3982 | H24: =E12 -> 0 | I24: =D12 -> 0 | J24: ='25-GEN-G-07'!AW33+'25-GEN-G-07'!BN33*27000 -> 49445437 | K24: 0 | M24: =K24-J24-L24 -> -49445437 | N24: =IF(M24<=0,"VƯỢT DỰ TOÁN","ĐẢM BẢO") -> VƯỢT DỰ TOÁN
A25: VTK | B25: Packing Material / Vật tư kiện | C25: =C14 -> 0 | D25: =B14 | F25: =J14+M14 -> 0 | G25: =I14+L14 -> 0 | H25: =E14 -> 0 | I25: =D14 -> 0 | J25: ='25-GEN-G-07'!AW59+'25-GEN-G-07'!BN59*27000 -> 0 | K25: 0 | M25: =K25-J25-L25 -> 0 | N25: =IF(M25<=0,"VƯỢT DỰ TOÁN","ĐẢM BẢO") -> VƯỢT DỰ TOÁN

Sheet Giải tình Hoàng Hà vit
A1: BID ANALYSIS - GIẢI TRÌNH MUA SẮM/ĐẤU THẦU
A3: Project | B3: PROJECT No/ Dự án: 25-GEN-G-08
A4: Dự án
A5: Subject | B5: Cung cấp vật tư bu lông, phụ kiện
A6: Chủ đề
A8: No. | B8: CONTENT | C8: Phạm vi công việc | H8: Dự toán | K8: Đã mua | L8: Đơn vị cung cấp chào giá (vnđ) | O8: Lựa chọn | P8: Ghi chú
A9: Item | B9: Description/ Chi tiết | C9: Profile/ Vật tư | D9: Grade/ Mác vật liệu | E9: Số lượng Mua | F9: Số lượng PR | G9: Đơn vị | H9: Khối lượng/ Số lượng | I9: Đơn giá (vnd) | J9: Thành tiền (vnd) | K9: Thành tiền (vnd) | L9: HOÀNG HÀ
L10: Phạm vi | M10: Đơn giá (VND) | N10: Thành Tiền (Không có VAT)
A11: Tổng | B11: Bolt-Material / Vật tư bulong, phụ kiện | H11: N/A | I11: N/A | N11: =SUM(N12:N21) -> 6397320 | P11: =J11-K11-N11 -> -6397320
A12: G07-VPK-002 | B12: Bu lông chìm trụ | C12: M6*20 | D12: Inox 304 | E12: 350 | F12: 350 | G12: cái | H12: N/A | I12: N/A | J12: N/A | L12: V | M12: 914 | N12: =M12*F12 -> 319900 | O12: HOÀNG HÀ
A13: G07-VPK-003 | B13: Bu lông chìm trụ | C13: M6*50 | D13: Inox 304 | E13: 380 | F13: 380 | G13: cái | H13: N/A | I13: N/A | J13: N/A | L13: V | M13: 1711 | N13: =M13*F13 -> 650180 | O13: HOÀNG HÀ
A14: G07-VPK-004 | B14: Bu lông chìm trụ | C14: M8*30 | D14: Inox 304 | E14: 120 | F14: 120 | G14: cái | H14: N/A | I14: N/A | J14: N/A | L14: V | M14: 2277 | N14: =M14*F14 -> 273240 | O14: HOÀNG HÀ
A15: G07-VPK-007 | B15: Long đen phẳng | C15: M6 | D15: Inox 304 | E15: 380 | F15: 380 | G15: cái | H15: N/A | I15: N/A | J15: N/A | L15: V | M15: 150 | N15: =M15*F15 -> 57000 | O15: HOÀNG HÀ
A16: G07-VPK-008 | B16: Long đen vênh | C16: M6 | D16: Inox 304 | E16: 730 | F16: 730 | G16: cái | H16: N/A | I16: N/A | J16: N/A | L16: V | M16: 150 | N16: =M16*F16 -> 109500 | O16: HOÀNG HÀ
A17: G07-VPK-009 | B17: Long đen phẳng | C17: M8 | D17: Inox 304 | E17: 120 | F17: 120 | G17: cái | H17: N/A | I17: N/A | J17: N/A | L17: V | M17: 300 | N17: =M17*F17 -> 36000 | O17: HOÀNG HÀ
A18: G07-VPK-010 | B18: Long đen vênh | C18: M8 | D18: Inox 304 | E18: 120 | F18: 120 | G18: cái | H18: N/A | I18: N/A | J18: N/A | L18: V | M18: 300 | N18: =M18*F18 -> 36000 | O18: HOÀNG HÀ
A19: G07-VPK-013 | B19: Bulông nở | C19: Bulong nở M16x150-HDG | D19: mạ kẽm nhúng nóng | E19: 176 | F19: 176 | G19: cái | H19: N/A | I19: N/A | J19: N/A | L19: V | M19: 22500 | N19: 3960000 | O19: HOÀNG HÀ
A20: G07-VPK-014 | B20: Bolt | C20: Bolt M16x100-8.8-DIN933-HDG | D20: mạ kẽm nhúng nóng | E20: 65 | F20: 65 | G20: cái | H20: N/A | I20: N/A | J20: N/A | L20: V | M20: 14700 | N20: 955500 | O20: HOÀNG HÀ
A21: G07-VPK-015 | B21: Nut | C21: Nut M16-8.0-DIN934-HDG | D21: mạ kẽm nhúng nóng | E21: 130 | F21: 130 | G21: cái | H21: N/A | I21: N/A | J21: N/A | L21: V | M21: 0 | N21: 0 | O21: HOÀNG HÀ
B22: Xếp hạng | M22: 1
A23: Ghi chú: Tiếp tục công tác mua sắm để đảm báo tiến độ
A24: NGƯỜI ĐỀ NGHỊ/ RECOMMENDATION BY: | C24: NGƯỜI KIỂM TRA/ DEPARTMENT HEAD CHECK BY: | G24: APPROVED BY: PHÊ DUYỆT
G25: Nguyễn Quang Vinh | K25: Hoàng Ngọc Bằng | O25: Đoàn Văn Toàn

Sheet Ngọc Hiếu 26-1
A1: BID ANALYSIS - GIẢI TRÌNH MUA SẮM/ĐẤU THẦU
A3: Project | B3: PROJECT No/ Dự án: 25-GEN-G-07
A4: Dự án
A5: Subject | B5: Cung cấp vật tư chính thép đen ngọc hiếu 26-1-20226
A6: Chủ đề
A8: No. | B8: CONTENT | C8: Phạm vi công việc | H8: Dự toán | K8: Đã mua | L8: Đơn vị cung cấp chào giá phần còn lại (VNĐ) | O8: Đơn vị cung cấp chào giá phần còn lại (VNĐ) | R8: Đơn vị cung cấp chào giá phần còn lại (VNĐ) | U8: Ghi chú
A9: Item | B9: Description/ Chi tiết | C9: Profile/ Vật tư | D9: Grade/ Mác vật liệu | E9: Grade/ Mác vật liệu mua | F9: Số lượng Mua (M) | G9: Số lượng PR (M) | H9: Khối lượng/ Số lượng | I9: Đơn giá (vnd) | J9: Thành tiền (vnd) | K9: Thành tiền (vnd) | L9: NGỌC HIẾU | O9: Hùng Nguyên | R9: APEC
L10: Phạm vi | M10: Đơn giá trước VAT (VNĐ/KG) | N10: Thành Tiền | O10: Phạm vi | P10: Đơn giá trước VAT (VNĐ/KG) | Q10: Thành Tiền | R10: Phạm vi | S10: Đơn giá trước VAT (VNĐ/KG) | T10: Thành Tiền
A11: Tổng | B11: Main-Material / Vật tư chính thép đen | H11: N/A | I11: N/A | K11: ='Tổng hợp'!J20-N11 -> 4.2305787e+08 | N11: =N12 -> 7141816 | U11: =J11-K11-N11 -> -4.3019969e+08
A12: G07-VTC01-008 | B12: PL2X1200X2500 | C12: Thép tấm 2*1250*2500 | D12: Q235A/SS400 | E12: SS400 | F12: =10*1.25*2.5 -> 31.25 | G12: 30 | H12: N/A | I12: N/A | J12: N/A | K12: N/A | L12: V | M12: 14545.45 | N12: 7141816 | O12: X | P12: #N/A | Q12: #N/A | R12: X | S12: #N/A | T12: =VLOOKUP(D12,'[115]DA 95'!$B$20:$N$31,13,0) -> #N/A | U12: Chọn Ngọc Hiếu
B13: Xếp hạng | M13: 1 | P13: 2 | S13: 3
A14: Ghi chú: Tiếp tục công tác mua sắm để đảm báo tiến độ
A15: NGƯỜI ĐỀ NGHỊ/ RECOMMENDATION BY: | F15: NGƯỜI KIỂM TRA/ DEPARTMENT HEAD CHECK BY: | N15: APPROVED BY: PHÊ DUYỆT
N16: Nguyễn Quang Vinh | Q16: Hoàng Ngọc Bằng | T16: Đoàn Văn Toàn

Sheet Hùng nguyên 26-1 (2)
A1: BID ANALYSIS - GIẢI TRÌNH MUA SẮM/ĐẤU THẦU
A3: Project | B3: PROJECT No/ Dự án: 25-GEN-G-07
A4: Dự án
A5: Subject | B5: Cung cấp vật tư chính thép đen
A6: Chủ đề
A8: No. | B8: CONTENT | C8: Phạm vi công việc | H8: Dự toán | K8: Đã mua | L8: Đơn vị cung cấp chào giá phần còn lại (VNĐ) | O8: Đơn vị cung cấp chào giá phần còn lại (VNĐ) | R8: Đơn vị cung cấp chào giá phần còn lại (VNĐ) | U8: Ghi chú
A9: Item | B9: Description/ Chi tiết | C9: Profile/ Vật tư | D9: Grade/ Mác vật liệu | E9: Grade/ Mác vật liệu mua | F9: Số lượng Mua (M) | G9: Số lượng PR (M) | H9: Khối lượng/ Số lượng | I9: Đơn giá (vnd) | J9: Thành tiền (vnd) | K9: Thành tiền (vnd) | L9: NGỌC HIẾU | O9: Hùng Nguyên | R9: APEC
L10: Phạm vi | M10: Đơn giá trước VAT (VNĐ/KG) | N10: Thành Tiền | O10: Phạm vi | P10: Đơn giá trước VAT (VNĐ/KG) | Q10: Thành Tiền | R10: Phạm vi | S10: Đơn giá trước VAT (VNĐ/KG) | T10: Thành Tiền
A11: Tổng | B11: Main-Material / Vật tư chính thép đen | H11: N/A | I11: N/A | K11: ='Tổng hợp'!J20 -> 4.3019969e+08 | Q11: =SUM(Q12:Q12) -> 33989082 | U11: =J11-K11-Q11-N11 -> -4.6418877e+08
A12: G07-VTC01-001 | B12: PL3X1500X6000 | C12: Thép tấm 3x2000x6000 | D12: Q235A/SS400 | E12: SS400 | F12: 108 | G12: 108 | H12: N/A | I12: N/A | J12: N/A | K12: N/A | L12: V | M12: 13909.09 | N12: #N/A | O12: V | P12: 13363.64 | Q12: 33989082 | R12: V | S12: =14850/1.1 -> 13500 | T12: =VLOOKUP(D12,'[115]DA 95'!$B$20:$N$31,13,0) -> #N/A | U12: Chọn Hùng Nguyên
B13: Xếp hạng | M13: 2 | P13: 1 | S13: 3
A14: Ghi chú: Tiếp tục công tác mua sắm để đảm báo tiến độ
A15: NGƯỜI ĐỀ NGHỊ/ RECOMMENDATION BY: | F15: NGƯỜI KIỂM TRA/ DEPARTMENT HEAD CHECK BY: | N15: APPROVED BY: PHÊ DUYỆT
N16: Nguyễn Quang Vinh | Q16: Hoàng Ngọc Bằng | T16: Đoàn Văn Toàn

Sheet Hùng nguyên 27-1
A1: BID ANALYSIS - GIẢI TRÌNH MUA SẮM/ĐẤU THẦU
A3: Project | B3: PROJECT No/ Dự án: 25-GEN-G-07
A4: Dự án
A5: Subject | B5: Cung cấp vật tư chính thép đen
A6: Chủ đề
A8: No. | B8: CONTENT | C8: Phạm vi công việc | H8: Dự toán | K8: Đã mua | L8: Đơn vị cung cấp chào giá phần còn lại (VNĐ) | O8: Đơn vị cung cấp chào giá phần còn lại (VNĐ) | R8: Đơn vị cung cấp chào giá phần còn lại (VNĐ) | U8: Ghi chú
A9: Item | B9: Description/ Chi tiết | C9: Profile/ Vật tư | D9: Grade/ Mác vật liệu | E9: Grade/ Mác vật liệu mua | F9: Số lượng Mua (M) | G9: Số lượng PR (M) | H9: Khối lượng/ Số lượng | I9: Đơn giá (vnd) | J9: Thành tiền (vnd) | K9: Thành tiền (vnd) | L9: NGỌC HIẾU | O9: Hùng Nguyên | R9: APEC
L10: Phạm vi | M10: Đơn giá trước VAT (VNĐ/KG) | N10: Thành Tiền | O10: Phạm vi | P10: Đơn giá trước VAT (VNĐ/KG) | Q10: Thành Tiền | R10: Phạm vi | S10: Đơn giá trước VAT (VNĐ/KG) | T10: Thành Tiền
A11: Tổng | B11: Main-Material / Vật tư chính thép đen | H11: N/A | I11: N/A | K11: ='Tổng hợp'!J20-Q11 -> 3.181745e+08 | Q11: =SUM(Q12:Q14) -> 1.1202519e+08 | U11: =J11-K11-Q11-N11 -> -4.3019969e+08
A12: G07-VTC01-011 | B12: PL14x2000x12000 (2 tờ) PL14x2000x4500 (1 tầm) | C12: Thép tấm 14x2000x12000 SS400 | D12: Q235A/SS400 | E12: SS400 | F12: =2*(24) -> 48 | G12: =2*(24) -> 48 | H12: N/A | I12: N/A | J12: N/A | K12: N/A | L12: X | M12: #N/A | N12: #N/A | O12: V | P12: 13727.27 | Q12: 72414095 | R12: X | S12: #N/A | T12: #N/A | U12: Chọn Hùng Nguyên
A13: G07-VTC01-011 | B13: PL14x2000x12000 (2 tờ) PL14x2000x4500 (1 tầm) | C13: Thép tấm 14x2000x4500 SS400 | D13: Q235A/SS400 | E13: SS400 | F13: 9 | G13: 9 | H13: N/A | I13: N/A | J13: N/A | K13: N/A | L13: V | M13: #N/A | N13: #N/A | O13: V | P13: 13727.27 | Q13: 13577643 | R13: X | S13: #N/A | T13: #N/A | U13: Chọn Hùng Nguyên
A14: G07-VTC01-012 | B14: PL20x2000x6000 | C14: Thép tấm 20x2000x6000 SS400 | D14: Q235A/SS400 | E14: SS400 | F14: 12 | G14: 12 | H14: N/A | I14: N/A | J14: N/A | K14: N/A | L14: V | M14: 13909.09 | N14: #N/A | O14: V | P14: 13818.18 | Q14: 26033451 | R14: X | S14: #N/A | T14: #N/A | U14: Chọn Hùng Nguyên
B15: Xếp hạng | M15: 2 | P15: 1 | S15: 3
A16: Ghi chú: Chưa có dự toán/ Tiếp tục công tác mua sắm để đảm báo tiến độ
A17: NGƯỜI ĐỀ NGHỊ/ RECOMMENDATION BY: | F17: NGƯỜI KIỂM TRA/ DEPARTMENT HEAD CHECK BY: | N17: APPROVED BY: PHÊ DUYỆT
N18: Nguyễn Quang Vinh | Q18: Hoàng Ngọc Bằng | T18: Đoàn Văn Toàn

Sheet BG Gnee 2
B1: GNEE STEEL CO.,LIMITED
B2: FLAT/RM 1512 15/F LUCKY CENTRE NO.165-171 WAN CHAI ROAD WAN CHAI HK
A3: TEL: +86 15286968617 E-mail:alice@gescosteel.com
A4: QUOTATION SHEET
A5: QUOTATION NO.: GNEEYPH20240527-1
A6: DATE: MAY.27TH,2024
A7: TO:IBS
A8: SR NO. | B8: PRODUCT NAME | C8: SPECIFICATION (mm) | F8: UNIT WEIGHT (KG/PCS) | G8: QUANTITY | I8: FOB CHINA
E9: Số lượng (m/m2) | G9: QTY (PCS) | H9: WEIGHT (KG) | I9: UNIT PRICE（USD/KG) | J9: AMOUNT (USD) | K9: lead time
A10: A-8 | B10: HARDOX 450 PLATE | C10: 6*2000*6000 | E10: =G10*2*6 -> 36 | F10: 565.2 | G10: 3 | H10: =G10*F10 -> 1695.6 | I10: 3.16 | J10: =I10*H10 -> 5358.096 | K10: 20days
A11: A-15 | B11: NM400 PLATE | C11: 12*1500*3700 | E11: =G11*1.5*3.7 -> 5.55 | F11: 653.5 | G11: 1 | H11: =G11*F11 -> 653.5 | I11: 1.1 | J11: =I11*H11 -> 718.85 | K11: 20days
A12: A-20 | B12: HARDOX 500 PLATE | C12: 16*2000*6000 | E12: =G12*2*6 -> 12 | F12: 1507.2 | G12: 1 | H12: =G12*F12 -> 1507.2 | I12: 3.07 | J12: =I12*H12 -> 4627.104 | K12: 20days
A13: A-27 | B13: HARDOX 500 PLATE | C13: 22*2000*6000 | E13: =G13*2*6 -> 12 | F13: =22*2*6*7.85 -> 2072.4 | G13: 1 | H13: =G13*F13 -> 2072.4 | I13: 3.16 | J13: =I13*H13 -> 6548.784 | K13: 20days
A14: A-5 | B14: SA240-304 PLATE | C14: 2*1219*2438 | E14: =G14*1.219*2.438 -> 2.971922 | F14: 47.2 | G14: 1 | H14: =G14*F14 -> 47.2 | I14: 3.29 | J14: =I14*H14 -> 155.288
A15: A-64 | B15: SUS 304 ROUND BAR | C15: 40*6000 | E15: =G15*6 -> 12 | F15: 59.8 | G15: 2 | H15: =G15*F15 -> 119.6 | I15: 3.72 | J15: =I15*H15 -> 444.912
A16: A-46 | B16: Q235B PIPE | C16: 102*6*6000 | E16: =G16*6 -> 6 | F16: 85.2 | G16: 1 | H16: =G16*F16 -> 85.2 | I16: 0.91 | J16: =I16*H16 -> 77.532
A17: A-47 | B17: Q235B PIPE | C17: 108*5*6000 | E17: =G17*6 -> 126 | F17: 76.2 | G17: 21 | H17: =G17*F17 -> 1600.2 | I17: 0.91 | J17: =I17*H17 -> 1456.182
A18: A-48 | B18: Q235B PIPE | C18: 121*5*6000 | E18: =G18*6 -> 60 | F18: 85.8 | G18: 10 | H18: =G18*F18 -> 858 | I18: 0.91 | J18: =I18*H18 -> 780.78
A19: A-49 | B19: Q235B PIPE | C19: 140*6*6000 | E19: =G19*6 -> 150 | F19: 119 | G19: 25 | H19: =G19*F19 -> 2975 | I19: 0.91 | J19: =I19*H19 -> 2707.25
A20: A-50 | B20: Q235B PIPE | C20: 168*8*6000 | E20: =G20*6 -> 18 | F20: 189.4 | G20: 3 | H20: =G20*F20 -> 568.2 | I20: 0.91 | J20: =I20*H20 -> 517.062
A21: A-51 | B21: Q235B PIPE | C21: 194*8*6000 | E21: =G21*6 -> 6 | F21: 220.2 | G21: 1 | H21: =G21*F21 -> 220.2 | I21: 0.91 | J21: =I21*H21 -> 200.382
A22: A-52 | B22: Q235B PIPE | C22: 245*10*12000 | E22: =G22*12 -> 12 | F22: 695.5 | G22: 1 | H22: =G22*F22 -> 695.5 | I22: 0.91 | J22: =I22*H22 -> 632.905
A23: A-53 | B23: Q235B PIPE | C23: 32*4*6000 | E23: =G23*6 -> 6 | F23: 16.6 | G23: 1 | H23: =G23*F23 -> 16.6 | I23: 0.91 | J23: =I23*H23 -> 15.106
A24: A-54 | B24: Q235B PIPE | C24: 60*3.5*6000 | E24: =G24*6 -> 6 | F24: 29.3 | G24: 1 | H24: =G24*F24 -> 29.3 | I24: 0.91 | J24: =I24*H24 -> 26.663
A25: A-55 | B25: Q235B PIPE | C25: 60*6*6000 | E25: =G25*6 -> 6 | F25: 47.9 | G25: 1 | H25: =G25*F25 -> 47.9 | I25: 0.91 | J25: =I25*H25 -> 43.589
A26: A-57 | B26: Q235B PIPE | C26: 76*5*6000 | E26: =G26*6 -> 36 | F26: 52.6 | G26: 6 | H26: =G26*F26 -> 315.6 | I26: 0.91 | J26: =I26*H26 -> 287.196
A27: AMOUNT | G27: =SUM(G10:G26) -> 80 | H27: =SUM(H10:H26) -> 13507.2 | J27: =SUM(J10:J26) -> 24597.681
A28: SPECIFICATION:
A29: 1. SURFACE: | C29: SAFETY
A30: 2. PACKAGE: | C30: SEA WORTHY PACKING
A31: 3. QUALITY STANDARD OF MATERIAL: | C31: ACCORDANCE WITH ABOVE SPECIFICATION.
A32: TERMS:
A33: 1. INSPECTION: | C33: MILL QUALITY TEST.(ORIGINAL MTC WILL BE PROVIDED.)
A34: 2. TOLERANCE OF AMOUNT: | C34: QUANTITY AND AMOUNT ARE ALLOWED MORE OR LESS 10%.
A35: 3.TERMS OF PAYMENT: | C35: 100% LC AT SIGHT.
A36: 4. TIME OF DELIVERY: | C36: 20DAYS AFTER ORIGINAL LC
A37: 5. PORT OF LOADING: | C37: ANY PORT,CHINA
A38: 6. PORT OF DESTINATION: | C38: HAIPHONG,VIETNAM
A39: 7. TRANSPORTATION: | C39: CONTAINER
A40: 8. VALID PERIOD OF PRICE: | C40: 5DAYS
A41: 9. ORIGIN OF GOODS: | C41: CHINA.
A42: 10.NOTE | C42: 1. ABOVE PRICE IS BASED ON FINAL WEIGHT
C43: 2. ABOVE PRICE DOES NOT CONTAIN THIRD PARTY INSPECTION FEE.
A44: BANK INFORMATION:
A45: BENIFICIARY COMPANY: | C45: GNEE STEEL CO.,LIMITED
A46: COMPANY ADDRESS: | C46: FLAT/RM 1512 15/F LUCKY CENTRE NO.165-171 WAN CHAI ROAD WAN CHAI HK
A47: BENIFICIARY BANK: | C47: ZHEJIANG CHOUZHOU COMMERCIAL BANK
A48: BANK ADDRESS: | C48: YIWU LEYUAN EAST JIANGBIN ROAD YIWU CITY ZHEJIANG PROVINCE CHINA
A49: SWIFT NO.: | C49: CZCBCN2X
A50: ACCOUNT NUMBER: | C50: NRA15628142010500008718

Sheet Báo giá của GNEE
B1: GNEE STEEL CO.,LIMITED
B2: FLAT/RM 1512 15/F LUCKY CENTRE NO.165-171 WAN CHAI ROAD WAN CHAI HK
A3: TEL: +86 15286968617 E-mail:alice@gescosteel.com
A4: QUOTATION SHEET
A5: QUOTATION NO.: GNEEYPH20240513-1
A6: DATE: MAY.13TH,2024
A7: TO:IBS
A8: SR NO. | B8: PRODUCT NAME | C8: SPECIFICATION (mm) | F8: UNIT WEIGHT (KG/PCS) | G8: QUANTITY | I8: CIF HAIPHONG, VIETNAM
E9: Số lượng (m/m2) | G9: QTY (PCS) | H9: WEIGHT (KG) | I9: UNIT PRICE（USD/KG) | J9: AMOUNT (USD) | M9: lead time
A10: A-8 | B10: HARDOX 450 PLATE | C10: 6*2000*6000 | E10: =G10*2*6 -> 36 | F10: 565.2 | G10: 3 | H10: =G10*F10 -> 1695.6 | I10: 3.21 | J10: =I10*H10 -> 5442.876 | K10: GNEEYPH20240513-1 | L10: kt: 1500X6000-2 tờ; 1500x5400-1 tờ. | M10: 20days
A11: A-9 | B11: Q235B PLATE | C11: 6*1500*6000 | E11: =G11*1.5*6 -> 18 | F11: 423.9 | G11: 2 | H11: =G11*F11 -> 847.8 | I11: 0.68 | J11: =I11*H11 -> 576.504 | K11: GNEEYPH20240513-1 | M11: 20days
A12: A-11 | B12: Q235B PLATE | C12: 8*1500*6000 | E12: =G12*1.5*6 -> 9 | F12: 565.2 | G12: 1 | H12: =G12*F12 -> 565.2 | I12: 0.7 | J12: =I12*H12 -> 395.64 | K12: GNEEYPH20240513-1 | M12: 20days
A13: A-12 | B13: Q355B PLATE | C13: 8*2000*12000 | E13: =G13*2*12 -> 24 | F13: 1507.2 | G13: 1 | H13: =G13*F13 -> 1507.2 | I13: 0.72 | J13: =I13*H13 -> 1085.184 | K13: GNEEYPH20240513-1 | M13: 20days
A14: A-13 | B14: Q235B PLATE | C14: 10*1500*6000 | E14: =G14*1.5*6 -> 9 | F14: 706.5 | G14: 1 | H14: =G14*F14 -> 706.5 | I14: 0.69 | J14: =I14*H14 -> 487.485 | K14: GNEEYPH20240513-1 | M14: 20days
A15: A-14 | B15: Q355B PLATE | C15: 10*2000*10000 | E15: =G15*2*10 -> 20 | F15: 1570 | G15: 1 | H15: =G15*F15 -> 1570 | I15: 0.72 | J15: =I15*H15 -> 1130.4 | K15: GNEEYPH20240513-1 | M15: 20days
A16: A-15 | B16: NM400 PLATE | C16: 12*1500*3700 | E16: =G16*1.5*3.7 -> 5.55 | F16: 653.5 | G16: 1 | H16: =G16*F16 -> 653.5 | I16: 1.15 | J16: =I16*H16 -> 751.525 | K16: GNEEYPH20240513-1 | L16: 12*1500*4250 | M16: 20days
A17: A-17 | B17: Q355B PLATE | C17: 12*2000*12000 | E17: =G17*2*12 -> 24 | F17: 2260.8 | G17: 1 | H17: =G17*F17 -> 2260.8 | I17: 0.72 | J17: =I17*H17 -> 1627.776 | K17: GNEEYPH20240513-1 | M17: 45days
A18: A-20 | B18: HARDOX 500 PLATE | C18: 16*2000*6000 | E18: =G18*2*6 -> 12 | F18: 1507.2 | G18: 1 | H18: =G18*F18 -> 1507.2 | I18: 3.12 | J18: =I18*H18 -> 4702.464 | K18: GNEEYPH20240513-1 | L18: kt: 1500X6000-1 tờ; 1500x2500-1 tờ. | M18: 20days
A19: A-22 | B19: Q355B PLATE | C19: 16*2000*8000 | E19: =G19*2*8 -> 16 | F19: 2009.6 | G19: 1 | H19: =G19*F19 -> 2009.6 | I19: 0.78 | J19: =I19*H19 -> 1567.488 | K19: GNEEYPH20240513-1 | M19: 20days
A20: A-42 | B20: Q355 H BEAM | C20: 200*200*8*12*12000 | E20: =G20*12 -> 96 | F20: =50.5*12 -> 606 | G20: 8 | H20: =G20*F20 -> 4848 | I20: 0.75 | J20: =I20*H20 -> 3636 | K20: GNEEYPH20240513-1 | M20: 20days
A21: A-43 | B21: Q355 H BEAM | C21: 250*250*9*14*12000 | E21: =G21*12 -> 12 | F21: =72.4*12 -> 868.8 | G21: 1 | H21: =G21*F21 -> 868.8 | I21: 0.75 | J21: =I21*H21 -> 651.6 | K21: GNEEYPH20240513-1
A22: A-73 | B22: Q235B RHS | C22: 150*100*6*12000 | E22: =G22*12 -> 24 | F22: 269 | G22: 2 | H22: =G22*F22 -> 538 | I22: 0.75 | J22: =I22*H22 -> 403.5 | K22: GNEEYPH20240513-1 | M22: 20days
A23: A-74 | B23: Q235B RHS | C23: 200*100*6*6000 | E23: =G23*6 -> 30 | F23: 162.8 | G23: 5 | H23: =G23*F23 -> 814 | I23: 0.75 | J23: =I23*H23 -> 610.5 | K23: GNEEYPH20240513-1 | M23: 20days
A24: A-75 | B24: Q235B SHS | C24: 200*200*10*6000 | E24: =G24*6 -> 60 | F24: 358 | G24: 10 | H24: =G24*F24 -> 3580 | I24: 0.75 | J24: =I24*H24 -> 2685 | K24: GNEEYPH20240513-1 | M24: 20days
A25: A-76 | B25: Q355B SHS | C25: 200*200*8*12000 | E25: =G25*12 -> 48 | F25: 289.4 | G25: 4 | H25: =G25*F25 -> 1157.6 | I25: 0.77 | J25: =I25*H25 -> 891.352 | K25: GNEEYPH20240513-1
A26: A-77 | B26: Q235B SHS | C26: 300*300*6*6000 | E26: =G26*6 -> 54 | F26: 332.4 | G26: 9 | H26: =G26*F26 -> 2991.6 | I26: 0.75 | J26: =I26*H26 -> 2243.7 | K26: GNEEYPH20240513-1 | M26: 20days
A27: AMOUNT | G27: =SUM(G10:G26) -> 52 | H27: =SUM(H10:H26) -> 28121.4 | J27: =SUM(J10:J26) -> 28888.994
A28: SPECIFICATION:
A29: 1. SURFACE: | C29: SAFETY
A30: 2. PACKAGE: | C30: SEA WORTHY PACKING
A31: 3. QUALITY STANDARD OF MATERIAL: | C31: ACCORDANCE WITH ABOVE SPECIFICATION.
A32: TERMS:
A33: 1. INSPECTION: | C33: MILL QUALITY TEST.(ORIGINAL MTC WILL BE PROVIDED.)
A34: 2. TOLERANCE OF AMOUNT: | C34: QUANTITY AND AMOUNT ARE ALLOWED MORE OR LESS 10%.
A35: 3.TERMS OF PAYMENT: | C35: 100% LC AT SIGHT.
A36: 4. TIME OF DELIVERY: | C36: 20DAYS AFTER ORIGINAL LC
A37: 5. PORT OF LOADING: | C37: ANY PORT,CHINA
A38: 6. PORT OF DESTINATION: | C38: HAIPHONG,VIETNAM
A39: 7. TRANSPORTATION: | C39: CONTAINER
A40: 8. VALID PERIOD OF PRICE: | C40: 5DAYS
A41: 9. ORIGIN OF GOODS: | C41: CHINA.
A42: 10.NOTE | C42: 1. ABOVE PRICE IS BASED ON FINAL WEIGHT
C43: 2. ABOVE PRICE DOES NOT CONTAIN THIRD PARTY INSPECTION FEE.
A44: BANK INFORMATION:
A45: BENIFICIARY COMPANY: | C45: GNEE STEEL CO.,LIMITED
A46: COMPANY ADDRESS: | C46: FLAT/RM 1512 15/F LUCKY CENTRE NO.165-171 WAN CHAI ROAD WAN CHAI HK
A47: BENIFICIARY BANK: | C47: ZHEJIANG CHOUZHOU COMMERCIAL BANK
A48: BANK ADDRESS: | C48: YIWU LEYUAN EAST JIANGBIN ROAD YIWU CITY ZHEJIANG PROVINCE CHINA
A49: SWIFT NO.: | C49: CZCBCN2X
A50: ACCOUNT NUMBER: | C50: NRA15628142010500008718

Sheet Dieu kien giao hang
A2: ĐIỀU KIỆN GIAO HÀNG NHẬP KHẨU
A3: STT | B3: Nội dung | C3: Số ngày | D3: Giá trị cộng dồn
A4: 1 | B4: Ký HD | C4: 0
A5: 2 | B5: Tạm ứng | C5: 0
A6: 3 | B6: Mở LC | C6: 5 | D6: =+C6+D5+C5 -> 5
A7: 4 | B7: Giao Hàng CIF | C7: 20 | D7: =+C7+D6 -> 25
A8: 5 | B8: Vận chuyển quốc tế | C8: 5 | D8: =+C8+D7 -> 30
A9: 6 | B9: Ngày thanh toán | C9: 3 | D9: =+C9+D8 -> 33
A10: 6 | B10: Thủ tục hải quan + vận chuyển nội địa | C10: 3 | D10: =+C10+D9 -> 36
B11: Ngày hàng về | C11: 2 | D11: =+C11+D10 -> 38
B12: Ngày mời nghiệm thu QC | C12: 1 | D12: =+C12+D11 -> 39
A13: 7 | B13: Nghiệm thu | C13: 12 | D13: =+C13+D12 -> 51
A14: 7 | B14: Bàn giao | C14: 1 | D14: =+C14+D13 -> 52
A16: ĐIỀU KIỆN GIAO HÀNG TRONG NƯỚC (VTU CHÍNH)
A17: STT | B17: Nội dung | C17: Số ngày | D17: Giá trị cộng dồn
A18: 1 | B18: Ký HD | C18: 0
A19: 2 | B19: Tạm ứng | C19: 0
A20: 3 | B20: Mở LC | C20: 0 | D20: =+C20+D19+C19 -> 0
A21: 4 | B21: Giao Hàng tại xưởng | C21: 4 | D21: =+C21+D20 -> 4
A22: 5 | B22: Nghiệm thu | C22: 2 | D22: =+C22+D21 -> 6
A23: 6 | B23: Bàn giao | C23: 1 | D23: =+C23+D22 -> 7
A26: ĐIỀU KIỆN GIAO HÀNG TRONG NƯỚC (VTU Phụ)
A27: STT | B27: Nội dung | C27: Số ngày | D27: Giá trị cộng dồn
A28: 1 | B28: Ký HD | C28: 0
A29: 2 | B29: Tạm ứng | C29: 0
A30: 3 | B30: Mở LC | C30: 0 | D30: =+C30+D29+C29 -> 0
A31: 4 | B31: Giao Hàng tại xưởng | C31: 26 | D31: =+C31+D30 -> 26
A32: 5 | B32: Nghiệm thu | C32: 2 | D32: =+C32+D31 -> 28
A33: 6 | B33: Bàn giao | C33: 1 | D33: =+C33+D32 -> 29

Sheet PL01 Hung nguyen
A1: CÔNG TY TNHH THƯƠNG MẠI HÙNG NGUYÊN Trụ sở: Số 673 đường 5/2, P.Hùng Vương, Q.Hồng Bàng, Hải Phòng VPGD: Số 955 đường Hùng Vương, P.Hùng Vương, Q.Hồng Bàng, TP.Hải Phòng Điện thoại: 0225.3529.509 / E: hungnguyenthep@gmail.com
A3: PHỤ LỤC SỐ 01 THUỘC HỢP ĐỒNG MUA BÁN SỐ: 030224/HN-IBS ngày 03/02/2024
A4: Hôm nay ngày 03/02/2024, Công ty TNHH Thương Mại Hùng Nguyên (Bên Bán) và CÔNG TY CỔ PHẦN CÔNG NGHIỆP NẶNG IBS (Bên Mua) thống nhất lập phụ lục hợp đồng số: 01 thuộc Hợp đồng mua bán số: 030224/HN-IBS ngày 03/02/2024 với các điều khoản cụ thể như sau:
A5: Điều 1: Thông tin lô hàng đính kèm hợp đồng:
A6: STT | C6: Tên hàng hóa | D6: Mác thép | E6: Xuất xứ | F6: Số lượng (Cây,Tấm) | G6: Trọng lượng (KG) | H6: Đơn giá Có VAT (VNĐ/KG) | I6: Đơn giá Chưa VAT (VND/KG) | K6: Thành tiền Chưa VAT (VNĐ)
A7: (a) | C7: (b) | F7: (c) | G7: (d) | H7: (e) | I7: (f) | K7: (g = d x f)
A8: 1 | B8: A-01 | C8: Thép tấm 10x2000x12000 | D8: A36/SS400 | E8: Trung Quốc | F8: 14 | G8: =ROUND(10*2*12*7.85*F8,0) -> 26376 | H8: 16550 | I8: =+ROUND(H8/1.1,2) -> 15045.45 | K8: =+ROUND(G8*I8,0) -> 396838789
A9: 2 | B9: A-06 | C9: Thép tấm 6x2000x12000 | D9: A36/SS400 | E9: Trung Quốc | F9: 22 | G9: =ROUND(6*2*12*7.85*F9,0) -> 24869 | H9: 16550 | I9: =+ROUND(H9/1.1,2) -> 15045.45 | K9: =+ROUND(G9*I9,0) -> 374165296
A10: 3 | B10: A-17 | C10: Thép tấm 12x2000x6000 | D10: A36/SS400 | E10: Trung Quốc | F10: 1 | G10: =ROUND(12*2*6*7.85*F10,0) -> 1130 | H10: 16550 | I10: =+ROUND(H10/1.1,2) -> 15045.45 | K10: =+ROUND(G10*I10,0) -> 17001359
A11: 4 | B11: A-15 | C11: Thép tấm 10x2000x12000 | D11: Q355/A572 | E11: Trung Quốc | F11: 1.5 | G11: =ROUND(10*2*12*7.85*F11,0) -> 2826 | H11: 17550 | I11: =+ROUND(H11/1.1,2) -> 15954.55 | K11: =+ROUND(G11*I11,0) -> 45087558
A12: 5 | B12: A-16 | C12: Thép tấm 12x2000x6000 | D12: Q355/A572 | E12: Trung Quốc | F12: 1 | G12: =ROUND(12*2*6*7.85*F12,0) -> 1130 | H12: 17550 | I12: =+ROUND(H12/1.1,2) -> 15954.55 | K12: =+ROUND(G12*I12,0) -> 18028642
A13: 6 | B13: A-18 | C13: Thép tấm 16x2000x6000 | D13: Q355/A572 | E13: Trung Quốc | F13: 1 | G13: =ROUND(16*2*6*7.85*F13,0) -> 1507 | H13: 17550 | I13: =+ROUND(H13/1.1,2) -> 15954.55 | K13: =+ROUND(G13*I13,0) -> 24043507
A14: 7 | B14: A-19 | C14: Thép tấm 20x2000x12000 | D14: Q355/A572 | E14: Trung Quốc | F14: 5 | G14: =ROUND(20*2*12*7.85*F14,0) -> 18840 | H14: 17550 | I14: =+ROUND(H14/1.1,2) -> 15954.55 | K14: =+ROUND(G14*I14,0) -> 300583722
A15: 8 | B15: A-20 | C15: Thép tấm 22x2000x12000 | D15: Q355/A572 | E15: Trung Quốc | F15: 3.5 | G15: =ROUND(22*2*12*7.85*F15,0) -> 14507 | H15: 18050 | I15: =+ROUND(H15/1.1,2) -> 16409.09 | K15: =+ROUND(G15*I15,0) -> 238046669
A16: 9 | B16: A-21 | C16: Thép tấm 25x2000x6000 | D16: Q355/A572 | E16: Trung Quốc | F16: 1 | G16: =ROUND(25*2*6*7.85*F16,0) -> 2355 | H16: 18050 | I16: =+ROUND(H16/1.1,2) -> 16409.09 | K16: =+ROUND(G16*I16,0) -> 38643407
A17: 10 | B17: A-22 | C17: Thép tấm 28x2000x6000 | D17: Q355/A572 | E17: Trung Quốc | F17: 1 | G17: =ROUND(28*2*6*7.85*F17,0) -> 2638 | H17: 18050 | I17: =+ROUND(H17/1.1,2) -> 16409.09 | K17: =+ROUND(G17*I17,0) -> 43287179
A18: 11 | B18: A-23 | C18: Thép tấm 32x2000x6000 | D18: Q355/A572 | E18: Trung Quốc | F18: 1 | G18: =ROUND(32*2*6*7.85*F18,0) -> 3014 | H18: 18050 | I18: =+ROUND(H18/1.1,2) -> 16409.09 | K18: =+ROUND(G18*I18,0) -> 49456997
A19: 12 | B19: A-24 | C19: Thép U125x65x6x8x12000 | D19: SS400 | E19: Nhật Bản/ Hàn Quốc/ Thái Lan | F19: 9 | G19: =ROUND(13.4*12*F19,2) -> 1447.2 | H19: 24050 | I19: =+ROUND(H19/1.1,2) -> 21863.64 | K19: =+ROUND(G19*I19,0) -> 31641060
A20: 13 | B20: A-25 | C20: Thép U150x75x6.5x10x12000 | D20: SS400 | E20: Việt Nam | F20: 7 | G20: =ROUND(18.6*12*F20,2) -> 1562.4 | H20: 18550 | I20: =+ROUND(H20/1.1,2) -> 16863.64 | K20: =+ROUND(G20*I20,0) -> 26347751
A21: 14 | B21: A-26 | C21: Thép U180x68x7x12000 | D21: SS400 | E21: Trung Quốc | F21: 54 | G21: =ROUND(18.6*12*F21,2) -> 12052.8 | H21: 18550 | I21: =+ROUND(H21/1.1,2) -> 16863.64 | K21: =+ROUND(G21*I21,0) -> 203254080
A22: 15 | B22: A-27 | C22: Thép U200x80x7.5x11x12000 | D22: SS400 | E22: Nhật Bản/ Hàn Quốc/ Thái Lan | F22: 24 | G22: =ROUND(24.6*12*F22,2) -> 7084.8 | H22: 24050 | I22: =+ROUND(H22/1.1,2) -> 21863.64 | K22: =+ROUND(G22*I22,0) -> 154899517
A23: 16 | B23: A-28 | C23: Thép U200x90x8x13.5x12000 | D23: SS400 | E23: Nhật Bản/ Hàn Quốc/ Thái Lan | F23: 7 | G23: =ROUND(30.3*12*F23,2) -> 2545.2 | H23: 24550 | I23: =+ROUND(H23/1.1,2) -> 22318.18 | K23: =+ROUND(G23*I23,0) -> 56804232
A24: 17 | B24: A-29 | C24: Thép U250x90x9x13x12000 | D24: SS400 | E24: Nhật Bản/ Hàn Quốc/ Thái Lan | F24: 3 | G24: =ROUND(34.6*12*F24,2) -> 1245.6 | H24: 24550 | I24: =+ROUND(H24/1.1,2) -> 22318.18 | K24: =+ROUND(G24*I24,0) -> 27799525
A25: 18 | B25: A-30 | C25: Thép H150x150x7x10x12000 | D25: SS400 | E25: Việt Nam | F25: 2 | G25: =ROUND(31.5*12*F25,2) -> 756 | H25: 20850 | I25: =+ROUND(H25/1.1,2) -> 18954.55 | K25: =+ROUND(G25*I25,0) -> 14329640
A26: 19 | B26: A-31 | C26: Thép H194x150x6x9x12000 | D26: SS400 | E26: Việt Nam | F26: 1 | G26: =ROUND(30.6*12*F26,2) -> 367.2 | H26: 20950 | I26: =+ROUND(H26/1.1,2) -> 19045.45 | K26: =+ROUND(G26*I26,0) -> 6993489
A27: 20 | B27: A-32 | C27: Thép H244x175x7x11x12000 | D27: SS400 | E27: Việt Nam | F27: 11 | G27: =ROUND(44.1*12*F27,2) -> 5821.2 | H27: 20950 | I27: =+ROUND(H27/1.1,2) -> 19045.45 | K27: =+ROUND(G27*I27,0) -> 110867374
A28: 21 | B28: A-33 | C28: Thép I250x125x6x9x12000 | D28: SS400 | E28: Việt Nam | F28: 7.5 | G28: =ROUND(29.6*12*F28,20) -> 2664 | H28: 20850 | I28: =+ROUND(H28/1.1,2) -> 18954.55 | K28: =+ROUND(G28*I28,0) -> 50494921
A29: 22 | B29: A-34 | C29: Thép I300x150x6.5x9x12000 | D29: SS400 | E29: Việt Nam | F29: 5.5 | G29: =ROUND(36.7*12*F29,2) -> 2422.2 | H29: 20850 | I29: =+ROUND(H29/1.1,2) -> 18954.55 | K29: =+ROUND(G29*I29,0) -> 45911711
A30: 23 | B30: A-35 | C30: Thép góc L100x100x10x12000 | D30: SS400 | E30: Việt Nam | F30: 3 | G30: =ROUND(181.26*F30,0) -> 544 | H30: 17350 | I30: =+ROUND(H30/1.1,2) -> 15772.73 | K30: =+ROUND(G30*I30,0) -> 8580365
A31: 24 | B31: A-36 | C31: Thép góc L100x100x7x6000 | D31: SS400 | E31: Việt Nam | F31: 1 | G31: =64.44*F31 -> 64.44 | H31: 17350 | I31: =+ROUND(H31/1.1,2) -> 15772.73 | K31: =+ROUND(G31*I31,0) -> 1016395
A32: 25 | B32: A-37 | C32: Thép góc L130x130x10x12000 | D32: SS400 | E32: Trung Quốc | F32: 1 | G32: =238.5*F32 -> 238.5 | H32: 18550 | I32: =+ROUND(H32/1.1,2) -> 16863.64 | K32: =+ROUND(G32*I32,0) -> 4021978
A33: 26 | B33: A-38 | C33: Thép góc L150x150x10x12000 | D33: SS400 | E33: Việt Nam | F33: 3 | G33: =ROUND(276.66*F33,2) -> 829.98 | H33: 19550 | I33: =+ROUND(H33/1.1,2) -> 17772.73 | K33: =+ROUND(G33*I33,0) -> 14751010
A34: 27 | B34: A-39 | C34: Thép góc L65x65x6x6000 | D34: SS400 | E34: Việt Nam | F34: 1 | G34: =35.49*F34 -> 35.49 | H34: 17050 | I34: =+ROUND(H34/1.1,2) -> 15500 | K34: =+ROUND(G34*I34,0) -> 550095
A35: 28 | B35: A-41 | C35: Thép góc L75x75x6x6000 | D35: SS400 | E35: Việt Nam | F35: 7 | G35: 288.47 | H35: 17050 | I35: =+ROUND(H35/1.1,2) -> 15500 | K35: =+ROUND(G35*I35,0) -> 4471285
A36: 29 | B36: A-42 | C36: Thép góc L75x75x8x6000 | D36: SS400 | E36: Việt Nam | F36: 1 | G36: 54.19 | H36: 17050 | I36: =+ROUND(H36/1.1,2) -> 15500 | K36: =+ROUND(G36*I36,0) -> 839945
A37: 30 | B37: A-43 | C37: Thép góc L90x90x10x12000 | D37: SS400 | E37: Việt Nam | F37: 12 | G37: =ROUND(162.18*F37,2) -> 1946.16 | H37: 17350 | I37: =+ROUND(H37/1.1,2) -> 15772.73 | K37: =+ROUND(G37*I37,0) -> 30696256
A38: 31 | B38: A-44 | C38: Thép góc L90x90x6x12000 | D38: SS400 | E38: Việt Nam | F38: 6 | G38: 597.6 | H38: 17350 | I38: =+ROUND(H38/1.1,2) -> 15772.73 | K38: =+ROUND(G38*I38,0) -> 9425783
A39: 32 | B39: A-45 | C39: Thép góc L90x90x7x6000 | D39: SS400 | E39: Việt Nam | F39: 10 | G39: 577.65 | H39: 17350 | I39: =+ROUND(H39/1.1,2) -> 15772.73 | K39: =+ROUND(G39*I39,0) -> 9111117
A40: 33 | B40: A-55 | C40: Thép tròn D10x6000 | D40: SS400/CB240/S45C | E40: Việt Nam/ Trung Quốc | F40: 1 | G40: 3.699 | H40: 18850 | I40: =+ROUND(H40/1.1,2) -> 17136.36 | K40: =+ROUND(G40*I40,0) -> 63387
A41: 34 | B41: A-56 | C41: Thép tròn D12x6000 | D41: SS400/CB240/S45C | E41: Việt Nam/ Trung Quốc | F41: 1 | G41: 5.32656 | H41: 18850 | I41: =+ROUND(H41/1.1,2) -> 17136.36 | K41: =+ROUND(G41*I41,0) -> 91278
A42: 35 | B42: A-57 | C42: Thép tròn D14x6000 | D42: SS400/CB240/S45C | E42: Việt Nam/ Trung Quốc | F42: 1 | G42: 7.25004 | H42: 18850 | I42: =+ROUND(H42/1.1,2) -> 17136.36 | K42: =+ROUND(G42*I42,0) -> 124239
A43: 36 | B43: A-58 | C43: Thép tròn D16x6000 | D43: SS400/CB240/S45C | E43: Việt Nam/ Trung Quốc | F43: 1 | G43: 9.46944 | H43: 18850 | I43: =+ROUND(H43/1.1,2) -> 17136.36 | K43: =+ROUND(G43*I43,0) -> 162272
A44: 37 | B44: A-59 | C44: Thép tròn D20x6000 | D44: SS400/CB240/S45C | E44: Việt Nam/ Trung Quốc | F44: 1 | G44: 14.8 | H44: 18850 | I44: =+ROUND(H44/1.1,2) -> 17136.36 | K44: =+ROUND(G44*I44,0) -> 253618
A45: 38 | B45: A-60 | C45: Thép tròn D38x6000 | D45: SS400/CB240/S45C | E45: Việt Nam/ Trung Quốc | F45: 1 | G45: 53.41 | H45: 19250 | I45: =+ROUND(H45/1.1,2) -> 17500 | K45: =+ROUND(G45*I45,0) -> 934675
A46: Tổng: | F46: =SUBTOTAL(9,F8:F45) -> 234 | G46: =SUBTOTAL(9,G8:G45) -> 142431.04 | H46: Cộng tiền hàng: | K46: =SUBTOTAL(9,K8:K45) -> 2359620123
A47: Thuế GTGT: 10% | G47: Tiền thuế GTGT: | K47: =ROUND(K46*0.1,0) -> 235962012
A48: Tổng số tiền viết bằng số: | K48: =SUM(K46:K47) -> 2595582135
A49: Số tiền viết bằng chữ: | D49: =+_xll.VND(K48) -> #NAME?
A52: Điều 2: Các điều khoản khác. - Phụ lục Hợp đồng số 01 có hiệu lực kể từ ngày ký và là một phần không thể tách rời của đồng mua bán số 030224/HN-IBS ngày 03/02/2024 - Những điều khoản khác của Hợp đồng mua bán số: 030224/HN-IBS giữ nguyên giá trị hiệu lực, hai bên có trách nhiệm cùng nhau thực hiện. - Phụ lục Hợp đồng này được lập thành 04 bản, mỗi bên giữ 02 bản có giá trị như nhau.
C56: ĐẠI DIỆN BÊN BÁN | G56: ĐẠI DIỆN BÊN MUA

Sheet vogt 060_Plan_Khong su dung
A1: THEO DÕI VẬT TƯ DỰ ÁN/ MATERIAL CONTROL LOG
A2: Tên dự án/ Project no.: VOGT 060
A3: Cập nhật ngày/ Update to: | C3: =TODAY() -> 46086
A4: Item/ STT | B4: Description/ Chi tiết | C4: Profile/ Vật tư | D4: Grade/ Mác vật liệu | E4: Unit/ Đơn vị | F4: U.Weight/ Đ.Trọng (Kg/m2,m,pcs) | G4: Net Quantity/Số lượng tinh | I4: Previous Ordered/Đã dự trù | K4: Current Ordered/Dự trù lần 1 | M4: Total Ordered/Tổng dự trù | O4: Ngày vật tư đưa vào sử dụng/ Material avaiable for fabrication date | P4: Tận dụng tồn kho/ Remain | R4: Khối lượng phải mua sắm/ total order | T4: Mua sắm trong nước/ Local purchase | AB4: Mua sắm nước ngoài/ Oversea purchase | AM4: Remarks/ Ghi chú
G5: Q.Ty/ Số lượng | H5: Weight/ Khối lượng (Kg) | I5: Q.Ty/ Số lượng | J5: Weight/ Khối lượng (Kg) | K5: Q.Ty/Số lượng | L5: Weight/Khối lượng (Kg) | M5: Q.Ty/ Số lượng | N5: Weight/Khối lượng (Kg) | P5: Q.Ty/ Số lượng | Q5: Weight/Khối lượng (Kg) | R5: Q.Ty/ Số lượng | S5: Weight/Khối lượng (Kg) | T5: Q.Ty/ Số lượng | U5: Weight/ Khối lượng (Kg) | V5: Nhà cung cấp/ Vendor | W5: Ngày ký HD/ Contract date | X5: Ngày giao hàng/ Handover date | Y5: Ngày nghiệm thu, Bàn giao/ Inspection date | Z5: Kết quả nghiệm thu/ Results | AA5: Bàn giao sản xuất/ Handover to Product | AB5: Q.Ty/ Số lượng | AC5: Weight/ Khối lượng (Kg) | AD5: Nhà cung cấp/ Vendor | AE5: Ngày ký HD/ Contract date | AF5: Ngày mở L/C/ LC issued date | AG5: Hàng đi từ cảng nước ngoài/ Export Port | AH5: Hàng Đến cảng HP (CIF)/ HaiPhong CIF | AI5: Thủ tục hải quan, vận chuyển/ Paper work, local transportaion date | AJ5: Ngày nghiệm thu, Bàn giao/ Handover date | AK5: Kết quả nghiệm thu/ Results | AL5: Bàn giao sản xuất/ Handover to Product
A6: 1 | B6: 2 | C6: 3 | D6: 4 | E6: 5 | F6: 6 | G6: 7 | H6: 8 | I6: 9 | J6: 10 | K6: 11 | L6: 12 | M6: 13 | N6: 14 | AM6: 15
A7: A. | B7: Main-Material / Vật tư chính | H7: =SUM(H8:H86) -> 447323.94 | J7: =SUM(J8:J86) -> 2826 | L7: =SUM(L8:L86) -> 493509.35 | N7: =SUM(N8:N86) -> 496335.35 | U7: =SUM(U8:U86) -> 452389.54 | AC7: =SUM(AC8:AC86) -> 43945.809 | AM7: .
A8: A-1 | B8: TÔN TẤM | C8: PL10X2000X12000 | D8: SS400 | E8: m2 | F8: 78.5 | G8: =+H8/F8 -> 612.19898 | H8: =1259.98+46797.64 -> 48057.62 | I8: 36 | J8: 2826 | K8: 650 | L8: =+K8*F8 -> 51025 | M8: =+K8+I8 -> 686 | N8: =+L8+J8 -> 53851 | O8: 45316 | R8: =+M8-P8 -> 686 | S8: =+N8-Q8 -> 53851 | T8: =+R8 -> 686 | U8: =+S8 -> 53851 | V8: Hùng Nguyên | W8: 45324 | X8: =+W8+'Dieu kien giao hang'!$C$21 -> 45328 | Y8: =+X8+'Dieu kien giao hang'!$C$22 -> 45330
A9: A-2 | B9: TÔN TẤM-LINER INOX | C9: PL1.5x1220x2440 | D9: SUH409 | E9: m2 | F9: =+H9/G9 -> 11.895 | G9: 2220.0992 | H9: 26408.08 | K9: 2510 | L9: =+K9*F9 -> 29856.45 | M9: =+K9+I9 -> 2510 | N9: =+L9+J9 -> 29856.45 | O9: 45371 | R9: =+M9-P9 -> 2510 | S9: =+N9-Q9 -> 29856.45 | AB9: =+R9 -> 2510 | AC9: =+S9 -> 29856.45 | AD9: GNEE | AE9: 45323 | AF9: =+AE9+'Dieu kien giao hang'!$C$6 -> 45328 | AG9: =AF9+'Dieu kien giao hang'!$C$7 -> 45348 | AH9: =AG9+'Dieu kien giao hang'!$C$8 -> 45353 | AI9: =AH9+'Dieu kien giao hang'!$C$10 -> 45356 | AJ9: =AI9+'Dieu kien giao hang'!$C$13 -> 45368
A10: A-3 | B10: TÔN TẤM-LINER INOX | C10: PL2x1220x2440 | D10: SUH409 | E10: m2 | F10: =+H10/G10 -> 15.968596 | G10: 736.67591 | H10: 11763.68 | K10: 835 | L10: =+K10*F10 -> 13333.778 | M10: =+K10+I10 -> 835 | N10: =+L10+J10 -> 13333.778 | O10: 45371 | R10: =+M10-P10 -> 835 | S10: =+N10-Q10 -> 13333.778 | AB10: =+R10 -> 835 | AC10: =+S10 -> 13333.778 | AD10: GNEE | AE10: 45323 | AF10: =+AE10+'Dieu kien giao hang'!$C$6 -> 45328 | AG10: =AF10+'Dieu kien giao hang'!$C$7 -> 45348 | AH10: =AG10+'Dieu kien giao hang'!$C$8 -> 45353 | AI10: =AH10+'Dieu kien giao hang'!$C$10 -> 45356 | AJ10: =AI10+'Dieu kien giao hang'!$C$13 -> 45368
A11: A-4 | B11: TÔN TẤM | C11: PL3 | D11: SUH409 | E11: m2 | F11: =+H11/G11 -> 23.55 | G11: 2.2573248 | H11: 53.16 | K11: 3 | L11: =+K11*F11 -> 70.65 | M11: =+K11+I11 -> 3 | N11: =+L11+J11 -> 70.65 | O11: 45371 | R11: =+M11-P11 -> 3 | S11: =+N11-Q11 -> 70.65 | AB11: =+R11 -> 3 | AC11: =+S11 -> 70.65 | AD11: GNEE | AE11: 45323 | AF11: =+AE11+'Dieu kien giao hang'!$C$6 -> 45328 | AG11: =AF11+'Dieu kien giao hang'!$C$7 -> 45348 | AH11: =AG11+'Dieu kien giao hang'!$C$8 -> 45353 | AI11: =AH11+'Dieu kien giao hang'!$C$10 -> 45356 | AJ11: =AI11+'Dieu kien giao hang'!$C$13 -> 45368
A12: A-5 | B12: TÔN TẤM | C12: PL6 | D12: A-240 TP304 | E12: m2 | F12: =+H12/G12 -> 47.1 | G12: 0.072186837 | H12: 3.4 | K12: 1 | L12: =+K12*F12 -> 47.1 | M12: =+K12+I12 -> 1 | N12: =+L12+J12 -> 47.1 | O12: 45371 | R12: =+M12-P12 -> 1 | S12: =+N12-Q12 -> 47.1 | AB12: =+R12 -> 1 | AC12: =+S12 -> 47.1 | AD12: GNEE | AE12: 45323 | AF12: =+AE12+'Dieu kien giao hang'!$C$6 -> 45328 | AG12: =AF12+'Dieu kien giao hang'!$C$7 -> 45348 | AH12: =AG12+'Dieu kien giao hang'!$C$8 -> 45353 | AI12: =AH12+'Dieu kien giao hang'!$C$10 -> 45356 | AJ12: =AI12+'Dieu kien giao hang'!$C$13 -> 45368
A13: A-6 | B13: TÔN TẤM | C13: PL6x2000x12000 | D13: SS400 | E13: m2 | F13: =+H13/G13 -> 47.1 | G13: 1159.5244 | H13: 54613.6 | K13: =1.12*G13 -> 1298.6673 | L13: =+K13*F13 -> 61167.232 | M13: =+K13+I13 -> 1298.6673 | N13: =+L13+J13 -> 61167.232 | O13: 45338 | R13: =+M13-P13 -> 1298.6673 | S13: =+N13-Q13 -> 61167.232 | T13: =+R13 -> 1298.6673 | U13: =+S13 -> 61167.232 | V13: Hùng Nguyên | W13: 45324 | X13: =+W13+'Dieu kien giao hang'!$C$21 -> 45328 | Y13: =+X13+'Dieu kien giao hang'!$C$22 -> 45330
A14: A-7 | B14: TÔN TẤM CUỘN CẮT | C14: PL6X1500X7100 | D14: SS400 | E14: m2 | F14: =+H14/G14 -> 47.1 | G14: 216 | H14: 10173.6 | K14: =1.08*G14 -> 233.28 | L14: =+K14*F14 -> 10987.488 | M14: =+K14+I14 -> 233.28 | N14: =+L14+J14 -> 10987.488 | O14: 45338 | R14: =+M14-P14 -> 233.28 | S14: =+N14-Q14 -> 10987.488 | T14: =+R14 -> 233.28 | U14: =+S14 -> 10987.488 | V14: Hùng Nguyên | W14: 45324 | X14: =+W14+'Dieu kien giao hang'!$C$21 -> 45328 | Y14: =+X14+'Dieu kien giao hang'!$C$22 -> 45330
A15: A-8 | B15: TÔN TẤM CUỘN CẮT | C15: PL6x1500x9000 | D15: SS400 | E15: m2 | F15: =+H15/G15 -> 47.1 | G15: 408 | H15: 19216.8 | K15: =1.08*G15 -> 440.64 | L15: =+K15*F15 -> 20754.144 | M15: =+K15+I15 -> 440.64 | N15: =+L15+J15 -> 20754.144 | O15: 45338 | R15: =+M15-P15 -> 440.64 | S15: =+N15-Q15 -> 20754.144 | T15: =+R15 -> 440.64 | U15: =+S15 -> 20754.144 | V15: Hùng Nguyên | W15: 45324 | X15: =+W15+'Dieu kien giao hang'!$C$21 -> 45328 | Y15: =+X15+'Dieu kien giao hang'!$C$22 -> 45330
A16: A-9 | B16: TÔN TẤM CUỘN CẮT | C16: PL6X1500X11000 | D16: SS400 | E16: m2 | F16: =+H16/G16 -> 47.1 | G16: 720 | H16: 33912 | K16: =1.08*G16 -> 777.6 | L16: =+K16*F16 -> 36624.96 | M16: =+K16+I16 -> 777.6 | N16: =+L16+J16 -> 36624.96 | O16: 45338 | R16: =+M16-P16 -> 777.6 | S16: =+N16-Q16 -> 36624.96 | T16: =+R16 -> 777.6 | U16: =+S16 -> 36624.96 | V16: Hùng Nguyên | W16: 45324 | X16: =+W16+'Dieu kien giao hang'!$C$21 -> 45328 | Y16: =+X16+'Dieu kien giao hang'!$C$22 -> 45330
A17: A-10 | B17: TÔN TẤM CUỘN CẮT | C17: PL8X1500X7100 | D17: SS400 | E17: m2 | F17: =+H17/G17 -> 62.8 | G17: 232 | H17: 14569.6 | K17: =1.08*G17 -> 250.56 | L17: =+K17*F17 -> 15735.168 | M17: =+K17+I17 -> 250.56 | N17: =+L17+J17 -> 15735.168 | O17: 45338 | R17: =+M17-P17 -> 250.56 | S17: =+N17-Q17 -> 15735.168 | T17: =+R17 -> 250.56 | U17: =+S17 -> 15735.168 | V17: Hùng Nguyên | W17: 45324 | X17: =+W17+'Dieu kien giao hang'!$C$21 -> 45328 | Y17: =+X17+'Dieu kien giao hang'!$C$22 -> 45330
A18: A-11 | B18: TÔN TẤM CUỘN CẮT | C18: PL8X1500X9000 | D18: SS400 | E18: m2 | F18: =+H18/G18 -> 62.8 | G18: 140 | H18: 8792 | K18: =1.08*G18 -> 151.2 | L18: =+K18*F18 -> 9495.36 | M18: =+K18+I18 -> 151.2 | N18: =+L18+J18 -> 9495.36 | O18: 45338 | R18: =+M18-P18 -> 151.2 | S18: =+N18-Q18 -> 9495.36 | T18: =+R18 -> 151.2 | U18: =+S18 -> 9495.36 | V18: Hùng Nguyên | W18: 45324 | X18: =+W18+'Dieu kien giao hang'!$C$21 -> 45328 | Y18: =+X18+'Dieu kien giao hang'!$C$22 -> 45330
A19: A-12 | B19: TÔN TẤM CUỘN CẮT | C19: PL8X1500X11000 | D19: SS400 | E19: m2 | F19: =+H19/G19 -> 62.8 | G19: 240 | H19: 15072 | K19: =1.08*G19 -> 259.2 | L19: =+K19*F19 -> 16277.76 | M19: =+K19+I19 -> 259.2 | N19: =+L19+J19 -> 16277.76 | O19: 45338 | R19: =+M19-P19 -> 259.2 | S19: =+N19-Q19 -> 16277.76 | T19: =+R19 -> 259.2 | U19: =+S19 -> 16277.76 | V19: Hùng Nguyên | W19: 45324 | X19: =+W19+'Dieu kien giao hang'!$C$21 -> 45328 | Y19: =+X19+'Dieu kien giao hang'!$C$22 -> 45330
A20: A-13 | B20: TÔN TẤM | C20: PL8X2000X12000 | D20: SS400 | E20: m2 | F20: =+H20/G20 -> 62.8 | G20: 140 | H20: 8792 | K20: =1.12*G20 -> 156.8 | L20: =+K20*F20 -> 9847.04 | M20: =+K20+I20 -> 156.8 | N20: =+L20+J20 -> 9847.04 | O20: 45338 | R20: =+M20-P20 -> 156.8 | S20: =+N20-Q20 -> 9847.04 | T20: =+R20 -> 156.8 | U20: =+S20 -> 9847.04 | V20: Hùng Nguyên | W20: 45324 | X20: =+W20+'Dieu kien giao hang'!$C$21 -> 45328 | Y20: =+X20+'Dieu kien giao hang'!$C$22 -> 45330
A21: A-14 | B21: TÔN TẤM | C21: PL10 | D21: A-240 TP304 | E21: m2 | F21: =+H21/G21 -> 78.5 | G21: 0.41579618 | H21: 32.64 | K21: =1.12*G21 -> 0.46569172 | L21: =+K21*F21 -> 36.5568 | M21: =+K21+I21 -> 0.46569172 | N21: =+L21+J21 -> 36.5568 | O21: 45371 | R21: =+M21-P21 -> 0.46569172 | S21: =+N21-Q21 -> 36.5568 | AB21: =+R21 -> 0.46569172 | AC21: =+S21 -> 36.5568 | AD21: GNEE | AE21: 45323 | AF21: =+AE21+'Dieu kien giao hang'!$C$6 -> 45328 | AG21: =AF21+'Dieu kien giao hang'!$C$7 -> 45348 | AH21: =AG21+'Dieu kien giao hang'!$C$8 -> 45353 | AI21: =AH21+'Dieu kien giao hang'!$C$10 -> 45356 | AJ21: =AI21+'Dieu kien giao hang'!$C$13 -> 45368
A22: A-15 | B22: TÔN TẤM | C22: PL10x2000x12000 | D22: A572-GR.50 | E22: m2 | F22: =+H22/G22 -> 78.5 | G22: 48.524841 | H22: 3809.2 | K22: =1.12*G22 -> 54.347822 | L22: =+K22*F22 -> 4266.304 | M22: =+K22+I22 -> 54.347822 | N22: =+L22+J22 -> 4266.304 | O22: 45338 | R22: =+M22-P22 -> 54.347822 | S22: =+N22-Q22 -> 4266.304 | T22: =+R22 -> 54.347822 | U22: =+S22 -> 4266.304 | V22: Hùng Nguyên | W22: 45324 | X22: =+W22+'Dieu kien giao hang'!$C$21 -> 45328 | Y22: =+X22+'Dieu kien giao hang'!$C$22 -> 45330
A23: A-16 | B23: TÔN TẤM | C23: PL12x2000x12000 | D23: A572-GR.50 | E23: m2 | F23: =+H23/G23 -> 94.2 | G23: 1.0292994 | H23: 96.96 | K23: =1.12*G23 -> 1.1528153 | L23: =+K23*F23 -> 108.5952 | M23: =+K23+I23 -> 1.1528153 | N23: =+L23+J23 -> 108.5952 | O23: 45338 | R23: =+M23-P23 -> 1.1528153 | S23: =+N23-Q23 -> 108.5952 | T23: =+R23 -> 1.1528153 | U23: =+S23 -> 108.5952 | V23: Hùng Nguyên | W23: 45324 | X23: =+W23+'Dieu kien giao hang'!$C$21 -> 45328 | Y23: =+X23+'Dieu kien giao hang'!$C$22 -> 45330
A24: A-17 | B24: TÔN TẤM | C24: PL12x2000x12000 | D24: SS400 | E24: m2 | F24: =+H24/G24 -> 94.2 | G24: 8.8276008 | H24: 831.56 | K24: =1.12*G24 -> 9.886913 | L24: =+K24*F24 -> 931.3472 | M24: =+K24+I24 -> 9.886913 | N24: =+L24+J24 -> 931.3472 | O24: 45338 | R24: =+M24-P24 -> 9.886913 | S24: =+N24-Q24 -> 931.3472 | T24: =+R24 -> 9.886913 | U24: =+S24 -> 931.3472 | V24: Hùng Nguyên | W24: 45324 | X24: =+W24+'Dieu kien giao hang'!$C$21 -> 45328 | Y24: =+X24+'Dieu kien giao hang'!$C$22 -> 45330
A25: A-18 | B25: TÔN TẤM | C25: PL16x2000x12000 | D25: A572-GR.50 | E25: m2 | F25: =+H25/G25 -> 125.6 | G25: 12.253503 | H25: 1539.04 | K25: =1.12*G25 -> 13.723924 | L25: =+K25*F25 -> 1723.7248 | M25: =+K25+I25 -> 13.723924 | N25: =+L25+J25 -> 1723.7248 | O25: 45338 | R25: =+M25-P25 -> 13.723924 | S25: =+N25-Q25 -> 1723.7248 | T25: =+R25 -> 13.723924 | U25: =+S25 -> 1723.7248 | V25: Hùng Nguyên | W25: 45324 | X25: =+W25+'Dieu kien giao hang'!$C$21 -> 45328 | Y25: =+X25+'Dieu kien giao hang'!$C$22 -> 45330
A26: A-19 | B26: TÔN TẤM | C26: PL20x2000x12000 | D26: A572-GR.50 | E26: m2 | F26: =+H26/G26 -> 157 | G26: 208.2242 | H26: 32691.2 | K26: =1.12*G26 -> 233.21111 | L26: =+K26*F26 -> 36614.144 | M26: =+K26+I26 -> 233.21111 | N26: =+L26+J26 -> 36614.144 | O26: 45338 | R26: =+M26-P26 -> 233.21111 | S26: =+N26-Q26 -> 36614.144 | T26: =+R26 -> 233.21111 | U26: =+S26 -> 36614.144 | V26: Hùng Nguyên | W26: 45324 | X26: =+W26+'Dieu kien giao hang'!$C$21 -> 45328 | Y26: =+X26+'Dieu kien giao hang'!$C$22 -> 45330
A27: A-20 | B27: TÔN TẤM | C27: PL22x2000x12000 | D27: A572-GR.50 | E27: m2 | F27: =+H27/G27 -> 172.7 | G27: 148.54105 | H27: 25653.04 | K27: =1.12*G27 -> 166.36598 | L27: =+K27*F27 -> 28731.405 | M27: =+K27+I27 -> 166.36598 | N27: =+L27+J27 -> 28731.405 | O27: 45338 | R27: =+M27-P27 -> 166.36598 | S27: =+N27-Q27 -> 28731.405 | T27: =+R27 -> 166.36598 | U27: =+S27 -> 28731.405 | V27: Hùng Nguyên | W27: 45324 | X27: =+W27+'Dieu kien giao hang'!$C$21 -> 45328 | Y27: =+X27+'Dieu kien giao hang'!$C$22 -> 45330
A28: A-21 | B28: TÔN TẤM | C28: PL25 | D28: A572-GR.50 | E28: m2 | F28: =+H28/G28 -> 196.25 | G28: 4.485707 | H28: 880.32 | K28: =1.12*G28 -> 5.0239918 | L28: =+K28*F28 -> 985.9584 | M28: =+K28+I28 -> 5.0239918 | N28: =+L28+J28 -> 985.9584 | O28: 45338 | R28: =+M28-P28 -> 5.0239918 | S28: =+N28-Q28 -> 985.9584 | T28: =+R28 -> 5.0239918 | U28: =+S28 -> 985.9584 | V28: Hùng Nguyên | W28: 45324 | X28: =+W28+'Dieu kien giao hang'!$C$21 -> 45328 | Y28: =+X28+'Dieu kien giao hang'!$C$22 -> 45330
A29: A-22 | B29: TÔN TẤM | C29: PL28 | D29: A572-GR.50 | E29: m2 | F29: =+H29/G29 -> 219.8 | G29: 5.099909 | H29: 1120.96 | K29: =1.12*G29 -> 5.7118981 | L29: =+K29*F29 -> 1255.4752 | M29: =+K29+I29 -> 5.7118981 | N29: =+L29+J29 -> 1255.4752 | O29: 45338 | R29: =+M29-P29 -> 5.7118981 | S29: =+N29-Q29 -> 1255.4752 | T29: =+R29 -> 5.7118981 | U29: =+S29 -> 1255.4752 | V29: Hùng Nguyên | W29: 45324 | X29: =+W29+'Dieu kien giao hang'!$C$21 -> 45328 | Y29: =+X29+'Dieu kien giao hang'!$C$22 -> 45330
A30: A-23 | B30: TÔN TẤM | C30: PL32x2000x6000 | D30: A572-GR.50 | E30: m2 | F30: =+H30/G30 -> 251.2 | G30: 7.6261146 | H30: 1915.68 | K30: =1.12*G30 -> 8.5412484 | L30: =+K30*F30 -> 2145.5616 | M30: =+K30+I30 -> 8.5412484 | N30: =+L30+J30 -> 2145.5616 | O30: 45338 | R30: =+M30-P30 -> 8.5412484 | S30: =+N30-Q30 -> 2145.5616 | T30: =+R30 -> 8.5412484 | U30: =+S30 -> 2145.5616 | V30: Hùng Nguyên | W30: 45324 | X30: =+W30+'Dieu kien giao hang'!$C$21 -> 45328 | Y30: =+X30+'Dieu kien giao hang'!$C$22 -> 45330
A31: A-24 | B31: THÉP HÌNH C | C31: C125X65X6X8-12000L | D31: SS400 | E31: m | F31: =+H31/G31 -> 12.511673 | G31: 373.52 | H31: 4673.36 | K31: =1.06*G31 -> 395.9312 | L31: =+K31*F31 -> 4953.7616 | M31: =+K31+I31 -> 395.9312 | N31: =+L31+J31 -> 4953.7616 | O31: 45338 | R31: =+M31-P31 -> 395.9312 | S31: =+N31-Q31 -> 4953.7616 | T31: =+R31 -> 395.9312 | U31: =+S31 -> 4953.7616 | V31: Hùng Nguyên | W31: 45324 | X31: =+W31+'Dieu kien giao hang'!$C$21 -> 45328 | Y31: =+X31+'Dieu kien giao hang'!$C$22 -> 45330
A32: A-25 | B32: THÉP HÌNH C | C32: C150X75X6.5X10-12000L | D32: SS400 | E32: m | F32: =+H32/G32 -> 18.612228 | G32: 151.264 | H32: 2815.36 | K32: =1.06*G32 -> 160.33984 | L32: =+K32*F32 -> 2984.2816 | M32: =+K32+I32 -> 160.33984 | N32: =+L32+J32 -> 2984.2816 | O32: 45338 | R32: =+M32-P32 -> 160.33984 | S32: =+N32-Q32 -> 2984.2816 | T32: =+R32 -> 160.33984 | U32: =+S32 -> 2984.2816 | V32: Hùng Nguyên | W32: 45324 | X32: =+W32+'Dieu kien giao hang'!$C$21 -> 45328 | Y32: =+X32+'Dieu kien giao hang'!$C$22 -> 45330
A33: A-26 | B33: THÉP HÌNH C | C33: C180X75X7X10.5-12000L | D33: SS400 | E33: m | F33: =+H33/G33 -> 20.123097 | G33: 1508.4 | H33: 30353.68 | K33: =1.06*G33 -> 1598.904 | L33: =+K33*F33 -> 32174.901 | M33: =+K33+I33 -> 1598.904 | N33: =+L33+J33 -> 32174.901 | O33: 45338 | R33: =+M33-P33 -> 1598.904 | S33: =+N33-Q33 -> 32174.901 | T33: =+R33 -> 1598.904 | U33: =+S33 -> 32174.901 | V33: Hùng Nguyên | W33: 45324 | X33: =+W33+'Dieu kien giao hang'!$C$21 -> 45328 | Y33: =+X33+'Dieu kien giao hang'!$C$22 -> 45330
A34: A-27 | B34: THÉP HÌNH C | C34: C200X80X7.5X11-12000L | D34: SS400 | E34: m | F34: =+H34/G34 -> 22.773663 | G34: 550.896 | H34: 12545.92 | K34: =1.06*G34 -> 583.94976 | L34: =+K34*F34 -> 13298.675 | M34: =+K34+I34 -> 583.94976 | N34: =+L34+J34 -> 13298.675 | O34: 45338 | R34: =+M34-P34 -> 583.94976 | S34: =+N34-Q34 -> 13298.675 | T34: =+R34 -> 583.94976 | U34: =+S34 -> 13298.675 | V34: Hùng Nguyên | W34: 45324 | X34: =+W34+'Dieu kien giao hang'!$C$21 -> 45328 | Y34: =+X34+'Dieu kien giao hang'!$C$22 -> 45330
A35: A-28 | B35: THÉP HÌNH C | C35: C200X90X8X13.5-12000L | D35: SS400 | E35: m | F35: =+H35/G35 -> 30.341183 | G35: 152.88 | H35: 4638.56 | K35: =1.06*G35 -> 162.0528 | L35: =+K35*F35 -> 4916.8736 | M35: =+K35+I35 -> 162.0528 | N35: =+L35+J35 -> 4916.8736 | O35: 45338 | R35: =+M35-P35 -> 162.0528 | S35: =+N35-Q35 -> 4916.8736 | T35: =+R35 -> 162.0528 | U35: =+S35 -> 4916.8736 | V35: Hùng Nguyên | W35: 45324 | X35: =+W35+'Dieu kien giao hang'!$C$21 -> 45328 | Y35: =+X35+'Dieu kien giao hang'!$C$22 -> 45330
A36: A-29 | B36: THÉP HÌNH C | C36: C250X90X9X13-12000L | D36: SS400 | E36: m | F36: =+H36/G36 -> 34.594627 | G36: 66.408 | H36: 2297.36 | K36: =1.06*G36 -> 70.39248 | L36: =+K36*F36 -> 2435.2016 | M36: =+K36+I36 -> 70.39248 | N36: =+L36+J36 -> 2435.2016 | O36: 45338 | R36: =+M36-P36 -> 70.39248 | S36: =+N36-Q36 -> 2435.2016 | T36: =+R36 -> 70.39248 | U36: =+S36 -> 2435.2016 | V36: Hùng Nguyên | W36: 45324 | X36: =+W36+'Dieu kien giao hang'!$C$21 -> 45328 | Y36: =+X36+'Dieu kien giao hang'!$C$22 -> 45330
A37: A-30 | B37: THÉP HÌNH H | C37: H150X150X7X10-12000L | D37: SS400 | E37: m | F37: =+H37/G37 -> 24.855967 | G37: 19.44 | H37: 483.2 | K37: =1.06*G37 -> 20.6064 | L37: =+K37*F37 -> 512.192 | M37: =+K37+I37 -> 20.6064 | N37: =+L37+J37 -> 512.192 | O37: 45338 | R37: =+M37-P37 -> 20.6064 | S37: =+N37-Q37 -> 512.192 | T37: =+R37 -> 20.6064 | U37: =+S37 -> 512.192 | V37: Hùng Nguyên | W37: 45324 | X37: =+W37+'Dieu kien giao hang'!$C$21 -> 45328 | Y37: =+X37+'Dieu kien giao hang'!$C$22 -> 45330
A38: A-31 | B38: THÉP HÌNH H | C38: H194X150X6X9-12000L | D38: SS400 | E38: m | F38: =+H38/G38 -> 30.612113 | G38: 6.208 | H38: 190.04 | K38: =1.06*G38 -> 6.58048 | L38: =+K38*F38 -> 201.4424 | M38: =+K38+I38 -> 6.58048 | N38: =+L38+J38 -> 201.4424 | O38: 45338 | R38: =+M38-P38 -> 6.58048 | S38: =+N38-Q38 -> 201.4424 | T38: =+R38 -> 6.58048 | U38: =+S38 -> 201.4424 | V38: Hùng Nguyên | W38: 45324 | X38: =+W38+'Dieu kien giao hang'!$C$21 -> 45328 | Y38: =+X38+'Dieu kien giao hang'!$C$22 -> 45330
A39: A-32 | B39: THÉP HÌNH H | C39: H244X175X7X11-12000L | D39: SS400 | E39: m | F39: =+H39/G39 -> 44.14586 | G39: 234.856 | H39: 10367.92 | K39: =1.06*G39 -> 248.94736 | L39: =+K39*F39 -> 10989.995 | M39: =+K39+I39 -> 248.94736 | N39: =+L39+J39 -> 10989.995 | O39: 45338 | R39: =+M39-P39 -> 248.94736 | S39: =+N39-Q39 -> 10989.995 | T39: =+R39 -> 248.94736 | U39: =+S39 -> 10989.995 | V39: Hùng Nguyên | W39: 45324 | X39: =+W39+'Dieu kien giao hang'!$C$21 -> 45328 | Y39: =+X39+'Dieu kien giao hang'!$C$22 -> 45330
A40: A-33 | B40: THÉP HÌNH H | C40: H250X125X6X9-12000L | D40: SS400 | E40: m | F40: =+H40/G40 -> 29.561881 | G40: 163.152 | H40: 4823.08 | K40: =1.06*G40 -> 172.94112 | L40: =+K40*F40 -> 5112.4648 | M40: =+K40+I40 -> 172.94112 | N40: =+L40+J40 -> 5112.4648 | O40: 45338 | R40: =+M40-P40 -> 172.94112 | S40: =+N40-Q40 -> 5112.4648 | T40: =+R40 -> 172.94112 | U40: =+S40 -> 5112.4648 | V40: Hùng Nguyên | W40: 45324 | X40: =+W40+'Dieu kien giao hang'!$C$21 -> 45328 | Y40: =+X40+'Dieu kien giao hang'!$C$22 -> 45330
A41: A-34 | B41: THÉP HÌNH H | C41: H300X150X6.5X9-12000L | D41: SS400 | E41: m | F41: =+H41/G41 -> 35.582918 | G41: 123.448 | H41: 4392.64 | K41: =1.06*G41 -> 130.85488 | L41: =+K41*F41 -> 4656.1984 | M41: =+K41+I41 -> 130.85488 | N41: =+L41+J41 -> 4656.1984 | O41: 45338 | R41: =+M41-P41 -> 130.85488 | S41: =+N41-Q41 -> 4656.1984 | T41: =+R41 -> 130.85488 | U41: =+S41 -> 4656.1984 | V41: Hùng Nguyên | W41: 45324 | X41: =+W41+'Dieu kien giao hang'!$C$21 -> 45328 | Y41: =+X41+'Dieu kien giao hang'!$C$22 -> 45330
A42: A-35 | B42: THÉP HÌNH L | C42: L100X100X10-12000L | D42: SS400 | E42: m | F42: =+H42/G42 -> 12.744347 | G42: 65.808 | H42: 838.68 | K42: =1.06*G42 -> 69.75648 | L42: =+K42*F42 -> 889.0008 | M42: =+K42+I42 -> 69.75648 | N42: =+L42+J42 -> 889.0008 | O42: 45338 | R42: =+M42-P42 -> 69.75648 | S42: =+N42-Q42 -> 889.0008 | T42: =+R42 -> 69.75648 | U42: =+S42 -> 889.0008 | V42: Hùng Nguyên | W42: 45324 | X42: =+W42+'Dieu kien giao hang'!$C$21 -> 45328 | Y42: =+X42+'Dieu kien giao hang'!$C$22 -> 45330
... A52: A-45 | B52: THÉP HÌNH L | C52: L90X90X7-12000L | D52: SS400 | E52: m | F52: =+H52/G52 -> 9.5901077 | G52: 116.616 | H52: 1118.36 | K52: =1.06*G52 -> 123.61296 | L52: =+K52*F52 -> 1185.4616 | M52: =+K52+I52 -> 123.61296 | N52: =+L52+J52 -> 1185.4616 | O52: 45338 | R52: =+M52-P52 -> 123.61296 | S52: =+N52-Q52 -> 1185.4616 | T52: =+R52 -> 123.61296 | U52: =+S52 -> 1185.4616 | V52: Hùng Nguyên | W52: 45324 | X52: =+W52+'Dieu kien giao hang'!$C$21 -> 45328 | Y52: =+X52+'Dieu kien giao hang'!$C$22 -> 45330
A53: A-46 | B53: THÉP ỐNG | C53: CHS60.3X3.9 | D53: A-106 GR B | E53: m | F53: =+H53/G53 -> 5.1938959 | G53: 22.28 | H53: 115.72 | K53: =1.06*G53 -> 23.6168 | L53: =+K53*F53 -> 122.6632 | M53: =+K53+I53 -> 23.6168 | N53: =+L53+J53 -> 122.6632 | O53: 45371 | R53: =+M53-P53 -> 23.6168 | S53: =+N53-Q53 -> 122.6632 | AB53: =+R53 -> 23.6168 | AC53: =+S53 -> 122.6632 | AD53: GNEE | AE53: 45323 | AF53: =+AE53+'Dieu kien giao hang'!$C$6 -> 45328 | AG53: =AF53+'Dieu kien giao hang'!$C$7 -> 45348 | AH53: =AG53+'Dieu kien giao hang'!$C$8 -> 45353 | AI53: =AH53+'Dieu kien giao hang'!$C$10 -> 45356 | AJ53: =AI53+'Dieu kien giao hang'!$C$13 -> 45368
A54: A-47 | B54: THÉP ỐNG | C54: CHS60.3X3.9 | D54: A-312 TP304 | E54: m | F54: =+H54/G54 -> 5.3510638 | G54: 11.28 | H54: 60.36 | K54: =1.06*G54 -> 11.9568 | L54: =+K54*F54 -> 63.9816 | M54: =+K54+I54 -> 11.9568 | N54: =+L54+J54 -> 63.9816 | O54: 45371 | R54: =+M54-P54 -> 11.9568 | S54: =+N54-Q54 -> 63.9816 | AB54: =+R54 -> 11.9568 | AC54: =+S54 -> 63.9816 | AD54: GNEE | AE54: 45323 | AF54: =+AE54+'Dieu kien giao hang'!$C$6 -> 45328 | AG54: =AF54+'Dieu kien giao hang'!$C$7 -> 45348 | AH54: =AG54+'Dieu kien giao hang'!$C$8 -> 45353 | AI54: =AH54+'Dieu kien giao hang'!$C$10 -> 45356 | AJ54: =AI54+'Dieu kien giao hang'!$C$13 -> 45368
A55: A-48 | B55: THÉP ỐNG | C55: CHS60.3X5.5 | D55: A-312 TP304 | E55: m | F55: =+H55/G55 -> 7.3287671 | G55: 0.584 | H55: 4.28 | K55: =1.06*G55 -> 0.61904 | L55: =+K55*F55 -> 4.5368 | M55: =+K55+I55 -> 0.61904 | N55: =+L55+J55 -> 4.5368 | O55: 45371 | R55: =+M55-P55 -> 0.61904 | S55: =+N55-Q55 -> 4.5368 | AB55: =+R55 -> 0.61904 | AC55: =+S55 -> 4.5368 | AD55: GNEE | AE55: 45323 | AF55: =+AE55+'Dieu kien giao hang'!$C$6 -> 45328 | AG55: =AF55+'Dieu kien giao hang'!$C$7 -> 45348 | AH55: =AG55+'Dieu kien giao hang'!$C$8 -> 45353 | AI55: =AH55+'Dieu kien giao hang'!$C$10 -> 45356 | AJ55: =AI55+'Dieu kien giao hang'!$C$13 -> 45368
A56: A-49 | B56: THÉP ỐNG | C56: CHS88.9X5.5 | D56: A-106 GR B | E56: m | F56: =+H56/G56 -> 11.004367 | G56: 0.916 | H56: 10.08 | K56: =1.06*G56 -> 0.97096 | L56: =+K56*F56 -> 10.6848 | M56: =+K56+I56 -> 0.97096 | N56: =+L56+J56 -> 10.6848 | O56: 45371 | R56: =+M56-P56 -> 0.97096 | S56: =+N56-Q56 -> 10.6848 | AB56: =+R56 -> 0.97096 | AC56: =+S56 -> 10.6848 | AD56: GNEE | AE56: 45323 | AF56: =+AE56+'Dieu kien giao hang'!$C$6 -> 45328 | AG56: =AF56+'Dieu kien giao hang'!$C$7 -> 45348 | AH56: =AG56+'Dieu kien giao hang'!$C$8 -> 45353 | AI56: =AH56+'Dieu kien giao hang'!$C$10 -> 45356 | AJ56: =AI56+'Dieu kien giao hang'!$C$13 -> 45368
A57: A-50 | B57: THÉP ỐNG | C57: CHS88.9X7.6 | D57: A500-GRB | E57: m | F57: =+H57/G57 -> 14.849537 | G57: 13.824 | H57: 205.28 | K57: =1.06*G57 -> 14.65344 | L57: =+K57*F57 -> 217.5968 | M57: =+K57+I57 -> 14.65344 | N57: =+L57+J57 -> 217.5968 | O57: 45338 | R57: =+M57-P57 -> 14.65344 | S57: =+N57-Q57 -> 217.5968 | AB57: =+R57 -> 14.65344 | AC57: =+S57 -> 217.5968 | AD57: GNEE | AE57: 45323 | AF57: =+AE57+'Dieu kien giao hang'!$C$6 -> 45328 | AG57: =AF57+'Dieu kien giao hang'!$C$7 -> 45348 | AH57: =AG57+'Dieu kien giao hang'!$C$8 -> 45353 | AI57: =AH57+'Dieu kien giao hang'!$C$10 -> 45356 | AJ57: =AI57+'Dieu kien giao hang'!$C$13 -> 45368
A58: A-51 | B58: THÉP ỐNG | C58: CHS114.3X6.0 | D58: A-312 TP304 | E58: m | F58: =+H58/G58 -> 16.190476 | G58: 1.428 | H58: 23.12 | K58: =1.06*G58 -> 1.51368 | L58: =+K58*F58 -> 24.5072 | M58: =+K58+I58 -> 1.51368 | N58: =+L58+J58 -> 24.5072 | O58: 45371 | R58: =+M58-P58 -> 1.51368 | S58: =+N58-Q58 -> 24.5072 | AB58: =+R58 -> 1.51368 | AC58: =+S58 -> 24.5072 | AD58: GNEE | AE58: 45323 | AF58: =+AE58+'Dieu kien giao hang'!$C$6 -> 45328 | AG58: =AF58+'Dieu kien giao hang'!$C$7 -> 45348 | AH58: =AG58+'Dieu kien giao hang'!$C$8 -> 45353 | AI58: =AH58+'Dieu kien giao hang'!$C$10 -> 45356 | AJ58: =AI58+'Dieu kien giao hang'!$C$13 -> 45368
A59: A-52 | B59: THÉP ỐNG | C59: CHS168.3X7.1 | D59: A-106 GR B | E59: m | F59: =+H59/G59 -> 26.025105 | G59: 2.868 | H59: 74.64 | K59: =1.06*G59 -> 3.04008 | L59: =+K59*F59 -> 79.1184 | M59: =+K59+I59 -> 3.04008 | N59: =+L59+J59 -> 79.1184 | O59: 45371 | R59: =+M59-P59 -> 3.04008 | S59: =+N59-Q59 -> 79.1184 | AB59: =+R59 -> 3.04008 | AC59: =+S59 -> 79.1184 | AD59: GNEE | AE59: 45323 | AF59: =+AE59+'Dieu kien giao hang'!$C$6 -> 45328 | AG59: =AF59+'Dieu kien giao hang'!$C$7 -> 45348 | AH59: =AG59+'Dieu kien giao hang'!$C$8 -> 45353 | AI59: =AH59+'Dieu kien giao hang'!$C$10 -> 45356 | AJ59: =AI59+'Dieu kien giao hang'!$C$13 -> 45368
A60: A-53 | B60: THÉP ỐNG | C60: CHS168.3X7.1 | D60: A-312 TP304 | E60: m | F60: =+H60/G60 -> 26.226686 | G60: 2.788 | H60: 73.12 | K60: =1.06*G60 -> 2.95528 | L60: =+K60*F60 -> 77.5072 | M60: =+K60+I60 -> 2.95528 | N60: =+L60+J60 -> 77.5072 | O60: 45371 | R60: =+M60-P60 -> 2.95528 | S60: =+N60-Q60 -> 77.5072 | AB60: =+R60 -> 2.95528 | AC60: =+S60 -> 77.5072 | AD60: GNEE | AE60: 45323 | AF60: =+AE60+'Dieu kien giao hang'!$C$6 -> 45328 | AG60: =AF60+'Dieu kien giao hang'!$C$7 -> 45348 | AH60: =AG60+'Dieu kien giao hang'!$C$8 -> 45353 | AI60: =AH60+'Dieu kien giao hang'!$C$10 -> 45356 | AJ60: =AI60+'Dieu kien giao hang'!$C$13 -> 45368
A61: A-54 | B61: THÉP TRÒN | C61: RB1 | D61: SUS304 | E61: m | F61: =+H61/G61 -> 0.0043715847 | G61: 146.4 | H61: 0.64 | K61: =1.06*G61 -> 155.184 | L61: =+K61*F61 -> 0.6784 | M61: =+K61+I61 -> 155.184 | N61: =+L61+J61 -> 0.6784 | O61: 45371 | R61: =+M61-P61 -> 155.184 | S61: =+N61-Q61 -> 0.6784 | AB61: =+R61 -> 155.184 | AC61: =+S61 -> 0.6784 | AD61: GNEE | AE61: 45323 | AF61: =+AE61+'Dieu kien giao hang'!$C$6 -> 45328 | AG61: =AF61+'Dieu kien giao hang'!$C$7 -> 45348 | AH61: =AG61+'Dieu kien giao hang'!$C$8 -> 45353 | AI61: =AH61+'Dieu kien giao hang'!$C$10 -> 45356 | AJ61: =AI61+'Dieu kien giao hang'!$C$13 -> 45368
A62: A-55 | B62: THÉP TRÒN | C62: RB10 | D62: SS400 | E62: m | F62: =+H62/G62 -> 0.55147059 | G62: 9.792 | H62: 5.4 | K62: =1.06*G62 -> 10.37952 | L62: =+K62*F62 -> 5.724 | M62: =+K62+I62 -> 10.37952 | N62: =+L62+J62 -> 5.724 | O62: 45338 | R62: =+M62-P62 -> 10.37952 | S62: =+N62-Q62 -> 5.724 | T62: =+R62 -> 10.37952 | U62: =+S62 -> 5.724 | V62: Hùng Nguyên | W62: 45324 | X62: =+W62+'Dieu kien giao hang'!$C$21 -> 45328 | Y62: =+X62+'Dieu kien giao hang'!$C$22 -> 45330
A63: A-56 | B63: THÉP TRÒN | C63: RB12 | D63: SS400 | E63: m | F63: =+H63/G63 -> 0.78431373 | G63: 2.04 | H63: 1.6 | K63: =1.06*G63 -> 2.1624 | L63: =+K63*F63 -> 1.696 | M63: =+K63+I63 -> 2.1624 | N63: =+L63+J63 -> 1.696 | O63: 45338 | R63: =+M63-P63 -> 2.1624 | S63: =+N63-Q63 -> 1.696 | T63: =+R63 -> 2.1624 | U63: =+S63 -> 1.696 | V63: Hùng Nguyên | W63: 45324 | X63: =+W63+'Dieu kien giao hang'!$C$21 -> 45328 | Y63: =+X63+'Dieu kien giao hang'!$C$22 -> 45330
A64: A-57 | B64: THÉP TRÒN | C64: RB13 | D64: SS400 | E64: m | F64: =+H64/G64 -> 0.93785311 | G64: 10.62 | H64: 9.96 | K64: =1.06*G64 -> 11.2572 | L64: =+K64*F64 -> 10.5576 | M64: =+K64+I64 -> 11.2572 | N64: =+L64+J64 -> 10.5576 | O64: 45338 | R64: =+M64-P64 -> 11.2572 | S64: =+N64-Q64 -> 10.5576 | T64: =+R64 -> 11.2572 | U64: =+S64 -> 10.5576 | V64: Hùng Nguyên | W64: 45324 | X64: =+W64+'Dieu kien giao hang'!$C$21 -> 45328 | Y64: =+X64+'Dieu kien giao hang'!$C$22 -> 45330
A65: A-58 | B65: THÉP TRÒN | C65: RB16 | D65: SS400 | E65: m | F65: =+H65/G65 -> 1.4267677 | G65: 9.504 | H65: 13.56 | K65: =1.06*G65 -> 10.07424 | L65: =+K65*F65 -> 14.3736 | M65: =+K65+I65 -> 10.07424 | N65: =+L65+J65 -> 14.3736 | O65: 45338 | R65: =+M65-P65 -> 10.07424 | S65: =+N65-Q65 -> 14.3736 | T65: =+R65 -> 10.07424 | U65: =+S65 -> 14.3736 | V65: Hùng Nguyên | W65: 45324 | X65: =+W65+'Dieu kien giao hang'!$C$21 -> 45328 | Y65: =+X65+'Dieu kien giao hang'!$C$22 -> 45330
A66: A-59 | B66: THÉP TRÒN | C66: RB19 | D66: SS400 | E66: m | F66: =+H66/G66 -> 2 | G66: 4.28 | H66: 8.56 | K66: =1.06*G66 -> 4.5368 | L66: =+K66*F66 -> 9.0736 | M66: =+K66+I66 -> 4.5368 | N66: =+L66+J66 -> 9.0736 | O66: 45338 | R66: =+M66-P66 -> 4.5368 | S66: =+N66-Q66 -> 9.0736 | T66: =+R66 -> 4.5368 | U66: =+S66 -> 9.0736 | V66: Hùng Nguyên | W66: 45324 | X66: =+W66+'Dieu kien giao hang'!$C$21 -> 45328 | Y66: =+X66+'Dieu kien giao hang'!$C$22 -> 45330
A67: A-60 | B67: THÉP TRÒN | C67: RB38 | D67: SS400 | E67: m | F67: =+H67/G67 -> 8.3393178 | G67: 13.368 | H67: 111.48 | K67: =1.06*G67 -> 14.17008 | L67: =+K67*F67 -> 118.1688 | M67: =+K67+I67 -> 14.17008 | N67: =+L67+J67 -> 118.1688 | O67: 45338 | R67: =+M67-P67 -> 14.17008 | S67: =+N67-Q67 -> 118.1688 | T67: =+R67 -> 14.17008 | U67: =+S67 -> 118.1688 | V67: Hùng Nguyên | W67: 45324 | X67: =+W67+'Dieu kien giao hang'!$C$21 -> 45328 | Y67: =+X67+'Dieu kien giao hang'!$C$22 -> 45330
A68: A-61 | B68: LƯỚI DẬP GIÃN | C68: EXPANDED_METAL_3/4"_#16_FLATTENED | D68: SS400-MẠ KẼM | E68: m2 | F68: =+H68/G68 -> 2.29 | G68: 34.934498 | H68: 80 | K68: =1.12*G68 -> 39.126638 | L68: =+K68*F68 -> 89.6 | M68: =+K68+I68 -> 39.126638 | N68: =+L68+J68 -> 89.6 | O68: 45392 | R68: =+M68-P68 -> 39.126638 | S68: =+N68-Q68 -> 89.6 | T68: =+R68 -> 39.126638 | U68: =+S68 -> 89.6 | V68: XALACO | W68: 45329 | X68: =+W68+'Dieu kien giao hang'!$C$31 -> 45355 | Y68: =+X68+'Dieu kien giao hang'!$C$32 -> 45357
A69: A-62 | B69: PIN HÀN+WASHER | C69: PIN Ø2.6X40( 01 PIN+01 SELF-LOCKING INSULAFTION WASHER 2 1/2"X2 1/2" SQUARE ) | D69: SUS304H | E69: Sets | F69: =+H69/G69 -> 0.063037975 | G69: 632 | H69: 39.84 | K69: 700 | L69: =+K69*F69 -> 44.126582 | M69: =+K69+I69 -> 700 | N69: =+L69+J69 -> 44.126582 | O69: 45392 | R69: =+M69-P69 -> 700 | S69: =+N69-Q69 -> 44.126582 | T69: =+R69 -> 700 | U69: =+S69 -> 44.126582 | V69: XALACO | W69: 45329 | X69: =+W69+'Dieu kien giao hang'!$C$31 -> 45355 | Y69: =+X69+'Dieu kien giao hang'!$C$32 -> 45357
A70: A-63 | B70: BỊT ĐẦU ỐNG | C70: 2"_3000# THREADED PIPE CAP | D70: A105 | E70: CÁI | F70: =+H70/G70 -> 1.73 | G70: 24 | H70: 41.52 | K70: =+G70 -> 24 | L70: =+K70*F70 -> 41.52 | M70: =+K70+I70 -> 24 | N70: =+L70+J70 -> 41.52 | O70: 45392 | R70: =+M70-P70 -> 24 | S70: =+N70-Q70 -> 41.52 | T70: =+R70 -> 24 | U70: =+S70 -> 41.52 | V70: XALACO | W70: 45329 | X70: =+W70+'Dieu kien giao hang'!$C$31 -> 45355 | Y70: =+X70+'Dieu kien giao hang'!$C$32 -> 45357
A71: A-64 | B71: NỐI ỐNG | C71: 2"_3000#_THREADED_COUPLING | D71: A105 | E71: CÁI | F71: =+H71/G71 -> 1.106 | G71: 40 | H71: 44.24 | K71: =+G71 -> 40 | L71: =+K71*F71 -> 44.24 | M71: =+K71+I71 -> 40 | N71: =+L71+J71 -> 44.24 | O71: 45392 | R71: =+M71-P71 -> 40 | S71: =+N71-Q71 -> 44.24 | T71: =+R71 -> 40 | U71: =+S71 -> 44.24 | V71: XALACO | W71: 45329 | X71: =+W71+'Dieu kien giao hang'!$C$31 -> 45355 | Y71: =+X71+'Dieu kien giao hang'!$C$32 -> 45357
A72: A-65 | B72: BỊT ĐẦU ỐNG | C72: 3"_3000# THREADED PIPE CAP | D72: A105 | E72: CÁI | F72: =+H72/G72 -> 3.94 | G72: 4 | H72: 15.76 | K72: =+G72 -> 4 | L72: =+K72*F72 -> 15.76 | M72: =+K72+I72 -> 4 | N72: =+L72+J72 -> 15.76 | O72: 45392 | R72: =+M72-P72 -> 4 | S72: =+N72-Q72 -> 15.76 | T72: =+R72 -> 4 | U72: =+S72 -> 15.76 | V72: XALACO | W72: 45329 | X72: =+W72+'Dieu kien giao hang'!$C$31 -> 45355 | Y72: =+X72+'Dieu kien giao hang'!$C$32 -> 45357
A73: A-66 | B73: BÍCH MÙ | C73: 4"_BLIND_FLANGE_#150_RF | D73: A105 | E73: CÁI | F73: =+H73/G73 -> 7.42 | G73: 4 | H73: 29.68 | K73: =+G73 -> 4 | L73: =+K73*F73 -> 29.68 | M73: =+K73+I73 -> 4 | N73: =+L73+J73 -> 29.68 | O73: 45392 | R73: =+M73-P73 -> 4 | S73: =+N73-Q73 -> 29.68 | T73: =+R73 -> 4 | U73: =+S73 -> 29.68 | V73: XALACO | W73: 45329 | X73: =+W73+'Dieu kien giao hang'!$C$31 -> 45355 | Y73: =+X73+'Dieu kien giao hang'!$C$32 -> 45357
A74: A-67 | B74: BÍCH | C74: 4"_FLANGE_#150_SORF | D74: A105 | E74: CÁI | F74: =+H74/G74 -> 5.69 | G74: 4 | H74: 22.76 | K74: =+G74 -> 4 | L74: =+K74*F74 -> 22.76 | M74: =+K74+I74 -> 4 | N74: =+L74+J74 -> 22.76 | O74: 45392 | R74: =+M74-P74 -> 4 | S74: =+N74-Q74 -> 22.76 | T74: =+R74 -> 4 | U74: =+S74 -> 22.76 | V74: XALACO | W74: 45329 | X74: =+W74+'Dieu kien giao hang'!$C$31 -> 45355 | Y74: =+X74+'Dieu kien giao hang'!$C$32 -> 45357
A75: A-68 | B75: GIOĂNG | C75: 4"_GASKET_#150_SORF | D75: NON_METALLIC | E75: CÁI | F75: =+H75/G75 -> 0.04 | G75: 4 | H75: 0.16 | K75: =+G75 -> 4 | L75: =+K75*F75 -> 0.16 | M75: =+K75+I75 -> 4 | N75: =+L75+J75 -> 0.16 | O75: 45392 | R75: =+M75-P75 -> 4 | S75: =+N75-Q75 -> 0.16 | T75: =+R75 -> 4 | U75: =+S75 -> 0.16 | V75: XALACO | W75: 45329 | X75: =+W75+'Dieu kien giao hang'!$C$31 -> 45355 | Y75: =+X75+'Dieu kien giao hang'!$C$32 -> 45357
A76: A-69 | B76: BÍCH MÙ | C76: 6"_BLIND_FLANGE_#150_RF | D76: A105 | E76: CÁI | F76: =+H76/G76 -> 12.07 | G76: 12 | H76: 144.84 | K76: =+G76 -> 12 | L76: =+K76*F76 -> 144.84 | M76: =+K76+I76 -> 12 | N76: =+L76+J76 -> 144.84 | O76: 45392 | R76: =+M76-P76 -> 12 | S76: =+N76-Q76 -> 144.84 | T76: =+R76 -> 12 | U76: =+S76 -> 144.84 | V76: XALACO | W76: 45329 | X76: =+W76+'Dieu kien giao hang'!$C$31 -> 45355 | Y76: =+X76+'Dieu kien giao hang'!$C$32 -> 45357
A77: A-70 | B77: BÍCH | C77: 6"_FLANGE_#150_SORF | D77: A105 | E77: CÁI | F77: =+H77/G77 -> 8.1 | G77: 12 | H77: 97.2 | K77: =+G77 -> 12 | L77: =+K77*F77 -> 97.2 | M77: =+K77+I77 -> 12 | N77: =+L77+J77 -> 97.2 | O77: 45392 | R77: =+M77-P77 -> 12 | S77: =+N77-Q77 -> 97.2 | T77: =+R77 -> 12 | U77: =+S77 -> 97.2 | V77: XALACO | W77: 45329 | X77: =+W77+'Dieu kien giao hang'!$C$31 -> 45355 | Y77: =+X77+'Dieu kien giao hang'!$C$32 -> 45357
A78: A-71 | B78: GIOĂNG | C78: 6"_GASKET_#150_SORF | D78: NON_METALLIC | E78: CÁI | F78: =+H78/G78 -> 0.05 | G78: 12 | H78: 0.6 | K78: =+G78 -> 12 | L78: =+K78*F78 -> 0.6 | M78: =+K78+I78 -> 12 | N78: =+L78+J78 -> 0.6 | O78: 45392 | R78: =+M78-P78 -> 12 | S78: =+N78-Q78 -> 0.6 | T78: =+R78 -> 12 | U78: =+S78 -> 0.6 | V78: XALACO | W78: 45329 | X78: =+W78+'Dieu kien giao hang'!$C$31 -> 45355 | Y78: =+X78+'Dieu kien giao hang'!$C$32 -> 45357
A79: A-72 | B79: BỊT ĐẦU ỐNG | C79: SQUARE HEAD PLUG 2"3000# | D79: A105 | E79: CÁI | F79: =+H79/G79 -> 0.881 | G79: 40 | H79: 35.24 | K79: =+G79 -> 40 | L79: =+K79*F79 -> 35.24 | M79: =+K79+I79 -> 40 | N79: =+L79+J79 -> 35.24 | O79: 45392 | R79: =+M79-P79 -> 40 | S79: =+N79-Q79 -> 35.24 | T79: =+R79 -> 40 | U79: =+S79 -> 35.24 | V79: XALACO | W79: 45329 | X79: =+W79+'Dieu kien giao hang'!$C$31 -> 45355 | Y79: =+X79+'Dieu kien giao hang'!$C$32 -> 45357
A80: A-73 | B80: ĐINH BẢO ÔN | C80: STUD M10X44( 01 PIN-SUS304+02 NUT-SUS304+02 PLATE WASHER-SUH409) | D80: SUS304+SUH409 | E80: Sets | F80: =+H80/G80 -> 0.18145522 | G80: 1072 | H80: 194.52 | K80: 1110 | L80: =+K80*F80 -> 201.4153 | M80: =+K80+I80 -> 1110 | N80: =+L80+J80 -> 201.4153 | O80: 45392 | R80: =+M80-P80 -> 1110 | S80: =+N80-Q80 -> 201.4153 | T80: =+R80 -> 1110 | U80: =+S80 -> 201.4153 | V80: XALACO | W80: 45329 | X80: =+W80+'Dieu kien giao hang'!$C$31 -> 45355 | Y80: =+X80+'Dieu kien giao hang'!$C$32 -> 45357 | AM80: XEM BẢN VẼ
A81: A-74 | B81: ĐINH BẢO ÔN | C81: STUD M10X67( 01 PIN-SUS304+02 NUT-SUS304+02 PLATE WASHER-SUH409) | D81: SUS304+SUH409 | E81: Sets | F81: =+H81/G81 -> 0.158 | G81: 2840 | H81: 448.72 | K81: 2930 | L81: =+K81*F81 -> 462.94 | M81: =+K81+I81 -> 2930 | N81: =+L81+J81 -> 462.94 | O81: 45392 | R81: =+M81-P81 -> 2930 | S81: =+N81-Q81 -> 462.94 | T81: =+R81 -> 2930 | U81: =+S81 -> 462.94 | V81: XALACO | W81: 45329 | X81: =+W81+'Dieu kien giao hang'!$C$31 -> 45355 | Y81: =+X81+'Dieu kien giao hang'!$C$32 -> 45357 | AM81: XEM BẢN VẼ
A82: A-75 | B82: ĐINH BẢO ÔN | C82: STUD M10X133( 01 PIN-SUS304+02 NUT-SUS304+02 PLATE WASHER-SUH409) | D82: SUS304+SUH409 | E82: Sets | F82: =+H82/G82 -> 0.27311175 | G82: 4152 | H82: 1133.96 | K82: 4280 | L82: =+K82*F82 -> 1168.9183 | M82: =+K82+I82 -> 4280 | N82: =+L82+J82 -> 1168.9183 | O82: 45392 | R82: =+M82-P82 -> 4280 | S82: =+N82-Q82 -> 1168.9183 | T82: =+R82 -> 4280 | U82: =+S82 -> 1168.9183 | V82: XALACO | W82: 45329 | X82: =+W82+'Dieu kien giao hang'!$C$31 -> 45355 | Y82: =+X82+'Dieu kien giao hang'!$C$32 -> 45357 | AM82: XEM BẢN VẼ
A83: A-76 | B83: ĐINH BẢO ÔN | C83: STUD M10X152( 01 PIN-SUS304+02 NUT-SUS304+02 PLATE WASHER-SUH409) | D83: SUS304+SUH409 | E83: Sets | F83: =+H83/G83 -> 0.206 | G83: 20 | H83: 4.12 | K83: 25 | L83: =+K83*F83 -> 5.15 | M83: =+K83+I83 -> 25 | N83: =+L83+J83 -> 5.15 | O83: 45392 | R83: =+M83-P83 -> 25 | S83: =+N83-Q83 -> 5.15 | T83: =+R83 -> 25 | U83: =+S83 -> 5.15 | V83: XALACO | W83: 45329 | X83: =+W83+'Dieu kien giao hang'!$C$31 -> 45355 | Y83: =+X83+'Dieu kien giao hang'!$C$32 -> 45357 | AM83: XEM BẢN VẼ
A84: A-77 | B84: ĐINH BẢO ÔN | C84: STUD M12X137( 01 PIN-SUS304+02 NUT-SUS304+02 PLATE WASHER-SUH409) | D84: SUS304+SUH409 | E84: Sets | F84: 0.2075 | G84: =3800*4 -> 15200 | H84: =+G84*F84 -> 3154 | K84: 16000 | L84: =+K84*F84 -> 3320 | M84: =+K84+I84 -> 16000 | N84: =+L84+J84 -> 3320 | O84: 45392 | R84: =+M84-P84 -> 16000 | S84: =+N84-Q84 -> 3320 | T84: =+R84 -> 16000 | U84: =+S84 -> 3320 | V84: XALACO | W84: 45329 | X84: =+W84+'Dieu kien giao hang'!$C$31 -> 45355 | Y84: =+X84+'Dieu kien giao hang'!$C$32 -> 45357 | AM84: XEM BẢN VẼ
A85: A-78 | B85: BÔNG BẢO ÔN | C85: BÔNG BẢO ÔN DÀY 25mm | D85: SUPERWOOD PLUS (128kg/m3) | E85: m3 | F85: =+H85/G85 -> 128 | G85: 56 | H85: 7168 | K85: =+G85*1.25 -> 70 | L85: =+K85*F85 -> 8960 | M85: =+K85+I85 -> 70 | N85: =+L85+J85 -> 8960 | O85: 45392 | R85: =+M85-P85 -> 70 | S85: =+N85-Q85 -> 8960 | T85: =+R85 -> 70 | U85: =+S85 -> 8960 | V85: XALACO | W85: 45329 | X85: =+W85+'Dieu kien giao hang'!$C$31 -> 45355 | Y85: =+X85+'Dieu kien giao hang'!$C$32 -> 45357
A86: A-79 | B86: BÔNG BẢO ÔN | C86: BÔNG BẢO ÔN DÀY 50mm | D86: SUPERWOOD PLUS (128kg/m3) | E86: m3 | F86: =+H86/G86 -> 128 | G86: 216 | H86: 27648 | K86: =+G86*1.25 -> 270 | L86: =+K86*F86 -> 34560 | M86: =+K86+I86 -> 270 | N86: =+L86+J86 -> 34560 | O86: 45392 | R86: =+M86-P86 -> 270 | S86: =+N86-Q86 -> 34560 | T86: =+R86 -> 270 | U86: =+S86 -> 34560 | V86: XALACO | W86: 45329 | X86: =+W86+'Dieu kien giao hang'!$C$31 -> 45355 | Y86: =+X86+'Dieu kien giao hang'!$C$32 -> 45357
A87: B. | B87: Accessory-Material / Vật tư phụ-Mạ kẽm nhúng nóng | H87: =+SUM(H88:H101) -> 46.52 | L87: =+SUM(L88:L101) -> 0 | N87: =+SUM(N88:N101) -> 0 | R87: =+M87-P87 -> 0 | S87: =+N87-Q87 -> 0
A88: B-1 | B88: Bu lông (1B+1N)-MẠ KẼM | C88: BOLT 1/2" DIA x 1 1/2" (40mm) LG | D88: A307 | E88: Sets | G88: 54 | I88: 60 | M88: =+K88+I88 -> 60 | O88: 45328 | R88: =+M88-P88 -> 60 | S88: =+N88-Q88 -> 0 | T88: =+R88 -> 60 | U88: =+S88 -> 0 | V88: XALACO | W88: 45329 | X88: =+W88+'Dieu kien giao hang'!$C$31 -> 45355 | Y88: =+X88+'Dieu kien giao hang'!$C$32 -> 45357 | AM88: BOLT M12X40-ISO4017-Gr8.8(1B+1N)-MẠ KẼM
A89: B-2 | B89: CHỐT | C89: CLEVIS PIN Ø12x52-DIN 1444-MẠ ĐIỆN PHÂN | D89: SS400-MẠ KẼM | E89: cái | G89: 96 | H89: 5.4 | K89: 100 | M89: =+K89+I89 -> 100 | O89: 45392 | R89: =+M89-P89 -> 100 | S89: =+N89-Q89 -> 0 | T89: =+R89 -> 100 | U89: =+S89 -> 0 | V89: XALACO | W89: 45329 | X89: =+W89+'Dieu kien giao hang'!$C$31 -> 45355 | Y89: =+X89+'Dieu kien giao hang'!$C$32 -> 45357
A90: B-3 | B90: GIỮ CHỐT | C90: COTTER PIN Ø3.2x25L-DIN 94- MẠ ĐIỆN PHÂN | D90: SS400-MẠ KẼM | E90: cái | G90: 96 | H90: 0.48 | K90: 100 | M90: =+K90+I90 -> 100 | O90: 45392 | R90: =+M90-P90 -> 100 | S90: =+N90-Q90 -> 0 | T90: =+R90 -> 100 | U90: =+S90 -> 0 | V90: XALACO | W90: 45329 | X90: =+W90+'Dieu kien giao hang'!$C$31 -> 45355 | Y90: =+X90+'Dieu kien giao hang'!$C$32 -> 45357
A91: B-4 | B91: EYE BOLT | C91: EYE BOLT D13 | D91: SS400-MẠ KẼM | E91: cái | G91: 12 | H91: 3 | K91: 18 | M91: =+K91+I91 -> 18 | O91: 45392 | R91: =+M91-P91 -> 18 | S91: =+N91-Q91 -> 0 | T91: =+R91 -> 18 | U91: =+S91 -> 0 | V91: XALACO | W91: 45329 | X91: =+W91+'Dieu kien giao hang'!$C$31 -> 45355 | Y91: =+X91+'Dieu kien giao hang'!$C$32 -> 45357
A92: B-5 | B92: VÒNG ĐỆM | C92: FLAT WASHER,ZINC PLATE,1/2"DIA | D92: SS400-MẠ KẼM | E92: cái | G92: 96 | H92: 0.6 | K92: 100 | M92: =+K92+I92 -> 100 | O92: 45392 | R92: =+M92-P92 -> 100 | S92: =+N92-Q92 -> 0 | T92: =+R92 -> 100 | U92: =+S92 -> 0 | V92: XALACO | W92: 45329 | X92: =+W92+'Dieu kien giao hang'!$C$31 -> 45355 | Y92: =+X92+'Dieu kien giao hang'!$C$32 -> 45357
A93: B-6 | B93: VÒNG ĐỆM | C93: FLAT WASHER,ZINC PLATE,5/8"DIA | D93: SS400-MẠ KẼM | E93: cái | G93: 96 | H93: 0.84 | K93: 100 | M93: =+K93+I93 -> 100 | O93: 45392 | R93: =+M93-P93 -> 100 | S93: =+N93-Q93 -> 0 | T93: =+R93 -> 100 | U93: =+S93 -> 0 | V93: XALACO | W93: 45329 | X93: =+W93+'Dieu kien giao hang'!$C$31 -> 45355 | Y93: =+X93+'Dieu kien giao hang'!$C$32 -> 45357
A94: B-7 | B94: ECU | C94: NUT_M16 | D94: 5.6-MẠ KẼM | E94: cái | G94: 96 | H94: 4.92 | K94: 100 | M94: =+K94+I94 -> 100 | O94: 45392 | R94: =+M94-P94 -> 100 | S94: =+N94-Q94 -> 0 | T94: =+R94 -> 100 | U94: =+S94 -> 0 | V94: XALACO | W94: 45329 | X94: =+W94+'Dieu kien giao hang'!$C$31 -> 45355 | Y94: =+X94+'Dieu kien giao hang'!$C$32 -> 45357
A95: B-8 | B95: GOĂNG | C95: GASKET TADPOLE MCMASTER-CARR PART 8815K33-3/4"x11/2" | D95: FIBER GLASS | E95: m | G95: 20.8 | H95: 2.08 | K95: 30 | M95: =+K95+I95 -> 30 | O95: 45392 | R95: =+M95-P95 -> 30 | S95: =+N95-Q95 -> 0 | T95: =+R95 -> 30 | U95: =+S95 -> 0 | V95: XALACO | W95: 45329 | X95: =+W95+'Dieu kien giao hang'!$C$31 -> 45355 | Y95: =+X95+'Dieu kien giao hang'!$C$32 -> 45357
A96: B-9 | B96: GOĂNG | C96: GASKET TADPOLE MCMASTER-CARR PART 8853K26-3/4"x11/2" | D96: FIBER GLASS | E96: m | G96: 19.9 | H96: 3.92 | K96: 30 | M96: =+K96+I96 -> 30 | O96: 45392 | R96: =+M96-P96 -> 30 | S96: =+N96-Q96 -> 0 | T96: =+R96 -> 30 | U96: =+S96 -> 0 | V96: XALACO | W96: 45329 | X96: =+W96+'Dieu kien giao hang'!$C$31 -> 45355 | Y96: =+X96+'Dieu kien giao hang'!$C$32 -> 45357
A97: B-10 | B97: KEO DÁN GIOĂNG | C97: HIGH TEMPERATURE ADHESIVE | D97: SILICA W/ INCONEL | E97: lits | G97: 2 | H97: 8.2 | K97: 2 | M97: =+K97+I97 -> 2 | O97: 45392 | R97: =+M97-P97 -> 2 | S97: =+N97-Q97 -> 0 | T97: =+R97 -> 2 | U97: =+S97 -> 0 | V97: XALACO | W97: 45329 | X97: =+W97+'Dieu kien giao hang'!$C$31 -> 45355 | Y97: =+X97+'Dieu kien giao hang'!$C$32 -> 45357
A98: B-11 | B98: GIOĂNG | C98: mcmaster-carr part no. 24175K46. STYLE 10 | D98: EPDM RUBBER | E98: m | G98: 29.232 | H98: 2.88 | K98: 40 | M98: =+K98+I98 -> 40 | O98: 45392 | R98: =+M98-P98 -> 40 | S98: =+N98-Q98 -> 0 | T98: =+R98 -> 40 | U98: =+S98 -> 0 | V98: XALACO | W98: 45329 | X98: =+W98+'Dieu kien giao hang'!$C$31 -> 45355 | Y98: =+X98+'Dieu kien giao hang'!$C$32 -> 45357
A99: B-12 | B99: VÍT | C99: SCREW M5x15L | D99: SCREWS,LOW PROFILE , SELF | E99: cái | G99: 288 | H99: 8.76 | K99: 300 | M99: =+K99+I99 -> 300 | O99: 45392 | R99: =+M99-P99 -> 300 | S99: =+N99-Q99 -> 0 | T99: =+R99 -> 300 | U99: =+S99 -> 0 | V99: XALACO | W99: 45329 | X99: =+W99+'Dieu kien giao hang'!$C$31 -> 45355 | Y99: =+X99+'Dieu kien giao hang'!$C$32 -> 45357
A100: B-13 | B100: VÍT | C100: SCREW M5x25L | D100: SCREWS,LOW PROFILE , SELF | E100: cái | G100: 152 | H100: 4.6 | K100: 180 | M100: =+K100+I100 -> 180 | O100: 45392 | R100: =+M100-P100 -> 180 | S100: =+N100-Q100 -> 0 | T100: =+R100 -> 180 | U100: =+S100 -> 0 | V100: XALACO | W100: 45329 | X100: =+W100+'Dieu kien giao hang'!$C$31 -> 45355 | Y100: =+X100+'Dieu kien giao hang'!$C$32 -> 45357
A101: B-14 | B101: GIOĂNG | C101: GASKET PL3 | D101: FIBER GLASS | E101: cái | G101: 4 | H101: 0.84 | K101: 4 | M101: =+K101+I101 -> 4 | O101: 45392 | R101: =+M101-P101 -> 4 | S101: =+N101-Q101 -> 0 | T101: =+R101 -> 4 | U101: =+S101 -> 0 | V101: XALACO | W101: 45329 | X101: =+W101+'Dieu kien giao hang'!$C$31 -> 45355 | Y101: =+X101+'Dieu kien giao hang'!$C$32 -> 45357 | AM101: XEM BẢN VẼ
