Workbook
Name \0: #REF!
Name \a: #N/A
Name \a: #N/A
Name \a: #N/A
Name \a: #REF!
Name \b: #N/A
Name \c: #N/A
Name \d: #N/A
Name \e: #N/A
Name \f: #N/A
Name \g: #N/A
Name \h: #N/A
Name \h: #N/A
Name \h: #N/A
Name \h: #REF!
Name \i: #N/A
Name \i: #N/A
Name \i: #N/A
Name \i: #REF!
Name \j: #N/A
Name \k: #N/A
Name \KWS123: #N/A
Name \m: #N/A
Name \m: #N/A
Name \m: #N/A
Name \m: #REF!
Name \n: #N/A
Name \p: #REF!
Name \s: #N/A
Name \s: #N/A
Name \s: #N/A
Name \s: #REF!
Name \t: #N/A
Name \v: #REF!
Name \w: #REF!
Name \z: #REF!
Name ______________SC2: #REF!
Name _____________MAC12: #REF!
Name _____________SC2: #REF!
Name ____________HE08: #REF!
Name ____________NO1: #REF!
Name ___________ddn600: #REF!
Name ___________HE1: #REF!
Name ___________sc1: #REF!
Name ___________SN3: #REF!
Name ___________TX1: #REF!
Name ___________VL100: #REF!
Name ___________VL200: #REF!
Name ___________VL250: #REF!
Name __________HE11: #REF!
Name __________nin190: #REF!
Name _________ddn600: #REF!
Name _________HE2: #REF!
Name _________ro1: #REF!
Name _________SN3: #REF!
Name _________TL1: #REF!
Name _________TX1: #REF!
Name _________VL100: #REF!
Name _________VL200: #REF!
Name _________VL250: #REF!

Sheet Vật tư keo 078 sửa chữa
A1: BID ANALYSIS - GIẢI TRÌNH MUA SẮM/ĐẤU THẦU
A3: Project | B3: PROJECT No/ Dự án: 24-VPI-I-078
A4: Dự án
A5: Subject | B5: Cung cấp vật tư keo dính chống cháy chịu nhiệt
A6: Chủ đề
A8: No. | B8: CONTENT | E8: Dự toán | H8: Đã mua | I8: Đơn vị cung cấp chào giá (vnđ) | L8: Lựa chọn | M8: Ghi chú
A9: Item | B9: Description/ Chi tiết | C9: ĐVT | D9: Số lượng | E9: Khối lượng/ Số lượng | F9: Đơn giá (vnd) | G9: Thành tiền (vnd) | H9: Thành tiền (vnd) | I9: VSAN
I10: Phạm vi | J10: Đơn giá (VND) | K10: Thành Tiền (Không có 8% VAT)
A11: Tổng | E11: N/A | F11: N/A | G11: N/A | H11: N/A | K11: =SUM(K12:K12) -> 17880000 | M11: =-K11 -> -17880000
A12: I78-A-173 | B12: HIGH TEMPERATURE ADHESIVE -20 ĐỘ C ĐẾN 1250 ĐỘ C | C12: Cái | D12: 6 | E12: N/A | F12: N/A | I12: V | J12: 2980000 | K12: =J12*D12 -> 17880000 | L12: VSAN | M12: -Vật tư theo yêu cầu của sản xuất/ không có trong dự toán
B13: Xếp hạng | J13: 1
A14: Ghi chú: PTM tiến hàng mua sắm để đảm bảo tiến độ
A15: NGƯỜI ĐỀ NGHỊ/ RECOMMENDATION BY: | C15: NGƯỜI KIỂM TRA/ DEPARTMENT HEAD CHECK BY: | G15: APPROVED BY: PHÊ DUYỆT
F16: Nguyễn Quang Vinh | I16: Hoàng Ngọc Bằng | L16: Đoàn Văn Toàn

Sheet Vật tư bolt vsan 3-3
A1: BID ANALYSIS - GIẢI TRÌNH MUA SẮM/ĐẤU THẦU
A3: Project | B3: PROJECT No/ Dự án: 24-VPI-I-078
A4: Dự án
A5: Subject | B5: Cung cấp vật tư Nut của VSAN 27-2
A6: Chủ đề
A8: No. | B8: CONTENT | E8: Dự toán | H8: Đã mua | I8: Đơn vị cung cấp chào giá (vnđ) | L8: Lựa chọn | M8: Ghi chú
A9: Item | B9: Description/ Chi tiết | C9: ĐVT | D9: Số lượng | E9: Khối lượng/ Số lượng | F9: Đơn giá (vnd) | G9: Thành tiền (vnd) | H9: Thành tiền (vnd) | I9: VSAN
I10: Phạm vi | J10: Đơn giá (VND/PSC) | K10: Thành Tiền (Không có 8% VAT)
A11: Tổng | E11: N/A | F11: N/A | G11: N/A | H11: N/A | K11: =SUM(K12:K12) -> 1071900 | M11: =-K11 -> -1071900
A12: I78-B-65 | B12: HEAVY HEX NUT 7/8"-9UNC-A194-2H | C12: Cái | D12: 54 | E12: N/A | F12: N/A | I12: V | J12: 19850 | K12: =J12*D12 -> 1071900 | L12: VSAN
A13: II | B13: Khối lượng dự kiến giao (Kg )/ Estimated weight (Kg):
A14: 1 | B14: …
A15: 2 | B15: …
A16: III | B16: Tiến độ/ Schedule
A17: 1 | B17: ….
A19: IV | B19: Nhân lực/ ManPower
A20: 1 | B20: Thợ Pha cắt / Thợ sắt / Thợ hàn / …
B21: ….
A22: V | B22: Yêu cầu kỹ thuật: Tham chiếu các tài liệu đính kèm/ Technical requirement – refer to document attached
B23: Xếp hạng | J23: 1
A24: Ghi chú: PTM tiến hàng mua sắm để đảm bảo tiến độ
A25: NGƯỜI ĐỀ NGHỊ/ RECOMMENDATION BY: | C25: NGƯỜI KIỂM TRA/ DEPARTMENT HEAD CHECK BY: | G25: APPROVED BY: PHÊ DUYỆT
F26: Nguyễn Quang Vinh | I26: Hoàng Ngọc Bằng | L26: Đoàn Văn Toàn

Sheet Vật tư gioang xalaco
A1: BID ANALYSIS - GIẢI TRÌNH MUA SẮM/ĐẤU THẦU
A3: Project | B3: PROJECT No/ Dự án: 24-VPI-I-078
A4: Dự án
A5: Subject | B5: Cung cấp vật tư MC Master cart
A6: Chủ đề
A8: No. | B8: CONTENT | E8: Dự toán | H8: Đã mua | I8: Đơn vị cung cấp chào giá (vnđ) | L8: Lựa chọn | M8: Ghi chú
A9: Item | B9: Description/ Chi tiết | C9: ĐVT | D9: Số lượng | E9: Khối lượng/ Số lượng | F9: Đơn giá (vnd) | G9: Thành tiền (vnd) | H9: Thành tiền (vnd) | I9: XALACO
I10: Phạm vi | J10: Đơn giá (VND) | K10: Thành Tiền (Không có 8% VAT)
A11: Tổng | E11: N/A | F11: N/A | G11: N/A | H11: N/A | K11: =SUM(K12:K12) -> 267827643 | M11: =-K11 -> -267827643
A12: 1 | B12: 1-1/2" overal witdh, 3/4" bubble width,25ft-8853-K26 (MC MasterCarr) | C12: Cuộn | D12: 9 | E12: N/A | F12: N/A | I12: V | J12: 29758627 | K12: =J12*D12 -> 267827643 | L12: XALACO | M12: Hàng mua theo yêu cầu của sản xuất
A13: II | B13: Khối lượng dự kiến giao (Kg )/ Estimated weight (Kg):
A14: 1 | B14: …
A15: 2 | B15: …
A16: III | B16: Tiến độ/ Schedule
A17: 1 | B17: ….
A19: IV | B19: Nhân lực/ ManPower
A20: 1 | B20: Thợ Pha cắt / Thợ sắt / Thợ hàn / …
B21: ….
A22: V | B22: Yêu cầu kỹ thuật: Tham chiếu các tài liệu đính kèm/ Technical requirement – refer to document attached
B23: Xếp hạng | J23: 1
A24: Ghi chú: PTM tiến hàng mua sắm để đảm bảo tiến độ
A25: NGƯỜI ĐỀ NGHỊ/ RECOMMENDATION BY: | C25: NGƯỜI KIỂM TRA/ DEPARTMENT HEAD CHECK BY: | G25: APPROVED BY: PHÊ DUYỆT
F26: Nguyễn Quang Vinh | I26: Hoàng Ngọc Bằng | L26: Đoàn Văn Toàn

Sheet 078
J1: THEO DÕI VẬT TƯ DỰ ÁN/ MATERIAL CONTROL LOG | O1: Hướng dẫn cập nhật thông tin: | S1: Thời gian nộp bảng cập nhật:
J2: Tên dự án/ Project no.: 24-VPI-I-078 | O2: - Chữ tô màu xanh: | Q2: Chưa cập nhật | S2: - Trong ngày khi có biến động. | CX2: H.Đồng Chuyến giao hàng số 1 | CZ2: H.Đồng Chuyến giao hàng số 2 | DB2: H.Đồng Chuyến giao hàng số 2 | DD2: H.Đồng Chuyến giao hàng số 2 | DF2: H.Đồng Chuyến giao hàng số 2 | DH2: H.Đồng Chuyến giao hàng số 2 | DJ2: H.Đồng Chuyến giao hàng số 2 | DL2: H.Đồng Chuyến giao hàng số 2 | DN2: H.Đồng Chuyến giao hàng số 2 | DP2: H.Đồng Chuyến giao hàng số 2 | DR2: H.Đồng Chuyến giao hàng số 2 | DT2: H.Đồng Chuyến giao hàng số 2 | DV2: H.Đồng Chuyến giao hàng số 3 | DX2: H.Đồng Chuyến giao hàng số 4 | DZ2: H.Đồng Chuyến giao hàng số 5
J3: Cập nhật ngày/ Update to: | L3: =TODAY() -> 46086 | O3: - Chữ tô màu đỏ: | Q3: Đã cập nhật mới | S3: - Báo cáo hàng tuần vào 16:30 mỗi chiều thứ 2. | AR3: =SUBTOTAL(9,AR8:AR332) -> 0 | AS3: =SUBTOTAL(9,AS8:AS332) -> 0 | AV3: =SUBTOTAL(9,AV8:AV332) -> 0 | AW3: =SUBTOTAL(9,AW8:AW332) -> 0
B4: Đánh giá (Thiếu/ Đủ/ Thừa) | J4: Item/ STT | K4: Description/ Chi tiết | L4: Profile/ Vật tư | M4: Grade/ Mác vật liệu | N4: Unit/ Đơn vị | O4: U.Weight/ Đ.Trọng (Kg/m2,m,pcs) | P4: Net Quantity/Số lượng tinh | R4: Current Ordered/Dự trù lần 0 (Ngày 06/1/2025) | T4: Current Ordered/Dự trù lần 1 (Ngày 14/2/2025) | V4: Current Ordered/Dự trù lần 2 (Ngày 08/4/2025) | X4: Current Ordered/Dự trù lần 3 (Ngày 10/4/2025) | Z4: Current Ordered/Dự trù lần 4 (Ngày 21/4/2025) | AB4: Current Ordered/Dự trù lần 5 (Ngày 23/5/2025) | AD4: Current Ordered/Dự trù lần 6 (Ngày 21/6/2025) | AF4: Current Ordered/Dự trù lần 7 (Ngày 3/7/2025) | AH4: Current Ordered/Dự trù lần 8 (Ngày 1/8/2025) | AJ4: Current Ordered/Dự trù lần 9 (Ngày 13/8/2025) | AL4: Current Ordered/Dự trù lần 10 (Ngày 25/10/2025) | AN4: Current Ordered/Dự trù lần 11 (Ngày 04/12/2025) | AP4: Current Ordered/Dự trù lần 12 (Ngày 05/1/2026) | AR4: Total Ordered/Tổng dự trù | AT4: Remarks/ Ghi chú | AU4: Tận dụng tồn kho/ Remain | AZ4: Khối lượng phải mua sắm/ total order | BB4: Ngày bàn giao vật tư/ Material avaiable for hand over date | BC4: VẬT TƯ TRONG NƯỚC | BN4: ĐÃ MUA TRONG NƯỚC | BP4: QC Nghiệm thu | BT4: Mua sắm nước ngoài/ Oversea purchase | CL4: ĐÃ MUA NHẬP KHẨU | CN4: Nghiệm thu | CR4: TỔNG ĐÃ MUA TRONG VÀ NGOÀI NƯỚC | CT4: So sánh với số lượng vật tư PR | CW4: Remarks/ Ghi chú | CX4: STACK TEMPLATE(ID1) | CZ4: BASE PLATE(ID2) | DB4: ER+FIELD CONECTTION(ID3) | DD4: BURNER DUCT(ID4) | DF4: DISTRIBUTION GRID(ID4) | DH4: INLET DUCT(ID4) | DJ4: SPOOL DUCT 2 & 3(ID4) | DL4: SPOOL DUCT 3 & 4(ID4) | DN4: SPOOL DUCT 4 & 5(ID4) | DP4: OUTLET DUCT(ID4) | DR4: OUTLET STACK(ID4) | DT4: PLATFORM(ID4) | DV4: PIPE SUPORT(ID5) | DX4: DRAIN PIPE(ID6) | DZ4: Small Bore Field Fabricated Bulk(ID7)
P5: Q.Ty/ S.Lượng | Q5: Weight/ K.Lượng (Kg) | R5: Q.Ty/ S.Lượng | S5: Weight/ K.Lượng (Kg) | T5: Q.Ty/ S.Lượng | U5: Weight/ K.Lượng (Kg) | V5: Q.Ty/ S.Lượng | W5: Weight/ K.Lượng (Kg) | X5: Q.Ty/ S.Lượng | Y5: Weight/ K.Lượng (Kg) | Z5: Q.Ty/ S.Lượng | AA5: Weight/ K.Lượng (Kg) | AB5: Q.Ty/ S.Lượng | AC5: Weight/ K.Lượng (Kg) | AD5: Q.Ty/ S.Lượng | AE5: Weight/ K.Lượng (Kg) | AF5: Q.Ty/ S.Lượng | AG5: Weight/ K.Lượng (Kg) | AH5: Q.Ty/ S.Lượng | AI5: Weight/ K.Lượng (Kg) | AJ5: Q.Ty/ S.Lượng | AK5: Weight/ K.Lượng (Kg) | AL5: Q.Ty/ S.Lượng | AM5: Weight/ K.Lượng (Kg) | AN5: Q.Ty/ S.Lượng | AO5: Weight/ K.Lượng (Kg) | AP5: Q.Ty/ S.Lượng | AQ5: Weight/ K.Lượng (Kg) | AR5: Q.Ty/ S.Lượng | AS5: Weight/ K.Lượng (Kg) | AU5: Report No. | AV5: Q.Ty/ S.Lượng | AW5: Weight/ K.Lượng (Kg) | AX5: Ngày nghiệm thu ACC | AY5: Remarks/ Ghi chú | AZ5: Q.Ty/ S.Lượng | BA5: Weight/ K.Lượng (Kg) | BC5: Số Hợp đồng / Contract No | BD5: Nhà cung cấp/ Vendor | BE5: Profile/ Vật tư | BF5: Grade/ Mác vật liệu | BG5: Contract weight ( K.Lượng theo HĐ) | BH5: Ngày ký HD/ Contract date | BI5: S.Lượng giao hàng thực tế/ Handover Q'ty | BJ5: K.Lượng giao hàng thực tế// Handover weight | BK5: Đơn giá / Unit Price (Not VAT) | BL5: Tổng tiền / Total Price (Not VAT) | BM5: Bàn giao sản xuất/ Handover to Product | BN5: Q.Ty/ S.Lượng | BO5: Weight/ K.Lượng (Kg) | BP5: Report No. | BQ5: Inspection date | BR5: Khối lượng nghiệm thu đạt/ Weight Acc. Inspection | BS5: Results | BT5: Số Hợp đồng / Contract No | BU5: Nhà cung cấp/ Vendor | BV5: Profile/ Vật tư | BW5: Grade/ Mác vật liệu | BX5: Weight/ Khối lượng (Kg) | BY5: Ngày ký HD/ Contract date | BZ5: Số lượng giao hàng thực tế/ Handover Q'ty | CA5: Khối lượng giao hàng thực tế/ Handover Q'ty | CB5: Đơn giá / Unit Price | CC5: Thành tiền Hợp đồng/ total | CD5: Ngày mở L/C/ LC issued date | CE5: Hàng đi từ cảng nước ngoài/ Export Port | CF5: Hàng Đến cảng HP (CIF)/ HaiPhong CIF | CG5: Ngày thanh toán / Payment date | CH5: Thủ tục hải quan, vận chuyển/ Paper work, local transportaion date | CI5: Ngày hàng về / Arived | CJ5: Ngày mời nghiệm thu / invice QC date | CK5: Bàn giao sản xuất/ Handover to Product | CL5: Q.Ty/ S.Lượng | CM5: Weight/ K.Lượng (Kg) | CN5: Report No. | CO5: Inspection date | CP5: Khối lượng nghiệm thu đạt/ Weight Acc. Inspection | CQ5: Results | CR5: Q.Ty/ S.Lượng | CS5: Weight/ K.Lượng (Kg) | CT5: Q.Ty/ S.Lượng | CU5: Weight/ K.Lượng (Kg) | CV5: Đánh giá (Thiếu/ Đủ/ Thừa) | CX5: Q'TY | CY5: WEIGHT | CZ5: Q'TY | DA5: WEIGHT | DB5: Q'TY | DC5: WEIGHT | DD5: Q'TY | DE5: WEIGHT | DF5: Q'TY | DG5: WEIGHT | DH5: Q'TY | DI5: WEIGHT | DJ5: Q'TY | DK5: WEIGHT | DL5: Q'TY | DM5: WEIGHT | DN5: Q'TY | DO5: WEIGHT | DP5: Q'TY | DQ5: WEIGHT | DR5: Q'TY | DS5: WEIGHT | DT5: Q'TY | DU5: WEIGHT | DV5: Q'TY | DW5: WEIGHT | DX5: Q'TY | DY5: WEIGHT | DZ5: Q'TY | EA5: WEIGHT
C6: Số lượng cần (M/M2) | E6: Đơn vị cung cấp | F6: Tiền cần cho phần hàng chưa nhận được hoặc chưa đặt hàng | G6: Xin chuyển đổi | H6: Note | I6: Kế hoạch/ ghi chú | J6: 1 | K6: 2 | L6: 3 | M6: 4 | N6: 5 | O6: 6 | P6: 7 | Q6: 8 | R6: 9 | S6: 10 | T6: 11 | U6: 12 | V6: 13 | W6: 14 | X6: 15 | Y6: 16 | AR6: 17 | AS6: 18 | AT6: 19 | AU6: 16 | AV6: 17 | AW6: 18 | AX6: 19 | AY6: 20 | AZ6: 21 | BA6: 22 | BB6: 23 | BC6: 24 | BD6: 25 | BE6: 26 | BF6: 27 | BG6: 28 | BH6: 29 | BI6: 30 | BJ6: 31 | BK6: 32 | BL6: 33 | BM6: 34 | BN6: 35 | BO6: 36 | BP6: 37 | BQ6: 38 | BR6: 39 | BS6: 40 | BT6: 41 | BU6: 42 | BV6: 43 | BW6: 44 | BX6: 45 | BY6: 46 | BZ6: 47 | CA6: 48 | CB6: 49 | CC6: 50 | CD6: 51 | CE6: 52 | CF6: 53 | CG6: 54 | CH6: 55 | CI6: 56 | CJ6: 57 | CK6: 58 | CL6: 59 | CM6: 60 | CN6: 61 | CO6: 62 | CP6: 63 | CQ6: 64 | CR6: 65 | CS6: 66 | CT6: 67 | CU6: 68 | CV6: 69 | CW6: 70
J7: A. | K7: Main-Material / Vật tư chính | AR7: =SUM(AR8:AR242) -> 42283.706 | AS7: =SUM(AS8:AS242) -> 688314.75 | AT7: =SUM(AT8:AT242) -> 0 | AU7: =SUM(AU8:AU242) -> 0 | AV7: =SUM(AV8:AV242) -> 819.85066 | AW7: =SUM(AW8:AW242) -> 34363.468 | AX7: =SUM(AX8:AX242) -> 0 | AY7: =SUM(AY8:AY242) -> 0 | ... CW7: =SUM(CW8:CW242) -> 0 | CY7: =+SUM(CY8:CY239) -> 946.00664 | DA7: =+SUM(DA8:DA239) -> 16062.753 | DC7: =+SUM(DC8:DC239) -> 9590.2057 | DE7: =+SUM(DE8:DE239) -> 107945 | DG7: =+SUM(DG8:DG239) -> 3996.3354 | DI7: =+SUM(DI8:DI239) -> 138107.64 | DK7: =+SUM(DK8:DK239) -> 17348.14 | DM7: =+SUM(DM8:DM239) -> 14757.32 | DO7: =+SUM(DO8:DO239) -> 14414.74 | DQ7: =+SUM(DQ8:DQ239) -> 13539.32 | DS7: =+SUM(DS8:DS239) -> 85632.2 | DU7: =+SUM(DU8:DU239) -> 200103.2 | DW7: =+SUM(DW8:DW239) -> 6938.85 | DY7: =+SUM(DY8:DY239) -> 1251.24 | EA7: =+SUM(EA8:EA239) -> 6926.6903
A8: =IF(J8=J7,"ok","Hiện") -> Hiện | B8: =CV8 -> Đủ | C8: =CT8 -> 0 | H8: Vật tư phụ | J8: I78-A-1 | K8: Đệm làm kín | L8: 5"_GASKET_#150_SORF | M8: CERAMIC_FIBER | N8: pcs | P8: 2 | R8: 2 | V8: =VLOOKUP(J8,[113]PR!$A:$S,15,0) -> 0 | W8: =VLOOKUP(J8,[113]PR!$A:$S,16,0) -> 0 | X8: =VLOOKUP(J8,[114]PR!$A:$U,17,0) -> 0 | Y8: =VLOOKUP(J8,[114]PR!$A:$U,18,0) -> 0 | Z8: 0 | AA8: 0 | AB8: 0 | AC8: 0 | AD8: 0 | AE8: 0 | AF8: 0 | AG8: 0 | AH8: 0 | AI8: 0 | AJ8: 0 | AK8: 0 | AL8: 0 | AM8: 0 | AP8: 0 | AQ8: 0 | AR8: =R8+T8+V8+X8+Z8+AB8+AD8+AF8+AH8+AJ8+AL8+AN8+AP8 -> 2 | AS8: =S8+U8+W8+Y8+AA8+AC8+AE8+AG8+AI8+AK8+AM8+AO8+AQ8 -> 0 | AT8: MUA CẤP I59 | AZ8: =IF(AR8>AV8,AR8-AV8,"0") -> 2 | BA8: =IF(AS8>AW8,AS8-AW8,"0") -> 0 | BB8: Done | BC8: Báo giá 8/1/2025 | BD8: Tam Đa | BE8: OD175 x ID114 , t=3mm | BF8: GASKET NON METALIC | BG8: N/A | BH8: 45665 | BI8: 2 | BJ8: N/A | BK8: 130000 | BL8: =BK8*BI8*1.1 -> 286000 | BM8: 45674 | BN8: =SUMIF($J:$J,J8,$BI:$BI) -> 2 | BO8: =SUMIF($J:$J,J8,$BJ:$BJ) -> 0 | BP8: ACC | CL8: =SUMIF($J:$J,J8,$BZ:$BZ) -> 0 | CM8: =SUMIF($J:$J,J8,$CA:$CA) -> 0 | CR8: =BN8+CL8 -> 2 | CS8: =BO8+CM8 -> 0 | CT8: =AZ8-CR8 -> 0 | CU8: =BA8-CS8 -> 0 | CV8: =IF(CT8<0,"Thừa",IF(CT8=0,"Đủ","Thiếu")) -> Đủ
A9: =IF(J9=J8,"ok","Hiện") -> Hiện | B9: =CV9 -> Đủ | C9: =CT9 -> 0 | H9: Vật tư phụ | J9: I78-A-2 | K9: Đệm làm kín | L9: 6"_GASKET_#150_SORF | M9: CERAMIC_FIBER | N9: pcs | P9: 11 | R9: 11 | V9: =VLOOKUP(J9,[113]PR!$A:$S,15,0) -> 0 | W9: =VLOOKUP(J9,[113]PR!$A:$S,16,0) -> 0 | X9: =VLOOKUP(J9,[114]PR!$A:$U,17,0) -> 0 | Y9: =VLOOKUP(J9,[114]PR!$A:$U,18,0) -> 0 | Z9: 0 | AA9: 0 | AB9: 0 | AC9: 0 | AD9: 0 | AE9: 0 | AF9: 0 | AG9: 0 | AH9: 0 | AI9: 0 | AJ9: 0 | AK9: 0 | AL9: 0 | AM9: 0 | AP9: 0 | AQ9: 0 | AR9: =R9+T9+V9+X9+Z9+AB9+AD9+AF9+AH9+AJ9+AL9+AN9+AP9 -> 11 | AS9: =S9+U9+W9+Y9+AA9+AC9+AE9+AG9+AI9+AK9+AM9+AO9+AQ9 -> 0 | AT9: MUA CẤP I59 | AZ9: =IF(AR9>AV9,AR9-AV9,"0") -> 11 | BA9: =IF(AS9>AW9,AS9-AW9,"0") -> 0 | BB9: Done | BC9: Báo giá 8/1/2025 | BD9: Tam Đa | BE9: OD196 x ID141.2 , t=3mm | BF9: GASKET NON METALIC | BG9: N/A | BH9: 45665 | BI9: 11 | BJ9: N/A | BK9: 155000 | BL9: =BK9*BI9*1.1 -> 1875500 | BM9: 45674 | BN9: =SUMIF($J:$J,J9,$BI:$BI) -> 11 | BO9: =SUMIF($J:$J,J9,$BJ:$BJ) -> 0 | BP9: ACC | CL9: =SUMIF($J:$J,J9,$BZ:$BZ) -> 0 | CM9: =SUMIF($J:$J,J9,$CA:$CA) -> 0 | CR9: =BN9+CL9 -> 11 | CS9: =BO9+CM9 -> 0 | CT9: =AZ9-CR9 -> 0 | CU9: =BA9-CS9 -> 0 | CV9: =IF(CT9<0,"Thừa",IF(CT9=0,"Đủ","Thiếu")) -> Đủ
A10: =IF(J10=J9,"ok","Hiện") -> Hiện | B10: =CV10 -> Đủ | C10: =CT10 -> 0 | H10: Vật tư phụ | J10: I78-A-3 | K10: Đệm làm kín | L10: 4"_GASKET_#150_SORF | M10: CERAMIC_FIBER | N10: pcs | P10: 3 | R10: 3 | V10: =VLOOKUP(J10,[113]PR!$A:$S,15,0) -> 0 | W10: =VLOOKUP(J10,[113]PR!$A:$S,16,0) -> 0 | X10: =VLOOKUP(J10,[114]PR!$A:$U,17,0) -> 0 | Y10: =VLOOKUP(J10,[114]PR!$A:$U,18,0) -> 0 | Z10: 0 | AA10: 0 | AB10: 0 | AC10: 0 | AD10: 0 | AE10: 0 | AF10: 0 | AG10: 0 | AH10: 0 | AI10: 0 | AJ10: 0 | AK10: 0 | AL10: 0 | AM10: 0 | AP10: 0 | AQ10: 0 | AR10: =R10+T10+V10+X10+Z10+AB10+AD10+AF10+AH10+AJ10+AL10+AN10+AP10 -> 3 | AS10: =S10+U10+W10+Y10+AA10+AC10+AE10+AG10+AI10+AK10+AM10+AO10+AQ10 -> 0 | AT10: MUA CẤP I59 | AZ10: =IF(AR10>AV10,AR10-AV10,"0") -> 3 | BA10: =IF(AS10>AW10,AS10-AW10,"0") -> 0 | BB10: Done | BC10: Báo giá 8/1/2025 | BD10: Tam Đa | BE10: OD222 x ID168 , t=3mm | BF10: GASKET NON METALIC | BG10: N/A | BH10: 45665 | BI10: 3 | BJ10: N/A | BK10: 180000 | BL10: =BK10*BI10*1.1 -> 594000 | BM10: 45674 | BN10: =SUMIF($J:$J,J10,$BI:$BI) -> 3 | BO10: =SUMIF($J:$J,J10,$BJ:$BJ) -> 0 | BP10: ACC | CL10: =SUMIF($J:$J,J10,$BZ:$BZ) -> 0 | CM10: =SUMIF($J:$J,J10,$CA:$CA) -> 0 | CR10: =BN10+CL10 -> 3 | CS10: =BO10+CM10 -> 0 | CT10: =AZ10-CR10 -> 0 | CU10: =BA10-CS10 -> 0 | CV10: =IF(CT10<0,"Thừa",IF(CT10=0,"Đủ","Thiếu")) -> Đủ
A11: =IF(J11=J10,"ok","Hiện") -> Hiện | B11: =CONCATENATE(CV11," Dùng cùng mã A-8") -> Thiếu Dùng cùng mã A-8 | C11: =CT11 -> 1.93637 | H11: Thép đen | J11: I78-A-4 | K11: tôn tấm | L11: PL1.5x1250x2500 | M11: JIS G3101-SS400 | N11: m2 | O11: 11.775 | P11: 1.6838 | Q11: 19.826745 | T11: 1.93637 | U11: 22.800757 | V11: =VLOOKUP(J11,[113]PR!$A:$S,15,0) -> 0 | W11: =VLOOKUP(J11,[113]PR!$A:$S,16,0) -> 0 | X11: =VLOOKUP(J11,[114]PR!$A:$U,17,0) -> 0 | Y11: =VLOOKUP(J11,[114]PR!$A:$U,18,0) -> 0 | Z11: 0 | AA11: 0 | AB11: 0 | AC11: 0 | AD11: 0 | AE11: 0 | AF11: 0 | AG11: 0 | AH11: 0 | AI11: 0 | AJ11: 0 | AK11: 0 | AL11: 0 | AM11: 0 | AP11: 0 | AQ11: 0 | AR11: =R11+T11+V11+X11+Z11+AB11+AD11+AF11+AH11+AJ11+AL11+AN11+AP11 -> 1.93637 | AS11: =S11+U11+W11+Y11+AA11+AC11+AE11+AG11+AI11+AK11+AM11+AO11+AQ11 -> 22.800757 | AT11: REV2-A572-->SS400 khách hàng REV | AZ11: =IF(AR11>AV11,AR11-AV11,"0") -> 1.93637 | BA11: =IF(AS11>AW11,AS11-AW11,"0") -> 22.800757 | BB11: 45762 | BN11: =SUMIF($J:$J,J11,$BI:$BI) -> 0 | BO11: =SUMIF($J:$J,J11,$BJ:$BJ) -> 0 | CL11: =SUMIF($J:$J,J11,$BZ:$BZ) -> 0 | CM11: =SUMIF($J:$J,J11,$CA:$CA) -> 0 | CR11: =BN11+CL11 -> 0 | CS11: =BO11+CM11 -> 0 | CT11: =AZ11-CR11 -> 1.93637 | CU11: =BA11-CS11 -> 22.800757 | CV11: =IF(CT11<0,"Thừa",IF(CT11=0,"Đủ","Thiếu")) -> Thiếu | CZ11: 1.6838 | DA11: 19.826745
A12: =IF(J12=J11,"ok","Hiện") -> Hiện | B12: =CONCATENATE(CV12," TK báo đủ") -> Thiếu TK báo đủ | C12: =CT12 -> 7.1458621 | E12: Thiếu 1 tờ mua thêm/ kiêm tra lại hàng tồn | H12: Thép trắng nhập | I12: Tấm PL1,5mmx1.22m*2.44m= 84 Tờ | J12: I78-A-5 | K12: tôn tấm( % C min 0.04%) | L12: PL1.5x1250x2500 | M12: JIS G4312 SUH409 | N12: m2 | O12: 11.55 | P12: 463.10156 | Q12: 5348.8231 | T12: 504.22026 | U12: 5823.744 | V12: =VLOOKUP(J12,[113]PR!$A:$S,15,0) -> 0 | W12: =VLOOKUP(J12,[113]PR!$A:$S,16,0) -> 0 | X12: =VLOOKUP(J12,[114]PR!$A:$U,17,0) -> 0 | Y12: =VLOOKUP(J12,[114]PR!$A:$U,18,0) -> 0 | Z12: 0 | AA12: 0 | AB12: 0 | AC12: 0 | AD12: 0 | AE12: 0 | AF12: 0 | AG12: 0 | AH12: 0 | AI12: 0 | AJ12: 0 | AK12: 0 | AL12: 0 | AM12: 0 | AP12: 0 | AQ12: 0 | AR12: =R12+T12+V12+X12+Z12+AB12+AD12+AF12+AH12+AJ12+AL12+AN12+AP12 -> 504.22026 | AS12: =S12+U12+W12+Y12+AA12+AC12+AE12+AG12+AI12+AK12+AM12+AO12+AQ12 -> 5823.744 | AV12: =1.22*2.44 * 83 -> 247.0744 | AW12: =AV12*O12 -> 2853.7093 | AZ12: =IF(AR12>AV12,AR12-AV12,"0") -> 257.14586 | BA12: =IF(AS12>AW12,AS12-AW12,"0") -> 2970.0347 | BN12: =SUMIF($J:$J,J12,$BI:$BI) -> 0 | BO12: =SUMIF($J:$J,J12,$BJ:$BJ) -> 0 | BT12: EYANG-IBS/25048HP01 | BU12: EYANG | BV12: PL1.5 x 1250 x 2500mm (CR/2B) | BW12: Stainless Steel ASTM A240 TP409 - Plate | BX12: 2887.5 | BY12: 45873 | BZ12: =1.25*2.5*80 -> 250 | CA12: 2887.5 | CB12: 1.422 | CC12: =CB12*CA12 -> 4106.025 | CH12: 45797 | CI12: 45798 | CJ12: 45798 | CK12: 45798 | CL12: =SUMIF($J:$J,J12,$BZ:$BZ) -> 250 | CM12: =SUMIF($J:$J,J12,$CA:$CA) -> 2887.5 | CR12: =BN12+CL12 -> 250 | CS12: =BO12+CM12 -> 2887.5 | CT12: =AZ12-CR12 -> 7.1458621 | CU12: =BA12-CS12 -> 82.534708 | CV12: =IF(CT12<0,"Thừa",IF(CT12=0,"Đủ","Thiếu")) -> Thiếu | DB12: 99.877966 | DC12: 1176.0631 | DJ12: 118.63 | DK12: 1396.9 | DL12: 118.63 | DM12: 1396.9 | DN12: 117.1 | DO12: 1378.9
A13: =IF(J13=J12,"ok","Hiện") -> Hiện | B13: =CV13 -> Thừa | C13: =CT13 -> -0.4586548 | J13: I78-A-6 | K13: tôn tấm( % C min 0.04%) | L13: PL1.5x1250x2500 | M13: JIS.G4304_SUS304 | N13: m2 | O13: 11.895 | P13: 451.73984 | Q13: 5373.4454 | T13: 506.54135 | U13: 6025.3093 | V13: =VLOOKUP(J13,[113]PR!$A:$S,15,0) -> 0 | W13: =VLOOKUP(J13,[113]PR!$A:$S,16,0) -> 0 | X13: =VLOOKUP(J13,[114]PR!$A:$U,17,0) -> 0 | Y13: =VLOOKUP(J13,[114]PR!$A:$U,18,0) -> 0 | Z13: 0 | AA13: 0 | AB13: 0 | AC13: 0 | AD13: 0 | AE13: 0 | AF13: 0 | AG13: 0 | AH13: 0 | AI13: 0 | AJ13: 0 | AK13: 0 | AL13: 8.625 | AM13: 102.59437 | AP13: 0 | AQ13: 0 | AR13: =R13+T13+V13+X13+Z13+AB13+AD13+AF13+AH13+AJ13+AL13+AN13+AP13 -> 515.16635 | AS13: =S13+U13+W13+Y13+AA13+AC13+AE13+AG13+AI13+AK13+AM13+AO13+AQ13 -> 6127.9037 | AT13: REV10-IBS REV | AZ13: =IF(AR13>AV13,AR13-AV13,"0") -> 515.16635 | BA13: =IF(AS13>AW13,AS13-AW13,"0") -> 6127.9037 | BC13: 0310-25/HĐKT?IBSHI-TP | BD13: Thịnh Phát | BE13: PL1.5x1250x2500 ( 3 tấm ) | BF13: JIS.G4304_SUS304 | BG13: 112 | BH13: 45933 | BI13: =3*1.25*2.5 -> 9.375 | BJ13: 112 | BK13: =65000/1.1 -> 59090.909 | BL13: =BK13*BJ13*1.1 -> 7280000 | BM13: 45934 | BN13: =SUMIF($J:$J,J13,$BI:$BI) -> 9.375 | BO13: =SUMIF($J:$J,J13,$BJ:$BJ) -> 112 | BT13: IBSHI-GNEE/2504-08 | BU13: GNEE | BV13: 1.5*1250*2500 | BW13: SUS304 PLATE | BX13: 6026.4 | BY13: 45755 | BZ13: 506.25 | CA13: 6026.4 | CB13: 2.61 | CC13: =CB13*CA13 -> 15728.904 | CI13: 45791 | CJ13: 45792 | CL13: =SUMIF($J:$J,J13,$BZ:$BZ) -> 506.25 | CM13: =SUMIF($J:$J,J13,$CA:$CA) -> 6026.4 | CR13: =BN13+CL13 -> 515.625 | CS13: =BO13+CM13 -> 6138.4 | CT13: =AZ13-CR13 -> -0.4586548 | CU13: =BA13-CS13 -> -10.496324 | CV13: =IF(CT13<0,"Thừa",IF(CT13=0,"Đủ","Thiếu")) -> Thừa | DB13: 53.732939 | DC13: 632.70535 | DH13: 402.61062 | DI13: 4740.74
A14: =IF(J14=J13,"ok","Hiện") -> Hiện | B14: =CONCATENATE(CV14," đủ") -> Thiếu đủ | C14: =CT14 -> 0.063129074 | H14: Thép trắng nhập | J14: I78-A-7 | K14: tôn tấm( % C min 0.04%) | L14: PL1.5x1250x2500 | M14: JIS.G4304_SUS310S | N14: m2 | O14: 11.625 | P14: 48.53552 | Q14: 564.22542 | T14: 53.188129 | U14: 618.312 | V14: =VLOOKUP(J14,[113]PR!$A:$S,15,0) -> 0 | W14: =VLOOKUP(J14,[113]PR!$A:$S,16,0) -> 0 | X14: =VLOOKUP(J14,[114]PR!$A:$U,17,0) -> 0 | Y14: =VLOOKUP(J14,[114]PR!$A:$U,18,0) -> 0 | Z14: 0 | AA14: 0 | AB14: 0 | AC14: 0 | AD14: 0 | AE14: 0 | AF14: 0 | AG14: 0 | AH14: 0 | AI14: 0 | AJ14: 0 | AK14: 0 | AL14: 0 | AM14: 0 | AP14: 0 | AQ14: 0 | AR14: =R14+T14+V14+X14+Z14+AB14+AD14+AF14+AH14+AJ14+AL14+AN14+AP14 -> 53.188129 | AS14: =S14+U14+W14+Y14+AA14+AC14+AE14+AG14+AI14+AK14+AM14+AO14+AQ14 -> 618.312 | AZ14: =IF(AR14>AV14,AR14-AV14,"0") -> 53.188129 | BA14: =IF(AS14>AW14,AS14-AW14,"0") -> 618.312 | BN14: =SUMIF($J:$J,J14,$BI:$BI) -> 0 | BO14: =SUMIF($J:$J,J14,$BJ:$BJ) -> 0 | BT14: IBSHI-GNEE/2504-08 | BU14: GNEE | BV14: 1.5*1250*2500 | BW14: SUS310S PLATE | BX14: 635.8 | BY14: 45755 | BZ14: 53.125 | CA14: 635.8 | CB14: 6.11 | CC14: =CB14*CA14 -> 3884.738 | CI14: 45791 | CJ14: 45792 | CL14: =SUMIF($J:$J,J14,$BZ:$BZ) -> 53.125 | CM14: =SUMIF($J:$J,J14,$CA:$CA) -> 635.8 | CR14: =BN14+CL14 -> 53.125 | CS14: =BO14+CM14 -> 635.8 | CT14: =AZ14-CR14 -> 0.063129074 | CU14: =BA14-CS14 -> -17.488 | CV14: =IF(CT14<0,"Thừa",IF(CT14=0,"Đủ","Thiếu")) -> Thiếu | DB14: 36.968613 | DC14: 435.30542 | DD14: 10.94862 | DE14: 128.92
A15: =IF(J15=J14,"ok","Hiện") -> Hiện | B15: =CV15 -> Thừa | C15: =CT15 -> -3.25 | H15: Thép đen | I15: Thép thường | J15: I78-A-8 | K15: tôn tấm | L15: PL1.5x1250x2500 | M15: JIS G3101-SS400 | N15: m2 | O15: 11.775 | P15: 1.6917197 | Q15: 19.92 | T15: 3 | U15: 35.325 | V15: =VLOOKUP(J15,[113]PR!$A:$S,15,0) -> 0 | W15: =VLOOKUP(J15,[113]PR!$A:$S,16,0) -> 0 | X15: =VLOOKUP(J15,[114]PR!$A:$U,17,0) -> 0 | Y15: =VLOOKUP(J15,[114]PR!$A:$U,18,0) -> 0 | Z15: 0 | AA15: 0 | AB15: 0 | AC15: 0 | AD15: 0 | AE15: 0 | AF15: 0 | AG15: 0 | AH15: 0 | AI15: 0 | AJ15: 0 | AK15: 0 | AL15: 0 | AM15: 0 | AP15: 0 | AQ15: 0 | AR15: =R15+T15+V15+X15+Z15+AB15+AD15+AF15+AH15+AJ15+AL15+AN15+AP15 -> 3 | AS15: =S15+U15+W15+Y15+AA15+AC15+AE15+AG15+AI15+AK15+AM15+AO15+AQ15 -> 35.325 | AZ15: =IF(AR15>AV15,AR15-AV15,"0") -> 3 | BA15: =IF(AS15>AW15,AS15-AW15,"0") -> 35.325 | BC15: 100425HN-IBS | BD15: Hùng Nguyên | BE15: Thép tấm 1.5x1250x2500 | BF15: SS400 | BG15: 73.59 | BH15: 45757 | BI15: 6.25 | BJ15: 73.59 | BK15: 20000 | BL15: =BK15*BJ15*1.1 -> 1618980 | BM15: 45758 | BN15: =SUMIF($J:$J,J15,$BI:$BI) -> 6.25 | BO15: =SUMIF($J:$J,J15,$BJ:$BJ) -> 73.59 | BP15: ACC | CL15: =SUMIF($J:$J,J15,$BZ:$BZ) -> 0 | CM15: =SUMIF($J:$J,J15,$CA:$CA) -> 0 | CR15: =BN15+CL15 -> 6.25 | CS15: =BO15+CM15 -> 73.59 | CT15: =AZ15-CR15 -> -3.25 | CU15: =BA15-CS15 -> -38.265 | CV15: =IF(CT15<0,"Thừa",IF(CT15=0,"Đủ","Thiếu")) -> Thừa | DP15: 1.6917197 | DQ15: 19.92
A16: =IF(J16=J15,"ok","Hiện") -> Hiện | B16: =CV16 -> Đủ | C16: =CT16 -> 0 | F16: Lấy 1 tờ tồn dự án 090 | J16: I78-A-9 | K16: tôn tấm( % C min 0.04%) | L16: PL2x1250x2500 | M16: JIS.G4304_SUS304 | N16: m2 | O16: 15.86 | P16: 427.02864 | Q16: 6772.6742 | T16: 478.83238 | U16: 7594.2815 | V16: =VLOOKUP(J16,[113]PR!$A:$S,15,0) -> 0 | W16: =VLOOKUP(J16,[113]PR!$A:$S,16,0) -> 0 | X16: =VLOOKUP(J16,[114]PR!$A:$U,17,0) -> 0 | Y16: =VLOOKUP(J16,[114]PR!$A:$U,18,0) -> 0 | Z16: 0 | AA16: 0 | AB16: 0 | AC16: 0 | AD16: 0 | AE16: 0 | AF16: 0 | AG16: 0 | AH16: 0 | AI16: 0 | AJ16: 0 | AK16: 0 | AL16: 24.125 | AM16: 382.6225 | AP16: 0 | AQ16: 0 | AR16: =R16+T16+V16+X16+Z16+AB16+AD16+AF16+AH16+AJ16+AL16+AN16+AP16 -> 502.95738 | AS16: =S16+U16+W16+Y16+AA16+AC16+AE16+AG16+AI16+AK16+AM16+AO16+AQ16 -> 7976.904 | AT16: REV10-IBS REV | AV16: 2.9573795 | AW16: 46.904038 | AY16: Lấy hàng tồn dự án 090 | AZ16: =IF(AR16>AV16,AR16-AV16,"0") -> 500 | BA16: =IF(AS16>AW16,AS16-AW16,"0") -> 7930 | BC16: 0310-25/HĐKT?IBSHI-TP | BD16: Thịnh Phát | BE16: PL2x1250x2500 (7 tấm ) | BF16: JIS.G4304_SUS304 | BG16: 344 | BH16: 45933 | BI16: =7*1.25*2.5 -> 21.875 | BJ16: 344 | BK16: =65000/1.1 -> 59090.909 | BL16: =BK16*BJ16*1.1 -> 22360000 | BM16: 45934 | BN16: =SUMIF($J:$J,J16,$BI:$BI) -> 21.875 | BO16: =SUMIF($J:$J,J16,$BJ:$BJ) -> 344 | BT16: IBSHI-GNEE/2504-08 | BU16: GNEE | BV16: 2*1250*2500 | BW16: SUS304 PLATE | BX16: 7588.8 | BY16: 45755 | BZ16: 478.125 | CA16: 7588.8 | CB16: 2.61 | CC16: =CB16*CA16 -> 19806.768 | CI16: 45791 | CJ16: 45792 | CL16: =SUMIF($J:$J,J16,$BZ:$BZ) -> 478.125 | CM16: =SUMIF($J:$J,J16,$CA:$CA) -> 7588.8 | CR16: =BN16+CL16 -> 500 | CS16: =BO16+CM16 -> 7932.8 | CT16: =AZ16-CR16 -> 0 | CU16: =BA16-CS16 -> -2.8 | CV16: =IF(CT16<0,"Thừa",IF(CT16=0,"Đủ","Thiếu")) -> Đủ | DB16: 6.8072736 | DC16: 106.8742 | DH16: 424.57325 | DI16: 6665.8
A17: =IF(J17=J16,"ok","Hiện") -> Hiện | B17: =CV17 -> Thừa | C17: =CT17 -> -3.2341072 | J17: I78-A-10 | K17: tôn tấm( % C min 0.04%) | L17: PL2x1250x2500 | M17: JIS.G4304_SUS310S | N17: m2 | O17: 15.5 | P17: 584.82924 | Q17: 9064.8532 | T17: 640.89089 | U17: 9933.8088 | V17: =VLOOKUP(J17,[113]PR!$A:$S,15,0) -> 0 | W17: =VLOOKUP(J17,[113]PR!$A:$S,16,0) -> 0 | X17: =VLOOKUP(J17,[114]PR!$A:$U,17,0) -> 0 | Y17: =VLOOKUP(J17,[114]PR!$A:$U,18,0) -> 0 | Z17: 0 | AA17: 0 | AB17: 0 | AC17: 0 | AD17: 70 | AE17: 1085 | AF17: 0 | AG17: 0 | AH17: 0 | AI17: 0 | AJ17: 0 | AK17: 0 | AL17: 29.625 | AM17: 459.1875 | AP17: 0 | AQ17: 0 | AR17: =R17+T17+V17+X17+Z17+AB17+AD17+AF17+AH17+AJ17+AL17+AN17+AP17 -> 740.51589 | AS17: =S17+U17+W17+Y17+AA17+AC17+AE17+AG17+AI17+AK17+AM17+AO17+AQ17 -> 11477.996 | AT17: REV10-IBS REV | AZ17: =IF(AR17>AV17,AR17-AV17,"0") -> 740.51589 | BA17: =IF(AS17>AW17,AS17-AW17,"0") -> 11477.996 | BN17: =SUMIF($J:$J,J17,$BI:$BI) -> 31.25 | BO17: =SUMIF($J:$J,J17,$BJ:$BJ) -> 478 | BT17: IBSHI-GNEE/2504-08 | BU17: GNEE | BV17: 2*1250*2500 | BW17: SUS310S PLATE | BX17: 10250 | BY17: 45755 | BZ17: 640.625 | CA17: 10250 | CB17: 6.11 | CC17: =CB17*CA17 -> 62627.5 | CI17: 45791 | CJ17: 45792 | CL17: =SUMIF($J:$J,J17,$BZ:$BZ) -> 712.5 | CM17: =SUMIF($J:$J,J17,$CA:$CA) -> 11400 | CR17: =BN17+CL17 -> 743.75 | CS17: =BO17+CM17 -> 11878 | CT17: =AZ17-CR17 -> -3.2341072 | CU17: =BA17-CS17 -> -400.00366 | CV17: =IF(CT17<0,"Thừa",IF(CT17=0,"Đủ","Thiếu")) -> Thừa | DB17: 1.786826 | DC17: 28.053168 | DD17: 575.22038 | DE17: 9030.96 | DJ17: 0.12356688 | DK17: 1.94 | DL17: 0.12356688 | DM17: 1.94 | DN17: 0.12356688 | DO17: 1.94
A18: =IF(J18=J17,"ok","Hiện") -> ok | J18: I78-A-10 | K18: tôn tấm( % C min 0.04%) | L18: PL2x1250x2500 | M18: JIS.G4304_SUS310S | N18: m2 | BT18: IBSHI-GNEE/2506-25 | BU18: GNEE | BV18: 2*1250*2500 | BW18: SUS310S PLATE | BX18: 1150 | BY18: 45833 | BZ18: =23*1250*2500/1000000 -> 71.875 | CA18: 1150 | CB18: 6.11 | CC18: =CB18*CA18 -> 7026.5 | CD18: 45846 | CF18: 45857 | CI18: 45867 | CJ18: 45868 | CL18: =SUMIF($J:$J,J18,$BZ:$BZ) -> 712.5 | CM18: =SUMIF($J:$J,J18,$CA:$CA) -> 11400
A19: =IF(J19=J18,"ok","Hiện") -> ok | J19: I78-A-10 | K19: tôn tấm( % C min 0.04%) | L19: PL2x1250x2500 | M19: JIS.G4304_SUS310S | N19: m2 | BC19: 1510-25/HĐKT?IBSHI-TP | BD19: Thịnh Phát | BE19: PL2x1250x2500 (10 tấm ) mác 310S (2mm) | BF19: 310S | BG19: 478 | BH19: 45945 | BI19: =10*1.25*2.5 -> 31.25 | BJ19: 478 | BK19: 222727 | BL19: =BK19*BJ19*1.1 -> 1.1710986e+08 | BM19: 45947
A20: =IF(J20=J19,"ok","Hiện") -> Hiện | B20: =CV20 -> Đủ | C20: =CT20 -> 0 | E20: Hàng tồn, đã mời | H20: Thép trắng nhập | I20: Tấm PL2mmx1.22m*2.44m= 20 Tờ | J20: I78-A-11 | K20: tôn tấm( % C min 0.04%) | L20: PL2x1250x2500 | M20: JIS G4312 SUH409 | N20: m2 | O20: 11.55 | P20: 52.501246 | Q20: 606.38939 | T20: 45 | U20: 519.75 | V20: =VLOOKUP(J20,[113]PR!$A:$S,15,0) -> 0 | W20: =VLOOKUP(J20,[113]PR!$A:$S,16,0) -> 0 | X20: =VLOOKUP(J20,[114]PR!$A:$U,17,0) -> 0 | Y20: =VLOOKUP(J20,[114]PR!$A:$U,18,0) -> 0 | Z20: 0 | AA20: 0 | AB20: 0 | AC20: 0 | AD20: 0 | AE20: 0 | AF20: 0 | AG20: 0 | AH20: 0 | AI20: 0 | AJ20: 0 | AK20: 0 | AL20: 1.875 | AM20: 28.875 | AP20: 0 | AQ20: 0 | AR20: =R20+T20+V20+X20+Z20+AB20+AD20+AF20+AH20+AJ20+AL20+AN20+AP20 -> 46.875 | AS20: =S20+U20+W20+Y20+AA20+AC20+AE20+AG20+AI20+AK20+AM20+AO20+AQ20 -> 548.625 | AT20: REV10-IBS REV | AV20: =1.22*2.44 * 20 -> 59.536 | AW20: =AV20*O20 -> 687.6408 | AZ20: =IF(AR20>AV20,AR20-AV20,"0") -> 0 | BA20: =IF(AS20>AW20,AS20-AW20,"0") -> 0 | BN20: =SUMIF($J:$J,J20,$BI:$BI) -> 0 | BO20: =SUMIF($J:$J,J20,$BJ:$BJ) -> 0 | CL20: =SUMIF($J:$J,J20,$BZ:$BZ) -> 0 | CM20: =SUMIF($J:$J,J20,$CA:$CA) -> 0 | CR20: =BN20+CL20 -> 0 | CS20: =BO20+CM20 -> 0 | CT20: =AZ20-CR20 -> 0 | CU20: =BA20-CS20 -> 0 | CV20: =IF(CT20<0,"Thừa",IF(CT20=0,"Đủ","Thiếu")) -> Đủ | DB20: 7.8235279 | DC20: 122.82939 | DJ20: 10.263694 | DK20: 161.14 | DL20: 10.263694 | DM20: 161.14 | DN20: 10.275159 | DO20: 161.32
A21: =IF(J21=J20,"ok","Hiện") -> Hiện | B21: =CV21 -> Đủ | C21: =CT21 -> 0 | H21: Thép trắng nhập | J21: I78-A-12 | K21: tôn tấm( % C min 0.04%) | L21: PL3 | M21: ASTM-A240-TP304H | N21: m2 | O21: 23.79 | P21: 81.054093 | Q21: =1840.5768608+87.7 -> 1928.2769 | T21: 90 | U21: 2141.1 | V21: =VLOOKUP(J21,[113]PR!$A:$S,15,0) -> 0 | W21: =VLOOKUP(J21,[113]PR!$A:$S,16,0) -> 0 | X21: =VLOOKUP(J21,[114]PR!$A:$U,17,0) -> 0 | Y21: =VLOOKUP(J21,[114]PR!$A:$U,18,0) -> 0 | Z21: 0 | AA21: 0 | AB21: 0 | AC21: 0 | AD21: 0 | AE21: 0 | AF21: 0 | AG21: 0 | AH21: 0 | AI21: 0 | AJ21: 0 | AK21: 0 | AL21: 0 | AM21: 0 | AP21: 0 | AQ21: 0 | AR21: =R21+T21+V21+X21+Z21+AB21+AD21+AF21+AH21+AJ21+AL21+AN21+AP21 -> 90 | AS21: =S21+U21+W21+Y21+AA21+AC21+AE21+AG21+AI21+AK21+AM21+AO21+AQ21 -> 2141.1 | AT21: 03 TỜ PL3x1500x5000 03 TỜ PL3x2000x5000 12 TỜ PL3x1250x2500 | AZ21: =IF(AR21>AV21,AR21-AV21,"0") -> 90 | BA21: =IF(AS21>AW21,AS21-AW21,"0") -> 2141.1 | BN21: =SUMIF($J:$J,J21,$BI:$BI) -> 0 | BO21: =SUMIF($J:$J,J21,$BJ:$BJ) -> 0 | BT21: IBSHI-GNEE/2504-08 | BU21: GNEE | BV21: 3*1500*5000 | BW21: A240-TP304H PLATE | BX21: 535.2 | BY21: 45755 | BZ21: 22.5 | CA21: 535.2 | CB21: 2.61 | CC21: =CB21*CA21 -> 1396.872 | CI21: 45791 | CJ21: 45792 | CL21: =SUMIF($J:$J,J21,$BZ:$BZ) -> 90 | CM21: =SUMIF($J:$J,J21,$CA:$CA) -> 2140.5 | CR21: =BN21+CL21 -> 90 | CS21: =BO21+CM21 -> 2140.5 | CT21: =AZ21-CR21 -> 0 | CU21: =BA21-CS21 -> 0.6 | CV21: =IF(CT21<0,"Thừa",IF(CT21=0,"Đủ","Thiếu")) -> Đủ | DF21: 78.119612 | DG21: 1839.7169 | DH21: 3.76 | DI21: 88.56
A22: =IF(J22=J21,"ok","Hiện") -> ok | H22: Thép trắng nhập | J22: I78-A-12 | K22: tôn tấm( % C min 0.04%) | L22: PL3 | M22: ASTM-A240-TP304H | BT22: IBSHI-GNEE/2504-08 | BU22: GNEE | BV22: 3*2000*5000 | BW22: A240-TP304H PLATE | BX22: 713.7 | BY22: 45755 | BZ22: 30 | CA22: 713.7 | CB22: 2.96 | CC22: =CB22*CA22 -> 2112.552 | CI22: 45791 | CJ22: 45792
A23: =IF(J23=J22,"ok","Hiện") -> ok | H23: Thép trắng nhập | J23: I78-A-12 | K23: tôn tấm( % C min 0.04%) | L23: PL3 | M23: ASTM-A240-TP304H | BT23: IBSHI-GNEE/2504-08 | BU23: GNEE | BV23: 3*1250*2500 | BW23: A240-TP304H PLATE | BX23: 891.6 | BY23: 45755 | BZ23: 37.5 | CA23: 891.6 | CB23: 2.91 | CC23: =CB23*CA23 -> 2594.556 | CI23: 45791 | CJ23: 45792
A24: =IF(J24=J23,"ok","Hiện") -> Hiện | B24: =CONCATENATE(CV24," Dùng cùng A-16") -> Thiếu Dùng cùng A-16 | C24: =CT24 -> 2.18894 | E24: Dùng cùng A-16 | H24: Thép đen | J24: I78-A-13 | K24: tôn tấm | L24: PL3x1500x6000 | M24: JIS G3101-SS400 | N24: m2 | O24: 23.55 | P24: 1.6838 | Q24: 39.65349 | T24: 2.18894 | U24: 51.549537 | V24: =VLOOKUP(J24,[113]PR!$A:$S,15,0) -> 0 | W24: =VLOOKUP(J24,[113]PR!$A:$S,16,0) -> 0 | X24: =VLOOKUP(J24,[114]PR!$A:$U,17,0) -> 0 | Y24: =VLOOKUP(J24,[114]PR!$A:$U,18,0) -> 0 | Z24: 0 | AA24: 0 | AB24: 0 | AC24: 0 | AD24: 0 | AE24: 0 | AF24: 0 | AG24: 0 | AH24: 0 | AI24: 0 | AJ24: 0 | AK24: 0 | AL24: 0 | AM24: 0 | AP24: 0 | AQ24: 0 | AR24: =R24+T24+V24+X24+Z24+AB24+AD24+AF24+AH24+AJ24+AL24+AN24+AP24 -> 2.18894 | AS24: =S24+U24+W24+Y24+AA24+AC24+AE24+AG24+AI24+AK24+AM24+AO24+AQ24 -> 51.549537 | AZ24: =IF(AR24>AV24,AR24-AV24,"0") -> 2.18894 | BA24: =IF(AS24>AW24,AS24-AW24,"0") -> 51.549537 | BB24: 45762 | BN24: =SUMIF($J:$J,J24,$BI:$BI) -> 0 | BO24: =SUMIF($J:$J,J24,$BJ:$BJ) -> 0 | CL24: =SUMIF($J:$J,J24,$BZ:$BZ) -> 0 | CM24: =SUMIF($J:$J,J24,$CA:$CA) -> 0 | CR24: =BN24+CL24 -> 0 | CS24: =BO24+CM24 -> 0 | CT24: =AZ24-CR24 -> 2.18894 | CU24: =BA24-CS24 -> 51.549537 | CV24: =IF(CT24<0,"Thừa",IF(CT24=0,"Đủ","Thiếu")) -> Thiếu | CZ24: 1.6838 | DA24: 39.65349
A25: =IF(J25=J24,"ok","Hiện") -> Hiện | B25: =CV25 -> Thừa | C25: =CT25 -> -0.125 | H25: Thép trắng nhập | J25: I78-A-14 | K25: tôn tấm( % C min 0.04%) | L25: PL3x1250x2500 | M25: JIS G4312 SUH409 | N25: m2 | O25: 11.55 | P25: 4.5264069 | Q25: 52.28 | T25: 3 | U25: 69.3 | V25: =VLOOKUP(J25,[113]PR!$A:$S,15,0) -> 0 | W25: =VLOOKUP(J25,[113]PR!$A:$S,16,0) -> 0 | X25: =VLOOKUP(J25,[114]PR!$A:$U,17,0) -> 0 | Y25: =VLOOKUP(J25,[114]PR!$A:$U,18,0) -> 0 | Z25: 0 | AA25: 0 | AB25: 0 | AC25: 0 | AD25: 0 | AE25: 0 | AF25: 0 | AG25: 0 | AH25: 0 | AI25: 0 | AJ25: 0 | AK25: 0 | AL25: 0 | AM25: 0 | AP25: 0 | AQ25: 0 | AR25: =R25+T25+V25+X25+Z25+AB25+AD25+AF25+AH25+AJ25+AL25+AN25+AP25 -> 3 | AS25: =S25+U25+W25+Y25+AA25+AC25+AE25+AG25+AI25+AK25+AM25+AO25+AQ25 -> 69.3 | AZ25: =IF(AR25>AV25,AR25-AV25,"0") -> 3 | BA25: =IF(AS25>AW25,AS25-AW25,"0") -> 69.3 | BN25: =SUMIF($J:$J,J25,$BI:$BI) -> 0 | BO25: =SUMIF($J:$J,J25,$BJ:$BJ) -> 0 | BT25: EYANG-IBS/25048HP01 | BU25: EYANG | BV25: PL3 x 1250 x 2500mm ( HR/No1) | BW25: Stainless Steel ASTM A240 TP409 - Plate | BX25: 72.1875 | BY25: 45873 | BZ25: =1.25*2.5*1 -> 3.125 | CA25: 72.1875 | CB25: 1.502 | CC25: =CB25*CA25 -> 108.42562 | CH25: 45797 | CI25: 45798 | CJ25: 45798 | CK25: 45798 | CL25: =SUMIF($J:$J,J25,$BZ:$BZ) -> 3.125 | CM25: =SUMIF($J:$J,J25,$CA:$CA) -> 72.1875 | CR25: =BN25+CL25 -> 3.125 | CS25: =BO25+CM25 -> 72.1875 | CT25: =AZ25-CR25 -> -0.125 | CU25: =BA25-CS25 -> -2.8875 | CV25: =IF(CT25<0,"Thừa",IF(CT25=0,"Đủ","Thiếu")) -> Thừa | DJ25: 1 | DK25: 23.46 | DL25: 0.55 | DM25: 12.98 | DN25: 0.67 | DO25: 15.84
A26: =IF(J26=J25,"ok","Hiện") -> Hiện | B26: =CV26 -> Thừa | C26: =CT26 -> -0.125 | H26: Thép trắng nhập | J26: I78-A-15 | K26: tôn tấm( % C min 0.04%) | L26: PL3x1250x2500 | M26: JIS.G4304_SUS310S | N26: m2 | O26: 23.25 | P26: 2.6615054 | Q26: 61.88 | T26: 3 | U26: 69.75 | V26: =VLOOKUP(J26,[113]PR!$A:$S,15,0) -> 0 | W26: =VLOOKUP(J26,[113]PR!$A:$S,16,0) -> 0 | X26: =VLOOKUP(J26,[114]PR!$A:$U,17,0) -> 0 | Y26: =VLOOKUP(J26,[114]PR!$A:$U,18,0) -> 0 | Z26: 0 | AA26: 0 | AB26: 0 | AC26: 0 | AD26: 0 | AE26: 0 | AF26: 0 | AG26: 0 | AH26: 0 | AI26: 0 | AJ26: 0 | AK26: 0 | AL26: 0 | AM26: 0 | AP26: 0 | AQ26: 0 | AR26: =R26+T26+V26+X26+Z26+AB26+AD26+AF26+AH26+AJ26+AL26+AN26+AP26 -> 3 | AS26: =S26+U26+W26+Y26+AA26+AC26+AE26+AG26+AI26+AK26+AM26+AO26+AQ26 -> 69.75 | AZ26: =IF(AR26>AV26,AR26-AV26,"0") -> 3 | BA26: =IF(AS26>AW26,AS26-AW26,"0") -> 69.75 | BN26: =SUMIF($J:$J,J26,$BI:$BI) -> 0 | BO26: =SUMIF($J:$J,J26,$BJ:$BJ) -> 0 | BT26: IBSHI-GNEE/2504-08 | BU26: GNEE | BV26: 3*1250*2500 | BW26: SUS310S PLATE | BX26: 74.8 | BY26: 45755 | BZ26: 3.125 | CA26: 74.8 | CB26: 6.11 | CC26: =CB26*CA26 -> 457.028 | CI26: 45791 | CJ26: 45792 | CL26: =SUMIF($J:$J,J26,$BZ:$BZ) -> 3.125 | CM26: =SUMIF($J:$J,J26,$CA:$CA) -> 74.8 | CR26: =BN26+CL26 -> 3.125 | CS26: =BO26+CM26 -> 74.8 | CT26: =AZ26-CR26 -> -0.125 | CU26: =BA26-CS26 -> -5.05 | CV26: =IF(CT26<0,"Thừa",IF(CT26=0,"Đủ","Thiếu")) -> Thừa | DD26: 2.6276008 | DE26: 61.88
A27: =IF(J27=J26,"ok","Hiện") -> Hiện | B27: =CONCATENATE(CV27," Thiếu do tính") -> Thiếu Thiếu do tính | C27: =CT27 -> 0.0022059448 | H27: Thép đen | J27: I78-A-16 | K27: tôn tấm | L27: PL3x1500x6000 | M27: JIS G3101-SS400 | N27: m2 | O27: 23.55 | P27: 16.622505 | Q27: 391.46 | T27: 18.617206 | U27: 438.4352 | V27: =VLOOKUP(J27,[113]PR!$A:$S,15,0) -> 0 | W27: =VLOOKUP(J27,[113]PR!$A:$S,16,0) -> 0 | X27: =VLOOKUP(J27,[114]PR!$A:$U,17,0) -> 0 | Y27: =VLOOKUP(J27,[114]PR!$A:$U,18,0) -> 0 | Z27: 0 | AA27: 0 | AB27: 0 | AC27: 0 | AD27: 0 | AE27: 0 | AF27: 0 | AG27: 0 | AH27: 0 | AI27: 0 | AJ27: 0 | AK27: 0 | AL27: 0 | AM27: 0 | AP27: 0 | AQ27: 0 | AR27: =R27+T27+V27+X27+Z27+AB27+AD27+AF27+AH27+AJ27+AL27+AN27+AP27 -> 18.617206 | AS27: =S27+U27+W27+Y27+AA27+AC27+AE27+AG27+AI27+AK27+AM27+AO27+AQ27 -> 438.4352 | AZ27: =IF(AR27>AV27,AR27-AV27,"0") -> 18.617206 | BA27: =IF(AS27>AW27,AS27-AW27,"0") -> 438.4352 | BC27: 030325HN-IBS | BD27: Hùng Nguyên | BE27: Thép tấm 3x1500x6000 | BF27: SS400 | BG27: 211.95 | BH27: 45719 | BI27: 9 | BJ27: 211.95 | BK27: 13181.82 | BL27: =BK27*BJ27*1.1 -> 3073275.4 | BM27: 45757 | BN27: =SUMIF($J:$J,J27,$BI:$BI) -> 18.615 | BO27: =SUMIF($J:$J,J27,$BJ:$BJ) -> 438.38 | BP27: ACC | CL27: =SUMIF($J:$J,J27,$BZ:$BZ) -> 0 | CM27: =SUMIF($J:$J,J27,$CA:$CA) -> 0 | CR27: =BN27+CL27 -> 18.615 | CS27: =BO27+CM27 -> 438.38 | CT27: =AZ27-CR27 -> 0.0022059448 | CU27: =BA27-CS27 -> 0.0552 | CV27: =IF(CT27<0,"Thừa",IF(CT27=0,"Đủ","Thiếu")) -> Thiếu | DP27: 0.017834395 | DQ27: 0.42 | DR27: 0.5418259 | DS27: 12.76 | DT27: 16.062845 | DU27: 378.28
A28: =IF(J28=J27,"ok","Hiện") -> ok | H28: Thép đen | J28: I78-A-16 | K28: tôn tấm | L28: PL3x1500x6000 | M28: JIS G3101-SS400 | N28: m2 | O28: 23.55 | P28: 16.622505 | Q28: 391.46 | BC28: 030325HN-IBS | BD28: Hùng Nguyên | BE28: Thép tấm 3x1500x6410 | BF28: SS400 | BG28: 226.43 | BH28: 45719 | BI28: 9.615 | BJ28: 226.43 | BK28: 13181.82 | BL28: =BK28*BJ28*1.1 -> 3283235.5 | BM28: 45757 | BP28: ACC
A29: =IF(J29=J28,"ok","Hiện") -> Hiện | B29: =CV29 -> Đủ | C29: =CT29 -> 0 | G29: Hàng tồn | H29: Thép trắng nhập | J29: I78-A-17 | K29: tôn tấm( % C min 0.04%) | L29: PL4x500x1000 | M29: ASTM-A240-TP304H | N29: m2 | O29: 31.72 | P29: 0.36672 | Q29: 11.632358 | T29: 0.5 | U29: 15.86 | V29: =VLOOKUP(J29,[113]PR!$A:$S,15,0) -> 0 | W29: =VLOOKUP(J29,[113]PR!$A:$S,16,0) -> 0 | X29: =VLOOKUP(J29,[114]PR!$A:$U,17,0) -> 0 | Y29: =VLOOKUP(J29,[114]PR!$A:$U,18,0) -> 0 | Z29: 0 | AA29: 0 | AB29: 0 | AC29: 0 | AD29: 0 | AE29: 0 | AF29: 0 | AG29: 0 | AH29: 0 | AI29: 0 | AJ29: 0 | AK29: 0 | AL29: 0 | AM29: 0 | AP29: 0 | AQ29: 0 | AR29: =R29+T29+V29+X29+Z29+AB29+AD29+AF29+AH29+AJ29+AL29+AN29+AP29 -> 0.5 | AS29: =S29+U29+W29+Y29+AA29+AC29+AE29+AG29+AI29+AK29+AM29+AO29+AQ29 -> 15.86 | AV29: 0.5 | AW29: =AV29*O29 -> 15.86 | AY29: Đã mời nghiệm thu ngày 15/5 | AZ29: =IF(AR29>AV29,AR29-AV29,"0") -> 0 | BA29: =IF(AS29>AW29,AS29-AW29,"0") -> 0 | BN29: =SUMIF($J:$J,J29,$BI:$BI) -> 0 | BO29: =SUMIF($J:$J,J29,$BJ:$BJ) -> 0 | CL29: =SUMIF($J:$J,J29,$BZ:$BZ) -> 0 | CM29: =SUMIF($J:$J,J29,$CA:$CA) -> 0 | CR29: =BN29+CL29 -> 0 | CS29: =BO29+CM29 -> 0 | CT29: =AZ29-CR29 -> 0 | CU29: =BA29-CS29 -> 0 | CV29: =IF(CT29<0,"Thừa",IF(CT29=0,"Đủ","Thiếu")) -> Đủ | DF29: 0.37045727 | DG29: 11.632358
A30: =IF(J30=J29,"ok","Hiện") -> Hiện | B30: =CV30 -> Thừa | C30: =CT30 -> -0.5 | H30: Thép đen | J30: I78-A-18 | K30: tôn tấm | L30: PL4x1500x6000 | M30: JIS G3101-SS400 | N30: m2 | O30: 31.4 | P30: 3.447056 | Q30: 108.23756 | T30: 4 | U30: 125.6 | V30: =VLOOKUP(J30,[113]PR!$A:$S,15,0) -> 0 | W30: =VLOOKUP(J30,[113]PR!$A:$S,16,0) -> 0 | X30: =VLOOKUP(J30,[114]PR!$A:$U,17,0) -> 0 | Y30: =VLOOKUP(J30,[114]PR!$A:$U,18,0) -> 0 | Z30: 0 | AA30: 0 | AB30: 0 | AC30: 0 | AD30: 0 | AE30: 0 | AF30: 0 | AG30: 0 | AH30: 0 | AI30: 0 | AJ30: 0 | AK30: 0 | AL30: 0 | AM30: 0 | AP30: 0 | AQ30: 0 | AR30: =R30+T30+V30+X30+Z30+AB30+AD30+AF30+AH30+AJ30+AL30+AN30+AP30 -> 4 | AS30: =S30+U30+W30+Y30+AA30+AC30+AE30+AG30+AI30+AK30+AM30+AO30+AQ30 -> 125.6 | AZ30: =IF(AR30>AV30,AR30-AV30,"0") -> 4 | BA30: =IF(AS30>AW30,AS30-AW30,"0") -> 125.6 | BC30: 030325HN-IBS | BD30: Hùng Nguyên | BE30: Thép tấm 4x1500x3000 | BF30: SS400 | BG30: 141.3 | BH30: 45719 | BI30: 4.5 | BJ30: 141.3 | BK30: 13181.82 | BL30: =BK30*BJ30*1.1 -> 2048850.3 | BM30: 45757 | BN30: =SUMIF($J:$J,J30,$BI:$BI) -> 4.5 | BO30: =SUMIF($J:$J,J30,$BJ:$BJ) -> 141.3 | BP30: ACC | CL30: =SUMIF($J:$J,J30,$BZ:$BZ) -> 0 | CM30: =SUMIF($J:$J,J30,$CA:$CA) -> 0 | CR30: =BN30+CL30 -> 4.5 | CS30: =BO30+CM30 -> 141.3 | CT30: =AZ30-CR30 -> -0.5 | CU30: =BA30-CS30 -> -15.7 | CV30: =IF(CT30<0,"Thừa",IF(CT30=0,"Đủ","Thiếu")) -> Thừa | DB30: 3.447056 | DC30: 108.23756
A31: =IF(J31=J30,"ok","Hiện") -> Hiện | B31: =CV31 -> Đủ | C31: =CT31 -> 0 | H31: Thép trắng nhập | J31: I78-A-19 | K31: tôn tấm( % C min 0.04%) | L31: PL5x1500x1200 | M31: ASTM-A240-TP304H | N31: m2 | O31: 39.65 | P31: 1.37408 | Q31: 54.482272 | T31: 1.8 | U31: 71.37 | V31: =VLOOKUP(J31,[113]PR!$A:$S,15,0) -> 0 | W31: =VLOOKUP(J31,[113]PR!$A:$S,16,0) -> 0 | X31: =VLOOKUP(J31,[114]PR!$A:$U,17,0) -> 0 | Y31: =VLOOKUP(J31,[114]PR!$A:$U,18,0) -> 0 | Z31: 0 | AA31: 0 | AB31: 0 | AC31: 0 | AD31: 0 | AE31: 0 | AF31: 0 | AG31: 0 | AH31: 0 | AI31: 0 | AJ31: 0 | AK31: 0 | AL31: 0 | AM31: 0 | AP31: 0 | AQ31: 0 | AR31: =R31+T31+V31+X31+Z31+AB31+AD31+AF31+AH31+AJ31+AL31+AN31+AP31 -> 1.8 | AS31: =S31+U31+W31+Y31+AA31+AC31+AE31+AG31+AI31+AK31+AM31+AO31+AQ31 -> 71.37 | AZ31: =IF(AR31>AV31,AR31-AV31,"0") -> 1.8 | BA31: =IF(AS31>AW31,AS31-AW31,"0") -> 71.37 | BN31: =SUMIF($J:$J,J31,$BI:$BI) -> 0 | BO31: =SUMIF($J:$J,J31,$BJ:$BJ) -> 0 | BT31: IBSHI-GNEE/2504-08 | BU31: GNEE | BV31: 5*1500*1200 | BW31: A240-TP304H PLATE | BX31: 71.4 | BY31: 45755 | BZ31: 1.8 | CA31: 71.4 | CB31: 2.88 | CC31: =CB31*CA31 -> 205.632 | CI31: 45791 | CJ31: 45792 | CL31: =SUMIF($J:$J,J31,$BZ:$BZ) -> 1.8 | CM31: =SUMIF($J:$J,J31,$CA:$CA) -> 71.4 | CR31: =BN31+CL31 -> 1.8 | CS31: =BO31+CM31 -> 71.4 | CT31: =AZ31-CR31 -> 0 | CU31: =BA31-CS31 -> -0.03 | CV31: =IF(CT31<0,"Thừa",IF(CT31=0,"Đủ","Thiếu")) -> Đủ | DF31: 1.3880834 | DG31: 54.482272
A32: =IF(J32=J31,"ok","Hiện") -> Hiện | B32: =CV32 -> Thừa | C32: =CT32 -> -2.2040886 | H32: Thép đen | J32: I78-A-20 | K32: tôn tấm | L32: PL5x1500x6000 | M32: JIS G3101-SS400 | N32: m2 | O32: 39.25 | P32: 1.9964447 | Q32: 78.360454 | T32: 2.2959114 | U32: 90.114522 | V32: =VLOOKUP(J32,[113]PR!$A:$S,15,0) -> 0 | W32: =VLOOKUP(J32,[113]PR!$A:$S,16,0) -> 0 | X32: =VLOOKUP(J32,[114]PR!$A:$U,17,0) -> 0 | Y32: =VLOOKUP(J32,[114]PR!$A:$U,18,0) -> 0 | Z32: 0 | AA32: 0 | AB32: 0 | AC32: 0 | AD32: 0 | AE32: 0 | AF32: 0 | AG32: 0 | AH32: 0 | AI32: 0 | AJ32: 0 | AK32: 0 | AL32: 0 | AM32: 0 | AP32: 0 | AQ32: 0 | AR32: =R32+T32+V32+X32+Z32+AB32+AD32+AF32+AH32+AJ32+AL32+AN32+AP32 -> 2.2959114 | AS32: =S32+U32+W32+Y32+AA32+AC32+AE32+AG32+AI32+AK32+AM32+AO32+AQ32 -> 90.114522 | AZ32: =IF(AR32>AV32,AR32-AV32,"0") -> 2.2959114 | BA32: =IF(AS32>AW32,AS32-AW32,"0") -> 90.114522 | BC32: 030325HN-IBS | BD32: Hùng Nguyên | BE32: Thép tấm 5x1500x3000 | BF32: SS400 | BG32: 176.63 | BH32: 45719 | BI32: 4.5 | BJ32: 176.63 | BK32: 13181.82 | BL32: =BK32*BJ32*1.1 -> 2561135.4 | BM32: 45757 | BN32: =SUMIF($J:$J,J32,$BI:$BI) -> 4.5 | BO32: =SUMIF($J:$J,J32,$BJ:$BJ) -> 176.63 | BP32: ACC | CL32: =SUMIF($J:$J,J32,$BZ:$BZ) -> 0 | CM32: =SUMIF($J:$J,J32,$CA:$CA) -> 0 | CR32: =BN32+CL32 -> 4.5 | CS32: =BO32+CM32 -> 176.63 | CT32: =AZ32-CR32 -> -2.2040886 | CU32: =BA32-CS32 -> -86.515478 | CV32: =IF(CT32<0,"Thừa",IF(CT32=0,"Đủ","Thiếu")) -> Thừa | DB32: 1.9964447 | DC32: 78.360454
A33: =IF(J33=J32,"ok","Hiện") -> Hiện | B33: =CV33 -> Đủ | C33: =CT33 -> 0 | H33: Thép trắng nhập | J33: I78-A-21 | K33: tôn tấm( % C min 0.04%) | L33: PL6x1500x6000 | M33: ASTM-A240-TP304H | N33: m2 | O33: 47.58 | P33: 5.5152768 | Q33: =250.8368696+11.58 -> 262.41687 | T33: 7.5 | U33: 356.85 | V33: =VLOOKUP(J33,[113]PR!$A:$S,15,0) -> 0 | W33: =VLOOKUP(J33,[113]PR!$A:$S,16,0) -> 0 | X33: =VLOOKUP(J33,[114]PR!$A:$U,17,0) -> 0 | Y33: =VLOOKUP(J33,[114]PR!$A:$U,18,0) -> 0 | Z33: 0 | AA33: 0 | AB33: 0 | AC33: 0 | AD33: 0 | AE33: 0 | AF33: 0 | AG33: 0 | AH33: 0 | AI33: 0 | AJ33: 0 | AK33: 0 | AL33: 0 | AM33: 0 | AP33: 0 | AQ33: 0 | AR33: =R33+T33+V33+X33+Z33+AB33+AD33+AF33+AH33+AJ33+AL33+AN33+AP33 -> 7.5 | AS33: =S33+U33+W33+Y33+AA33+AC33+AE33+AG33+AI33+AK33+AM33+AO33+AQ33 -> 356.85 | AZ33: =IF(AR33>AV33,AR33-AV33,"0") -> 7.5 | BA33: =IF(AS33>AW33,AS33-AW33,"0") -> 356.85 | BN33: =SUMIF($J:$J,J33,$BI:$BI) -> 0 | BO33: =SUMIF($J:$J,J33,$BJ:$BJ) -> 0 | BT33: IBSHI-GNEE/2504-08 | BU33: GNEE | BV33: 6*1500*5000 | BW33: A240-TP304H PLATE | BX33: 356.9 | BY33: 45755 | BZ33: 7.5 | CA33: 356.9 | CB33: 2.88 | CC33: =CB33*CA33 -> 1027.872 | CI33: 45791 | CJ33: 45792 | CL33: =SUMIF($J:$J,J33,$BZ:$BZ) -> 7.5 | CM33: =SUMIF($J:$J,J33,$CA:$CA) -> 356.9 | CR33: =BN33+CL33 -> 7.5 | CS33: =BO33+CM33 -> 356.9 | CT33: =AZ33-CR33 -> 0 | CU33: =BA33-CS33 -> -0.05 | CV33: =IF(CT33<0,"Thừa",IF(CT33=0,"Đủ","Thiếu")) -> Đủ | DF33: 5.2551352 | DG33: 247.51687 | DH33: 0.070488323 | DI33: 3.32
A34: =IF(J34=J33,"ok","Hiện") -> Hiện | B34: =CV34 -> Đủ | C34: =CT34 -> 0 | H34: Thép trắng nhập | J34: I78-A-22 | K34: tôn tấm( % C min 0.04%) | L34: PL6x1500x2500 | M34: ASTM-A240-TP310S | N34: m2 | O34: 46.5 | P34: 2.1713978 | Q34: 100.97 | T34: 3.75 | U34: 174.375 | V34: =VLOOKUP(J34,[113]PR!$A:$S,15,0) -> 0 | W34: =VLOOKUP(J34,[113]PR!$A:$S,16,0) -> 0 | X34: =VLOOKUP(J34,[114]PR!$A:$U,17,0) -> 0 | Y34: =VLOOKUP(J34,[114]PR!$A:$U,18,0) -> 0 | Z34: 0 | AA34: 0 | AB34: 0 | AC34: 0 | AD34: 0 | AE34: 0 | AF34: 0 | AG34: 0 | AH34: 0 | AI34: 0 | AJ34: 0 | AK34: 0 | AL34: 0 | AM34: 0 | AP34: 0 | AQ34: 0 | AR34: =R34+T34+V34+X34+Z34+AB34+AD34+AF34+AH34+AJ34+AL34+AN34+AP34 -> 3.75 | AS34: =S34+U34+W34+Y34+AA34+AC34+AE34+AG34+AI34+AK34+AM34+AO34+AQ34 -> 174.375 | AZ34: =IF(AR34>AV34,AR34-AV34,"0") -> 3.75 | BA34: =IF(AS34>AW34,AS34-AW34,"0") -> 174.375 | BN34: =SUMIF($J:$J,J34,$BI:$BI) -> 0 | BO34: =SUMIF($J:$J,J34,$BJ:$BJ) -> 0 | BT34: IBSHI-GNEE/2504-08 | BU34: GNEE | BV34: 6*1500*2500 | BW34: A240-TP310S PLATE | BX34: 180 | BY34: 45755 | BZ34: 3.75 | CA34: 180 | CB34: 6.11 | CC34: =CB34*CA34 -> 1099.8 | CI34: 45791 | CJ34: 45792 | CL34: =SUMIF($J:$J,J34,$BZ:$BZ) -> 3.75 | CM34: =SUMIF($J:$J,J34,$CA:$CA) -> 180 | CR34: =BN34+CL34 -> 3.75 | CS34: =BO34+CM34 -> 180 | CT34: =AZ34-CR34 -> 0 | CU34: =BA34-CS34 -> -5.625 | CV34: =IF(CT34<0,"Thừa",IF(CT34=0,"Đủ","Thiếu")) -> Đủ | DB34: 1.8980359 | DC34: 89.397491 | DD34: 0.24585987 | DE34: 11.58
A35: =IF(J35=J34,"ok","Hiện") -> Hiện | B35: =CV35 -> Đủ | C35: =CT35 -> 0 | H35: Thép đen | J35: I78-A-23 | K35: tôn tấm | L35: PL6x500x1000 | M35: A387-GR22 | N35: m2 | O35: 47.1 | P35: 0.3 | Q35: 14.13 | T35: 0.5 | U35: 23.55 | V35: =VLOOKUP(J35,[113]PR!$A:$S,15,0) -> -0.5 | W35: -23.55 | X35: =VLOOKUP(J35,[114]PR!$A:$U,17,0) -> 0 | Y35: =VLOOKUP(J35,[114]PR!$A:$U,18,0) -> 0 | Z35: 0 | AA35: 0 | AB35: 0 | AC35: 0 | AD35: 0 | AE35: 0 | AF35: 0 | AG35: 0 | AH35: 0 | AI35: 0 | AJ35: 0 | AK35: 0 | AL35: 0 | AM35: 0 | AP35: 0 | AQ35: 0 | AR35: =R35+T35+V35+X35+Z35+AB35+AD35+AF35+AH35+AJ35+AL35+AN35+AP35 -> 0 | AS35: =S35+U35+W35+Y35+AA35+AC35+AE35+AG35+AI35+AK35+AM35+AO35+AQ35 -> 0 | AT35: REV2-VOGT CẤP | AZ35: =IF(AR35>AV35,AR35-AV35,"0") -> 0 | BA35: =IF(AS35>AW35,AS35-AW35,"0") -> 0 | BN35: =SUMIF($J:$J,J35,$BI:$BI) -> 0 | BO35: =SUMIF($J:$J,J35,$BJ:$BJ) -> 0 | CL35: =SUMIF($J:$J,J35,$BZ:$BZ) -> 0 | CM35: =SUMIF($J:$J,J35,$CA:$CA) -> 0 | CR35: =BN35+CL35 -> 0 | CS35: =BO35+CM35 -> 0 | CT35: =AZ35-CR35 -> 0 | CU35: =BA35-CS35 -> 0 | CV35: =IF(CT35<0,"Thừa",IF(CT35=0,"Đủ","Thiếu")) -> Đủ | DZ35: 0.3 | EA35: 14.13
A36: =IF(J36=J35,"ok","Hiện") -> Hiện | B36: =CONCATENATE(CV36," Mua đủ theo Pr") -> Thiếu Mua đủ theo Pr | C36: =CT36 -> 8.4981285 | H36: Thép đen | J36: I78-A-24 | K36: tôn tấm | L36: PL6-cuộn | M36: JIS G3101-SS400 | N36: m2 | O36: 47.1 | P36: 1896.724 | Q36: 89335.701 | T36: 2143.2981 | U36: 100949.34 | V36: =VLOOKUP(J36,[113]PR!$A:$S,15,0) -> 0 | W36: =VLOOKUP(J36,[113]PR!$A:$S,16,0) -> 0 | X36: =VLOOKUP(J36,[114]PR!$A:$U,17,0) -> 0 | Y36: =VLOOKUP(J36,[114]PR!$A:$U,18,0) -> 0 | Z36: 0 | AA36: 0 | AB36: 0 | AC36: 0 | AD36: 0 | AE36: 0 | AF36: 0 | AG36: 0 | AH36: 0 | AI36: 0 | AJ36: 0 | AK36: 0 | AL36: 0 | AM36: 0 | AP36: 0 | AQ36: 0 | AR36: =R36+T36+V36+X36+Z36+AB36+AD36+AF36+AH36+AJ36+AL36+AN36+AP36 -> 2143.2981 | AS36: =S36+U36+W36+Y36+AA36+AC36+AE36+AG36+AI36+AK36+AM36+AO36+AQ36 -> 100949.34 | AT36: (REV4-KHỔ TÔN) PL6x2000x12000-45 TỜ PL6x1500x12600-28 TỜ PL6x1500X9400-8 TỜ PL6x2000x12900-16 TỜ | AZ36: =IF(AR36>AV36,AR36-AV36,"0") -> 2143.2981 | BA36: =IF(AS36>AW36,AS36-AW36,"0") -> 100949.34 | BC36: 030325HN-IBS | BD36: Hùng Nguyên | BE36: Thép tấm 6x2000x12000 | BF36: SS400 | BG36: 50868 | BH36: 45719 | BI36: 1080 | BJ36: 50868 | BK36: 13363.64 | BL36: =BK36*BJ36*1.1 -> 7.477598e+08 | BM36: 45757 | BN36: =SUMIF($J:$J,J36,$BI:$BI) -> 2134.8 | BO36: =SUMIF($J:$J,J36,$BJ:$BJ) -> 100549.08 | BP36: ACC | CL36: =SUMIF($J:$J,J36,$BZ:$BZ) -> 0 | CM36: =SUMIF($J:$J,J36,$CA:$CA) -> 0 | CR36: =BN36+CL36 -> 2134.8 | CS36: =BO36+CM36 -> 100549.08 | CT36: =AZ36-CR36 -> 8.4981285 | CU36: =BA36-CS36 -> 400.26185 | CV36: =IF(CT36<0,"Thừa",IF(CT36=0,"Đủ","Thiếu")) -> Thiếu | DB36: 1.3151001 | DC36: 61.941217 | DD36: 495.10955 | DE36: 23319.66 | DF36: 0.62016 | DG36: 29.209536 | DH36: 706.96943 | DI36: 33298.26 | DJ36: 108.66667 | DK36: 5118.2 | DL36: 107.50573 | DM36: 5063.52 | DN36: 107.3448 | DO36: 5055.94 | DP36: 153.85478 | DQ36: 7246.56 | DR36: 53.32017 | DS36: 2511.38 | DT36: 159.52527 | DU36: 7513.64 | DV36: 1.2008493 | DW36: 56.56 | DZ36: 0.5 | EA36: 23.55
A37: =IF(J37=J36,"ok","Hiện") -> ok | H37: Thép đen | J37: I78-A-24 | K37: tôn tấm | L37: PL6-cuộn | M37: JIS G3101-SS400 | N37: m2 | BC37: 150425HN-IBS | BD37: Hùng Nguyên | BE37: Thép tấm 6x1500x12600 | BF37: SS400 | BG37: 24925.32 | BH37: 45762 | BI37: =1.5*12.6*28 -> 529.2 | BJ37: 24925.32 | BK37: 13090.91 | BL37: =BK37*BJ37*1.1 -> 3.5892463e+08 | BM37: 45765 | BP37: ACC
A38: =IF(J38=J37,"ok","Hiện") -> ok | H38: Thép đen | J38: I78-A-24 | K38: tôn tấm | L38: PL6-cuộn | M38: JIS G3101-SS400 | N38: m2 | BC38: 150425HN-IBS | BD38: Hùng Nguyên | BE38: Thép tấm 6x1500x9400 | BF38: SS400 | BG38: 5312.88 | BH38: 45762 | BI38: =1.5*9.4*8 -> 112.8 | BJ38: 5312.88 | BK38: 13090.91 | BL38: =BK38*BJ38*1.1 -> 76505477 | BM38: 45765 | BP38: ACC
A39: =IF(J39=J38,"ok","Hiện") -> ok | H39: Thép đen | J39: I78-A-24 | K39: tôn tấm | L39: PL6-cuộn | M39: JIS G3101-SS400 | N39: m2 | BC39: 150425HN-IBS | BD39: Hùng Nguyên | BE39: Thép tấm 6x2000x12900 | BF39: SS400 | BG39: 19442.88 | BH39: 45762 | BI39: =2*12.9*16 -> 412.8 | BJ39: 19442.88 | BK39: 13181.82 | BL39: =BK39*BJ39*1.1 -> 2.819218e+08 | BM39: 45765 | BP39: ACC
A40: =IF(J40=J39,"ok","Hiện") -> Hiện | B40: =CV40 -> Đủ | C40: =CT40 -> 0 | H40: Thép đen | J40: I78-A-25 | K40: tôn tấm cuộn | L40: PL6-cuộn | M40: JIS G3101-SS400 | N40: m2 | O40: 47.1 | P40: 488.16985 | Q40: 22992.8 | T40: 510.3 | U40: 24035.13 | V40: =VLOOKUP(J40,[113]PR!$A:$S,15,0) -> 0 | W40: =VLOOKUP(J40,[113]PR!$A:$S,16,0) -> 0 | X40: =VLOOKUP(J40,[114]PR!$A:$U,17,0) -> 0 | Y40: =VLOOKUP(J40,[114]PR!$A:$U,18,0) -> 0 | Z40: 0 | AA40: 0 | AB40: 0 | AC40: 0 | AD40: 0 | AE40: 0 | AF40: 0 | AG40: 0 | AH40: 0 | AI40: 0 | AJ40: 0 | AK40: 0 | AL40: 0 | AM40: 0 | AP40: 0 | AQ40: 0 | AR40: =R40+T40+V40+X40+Z40+AB40+AD40+AF40+AH40+AJ40+AL40+AN40+AP40 -> 510.3 | AS40: =S40+U40+W40+Y40+AA40+AC40+AE40+AG40+AI40+AK40+AM40+AO40+AQ40 -> 24035.13 | AT40: 27 tờ PL6X1500x12600 | AZ40: =IF(AR40>AV40,AR40-AV40,"0") -> 510.3 | BA40: =IF(AS40>AW40,AS40-AW40,"0") -> 24035.13 | BC40: 030325HN-IBS | BD40: Hùng Nguyên | BE40: Thép tấm 6x1500x12600 | BF40: SS400 | BG40: 16023.42 | BH40: 45719 | BI40: 340.2 | BJ40: 16023.42 | BK40: 13181.82 | BL40: =BK40*BJ40*1.1 -> 2.3233962e+08 | BM40: 45751 | BN40: =SUMIF($J:$J,J40,$BI:$BI) -> 510.3 | BO40: =SUMIF($J:$J,J40,$BJ:$BJ) -> 24035.13 | BP40: ACC | CL40: =SUMIF($J:$J,J40,$BZ:$BZ) -> 0 | CM40: =SUMIF($J:$J,J40,$CA:$CA) -> 0 | CR40: =BN40+CL40 -> 510.3 | CS40: =BO40+CM40 -> 24035.13 | CT40: =AZ40-CR40 -> 0 | CU40: =BA40-CS40 -> 0 | CV40: =IF(CT40<0,"Thừa",IF(CT40=0,"Đủ","Thiếu")) -> Đủ | DR40: 488.16985 | DS40: 22992.8
A41: =IF(J41=J40,"ok","Hiện") -> ok | H41: Thép đen | J41: I78-A-25 | K41: tôn tấm cuộn | L41: PL6-cuộn | M41: JIS G3101-SS400 | N41: m2 | BC41: 150425HN-IBS | BD41: Hùng Nguyên | BE41: Thép tấm 6x1500x12600 | BF41: SS400 | BG41: 8011.71 | BH41: 45762 | BI41: =9*1.5*12.6 -> 170.1 | BJ41: 8011.71 | BK41: 13090.91 | BL41: =BK41*BJ41*1.1 -> 1.1536863e+08 | BM41: 45765 | BP41: ACC
A42: =IF(J42=J41,"ok","Hiện") -> Hiện | B42: =CV42 -> Thừa | C42: =CT42 -> -4 | H42: Thép đen | J42: I78-A-26 | K42: tôn nhám | L42: TÔN NHÁM CPL6x1500x6000 | M42: JIS G3101-SS400 | N42: m2 | O42: 50.1 | P42: 57.458211 | Q42: 2878.6564 | T42: 72 | U42: 3607.2 | V42: =VLOOKUP(J42,[113]PR!$A:$S,15,0) -> 0 | W42: =VLOOKUP(J42,[113]PR!$A:$S,16,0) -> 0 | X42: =VLOOKUP(J42,[114]PR!$A:$U,17,0) -> 0 | Y42: =VLOOKUP(J42,[114]PR!$A:$U,18,0) -> 0 | Z42: 0 | AA42: 0 | AB42: 0 | AC42: 0 | AD42: 0 | AE42: 0 | AF42: 0 | AG42: 0 | AH42: 5 | AI42: 250.5 | AJ42: 0 | AK42: 0 | AL42: 0 | AM42: 0 | AP42: 0 | AQ42: 0 | AR42: =R42+T42+V42+X42+Z42+AB42+AD42+AF42+AH42+AJ42+AL42+AN42+AP42 -> 77 | AS42: =S42+U42+W42+Y42+AA42+AC42+AE42+AG42+AI42+AK42+AM42+AO42+AQ42 -> 3857.7 | AT42: REV8-IBS REV | AZ42: =IF(AR42>AV42,AR42-AV42,"0") -> 77 | BA42: =IF(AS42>AW42,AS42-AW42,"0") -> 3857.7 | BC42: 030325HN-IBS | BD42: Hùng Nguyên | BE42: Thép tấm nhám 6x1500x6000 | BF42: SS400 | BG42: 1803.6 | BH42: 45719 | BI42: 36 | BJ42: 1803.6 | BK42: 13909.09 | BL42: =BK42*BJ42*1.1 -> 27595078 | BM42: 45751 | BN42: =SUMIF($J:$J,J42,$BI:$BI) -> 81 | BO42: =SUMIF($J:$J,J42,$BJ:$BJ) -> 4058.1 | BP42: ACC | CL42: =SUMIF($J:$J,J42,$BZ:$BZ) -> 0 | CM42: =SUMIF($J:$J,J42,$CA:$CA) -> 0 | CR42: =BN42+CL42 -> 81 | CS42: =BO42+CM42 -> 4058.1 | CT42: =AZ42-CR42 -> -4 | CU42: =BA42-CS42 -> -200.4 | CV42: =IF(CT42<0,"Thừa",IF(CT42=0,"Đủ","Thiếu")) -> Thừa | DB42: 55.954912 | DC42: 2635.4764 | DT42: 5.166879 | DU42: 243.36
A43: =IF(J43=J42,"ok","Hiện") -> ok | H43: Thép đen | J43: I78-A-26 | K43: tôn nhám | L43: TÔN NHÁM CPL6x1500x6000 | M43: JIS G3101-SS400 | N43: m2 | BC43: 150425HN-IBS | BD43: Hùng Nguyên | BE43: Thép tấm nhám 6x1500x6000 | BF43: SS400 | BG43: 1803.6 | BH43: 45762 | BI43: =4*9 -> 36 | BJ43: 1803.6 | BK43: 13909.09 | BL43: =BK43*BJ43*1.1 -> 27595078 | BM43: 45765 | BP43: ACC
A44: =IF(J44=J43,"ok","Hiện") -> ok | J44: I78-A-26 | K44: tôn nhám | L44: TÔN NHÁM CPL6x1500x6000 | M44: JIS G3101-SS400 | N44: m2 | BD44: Hùng Nguyên | BE44: Thép tấm nhám 6x1500x6000 | BF44: SS400 | BG44: 450.9 | BH44: 45937 | BI44: 9 | BJ44: 450.9 | BK44: 13636.6 | BL44: =BK44*BJ44*1.1 -> 6763617.2 | BM44: 45943
A45: =IF(J45=J44,"ok","Hiện") -> Hiện | B45: =CONCATENATE(CV45," Thiếu do tính") -> Thiếu Thiếu do tính | C45: =CT45 -> 2.004 | H45: Thép đen | J45: I78-A-27 | K45: tôn tấm | L45: PL8x2000x6000 | M45: JIS G3101-SS400 | N45: m2 | O45: 62.8 | P45: 50.2 | Q45: 3152.56 | T45: 56.224 | U45: 3530.8672 | V45: =VLOOKUP(J45,[113]PR!$A:$S,15,0) -> 0 | W45: =VLOOKUP(J45,[113]PR!$A:$S,16,0) -> 0 | X45: =VLOOKUP(J45,[114]PR!$A:$U,17,0) -> 0 | Y45: =VLOOKUP(J45,[114]PR!$A:$U,18,0) -> 0 | Z45: 0 | AA45: 0 | AB45: 0 | AC45: 0 | AD45: 0 | AE45: 0 | AF45: 0 | AG45: 0 | AH45: 2 | AI45: 125.6 | AJ45: 0 | AK45: 0 | AL45: 0 | AM45: 0 | AP45: 0 | AQ45: 0 | AR45: =R45+T45+V45+X45+Z45+AB45+AD45+AF45+AH45+AJ45+AL45+AN45+AP45 -> 58.224 | AS45: =S45+U45+W45+Y45+AA45+AC45+AE45+AG45+AI45+AK45+AM45+AO45+AQ45 -> 3656.4672 | AT45: REV8-IBS REV | AZ45: =IF(AR45>AV45,AR45-AV45,"0") -> 58.224 | BA45: =IF(AS45>AW45,AS45-AW45,"0") -> 3656.4672 | BC45: 030325HN-IBS | BD45: Hùng Nguyên | BE45: Thép tấm 8x2000x6000 | BF45: SS400 | BG45: 3014.4 | BH45: 45719 | BI45: 48 | BJ45: 3014.4 | BK45: 13363.64 | BL45: =BK45*BJ45*1.1 -> 44311692 | BM45: 45751 | BN45: =SUMIF($J:$J,J45,$BI:$BI) -> 56.22 | BO45: =SUMIF($J:$J,J45,$BJ:$BJ) -> 3530.62 | BP45: ACC | CL45: =SUMIF($J:$J,J45,$BZ:$BZ) -> 0 | CM45: =SUMIF($J:$J,J45,$CA:$CA) -> 0 | CR45: =BN45+CL45 -> 56.22 | CS45: =BO45+CM45 -> 3530.62 | CT45: =AZ45-CR45 -> 2.004 | CU45: =BA45-CS45 -> 125.8472 | CV45: =IF(CT45<0,"Thừa",IF(CT45=0,"Đủ","Thiếu")) -> Thiếu | DB45: 12.15 | DC45: 763.02 | DH45: 0.91050955 | DI45: 57.18 | DR45: 35.785987 | DS45: 2247.36 | DT45: 1.3535032 | DU45: 85
A46: =IF(J46=J45,"ok","Hiện") -> ok | H46: Thép đen | J46: I78-A-27 | K46: tôn tấm | L46: PL8x2000x6000 | M46: JIS G3101-SS400 | N46: m2 | O46: 62.8 | P46: 50.2 | Q46: 3152.56 | BC46: 030325HN-IBS | BD46: Hùng Nguyên | BE46: Thép tấm 8x2000x4110 | BF46: SS400 | BG46: 516.22 | BH46: 45719 | BI46: 8.22 | BJ46: 516.22 | BK46: 13363.64 | BL46: =BK46*BJ46*1.1 -> 7588436.1 | BM46: 45757 | BP46: ACC
A47: =IF(J47=J46,"ok","Hiện") -> Hiện | B47: =CV47 -> Đủ | C47: =CT47 -> 0 | H47: Thép đen | J47: I78-A-28 | K47: tôn tấm cuộn | L47: PL8-cuộn | M47: JIS G3101-SS400 | N47: m2 | O47: 62.8 | P47: 378.38567 | Q47: 23762.62 | T47: 395.7 | U47: 24849.96 | V47: =VLOOKUP(J47,[113]PR!$A:$S,15,0) -> 0 | W47: =VLOOKUP(J47,[113]PR!$A:$S,16,0) -> 0 | X47: =VLOOKUP(J47,[114]PR!$A:$U,17,0) -> 0 | Y47: =VLOOKUP(J47,[114]PR!$A:$U,18,0) -> 0 | Z47: 0 | AA47: 0 | AB47: 0 | AC47: 0 | AD47: 0 | AE47: 0 | AF47: 0 | AG47: 0 | AH47: 0 | AI47: 0 | AJ47: 0 | AK47: 0 | AL47: 0 | AM47: 0 | AP47: 0 | AQ47: 0 | AR47: =R47+T47+V47+X47+Z47+AB47+AD47+AF47+AH47+AJ47+AL47+AN47+AP47 -> 395.7 | AS47: =S47+U47+W47+Y47+AA47+AC47+AE47+AG47+AI47+AK47+AM47+AO47+AQ47 -> 24849.96 | AT47: 04 tờ PL8X1500x12600 22 tờ PL8x1500x9700 | AZ47: =IF(AR47>AV47,AR47-AV47,"0") -> 395.7 | BA47: =IF(AS47>AW47,AS47-AW47,"0") -> 24849.96 | BC47: 030325HN-IBS | BD47: Hùng Nguyên | BE47: Thép tấm 8x1500x12600 | BF47: SS400 | BG47: 4747.68 | BH47: 45719 | BI47: 75.6 | BJ47: 4747.68 | BK47: 13181.82 | BL47: =BK47*BJ47*1.1 -> 68841369 | BM47: 45752 | BN47: =SUMIF($J:$J,J47,$BI:$BI) -> 395.7 | BO47: =SUMIF($J:$J,J47,$BJ:$BJ) -> 24849.96 | BP47: ACC | CL47: =SUMIF($J:$J,J47,$BZ:$BZ) -> 0 | CM47: =SUMIF($J:$J,J47,$CA:$CA) -> 0 | CR47: =BN47+CL47 -> 395.7 | CS47: =BO47+CM47 -> 24849.96 | CT47: =AZ47-CR47 -> 0 | CU47: =BA47-CS47 -> 0 | CV47: =IF(CT47<0,"Thừa",IF(CT47=0,"Đủ","Thiếu")) -> Đủ | DR47: 378.38567 | DS47: 23762.62
A48: =IF(J48=J47,"ok","Hiện") -> ok | H48: Thép đen | J48: I78-A-28 | K48: tôn tấm cuộn | L48: PL8-cuộn | M48: JIS G3101-SS400 | N48: m2 | BC48: 150425HN-IBS | BD48: Hùng Nguyên | BE48: Thép tấm 8x1500x9700 | BF48: SS400 | BG48: 9137.4 | BH48: 45762 | BI48: =10*1.5*9.7 -> 145.5 | BJ48: 9137.4 | BK48: 13181.82 | BL48: =BK48*BJ48*1.1 -> 1.3249232e+08 | BM48: 45765 | BP48: ACC
A49: =IF(J49=J48,"ok","Hiện") -> ok | H49: Thép đen | J49: I78-A-28 | K49: tôn tấm cuộn | L49: PL8-cuộn | M49: JIS G3101-SS400 | N49: m2 | O49: 62.8 | P49: 378.38567 | Q49: 23762.62 | BC49: 030325HN-IBS | BD49: Hùng Nguyên | BE49: Thép tấm 8x1500x9700 | BF49: SS400 | BG49: 10964.88 | BH49: 45719 | BI49: 174.6 | BJ49: 10964.88 | BK49: 13181.82 | BL49: =BK49*BJ49*1.1 -> 1.5899078e+08 | BM49: 45752 | BP49: ACC
A50: =IF(J50=J49,"ok","Hiện") -> Hiện | B50: =CV50 -> Đủ | C50: =CT50 -> 0 | E50: GNEE đã chốt đơn 2 | H50: Thép trắng nhập | J50: I78-A-29 | K50: tôn tấm( % C min 0.04%) | L50: PL10x1500x800 | M50: ASTM-A240-TP304H | N50: m2 | O50: 79.3 | P50: 0.83973296 | Q50: 66.590824 | T50: 1.2 | U50: 95.16 | V50: =VLOOKUP(J50,[113]PR!$A:$S,15,0) -> 0 | W50: =VLOOKUP(J50,[113]PR!$A:$S,16,0) -> 0 | X50: =VLOOKUP(J50,[114]PR!$A:$U,17,0) -> 0 | Y50: =VLOOKUP(J50,[114]PR!$A:$U,18,0) -> 0 | Z50: 0 | AA50: 0 | AB50: 0 | AC50: 0 | AD50: 0 | AE50: 0 | AF50: 0 | AG50: 0 | AH50: 0 | AI50: 0 | AJ50: 0 | AK50: 0 | AL50: 0 | AM50: 0 | AP50: 0 | AQ50: 0 | AR50: =R50+T50+V50+X50+Z50+AB50+AD50+AF50+AH50+AJ50+AL50+AN50+AP50 -> 1.2 | AS50: =S50+U50+W50+Y50+AA50+AC50+AE50+AG50+AI50+AK50+AM50+AO50+AQ50 -> 95.16 | AZ50: =IF(AR50>AV50,AR50-AV50,"0") -> 1.2 | BA50: =IF(AS50>AW50,AS50-AW50,"0") -> 95.16 | BN50: =SUMIF($J:$J,J50,$BI:$BI) -> 0 | BO50: =SUMIF($J:$J,J50,$BJ:$BJ) -> 0 | BT50: IBSHI-GNEE/2504-08 | BU50: GNEE | BV50: 10*1500*800 | BW50: A240-TP304H PLATE | BX50: 478.8 | BY50: 45755 | BZ50: 1.2 | CA50: 478.8 | CB50: 2.88 | CC50: =CB50*CA50 -> 1378.944 | CI50: 45791 | CJ50: 45792 | CL50: =SUMIF($J:$J,J50,$BZ:$BZ) -> 1.2 | CM50: =SUMIF($J:$J,J50,$CA:$CA) -> 478.8 | CR50: =BN50+CL50 -> 1.2 | CS50: =BO50+CM50 -> 478.8 | CT50: =AZ50-CR50 -> 0 | CU50: =BA50-CS50 -> -383.64 | CV50: =IF(CT50<0,"Thừa",IF(CT50=0,"Đủ","Thiếu")) -> Đủ | DF50: 0.64013789 | DG50: 50.250824 | DH50: 0.20815287 | DI50: 16.34
A51: =IF(J51=J50,"ok","Hiện") -> Hiện | B51: =CV51 -> Đủ | C51: =CT51 -> 0 | H51: Thép đen | J51: I78-A-30 | K51: tôn tấm | L51: PL10x1500x6000 | M51: ASTM-A572-GR.50 | N51: m2 | O51: 78.5 | P51: 5.4397452 | Q51: 427.02 | T51: 6.75 | U51: 529.875 | V51: =VLOOKUP(J51,[113]PR!$A:$S,15,0) -> 0 | W51: =VLOOKUP(J51,[113]PR!$A:$S,16,0) -> 0 | X51: =VLOOKUP(J51,[114]PR!$A:$U,17,0) -> 0 | Y51: =VLOOKUP(J51,[114]PR!$A:$U,18,0) -> 0 | Z51: 0 | AA51: 0 | AB51: 0 | AC51: 0 | AD51: 0 | AE51: 0 | AF51: 0 | AG51: 0 | AH51: 0 | AI51: 0 | AJ51: 0 | AK51: 0 | AL51: 0 | AM51: 0 | AP51: 0 | AQ51: 0 | AR51: =R51+T51+V51+X51+Z51+AB51+AD51+AF51+AH51+AJ51+AL51+AN51+AP51 -> 6.75 | AS51: =S51+U51+W51+Y51+AA51+AC51+AE51+AG51+AI51+AK51+AM51+AO51+AQ51 -> 529.875 | AZ51: =IF(AR51>AV51,AR51-AV51,"0") -> 6.75 | BA51: =IF(AS51>AW51,AS51-AW51,"0") -> 529.875 | BB51: 45762 | BC51: 030325HN-IBS | BD51: Hùng Nguyên | BE51: Thép tấm 10x1500x4500 | BF51: Q355B | BG51: 529.88 | BH51: 45719 | BI51: 6.75 | BJ51: 529.88 | BK51: 13818.18 | BL51: =BK51*BJ51*1.1 -> 8054174.9 | BM51: 45750 | BN51: =SUMIF($J:$J,J51,$BI:$BI) -> 6.75 | BO51: =SUMIF($J:$J,J51,$BJ:$BJ) -> 529.88 | BP51: ACC | CL51: =SUMIF($J:$J,J51,$BZ:$BZ) -> 0 | CM51: =SUMIF($J:$J,J51,$CA:$CA) -> 0 | CR51: =BN51+CL51 -> 6.75 | CS51: =BO51+CM51 -> 529.88 | CT51: =AZ51-CR51 -> 0 | CU51: =BA51-CS51 -> -0.005 | CV51: =IF(CT51<0,"Thừa",IF(CT51=0,"Đủ","Thiếu")) -> Đủ | DH51: 5.4397452 | DI51: 427.02
A52: =IF(J52=J51,"ok","Hiện") -> Hiện | B52: =CV52 -> Thừa | C52: =CT52 -> -0.13194904 | E52: GNEE đã chốt đơn 2 | H52: Thép trắng nhập | J52: I78-A-31 | K52: tôn tấm( % C min 0.04%) | L52: PL10x1500x6000 | M52: JIS.G4304_SUS310S | N52: m2 | O52: 77.5 | P52: 4.572129 | Q52: 354.34 | T52: 5.868051 | U52: 454.77395 | V52: =VLOOKUP(J52,[113]PR!$A:$S,15,0) -> 0 | W52: =VLOOKUP(J52,[113]PR!$A:$S,16,0) -> 0 | X52: =VLOOKUP(J52,[114]PR!$A:$U,17,0) -> 0 | Y52: =VLOOKUP(J52,[114]PR!$A:$U,18,0) -> 0 | Z52: 0 | AA52: 0 | AB52: 0 | AC52: 0 | AD52: 0 | AE52: 0 | AF52: 0 | AG52: 0 | AH52: 0 | AI52: 0 | AJ52: 0 | AK52: 0 | AL52: 0 | AM52: 0 | AP52: 0 | AQ52: 0 | AR52: =R52+T52+V52+X52+Z52+AB52+AD52+AF52+AH52+AJ52+AL52+AN52+AP52 -> 5.868051 | AS52: =S52+U52+W52+Y52+AA52+AC52+AE52+AG52+AI52+AK52+AM52+AO52+AQ52 -> 454.77395 | AZ52: =IF(AR52>AV52,AR52-AV52,"0") -> 5.868051 | BA52: =IF(AS52>AW52,AS52-AW52,"0") -> 454.77395 | BN52: =SUMIF($J:$J,J52,$BI:$BI) -> 0 | BO52: =SUMIF($J:$J,J52,$BJ:$BJ) -> 0 | BT52: IBSHI-GNEE/2504-08 | BU52: GNEE | BV52: 10*1500*4000 | BW52: SUS310S PLATE | BX52: 478.8 | BY52: 45755 | BZ52: 6 | CA52: 478.8 | CB52: 6.11 | CC52: =CB52*CA52 -> 2925.468 | CI52: 45791 | CJ52: 45792 | CL52: =SUMIF($J:$J,J52,$BZ:$BZ) -> 6 | CM52: =SUMIF($J:$J,J52,$CA:$CA) -> 478.8 | CR52: =BN52+CL52 -> 6 | CS52: =BO52+CM52 -> 478.8 | CT52: =AZ52-CR52 -> -0.13194904 | CU52: =BA52-CS52 -> -24.026051 | CV52: =IF(CT52<0,"Thừa",IF(CT52=0,"Đủ","Thiếu")) -> Thừa | DD52: 4.5138854 | DE52: 354.34
A53: =IF(J53=J52,"ok","Hiện") -> Hiện | B53: =CV53 -> Thừa | C53: =CT53 -> -0.0023315873 | H53: Thép đen | J53: I78-A-32 | K53: tôn tấm | L53: PL10x2000x12000 | M53: JIS G3101-SS400 | N53: m2 | O53: 78.5 | P53: 200.41231 | Q53: 15732.367 | T53: 222.45767 | U53: 17462.927 | V53: =VLOOKUP(J53,[113]PR!$A:$S,15,0) -> 0 | W53: =VLOOKUP(J53,[113]PR!$A:$S,16,0) -> 0 | X53: =VLOOKUP(J53,[114]PR!$A:$U,17,0) -> 0 | Y53: =VLOOKUP(J53,[114]PR!$A:$U,18,0) -> 0 | Z53: 0 | AA53: 0 | AB53: 18 | AC53: 1413 | AD53: 0 | AE53: 0 | AF53: 0 | AG53: 0 | AH53: 0 | AI53: 0 | AJ53: 0 | AK53: 0 | AL53: 0 | AM53: 0 | AP53: 0 | AQ53: 0 | AR53: =R53+T53+V53+X53+Z53+AB53+AD53+AF53+AH53+AJ53+AL53+AN53+AP53 -> 240.45767 | AS53: =S53+U53+W53+Y53+AA53+AC53+AE53+AG53+AI53+AK53+AM53+AO53+AQ53 -> 18875.927 | AT53: REV5-IBD REV | AZ53: =IF(AR53>AV53,AR53-AV53,"0") -> 240.45767 | BA53: =IF(AS53>AW53,AS53-AW53,"0") -> 18875.927 | BB53: 45762 | BC53: 030325HN-IBS | BD53: Hùng Nguyên | BE53: Thép tấm 10x2000x12000 | BF53: SS400 | BG53: 16956 | BH53: 45719 | BI53: 216 | BJ53: 16956 | BK53: 13272.73 | BL53: =BK53*BJ53*1.1 -> 2.4755765e+08 | BM53: 45750 | BN53: =SUMIF($J:$J,J53,$BI:$BI) -> 240.46 | BO53: =SUMIF($J:$J,J53,$BJ:$BJ) -> 18876.11 | BP53: ACC | CL53: =SUMIF($J:$J,J53,$BZ:$BZ) -> 0 | CM53: =SUMIF($J:$J,J53,$CA:$CA) -> 0 | CR53: =BN53+CL53 -> 240.46 | CS53: =BO53+CM53 -> 18876.11 | CT53: =AZ53-CR53 -> -0.0023315873 | CU53: =BA53-CS53 -> -0.1830296 | CV53: =IF(CT53<0,"Thừa",IF(CT53=0,"Đủ","Thiếu")) -> Thừa | CX53: 12.05104 | CY53: 946.00664 | DD53: 9.3926115 | DE53: 737.32 | DH53: 25.215541 | DI53: 1979.42 | DJ53: 9.6221656 | DK53: 755.34 | DL53: 9.6208917 | DM53: 755.24 | DN53: 9.6170701 | DO53: 754.94 | DP53: 4.3877707 | DQ53: 344.44 | DR53: 28.909809 | DS53: 2269.42 | DT53: 91.503185 | DU53: 7183
A54: =IF(J54=J53,"ok","Hiện") -> ok | H54: Thép đen | J54: I78-A-32 | K54: tôn tấm | L54: PL10x2000x12000 | M54: JIS G3101-SS400 | N54: m2 | O54: 78.5 | P54: 200.41231 | Q54: 15732.367 | BC54: 030325HN-IBS | BD54: Hùng Nguyên | BE54: Thép tấm 10x2000x4310 | BF54: SS400 | BG54: 676.67 | BH54: 45719 | BI54: 8.62 | BJ54: 676.67 | BK54: 13272.73 | BL54: =BK54*BJ54*1.1 -> 9879384 | BM54: 45750 | BP54: ACC
A55: =IF(J55=J54,"ok","Hiện") -> ok | H55: Thép đen | J55: I78-A-32 | K55: tôn tấm | L55: PL10x2000x12000 | M55: JIS G3101-SS400 | N55: m2 | BC55: 050625/HN-IBS | BD55: Hùng Nguyên | BE55: Thép tấm 10x2000x7920 | BF55: SS400 | BG55: 1243.44 | BH55: 45813 | BI55: =2*7.92 -> 15.84 | BJ55: 1243.44 | BK55: 13090.91 | BL55: =BK55*BJ55*1.1 -> 17905537 | BM55: 45815
A56: =IF(J56=J55,"ok","Hiện") -> Hiện | B56: =CV56 -> Đủ | C56: =CT56 -> 0 | H56: Thép đen | J56: I78-A-33 | K56: tôn tấm | L56: PL10-cuộn 2000 | M56: JIS G3101-SS400 | N56: m2 | O56: 78.5 | P56: 46.922038 | Q56: 3683.38 | T56: 50.4 | U56: 3956.4 | V56: =VLOOKUP(J56,[113]PR!$A:$S,15,0) -> 0 | W56: =VLOOKUP(J56,[113]PR!$A:$S,16,0) -> 0 | X56: =VLOOKUP(J56,[114]PR!$A:$U,17,0) -> 0 | Y56: =VLOOKUP(J56,[114]PR!$A:$U,18,0) -> 0 | Z56: 0 | AA56: 0 | AB56: 0 | AC56: 0 | AD56: 0 | AE56: 0 | AF56: 0 | AG56: 0 | AH56: 0 | AI56: 0 | AJ56: 0 | AK56: 0 | AL56: 0 | AM56: 0 | AP56: 0 | AQ56: 0 | AR56: =R56+T56+V56+X56+Z56+AB56+AD56+AF56+AH56+AJ56+AL56+AN56+AP56 -> 50.4 | AS56: =S56+U56+W56+Y56+AA56+AC56+AE56+AG56+AI56+AK56+AM56+AO56+AQ56 -> 3956.4 | AT56: 02 TỜ PL10x2000x12600 | AZ56: =IF(AR56>AV56,AR56-AV56,"0") -> 50.4 | BA56: =IF(AS56>AW56,AS56-AW56,"0") -> 3956.4 | BC56: 030325HN-IBS | BD56: Hùng Nguyên | BE56: Thép tấm 10x2000x12600 | BF56: SS400 | BG56: 3956.4 | BH56: 45719 | BI56: 50.4 | BJ56: 3956.4 | BK56: 13363.64 | BL56: =BK56*BJ56*1.1 -> 58159096 | BM56: 45752 | BN56: =SUMIF($J:$J,J56,$BI:$BI) -> 50.4 | BO56: =SUMIF($J:$J,J56,$BJ:$BJ) -> 3956.4 | BP56: ACC | CL56: =SUMIF($J:$J,J56,$BZ:$BZ) -> 0 | CM56: =SUMIF($J:$J,J56,$CA:$CA) -> 0 | CR56: =BN56+CL56 -> 50.4 | CS56: =BO56+CM56 -> 3956.4 | CT56: =AZ56-CR56 -> 0 | CU56: =BA56-CS56 -> 0 | CV56: =IF(CT56<0,"Thừa",IF(CT56=0,"Đủ","Thiếu")) -> Đủ | DR56: 46.922038 | DS56: 3683.38
A57: =IF(J57=J56,"ok","Hiện") -> Hiện | B57: =CV57 -> Đủ | C57: =CT57 -> 0 | E57: GNEE đã chốt đơn 2 | H57: Thép trắng nhập | J57: I78-A-34 | K57: tôn tấm( % C min 0.04%) | L57: PL12x1000x2000 | M57: ASTM-A240-TP304H | N57: m2 | O57: 95.16 | P57: 1.3622198 | Q57: 129.62884 | T57: 2 | U57: 190.32 | V57: =VLOOKUP(J57,[113]PR!$A:$S,15,0) -> 0 | W57: =VLOOKUP(J57,[113]PR!$A:$S,16,0) -> 0 | X57: =VLOOKUP(J57,[114]PR!$A:$U,17,0) -> 0 | Y57: =VLOOKUP(J57,[114]PR!$A:$U,18,0) -> 0 | Z57: 0 | AA57: 0 | AB57: 0 | AC57: 0 | AD57: 0 | AE57: 0 | AF57: 0 | AG57: 0 | AH57: 0 | AI57: 0 | AJ57: 0 | AK57: 0 | AL57: 0 | AM57: 0 | AP57: 0 | AQ57: 0 | AR57: =R57+T57+V57+X57+Z57+AB57+AD57+AF57+AH57+AJ57+AL57+AN57+AP57 -> 2 | AS57: =S57+U57+W57+Y57+AA57+AC57+AE57+AG57+AI57+AK57+AM57+AO57+AQ57 -> 190.32 | AZ57: =IF(AR57>AV57,AR57-AV57,"0") -> 2 | BA57: =IF(AS57>AW57,AS57-AW57,"0") -> 190.32 | BN57: =SUMIF($J:$J,J57,$BI:$BI) -> 0 | BO57: =SUMIF($J:$J,J57,$BJ:$BJ) -> 0 | BT57: IBSHI-GNEE/2504-08 | BU57: GNEE | BV57: 12*1000*2000 | BW57: A240-TP304H PLATE | BX57: 190.3 | BY57: 45755 | BZ57: 2 | CA57: 190.3 | CB57: 3.04 | CC57: =CB57*CA57 -> 578.512 | CI57: 45791 | CJ57: 45792 | CL57: =SUMIF($J:$J,J57,$BZ:$BZ) -> 2 | CM57: =SUMIF($J:$J,J57,$CA:$CA) -> 190.3 | CR57: =BN57+CL57 -> 2 | CS57: =BO57+CM57 -> 190.3 | CT57: =AZ57-CR57 -> 0 | CU57: =BA57-CS57 -> 0.02 | CV57: =IF(CT57<0,"Thừa",IF(CT57=0,"Đủ","Thiếu")) -> Đủ | DD57: 0.61571125 | DE57: 58 | DF57: 0.76039103 | DG57: 71.628835
A58: =IF(J58=J57,"ok","Hiện") -> Hiện | B58: =CV58 -> Thừa | C58: =CT58 -> -2.5996297 | H58: Thép đen | J58: I78-A-35 | K58: tôn tấm | L58: PL12x2000x12000 | M58: ASTM-A572-GR.50 | N58: m2 | O58: 94.2 | P58: 21.384259 | Q58: 2014.3972 | T58: 23.95037 | U58: 2256.1249 | V58: =VLOOKUP(J58,[113]PR!$A:$S,15,0) -> 0 | W58: =VLOOKUP(J58,[113]PR!$A:$S,16,0) -> 0 | X58: =VLOOKUP(J58,[114]PR!$A:$U,17,0) -> 0 | Y58: =VLOOKUP(J58,[114]PR!$A:$U,18,0) -> 0 | Z58: 6.45 | AA58: 607.59 | AB58: 0 | AC58: 0 | AD58: 0 | AE58: 0 | AF58: 0 | AG58: 0 | AH58: 0 | AI58: 0 | AJ58: 0 | AK58: 0 | AL58: 0 | AM58: 0 | AP58: 0 | AQ58: 0 | AR58: =R58+T58+V58+X58+Z58+AB58+AD58+AF58+AH58+AJ58+AL58+AN58+AP58 -> 30.40037 | AS58: =S58+U58+W58+Y58+AA58+AC58+AE58+AG58+AI58+AK58+AM58+AO58+AQ58 -> 2863.7149 | AT58: REV4( IBS REV) BỔ SUNG PL12X1500X4300 | AZ58: =IF(AR58>AV58,AR58-AV58,"0") -> 30.40037 | BA58: =IF(AS58>AW58,AS58-AW58,"0") -> 2863.7149 | BB58: 45762 | BC58: 030325HN-IBS | BD58: Hùng Nguyên | BE58: Thép tấm 12x2000x12000 | BF58: Q355B | BG58: 2260.8 | BH58: 45719 | BI58: 24 | BJ58: 2260.8 | BK58: 14000 | BL58: =BK58*BJ58*1.1 -> 34816320 | BM58: 45750 | BN58: =SUMIF($J:$J,J58,$BI:$BI) -> 33 | BO58: =SUMIF($J:$J,J58,$BJ:$BJ) -> 3391.2 | BP58: ACC | CL58: =SUMIF($J:$J,J58,$BZ:$BZ) -> 0 | CM58: =SUMIF($J:$J,J58,$CA:$CA) -> 0 | CR58: =BN58+CL58 -> 33 | CS58: =BO58+CM58 -> 3391.2 | CT58: =AZ58-CR58 -> -2.5996297 | CU58: =BA58-CS58 -> -527.48512 | CV58: =IF(CT58<0,"Thừa",IF(CT58=0,"Đủ","Thiếu")) -> Thừa | DB58: 1.441584 | DC58: 135.79721 | DH58: 19.942675 | DI58: 1878.6
A59: =IF(J59=J58,"ok","Hiện") -> ok | H59: Thép đen | J59: I78-A-35 | K59: tôn tấm | L59: PL12x2000x12000 | M59: ASTM-A572-GR.50 | N59: m2 | BC59: 180425HN-IBS | BD59: Hùng Nguyên | BE59: Thép tấm 12x1500x6000 Q355B | BG59: 1130.4 | BH59: 45765 | BI59: 9 | BJ59: 1130.4 | BK59: 14000 | BL59: =BK59*BJ59*1.1 -> 17408160 | BM59: 45768 | BN59: =SUMIF($J:$J,J59,$BI:$BI) -> 33
A60: =IF(J60=J59,"ok","Hiện") -> Hiện | B60: =CONCATENATE(CV60," Thiếu do tính") -> Thiếu Thiếu do tính | C60: =CT60 -> 0.0030450752 | H60: Thép đen | J60: I78-A-36 | K60: tôn tấm | L60: PL12x2000x12000 | M60: JIS G3101-SS400 | N60: m2 | O60: 94.2 | P60: 90.011647 | Q60: 8479.0972 | T60: 100.81305 | U60: 9496.5888 | V60: =VLOOKUP(J60,[113]PR!$A:$S,15,0) -> 0 | W60: =VLOOKUP(J60,[113]PR!$A:$S,16,0) -> 0 | X60: =VLOOKUP(J60,[114]PR!$A:$U,17,0) -> 0 | Y60: =VLOOKUP(J60,[114]PR!$A:$U,18,0) -> 0 | Z60: 0 | AA60: 0 | AB60: 0 | AC60: 0 | AD60: 0 | AE60: 0 | AF60: 0 | AG60: 0 | AH60: 0 | AI60: 0 | AJ60: 0 | AK60: 0 | AL60: 0 | AM60: 0 | AP60: 0 | AQ60: 0 | AR60: =R60+T60+V60+X60+Z60+AB60+AD60+AF60+AH60+AJ60+AL60+AN60+AP60 -> 100.81305 | AS60: =S60+U60+W60+Y60+AA60+AC60+AE60+AG60+AI60+AK60+AM60+AO60+AQ60 -> 9496.5888 | AZ60: =IF(AR60>AV60,AR60-AV60,"0") -> 100.81305 | BA60: =IF(AS60>AW60,AS60-AW60,"0") -> 9496.5888 | BC60: 030325HN-IBS | BD60: Hùng Nguyên | BE60: Thép tấm 12x2000x12000 (2 tờ) | BF60: SS400 | BG60: 9043.2 | BH60: 45719 | BI60: 96 | BJ60: 9043.2 | BK60: 13363.64 | BL60: =BK60*BJ60*1.1 -> 1.3293508e+08 | BM60: 45752 | BN60: =SUMIF($J:$J,J60,$BI:$BI) -> 100.81 | BO60: =SUMIF($J:$J,J60,$BJ:$BJ) -> 9496.3 | BP60: ACC | CL60: =SUMIF($J:$J,J60,$BZ:$BZ) -> 0 | CM60: =SUMIF($J:$J,J60,$CA:$CA) -> 0 | CR60: =BN60+CL60 -> 100.81 | CS60: =BO60+CM60 -> 9496.3 | CT60: =AZ60-CR60 -> 0.0030450752 | CU60: =BA60-CS60 -> 0.28884608 | CV60: =IF(CT60<0,"Thừa",IF(CT60=0,"Đủ","Thiếu")) -> Thiếu | DB60: 0.6264 | DC60: 59.00688 | DH60: 4.5804671 | DI60: 431.48 | DP60: 0.12526539 | DQ60: 11.8 | DR60: 7.5214437 | DS60: 708.52 | DT60: 42.775796 | DU60: 4029.48 | DV60: 13.737155 | DW60: 1294.04 | DZ60: 20.64512 | EA60: 1944.7703
A61: =IF(J61=J60,"ok","Hiện") -> ok | H61: Thép đen | J61: I78-A-36 | K61: tôn tấm | L61: PL12x2000x12000 | M61: JIS G3101-SS400 | N61: m2 | O61: 94.2 | P61: 90.011647 | Q61: 8479.0972 | BC61: 030325HN-IBS | BD61: Hùng Nguyên | BE61: Thép tấm 12x2000x2405 | BF61: SS400 | BG61: 453.1 | BH61: 45719 | BI61: 4.81 | BJ61: 453.1 | BK61: 13363.64 | BL61: =BK61*BJ61*1.1 -> 6660571.8 | BM61: 45752 | BP61: ACC
A62: =IF(J62=J61,"ok","Hiện") -> Hiện | B62: =CV62 -> Đủ | C62: =CT62 -> 0 | H62: Thép đen | J62: I78-A-37 | K62: tôn tấm | L62: PL14x2000x7500 | M62: ASTM-A572-GR.50 | N62: m2 | O62: 109.9 | P62: 12.569427 | Q62: 1381.38 | T62: 15 | U62: 1648.5 | V62: =VLOOKUP(J62,[113]PR!$A:$S,15,0) -> 0 | W62: =VLOOKUP(J62,[113]PR!$A:$S,16,0) -> 0 | X62: =VLOOKUP(J62,[114]PR!$A:$U,17,0) -> 0 | Y62: =VLOOKUP(J62,[114]PR!$A:$U,18,0) -> 0 | Z62: 0 | AA62: 0 | AB62: 0 | AC62: 0 | AD62: 0 | AE62: 0 | AF62: 0 | AG62: 0 | AH62: 0 | AI62: 0 | AJ62: 0 | AK62: 0 | AL62: 0 | AM62: 0 | AP62: 0 | AQ62: 0 | AR62: =R62+T62+V62+X62+Z62+AB62+AD62+AF62+AH62+AJ62+AL62+AN62+AP62 -> 15 | AS62: =S62+U62+W62+Y62+AA62+AC62+AE62+AG62+AI62+AK62+AM62+AO62+AQ62 -> 1648.5 | AZ62: =IF(AR62>AV62,AR62-AV62,"0") -> 15 | BA62: =IF(AS62>AW62,AS62-AW62,"0") -> 1648.5 | BB62: 45762 | BC62: 030325HN-IBS | BD62: Hùng Nguyên | BE62: Thép tấm 14x2000x7500 | BF62: Q355B | BG62: 1648.5 | BH62: 45719 | BI62: 15 | BJ62: 1648.5 | BK62: 14363.64 | BL62: =BK62*BJ62*1.1 -> 26046307 | BM62: 45747 | BN62: =SUMIF($J:$J,J62,$BI:$BI) -> 15 | BO62: =SUMIF($J:$J,J62,$BJ:$BJ) -> 1648.5 | BP62: ACC | CL62: =SUMIF($J:$J,J62,$BZ:$BZ) -> 0 | CM62: =SUMIF($J:$J,J62,$CA:$CA) -> 0 | CR62: =BN62+CL62 -> 15 | CS62: =BO62+CM62 -> 1648.5 | CT62: =AZ62-CR62 -> 0 | CU62: =BA62-CS62 -> 0 | CV62: =IF(CT62<0,"Thừa",IF(CT62=0,"Đủ","Thiếu")) -> Đủ | DH62: 12.569427 | DI62: 1381.38
A63: =IF(J63=J62,"ok","Hiện") -> Hiện | B63: =CV63 -> Đủ | C63: =CT63 -> 0 | H63: Thép đen | J63: I78-A-38 | K63: tôn tấm | L63: PL14x1500x6000 | M63: ASTM-A572-GR.50 | N63: m2 | O63: 109.9 | P63: 8.1532302 | Q63: 896.04 | T63: 9 | U63: 989.1 | V63: =VLOOKUP(J63,[113]PR!$A:$S,15,0) -> 0 | W63: =VLOOKUP(J63,[113]PR!$A:$S,16,0) -> 0 | X63: =VLOOKUP(J63,[114]PR!$A:$U,17,0) -> 0 | Y63: =VLOOKUP(J63,[114]PR!$A:$U,18,0) -> 0 | Z63: 0 | AA63: 0 | AB63: 0 | AC63: 0 | AD63: 0 | AE63: 0 | AF63: 0 | AG63: 0 | AH63: 0 | AI63: 0 | AJ63: 0 | AK63: 0 | AL63: 0 | AM63: 0 | AP63: 0 | AQ63: 0 | AR63: =R63+T63+V63+X63+Z63+AB63+AD63+AF63+AH63+AJ63+AL63+AN63+AP63 -> 9 | AS63: =S63+U63+W63+Y63+AA63+AC63+AE63+AG63+AI63+AK63+AM63+AO63+AQ63 -> 989.1 | AT63: REV2-SS400--->A572 IBS REV | AZ63: =IF(AR63>AV63,AR63-AV63,"0") -> 9 | BA63: =IF(AS63>AW63,AS63-AW63,"0") -> 989.1 | BC63: 030325HN-IBS | BD63: Hùng Nguyên | BE63: Thép tấm 14x1500x6000 | BF63: Q355B | BG63: 989.1 | BH63: 45719 | BI63: 9 | BJ63: 989.1 | BK63: 14181.82 | BL63: =BK63*BJ63*1.1 -> 15429962 | BM63: 45757 | BN63: =SUMIF($J:$J,J63,$BI:$BI) -> 9 | BO63: =SUMIF($J:$J,J63,$BJ:$BJ) -> 989.1 | BP63: Đã mời nghiệm thu, đang đợi QC | CL63: =SUMIF($J:$J,J63,$BZ:$BZ) -> 0 | CM63: =SUMIF($J:$J,J63,$CA:$CA) -> 0 | CR63: =BN63+CL63 -> 9 | CS63: =BO63+CM63 -> 989.1 | CT63: =AZ63-CR63 -> 0 | CU63: =BA63-CS63 -> 0 | CV63: =IF(CT63<0,"Thừa",IF(CT63=0,"Đủ","Thiếu")) -> Đủ | DD63: 7.8989991 | DE63: 868.1 | DJ63: 0.2511374 | DK63: 27.6
A64: =IF(J64=J63,"ok","Hiện") -> Hiện | B64: =CV64 -> Đủ | C64: =CT64 -> 0 | E64: Đã đặt thêm Hùng Nguyên | H64: Thép đen | J64: I78-A-39 | K64: tôn tấm | L64: PL16x2000x12000 | M64: ASTM-A572-GR.50 | N64: m2 | O64: 125.6 | P64: 65.908121 | Q64: 8278.06 | T64: 72 | U64: 9043.2 | V64: =VLOOKUP(J64,[113]PR!$A:$S,15,0) -> 9 | W64: =VLOOKUP(J64,[113]PR!$A:$S,16,0) -> 1130.4 | X64: =VLOOKUP(J64,[114]PR!$A:$U,17,0) -> 0 | Y64: =VLOOKUP(J64,[114]PR!$A:$U,18,0) -> 0 | Z64: 0 | AA64: 0 | AB64: 0 | AC64: 0 | AD64: 0 | AE64: 0 | AF64: 0 | AG64: 0 | AH64: 0 | AI64: 0 | AJ64: 0 | AK64: 0 | AL64: 0 | AM64: 0 | AP64: 0 | AQ64: 0 | AR64: =R64+T64+V64+X64+Z64+AB64+AD64+AF64+AH64+AJ64+AL64+AN64+AP64 -> 81 | AS64: =S64+U64+W64+Y64+AA64+AC64+AE64+AG64+AI64+AK64+AM64+AO64+AQ64 -> 10173.6 | AT64: REV2-THÊM 1 TỜ 1500X6000 IBS REV( THAY ĐỔI VỊ TRÍ NỐI) | AZ64: =IF(AR64>AV64,AR64-AV64,"0") -> 81 | BA64: =IF(AS64>AW64,AS64-AW64,"0") -> 10173.6 | BB64: 45762 | BC64: 030325HN-IBS | BD64: Hùng Nguyên | BE64: Thép tấm 16x2000x12000 | BF64: Q355B | BG64: 9043.2 | BH64: 45719 | BI64: 72 | BJ64: 9043.2 | BK64: 14545.45 | BL64: =BK64*BJ64*1.1 -> 1.4469115e+08 | BM64: 45747 | BN64: =SUMIF($J:$J,J64,$BI:$BI) -> 81 | BO64: =SUMIF($J:$J,J64,$BJ:$BJ) -> 9891 | BP64: ACC | CL64: =SUMIF($J:$J,J64,$BZ:$BZ) -> 0 | CM64: =SUMIF($J:$J,J64,$CA:$CA) -> 0 | CR64: =BN64+CL64 -> 81 | CS64: =BO64+CM64 -> 9891 | CT64: =AZ64-CR64 -> 0 | CU64: =BA64-CS64 -> 282.6 | CV64: =IF(CT64<0,"Thừa",IF(CT64=0,"Đủ","Thiếu")) -> Đủ | DD64: 0.68917197 | DE64: 86.56 | DH64: 65.218949 | DI64: 8191.5
A65: =IF(J65=J64,"ok","Hiện") -> ok | H65: Thép đen | J65: I78-A-39 | K65: tôn tấm | L65: PL16x2000x12000 | M65: ASTM-A572-GR.50 | N65: m2 | BC65: 180425HN-IBS | BD65: Hùng Nguyên | BE65: Thép tấm 16x1500x6000 Q355B | BF65: Q355B | BG65: 847.8 | BH65: 45765 | BI65: 9 | BJ65: 847.8 | BK65: 14818.18 | BL65: =BK65*BJ65*1.1 -> 13819138 | BM65: 45768 | BN65: =SUMIF($J:$J,J65,$BI:$BI) -> 81
A66: =IF(J66=J65,"ok","Hiện") -> Hiện | B66: =CONCATENATE(CV66," Thiếu do tính") -> Thiếu Thiếu do tính | C66: =CT66 -> 0.0015207006 | H66: Thép đen | J66: I78-A-40 | K66: tôn tấm | L66: PL16x2000x12000 | M66: JIS G3101-SS400 | N66: m2 | O66: 125.6 | P66: 18.695064 | Q66: 2348.1 | T66: 20.751521 | U66: 2606.391 | V66: =VLOOKUP(J66,[113]PR!$A:$S,15,0) -> 0 | W66: =VLOOKUP(J66,[113]PR!$A:$S,16,0) -> 0 | X66: =VLOOKUP(J66,[114]PR!$A:$U,17,0) -> 0 | Y66: =VLOOKUP(J66,[114]PR!$A:$U,18,0) -> 0 | Z66: 0 | AA66: 0 | AB66: 0 | AC66: 0 | AD66: 0 | AE66: 0 | AF66: 0 | AG66: 0 | AH66: 0 | AI66: 0 | AJ66: 0 | AK66: 0 | AL66: 0 | AM66: 0 | AP66: 0 | AQ66: 0 | AR66: =R66+T66+V66+X66+Z66+AB66+AD66+AF66+AH66+AJ66+AL66+AN66+AP66 -> 20.751521 | AS66: =S66+U66+W66+Y66+AA66+AC66+AE66+AG66+AI66+AK66+AM66+AO66+AQ66 -> 2606.391 | AZ66: =IF(AR66>AV66,AR66-AV66,"0") -> 20.751521 | BA66: =IF(AS66>AW66,AS66-AW66,"0") -> 2606.391 | BC66: 030325HN-IBS | BD66: Hùng Nguyên | BE66: Thép tấm 16x2000x10375 | BF66: SS400 | BG66: 2606.2 | BH66: 45719 | BI66: 20.75 | BJ66: 2606.2 | BK66: 13909.09 | BL66: =BK66*BJ66*1.1 -> 39874857 | BM66: 45751 | BN66: =SUMIF($J:$J,J66,$BI:$BI) -> 20.75 | BO66: =SUMIF($J:$J,J66,$BJ:$BJ) -> 2606.2 | BP66: ACC | CL66: =SUMIF($J:$J,J66,$BZ:$BZ) -> 0 | CM66: =SUMIF($J:$J,J66,$CA:$CA) -> 0 | CR66: =BN66+CL66 -> 20.75 | CS66: =BO66+CM66 -> 2606.2 | CT66: =AZ66-CR66 -> 0.0015207006 | CU66: =BA66-CS66 -> 0.191 | CV66: =IF(CT66<0,"Thừa",IF(CT66=0,"Đủ","Thiếu")) -> Thiếu | DR66: 1.5211783 | DS66: 191.06 | DT66: 17.173885 | DU66: 2157.04
A67: =IF(J67=J66,"ok","Hiện") -> Hiện | B67: =CV67 -> Thừa | C67: =CT67 -> -69 | H67: Thép đen | J67: I78-A-41 | K67: tôn tấm | L67: PL19x2000x12000 | M67: ASTM-A572-GR.50 | N67: m2 | O67: 149.15 | P67: 48.365002 | Q67: 7213.64 | T67: 54.168802 | U67: 8079.2768 | V67: =VLOOKUP(J67,[113]PR!$A:$S,15,0) -> 10.231198 | W67: =VLOOKUP(J67,[113]PR!$A:$S,16,0) -> 1525.9832 | X67: =VLOOKUP(J67,[114]PR!$A:$U,17,0) -> 0 | Y67: =VLOOKUP(J67,[114]PR!$A:$U,18,0) -> 0 | Z67: 0 | AA67: 0 | AB67: -64.4 | AC67: -9605.26 | AD67: 0 | AE67: 0 | AF67: 0 | AG67: 0 | AH67: 0 | AI67: 0 | AJ67: 0 | AK67: 0 | AL67: 0 | AM67: 0 | AP67: 0 | AQ67: 0 | AR67: =R67+T67+V67+X67+Z67+AB67+AD67+AF67+AH67+AJ67+AL67+AN67+AP67 -> 0 | AS67: =S67+U67+W67+Y67+AA67+AC67+AE67+AG67+AI67+AK67+AM67+AO67+AQ67 -> -1.8189894e-12 | AT67: REV5-IBS REV | AZ67: =IF(AR67>AV67,AR67-AV67,"0") -> 0 | BA67: =IF(AS67>AW67,AS67-AW67,"0") -> 0 | BB67: 45762 | BC67: 030325HN-IBS | BD67: Hùng Nguyên | BE67: Thép tấm 20x2000x12000 (Đợi ngày 31/3) | BF67: A572-GR.50 | BG67: =11304/3 -> 3768 | BH67: 45719 | BI67: =24 -> 24 | BJ67: =11304/3 -> 3768 | BK67: 15272.73 | BL67: =BK67*BJ67*1.1 -> 63302411 | BM67: 45751 | BN67: =SUMIF($J:$J,J67,$BI:$BI) -> 69 | BO67: =SUMIF($J:$J,J67,$BJ:$BJ) -> 10126.5 | BP67: Đợi thiết kế chuyển đổi | CL67: =SUMIF($J:$J,J67,$BZ:$BZ) -> 0 | CM67: =SUMIF($J:$J,J67,$CA:$CA) -> 0 | CR67: =BN67+CL67 -> 69 | CS67: =BO67+CM67 -> 10126.5 | CT67: =AZ67-CR67 -> -69 | CU67: =BA67-CS67 -> -10126.5 | CV67: =IF(CT67<0,"Thừa",IF(CT67=0,"Đủ","Thiếu")) -> Thừa | DD67: 16.211063 | DE67: 2417.88 | DH67: 32.153939 | DI67: 4795.76
A68: =IF(J68=J67,"ok","Hiện") -> ok | H68: Thép đen | J68: I78-A-41 | K68: tôn tấm | L68: PL19x2000x12000 | M68: ASTM-A572-GR.50 | N68: m2 | BC68: 230425HN-IBS | BD68: Hùng Nguyên | BE68: Thép tấm 18x1500x12000*2 PSC Thép tấm 18x1500x6000*2 PSC | BF68: Q355B | BG68: 6358.5 | BH68: 45770 | BI68: =1.5*12*2+1.5*6 -> 45 | BJ68: 6358.5 | BK68: 14909.09 | BL68: =BK68*BJ68*1.1 -> 1.0427939e+08 | BM68: 45771 | BN68: =SUMIF($J:$J,J68,$BI:$BI) -> 69
A69: =IF(J69=J68,"ok","Hiện") -> Hiện | B69: =CV69 -> Đủ | C69: =CT69 -> 0 | E69: Hàng tồnPL20\ | H69: Thép đen | I69: mua thêm | J69: I78-A-42 | K69: tôn tấm | L69: PL20x1500x2000 | M69: JIS G3101-SS400 | N69: m2 | O69: 157 | P69: 8.0858599 | Q69: 1269.48 | T69: 9 | U69: 1413 | V69: =VLOOKUP(J69,[113]PR!$A:$S,15,0) -> -9 | W69: =VLOOKUP(J69,[113]PR!$A:$S,16,0) -> -1413 | X69: =VLOOKUP(J69,[114]PR!$A:$U,17,0) -> 0 | Y69: =VLOOKUP(J69,[114]PR!$A:$U,18,0) -> 0 | Z69: 0 | AA69: 0 | AB69: 3 | AC69: 471 | AD69: 0 | AE69: 0 | AF69: 0 | AG69: 0 | AH69: 0 | AI69: 0 | AJ69: 0 | AK69: 0 | AL69: 0 | AM69: 0 | AP69: 0 | AQ69: 0 | AR69: =R69+T69+V69+X69+Z69+AB69+AD69+AF69+AH69+AJ69+AL69+AN69+AP69 -> 3 | AS69: =S69+U69+W69+Y69+AA69+AC69+AE69+AG69+AI69+AK69+AM69+AO69+AQ69 -> 471 | AT69: REV5-IBS REV | AV69: 3 | AW69: 471 | AY69: Dùng hàng tồn | AZ69: =IF(AR69>AV69,AR69-AV69,"0") -> 0 | BA69: =IF(AS69>AW69,AS69-AW69,"0") -> 0 | BN69: =SUMIF($J:$J,J69,$BI:$BI) -> 0 | BO69: =SUMIF($J:$J,J69,$BJ:$BJ) -> 0 | CL69: =SUMIF($J:$J,J69,$BZ:$BZ) -> 0 | CM69: =SUMIF($J:$J,J69,$CA:$CA) -> 0 | CR69: =BN69+CL69 -> 0 | CS69: =BO69+CM69 -> 0 | CT69: =AZ69-CR69 -> 0 | CU69: =BA69-CS69 -> 0 | CV69: =IF(CT69<0,"Thừa",IF(CT69=0,"Đủ","Thiếu")) -> Đủ | DD69: 0.68420382 | DE69: 107.42 | DT69: 7.4016561 | DU69: 1162.06
A70: =IF(J70=J69,"ok","Hiện") -> Hiện | B70: =CV70 -> Thừa | C70: =CT70 -> -4.4 | H70: Thép đen | J70: I78-A-43 | K70: tôn tấm | L70: PL22x2000x3800 | M70: ASTM-A572-GR.50 | N70: m2 | O70: 172.7 | P70: 6.841368 | Q70: 1181.5043 | T70: 7.6 | U70: 1312.52 | V70: =VLOOKUP(J70,[113]PR!$A:$S,15,0) -> 0 | W70: =VLOOKUP(J70,[113]PR!$A:$S,16,0) -> 0 | X70: =VLOOKUP(J70,[114]PR!$A:$U,17,0) -> 0 | Y70: =VLOOKUP(J70,[114]PR!$A:$U,18,0) -> 0 | Z70: 0 | AA70: 0 | AB70: 0 | AC70: 0 | AD70: 0 | AE70: 0 | AF70: 0 | AG70: 0 | AH70: 0 | AI70: 0 | AJ70: 0 | AK70: 0 | AL70: 0 | AM70: 0 | AP70: 0 | AQ70: 0 | AR70: =R70+T70+V70+X70+Z70+AB70+AD70+AF70+AH70+AJ70+AL70+AN70+AP70 -> 7.6 | AS70: =S70+U70+W70+Y70+AA70+AC70+AE70+AG70+AI70+AK70+AM70+AO70+AQ70 -> 1312.52 | AZ70: =IF(AR70>AV70,AR70-AV70,"0") -> 7.6 | BA70: =IF(AS70>AW70,AS70-AW70,"0") -> 1312.52 | BB70: 45762 | BC70: 030325HN-IBS | BD70: Hùng Nguyên | BE70: Thép tấm 22x2000x6000 | BF70: A572/Q355B | BG70: 2072.4 | BH70: 45719 | BI70: 12 | BJ70: 2072.4 | BK70: 15090.91 | BL70: =BK70*BJ70*1.1 -> 34401842 | BM70: 45747 | BN70: =SUMIF($J:$J,J70,$BI:$BI) -> 12 | BO70: =SUMIF($J:$J,J70,$BJ:$BJ) -> 2072.4 | BP70: ACC | CL70: =SUMIF($J:$J,J70,$BZ:$BZ) -> 0 | CM70: =SUMIF($J:$J,J70,$CA:$CA) -> 0 | CR70: =BN70+CL70 -> 12 | CS70: =BO70+CM70 -> 2072.4 | CT70: =AZ70-CR70 -> -4.4 | CU70: =BA70-CS70 -> -759.88 | CV70: =IF(CT70<0,"Thừa",IF(CT70=0,"Đủ","Thiếu")) -> Thừa | DB70: 6.841368 | DC70: 1181.5043
A71: =IF(J71=J70,"ok","Hiện") -> Hiện | B71: =CONCATENATE(CV71," Dùng lẫn A572, A-43") -> Thiếu Dùng lẫn A572, A-43 | C71: =CT71 -> 3 | E71: Dùng lẫn A572, A-43 | H71: Thép đen | J71: I78-A-44 | K71: tôn tấm | L71: PL22x2000x1600 | M71: ASTM-A572-GR.50 | N71: m2 | O71: 172.7 | P71: 2.3814708 | Q71: 411.28 | T71: 3 | U71: 518.1 | V71: =VLOOKUP(J71,[113]PR!$A:$S,15,0) -> 0 | W71: =VLOOKUP(J71,[113]PR!$A:$S,16,0) -> 0 | X71: =VLOOKUP(J71,[114]PR!$A:$U,17,0) -> 0 | Y71: =VLOOKUP(J71,[114]PR!$A:$U,18,0) -> 0 | Z71: 0 | AA71: 0 | AB71: 0 | AC71: 0 | AD71: 0 | AE71: 0 | AF71: 0 | AG71: 0 | AH71: 0 | AI71: 0 | AJ71: 0 | AK71: 0 | AL71: 0 | AM71: 0 | AP71: 0 | AQ71: 0 | AR71: =R71+T71+V71+X71+Z71+AB71+AD71+AF71+AH71+AJ71+AL71+AN71+AP71 -> 3 | AS71: =S71+U71+W71+Y71+AA71+AC71+AE71+AG71+AI71+AK71+AM71+AO71+AQ71 -> 518.1 | AT71: REV2-SS400--->A572(IBS REV) | AZ71: =IF(AR71>AV71,AR71-AV71,"0") -> 3 | BA71: =IF(AS71>AW71,AS71-AW71,"0") -> 518.1 | BN71: =SUMIF($J:$J,J71,$BI:$BI) -> 0 | BO71: =SUMIF($J:$J,J71,$BJ:$BJ) -> 0 | CL71: =SUMIF($J:$J,J71,$BZ:$BZ) -> 0 | CM71: =SUMIF($J:$J,J71,$CA:$CA) -> 0 | CR71: =BN71+CL71 -> 0 | CS71: =BO71+CM71 -> 0 | CT71: =AZ71-CR71 -> 3 | CU71: =BA71-CS71 -> 518.1 | CV71: =IF(CT71<0,"Thừa",IF(CT71=0,"Đủ","Thiếu")) -> Thiếu | DD71: 2.3814708 | DE71: 411.28
A72: =IF(J72=J71,"ok","Hiện") -> Hiện | B72: =CV72 -> Đủ | C72: =CT72 -> 0 | H72: Thép trắng nhập | J72: I78-A-45 | K72: tôn tấm( % C min 0.04%) | L72: PL25x1500x2000 | M72: ASTM-A240-TP304H | N72: m2 | O72: 198.25 | P72: 2.53472 | Q72: 502.50824 | T72: 3 | U72: 594.75 | V72: =VLOOKUP(J72,[113]PR!$A:$S,15,0) -> 0 | W72: =VLOOKUP(J72,[113]PR!$A:$S,16,0) -> 0 | X72: =VLOOKUP(J72,[114]PR!$A:$U,17,0) -> 0 | Y72: =VLOOKUP(J72,[114]PR!$A:$U,18,0) -> 0 | Z72: 0 | AA72: 0 | AB72: 0 | AC72: 0 | AD72: 0 | AE72: 0 | AF72: 0 | AG72: 0 | AH72: 0 | AI72: 0 | AJ72: 0 | AK72: 0 | AL72: 0 | AM72: 0 | AP72: 0 | AQ72: 0 | AR72: =R72+T72+V72+X72+Z72+AB72+AD72+AF72+AH72+AJ72+AL72+AN72+AP72 -> 3 | AS72: =S72+U72+W72+Y72+AA72+AC72+AE72+AG72+AI72+AK72+AM72+AO72+AQ72 -> 594.75 | AZ72: =IF(AR72>AV72,AR72-AV72,"0") -> 3 | BA72: =IF(AS72>AW72,AS72-AW72,"0") -> 594.75 | BN72: =SUMIF($J:$J,J72,$BI:$BI) -> 0 | BO72: =SUMIF($J:$J,J72,$BJ:$BJ) -> 0 | BT72: IBSHI-GNEE/2504-08 | BU72: GNEE | BV72: 25*1500*2000 | BW72: A240-TP304H PLATE | BX72: 594.8 | BY72: 45755 | BZ72: 3 | CA72: 594.8 | CB72: 3.23 | CC72: =CB72*CA72 -> 1921.204 | CI72: 45791 | CJ72: 45792 | CL72: =SUMIF($J:$J,J72,$BZ:$BZ) -> 3 | CM72: =SUMIF($J:$J,J72,$CA:$CA) -> 594.8 | CR72: =BN72+CL72 -> 3 | CS72: =BO72+CM72 -> 594.8 | CT72: =AZ72-CR72 -> 0 | CU72: =BA72-CS72 -> -0.05 | CV72: =IF(CT72<0,"Thừa",IF(CT72=0,"Đủ","Thiếu")) -> Đủ | DF72: 2.5605515 | DG72: 502.50824
A73: =IF(J73=J72,"ok","Hiện") -> Hiện | B73: =CV73 -> Thừa | C73: =CT73 -> -1.8754558 | H73: Thép đen | J73: I78-A-46 | K73: tôn tấm | L73: PL25x2000x12000 | M73: ASTM-A572-GR.50 | N73: m2 | O73: 196.25 | P73: 214.52662 | Q73: 42100.848 | T73: 238.12454 | U73: 46731.942 | V73: =VLOOKUP(J73,[113]PR!$A:$S,15,0) -> 0 | W73: =VLOOKUP(J73,[113]PR!$A:$S,16,0) -> 0 | X73: =VLOOKUP(J73,[114]PR!$A:$U,17,0) -> 0 | Y73: =VLOOKUP(J73,[114]PR!$A:$U,18,0) -> 0 | Z73: 0 | AA73: 0 | AB73: 0 | AC73: 0 | AD73: 0 | AE73: 0 | AF73: 0 | AG73: 0 | AH73: 0 | AI73: 0 | AJ73: 0 | AK73: 0 | AL73: 0 | AM73: 0 | AP73: 0 | AQ73: 0 | AR73: =R73+T73+V73+X73+Z73+AB73+AD73+AF73+AH73+AJ73+AL73+AN73+AP73 -> 238.12454 | AS73: =S73+U73+W73+Y73+AA73+AC73+AE73+AG73+AI73+AK73+AM73+AO73+AQ73 -> 46731.942 | AZ73: =IF(AR73>AV73,AR73-AV73,"0") -> 238.12454 | BA73: =IF(AS73>AW73,AS73-AW73,"0") -> 46731.942 | BB73: 45762 | BC73: 030325HN-IBS | BD73: Hùng Nguyên | BE73: Thép tấm 25x2000x12000 | BF73: A572/Q355B | BG73: 47100 | BH73: 45719 | BI73: 240 | BJ73: 47100 | BK73: 15090.91 | BL73: =BK73*BJ73*1.1 -> 7.8186005e+08 | BM73: 45747 | BN73: =SUMIF($J:$J,J73,$BI:$BI) -> 240 | BO73: =SUMIF($J:$J,J73,$BJ:$BJ) -> 47100 | BP73: ACC | CL73: =SUMIF($J:$J,J73,$BZ:$BZ) -> 0 | CM73: =SUMIF($J:$J,J73,$CA:$CA) -> 0 | CR73: =BN73+CL73 -> 240 | CS73: =BO73+CM73 -> 47100 | CT73: =AZ73-CR73 -> -1.8754558 | CU73: =BA73-CS73 -> -368.05821 | CV73: =IF(CT73<0,"Thừa",IF(CT73=0,"Đủ","Thiếu")) -> Thừa | CZ73: 11.965968 | DA73: 2348.3212 | DB73: 0.961056 | DC73: 188.60724 | DD73: 110.89722 | DE73: 21763.58 | DH73: 90.702369 | DI73: 17800.34
A74: =IF(J74=J73,"ok","Hiện") -> Hiện | B74: =CV74 -> Thừa | C74: =CT74 -> -3.159839 | H74: Thép đen | J74: I78-A-47 | K74: tôn tấm | L74: PL25x2000x12000 | M74: JIS G3101-SS400 | N74: m2 | O74: 196.25 | P74: 18.607287 | Q74: 3651.68 | T74: 20.840161 | U74: 4089.8816 | V74: =VLOOKUP(J74,[113]PR!$A:$S,15,0) -> 0 | W74: =VLOOKUP(J74,[113]PR!$A:$S,16,0) -> 0 | X74: =VLOOKUP(J74,[114]PR!$A:$U,17,0) -> 0 | Y74: =VLOOKUP(J74,[114]PR!$A:$U,18,0) -> 0 | Z74: 0 | AA74: 0 | AB74: 0 | AC74: 0 | AD74: 0 | AE74: 0 | AF74: 0 | AG74: 0 | AH74: 0 | AI74: 0 | AJ74: 0 | AK74: 0 | AL74: 0 | AM74: 0 | AP74: 0 | AQ74: 0 | AR74: =R74+T74+V74+X74+Z74+AB74+AD74+AF74+AH74+AJ74+AL74+AN74+AP74 -> 20.840161 | AS74: =S74+U74+W74+Y74+AA74+AC74+AE74+AG74+AI74+AK74+AM74+AO74+AQ74 -> 4089.8816 | AZ74: =IF(AR74>AV74,AR74-AV74,"0") -> 20.840161 | BA74: =IF(AS74>AW74,AS74-AW74,"0") -> 4089.8816 | BC74: 030325HN-IBS | BD74: Hùng Nguyên | BE74: Thép tấm 25x2000x12000 | BF74: A36/SS400 | BG74: 4710 | BH74: 45719 | BI74: 24 | BJ74: 4710 | BK74: 14000 | BL74: =BK74*BJ74*1.1 -> 72534000 | BM74: 45752 | BN74: =SUMIF($J:$J,J74,$BI:$BI) -> 24 | BO74: =SUMIF($J:$J,J74,$BJ:$BJ) -> 4710 | BP74: ACC | CL74: =SUMIF($J:$J,J74,$BZ:$BZ) -> 0 | CM74: =SUMIF($J:$J,J74,$CA:$CA) -> 0 | CR74: =BN74+CL74 -> 24 | CS74: =BO74+CM74 -> 4710 | CT74: =AZ74-CR74 -> -3.159839 | CU74: =BA74-CS74 -> -620.1184 | CV74: =IF(CT74<0,"Thừa",IF(CT74=0,"Đủ","Thiếu")) -> Thừa | DD74: 3.9776815 | DE74: 780.62 | DH74: 0.29951592 | DI74: 58.78 | DJ74: 0.10629299 | DK74: 20.86 | DL74: 0.10629299 | DM74: 20.86 | DN74: 0.10629299 | DO74: 20.86 | DP74: 0.074904459 | DQ74: 14.7 | DT74: 13.936306 | DU74: 2735
A75: =IF(J75=J74,"ok","Hiện") -> Hiện | B75: =CV75 -> Thừa | C75: =CT75 -> -5 | H75: Thép đen | J75: I78-A-48 | K75: tôn tấm | L75: PL32x2000x12000 | M75: ASTM-A572-GR.50 | N75: m2 | O75: 251.2 | P75: 16.832052 | Q75: 4228.2116 | T75: 19 | U75: 4772.8 | V75: =VLOOKUP(J75,[113]PR!$A:$S,15,0) -> 0 | W75: =VLOOKUP(J75,[113]PR!$A:$S,16,0) -> 0 | X75: =VLOOKUP(J75,[114]PR!$A:$U,17,0) -> 0 | Y75: =VLOOKUP(J75,[114]PR!$A:$U,18,0) -> 0 | Z75: 0 | AA75: 0 | AB75: 0 | AC75: 0 | AD75: 0 | AE75: 0 | AF75: 0 | AG75: 0 | AH75: 0 | AI75: 0 | AJ75: 0 | AK75: 0 | AL75: 0 | AM75: 0 | AP75: 0 | AQ75: 0 | AR75: =R75+T75+V75+X75+Z75+AB75+AD75+AF75+AH75+AJ75+AL75+AN75+AP75 -> 19 | AS75: =S75+U75+W75+Y75+AA75+AC75+AE75+AG75+AI75+AK75+AM75+AO75+AQ75 -> 4772.8 | AZ75: =IF(AR75>AV75,AR75-AV75,"0") -> 19 | BA75: =IF(AS75>AW75,AS75-AW75,"0") -> 4772.8 | BB75: 45762 | BC75: 030325HN-IBS | BD75: Hùng Nguyên | BE75: Thép tấm 32x2000x12000 | BF75: A572/Q355B | BG75: 6028.8 | BH75: 45719 | BI75: 24 | BJ75: 6028.8 | BK75: 15272.73 | BL75: =BK75*BJ75*1.1 -> 1.0128386e+08 | BM75: 45747 | BN75: =SUMIF($J:$J,J75,$BI:$BI) -> 24 | BO75: =SUMIF($J:$J,J75,$BJ:$BJ) -> 6028.8 | BP75: ACC | CL75: =SUMIF($J:$J,J75,$BZ:$BZ) -> 0 | CM75: =SUMIF($J:$J,J75,$CA:$CA) -> 0 | CR75: =BN75+CL75 -> 24 | CS75: =BO75+CM75 -> 6028.8 | CT75: =AZ75-CR75 -> -5 | CU75: =BA75-CS75 -> -1256 | CV75: =IF(CT75<0,"Thừa",IF(CT75=0,"Đủ","Thiếu")) -> Thừa | CZ75: 7.847976 | DA75: 1971.4116 | DH75: 8.9840764 | DI75: 2256.8
A76: =IF(J76=J75,"ok","Hiện") -> Hiện | B76: =CONCATENATE(CV76," Dùng lẫn A572, A-48") -> Thiếu Dùng lẫn A572, A-48 | C76: =CT76 -> 4 | E76: Dùng lẫn A572 | H76: Thép đen | J76: I78-A-49 | K76: tôn tấm | L76: PL32x2000x2000 | M76: ASTM-A572-GR.50 | N76: m2 | O76: 251.2 | P76: 3.4042994 | Q76: 855.16 | T76: 4 | U76: 1004.8 | V76: =VLOOKUP(J76,[113]PR!$A:$S,15,0) -> 0 | W76: =VLOOKUP(J76,[113]PR!$A:$S,16,0) -> 0 | X76: =VLOOKUP(J76,[114]PR!$A:$U,17,0) -> 0 | Y76: =VLOOKUP(J76,[114]PR!$A:$U,18,0) -> 0 | Z76: 0 | AA76: 0 | AB76: 0 | AC76: 0 | AD76: 0 | AE76: 0 | AF76: 0 | AG76: 0 | AH76: 0 | AI76: 0 | AJ76: 0 | AK76: 0 | AL76: 0 | AM76: 0 | AP76: 0 | AQ76: 0 | AR76: =R76+T76+V76+X76+Z76+AB76+AD76+AF76+AH76+AJ76+AL76+AN76+AP76 -> 4 | AS76: =S76+U76+W76+Y76+AA76+AC76+AE76+AG76+AI76+AK76+AM76+AO76+AQ76 -> 1004.8 | AT76: REV2-SS400--->A572(IBS REV) | AZ76: =IF(AR76>AV76,AR76-AV76,"0") -> 4 | BA76: =IF(AS76>AW76,AS76-AW76,"0") -> 1004.8 | BN76: =SUMIF($J:$J,J76,$BI:$BI) -> 0 | BO76: =SUMIF($J:$J,J76,$BJ:$BJ) -> 0 | CL76: =SUMIF($J:$J,J76,$BZ:$BZ) -> 0 | CM76: =SUMIF($J:$J,J76,$CA:$CA) -> 0 | CR76: =BN76+CL76 -> 0 | CS76: =BO76+CM76 -> 0 | CT76: =AZ76-CR76 -> 4 | CU76: =BA76-CS76 -> 1004.8 | CV76: =IF(CT76<0,"Thừa",IF(CT76=0,"Đủ","Thiếu")) -> Thiếu | DD76: 1.9629777 | DE76: 493.1 | DR76: 1.4413217 | DS76: 362.06
A77: =IF(J77=J76,"ok","Hiện") -> Hiện | B77: =CV77 -> Thừa | C77: =CT77 -> -1.6 | G77: Xin chuyển mác A36 | H77: Thép đen | J77: I78-A-50 | K77: tôn tấm | L77: PL35x2000x12000 | M77: JIS G3101-SS400 | N77: m2 | O77: 274.75 | P77: 13.42253 | Q77: 3687.84 | T77: 22.4 | U77: 6154.4 | V77: =VLOOKUP(J77,[113]PR!$A:$S,15,0) -> 0 | W77: =VLOOKUP(J77,[113]PR!$A:$S,16,0) -> 0 | X77: =VLOOKUP(J77,[114]PR!$A:$U,17,0) -> 0 | Y77: =VLOOKUP(J77,[114]PR!$A:$U,18,0) -> 0 | Z77: 0 | AA77: 0 | AB77: 0 | AC77: 0 | AD77: 0 | AE77: 0 | AF77: 0 | AG77: 0 | AH77: 0 | AI77: 0 | AJ77: 0 | AK77: 0 | AL77: 0 | AM77: 0 | AP77: 0 | AQ77: 0 | AR77: =R77+T77+V77+X77+Z77+AB77+AD77+AF77+AH77+AJ77+AL77+AN77+AP77 -> 22.4 | AS77: =S77+U77+W77+Y77+AA77+AC77+AE77+AG77+AI77+AK77+AM77+AO77+AQ77 -> 6154.4 | AZ77: =IF(AR77>AV77,AR77-AV77,"0") -> 22.4 | BA77: =IF(AS77>AW77,AS77-AW77,"0") -> 6154.4 | BC77: 131/2025/CTC-IBS | BD77: Citicom | BE77: PL35x2mx12m | BF77: SS400 | BG77: 6594 | BH77: 45750 | BI77: =24 -> 24 | BJ77: 6594 | BK77: =15300/1.1 -> 13909.091 | BL77: =BK77*BJ77*1.1 -> 100888200 | BM77: 45765 | BN77: =SUMIF($J:$J,J77,$BI:$BI) -> 24 | BO77: =SUMIF($J:$J,J77,$BJ:$BJ) -> 6594 | BP77: ACC | CL77: =SUMIF($J:$J,J77,$BZ:$BZ) -> 0 | CM77: =SUMIF($J:$J,J77,$CA:$CA) -> 0 | CR77: =BN77+CL77 -> 24 | CS77: =BO77+CM77 -> 6594 | CT77: =AZ77-CR77 -> -1.6 | CU77: =BA77-CS77 -> -439.6 | CV77: =IF(CT77<0,"Thừa",IF(CT77=0,"Đủ","Thiếu")) -> Thừa | DR77: 13.42253 | DS77: 3687.84
A78: =IF(J78=J77,"ok","Hiện") -> Hiện | B78: =CONCATENATE(CV78," TK báo đủ nếu gia công không hỏng") -> Thiếu TK báo đủ nếu gia công không hỏng | C78: =CT78 -> 1 | G78: Xin chuyển đổi PL50x2000x12000 | H78: Thép đen | J78: I78-A-51 | K78: tôn tấm | L78: PL48x2000x12000 | M78: ASTM-A572-GR.50 | N78: m2 | O78: 376.8 | P78: 22.203776 | Q78: 8366.3828 | T78: 25 | U78: 9420 | V78: =VLOOKUP(J78,[113]PR!$A:$S,15,0) -> 0 | W78: =VLOOKUP(J78,[113]PR!$A:$S,16,0) -> 0 | X78: =VLOOKUP(J78,[114]PR!$A:$U,17,0) -> 0 | Y78: =VLOOKUP(J78,[114]PR!$A:$U,18,0) -> 0 | Z78: 0 | AA78: 0 | AB78: 0 | AC78: 0 | AD78: 0 | AE78: 0 | AF78: 0 | AG78: 0 | AH78: 0 | AI78: 0 | AJ78: 0 | AK78: 0 | AL78: 0 | AM78: 0 | AP78: 0 | AQ78: 0 | AR78: =R78+T78+V78+X78+Z78+AB78+AD78+AF78+AH78+AJ78+AL78+AN78+AP78 -> 25 | AS78: =S78+U78+W78+Y78+AA78+AC78+AE78+AG78+AI78+AK78+AM78+AO78+AQ78 -> 9420 | AZ78: =IF(AR78>AV78,AR78-AV78,"0") -> 25 | BA78: =IF(AS78>AW78,AS78-AW78,"0") -> 9420 | BB78: 45762 | BC78: 030325HN-IBS | BD78: Hùng Nguyên | BE78: Thép tấm 50x2000x12000 | BF78: A572-GR.50 | BG78: 9420 | BH78: 45719 | BI78: 24 | BJ78: 9420 | BK78: 15272.73 | BL78: =BK78*BJ78*1.1 -> 1.5825603e+08 | BM78: 45751 | BN78: =SUMIF($J:$J,J78,$BI:$BI) -> 24 | BO78: =SUMIF($J:$J,J78,$BJ:$BJ) -> 9420 | BP78: ACC | CL78: =SUMIF($J:$J,J78,$BZ:$BZ) -> 0 | CM78: =SUMIF($J:$J,J78,$CA:$CA) -> 0 | CR78: =BN78+CL78 -> 24 | CS78: =BO78+CM78 -> 9420 | CT78: =AZ78-CR78 -> 1 | CU78: =BA78-CS78 -> 0 | CV78: =IF(CT78<0,"Thừa",IF(CT78=0,"Đủ","Thiếu")) -> Thiếu | CZ78: 22.203776 | DA78: 8366.3828
A79: =IF(J79=J78,"ok","Hiện") -> Hiện | B79: =CONCATENATE(CV79," Chia diện tích là đủ") -> Thừa Chia diện tích là đủ | C79: =CT79 -> -2644.906 | J79: I78-A-52 | K79: gratting-mạ kẽm nóng | L79: GRATTING 32x5 | M79: JIS G3101-SS400-H.D.G | N79: m2 | O79: 50 | P79: 749.6024 | Q79: 37480.12 | T79: 749.6024 | U79: 37480.12 | V79: =VLOOKUP(J79,[113]PR!$A:$S,15,0) -> 0 | W79: =VLOOKUP(J79,[113]PR!$A:$S,16,0) -> 0 | X79: =VLOOKUP(J79,[114]PR!$A:$U,17,0) -> -38.5084 | Y79: =VLOOKUP(J79,[114]PR!$A:$U,18,0) -> -1925.42 | Z79: 0 | AA79: 0 | AB79: 0 | AC79: 0 | AD79: 0 | AE79: 0 | AF79: 0 | AG79: 0 | AH79: 0 | AI79: 0 | AJ79: 0 | AK79: 0 | AL79: 0 | AM79: 0 | AP79: 0 | AQ79: 0 | AR79: =R79+T79+V79+X79+Z79+AB79+AD79+AF79+AH79+AJ79+AL79+AN79+AP79 -> 711.094 | AS79: =S79+U79+W79+Y79+AA79+AC79+AE79+AG79+AI79+AK79+AM79+AO79+AQ79 -> 35554.7 | AT79: REV3-IBS REV GIẢM SL | AZ79: =IF(AR79>AV79,AR79-AV79,"0") -> 711.094 | BA79: =IF(AS79>AW79,AS79-AW79,"0") -> 35554.7 | BC79: 2307-1/HĐKT/IBS-WWHD | BD79: WINWIN HD | BE79: Tấm sàn (Grating): Serrated bearing bar 32x5 -Pitch 30, Cross bar 6x6 - Pitch 100. | BH79: 45861 | BI79: 450 | BJ79: 17310 | BK79: 40500 | BL79: =BK79*BJ79*1.1 -> 7.711605e+08 | BM79: 45906 | BN79: =SUMIF($J:$J,J79,$BI:$BI) -> 3356 | BO79: =SUMIF($J:$J,J79,$BJ:$BJ) -> 39034 | CL79: =SUMIF($J:$J,J79,$BZ:$BZ) -> 0 | CM79: =SUMIF($J:$J,J79,$CA:$CA) -> 0 | CR79: =BN79+CL79 -> 3356 | CS79: =BO79+CM79 -> 39034 | CT79: =AZ79-CR79 -> -2644.906 | CU79: =BA79-CS79 -> -3479.3 | CV79: =IF(CT79<0,"Thừa",IF(CT79=0,"Đủ","Thiếu")) -> Thừa | DT79: 749.6024 | DU79: 37480.12
A80: =IF(J80=J79,"ok","Hiện") -> ok | J80: I78-A-52 | K80: gratting-mạ kẽm nóng | L80: GRATTING 32x5 | M80: JIS G3101-SS400-H.D.G | N80: m2 | BC80: 2307-1/HĐKT/IBS-WWHD | BD80: WINWIN HD | BE80: Kẹp sàn Grating (loại SY) | BH80: 45861 | BI80: 1308 | BJ80: 1180 | BK80: 20000 | BL80: =BK80*BI80*1.1 -> 28776000 | BM80: 45906
A81: =IF(J81=J80,"ok","Hiện") -> ok | J81: I78-A-52 | K81: gratting-mạ kẽm nóng | L81: GRATTING 32x5 | M81: JIS G3101-SS400-H.D.G | N81: m2 | BC81: 2407-1/HĐKT/IBS-WWHD | BD81: WINWIN HD | BE81: Tấm sàn (Grating): Serrated bearing bar 32x5 -Pitch 30, Cross bar 6x6 - Pitch 100. | BH81: 45862 | BI81: 418 | BJ81: 19236 | BK81: 40500 | BL81: =BK81*BJ81*1.1 -> 8.569638e+08 | BM81: 45924
A82: =IF(J82=J81,"ok","Hiện") -> ok | J82: I78-A-52 | K82: gratting-mạ kẽm nóng | L82: GRATTING 32x5 | M82: JIS G3101-SS400-H.D.G | N82: m2 | BC82: 2407-1/HĐKT/IBS-WWHD | BD82: WINWIN HD | BE82: Kẹp sàn Grating (loại SY) | BH82: 45862 | BI82: 1180 | BJ82: 1308 | BK82: 20000 | BL82: =BK82*BI82*1.1 -> 25960000 | BM82: 45924
A83: =IF(J83=J82,"ok","Hiện") -> Hiện | B83: =CV83 -> Đủ | C83: =CT83 -> 0 | H83: Thép trắng nhập | J83: I78-A-53 | K83: thép tròn | L83: RB1 | M83: SUS304 | N83: KG | O83: 0 | Q83: 3.16 | T83: 6 | U83: 6 | V83: =VLOOKUP(J83,[113]PR!$A:$S,15,0) -> 0 | W83: =VLOOKUP(J83,[113]PR!$A:$S,16,0) -> 0 | X83: =VLOOKUP(J83,[114]PR!$A:$U,17,0) -> 0 | Y83: =VLOOKUP(J83,[114]PR!$A:$U,18,0) -> 0 | Z83: 0 | AA83: 0 | AB83: 0 | AC83: 0 | AD83: 0 | AE83: 0 | AF83: 0 | AG83: 0 | AH83: 0 | AI83: 0 | AJ83: 0 | AK83: 0 | AL83: 0 | AM83: 0 | AP83: 0 | AQ83: 0 | AR83: =R83+T83+V83+X83+Z83+AB83+AD83+AF83+AH83+AJ83+AL83+AN83+AP83 -> 6 | AS83: =S83+U83+W83+Y83+AA83+AC83+AE83+AG83+AI83+AK83+AM83+AO83+AQ83 -> 6 | AZ83: =IF(AR83>AV83,AR83-AV83,"0") -> 6 | BA83: =IF(AS83>AW83,AS83-AW83,"0") -> 6 | BC83: Chợ sắt | BD83: Quang mua | BE83: INOX 1mm | BG83: 6 | BH83: 45783 | BI83: 6 | BJ83: 6 | BK83: 110000 | BL83: =BK83*BJ83*1.1 -> 726000 | BM83: 45783 | BN83: =SUMIF($J:$J,J83,$BI:$BI) -> 6 | BO83: =SUMIF($J:$J,J83,$BJ:$BJ) -> 6 | CL83: =SUMIF($J:$J,J83,$BZ:$BZ) -> 0 | CM83: =SUMIF($J:$J,J83,$CA:$CA) -> 0 | CR83: =BN83+CL83 -> 6 | CS83: =BO83+CM83 -> 6 | CT83: =AZ83-CR83 -> 0 | CU83: =BA83-CS83 -> 0 | CV83: =IF(CT83<0,"Thừa",IF(CT83=0,"Đủ","Thiếu")) -> Đủ | DE83: 2.24 | DI83: 0.68 | DK83: 0.12 | DM83: 0.12
A84: =IF(J84=J83,"ok","Hiện") -> Hiện | B84: =CV84 -> Thừa | C84: =CT84 -> -0.49056 | G84: Xin chuyển RB14 | H84: Thép trắng nhập | J84: I78-A-54 | K84: thép tròn( % C min 0.04%) | L84: RB13-1510L | M84: JIS.G4303_SUS310S | N84: m | O84: 1 | P84: 1.424 | Q84: 1.34 | T84: 1.50944 | U84: 1.50944 | V84: =VLOOKUP(J84,[113]PR!$A:$S,15,0) -> 0 | W84: =VLOOKUP(J84,[113]PR!$A:$S,16,0) -> 0 | X84: =VLOOKUP(J84,[114]PR!$A:$U,17,0) -> 0 | Y84: =VLOOKUP(J84,[114]PR!$A:$U,18,0) -> 0 | Z84: 0 | AA84: 0 | AB84: 0 | AC84: 0 | AD84: 0 | AE84: 0 | AF84: 0 | AG84: 0 | AH84: 0 | AI84: 0 | AJ84: 0 | AK84: 0 | AL84: 0 | AM84: 0 | AP84: 0 | AQ84: 0 | AR84: =R84+T84+V84+X84+Z84+AB84+AD84+AF84+AH84+AJ84+AL84+AN84+AP84 -> 1.50944 | AS84: =S84+U84+W84+Y84+AA84+AC84+AE84+AG84+AI84+AK84+AM84+AO84+AQ84 -> 1.50944 | AZ84: =IF(AR84>AV84,AR84-AV84,"0") -> 1.50944 | BA84: =IF(AS84>AW84,AS84-AW84,"0") -> 1.50944 | BN84: =SUMIF($J:$J,J84,$BI:$BI) -> 0 | BO84: =SUMIF($J:$J,J84,$BJ:$BJ) -> 0 | BT84: IBSHI-GNEE/2504-08 | BU84: GNEE | BV84: 14*2000 | BW84: SUS310S ROUND BAR | BX84: 2.5 | BY84: 45755 | BZ84: 2 | CA84: 2.5 | CB84: 8.04 | CC84: =CB84*CA84 -> 20.1 | CI84: 45791 | CJ84: 45792 | CL84: =SUMIF($J:$J,J84,$BZ:$BZ) -> 2 | CM84: =SUMIF($J:$J,J84,$CA:$CA) -> 2.5 | CR84: =BN84+CL84 -> 2 | CS84: =BO84+CM84 -> 2.5 | CT84: =AZ84-CR84 -> -0.49056 | CU84: =BA84-CS84 -> -0.99056 | CV84: =IF(CT84<0,"Thừa",IF(CT84=0,"Đủ","Thiếu")) -> Thừa | DD84: 1.424 | DE84: 1.34
A85: =IF(J85=J84,"ok","Hiện") -> Hiện | B85: =CV85 -> Thừa | C85: =CT85 -> -0.3522 | H85: Thép đen | J85: I78-A-55 | K85: thép tròn | L85: RB13-6000L | M85: JIS G3101-SS400 | N85: m | O85: 1 | P85: 33.63 | Q85: 31.36 | T85: 35.6478 | U85: 35.6478 | V85: =VLOOKUP(J85,[113]PR!$A:$S,15,0) -> 0 | W85: =VLOOKUP(J85,[113]PR!$A:$S,16,0) -> 0 | X85: =VLOOKUP(J85,[114]PR!$A:$U,17,0) -> 0 | Y85: =VLOOKUP(J85,[114]PR!$A:$U,18,0) -> 0 | Z85: 0 | AA85: 0 | AB85: 0 | AC85: 0 | AD85: 0 | AE85: 0 | AF85: 0 | AG85: 0 | AH85: 0 | AI85: 0 | AJ85: 0 | AK85: 0 | AL85: 0 | AM85: 0 | AP85: 0 | AQ85: 0 | AR85: =R85+T85+V85+X85+Z85+AB85+AD85+AF85+AH85+AJ85+AL85+AN85+AP85 -> 35.6478 | AS85: =S85+U85+W85+Y85+AA85+AC85+AE85+AG85+AI85+AK85+AM85+AO85+AQ85 -> 35.6478 | AZ85: =IF(AR85>AV85,AR85-AV85,"0") -> 35.6478 | BA85: =IF(AS85>AW85,AS85-AW85,"0") -> 35.6478 | BN85: =SUMIF($J:$J,J85,$BI:$BI) -> 0 | BO85: =SUMIF($J:$J,J85,$BJ:$BJ) -> 0 | BT85: IBSHI-GNEE/2503-18 | BU85: GNEE STEEL CO., LIMITED | BV85: RB14*6000 | BW85: JIS G3101-SS400 | BX85: 43.8 | BY85: 45734 | BZ85: 36 | CA85: 43.8 | CB85: 0.75 | CC85: =CB85*CA85 -> 32.85 | CK85: 45795 | CL85: =SUMIF($J:$J,J85,$BZ:$BZ) -> 36 | CM85: =SUMIF($J:$J,J85,$CA:$CA) -> 43.8 | CR85: =BN85+CL85 -> 36 | CS85: =BO85+CM85 -> 43.8 | CT85: =AZ85-CR85 -> -0.3522 | CU85: =BA85-CS85 -> -8.1522 | CV85: =IF(CT85<0,"Thừa",IF(CT85=0,"Đủ","Thiếu")) -> Thừa | DD85: 3.54 | DE85: 3.3 | DH85: 7.08 | DI85: 6.6 | DJ85: 7.08 | DK85: 6.6 | DL85: 7.08 | DM85: 6.6 | DN85: 7.08 | DO85: 6.6 | DP85: 1.77 | DQ85: 1.66
A86: =IF(J86=J85,"ok","Hiện") -> Hiện | B86: =CV86 -> Thừa | C86: =CT86 -> -4.5062 | H86: Thép đen | J86: I78-A-56 | K86: thép tròn | L86: RB16-6000L | M86: JIS G3101-SS400 | N86: m | O86: 1.6 | P86: 12.73 | Q86: 18.08 | T86: 13.4938 | U86: 21.59008 | V86: =VLOOKUP(J86,[113]PR!$A:$S,15,0) -> 0 | W86: =VLOOKUP(J86,[113]PR!$A:$S,16,0) -> 0 | X86: =VLOOKUP(J86,[114]PR!$A:$U,17,0) -> 0 | Y86: =VLOOKUP(J86,[114]PR!$A:$U,18,0) -> 0 | Z86: 0 | AA86: 0 | AB86: 0 | AC86: 0 | AD86: 0 | AE86: 0 | AF86: 0 | AG86: 0 | AH86: 0 | AI86: 0 | AJ86: 0 | AK86: 0 | AL86: 0 | AM86: 0 | AP86: 0 | AQ86: 0 | AR86: =R86+T86+V86+X86+Z86+AB86+AD86+AF86+AH86+AJ86+AL86+AN86+AP86 -> 13.4938 | AS86: =S86+U86+W86+Y86+AA86+AC86+AE86+AG86+AI86+AK86+AM86+AO86+AQ86 -> 21.59008 | AZ86: =IF(AR86>AV86,AR86-AV86,"0") -> 13.4938 | BA86: =IF(AS86>AW86,AS86-AW86,"0") -> 21.59008 | BN86: =SUMIF($J:$J,J86,$BI:$BI) -> 0 | BO86: =SUMIF($J:$J,J86,$BJ:$BJ) -> 0 | BT86: IBSHI-GNEE/2503-18 | BU86: GNEE STEEL CO., LIMITED | BV86: RB16*6000 | BW86: JIS G3101-SS400 | BX86: 28.5 | BY86: 45734 | BZ86: 18 | CA86: 28.5 | CB86: 0.75 | CC86: =CB86*CA86 -> 21.375 | CK86: 45795 | CL86: =SUMIF($J:$J,J86,$BZ:$BZ) -> 18 | CM86: =SUMIF($J:$J,J86,$CA:$CA) -> 28.5 | CR86: =BN86+CL86 -> 18 | CS86: =BO86+CM86 -> 28.5 | CT86: =AZ86-CR86 -> -4.5062 | CU86: =BA86-CS86 -> -6.90992 | CV86: =IF(CT86<0,"Thừa",IF(CT86=0,"Đủ","Thiếu")) -> Thừa | DT86: 12.73 | DU86: 18.08
A87: =IF(J87=J86,"ok","Hiện") -> Hiện | B87: =CV87 -> Đủ | C87: =CT87 -> 0 | G87: Hàng tồn | H87: Thép đen | J87: I78-A-57 | K87: thép tròn | L87: RB19-6000L | M87: JIS G3101-SS400 | N87: m | O87: 2.2 | P87: 21.4 | Q87: 42.72 | T87: 22.684 | U87: 49.9048 | V87: =VLOOKUP(J87,[113]PR!$A:$S,15,0) -> 0 | W87: =VLOOKUP(J87,[113]PR!$A:$S,16,0) -> 0 | X87: =VLOOKUP(J87,[114]PR!$A:$U,17,0) -> 0 | Y87: =VLOOKUP(J87,[114]PR!$A:$U,18,0) -> 0 | Z87: 0 | AA87: 0 | AB87: 0 | AC87: 0 | AD87: 0 | AE87: 0 | AF87: 0 | AG87: 0 | AH87: 0 | AI87: 0 | AJ87: 0 | AK87: 0 | AL87: 0 | AM87: 0 | AP87: 0 | AQ87: 0 | AR87: =R87+T87+V87+X87+Z87+AB87+AD87+AF87+AH87+AJ87+AL87+AN87+AP87 -> 22.684 | AS87: =S87+U87+W87+Y87+AA87+AC87+AE87+AG87+AI87+AK87+AM87+AO87+AQ87 -> 49.9048 | AV87: 22.684 | AW87: 49.9048 | AY87: Đã mời nghiệm thu ngyaf 18/4 | AZ87: =IF(AR87>AV87,AR87-AV87,"0") -> 0 | BA87: =IF(AS87>AW87,AS87-AW87,"0") -> 0 | BN87: =SUMIF($J:$J,J87,$BI:$BI) -> 0 | BO87: =SUMIF($J:$J,J87,$BJ:$BJ) -> 0 | CL87: =SUMIF($J:$J,J87,$BZ:$BZ) -> 0 | CM87: =SUMIF($J:$J,J87,$CA:$CA) -> 0 | CR87: =BN87+CL87 -> 0 | CS87: =BO87+CM87 -> 0 | CT87: =AZ87-CR87 -> 0 | CU87: =BA87-CS87 -> 0 | CV87: =IF(CT87<0,"Thừa",IF(CT87=0,"Đủ","Thiếu")) -> Đủ | DD87: 2.14 | DE87: 4.28 | DH87: 4.28 | DI87: 8.54 | DJ87: 4.28 | DK87: 8.54 | DL87: 4.28 | DM87: 8.54 | DN87: 4.28 | DO87: 8.54 | DP87: 1.07 | DQ87: 2.14 | DR87: 1.07 | DS87: 2.14
A88: =IF(J88=J87,"ok","Hiện") -> Hiện | B88: =CV88 -> Thừa | C88: =CT88 -> -2.32248 | H88: Thép đen | J88: I78-A-58 | K88: thép tròn | L88: RB38-6000L | M88: JIS G3101-SS400 | N88: m | O88: 8.9 | P88: 43.092 | Q88: 359.56 | T88: 45.67752 | U88: 406.52993 | V88: =VLOOKUP(J88,[113]PR!$A:$S,15,0) -> 0 | W88: =VLOOKUP(J88,[113]PR!$A:$S,16,0) -> 0 | X88: =VLOOKUP(J88,[114]PR!$A:$U,17,0) -> 0 | Y88: =VLOOKUP(J88,[114]PR!$A:$U,18,0) -> 0 | Z88: 0 | AA88: 0 | AB88: 0 | AC88: 0 | AD88: 0 | AE88: 0 | AF88: 0 | AG88: 0 | AH88: 0 | AI88: 0 | AJ88: 0 | AK88: 0 | AL88: 0 | AM88: 0 | AP88: 0 | AQ88: 0 | AR88: =R88+T88+V88+X88+Z88+AB88+AD88+AF88+AH88+AJ88+AL88+AN88+AP88 -> 45.67752 | AS88: =S88+U88+W88+Y88+AA88+AC88+AE88+AG88+AI88+AK88+AM88+AO88+AQ88 -> 406.52993 | AZ88: =IF(AR88>AV88,AR88-AV88,"0") -> 45.67752 | BA88: =IF(AS88>AW88,AS88-AW88,"0") -> 406.52993 | BN88: =SUMIF($J:$J,J88,$BI:$BI) -> 0 | BO88: =SUMIF($J:$J,J88,$BJ:$BJ) -> 0 | BT88: IBSHI-GNEE/2503-18 | BU88: GNEE STEEL CO., LIMITED | BV88: RB38*6000 | BW88: JIS G3101-SS400 | BX88: 428 | BY88: 45734 | BZ88: 48 | CA88: 428 | CB88: 0.75 | CC88: =CB88*CA88 -> 321 | CK88: 45795 | CL88: =SUMIF($J:$J,J88,$BZ:$BZ) -> 48 | CM88: =SUMIF($J:$J,J88,$CA:$CA) -> 428 | CR88: =BN88+CL88 -> 48 | CS88: =BO88+CM88 -> 428 | CT88: =AZ88-CR88 -> -2.32248 | CU88: =BA88-CS88 -> -21.470072 | CV88: =IF(CT88<0,"Thừa",IF(CT88=0,"Đủ","Thiếu")) -> Thừa | DD88: 4.456 | DE88: 37.16 | DH88: 9.52 | DI88: 79.5 | DJ88: 8.912 | DK88: 74.34 | DL88: 8.912 | DM88: 74.34 | DN88: 8.912 | DO88: 74.34 | DP88: 2.38 | DQ88: 19.88
A89: =IF(J89=J88,"ok","Hiện") -> Hiện | B89: =CV89 -> Thừa | C89: =CT89 -> -0.9532 | H89: Thép đen | J89: I78-A-59 | K89: thép xoắn | L89: THÉP XOẮN XÂY DỰNG D27-11800L | M89: JIS G3101-SS400 | N89: m | O89: 4.2919374 | P89: 187.78 | Q89: 805.94 | T89: 199.0468 | U89: 854.2964 | V89: =VLOOKUP(J89,[113]PR!$A:$S,15,0) -> 0 | W89: =VLOOKUP(J89,[113]PR!$A:$S,16,0) -> 0 | X89: =VLOOKUP(J89,[114]PR!$A:$U,17,0) -> 0 | Y89: =VLOOKUP(J89,[114]PR!$A:$U,18,0) -> 0 | Z89: 0 | AA89: 0 | AB89: 0 | AC89: 0 | AD89: 0 | AE89: 0 | AF89: 0 | AG89: 0 | AH89: 0 | AI89: 0 | AJ89: 0 | AK89: 0 | AL89: 0 | AM89: 0 | AP89: 0 | AQ89: 0 | AR89: =R89+T89+V89+X89+Z89+AB89+AD89+AF89+AH89+AJ89+AL89+AN89+AP89 -> 199.0468 | AS89: =S89+U89+W89+Y89+AA89+AC89+AE89+AG89+AI89+AK89+AM89+AO89+AQ89 -> 854.2964 | AZ89: =IF(AR89>AV89,AR89-AV89,"0") -> 199.0468 | BA89: =IF(AS89>AW89,AS89-AW89,"0") -> 854.2964 | BC89: Báo giá ngày 12/5/2025 | BD89: Sao Phương nam | BE89: Thép xoắn D28 | BF89: CB400 | BG89: 878 | BH89: 45789 | BI89: 200 | BJ89: 878 | BK89: 14500 | BL89: =13661000+348000 -> 14009000 | BM89: 45789 | BN89: =SUMIF($J:$J,J89,$BI:$BI) -> 200 | BO89: =SUMIF($J:$J,J89,$BJ:$BJ) -> 878 | CL89: =SUMIF($J:$J,J89,$BZ:$BZ) -> 0 | CM89: =SUMIF($J:$J,J89,$CA:$CA) -> 0 | CR89: =BN89+CL89 -> 200 | CS89: =BO89+CM89 -> 878 | CT89: =AZ89-CR89 -> -0.9532 | CU89: =BA89-CS89 -> -23.7036 | CV89: =IF(CT89<0,"Thừa",IF(CT89=0,"Đủ","Thiếu")) -> Thừa | DT89: 187.78 | DU89: 805.94
A90: =IF(J90=J89,"ok","Hiện") -> Hiện | B90: =CV90 -> Thừa | C90: =CT90 -> -3.72724 | H90: Thép đen nhập | J90: I78-A-60 | K90: ống hộp vuông | L90: SHS100x100x6-6000L | M90: STKR400 | N90: m | O90: 17 | P90: 30.446 | Q90: 535.54 | T90: 32.27276 | U90: 548.63692 | V90: =VLOOKUP(J90,[113]PR!$A:$S,15,0) -> 0 | W90: =VLOOKUP(J90,[113]PR!$A:$S,16,0) -> 0 | X90: =VLOOKUP(J90,[114]PR!$A:$U,17,0) -> 0 | Y90: =VLOOKUP(J90,[114]PR!$A:$U,18,0) -> 0 | Z90: 0 | AA90: 0 | AB90: 0 | AC90: 0 | AD90: 0 | AE90: 0 | AF90: 0 | AG90: 0 | AH90: 0 | AI90: 0 | AJ90: 0 | AK90: 0 | AL90: 0 | AM90: 0 | AP90: 0 | AQ90: 0 | AR90: =R90+T90+V90+X90+Z90+AB90+AD90+AF90+AH90+AJ90+AL90+AN90+AP90 -> 32.27276 | AS90: =S90+U90+W90+Y90+AA90+AC90+AE90+AG90+AI90+AK90+AM90+AO90+AQ90 -> 548.63692 | AZ90: =IF(AR90>AV90,AR90-AV90,"0") -> 32.27276 | BA90: =IF(AS90>AW90,AS90-AW90,"0") -> 548.63692 | BN90: =SUMIF($J:$J,J90,$BI:$BI) -> 0 | BO90: =SUMIF($J:$J,J90,$BJ:$BJ) -> 0 | BT90: IBSHI-GNEE/2503-18 | BU90: GNEE STEEL CO., LIMITED | BV90: SHS100*100*6*6000 | BW90: STKR400 | BX90: 637.8 | BY90: 45734 | BZ90: 36 | CA90: 637.8 | CB90: 0.65 | CC90: =CB90*CA90 -> 414.57 | CK90: 45795 | CL90: =SUMIF($J:$J,J90,$BZ:$BZ) -> 36 | CM90: =SUMIF($J:$J,J90,$CA:$CA) -> 637.8 | CR90: =BN90+CL90 -> 36 | CS90: =BO90+CM90 -> 637.8 | CT90: =AZ90-CR90 -> -3.72724 | CU90: =BA90-CS90 -> -89.16308 | CV90: =IF(CT90<0,"Thừa",IF(CT90=0,"Đủ","Thiếu")) -> Thừa | DV90: 30.446 | DW90: 535.54
A91: =IF(J91=J90,"ok","Hiện") -> Hiện | B91: =CV91 -> Thừa | C91: =CT91 -> -1.30964 | H91: Thép trắng nhập | J91: I78-A-61 | K91: ống hộp vuông( % C min 0.04%) | L91: SHS150x150x5-6000L | M91: ASTM-A544_TP304 | N91: m | O91: 22.5 | P91: 21.406 | Q91: 490.24 | T91: 22.69036 | U91: 510.5331 | V91: =VLOOKUP(J91,[113]PR!$A:$S,15,0) -> 0 | W91: =VLOOKUP(J91,[113]PR!$A:$S,16,0) -> 0 | X91: =VLOOKUP(J91,[114]PR!$A:$U,17,0) -> 0 | Y91: =VLOOKUP(J91,[114]PR!$A:$U,18,0) -> 0 | Z91: 0 | AA91: 0 | AB91: 0 | AC91: 0 | AD91: 0 | AE91: 0 | AF91: 0 | AG91: 0 | AH91: 0 | AI91: 0 | AJ91: 0 | AK91: 0 | AL91: 0 | AM91: 0 | AP91: 0 | AQ91: 0 | AR91: =R91+T91+V91+X91+Z91+AB91+AD91+AF91+AH91+AJ91+AL91+AN91+AP91 -> 22.69036 | AS91: =S91+U91+W91+Y91+AA91+AC91+AE91+AG91+AI91+AK91+AM91+AO91+AQ91 -> 510.5331 | AZ91: =IF(AR91>AV91,AR91-AV91,"0") -> 22.69036 | BA91: =IF(AS91>AW91,AS91-AW91,"0") -> 510.5331 | BN91: =SUMIF($J:$J,J91,$BI:$BI) -> 0 | BO91: =SUMIF($J:$J,J91,$BJ:$BJ) -> 0 | BT91: IBSHI-GNEE/2504-08 | BU91: GNEE | BV91: 150*150*5*6000 | BW91: A544 TP304 SHS | BX91: 552 | BY91: 45755 | BZ91: 24 | CA91: 552 | CB91: 3.31 | CC91: =CB91*CA91 -> 1827.12 | CI91: 45791 | CJ91: 45792 | CL91: =SUMIF($J:$J,J91,$BZ:$BZ) -> 24 | CM91: =SUMIF($J:$J,J91,$CA:$CA) -> 552 | CR91: =BN91+CL91 -> 24 | CS91: =BO91+CM91 -> 552 | CT91: =AZ91-CR91 -> -1.30964 | CU91: =BA91-CS91 -> -41.4669 | CV91: =IF(CT91<0,"Thừa",IF(CT91=0,"Đủ","Thiếu")) -> Thừa | DD91: 21.406 | DE91: 490.24
A92: =IF(J92=J91,"ok","Hiện") -> Hiện | B92: =CV92 -> Đủ | C92: =CT92 -> 0 | H92: Thép đen nhập | J92: I78-A-62 | K92: ống hộp vuông | L92: SHS150x150x6-6000L | M92: STKR400 | N92: m | O92: 26.4 | P92: 5.6 | Q92: 151.26 | T92: 6 | U92: 158.4 | V92: =VLOOKUP(J92,[113]PR!$A:$S,15,0) -> 0 | W92: =VLOOKUP(J92,[113]PR!$A:$S,16,0) -> 0 | X92: =VLOOKUP(J92,[114]PR!$A:$U,17,0) -> 0 | Y92: =VLOOKUP(J92,[114]PR!$A:$U,18,0) -> 0 | Z92: 0 | AA92: 0 | AB92: 0 | AC92: 0 | AD92: 0 | AE92: 0 | AF92: 0 | AG92: 0 | AH92: 0 | AI92: 0 | AJ92: 0 | AK92: 0 | AL92: 0 | AM92: 0 | AP92: 0 | AQ92: 0 | AR92: =R92+T92+V92+X92+Z92+AB92+AD92+AF92+AH92+AJ92+AL92+AN92+AP92 -> 6 | AS92: =S92+U92+W92+Y92+AA92+AC92+AE92+AG92+AI92+AK92+AM92+AO92+AQ92 -> 158.4 | AZ92: =IF(AR92>AV92,AR92-AV92,"0") -> 6 | BA92: =IF(AS92>AW92,AS92-AW92,"0") -> 158.4 | BN92: =SUMIF($J:$J,J92,$BI:$BI) -> 0 | BO92: =SUMIF($J:$J,J92,$BJ:$BJ) -> 0 | BT92: IBSHI-GNEE/2503-18 | BU92: GNEE STEEL CO., LIMITED | BV92: SHS150*150*6*6000 | BW92: STKR400 | BX92: 162.8 | BY92: 45734 | BZ92: 6 | CA92: 162.8 | CB92: 0.65 | CC92: =CB92*CA92 -> 105.82 | CK92: 45795 | CL92: =SUMIF($J:$J,J92,$BZ:$BZ) -> 6 | CM92: =SUMIF($J:$J,J92,$CA:$CA) -> 162.8 | CR92: =BN92+CL92 -> 6 | CS92: =BO92+CM92 -> 162.8 | CT92: =AZ92-CR92 -> 0 | CU92: =BA92-CS92 -> -4.4 | CV92: =IF(CT92<0,"Thừa",IF(CT92=0,"Đủ","Thiếu")) -> Đủ | DV92: 5.6 | DW92: 151.26
A93: =IF(J93=J92,"ok","Hiện") -> Hiện | B93: =CONCATENATE(CV93," Thiếu ít") -> Thiếu Thiếu ít | C93: =CT93 -> 0.00144 | H93: Thép đen nhập | J93: I78-A-63 | K93: ống hộp vuông | L93: SHS200x200x6-6000L | M93: STKR400 | N93: m | O93: 35.8 | P93: 9.624 | Q93: 356.82 | T93: 10.20144 | U93: 365.21155 | V93: =VLOOKUP(J93,[113]PR!$A:$S,15,0) -> 0 | W93: =VLOOKUP(J93,[113]PR!$A:$S,16,0) -> 0 | X93: =VLOOKUP(J93,[114]PR!$A:$U,17,0) -> 0 | Y93: =VLOOKUP(J93,[114]PR!$A:$U,18,0) -> 0 | Z93: 0 | AA93: 0 | AB93: 0 | AC93: 0 | AD93: 0 | AE93: 0 | AF93: 0 | AG93: 0 | AH93: 1.8 | AI93: 64.44 | AJ93: 0 | AK93: 0 | AL93: 0 | AM93: 0 | AP93: 0 | AQ93: 0 | AR93: =R93+T93+V93+X93+Z93+AB93+AD93+AF93+AH93+AJ93+AL93+AN93+AP93 -> 12.00144 | AS93: =S93+U93+W93+Y93+AA93+AC93+AE93+AG93+AI93+AK93+AM93+AO93+AQ93 -> 429.65155 | AT93: REV8-KHÁCH HÀNG REV | AZ93: =IF(AR93>AV93,AR93-AV93,"0") -> 12.00144 | BA93: =IF(AS93>AW93,AS93-AW93,"0") -> 429.65155 | BN93: =SUMIF($J:$J,J93,$BI:$BI) -> 0 | BO93: =SUMIF($J:$J,J93,$BJ:$BJ) -> 0 | BT93: IBSHI-GNEE/2503-18 | BU93: GNEE STEEL CO., LIMITED | BV93: SHS200*200*6*6000 | BW93: STKR400 | BX93: 438.6 | BY93: 45734 | BZ93: 12 | CA93: 438.6 | CB93: 0.66 | CC93: =CB93*CA93 -> 289.476 | CK93: 45795 | CL93: =SUMIF($J:$J,J93,$BZ:$BZ) -> 12 | CM93: =SUMIF($J:$J,J93,$CA:$CA) -> 438.6 | CR93: =BN93+CL93 -> 12 | CS93: =BO93+CM93 -> 438.6 | CT93: =AZ93-CR93 -> 0.00144 | CU93: =BA93-CS93 -> -8.948448 | CV93: =IF(CT93<0,"Thừa",IF(CT93=0,"Đủ","Thiếu")) -> Thiếu | DV93: 9.624 | DW93: 356.82
A94: =IF(J94=J93,"ok","Hiện") -> Hiện | B94: =CV94 -> Thừa | C94: =CT94 -> -3.77824 | J94: I78-A-64 | K94: thép ống( % C min 0.04%) | L94: CHS21.3x3.7-6000L | M94: ASTM-A312 TP304 | N94: m | O94: 1.6 | P94: 2.096 | Q94: 3.26 | T94: 2.22176 | U94: 3.554816 | V94: =VLOOKUP(J94,[113]PR!$A:$S,15,0) -> 0 | W94: =VLOOKUP(J94,[113]PR!$A:$S,16,0) -> 0 | X94: =VLOOKUP(J94,[114]PR!$A:$U,17,0) -> 0 | Y94: =VLOOKUP(J94,[114]PR!$A:$U,18,0) -> 0 | Z94: 0 | AA94: 0 | AB94: 0 | AC94: 0 | AD94: 0 | AE94: 0 | AF94: 0 | AG94: 0 | AH94: 0 | AI94: 0 | AJ94: 0 | AK94: 0 | AL94: 0 | AM94: 0 | AP94: 0 | AQ94: 0 | AR94: =R94+T94+V94+X94+Z94+AB94+AD94+AF94+AH94+AJ94+AL94+AN94+AP94 -> 2.22176 | AS94: =S94+U94+W94+Y94+AA94+AC94+AE94+AG94+AI94+AK94+AM94+AO94+AQ94 -> 3.554816 | AZ94: =IF(AR94>AV94,AR94-AV94,"0") -> 2.22176 | BA94: =IF(AS94>AW94,AS94-AW94,"0") -> 3.554816 | BC94: Dơn đặt hàng số 08072025 | BD94: Thịnh Phát | BE94: 1 ống 21.3x3.73/304 A312=1c=10kg x 95k (DA078) | BF94: 304 | BG94: 9.2 | BH94: 45846 | BI94: 6 | BJ94: 9.2 | BK94: =95000/1.1 -> 86363.636 | BL94: =BK94*BJ94*1.1 -> 874000 | BM94: 45842 | BN94: =SUMIF($J:$J,J94,$BI:$BI) -> 6 | BO94: =SUMIF($J:$J,J94,$BJ:$BJ) -> 9.2 | CL94: =SUMIF($J:$J,J94,$BZ:$BZ) -> 0 | CM94: =SUMIF($J:$J,J94,$CA:$CA) -> 0 | CR94: =BN94+CL94 -> 6 | CS94: =BO94+CM94 -> 9.2 | CT94: =AZ94-CR94 -> -3.77824 | CU94: =BA94-CS94 -> -5.645184 | CV94: =IF(CT94<0,"Thừa",IF(CT94=0,"Đủ","Thiếu")) -> Thừa | DH94: 2.096 | DI94: 3.26
A95: =IF(J95=J94,"ok","Hiện") -> Hiện | B95: =CV95 -> Đủ | C95: =CT95 -> 0 | E95: GNEE đã chốt đơn 2/ Hàng tồn | H95: Thép trắng nhập | J95: I78-A-65 | K95: thép ống( % C min 0.04%) | L95: CHS33.4x4.5-6000L | M95: ASME-SA312-TP304 | N95: m | O95: 3.2 | P95: 29.468 | Q95: 91.16 | T95: 31.23608 | U95: 99.955456 | V95: =VLOOKUP(J95,[113]PR!$A:$S,15,0) -> 0 | W95: =VLOOKUP(J95,[113]PR!$A:$S,16,0) -> 0 | X95: =VLOOKUP(J95,[114]PR!$A:$U,17,0) -> 0 | Y95: =VLOOKUP(J95,[114]PR!$A:$U,18,0) -> 0 | Z95: 0 | AA95: 0 | AB95: 0 | AC95: 0 | AD95: 0 | AE95: 0 | AF95: 0 | AG95: 0 | AH95: 0 | AI95: 0 | AJ95: 0 | AK95: 0 | AL95: 0 | AM95: 0 | AP95: 0 | AQ95: 0 | AR95: =R95+T95+V95+X95+Z95+AB95+AD95+AF95+AH95+AJ95+AL95+AN95+AP95 -> 31.23608 | AS95: =S95+U95+W95+Y95+AA95+AC95+AE95+AG95+AI95+AK95+AM95+AO95+AQ95 -> 99.955456 | AV95: 7.23608 | AW95: =AV95*O95 -> 23.155456 | AY95: Đã mời nghiệm thu ngày 15/5 | AZ95: =IF(AR95>AV95,AR95-AV95,"0") -> 24 | BA95: =IF(AS95>AW95,AS95-AW95,"0") -> 76.8 | BN95: =SUMIF($J:$J,J95,$BI:$BI) -> 0 | BO95: =SUMIF($J:$J,J95,$BJ:$BJ) -> 0 | BT95: IBSHI-GNEE/2504-08 | BU95: GNEE | BV95: 33.4*4.5*6000 | BW95: SA312-TP304 PIPE | BX95: 77.6 | BY95: 45755 | BZ95: 24 | CA95: 77.6 | CB95: 3.31 | CC95: =CB95*CA95 -> 256.856 | CI95: 45791 | CJ95: 45792 | CL95: =SUMIF($J:$J,J95,$BZ:$BZ) -> 24 | CM95: =SUMIF($J:$J,J95,$CA:$CA) -> 77.6 | CR95: =BN95+CL95 -> 24 | CS95: =BO95+CM95 -> 77.6 | CT95: =AZ95-CR95 -> 0 | CU95: =BA95-CS95 -> -0.8 | CV95: =IF(CT95<0,"Thừa",IF(CT95=0,"Đủ","Thiếu")) -> Đủ | DX95: 29.468 | DY95: 91.16
A96: =IF(J96=J95,"ok","Hiện") -> Hiện | B96: =CV96 -> Thừa | C96: =CT96 -> -1.83288 | H96: Thép đen nhập | J96: I78-A-66 | K96: thép ống | L96: CHS48.3x3.6-6000L | M96: ASTM-A106-GRB | N96: m | O96: 4.1 | P96: 15.252 | Q96: 60.58 | T96: 16.16712 | U96: 66.285192 | V96: =VLOOKUP(J96,[113]PR!$A:$S,15,0) -> 0 | W96: =VLOOKUP(J96,[113]PR!$A:$S,16,0) -> 0 | X96: =VLOOKUP(J96,[114]PR!$A:$U,17,0) -> 0 | Y96: =VLOOKUP(J96,[114]PR!$A:$U,18,0) -> 0 | Z96: 0 | AA96: 0 | AB96: 0 | AC96: 0 | AD96: 0 | AE96: 0 | AF96: 0 | AG96: 0 | AH96: 0 | AI96: 0 | AJ96: 0 | AK96: 0 | AL96: 0 | AM96: 0 | AP96: 0 | AQ96: 0 | AR96: =R96+T96+V96+X96+Z96+AB96+AD96+AF96+AH96+AJ96+AL96+AN96+AP96 -> 16.16712 | AS96: =S96+U96+W96+Y96+AA96+AC96+AE96+AG96+AI96+AK96+AM96+AO96+AQ96 -> 66.285192 | AZ96: =IF(AR96>AV96,AR96-AV96,"0") -> 16.16712 | BA96: =IF(AS96>AW96,AS96-AW96,"0") -> 66.285192 | BN96: =SUMIF($J:$J,J96,$BI:$BI) -> 0 | BO96: =SUMIF($J:$J,J96,$BJ:$BJ) -> 0 | BT96: IBSHI-GNEE/2503-18 | BU96: GNEE STEEL CO., LIMITED | BV96: CHS48.3*3.6*6000 | BW96: ASTM-A106-GRB | BX96: 71.4 | BY96: 45734 | BZ96: 18 | CA96: 71.4 | CB96: 0.78 | CC96: =CB96*CA96 -> 55.692 | CK96: 45795 | CL96: =SUMIF($J:$J,J96,$BZ:$BZ) -> 18 | CM96: =SUMIF($J:$J,J96,$CA:$CA) -> 71.4 | CR96: =BN96+CL96 -> 18 | CS96: =BO96+CM96 -> 71.4 | CT96: =AZ96-CR96 -> -1.83288 | CU96: =BA96-CS96 -> -5.114808 | CV96: =IF(CT96<0,"Thừa",IF(CT96=0,"Đủ","Thiếu")) -> Thừa | DR96: 15.252 | DS96: 60.58
A97: =IF(J97=J96,"ok","Hiện") -> Hiện | B97: =CV97 -> Thừa | C97: =CT97 -> -243.72204 | H97: Thép đen nhập | J97: I78-A-67 | K97: thép ống | L97: CHS48.3x3.6-6000L | M97: ASTM-A53-GR.B | N97: m | O97: 4.1 | P97: 4706.866 | Q97: 18695.96 | T97: 4989.278 | U97: 20456.04 | V97: =VLOOKUP(J97,[113]PR!$A:$S,15,0) -> 0 | W97: =VLOOKUP(J97,[113]PR!$A:$S,16,0) -> 0 | X97: =VLOOKUP(J97,[114]PR!$A:$U,17,0) -> -283 | Y97: =VLOOKUP(J97,[114]PR!$A:$U,18,0) -> -1160.3 | Z97: 0 | AA97: 0 | AB97: 0 | AC97: 0 | AD97: 0 | AE97: 0 | AF97: 0 | AG97: 0 | AH97: 0 | AI97: 0 | AJ97: 0 | AK97: 0 | AL97: 0 | AM97: 0 | AP97: 0 | AQ97: 0 | AR97: =R97+T97+V97+X97+Z97+AB97+AD97+AF97+AH97+AJ97+AL97+AN97+AP97 -> 4706.278 | AS97: =S97+U97+W97+Y97+AA97+AC97+AE97+AG97+AI97+AK97+AM97+AO97+AQ97 -> 19295.74 | AT97: REV3-IBS REV GIẢM SL | AZ97: =IF(AR97>AV97,AR97-AV97,"0") -> 4706.278 | BA97: =IF(AS97>AW97,AS97-AW97,"0") -> 19295.74 | BN97: =SUMIF($J:$J,J97,$BI:$BI) -> 0 | BO97: =SUMIF($J:$J,J97,$BJ:$BJ) -> 0 | BT97: IBSHI-GNEE/2503-18 | BU97: GNEE STEEL CO., LIMITED | BV97: CHS48.3*3.6*6000 | BW97: ASTM-A53-GR.B | BX97: 19635 | BY97: 45734 | BZ97: 4950 | CA97: 19635 | CB97: 0.78 | CC97: =CB97*CA97 -> 15315.3 | CK97: 45795 | CL97: =SUMIF($J:$J,J97,$BZ:$BZ) -> 4950 | CM97: =SUMIF($J:$J,J97,$CA:$CA) -> 19635 | CR97: =BN97+CL97 -> 4950 | CS97: =BO97+CM97 -> 19635 | CT97: =AZ97-CR97 -> -243.72204 | CU97: =BA97-CS97 -> -339.26036 | CV97: =IF(CT97<0,"Thừa",IF(CT97=0,"Đủ","Thiếu")) -> Thừa | DT97: 4706.962 | DU97: 18696.34
A98: =IF(J98=J97,"ok","Hiện") -> Hiện | B98: =CV98 -> Thừa | C98: =CT98 -> -3.0226 | H98: Thép đen nhập | J98: I78-A-68 | K98: thép ống | L98: CHS60.3x3.91-6000L | M98: ASTM-A106-GRB | N98: m | O98: 5.4 | P98: 19.79 | Q98: 103.72 | T98: 20.9774 | U98: 113.27796 | V98: =VLOOKUP(J98,[113]PR!$A:$S,15,0) -> 0 | W98: =VLOOKUP(J98,[113]PR!$A:$S,16,0) -> 0 | X98: =VLOOKUP(J98,[114]PR!$A:$U,17,0) -> 0 | Y98: =VLOOKUP(J98,[114]PR!$A:$U,18,0) -> 0 | Z98: 0 | AA98: 0 | AB98: 0 | AC98: 0 | AD98: 0 | AE98: 0 | AF98: 0 | AG98: 0 | AH98: 0 | AI98: 0 | AJ98: 0 | AK98: 0 | AL98: 0 | AM98: 0 | AP98: 0 | AQ98: 0 | AR98: =R98+T98+V98+X98+Z98+AB98+AD98+AF98+AH98+AJ98+AL98+AN98+AP98 -> 20.9774 | AS98: =S98+U98+W98+Y98+AA98+AC98+AE98+AG98+AI98+AK98+AM98+AO98+AQ98 -> 113.27796 | AZ98: =IF(AR98>AV98,AR98-AV98,"0") -> 20.9774 | BA98: =IF(AS98>AW98,AS98-AW98,"0") -> 113.27796 | BN98: =SUMIF($J:$J,J98,$BI:$BI) -> 0 | BO98: =SUMIF($J:$J,J98,$BJ:$BJ) -> 0 | BT98: IBSHI-GNEE/2503-18 | BU98: GNEE STEEL CO., LIMITED | BV98: CHS60.3*3.91*6000 | BW98: ASTM-A106-GRB | BX98: 130.4 | BY98: 45734 | BZ98: 24 | CA98: 130.4 | CB98: 0.8 | CC98: =CB98*CA98 -> 104.32 | CK98: 45795 | CL98: =SUMIF($J:$J,J98,$BZ:$BZ) -> 24 | CM98: =SUMIF($J:$J,J98,$CA:$CA) -> 130.4 | CR98: =BN98+CL98 -> 24 | CS98: =BO98+CM98 -> 130.4 | CT98: =AZ98-CR98 -> -3.0226 | CU98: =BA98-CS98 -> -17.12204 | CV98: =IF(CT98<0,"Thừa",IF(CT98=0,"Đủ","Thiếu")) -> Thừa | DB98: 1 | DC98: 5.44 | DP98: 17.29 | DQ98: 90.32 | DR98: 1.504 | DS98: 7.96
A99: =IF(J99=J98,"ok","Hiện") -> Hiện | B99: =CV99 -> Đủ | C99: =CT99 -> 0 | E99: GNEE đã chốt đơn 2/ Hàng tồn | H99: Thép trắng nhập | J99: I78-A-69 | K99: thép ống( % C min 0.04%) | L99: CHS60.3x3.91-6000L | M99: ASTM-A312 TP304 | N99: m | O99: 5.45 | P99: 37.608 | Q99: 201.85104 | T99: 39.86448 | U99: 217.26142 | V99: =VLOOKUP(J99,[113]PR!$A:$S,15,0) -> 0 | W99: =VLOOKUP(J99,[113]PR!$A:$S,16,0) -> 0 | X99: =VLOOKUP(J99,[114]PR!$A:$U,17,0) -> 0 | Y99: =VLOOKUP(J99,[114]PR!$A:$U,18,0) -> 0 | Z99: 0 | AA99: 0 | AB99: 0 | AC99: 0 | AD99: 0 | AE99: 0 | AF99: 0 | AG99: 0 | AH99: 0 | AI99: 0 | AJ99: 0 | AK99: 0 | AL99: 0 | AM99: 0 | AP99: 0 | AQ99: 0 | AR99: =R99+T99+V99+X99+Z99+AB99+AD99+AF99+AH99+AJ99+AL99+AN99+AP99 -> 39.86448 | AS99: =S99+U99+W99+Y99+AA99+AC99+AE99+AG99+AI99+AK99+AM99+AO99+AQ99 -> 217.26142 | AV99: 27.86448 | AW99: =AV99*O99 -> 151.86142 | AY99: Đã mời nghiệm thu ngày 15/5 | AZ99: =IF(AR99>AV99,AR99-AV99,"0") -> 12 | BA99: =IF(AS99>AW99,AS99-AW99,"0") -> 65.4 | BN99: =SUMIF($J:$J,J99,$BI:$BI) -> 0 | BO99: =SUMIF($J:$J,J99,$BJ:$BJ) -> 0 | BT99: IBSHI-GNEE/2504-08 | BU99: GNEE | BV99: 60.3*3.91*6000 | BW99: A312 TP304 PIPE | BX99: 66 | BY99: 45755 | BZ99: 12 | CA99: 66 | CB99: 3.31 | CC99: =CB99*CA99 -> 218.46 | CI99: 45791 | CJ99: 45792 | CL99: =SUMIF($J:$J,J99,$BZ:$BZ) -> 12 | CM99: =SUMIF($J:$J,J99,$CA:$CA) -> 66 | CR99: =BN99+CL99 -> 12 | CS99: =BO99+CM99 -> 66 | CT99: =AZ99-CR99 -> 0 | CU99: =BA99-CS99 -> -0.6 | CV99: =IF(CT99<0,"Thừa",IF(CT99=0,"Đủ","Thiếu")) -> Đủ | DB99: 10.116 | DC99: 55.03104 | DD99: 12.948 | DE99: 69.14 | DH99: 8.24 | DI99: 44 | DJ99: 2.146 | DK99: 11.46 | DL99: 2.146 | DM99: 11.46 | DN99: 2.014 | DO99: 10.76
A100: =IF(J100=J99,"ok","Hiện") -> Hiện | B100: =CV100 -> Đủ | C100: =CT100 -> 0 | G100: Hàng tồn | H100: Thép trắng nhập | J100: I78-A-70 | K100: thép ống( % C min 0.04%) | L100: CHS60.3x5.5-6000L | M100: ASTM-A312 TP304 | N100: m | O100: 7.57 | P100: 0.328 | Q100: 2.42 | T100: 0.34768 | U100: 2.6319376 | V100: =VLOOKUP(J100,[113]PR!$A:$S,15,0) -> 0 | W100: =VLOOKUP(J100,[113]PR!$A:$S,16,0) -> 0 | X100: =VLOOKUP(J100,[114]PR!$A:$U,17,0) -> 0 | Y100: =VLOOKUP(J100,[114]PR!$A:$U,18,0) -> 0 | Z100: 0 | AA100: 0 | AB100: 0 | AC100: 0 | AD100: 0 | AE100: 0 | AF100: 0 | AG100: 0 | AH100: 0 | AI100: 0 | AJ100: 0 | AK100: 0 | AL100: 0 | AM100: 0 | AP100: 0 | AQ100: 0 | AR100: =R100+T100+V100+X100+Z100+AB100+AD100+AF100+AH100+AJ100+AL100+AN100+AP100 -> 0.34768 | AS100: =S100+U100+W100+Y100+AA100+AC100+AE100+AG100+AI100+AK100+AM100+AO100+AQ100 -> 2.6319376 | AV100: 0.34768 | AW100: =AV100*O100 -> 2.6319376 | AY100: Đã mời nghiệm thu ngày 15/5 | AZ100: =IF(AR100>AV100,AR100-AV100,"0") -> 0 | BA100: =IF(AS100>AW100,AS100-AW100,"0") -> 0 | BN100: =SUMIF($J:$J,J100,$BI:$BI) -> 0 | BO100: =SUMIF($J:$J,J100,$BJ:$BJ) -> 0 | CL100: =SUMIF($J:$J,J100,$BZ:$BZ) -> 0 | CM100: =SUMIF($J:$J,J100,$CA:$CA) -> 0 | CR100: =BN100+CL100 -> 0 | CS100: =BO100+CM100 -> 0 | CT100: =AZ100-CR100 -> 0 | CU100: =BA100-CS100 -> 0 | CV100: =IF(CT100<0,"Thừa",IF(CT100=0,"Đủ","Thiếu")) -> Đủ | DH100: 0.328 | DI100: 2.42
...

Sheet Tổng hợp
A1: Item/ STT | B1: Total Ordered/Tổng dự trù | D1: Tận dụng tồn kho/ Remain | G1: Khối lượng phải mua sắm/ total order | I1: VẬT TƯ TRONG NƯỚC | L1: VẬT TƯ OVERSEA | O1: Khối lượng phải mua còn lại theo PR/ total order from PR | Q1: Khối lượng phải mua còn lại/ total order
B2: Q.Ty/S.Lượng (M/M2/Set) | C2: Weight/K.Lượng (Kg) | D2: Q.Ty/S.Lượng (M/M2/Set) | E2: Weight/K.Lượng (Kg) | F2: Đã nghiệm thu (Kg) | G2: Q.Ty/ S.Lượng | H2: Weight/ K.Lượng (Kg) | I2: S.Lượng giao hàng thực tế/ Handover Q'ty | J2: K.Lượng giao hàng thực tế// Handover weight | K2: Khối lượng nghiệm thu đạt/ Weight Acc. Inspection | L2: S.Lượng giao hàng thực tế/ Handover Q'ty | M2: K.Lượng giao hàng thực tế// Handover weight | N2: Khối lượng nghiệm thu đạt/ Weight Acc. Inspection | O2: Q.Ty/S.Lượng (M/M2/Set) | P2: Weight/ K.Lượng (Kg) | Q2: Q.Ty/S.Lượng (M/M2/Set) | R2: Weight/ K.Lượng (Kg)
A3: A. | B3: Main-Material / Vật tư chính
A4: 1 | B4: ='078'!AR7 -> 42283.706 | C4: ='078'!AS7 -> 688314.75 | D4: ='078'!AV7 -> 819.85066 | E4: ='078'!AW7 -> 34363.468 | F4: =E4 -> 34363.468 | G4: ='078'!AZ7 -> 41489.675 | H4: ='078'!BA7 -> 654353.36 | I4: ='078'!BI7 -> 33991.021 | J4: ='078'!BJ7 -> 481149.21 | K4: ='078'!BR7 -> 0 | L4: ='078'!BZ7 -> 10816.6 | M4: ='078'!CA7 -> 166044.39 | N4: 0 | O4: =B4-I4-L4-E4 -> -36887.383 | P4: =C4-J4-M4-F4 -> 6757.6852 | Q4: ='078'!CT7 -> -3317.9457 | R4: ='078'!CU7 -> 7159.76
A5: B. | B5: Accessory-Material / Vật tư phụ
A6: 1 | B6: ='078'!AR243 -> 19395 | C6: ='078'!AS243 -> 0 | D6: ='078'!AV243 -> 0 | E6: ='078'!AW243 -> 0 | F6: =E6 -> 0 | G6: ='078'!AZ243 -> 19449 | H6: ='078'!BA9 -> 0 | I6: ='078'!BI243 -> 19429 | J6: ='078'!BJ243 -> 0 | K6: ='078'!BR243 -> 0 | O6: =B6-I6 -> -34 | P6: =C6-J6 -> 0 | Q6: ='078'!CT243 -> 20 | R6: ='078'!CU243 -> 0
A7: C. | B7: Packing Material / Vật tư kiện
A8: 1 | B8: ='078'!AR310 -> 26592.682 | C8: ='078'!AS310 -> 77765.554 | D8: ='078'!AV310 -> 1634.9042 | E8: ='078'!AW310 -> 7177.7415 | F8: =E8 -> 7177.7415 | G8: ='078'!AZ310 -> 24957.778 | H8: ='078'!BA310 -> 70587.812 | I8: ='078'!BI310 -> 21445.505 | J8: ='078'!BJ310 -> 72120.6 | K8: ='078'!BR310 -> 0 | O8: =B8-I8 -> 5147.1772 | P8: =C8-J8 -> 5644.9539 | Q8: ='078'!CT310 -> 3512.273 | R8: ='078'!CU310 -> -1532.7876
A11: STT/ No. | B11: Dự án/ Hạng mục/ Project/ Items | C11: Thiết kế, Dự toán/ Design, Estimation | F11: Mua sắm/ Ordered, Puchased (Đến hiện tại/ Up to now) | K11: Chênh lệch/ Diff. (VND) | L11: Ghi chú/ Remarks
F12: Hàng mua thêm | H12: Hàng tồn
C13: Khối lượng/ Weight (Kg) | D13: Số lượng/ Q'ty (M/M2//PSC) | E13: Tổng Giá trị/ Total Cost (VND) | F13: Khối lượng/ Weight (Kg) | G13: Số lượng/ Q'ty (M/M2//PSC) | H13: Khối lượng/ Weight (Kg/N/A) Materials available at the factory | I13: Số lượng/ Q'ty (M/M2/PSC) Materials available at the factory | J13: Tổng Giá trị mua thêm/ Total Cost (VND)
A14: 1.1 | B14: Vật tư chính/ Main-Material | C14: =C4 -> 688314.75 | D14: =B4 -> 42283.706 | F14: =J4+M4 -> 647193.6 | G14: =I4+L4 -> 44807.621 | H14: =E4 -> 34363.468 | I14: =D4 -> 819.85066 | J14: ='078'!BL7+'078'!CC7*26200 -> 1.8949359e+10
A15: 1.2 | B15: Vật tư phụ/ Accessory-Material | C15: =C6 -> 0 | D15: =B6 -> 19395 | F15: =J6+M6 -> 0 | G15: =I6+L6 -> 19429 | H15: =E6 -> 0 | I15: =D6 -> 0 | J15: ='078'!BL243+'078'!CC243*26200 -> 547538486
A16: 1.3 | B16: Vật tư kiện/ Packing Material | C16: =C8 -> 77765.554 | D16: =B8 -> 26592.682 | F16: =J8+M8 -> 72120.6 | G16: =I8+L8 -> 21445.505 | H16: =E8 -> 7177.7415 | I16: =D8 -> 1634.9042 | J16: ='078'!BL310+'078'!CC310*26200 -> 1.4114211e+09

Sheet BG Gnee 2
B1: GNEE STEEL CO.,LIMITED
B2: FLAT/RM 1512 15/F LUCKY CENTRE NO.165-171 WAN CHAI ROAD WAN CHAI HK
A3: TEL: +86 15286968617 E-mail:alice@gescosteel.com
A4: QUOTATION SHEET
A5: QUOTATION NO.: GNEEYPH20240527-1
A6: DATE: MAY.27TH,2024
A7: TO:IBS
A8: SR NO. | B8: PRODUCT NAME | C8: SPECIFICATION (mm) | F8: UNIT WEIGHT (KG/PCS) | G8: QUANTITY | I8: FOB CHINA
E9: Số lượng (m/m2) | G9: QTY (PCS) | H9: WEIGHT (KG) | I9: UNIT PRICE（USD/KG) | J9: AMOUNT (USD) | K9: lead time
A10: A-8 | B10: HARDOX 450 PLATE | C10: 6*2000*6000 | E10: =G10*2*6 -> 36 | F10: 565.2 | G10: 3 | H10: =G10*F10 -> 1695.6 | I10: 3.16 | J10: =I10*H10 -> 5358.096 | K10: 20days
A11: A-15 | B11: NM400 PLATE | C11: 12*1500*3700 | E11: =G11*1.5*3.7 -> 5.55 | F11: 653.5 | G11: 1 | H11: =G11*F11 -> 653.5 | I11: 1.1 | J11: =I11*H11 -> 718.85 | K11: 20days
A12: A-20 | B12: HARDOX 500 PLATE | C12: 16*2000*6000 | E12: =G12*2*6 -> 12 | F12: 1507.2 | G12: 1 | H12: =G12*F12 -> 1507.2 | I12: 3.07 | J12: =I12*H12 -> 4627.104 | K12: 20days
A13: A-27 | B13: HARDOX 500 PLATE | C13: 22*2000*6000 | E13: =G13*2*6 -> 12 | F13: =22*2*6*7.85 -> 2072.4 | G13: 1 | H13: =G13*F13 -> 2072.4 | I13: 3.16 | J13: =I13*H13 -> 6548.784 | K13: 20days
A14: A-5 | B14: SA240-304 PLATE | C14: 2*1219*2438 | E14: =G14*1.219*2.438 -> 2.971922 | F14: 47.2 | G14: 1 | H14: =G14*F14 -> 47.2 | I14: 3.29 | J14: =I14*H14 -> 155.288
A15: A-64 | B15: SUS 304 ROUND BAR | C15: 40*6000 | E15: =G15*6 -> 12 | F15: 59.8 | G15: 2 | H15: =G15*F15 -> 119.6 | I15: 3.72 | J15: =I15*H15 -> 444.912
A16: A-46 | B16: Q235B PIPE | C16: 102*6*6000 | E16: =G16*6 -> 6 | F16: 85.2 | G16: 1 | H16: =G16*F16 -> 85.2 | I16: 0.91 | J16: =I16*H16 -> 77.532
A17: A-47 | B17: Q235B PIPE | C17: 108*5*6000 | E17: =G17*6 -> 126 | F17: 76.2 | G17: 21 | H17: =G17*F17 -> 1600.2 | I17: 0.91 | J17: =I17*H17 -> 1456.182
A18: A-48 | B18: Q235B PIPE | C18: 121*5*6000 | E18: =G18*6 -> 60 | F18: 85.8 | G18: 10 | H18: =G18*F18 -> 858 | I18: 0.91 | J18: =I18*H18 -> 780.78
A19: A-49 | B19: Q235B PIPE | C19: 140*6*6000 | E19: =G19*6 -> 150 | F19: 119 | G19: 25 | H19: =G19*F19 -> 2975 | I19: 0.91 | J19: =I19*H19 -> 2707.25
A20: A-50 | B20: Q235B PIPE | C20: 168*8*6000 | E20: =G20*6 -> 18 | F20: 189.4 | G20: 3 | H20: =G20*F20 -> 568.2 | I20: 0.91 | J20: =I20*H20 -> 517.062
A21: A-51 | B21: Q235B PIPE | C21: 194*8*6000 | E21: =G21*6 -> 6 | F21: 220.2 | G21: 1 | H21: =G21*F21 -> 220.2 | I21: 0.91 | J21: =I21*H21 -> 200.382
A22: A-52 | B22: Q235B PIPE | C22: 245*10*12000 | E22: =G22*12 -> 12 | F22: 695.5 | G22: 1 | H22: =G22*F22 -> 695.5 | I22: 0.91 | J22: =I22*H22 -> 632.905
A23: A-53 | B23: Q235B PIPE | C23: 32*4*6000 | E23: =G23*6 -> 6 | F23: 16.6 | G23: 1 | H23: =G23*F23 -> 16.6 | I23: 0.91 | J23: =I23*H23 -> 15.106
A24: A-54 | B24: Q235B PIPE | C24: 60*3.5*6000 | E24: =G24*6 -> 6 | F24: 29.3 | G24: 1 | H24: =G24*F24 -> 29.3 | I24: 0.91 | J24: =I24*H24 -> 26.663
A25: A-55 | B25: Q235B PIPE | C25: 60*6*6000 | E25: =G25*6 -> 6 | F25: 47.9 | G25: 1 | H25: =G25*F25 -> 47.9 | I25: 0.91 | J25: =I25*H25 -> 43.589
A26: A-57 | B26: Q235B PIPE | C26: 76*5*6000 | E26: =G26*6 -> 36 | F26: 52.6 | G26: 6 | H26: =G26*F26 -> 315.6 | I26: 0.91 | J26: =I26*H26 -> 287.196
A27: AMOUNT | G27: =SUM(G10:G26) -> 80 | H27: =SUM(H10:H26) -> 13507.2 | J27: =SUM(J10:J26) -> 24597.681
A28: SPECIFICATION:
A29: 1. SURFACE: | C29: SAFETY
A30: 2. PACKAGE: | C30: SEA WORTHY PACKING
A31: 3. QUALITY STANDARD OF MATERIAL: | C31: ACCORDANCE WITH ABOVE SPECIFICATION.
A32: TERMS:
A33: 1. INSPECTION: | C33: MILL QUALITY TEST.(ORIGINAL MTC WILL BE PROVIDED.)
A34: 2. TOLERANCE OF AMOUNT: | C34: QUANTITY AND AMOUNT ARE ALLOWED MORE OR LESS 10%.
A35: 3.TERMS OF PAYMENT: | C35: 100% LC AT SIGHT.
A36: 4. TIME OF DELIVERY: | C36: 20DAYS AFTER ORIGINAL LC
A37: 5. PORT OF LOADING: | C37: ANY PORT,CHINA
A38: 6. PORT OF DESTINATION: | C38: HAIPHONG,VIETNAM
A39: 7. TRANSPORTATION: | C39: CONTAINER
A40: 8. VALID PERIOD OF PRICE: | C40: 5DAYS
A41: 9. ORIGIN OF GOODS: | C41: CHINA.
A42: 10.NOTE | C42: 1. ABOVE PRICE IS BASED ON FINAL WEIGHT
C43: 2. ABOVE PRICE DOES NOT CONTAIN THIRD PARTY INSPECTION FEE.
A44: BANK INFORMATION:
A45: BENIFICIARY COMPANY: | C45: GNEE STEEL CO.,LIMITED
A46: COMPANY ADDRESS: | C46: FLAT/RM 1512 15/F LUCKY CENTRE NO.165-171 WAN CHAI ROAD WAN CHAI HK
A47: BENIFICIARY BANK: | C47: ZHEJIANG CHOUZHOU COMMERCIAL BANK
A48: BANK ADDRESS: | C48: YIWU LEYUAN EAST JIANGBIN ROAD YIWU CITY ZHEJIANG PROVINCE CHINA
A49: SWIFT NO.: | C49: CZCBCN2X
A50: ACCOUNT NUMBER: | C50: NRA15628142010500008718

Sheet Báo giá của GNEE
B1: GNEE STEEL CO.,LIMITED
B2: FLAT/RM 1512 15/F LUCKY CENTRE NO.165-171 WAN CHAI ROAD WAN CHAI HK
A3: TEL: +86 15286968617 E-mail:alice@gescosteel.com
A4: QUOTATION SHEET
A5: QUOTATION NO.: GNEEYPH20240513-1
A6: DATE: MAY.13TH,2024
A7: TO:IBS
A8: SR NO. | B8: PRODUCT NAME | C8: SPECIFICATION (mm) | F8: UNIT WEIGHT (KG/PCS) | G8: QUANTITY | I8: CIF HAIPHONG, VIETNAM
E9: Số lượng (m/m2) | G9: QTY (PCS) | H9: WEIGHT (KG) | I9: UNIT PRICE（USD/KG) | J9: AMOUNT (USD) | M9: lead time
A10: A-8 | B10: HARDOX 450 PLATE | C10: 6*2000*6000 | E10: =G10*2*6 -> 36 | F10: 565.2 | G10: 3 | H10: =G10*F10 -> 1695.6 | I10: 3.21 | J10: =I10*H10 -> 5442.876 | K10: GNEEYPH20240513-1 | L10: kt: 1500X6000-2 tờ; 1500x5400-1 tờ. | M10: 20days
A11: A-9 | B11: Q235B PLATE | C11: 6*1500*6000 | E11: =G11*1.5*6 -> 18 | F11: 423.9 | G11: 2 | H11: =G11*F11 -> 847.8 | I11: 0.68 | J11: =I11*H11 -> 576.504 | K11: GNEEYPH20240513-1 | M11: 20days
A12: A-11 | B12: Q235B PLATE | C12: 8*1500*6000 | E12: =G12*1.5*6 -> 9 | F12: 565.2 | G12: 1 | H12: =G12*F12 -> 565.2 | I12: 0.7 | J12: =I12*H12 -> 395.64 | K12: GNEEYPH20240513-1 | M12: 20days
A13: A-12 | B13: Q355B PLATE | C13: 8*2000*12000 | E13: =G13*2*12 -> 24 | F13: 1507.2 | G13: 1 | H13: =G13*F13 -> 1507.2 | I13: 0.72 | J13: =I13*H13 -> 1085.184 | K13: GNEEYPH20240513-1 | M13: 20days
A14: A-13 | B14: Q235B PLATE | C14: 10*1500*6000 | E14: =G14*1.5*6 -> 9 | F14: 706.5 | G14: 1 | H14: =G14*F14 -> 706.5 | I14: 0.69 | J14: =I14*H14 -> 487.485 | K14: GNEEYPH20240513-1 | M14: 20days
A15: A-14 | B15: Q355B PLATE | C15: 10*2000*10000 | E15: =G15*2*10 -> 20 | F15: 1570 | G15: 1 | H15: =G15*F15 -> 1570 | I15: 0.72 | J15: =I15*H15 -> 1130.4 | K15: GNEEYPH20240513-1 | M15: 20days
A16: A-15 | B16: NM400 PLATE | C16: 12*1500*3700 | E16: =G16*1.5*3.7 -> 5.55 | F16: 653.5 | G16: 1 | H16: =G16*F16 -> 653.5 | I16: 1.15 | J16: =I16*H16 -> 751.525 | K16: GNEEYPH20240513-1 | L16: 12*1500*4250 | M16: 20days
A17: A-17 | B17: Q355B PLATE | C17: 12*2000*12000 | E17: =G17*2*12 -> 24 | F17: 2260.8 | G17: 1 | H17: =G17*F17 -> 2260.8 | I17: 0.72 | J17: =I17*H17 -> 1627.776 | K17: GNEEYPH20240513-1 | M17: 45days
A18: A-20 | B18: HARDOX 500 PLATE | C18: 16*2000*6000 | E18: =G18*2*6 -> 12 | F18: 1507.2 | G18: 1 | H18: =G18*F18 -> 1507.2 | I18: 3.12 | J18: =I18*H18 -> 4702.464 | K18: GNEEYPH20240513-1 | L18: kt: 1500X6000-1 tờ; 1500x2500-1 tờ. | M18: 20days
A19: A-22 | B19: Q355B PLATE | C19: 16*2000*8000 | E19: =G19*2*8 -> 16 | F19: 2009.6 | G19: 1 | H19: =G19*F19 -> 2009.6 | I19: 0.78 | J19: =I19*H19 -> 1567.488 | K19: GNEEYPH20240513-1 | M19: 20days
A20: A-42 | B20: Q355 H BEAM | C20: 200*200*8*12*12000 | E20: =G20*12 -> 96 | F20: =50.5*12 -> 606 | G20: 8 | H20: =G20*F20 -> 4848 | I20: 0.75 | J20: =I20*H20 -> 3636 | K20: GNEEYPH20240513-1 | M20: 20days
A21: A-43 | B21: Q355 H BEAM | C21: 250*250*9*14*12000 | E21: =G21*12 -> 12 | F21: =72.4*12 -> 868.8 | G21: 1 | H21: =G21*F21 -> 868.8 | I21: 0.75 | J21: =I21*H21 -> 651.6 | K21: GNEEYPH20240513-1
A22: A-73 | B22: Q235B RHS | C22: 150*100*6*12000 | E22: =G22*12 -> 24 | F22: 269 | G22: 2 | H22: =G22*F22 -> 538 | I22: 0.75 | J22: =I22*H22 -> 403.5 | K22: GNEEYPH20240513-1 | M22: 20days
A23: A-74 | B23: Q235B RHS | C23: 200*100*6*6000 | E23: =G23*6 -> 30 | F23: 162.8 | G23: 5 | H23: =G23*F23 -> 814 | I23: 0.75 | J23: =I23*H23 -> 610.5 | K23: GNEEYPH20240513-1 | M23: 20days
A24: A-75 | B24: Q235B SHS | C24: 200*200*10*6000 | E24: =G24*6 -> 60 | F24: 358 | G24: 10 | H24: =G24*F24 -> 3580 | I24: 0.75 | J24: =I24*H24 -> 2685 | K24: GNEEYPH20240513-1 | M24: 20days
A25: A-76 | B25: Q355B SHS | C25: 200*200*8*12000 | E25: =G25*12 -> 48 | F25: 289.4 | G25: 4 | H25: =G25*F25 -> 1157.6 | I25: 0.77 | J25: =I25*H25 -> 891.352 | K25: GNEEYPH20240513-1
A26: A-77 | B26: Q235B SHS | C26: 300*300*6*6000 | E26: =G26*6 -> 54 | F26: 332.4 | G26: 9 | H26: =G26*F26 -> 2991.6 | I26: 0.75 | J26: =I26*H26 -> 2243.7 | K26: GNEEYPH20240513-1 | M26: 20days
A27: AMOUNT | G27: =SUM(G10:G26) -> 52 | H27: =SUM(H10:H26) -> 28121.4 | J27: =SUM(J10:J26) -> 28888.994
A28: SPECIFICATION:
A29: 1. SURFACE: | C29: SAFETY
A30: 2. PACKAGE: | C30: SEA WORTHY PACKING
A31: 3. QUALITY STANDARD OF MATERIAL: | C31: ACCORDANCE WITH ABOVE SPECIFICATION.
A32: TERMS:
A33: 1. INSPECTION: | C33: MILL QUALITY TEST.(ORIGINAL MTC WILL BE PROVIDED.)
A34: 2. TOLERANCE OF AMOUNT: | C34: QUANTITY AND AMOUNT ARE ALLOWED MORE OR LESS 10%.
A35: 3.TERMS OF PAYMENT: | C35: 100% LC AT SIGHT.
A36: 4. TIME OF DELIVERY: | C36: 20DAYS AFTER ORIGINAL LC
A37: 5. PORT OF LOADING: | C37: ANY PORT,CHINA
A38: 6. PORT OF DESTINATION: | C38: HAIPHONG,VIETNAM
A39: 7. TRANSPORTATION: | C39: CONTAINER
A40: 8. VALID PERIOD OF PRICE: | C40: 5DAYS
A41: 9. ORIGIN OF GOODS: | C41: CHINA.
A42: 10.NOTE | C42: 1. ABOVE PRICE IS BASED ON FINAL WEIGHT
C43: 2. ABOVE PRICE DOES NOT CONTAIN THIRD PARTY INSPECTION FEE.
A44: BANK INFORMATION:
A45: BENIFICIARY COMPANY: | C45: GNEE STEEL CO.,LIMITED
A46: COMPANY ADDRESS: | C46: FLAT/RM 1512 15/F LUCKY CENTRE NO.165-171 WAN CHAI ROAD WAN CHAI HK
A47: BENIFICIARY BANK: | C47: ZHEJIANG CHOUZHOU COMMERCIAL BANK
A48: BANK ADDRESS: | C48: YIWU LEYUAN EAST JIANGBIN ROAD YIWU CITY ZHEJIANG PROVINCE CHINA
A49: SWIFT NO.: | C49: CZCBCN2X
A50: ACCOUNT NUMBER: | C50: NRA15628142010500008718

Sheet Dieu kien giao hang
A2: ĐIỀU KIỆN GIAO HÀNG NHẬP KHẨU
A3: STT | B3: Nội dung | C3: Số ngày | D3: Giá trị cộng dồn
A4: 1 | B4: Ký HD | C4: 0
A5: 2 | B5: Tạm ứng | C5: 0
A6: 3 | B6: Mở LC | C6: 5 | D6: =+C6+D5+C5 -> 5
A7: 4 | B7: Giao Hàng CIF | C7: 20 | D7: =+C7+D6 -> 25
A8: 5 | B8: Vận chuyển quốc tế | C8: 5 | D8: =+C8+D7 -> 30
A9: 6 | B9: Ngày thanh toán | C9: 3 | D9: =+C9+D8 -> 33
A10: 6 | B10: Thủ tục hải quan + vận chuyển nội địa | C10: 3 | D10: =+C10+D9 -> 36
B11: Ngày hàng về | C11: 2 | D11: =+C11+D10 -> 38
B12: Ngày mời nghiệm thu QC | C12: 1 | D12: =+C12+D11 -> 39
A13: 7 | B13: Nghiệm thu | C13: 12 | D13: =+C13+D12 -> 51
A14: 7 | B14: Bàn giao | C14: 1 | D14: =+C14+D13 -> 52
A16: ĐIỀU KIỆN GIAO HÀNG TRONG NƯỚC (VTU CHÍNH)
A17: STT | B17: Nội dung | C17: Số ngày | D17: Giá trị cộng dồn
A18: 1 | B18: Ký HD | C18: 0
A19: 2 | B19: Tạm ứng | C19: 0
A20: 3 | B20: Mở LC | C20: 0 | D20: =+C20+D19+C19 -> 0
A21: 4 | B21: Giao Hàng tại xưởng | C21: 4 | D21: =+C21+D20 -> 4
A22: 5 | B22: Nghiệm thu | C22: 2 | D22: =+C22+D21 -> 6
A23: 6 | B23: Bàn giao | C23: 1 | D23: =+C23+D22 -> 7
A26: ĐIỀU KIỆN GIAO HÀNG TRONG NƯỚC (VTU Phụ)
A27: STT | B27: Nội dung | C27: Số ngày | D27: Giá trị cộng dồn
A28: 1 | B28: Ký HD | C28: 0
A29: 2 | B29: Tạm ứng | C29: 0
A30: 3 | B30: Mở LC | C30: 0 | D30: =+C30+D29+C29 -> 0
A31: 4 | B31: Giao Hàng tại xưởng | C31: 26 | D31: =+C31+D30 -> 26
A32: 5 | B32: Nghiệm thu | C32: 2 | D32: =+C32+D31 -> 28
A33: 6 | B33: Bàn giao | C33: 1 | D33: =+C33+D32 -> 29

Sheet PL01 Hung nguyen
A1: CÔNG TY TNHH THƯƠNG MẠI HÙNG NGUYÊN Trụ sở: Số 673 đường 5/2, P.Hùng Vương, Q.Hồng Bàng, Hải Phòng VPGD: Số 955 đường Hùng Vương, P.Hùng Vương, Q.Hồng Bàng, TP.Hải Phòng Điện thoại: 0225.3529.509 / E: hungnguyenthep@gmail.com
A3: PHỤ LỤC SỐ 01 THUỘC HỢP ĐỒNG MUA BÁN SỐ: 030224/HN-IBS ngày 03/02/2024
A4: Hôm nay ngày 03/02/2024, Công ty TNHH Thương Mại Hùng Nguyên (Bên Bán) và CÔNG TY CỔ PHẦN CÔNG NGHIỆP NẶNG IBS (Bên Mua) thống nhất lập phụ lục hợp đồng số: 01 thuộc Hợp đồng mua bán số: 030224/HN-IBS ngày 03/02/2024 với các điều khoản cụ thể như sau:
A5: Điều 1: Thông tin lô hàng đính kèm hợp đồng:
A6: STT | C6: Tên hàng hóa | D6: Mác thép | E6: Xuất xứ | F6: Số lượng (Cây,Tấm) | G6: Trọng lượng (KG) | H6: Đơn giá Có VAT (VNĐ/KG) | I6: Đơn giá Chưa VAT (VND/KG) | K6: Thành tiền Chưa VAT (VNĐ)
A7: (a) | C7: (b) | F7: (c) | G7: (d) | H7: (e) | I7: (f) | K7: (g = d x f)
A8: 1 | B8: A-01 | C8: Thép tấm 10x2000x12000 | D8: A36/SS400 | E8: Trung Quốc | F8: 14 | G8: =ROUND(10*2*12*7.85*F8,0) -> 26376 | H8: 16550 | I8: =+ROUND(H8/1.1,2) -> 15045.45 | K8: =+ROUND(G8*I8,0) -> 396838789
A9: 2 | B9: A-06 | C9: Thép tấm 6x2000x12000 | D9: A36/SS400 | E9: Trung Quốc | F9: 22 | G9: =ROUND(6*2*12*7.85*F9,0) -> 24869 | H9: 16550 | I9: =+ROUND(H9/1.1,2) -> 15045.45 | K9: =+ROUND(G9*I9,0) -> 374165296
A10: 3 | B10: A-17 | C10: Thép tấm 12x2000x6000 | D10: A36/SS400 | E10: Trung Quốc | F10: 1 | G10: =ROUND(12*2*6*7.85*F10,0) -> 1130 | H10: 16550 | I10: =+ROUND(H10/1.1,2) -> 15045.45 | K10: =+ROUND(G10*I10,0) -> 17001359
A11: 4 | B11: A-15 | C11: Thép tấm 10x2000x12000 | D11: Q355/A572 | E11: Trung Quốc | F11: 1.5 | G11: =ROUND(10*2*12*7.85*F11,0) -> 2826 | H11: 17550 | I11: =+ROUND(H11/1.1,2) -> 15954.55 | K11: =+ROUND(G11*I11,0) -> 45087558
A12: 5 | B12: A-16 | C12: Thép tấm 12x2000x6000 | D12: Q355/A572 | E12: Trung Quốc | F12: 1 | G12: =ROUND(12*2*6*7.85*F12,0) -> 1130 | H12: 17550 | I12: =+ROUND(H12/1.1,2) -> 15954.55 | K12: =+ROUND(G12*I12,0) -> 18028642
A13: 6 | B13: A-18 | C13: Thép tấm 16x2000x6000 | D13: Q355/A572 | E13: Trung Quốc | F13: 1 | G13: =ROUND(16*2*6*7.85*F13,0) -> 1507 | H13: 17550 | I13: =+ROUND(H13/1.1,2) -> 15954.55 | K13: =+ROUND(G13*I13,0) -> 24043507
A14: 7 | B14: A-19 | C14: Thép tấm 20x2000x12000 | D14: Q355/A572 | E14: Trung Quốc | F14: 5 | G14: =ROUND(20*2*12*7.85*F14,0) -> 18840 | H14: 17550 | I14: =+ROUND(H14/1.1,2) -> 15954.55 | K14: =+ROUND(G14*I14,0) -> 300583722
A15: 8 | B15: A-20 | C15: Thép tấm 22x2000x12000 | D15: Q355/A572 | E15: Trung Quốc | F15: 3.5 | G15: =ROUND(22*2*12*7.85*F15,0) -> 14507 | H15: 18050 | I15: =+ROUND(H15/1.1,2) -> 16409.09 | K15: =+ROUND(G15*I15,0) -> 238046669
A16: 9 | B16: A-21 | C16: Thép tấm 25x2000x6000 | D16: Q355/A572 | E16: Trung Quốc | F16: 1 | G16: =ROUND(25*2*6*7.85*F16,0) -> 2355 | H16: 18050 | I16: =+ROUND(H16/1.1,2) -> 16409.09 | K16: =+ROUND(G16*I16,0) -> 38643407
A17: 10 | B17: A-22 | C17: Thép tấm 28x2000x6000 | D17: Q355/A572 | E17: Trung Quốc | F17: 1 | G17: =ROUND(28*2*6*7.85*F17,0) -> 2638 | H17: 18050 | I17: =+ROUND(H17/1.1,2) -> 16409.09 | K17: =+ROUND(G17*I17,0) -> 43287179
A18: 11 | B18: A-23 | C18: Thép tấm 32x2000x6000 | D18: Q355/A572 | E18: Trung Quốc | F18: 1 | G18: =ROUND(32*2*6*7.85*F18,0) -> 3014 | H18: 18050 | I18: =+ROUND(H18/1.1,2) -> 16409.09 | K18: =+ROUND(G18*I18,0) -> 49456997
A19: 12 | B19: A-24 | C19: Thép U125x65x6x8x12000 | D19: SS400 | E19: Nhật Bản/ Hàn Quốc/ Thái Lan | F19: 9 | G19: =ROUND(13.4*12*F19,2) -> 1447.2 | H19: 24050 | I19: =+ROUND(H19/1.1,2) -> 21863.64 | K19: =+ROUND(G19*I19,0) -> 31641060
A20: 13 | B20: A-25 | C20: Thép U150x75x6.5x10x12000 | D20: SS400 | E20: Việt Nam | F20: 7 | G20: =ROUND(18.6*12*F20,2) -> 1562.4 | H20: 18550 | I20: =+ROUND(H20/1.1,2) -> 16863.64 | K20: =+ROUND(G20*I20,0) -> 26347751
A21: 14 | B21: A-26 | C21: Thép U180x68x7x12000 | D21: SS400 | E21: Trung Quốc | F21: 54 | G21: =ROUND(18.6*12*F21,2) -> 12052.8 | H21: 18550 | I21: =+ROUND(H21/1.1,2) -> 16863.64 | K21: =+ROUND(G21*I21,0) -> 203254080
A22: 15 | B22: A-27 | C22: Thép U200x80x7.5x11x12000 | D22: SS400 | E22: Nhật Bản/ Hàn Quốc/ Thái Lan | F22: 24 | G22: =ROUND(24.6*12*F22,2) -> 7084.8 | H22: 24050 | I22: =+ROUND(H22/1.1,2) -> 21863.64 | K22: =+ROUND(G22*I22,0) -> 154899517
A23: 16 | B23: A-28 | C23: Thép U200x90x8x13.5x12000 | D23: SS400 | E23: Nhật Bản/ Hàn Quốc/ Thái Lan | F23: 7 | G23: =ROUND(30.3*12*F23,2) -> 2545.2 | H23: 24550 | I23: =+ROUND(H23/1.1,2) -> 22318.18 | K23: =+ROUND(G23*I23,0) -> 56804232
A24: 17 | B24: A-29 | C24: Thép U250x90x9x13x12000 | D24: SS400 | E24: Nhật Bản/ Hàn Quốc/ Thái Lan | F24: 3 | G24: =ROUND(34.6*12*F24,2) -> 1245.6 | H24: 24550 | I24: =+ROUND(H24/1.1,2) -> 22318.18 | K24: =+ROUND(G24*I24,0) -> 27799525
A25: 18 | B25: A-30 | C25: Thép H150x150x7x10x12000 | D25: SS400 | E25: Việt Nam | F25: 2 | G25: =ROUND(31.5*12*F25,2) -> 756 | H25: 20850 | I25: =+ROUND(H25/1.1,2) -> 18954.55 | K25: =+ROUND(G25*I25,0) -> 14329640
A26: 19 | B26: A-31 | C26: Thép H194x150x6x9x12000 | D26: SS400 | E26: Việt Nam | F26: 1 | G26: =ROUND(30.6*12*F26,2) -> 367.2 | H26: 20950 | I26: =+ROUND(H26/1.1,2) -> 19045.45 | K26: =+ROUND(G26*I26,0) -> 6993489
A27: 20 | B27: A-32 | C27: Thép H244x175x7x11x12000 | D27: SS400 | E27: Việt Nam | F27: 11 | G27: =ROUND(44.1*12*F27,2) -> 5821.2 | H27: 20950 | I27: =+ROUND(H27/1.1,2) -> 19045.45 | K27: =+ROUND(G27*I27,0) -> 110867374
A28: 21 | B28: A-33 | C28: Thép I250x125x6x9x12000 | D28: SS400 | E28: Việt Nam | F28: 7.5 | G28: =ROUND(29.6*12*F28,20) -> 2664 | H28: 20850 | I28: =+ROUND(H28/1.1,2) -> 18954.55 | K28: =+ROUND(G28*I28,0) -> 50494921
A29: 22 | B29: A-34 | C29: Thép I300x150x6.5x9x12000 | D29: SS400 | E29: Việt Nam | F29: 5.5 | G29: =ROUND(36.7*12*F29,2) -> 2422.2 | H29: 20850 | I29: =+ROUND(H29/1.1,2) -> 18954.55 | K29: =+ROUND(G29*I29,0) -> 45911711
A30: 23 | B30: A-35 | C30: Thép góc L100x100x10x12000 | D30: SS400 | E30: Việt Nam | F30: 3 | G30: =ROUND(181.26*F30,0) -> 544 | H30: 17350 | I30: =+ROUND(H30/1.1,2) -> 15772.73 | K30: =+ROUND(G30*I30,0) -> 8580365
A31: 24 | B31: A-36 | C31: Thép góc L100x100x7x6000 | D31: SS400 | E31: Việt Nam | F31: 1 | G31: =64.44*F31 -> 64.44 | H31: 17350 | I31: =+ROUND(H31/1.1,2) -> 15772.73 | K31: =+ROUND(G31*I31,0) -> 1016395
A32: 25 | B32: A-37 | C32: Thép góc L130x130x10x12000 | D32: SS400 | E32: Trung Quốc | F32: 1 | G32: =238.5*F32 -> 238.5 | H32: 18550 | I32: =+ROUND(H32/1.1,2) -> 16863.64 | K32: =+ROUND(G32*I32,0) -> 4021978
A33: 26 | B33: A-38 | C33: Thép góc L150x150x10x12000 | D33: SS400 | E33: Việt Nam | F33: 3 | G33: =ROUND(276.66*F33,2) -> 829.98 | H33: 19550 | I33: =+ROUND(H33/1.1,2) -> 17772.73 | K33: =+ROUND(G33*I33,0) -> 14751010
A34: 27 | B34: A-39 | C34: Thép góc L65x65x6x6000 | D34: SS400 | E34: Việt Nam | F34: 1 | G34: =35.49*F34 -> 35.49 | H34: 17050 | I34: =+ROUND(H34/1.1,2) -> 15500 | K34: =+ROUND(G34*I34,0) -> 550095
A35: 28 | B35: A-41 | C35: Thép góc L75x75x6x6000 | D35: SS400 | E35: Việt Nam | F35: 7 | G35: 288.47 | H35: 17050 | I35: =+ROUND(H35/1.1,2) -> 15500 | K35: =+ROUND(G35*I35,0) -> 4471285
A36: 29 | B36: A-42 | C36: Thép góc L75x75x8x6000 | D36: SS400 | E36: Việt Nam | F36: 1 | G36: 54.19 | H36: 17050 | I36: =+ROUND(H36/1.1,2) -> 15500 | K36: =+ROUND(G36*I36,0) -> 839945
A37: 30 | B37: A-43 | C37: Thép góc L90x90x10x12000 | D37: SS400 | E37: Việt Nam | F37: 12 | G37: =ROUND(162.18*F37,2) -> 1946.16 | H37: 17350 | I37: =+ROUND(H37/1.1,2) -> 15772.73 | K37: =+ROUND(G37*I37,0) -> 30696256
A38: 31 | B38: A-44 | C38: Thép góc L90x90x6x12000 | D38: SS400 | E38: Việt Nam | F38: 6 | G38: 597.6 | H38: 17350 | I38: =+ROUND(H38/1.1,2) -> 15772.73 | K38: =+ROUND(G38*I38,0) -> 9425783
A39: 32 | B39: A-45 | C39: Thép góc L90x90x7x6000 | D39: SS400 | E39: Việt Nam | F39: 10 | G39: 577.65 | H39: 17350 | I39: =+ROUND(H39/1.1,2) -> 15772.73 | K39: =+ROUND(G39*I39,0) -> 9111117
A40: 33 | B40: A-55 | C40: Thép tròn D10x6000 | D40: SS400/CB240/S45C | E40: Việt Nam/ Trung Quốc | F40: 1 | G40: 3.699 | H40: 18850 | I40: =+ROUND(H40/1.1,2) -> 17136.36 | K40: =+ROUND(G40*I40,0) -> 63387
A41: 34 | B41: A-56 | C41: Thép tròn D12x6000 | D41: SS400/CB240/S45C | E41: Việt Nam/ Trung Quốc | F41: 1 | G41: 5.32656 | H41: 18850 | I41: =+ROUND(H41/1.1,2) -> 17136.36 | K41: =+ROUND(G41*I41,0) -> 91278
A42: 35 | B42: A-57 | C42: Thép tròn D14x6000 | D42: SS400/CB240/S45C | E42: Việt Nam/ Trung Quốc | F42: 1 | G42: 7.25004 | H42: 18850 | I42: =+ROUND(H42/1.1,2) -> 17136.36 | K42: =+ROUND(G42*I42,0) -> 124239
A43: 36 | B43: A-58 | C43: Thép tròn D16x6000 | D43: SS400/CB240/S45C | E43: Việt Nam/ Trung Quốc | F43: 1 | G43: 9.46944 | H43: 18850 | I43: =+ROUND(H43/1.1,2) -> 17136.36 | K43: =+ROUND(G43*I43,0) -> 162272
A44: 37 | B44: A-59 | C44: Thép tròn D20x6000 | D44: SS400/CB240/S45C | E44: Việt Nam/ Trung Quốc | F44: 1 | G44: 14.8 | H44: 18850 | I44: =+ROUND(H44/1.1,2) -> 17136.36 | K44: =+ROUND(G44*I44,0) -> 253618
A45: 38 | B45: A-60 | C45: Thép tròn D38x6000 | D45: SS400/CB240/S45C | E45: Việt Nam/ Trung Quốc | F45: 1 | G45: 53.41 | H45: 19250 | I45: =+ROUND(H45/1.1,2) -> 17500 | K45: =+ROUND(G45*I45,0) -> 934675
A46: Tổng: | F46: =SUBTOTAL(9,F8:F45) -> 234 | G46: =SUBTOTAL(9,G8:G45) -> 142431.04 | H46: Cộng tiền hàng: | K46: =SUBTOTAL(9,K8:K45) -> 2359620123
A47: Thuế GTGT: 10% | G47: Tiền thuế GTGT: | K47: =ROUND(K46*0.1,0) -> 235962012
A48: Tổng số tiền viết bằng số: | K48: =SUM(K46:K47) -> 2595582135
A49: Số tiền viết bằng chữ: | D49: =+_xll.VND(K48) -> #NAME?
A52: Điều 2: Các điều khoản khác. - Phụ lục Hợp đồng số 01 có hiệu lực kể từ ngày ký và là một phần không thể tách rời của đồng mua bán số 030224/HN-IBS ngày 03/02/2024 - Những điều khoản khác của Hợp đồng mua bán số: 030224/HN-IBS giữ nguyên giá trị hiệu lực, hai bên có trách nhiệm cùng nhau thực hiện. - Phụ lục Hợp đồng này được lập thành 04 bản, mỗi bên giữ 02 bản có giá trị như nhau.
C56: ĐẠI DIỆN BÊN BÁN | G56: ĐẠI DIỆN BÊN MUA

Sheet vogt 060_Plan_Khong su dung
A1: THEO DÕI VẬT TƯ DỰ ÁN/ MATERIAL CONTROL LOG
A2: Tên dự án/ Project no.: VOGT 060
A3: Cập nhật ngày/ Update to: | C3: =TODAY() -> 46086
A4: Item/ STT | B4: Description/ Chi tiết | C4: Profile/ Vật tư | D4: Grade/ Mác vật liệu | E4: Unit/ Đơn vị | F4: U.Weight/ Đ.Trọng (Kg/m2,m,pcs) | G4: Net Quantity/Số lượng tinh | I4: Previous Ordered/Đã dự trù | K4: Current Ordered/Dự trù lần 1 | M4: Total Ordered/Tổng dự trù | O4: Ngày vật tư đưa vào sử dụng/ Material avaiable for fabrication date | P4: Tận dụng tồn kho/ Remain | R4: Khối lượng phải mua sắm/ total order | T4: Mua sắm trong nước/ Local purchase | AB4: Mua sắm nước ngoài/ Oversea purchase | AM4: Remarks/ Ghi chú
G5: Q.Ty/ Số lượng | H5: Weight/ Khối lượng (Kg) | I5: Q.Ty/ Số lượng | J5: Weight/ Khối lượng (Kg) | K5: Q.Ty/Số lượng | L5: Weight/Khối lượng (Kg) | M5: Q.Ty/ Số lượng | N5: Weight/Khối lượng (Kg) | P5: Q.Ty/ Số lượng | Q5: Weight/Khối lượng (Kg) | R5: Q.Ty/ Số lượng | S5: Weight/Khối lượng (Kg) | T5: Q.Ty/ Số lượng | U5: Weight/ Khối lượng (Kg) | V5: Nhà cung cấp/ Vendor | W5: Ngày ký HD/ Contract date | X5: Ngày giao hàng/ Handover date | Y5: Ngày nghiệm thu, Bàn giao/ Inspection date | Z5: Kết quả nghiệm thu/ Results | AA5: Bàn giao sản xuất/ Handover to Product | AB5: Q.Ty/ Số lượng | AC5: Weight/ Khối lượng (Kg) | AD5: Nhà cung cấp/ Vendor | AE5: Ngày ký HD/ Contract date | AF5: Ngày mở L/C/ LC issued date | AG5: Hàng đi từ cảng nước ngoài/ Export Port | AH5: Hàng Đến cảng HP (CIF)/ HaiPhong CIF | AI5: Thủ tục hải quan, vận chuyển/ Paper work, local transportaion date | AJ5: Ngày nghiệm thu, Bàn giao/ Handover date | AK5: Kết quả nghiệm thu/ Results | AL5: Bàn giao sản xuất/ Handover to Product
A6: 1 | B6: 2 | C6: 3 | D6: 4 | E6: 5 | F6: 6 | G6: 7 | H6: 8 | I6: 9 | J6: 10 | K6: 11 | L6: 12 | M6: 13 | N6: 14 | AM6: 15
A7: A. | B7: Main-Material / Vật tư chính | H7: =SUM(H8:H86) -> 447323.94 | J7: =SUM(J8:J86) -> 2826 | L7: =SUM(L8:L86) -> 493509.35 | N7: =SUM(N8:N86) -> 496335.35 | U7: =SUM(U8:U86) -> 452389.54 | AC7: =SUM(AC8:AC86) -> 43945.809 | AM7: .
A8: A-1 | B8: TÔN TẤM | C8: PL10X2000X12000 | D8: SS400 | E8: m2 | F8: 78.5 | G8: =+H8/F8 -> 612.19898 | H8: =1259.98+46797.64 -> 48057.62 | I8: 36 | J8: 2826 | K8: 650 | L8: =+K8*F8 -> 51025 | M8: =+K8+I8 -> 686 | N8: =+L8+J8 -> 53851 | O8: 45316 | R8: =+M8-P8 -> 686 | S8: =+N8-Q8 -> 53851 | T8: =+R8 -> 686 | U8: =+S8 -> 53851 | V8: Hùng Nguyên | W8: 45324 | X8: =+W8+'Dieu kien giao hang'!$C$21 -> 45328 | Y8: =+X8+'Dieu kien giao hang'!$C$22 -> 45330
A9: A-2 | B9: TÔN TẤM-LINER INOX | C9: PL1.5x1220x2440 | D9: SUH409 | E9: m2 | F9: =+H9/G9 -> 11.895 | G9: 2220.0992 | H9: 26408.08 | K9: 2510 | L9: =+K9*F9 -> 29856.45 | M9: =+K9+I9 -> 2510 | N9: =+L9+J9 -> 29856.45 | O9: 45371 | R9: =+M9-P9 -> 2510 | S9: =+N9-Q9 -> 29856.45 | AB9: =+R9 -> 2510 | AC9: =+S9 -> 29856.45 | AD9: GNEE | AE9: 45323 | AF9: =+AE9+'Dieu kien giao hang'!$C$6 -> 45328 | AG9: =AF9+'Dieu kien giao hang'!$C$7 -> 45348 | AH9: =AG9+'Dieu kien giao hang'!$C$8 -> 45353 | AI9: =AH9+'Dieu kien giao hang'!$C$10 -> 45356 | AJ9: =AI9+'Dieu kien giao hang'!$C$13 -> 45368
A10: A-3 | B10: TÔN TẤM-LINER INOX | C10: PL2x1220x2440 | D10: SUH409 | E10: m2 | F10: =+H10/G10 -> 15.968596 | G10: 736.67591 | H10: 11763.68 | K10: 835 | L10: =+K10*F10 -> 13333.778 | M10: =+K10+I10 -> 835 | N10: =+L10+J10 -> 13333.778 | O10: 45371 | R10: =+M10-P10 -> 835 | S10: =+N10-Q10 -> 13333.778 | AB10: =+R10 -> 835 | AC10: =+S10 -> 13333.778 | AD10: GNEE | AE10: 45323 | AF10: =+AE10+'Dieu kien giao hang'!$C$6 -> 45328 | AG10: =AF10+'Dieu kien giao hang'!$C$7 -> 45348 | AH10: =AG10+'Dieu kien giao hang'!$C$8 -> 45353 | AI10: =AH10+'Dieu kien giao hang'!$C$10 -> 45356 | AJ10: =AI10+'Dieu kien giao hang'!$C$13 -> 45368
A11: A-4 | B11: TÔN TẤM | C11: PL3 | D11: SUH409 | E11: m2 | F11: =+H11/G11 -> 23.55 | G11: 2.2573248 | H11: 53.16 | K11: 3 | L11: =+K11*F11 -> 70.65 | M11: =+K11+I11 -> 3 | N11: =+L11+J11 -> 70.65 | O11: 45371 | R11: =+M11-P11 -> 3 | S11: =+N11-Q11 -> 70.65 | AB11: =+R11 -> 3 | AC11: =+S11 -> 70.65 | AD11: GNEE | AE11: 45323 | AF11: =+AE11+'Dieu kien giao hang'!$C$6 -> 45328 | AG11: =AF11+'Dieu kien giao hang'!$C$7 -> 45348 | AH11: =AG11+'Dieu kien giao hang'!$C$8 -> 45353 | AI11: =AH11+'Dieu kien giao hang'!$C$10 -> 45356 | AJ11: =AI11+'Dieu kien giao hang'!$C$13 -> 45368
A12: A-5 | B12: TÔN TẤM | C12: PL6 | D12: A-240 TP304 | E12: m2 | F12: =+H12/G12 -> 47.1 | G12: 0.072186837 | H12: 3.4 | K12: 1 | L12: =+K12*F12 -> 47.1 | M12: =+K12+I12 -> 1 | N12: =+L12+J12 -> 47.1 | O12: 45371 | R12: =+M12-P12 -> 1 | S12: =+N12-Q12 -> 47.1 | AB12: =+R12 -> 1 | AC12: =+S12 -> 47.1 | AD12: GNEE | AE12: 45323 | AF12: =+AE12+'Dieu kien giao hang'!$C$6 -> 45328 | AG12: =AF12+'Dieu kien giao hang'!$C$7 -> 45348 | AH12: =AG12+'Dieu kien giao hang'!$C$8 -> 45353 | AI12: =AH12+'Dieu kien giao hang'!$C$10 -> 45356 | AJ12: =AI12+'Dieu kien giao hang'!$C$13 -> 45368
A13: A-6 | B13: TÔN TẤM | C13: PL6x2000x12000 | D13: SS400 | E13: m2 | F13: =+H13/G13 -> 47.1 | G13: 1159.5244 | H13: 54613.6 | K13: =1.12*G13 -> 1298.6673 | L13: =+K13*F13 -> 61167.232 | M13: =+K13+I13 -> 1298.6673 | N13: =+L13+J13 -> 61167.232 | O13: 45338 | R13: =+M13-P13 -> 1298.6673 | S13: =+N13-Q13 -> 61167.232 | T13: =+R13 -> 1298.6673 | U13: =+S13 -> 61167.232 | V13: Hùng Nguyên | W13: 45324 | X13: =+W13+'Dieu kien giao hang'!$C$21 -> 45328 | Y13: =+X13+'Dieu kien giao hang'!$C$22 -> 45330
A14: A-7 | B14: TÔN TẤM CUỘN CẮT | C14: PL6X1500X7100 | D14: SS400 | E14: m2 | F14: =+H14/G14 -> 47.1 | G14: 216 | H14: 10173.6 | K14: =1.08*G14 -> 233.28 | L14: =+K14*F14 -> 10987.488 | M14: =+K14+I14 -> 233.28 | N14: =+L14+J14 -> 10987.488 | O14: 45338 | R14: =+M14-P14 -> 233.28 | S14: =+N14-Q14 -> 10987.488 | T14: =+R14 -> 233.28 | U14: =+S14 -> 10987.488 | V14: Hùng Nguyên | W14: 45324 | X14: =+W14+'Dieu kien giao hang'!$C$21 -> 45328 | Y14: =+X14+'Dieu kien giao hang'!$C$22 -> 45330
A15: A-8 | B15: TÔN TẤM CUỘN CẮT | C15: PL6x1500x9000 | D15: SS400 | E15: m2 | F15: =+H15/G15 -> 47.1 | G15: 408 | H15: 19216.8 | K15: =1.08*G15 -> 440.64 | L15: =+K15*F15 -> 20754.144 | M15: =+K15+I15 -> 440.64 | N15: =+L15+J15 -> 20754.144 | O15: 45338 | R15: =+M15-P15 -> 440.64 | S15: =+N15-Q15 -> 20754.144 | T15: =+R15 -> 440.64 | U15: =+S15 -> 20754.144 | V15: Hùng Nguyên | W15: 45324 | X15: =+W15+'Dieu kien giao hang'!$C$21 -> 45328 | Y15: =+X15+'Dieu kien giao hang'!$C$22 -> 45330
A16: A-9 | B16: TÔN TẤM CUỘN CẮT | C16: PL6X1500X11000 | D16: SS400 | E16: m2 | F16: =+H16/G16 -> 47.1 | G16: 720 | H16: 33912 | K16: =1.08*G16 -> 777.6 | L16: =+K16*F16 -> 36624.96 | M16: =+K16+I16 -> 777.6 | N16: =+L16+J16 -> 36624.96 | O16: 45338 | R16: =+M16-P16 -> 777.6 | S16: =+N16-Q16 -> 36624.96 | T16: =+R16 -> 777.6 | U16: =+S16 -> 36624.96 | V16: Hùng Nguyên | W16: 45324 | X16: =+W16+'Dieu kien giao hang'!$C$21 -> 45328 | Y16: =+X16+'Dieu kien giao hang'!$C$22 -> 45330
A17: A-10 | B17: TÔN TẤM CUỘN CẮT | C17: PL8X1500X7100 | D17: SS400 | E17: m2 | F17: =+H17/G17 -> 62.8 | G17: 232 | H17: 14569.6 | K17: =1.08*G17 -> 250.56 | L17: =+K17*F17 -> 15735.168 | M17: =+K17+I17 -> 250.56 | N17: =+L17+J17 -> 15735.168 | O17: 45338 | R17: =+M17-P17 -> 250.56 | S17: =+N17-Q17 -> 15735.168 | T17: =+R17 -> 250.56 | U17: =+S17 -> 15735.168 | V17: Hùng Nguyên | W17: 45324 | X17: =+W17+'Dieu kien giao hang'!$C$21 -> 45328 | Y17: =+X17+'Dieu kien giao hang'!$C$22 -> 45330
A18: A-11 | B18: TÔN TẤM CUỘN CẮT | C18: PL8X1500X9000 | D18: SS400 | E18: m2 | F18: =+H18/G18 -> 62.8 | G18: 140 | H18: 8792 | K18: =1.08*G18 -> 151.2 | L18: =+K18*F18 -> 9495.36 | M18: =+K18+I18 -> 151.2 | N18: =+L18+J18 -> 9495.36 | O18: 45338 | R18: =+M18-P18 -> 151.2 | S18: =+N18-Q18 -> 9495.36 | T18: =+R18 -> 151.2 | U18: =+S18 -> 9495.36 | V18: Hùng Nguyên | W18: 45324 | X18: =+W18+'Dieu kien giao hang'!$C$21 -> 45328 | Y18: =+X18+'Dieu kien giao hang'!$C$22 -> 45330
A19: A-12 | B19: TÔN TẤM CUỘN CẮT | C19: PL8X1500X11000 | D19: SS400 | E19: m2 | F19: =+H19/G19 -> 62.8 | G19: 240 | H19: 15072 | K19: =1.08*G19 -> 259.2 | L19: =+K19*F19 -> 16277.76 | M19: =+K19+I19 -> 259.2 | N19: =+L19+J19 -> 16277.76 | O19: 45338 | R19: =+M19-P19 -> 259.2 | S19: =+N19-Q19 -> 16277.76 | T19: =+R19 -> 259.2 | U19: =+S19 -> 16277.76 | V19: Hùng Nguyên | W19: 45324 | X19: =+W19+'Dieu kien giao hang'!$C$21 -> 45328 | Y19: =+X19+'Dieu kien giao hang'!$C$22 -> 45330
A20: A-13 | B20: TÔN TẤM | C20: PL8X2000X12000 | D20: SS400 | E20: m2 | F20: =+H20/G20 -> 62.8 | G20: 140 | H20: 8792 | K20: =1.12*G20 -> 156.8 | L20: =+K20*F20 -> 9847.04 | M20: =+K20+I20 -> 156.8 | N20: =+L20+J20 -> 9847.04 | O20: 45338 | R20: =+M20-P20 -> 156.8 | S20: =+N20-Q20 -> 9847.04 | T20: =+R20 -> 156.8 | U20: =+S20 -> 9847.04 | V20: Hùng Nguyên | W20: 45324 | X20: =+W20+'Dieu kien giao hang'!$C$21 -> 45328 | Y20: =+X20+'Dieu kien giao hang'!$C$22 -> 45330
A21: A-14 | B21: TÔN TẤM | C21: PL10 | D21: A-240 TP304 | E21: m2 | F21: =+H21/G21 -> 78.5 | G21: 0.41579618 | H21: 32.64 | K21: =1.12*G21 -> 0.46569172 | L21: =+K21*F21 -> 36.5568 | M21: =+K21+I21 -> 0.46569172 | N21: =+L21+J21 -> 36.5568 | O21: 45371 | R21: =+M21-P21 -> 0.46569172 | S21: =+N21-Q21 -> 36.5568 | AB21: =+R21 -> 0.46569172 | AC21: =+S21 -> 36.5568 | AD21: GNEE | AE21: 45323 | AF21: =+AE21+'Dieu kien giao hang'!$C$6 -> 45328 | AG21: =AF21+'Dieu kien giao hang'!$C$7 -> 45348 | AH21: =AG21+'Dieu kien giao hang'!$C$8 -> 45353 | AI21: =AH21+'Dieu kien giao hang'!$C$10 -> 45356 | AJ21: =AI21+'Dieu kien giao hang'!$C$13 -> 45368
A22: A-15 | B22: TÔN TẤM | C22: PL10x2000x12000 | D22: A572-GR.50 | E22: m2 | F22: =+H22/G22 -> 78.5 | G22: 48.524841 | H22: 3809.2 | K22: =1.12*G22 -> 54.347822 | L22: =+K22*F22 -> 4266.304 | M22: =+K22+I22 -> 54.347822 | N22: =+L22+J22 -> 4266.304 | O22: 45338 | R22: =+M22-P22 -> 54.347822 | S22: =+N22-Q22 -> 4266.304 | T22: =+R22 -> 54.347822 | U22: =+S22 -> 4266.304 | V22: Hùng Nguyên | W22: 45324 | X22: =+W22+'Dieu kien giao hang'!$C$21 -> 45328 | Y22: =+X22+'Dieu kien giao hang'!$C$22 -> 45330
A23: A-16 | B23: TÔN TẤM | C23: PL12x2000x12000 | D23: A572-GR.50 | E23: m2 | F23: =+H23/G23 -> 94.2 | G23: 1.0292994 | H23: 96.96 | K23: =1.12*G23 -> 1.1528153 | L23: =+K23*F23 -> 108.5952 | M23: =+K23+I23 -> 1.1528153 | N23: =+L23+J23 -> 108.5952 | O23: 45338 | R23: =+M23-P23 -> 1.1528153 | S23: =+N23-Q23 -> 108.5952 | T23: =+R23 -> 1.1528153 | U23: =+S23 -> 108.5952 | V23: Hùng Nguyên | W23: 45324 | X23: =+W23+'Dieu kien giao hang'!$C$21 -> 45328 | Y23: =+X23+'Dieu kien giao hang'!$C$22 -> 45330
A24: A-17 | B24: TÔN TẤM | C24: PL12x2000x12000 | D24: SS400 | E24: m2 | F24: =+H24/G24 -> 94.2 | G24: 8.8276008 | H24: 831.56 | K24: =1.12*G24 -> 9.886913 | L24: =+K24*F24 -> 931.3472 | M24: =+K24+I24 -> 9.886913 | N24: =+L24+J24 -> 931.3472 | O24: 45338 | R24: =+M24-P24 -> 9.886913 | S24: =+N24-Q24 -> 931.3472 | T24: =+R24 -> 9.886913 | U24: =+S24 -> 931.3472 | V24: Hùng Nguyên | W24: 45324 | X24: =+W24+'Dieu kien giao hang'!$C$21 -> 45328 | Y24: =+X24+'Dieu kien giao hang'!$C$22 -> 45330
A25: A-18 | B25: TÔN TẤM | C25: PL16x2000x12000 | D25: A572-GR.50 | E25: m2 | F25: =+H25/G25 -> 125.6 | G25: 12.253503 | H25: 1539.04 | K25: =1.12*G25 -> 13.723924 | L25: =+K25*F25 -> 1723.7248 | M25: =+K25+I25 -> 13.723924 | N25: =+L25+J25 -> 1723.7248 | O25: 45338 | R25: =+M25-P25 -> 13.723924 | S25: =+N25-Q25 -> 1723.7248 | T25: =+R25 -> 13.723924 | U25: =+S25 -> 1723.7248 | V25: Hùng Nguyên | W25: 45324 | X25: =+W25+'Dieu kien giao hang'!$C$21 -> 45328 | Y25: =+X25+'Dieu kien giao hang'!$C$22 -> 45330
A26: A-19 | B26: TÔN TẤM | C26: PL20x2000x12000 | D26: A572-GR.50 | E26: m2 | F26: =+H26/G26 -> 157 | G26: 208.2242 | H26: 32691.2 | K26: =1.12*G26 -> 233.21111 | L26: =+K26*F26 -> 36614.144 | M26: =+K26+I26 -> 233.21111 | N26: =+L26+J26 -> 36614.144 | O26: 45338 | R26: =+M26-P26 -> 233.21111 | S26: =+N26-Q26 -> 36614.144 | T26: =+R26 -> 233.21111 | U26: =+S26 -> 36614.144 | V26: Hùng Nguyên | W26: 45324 | X26: =+W26+'Dieu kien giao hang'!$C$21 -> 45328 | Y26: =+X26+'Dieu kien giao hang'!$C$22 -> 45330
A27: A-20 | B27: TÔN TẤM | C27: PL22x2000x12000 | D27: A572-GR.50 | E27: m2 | F27: =+H27/G27 -> 172.7 | G27: 148.54105 | H27: 25653.04 | K27: =1.12*G27 -> 166.36598 | L27: =+K27*F27 -> 28731.405 | M27: =+K27+I27 -> 166.36598 | N27: =+L27+J27 -> 28731.405 | O27: 45338 | R27: =+M27-P27 -> 166.36598 | S27: =+N27-Q27 -> 28731.405 | T27: =+R27 -> 166.36598 | U27: =+S27 -> 28731.405 | V27: Hùng Nguyên | W27: 45324 | X27: =+W27+'Dieu kien giao hang'!$C$21 -> 45328 | Y27: =+X27+'Dieu kien giao hang'!$C$22 -> 45330
A28: A-21 | B28: TÔN TẤM | C28: PL25 | D28: A572-GR.50 | E28: m2 | F28: =+H28/G28 -> 196.25 | G28: 4.485707 | H28: 880.32 | K28: =1.12*G28 -> 5.0239918 | L28: =+K28*F28 -> 985.9584 | M28: =+K28+I28 -> 5.0239918 | N28: =+L28+J28 -> 985.9584 | O28: 45338 | R28: =+M28-P28 -> 5.0239918 | S28: =+N28-Q28 -> 985.9584 | T28: =+R28 -> 5.0239918 | U28: =+S28 -> 985.9584 | V28: Hùng Nguyên | W28: 45324 | X28: =+W28+'Dieu kien giao hang'!$C$21 -> 45328 | Y28: =+X28+'Dieu kien giao hang'!$C$22 -> 45330
A29: A-22 | B29: TÔN TẤM | C29: PL28 | D29: A572-GR.50 | E29: m2 | F29: =+H29/G29 -> 219.8 | G29: 5.099909 | H29: 1120.96 | K29: =1.12*G29 -> 5.7118981 | L29: =+K29*F29 -> 1255.4752 | M29: =+K29+I29 -> 5.7118981 | N29: =+L29+J29 -> 1255.4752 | O29: 45338 | R29: =+M29-P29 -> 5.7118981 | S29: =+N29-Q29 -> 1255.4752 | T29: =+R29 -> 5.7118981 | U29: =+S29 -> 1255.4752 | V29: Hùng Nguyên | W29: 45324 | X29: =+W29+'Dieu kien giao hang'!$C$21 -> 45328 | Y29: =+X29+'Dieu kien giao hang'!$C$22 -> 45330
A30: A-23 | B30: TÔN TẤM | C30: PL32x2000x6000 | D30: A572-GR.50 | E30: m2 | F30: =+H30/G30 -> 251.2 | G30: 7.6261146 | H30: 1915.68 | K30: =1.12*G30 -> 8.5412484 | L30: =+K30*F30 -> 2145.5616 | M30: =+K30+I30 -> 8.5412484 | N30: =+L30+J30 -> 2145.5616 | O30: 45338 | R30: =+M30-P30 -> 8.5412484 | S30: =+N30-Q30 -> 2145.5616 | T30: =+R30 -> 8.5412484 | U30: =+S30 -> 2145.5616 | V30: Hùng Nguyên | W30: 45324 | X30: =+W30+'Dieu kien giao hang'!$C$21 -> 45328 | Y30: =+X30+'Dieu kien giao hang'!$C$22 -> 45330
A31: A-24 | B31: THÉP HÌNH C | C31: C125X65X6X8-12000L | D31: SS400 | E31: m | F31: =+H31/G31 -> 12.511673 | G31: 373.52 | H31: 4673.36 | K31: =1.06*G31 -> 395.9312 | L31: =+K31*F31 -> 4953.7616 | M31: =+K31+I31 -> 395.9312 | N31: =+L31+J31 -> 4953.7616 | O31: 45338 | R31: =+M31-P31 -> 395.9312 | S31: =+N31-Q31 -> 4953.7616 | T31: =+R31 -> 395.9312 | U31: =+S31 -> 4953.7616 | V31: Hùng Nguyên | W31: 45324 | X31: =+W31+'Dieu kien giao hang'!$C$21 -> 45328 | Y31: =+X31+'Dieu kien giao hang'!$C$22 -> 45330
A32: A-25 | B32: THÉP HÌNH C | C32: C150X75X6.5X10-12000L | D32: SS400 | E32: m | F32: =+H32/G32 -> 18.612228 | G32: 151.264 | H32: 2815.36 | K32: =1.06*G32 -> 160.33984 | L32: =+K32*F32 -> 2984.2816 | M32: =+K32+I32 -> 160.33984 | N32: =+L32+J32 -> 2984.2816 | O32: 45338 | R32: =+M32-P32 -> 160.33984 | S32: =+N32-Q32 -> 2984.2816 | T32: =+R32 -> 160.33984 | U32: =+S32 -> 2984.2816 | V32: Hùng Nguyên | W32: 45324 | X32: =+W32+'Dieu kien giao hang'!$C$21 -> 45328 | Y32: =+X32+'Dieu kien giao hang'!$C$22 -> 45330
A33: A-26 | B33: THÉP HÌNH C | C33: C180X75X7X10.5-12000L | D33: SS400 | E33: m | F33: =+H33/G33 -> 20.123097 | G33: 1508.4 | H33: 30353.68 | K33: =1.06*G33 -> 1598.904 | L33: =+K33*F33 -> 32174.901 | M33: =+K33+I33 -> 1598.904 | N33: =+L33+J33 -> 32174.901 | O33: 45338 | R33: =+M33-P33 -> 1598.904 | S33: =+N33-Q33 -> 32174.901 | T33: =+R33 -> 1598.904 | U33: =+S33 -> 32174.901 | V33: Hùng Nguyên | W33: 45324 | X33: =+W33+'Dieu kien giao hang'!$C$21 -> 45328 | Y33: =+X33+'Dieu kien giao hang'!$C$22 -> 45330
A34: A-27 | B34: THÉP HÌNH C | C34: C200X80X7.5X11-12000L | D34: SS400 | E34: m | F34: =+H34/G34 -> 22.773663 | G34: 550.896 | H34: 12545.92 | K34: =1.06*G34 -> 583.94976 | L34: =+K34*F34 -> 13298.675 | M34: =+K34+I34 -> 583.94976 | N34: =+L34+J34 -> 13298.675 | O34: 45338 | R34: =+M34-P34 -> 583.94976 | S34: =+N34-Q34 -> 13298.675 | T34: =+R34 -> 583.94976 | U34: =+S34 -> 13298.675 | V34: Hùng Nguyên | W34: 45324 | X34: =+W34+'Dieu kien giao hang'!$C$21 -> 45328 | Y34: =+X34+'Dieu kien giao hang'!$C$22 -> 45330
A35: A-28 | B35: THÉP HÌNH C | C35: C200X90X8X13.5-12000L | D35: SS400 | E35: m | F35: =+H35/G35 -> 30.341183 | G35: 152.88 | H35: 4638.56 | K35: =1.06*G35 -> 162.0528 | L35: =+K35*F35 -> 4916.8736 | M35: =+K35+I35 -> 162.0528 | N35: =+L35+J35 -> 4916.8736 | O35: 45338 | R35: =+M35-P35 -> 162.0528 | S35: =+N35-Q35 -> 4916.8736 | T35: =+R35 -> 162.0528 | U35: =+S35 -> 4916.8736 | V35: Hùng Nguyên | W35: 45324 | X35: =+W35+'Dieu kien giao hang'!$C$21 -> 45328 | Y35: =+X35+'Dieu kien giao hang'!$C$22 -> 45330
A36: A-29 | B36: THÉP HÌNH C | C36: C250X90X9X13-12000L | D36: SS400 | E36: m | F36: =+H36/G36 -> 34.594627 | G36: 66.408 | H36: 2297.36 | K36: =1.06*G36 -> 70.39248 | L36: =+K36*F36 -> 2435.2016 | M36: =+K36+I36 -> 70.39248 | N36: =+L36+J36 -> 2435.2016 | O36: 45338 | R36: =+M36-P36 -> 70.39248 | S36: =+N36-Q36 -> 2435.2016 | T36: =+R36 -> 70.39248 | U36: =+S36 -> 2435.2016 | V36: Hùng Nguyên | W36: 45324 | X36: =+W36+'Dieu kien giao hang'!$C$21 -> 45328 | Y36: =+X36+'Dieu kien giao hang'!$C$22 -> 45330
A37: A-30 | B37: THÉP HÌNH H | C37: H150X150X7X10-12000L | D37: SS400 | E37: m | F37: =+H37/G37 -> 24.855967 | G37: 19.44 | H37: 483.2 | K37: =1.06*G37 -> 20.6064 | L37: =+K37*F37 -> 512.192 | M37: =+K37+I37 -> 20.6064 | N37: =+L37+J37 -> 512.192 | O37: 45338 | R37: =+M37-P37 -> 20.6064 | S37: =+N37-Q37 -> 512.192 | T37: =+R37 -> 20.6064 | U37: =+S37 -> 512.192 | V37: Hùng Nguyên | W37: 45324 | X37: =+W37+'Dieu kien giao hang'!$C$21 -> 45328 | Y37: =+X37+'Dieu kien giao hang'!$C$22 -> 45330
A38: A-31 | B38: THÉP HÌNH H | C38: H194X150X6X9-12000L | D38: SS400 | E38: m | F38: =+H38/G38 -> 30.612113 | G38: 6.208 | H38: 190.04 | K38: =1.06*G38 -> 6.58048 | L38: =+K38*F38 -> 201.4424 | M38: =+K38+I38 -> 6.58048 | N38: =+L38+J38 -> 201.4424 | O38: 45338 | R38: =+M38-P38 -> 6.58048 | S38: =+N38-Q38 -> 201.4424 | T38: =+R38 -> 6.58048 | U38: =+S38 -> 201.4424 | V38: Hùng Nguyên | W38: 45324 | X38: =+W38+'Dieu kien giao hang'!$C$21 -> 45328 | Y38: =+X38+'Dieu kien giao hang'!$C$22 -> 45330
A39: A-32 | B39: THÉP HÌNH H | C39: H244X175X7X11-12000L | D39: SS400 | E39: m | F39: =+H39/G39 -> 44.14586 | G39: 234.856 | H39: 10367.92 | K39: =1.06*G39 -> 248.94736 | L39: =+K39*F39 -> 10989.995 | M39: =+K39+I39 -> 248.94736 | N39: =+L39+J39 -> 10989.995 | O39: 45338 | R39: =+M39-P39 -> 248.94736 | S39: =+N39-Q39 -> 10989.995 | T39: =+R39 -> 248.94736 | U39: =+S39 -> 10989.995 | V39: Hùng Nguyên | W39: 45324 | X39: =+W39+'Dieu kien giao hang'!$C$21 -> 45328 | Y39: =+X39+'Dieu kien giao hang'!$C$22 -> 45330
A40: A-33 | B40: THÉP HÌNH H | C40: H250X125X6X9-12000L | D40: SS400 | E40: m | F40: =+H40/G40 -> 29.561881 | G40: 163.152 | H40: 4823.08 | K40: =1.06*G40 -> 172.94112 | L40: =+K40*F40 -> 5112.4648 | M40: =+K40+I40 -> 172.94112 | N40: =+L40+J40 -> 5112.4648 | O40: 45338 | R40: =+M40-P40 -> 172.94112 | S40: =+N40-Q40 -> 5112.4648 | T40: =+R40 -> 172.94112 | U40: =+S40 -> 5112.4648 | V40: Hùng Nguyên | W40: 45324 | X40: =+W40+'Dieu kien giao hang'!$C$21 -> 45328 | Y40: =+X40+'Dieu kien giao hang'!$C$22 -> 45330
A41: A-34 | B41: THÉP HÌNH H | C41: H300X150X6.5X9-12000L | D41: SS400 | E41: m | F41: =+H41/G41 -> 35.582918 | G41: 123.448 | H41: 4392.64 | K41: =1.06*G41 -> 130.85488 | L41: =+K41*F41 -> 4656.1984 | M41: =+K41+I41 -> 130.85488 | N41: =+L41+J41 -> 4656.1984 | O41: 45338 | R41: =+M41-P41 -> 130.85488 | S41: =+N41-Q41 -> 4656.1984 | T41: =+R41 -> 130.85488 | U41: =+S41 -> 4656.1984 | V41: Hùng Nguyên | W41: 45324 | X41: =+W41+'Dieu kien giao hang'!$C$21 -> 45328 | Y41: =+X41+'Dieu kien giao hang'!$C$22 -> 45330
A42: A-35 | B42: THÉP HÌNH L | C42: L100X100X10-12000L | D42: SS400 | E42: m | F42: =+H42/G42 -> 12.744347 | G42: 65.808 | H42: 838.68 | K42: =1.06*G42 -> 69.75648 | L42: =+K42*F42 -> 889.0008 | M42: =+K42+I42 -> 69.75648 | N42: =+L42+J42 -> 889.0008 | O42: 45338 | R42: =+M42-P42 -> 69.75648 | S42: =+N42-Q42 -> 889.0008 | T42: =+R42 -> 69.75648 | U42: =+S42 -> 889.0008 | V42: Hùng Nguyên | W42: 45324 | X42: =+W42+'Dieu kien giao hang'!$C$21 -> 45328 | Y42: =+X42+'Dieu kien giao hang'!$C$22 -> 45330
... A52: A-45 | B52: THÉP HÌNH L | C52: L90X90X7-12000L | D52: SS400 | E52: m | F52: =+H52/G52 -> 9.5901077 | G52: 116.616 | H52: 1118.36 | K52: =1.06*G52 -> 123.61296 | L52: =+K52*F52 -> 1185.4616 | M52: =+K52+I52 -> 123.61296 | N52: =+L52+J52 -> 1185.4616 | O52: 45338 | R52: =+M52-P52 -> 123.61296 | S52: =+N52-Q52 -> 1185.4616 | T52: =+R52 -> 123.61296 | U52: =+S52 -> 1185.4616 | V52: Hùng Nguyên | W52: 45324 | X52: =+W52+'Dieu kien giao hang'!$C$21 -> 45328 | Y52: =+X52+'Dieu kien giao hang'!$C$22 -> 45330
A53: A-46 | B53: THÉP ỐNG | C53: CHS60.3X3.9 | D53: A-106 GR B | E53: m | F53: =+H53/G53 -> 5.1938959 | G53: 22.28 | H53: 115.72 | K53: =1.06*G53 -> 23.6168 | L53: =+K53*F53 -> 122.6632 | M53: =+K53+I53 -> 23.6168 | N53: =+L53+J53 -> 122.6632 | O53: 45371 | R53: =+M53-P53 -> 23.6168 | S53: =+N53-Q53 -> 122.6632 | AB53: =+R53 -> 23.6168 | AC53: =+S53 -> 122.6632 | AD53: GNEE | AE53: 45323 | AF53: =+AE53+'Dieu kien giao hang'!$C$6 -> 45328 | AG53: =AF53+'Dieu kien giao hang'!$C$7 -> 45348 | AH53: =AG53+'Dieu kien giao hang'!$C$8 -> 45353 | AI53: =AH53+'Dieu kien giao hang'!$C$10 -> 45356 | AJ53: =AI53+'Dieu kien giao hang'!$C$13 -> 45368
A54: A-47 | B54: THÉP ỐNG | C54: CHS60.3X3.9 | D54: A-312 TP304 | E54: m | F54: =+H54/G54 -> 5.3510638 | G54: 11.28 | H54: 60.36 | K54: =1.06*G54 -> 11.9568 | L54: =+K54*F54 -> 63.9816 | M54: =+K54+I54 -> 11.9568 | N54: =+L54+J54 -> 63.9816 | O54: 45371 | R54: =+M54-P54 -> 11.9568 | S54: =+N54-Q54 -> 63.9816 | AB54: =+R54 -> 11.9568 | AC54: =+S54 -> 63.9816 | AD54: GNEE | AE54: 45323 | AF54: =+AE54+'Dieu kien giao hang'!$C$6 -> 45328 | AG54: =AF54+'Dieu kien giao hang'!$C$7 -> 45348 | AH54: =AG54+'Dieu kien giao hang'!$C$8 -> 45353 | AI54: =AH54+'Dieu kien giao hang'!$C$10 -> 45356 | AJ54: =AI54+'Dieu kien giao hang'!$C$13 -> 45368
A55: A-48 | B55: THÉP ỐNG | C55: CHS60.3X5.5 | D55: A-312 TP304 | E55: m | F55: =+H55/G55 -> 7.3287671 | G55: 0.584 | H55: 4.28 | K55: =1.06*G55 -> 0.61904 | L55: =+K55*F55 -> 4.5368 | M55: =+K55+I55 -> 0.61904 | N55: =+L55+J55 -> 4.5368 | O55: 45371 | R55: =+M55-P55 -> 0.61904 | S55: =+N55-Q55 -> 4.5368 | AB55: =+R55 -> 0.61904 | AC55: =+S55 -> 4.5368 | AD55: GNEE | AE55: 45323 | AF55: =+AE55+'Dieu kien giao hang'!$C$6 -> 45328 | AG55: =AF55+'Dieu kien giao hang'!$C$7 -> 45348 | AH55: =AG55+'Dieu kien giao hang'!$C$8 -> 45353 | AI55: =AH55+'Dieu kien giao hang'!$C$10 -> 45356 | AJ55: =AI55+'Dieu kien giao hang'!$C$13 -> 45368
A56: A-49 | B56: THÉP ỐNG | C56: CHS88.9X5.5 | D56: A-106 GR B | E56: m | F56: =+H56/G56 -> 11.004367 | G56: 0.916 | H56: 10.08 | K56: =1.06*G56 -> 0.97096 | L56: =+K56*F56 -> 10.6848 | M56: =+K56+I56 -> 0.97096 | N56: =+L56+J56 -> 10.6848 | O56: 45371 | R56: =+M56-P56 -> 0.97096 | S56: =+N56-Q56 -> 10.6848 | AB56: =+R56 -> 0.97096 | AC56: =+S56 -> 10.6848 | AD56: GNEE | AE56: 45323 | AF56: =+AE56+'Dieu kien giao hang'!$C$6 -> 45328 | AG56: =AF56+'Dieu kien giao hang'!$C$7 -> 45348 | AH56: =AG56+'Dieu kien giao hang'!$C$8 -> 45353 | AI56: =AH56+'Dieu kien giao hang'!$C$10 -> 45356 | AJ56: =AI56+'Dieu kien giao hang'!$C$13 -> 45368
A57: A-50 | B57: THÉP ỐNG | C57: CHS88.9X7.6 | D57: A500-GRB | E57: m | F57: =+H57/G57 -> 14.849537 | G57: 13.824 | H57: 205.28 | K57: =1.06*G57 -> 14.65344 | L57: =+K57*F57 -> 217.5968 | M57: =+K57+I57 -> 14.65344 | N57: =+L57+J57 -> 217.5968 | O57: 45338 | R57: =+M57-P57 -> 14.65344 | S57: =+N57-Q57 -> 217.5968 | AB57: =+R57 -> 14.65344 | AC57: =+S57 -> 217.5968 | AD57: GNEE | AE57: 45323 | AF57: =+AE57+'Dieu kien giao hang'!$C$6 -> 45328 | AG57: =AF57+'Dieu kien giao hang'!$C$7 -> 45348 | AH57: =AG57+'Dieu kien giao hang'!$C$8 -> 45353 | AI57: =AH57+'Dieu kien giao hang'!$C$10 -> 45356 | AJ57: =AI57+'Dieu kien giao hang'!$C$13 -> 45368
A58: A-51 | B58: THÉP ỐNG | C58: CHS114.3X6.0 | D58: A-312 TP304 | E58: m | F58: =+H58/G58 -> 16.190476 | G58: 1.428 | H58: 23.12 | K58: =1.06*G58 -> 1.51368 | L58: =+K58*F58 -> 24.5072 | M58: =+K58+I58 -> 1.51368 | N58: =+L58+J58 -> 24.5072 | O58: 45371 | R58: =+M58-P58 -> 1.51368 | S58: =+N58-Q58 -> 24.5072 | AB58: =+R58 -> 1.51368 | AC58: =+S58 -> 24.5072 | AD58: GNEE | AE58: 45323 | AF58: =+AE58+'Dieu kien giao hang'!$C$6 -> 45328 | AG58: =AF58+'Dieu kien giao hang'!$C$7 -> 45348 | AH58: =AG58+'Dieu kien giao hang'!$C$8 -> 45353 | AI58: =AH58+'Dieu kien giao hang'!$C$10 -> 45356 | AJ58: =AI58+'Dieu kien giao hang'!$C$13 -> 45368
A59: A-52 | B59: THÉP ỐNG | C59: CHS168.3X7.1 | D59: A-106 GR B | E59: m | F59: =+H59/G59 -> 26.025105 | G59: 2.868 | H59: 74.64 | K59: =1.06*G59 -> 3.04008 | L59: =+K59*F59 -> 79.1184 | M59: =+K59+I59 -> 3.04008 | N59: =+L59+J59 -> 79.1184 | O59: 45371 | R59: =+M59-P59 -> 3.04008 | S59: =+N59-Q59 -> 79.1184 | AB59: =+R59 -> 3.04008 | AC59: =+S59 -> 79.1184 | AD59: GNEE | AE59: 45323 | AF59: =+AE59+'Dieu kien giao hang'!$C$6 -> 45328 | AG59: =AF59+'Dieu kien giao hang'!$C$7 -> 45348 | AH59: =AG59+'Dieu kien giao hang'!$C$8 -> 45353 | AI59: =AH59+'Dieu kien giao hang'!$C$10 -> 45356 | AJ59: =AI59+'Dieu kien giao hang'!$C$13 -> 45368
A60: A-53 | B60: THÉP ỐNG | C60: CHS168.3X7.1 | D60: A-312 TP304 | E60: m | F60: =+H60/G60 -> 26.226686 | G60: 2.788 | H60: 73.12 | K60: =1.06*G60 -> 2.95528 | L60: =+K60*F60 -> 77.5072 | M60: =+K60+I60 -> 2.95528 | N60: =+L60+J60 -> 77.5072 | O60: 45371 | R60: =+M60-P60 -> 2.95528 | S60: =+N60-Q60 -> 77.5072 | AB60: =+R60 -> 2.95528 | AC60: =+S60 -> 77.5072 | AD60: GNEE | AE60: 45323 | AF60: =+AE60+'Dieu kien giao hang'!$C$6 -> 45328 | AG60: =AF60+'Dieu kien giao hang'!$C$7 -> 45348 | AH60: =AG60+'Dieu kien giao hang'!$C$8 -> 45353 | AI60: =AH60+'Dieu kien giao hang'!$C$10 -> 45356 | AJ60: =AI60+'Dieu kien giao hang'!$C$13 -> 45368
A61: A-54 | B61: THÉP TRÒN | C61: RB1 | D61: SUS304 | E61: m | F61: =+H61/G61 -> 0.0043715847 | G61: 146.4 | H61: 0.64 | K61: =1.06*G61 -> 155.184 | L61: =+K61*F61 -> 0.6784 | M61: =+K61+I61 -> 155.184 | N61: =+L61+J61 -> 0.6784 | O61: 45371 | R61: =+M61-P61 -> 155.184 | S61: =+N61-Q61 -> 0.6784 | AB61: =+R61 -> 155.184 | AC61: =+S61 -> 0.6784 | AD61: GNEE | AE61: 45323 | AF61: =+AE61+'Dieu kien giao hang'!$C$6 -> 45328 | AG61: =AF61+'Dieu kien giao hang'!$C$7 -> 45348 | AH61: =AG61+'Dieu kien giao hang'!$C$8 -> 45353 | AI61: =AH61+'Dieu kien giao hang'!$C$10 -> 45356 | AJ61: =AI61+'Dieu kien giao hang'!$C$13 -> 45368
A62: A-55 | B62: THÉP TRÒN | C62: RB10 | D62: SS400 | E62: m | F62: =+H62/G62 -> 0.55147059 | G62: 9.792 | H62: 5.4 | K62: =1.06*G62 -> 10.37952 | L62: =+K62*F62 -> 5.724 | M62: =+K62+I62 -> 10.37952 | N62: =+L62+J62 -> 5.724 | O62: 45338 | R62: =+M62-P62 -> 10.37952 | S62: =+N62-Q62 -> 5.724 | T62: =+R62 -> 10.37952 | U62: =+S62 -> 5.724 | V62: Hùng Nguyên | W62: 45324 | X62: =+W62+'Dieu kien giao hang'!$C$21 -> 45328 | Y62: =+X62+'Dieu kien giao hang'!$C$22 -> 45330
A63: A-56 | B63: THÉP TRÒN | C63: RB12 | D63: SS400 | E63: m | F63: =+H63/G63 -> 0.78431373 | G63: 2.04 | H63: 1.6 | K63: =1.06*G63 -> 2.1624 | L63: =+K63*F63 -> 1.696 | M63: =+K63+I63 -> 2.1624 | N63: =+L63+J63 -> 1.696 | O63: 45338 | R63: =+M63-P63 -> 2.1624 | S63: =+N63-Q63 -> 1.696 | T63: =+R63 -> 2.1624 | U63: =+S63 -> 1.696 | V63: Hùng Nguyên | W63: 45324 | X63: =+W63+'Dieu kien giao hang'!$C$21 -> 45328 | Y63: =+X63+'Dieu kien giao hang'!$C$22 -> 45330
A64: A-57 | B64: THÉP TRÒN | C64: RB13 | D64: SS400 | E64: m | F64: =+H64/G64 -> 0.93785311 | G64: 10.62 | H64: 9.96 | K64: =1.06*G64 -> 11.2572 | L64: =+K64*F64 -> 10.5576 | M64: =+K64+I64 -> 11.2572 | N64: =+L64+J64 -> 10.5576 | O64: 45338 | R64: =+M64-P64 -> 11.2572 | S64: =+N64-Q64 -> 10.5576 | T64: =+R64 -> 11.2572 | U64: =+S64 -> 10.5576 | V64: Hùng Nguyên | W64: 45324 | X64: =+W64+'Dieu kien giao hang'!$C$21 -> 45328 | Y64: =+X64+'Dieu kien giao hang'!$C$22 -> 45330
A65: A-58 | B65: THÉP TRÒN | C65: RB16 | D65: SS400 | E65: m | F65: =+H65/G65 -> 1.4267677 | G65: 9.504 | H65: 13.56 | K65: =1.06*G65 -> 10.07424 | L65: =+K65*F65 -> 14.3736 | M65: =+K65+I65 -> 10.07424 | N65: =+L65+J65 -> 14.3736 | O65: 45338 | R65: =+M65-P65 -> 10.07424 | S65: =+N65-Q65 -> 14.3736 | T65: =+R65 -> 10.07424 | U65: =+S65 -> 14.3736 | V65: Hùng Nguyên | W65: 45324 | X65: =+W65+'Dieu kien giao hang'!$C$21 -> 45328 | Y65: =+X65+'Dieu kien giao hang'!$C$22 -> 45330
A66: A-59 | B66: THÉP TRÒN | C66: RB19 | D66: SS400 | E66: m | F66: =+H66/G66 -> 2 | G66: 4.28 | H66: 8.56 | K66: =1.06*G66 -> 4.5368 | L66: =+K66*F66 -> 9.0736 | M66: =+K66+I66 -> 4.5368 | N66: =+L66+J66 -> 9.0736 | O66: 45338 | R66: =+M66-P66 -> 4.5368 | S66: =+N66-Q66 -> 9.0736 | T66: =+R66 -> 4.5368 | U66: =+S66 -> 9.0736 | V66: Hùng Nguyên | W66: 45324 | X66: =+W66+'Dieu kien giao hang'!$C$21 -> 45328 | Y66: =+X66+'Dieu kien giao hang'!$C$22 -> 45330
A67: A-60 | B67: THÉP TRÒN | C67: RB38 | D67: SS400 | E67: m | F67: =+H67/G67 -> 8.3393178 | G67: 13.368 | H67: 111.48 | K67: =1.06*G67 -> 14.17008 | L67: =+K67*F67 -> 118.1688 | M67: =+K67+I67 -> 14.17008 | N67: =+L67+J67 -> 118.1688 | O67: 45338 | R67: =+M67-P67 -> 14.17008 | S67: =+N67-Q67 -> 118.1688 | T67: =+R67 -> 14.17008 | U67: =+S67 -> 118.1688 | V67: Hùng Nguyên | W67: 45324 | X67: =+W67+'Dieu kien giao hang'!$C$21 -> 45328 | Y67: =+X67+'Dieu kien giao hang'!$C$22 -> 45330
A68: A-61 | B68: LƯỚI DẬP GIÃN | C68: EXPANDED_METAL_3/4"_#16_FLATTENED | D68: SS400-MẠ KẼM | E68: m2 | F68: =+H68/G68 -> 2.29 | G68: 34.934498 | H68: 80 | K68: =1.12*G68 -> 39.126638 | L68: =+K68*F68 -> 89.6 | M68: =+K68+I68 -> 39.126638 | N68: =+L68+J68 -> 89.6 | O68: 45392 | R68: =+M68-P68 -> 39.126638 | S68: =+N68-Q68 -> 89.6 | T68: =+R68 -> 39.126638 | U68: =+S68 -> 89.6 | V68: XALACO | W68: 45329 | X68: =+W68+'Dieu kien giao hang'!$C$31 -> 45355 | Y68: =+X68+'Dieu kien giao hang'!$C$32 -> 45357
A69: A-62 | B69: PIN HÀN+WASHER | C69: PIN Ø2.6X40( 01 PIN+01 SELF-LOCKING INSULAFTION WASHER 2 1/2"X2 1/2" SQUARE ) | D69: SUS304H | E69: Sets | F69: =+H69/G69 -> 0.063037975 | G69: 632 | H69: 39.84 | K69: 700 | L69: =+K69*F69 -> 44.126582 | M69: =+K69+I69 -> 700 | N69: =+L69+J69 -> 44.126582 | O69: 45392 | R69: =+M69-P69 -> 700 | S69: =+N69-Q69 -> 44.126582 | T69: =+R69 -> 700 | U69: =+S69 -> 44.126582 | V69: XALACO | W69: 45329 | X69: =+W69+'Dieu kien giao hang'!$C$31 -> 45355 | Y69: =+X69+'Dieu kien giao hang'!$C$32 -> 45357
A70: A-63 | B70: BỊT ĐẦU ỐNG | C70: 2"_3000# THREADED PIPE CAP | D70: A105 | E70: CÁI | F70: =+H70/G70 -> 1.73 | G70: 24 | H70: 41.52 | K70: =+G70 -> 24 | L70: =+K70*F70 -> 41.52 | M70: =+K70+I70 -> 24 | N70: =+L70+J70 -> 41.52 | O70: 45392 | R70: =+M70-P70 -> 24 | S70: =+N70-Q70 -> 41.52 | T70: =+R70 -> 24 | U70: =+S70 -> 41.52 | V70: XALACO | W70: 45329 | X70: =+W70+'Dieu kien giao hang'!$C$31 -> 45355 | Y70: =+X70+'Dieu kien giao hang'!$C$32 -> 45357
A71: A-64 | B71: NỐI ỐNG | C71: 2"_3000#_THREADED_COUPLING | D71: A105 | E71: CÁI | F71: =+H71/G71 -> 1.106 | G71: 40 | H71: 44.24 | K71: =+G71 -> 40 | L71: =+K71*F71 -> 44.24 | M71: =+K71+I71 -> 40 | N71: =+L71+J71 -> 44.24 | O71: 45392 | R71: =+M71-P71 -> 40 | S71: =+N71-Q71 -> 44.24 | T71: =+R71 -> 40 | U71: =+S71 -> 44.24 | V71: XALACO | W71: 45329 | X71: =+W71+'Dieu kien giao hang'!$C$31 -> 45355 | Y71: =+X71+'Dieu kien giao hang'!$C$32 -> 45357
A72: A-65 | B72: BỊT ĐẦU ỐNG | C72: 3"_3000# THREADED PIPE CAP | D72: A105 | E72: CÁI | F72: =+H72/G72 -> 3.94 | G72: 4 | H72: 15.76 | K72: =+G72 -> 4 | L72: =+K72*F72 -> 15.76 | M72: =+K72+I72 -> 4 | N72: =+L72+J72 -> 15.76 | O72: 45392 | R72: =+M72-P72 -> 4 | S72: =+N72-Q72 -> 15.76 | T72: =+R72 -> 4 | U72: =+S72 -> 15.76 | V72: XALACO | W72: 45329 | X72: =+W72+'Dieu kien giao hang'!$C$31 -> 45355 | Y72: =+X72+'Dieu kien giao hang'!$C$32 -> 45357
A73: A-66 | B73: BÍCH MÙ | C73: 4"_BLIND_FLANGE_#150_RF | D73: A105 | E73: CÁI | F73: =+H73/G73 -> 7.42 | G73: 4 | H73: 29.68 | K73: =+G73 -> 4 | L73: =+K73*F73 -> 29.68 | M73: =+K73+I73 -> 4 | N73: =+L73+J73 -> 29.68 | O73: 45392 | R73: =+M73-P73 -> 4 | S73: =+N73-Q73 -> 29.68 | T73: =+R73 -> 4 | U73: =+S73 -> 29.68 | V73: XALACO | W73: 45329 | X73: =+W73+'Dieu kien giao hang'!$C$31 -> 45355 | Y73: =+X73+'Dieu kien giao hang'!$C$32 -> 45357
A74: A-67 | B74: BÍCH | C74: 4"_FLANGE_#150_SORF | D74: A105 | E74: CÁI | F74: =+H74/G74 -> 5.69 | G74: 4 | H74: 22.76 | K74: =+G74 -> 4 | L74: =+K74*F74 -> 22.76 | M74: =+K74+I74 -> 4 | N74: =+L74+J74 -> 22.76 | O74: 45392 | R74: =+M74-P74 -> 4 | S74: =+N74-Q74 -> 22.76 | T74: =+R74 -> 4 | U74: =+S74 -> 22.76 | V74: XALACO | W74: 45329 | X74: =+W74+'Dieu kien giao hang'!$C$31 -> 45355 | Y74: =+X74+'Dieu kien giao hang'!$C$32 -> 45357
A75: A-68 | B75: GIOĂNG | C75: 4"_GASKET_#150_SORF | D75: NON_METALLIC | E75: CÁI | F75: =+H75/G75 -> 0.04 | G75: 4 | H75: 0.16 | K75: =+G75 -> 4 | L75: =+K75*F75 -> 0.16 | M75: =+K75+I75 -> 4 | N75: =+L75+J75 -> 0.16 | O75: 45392 | R75: =+M75-P75 -> 4 | S75: =+N75-Q75 -> 0.16 | T75: =+R75 -> 4 | U75: =+S75 -> 0.16 | V75: XALACO | W75: 45329 | X75: =+W75+'Dieu kien giao hang'!$C$31 -> 45355 | Y75: =+X75+'Dieu kien giao hang'!$C$32 -> 45357
A76: A-69 | B76: BÍCH MÙ | C76: 6"_BLIND_FLANGE_#150_RF | D76: A105 | E76: CÁI | F76: =+H76/G76 -> 12.07 | G76: 12 | H76: 144.84 | K76: =+G76 -> 12 | L76: =+K76*F76 -> 144.84 | M76: =+K76+I76 -> 12 | N76: =+L76+J76 -> 144.84 | O76: 45392 | R76: =+M76-P76 -> 12 | S76: =+N76-Q76 -> 144.84 | T76: =+R76 -> 12 | U76: =+S76 -> 144.84 | V76: XALACO | W76: 45329 | X76: =+W76+'Dieu kien giao hang'!$C$31 -> 45355 | Y76: =+X76+'Dieu kien giao hang'!$C$32 -> 45357
A77: A-70 | B77: BÍCH | C77: 6"_FLANGE_#150_SORF | D77: A105 | E77: CÁI | F77: =+H77/G77 -> 8.1 | G77: 12 | H77: 97.2 | K77: =+G77 -> 12 | L77: =+K77*F77 -> 97.2 | M77: =+K77+I77 -> 12 | N77: =+L77+J77 -> 97.2 | O77: 45392 | R77: =+M77-P77 -> 12 | S77: =+N77-Q77 -> 97.2 | T77: =+R77 -> 12 | U77: =+S77 -> 97.2 | V77: XALACO | W77: 45329 | X77: =+W77+'Dieu kien giao hang'!$C$31 -> 45355 | Y77: =+X77+'Dieu kien giao hang'!$C$32 -> 45357
A78: A-71 | B78: GIOĂNG | C78: 6"_GASKET_#150_SORF | D78: NON_METALLIC | E78: CÁI | F78: =+H78/G78 -> 0.05 | G78: 12 | H78: 0.6 | K78: =+G78 -> 12 | L78: =+K78*F78 -> 0.6 | M78: =+K78+I78 -> 12 | N78: =+L78+J78 -> 0.6 | O78: 45392 | R78: =+M78-P78 -> 12 | S78: =+N78-Q78 -> 0.6 | T78: =+R78 -> 12 | U78: =+S78 -> 0.6 | V78: XALACO | W78: 45329 | X78: =+W78+'Dieu kien giao hang'!$C$31 -> 45355 | Y78: =+X78+'Dieu kien giao hang'!$C$32 -> 45357
A79: A-72 | B79: BỊT ĐẦU ỐNG | C79: SQUARE HEAD PLUG 2"3000# | D79: A105 | E79: CÁI | F79: =+H79/G79 -> 0.881 | G79: 40 | H79: 35.24 | K79: =+G79 -> 40 | L79: =+K79*F79 -> 35.24 | M79: =+K79+I79 -> 40 | N79: =+L79+J79 -> 35.24 | O79: 45392 | R79: =+M79-P79 -> 40 | S79: =+N79-Q79 -> 35.24 | T79: =+R79 -> 40 | U79: =+S79 -> 35.24 | V79: XALACO | W79: 45329 | X79: =+W79+'Dieu kien giao hang'!$C$31 -> 45355 | Y79: =+X79+'Dieu kien giao hang'!$C$32 -> 45357
A80: A-73 | B80: ĐINH BẢO ÔN | C80: STUD M10X44( 01 PIN-SUS304+02 NUT-SUS304+02 PLATE WASHER-SUH409) | D80: SUS304+SUH409 | E80: Sets | F80: =+H80/G80 -> 0.18145522 | G80: 1072 | H80: 194.52 | K80: 1110 | L80: =+K80*F80 -> 201.4153 | M80: =+K80+I80 -> 1110 | N80: =+L80+J80 -> 201.4153 | O80: 45392 | R80: =+M80-P80 -> 1110 | S80: =+N80-Q80 -> 201.4153 | T80: =+R80 -> 1110 | U80: =+S80 -> 201.4153 | V80: XALACO | W80: 45329 | X80: =+W80+'Dieu kien giao hang'!$C$31 -> 45355 | Y80: =+X80+'Dieu kien giao hang'!$C$32 -> 45357 | AM80: XEM BẢN VẼ
A81: A-74 | B81: ĐINH BẢO ÔN | C81: STUD M10X67( 01 PIN-SUS304+02 NUT-SUS304+02 PLATE WASHER-SUH409) | D81: SUS304+SUH409 | E81: Sets | F81: =+H81/G81 -> 0.158 | G81: 2840 | H81: 448.72 | K81: 2930 | L81: =+K81*F81 -> 462.94 | M81: =+K81+I81 -> 2930 | N81: =+L81+J81 -> 462.94 | O81: 45392 | R81: =+M81-P81 -> 2930 | S81: =+N81-Q81 -> 462.94 | T81: =+R81 -> 2930 | U81: =+S81 -> 462.94 | V81: XALACO | W81: 45329 | X81: =+W81+'Dieu kien giao hang'!$C$31 -> 45355 | Y81: =+X81+'Dieu kien giao hang'!$C$32 -> 45357 | AM81: XEM BẢN VẼ
A82: A-75 | B82: ĐINH BẢO ÔN | C82: STUD M10X133( 01 PIN-SUS304+02 NUT-SUS304+02 PLATE WASHER-SUH409) | D82: SUS304+SUH409 | E82: Sets | F82: =+H82/G82 -> 0.27311175 | G82: 4152 | H82: 1133.96 | K82: 4280 | L82: =+K82*F82 -> 1168.9183 | M82: =+K82+I82 -> 4280 | N82: =+L82+J82 -> 1168.9183 | O82: 45392 | R82: =+M82-P82 -> 4280 | S82: =+N82-Q82 -> 1168.9183 | T82: =+R82 -> 4280 | U82: =+S82 -> 1168.9183 | V82: XALACO | W82: 45329 | X82: =+W82+'Dieu kien giao hang'!$C$31 -> 45355 | Y82: =+X82+'Dieu kien giao hang'!$C$32 -> 45357 | AM82: XEM BẢN VẼ
A83: A-76 | B83: ĐINH BẢO ÔN | C83: STUD M10X152( 01 PIN-SUS304+02 NUT-SUS304+02 PLATE WASHER-SUH409) | D83: SUS304+SUH409 | E83: Sets | F83: =+H83/G83 -> 0.206 | G83: 20 | H83: 4.12 | K83: 25 | L83: =+K83*F83 -> 5.15 | M83: =+K83+I83 -> 25 | N83: =+L83+J83 -> 5.15 | O83: 45392 | R83: =+M83-P83 -> 25 | S83: =+N83-Q83 -> 5.15 | T83: =+R83 -> 25 | U83: =+S83 -> 5.15 | V83: XALACO | W83: 45329 | X83: =+W83+'Dieu kien giao hang'!$C$31 -> 45355 | Y83: =+X83+'Dieu kien giao hang'!$C$32 -> 45357 | AM83: XEM BẢN VẼ
A84: A-77 | B84: ĐINH BẢO ÔN | C84: STUD M12X137( 01 PIN-SUS304+02 NUT-SUS304+02 PLATE WASHER-SUH409) | D84: SUS304+SUH409 | E84: Sets | F84: 0.2075 | G84: =3800*4 -> 15200 | H84: =+G84*F84 -> 3154 | K84: 16000 | L84: =+K84*F84 -> 3320 | M84: =+K84+I84 -> 16000 | N84: =+L84+J84 -> 3320 | O84: 45392 | R84: =+M84-P84 -> 16000 | S84: =+N84-Q84 -> 3320 | T84: =+R84 -> 16000 | U84: =+S84 -> 3320 | V84: XALACO | W84: 45329 | X84: =+W84+'Dieu kien giao hang'!$C$31 -> 45355 | Y84: =+X84+'Dieu kien giao hang'!$C$32 -> 45357 | AM84: XEM BẢN VẼ
A85: A-78 | B85: BÔNG BẢO ÔN | C85: BÔNG BẢO ÔN DÀY 25mm | D85: SUPERWOOD PLUS (128kg/m3) | E85: m3 | F85: =+H85/G85 -> 128 | G85: 56 | H85: 7168 | K85: =+G85*1.25 -> 70 | L85: =+K85*F85 -> 8960 | M85: =+K85+I85 -> 70 | N85: =+L85+J85 -> 8960 | O85: 45392 | R85: =+M85-P85 -> 70 | S85: =+N85-Q85 -> 8960 | T85: =+R85 -> 70 | U85: =+S85 -> 8960 | V85: XALACO | W85: 45329 | X85: =+W85+'Dieu kien giao hang'!$C$31 -> 45355 | Y85: =+X85+'Dieu kien giao hang'!$C$32 -> 45357
A86: A-79 | B86: BÔNG BẢO ÔN | C86: BÔNG BẢO ÔN DÀY 50mm | D86: SUPERWOOD PLUS (128kg/m3) | E86: m3 | F86: =+H86/G86 -> 128 | G86: 216 | H86: 27648 | K86: =+G86*1.25 -> 270 | L86: =+K86*F86 -> 34560 | M86: =+K86+I86 -> 270 | N86: =+L86+J86 -> 34560 | O86: 45392 | R86: =+M86-P86 -> 270 | S86: =+N86-Q86 -> 34560 | T86: =+R86 -> 270 | U86: =+S86 -> 34560 | V86: XALACO | W86: 45329 | X86: =+W86+'Dieu kien giao hang'!$C$31 -> 45355 | Y86: =+X86+'Dieu kien giao hang'!$C$32 -> 45357
A87: B. | B87: Accessory-Material / Vật tư phụ-Mạ kẽm nhúng nóng | H87: =+SUM(H88:H101) -> 46.52 | L87: =+SUM(L88:L101) -> 0 | N87: =+SUM(N88:N101) -> 0 | R87: =+M87-P87 -> 0 | S87: =+N87-Q87 -> 0
A88: B-1 | B88: Bu lông (1B+1N)-MẠ KẼM | C88: BOLT 1/2" DIA x 1 1/2" (40mm) LG | D88: A307 | E88: Sets | G88: 54 | I88: 60 | M88: =+K88+I88 -> 60 | O88: 45328 | R88: =+M88-P88 -> 60 | S88: =+N88-Q88 -> 0 | T88: =+R88 -> 60 | U88: =+S88 -> 0 | V88: XALACO | W88: 45329 | X88: =+W88+'Dieu kien giao hang'!$C$31 -> 45355 | Y88: =+X88+'Dieu kien giao hang'!$C$32 -> 45357 | AM88: BOLT M12X40-ISO4017-Gr8.8(1B+1N)-MẠ KẼM
A89: B-2 | B89: CHỐT | C89: CLEVIS PIN Ø12x52-DIN 1444-MẠ ĐIỆN PHÂN | D89: SS400-MẠ KẼM | E89: cái | G89: 96 | H89: 5.4 | K89: 100 | M89: =+K89+I89 -> 100 | O89: 45392 | R89: =+M89-P89 -> 100 | S89: =+N89-Q89 -> 0 | T89: =+R89 -> 100 | U89: =+S89 -> 0 | V89: XALACO | W89: 45329 | X89: =+W89+'Dieu kien giao hang'!$C$31 -> 45355 | Y89: =+X89+'Dieu kien giao hang'!$C$32 -> 45357
A90: B-3 | B90: GIỮ CHỐT | C90: COTTER PIN Ø3.2x25L-DIN 94- MẠ ĐIỆN PHÂN | D90: SS400-MẠ KẼM | E90: cái | G90: 96 | H90: 0.48 | K90: 100 | M90: =+K90+I90 -> 100 | O90: 45392 | R90: =+M90-P90 -> 100 | S90: =+N90-Q90 -> 0 | T90: =+R90 -> 100 | U90: =+S90 -> 0 | V90: XALACO | W90: 45329 | X90: =+W90+'Dieu kien giao hang'!$C$31 -> 45355 | Y90: =+X90+'Dieu kien giao hang'!$C$32 -> 45357
A91: B-4 | B91: EYE BOLT | C91: EYE BOLT D13 | D91: SS400-MẠ KẼM | E91: cái | G91: 12 | H91: 3 | K91: 18 | M91: =+K91+I91 -> 18 | O91: 45392 | R91: =+M91-P91 -> 18 | S91: =+N91-Q91 -> 0 | T91: =+R91 -> 18 | U91: =+S91 -> 0 | V91: XALACO | W91: 45329 | X91: =+W91+'Dieu kien giao hang'!$C$31 -> 45355 | Y91: =+X91+'Dieu kien giao hang'!$C$32 -> 45357
A92: B-5 | B92: VÒNG ĐỆM | C92: FLAT WASHER,ZINC PLATE,1/2"DIA | D92: SS400-MẠ KẼM | E92: cái | G92: 96 | H92: 0.6 | K92: 100 | M92: =+K92+I92 -> 100 | O92: 45392 | R92: =+M92-P92 -> 100 | S92: =+N92-Q92 -> 0 | T92: =+R92 -> 100 | U92: =+S92 -> 0 | V92: XALACO | W92: 45329 | X92: =+W92+'Dieu kien giao hang'!$C$31 -> 45355 | Y92: =+X92+'Dieu kien giao hang'!$C$32 -> 45357
A93: B-6 | B93: VÒNG ĐỆM | C93: FLAT WASHER,ZINC PLATE,5/8"DIA | D93: SS400-MẠ KẼM | E93: cái | G93: 96 | H93: 0.84 | K93: 100 | M93: =+K93+I93 -> 100 | O93: 45392 | R93: =+M93-P93 -> 100 | S93: =+N93-Q93 -> 0 | T93: =+R93 -> 100 | U93: =+S93 -> 0 | V93: XALACO | W93: 45329 | X93: =+W93+'Dieu kien giao hang'!$C$31 -> 45355 | Y93: =+X93+'Dieu kien giao hang'!$C$32 -> 45357
A94: B-7 | B94: ECU | C94: NUT_M16 | D94: 5.6-MẠ KẼM | E94: cái | G94: 96 | H94: 4.92 | K94: 100 | M94: =+K94+I94 -> 100 | O94: 45392 | R94: =+M94-P94 -> 100 | S94: =+N94-Q94 -> 0 | T94: =+R94 -> 100 | U94: =+S94 -> 0 | V94: XALACO | W94: 45329 | X94: =+W94+'Dieu kien giao hang'!$C$31 -> 45355 | Y94: =+X94+'Dieu kien giao hang'!$C$32 -> 45357
A95: B-8 | B95: GOĂNG | C95: GASKET TADPOLE MCMASTER-CARR PART 8815K33-3/4"x11/2" | D95: FIBER GLASS | E95: m | G95: 20.8 | H95: 2.08 | K95: 30 | M95: =+K95+I95 -> 30 | O95: 45392 | R95: =+M95-P95 -> 30 | S95: =+N95-Q95 -> 0 | T95: =+R95 -> 30 | U95: =+S95 -> 0 | V95: XALACO | W95: 45329 | X95: =+W95+'Dieu kien giao hang'!$C$31 -> 45355 | Y95: =+X95+'Dieu kien giao hang'!$C$32 -> 45357
A96: B-9 | B96: GOĂNG | C96: GASKET TADPOLE MCMASTER-CARR PART 8853K26-3/4"x11/2" | D96: FIBER GLASS | E96: m | G96: 19.9 | H96: 3.92 | K96: 30 | M96: =+K96+I96 -> 30 | O96: 45392 | R96: =+M96-P96 -> 30 | S96: =+N96-Q96 -> 0 | T96: =+R96 -> 30 | U96: =+S96 -> 0 | V96: XALACO | W96: 45329 | X96: =+W96+'Dieu kien giao hang'!$C$31 -> 45355 | Y96: =+X96+'Dieu kien giao hang'!$C$32 -> 45357
A97: B-10 | B97: KEO DÁN GIOĂNG | C97: HIGH TEMPERATURE ADHESIVE | D97: SILICA W/ INCONEL | E97: lits | G97: 2 | H97: 8.2 | K97: 2 | M97: =+K97+I97 -> 2 | O97: 45392 | R97: =+M97-P97 -> 2 | S97: =+N97-Q97 -> 0 | T97: =+R97 -> 2 | U97: =+S97 -> 0 | V97: XALACO | W97: 45329 | X97: =+W97+'Dieu kien giao hang'!$C$31 -> 45355 | Y97: =+X97+'Dieu kien giao hang'!$C$32 -> 45357
A98: B-11 | B98: GIOĂNG | C98: mcmaster-carr part no. 24175K46. STYLE 10 | D98: EPDM RUBBER | E98: m | G98: 29.232 | H98: 2.88 | K98: 40 | M98: =+K98+I98 -> 40 | O98: 45392 | R98: =+M98-P98 -> 40 | S98: =+N98-Q98 -> 0 | T98: =+R98 -> 40 | U98: =+S98 -> 0 | V98: XALACO | W98: 45329 | X98: =+W98+'Dieu kien giao hang'!$C$31 -> 45355 | Y98: =+X98+'Dieu kien giao hang'!$C$32 -> 45357
A99: B-12 | B99: VÍT | C99: SCREW M5x15L | D99: SCREWS,LOW PROFILE , SELF | E99: cái | G99: 288 | H99: 8.76 | K99: 300 | M99: =+K99+I99 -> 300 | O99: 45392 | R99: =+M99-P99 -> 300 | S99: =+N99-Q99 -> 0 | T99: =+R99 -> 300 | U99: =+S99 -> 0 | V99: XALACO | W99: 45329 | X99: =+W99+'Dieu kien giao hang'!$C$31 -> 45355 | Y99: =+X99+'Dieu kien giao hang'!$C$32 -> 45357
A100: B-13 | B100: VÍT | C100: SCREW M5x25L | D100: SCREWS,LOW PROFILE , SELF | E100: cái | G100: 152 | H100: 4.6 | K100: 180 | M100: =+K100+I100 -> 180 | O100: 45392 | R100: =+M100-P100 -> 180 | S100: =+N100-Q100 -> 0 | T100: =+R100 -> 180 | U100: =+S100 -> 0 | V100: XALACO | W100: 45329 | X100: =+W100+'Dieu kien giao hang'!$C$31 -> 45355 | Y100: =+X100+'Dieu kien giao hang'!$C$32 -> 45357
A101: B-14 | B101: GIOĂNG | C101: GASKET PL3 | D101: FIBER GLASS | E101: cái | G101: 4 | H101: 0.84 | K101: 4 | M101: =+K101+I101 -> 4 | O101: 45392 | R101: =+M101-P101 -> 4 | S101: =+N101-Q101 -> 0 | T101: =+R101 -> 4 | U101: =+S101 -> 0 | V101: XALACO | W101: 45329 | X101: =+W101+'Dieu kien giao hang'!$C$31 -> 45355 | Y101: =+X101+'Dieu kien giao hang'!$C$32 -> 45357 | AM101: XEM BẢN VẼ
