Workbook
Name \0: #REF!
Name \a: #N/A
Name \a: #N/A
Name \a: #N/A
Name \a: #N/A
Name \a: #N/A
Name \a: #N/A
Name \a: #N/A
Name \a: #N/A
Name \a: #N/A
Name \a: #N/A
Name \a: #N/A
Name \a: #N/A
Name \b: #N/A
Name \c: #N/A
Name \d: #N/A
Name \e: #N/A
Name \f: #N/A
Name \g: #N/A
Name \h: #N/A
Name \h: #N/A
Name \h: #N/A
Name \h: #N/A
Name \h: #N/A
Name \h: #N/A
Name \h: #N/A
Name \h: #N/A
Name \h: #N/A
Name \h: #N/A
Name \h: #N/A
Name \h: #N/A
Name \i: #N/A
Name \i: #N/A
Name \i: #N/A
Name \i: #N/A
Name \i: #N/A
Name \i: #N/A
Name \i: #N/A
Name \i: #N/A
Name \i: #N/A
Name \i: #N/A
Name \i: #N/A
Name \i: #N/A
Name \j: #N/A
Name \k: #N/A
Name \KWS123: #N/A
Name \l: '[1]??-BLDG'!#REF!
Name \m: #N/A
Name \m: #N/A
Name \m: #N/A
Name \m: #N/A
Name \m: #N/A
Name \m: #N/A
Name \m: #N/A
Name \m: #N/A
Name \m: #N/A
Name \m: #N/A
Name \m: #N/A
Name \m: #N/A
Name \n: #N/A

Sheet HN-16-1
A1: BID ANALYSIS - GIẢI TRÌNH MUA SẮM/ĐẤU THẦU
A3: Project | B3: PROJECT No/ Dự án: 25-VPI-I-095
A4: Dự án
A5: Subject | B5: Cung cấp vật tư chính thép đen Hùng Nguyên ngày 16-1-2026
A6: Chủ đề
A8: No. | B8: CONTENT | C8: Phạm vi công việc | H8: Dự toán | K8: Đã mua | L8: Đơn vị cung cấp chào giá phần còn lại (VNĐ) | O8: Đơn vị cung cấp chào giá phần còn lại (VNĐ) | R8: Đơn vị cung cấp chào giá phần còn lại (VNĐ) | U8: Ghi chú
A9: Item | B9: Description/ Chi tiết | C9: Profile/ Vật tư | D9: Grade/ Mác vật liệu | E9: Grade/ Mác vật liệu mua | F9: Số lượng Mua (M) | G9: Số lượng PR (M) | H9: Khối lượng/ Số lượng | I9: Đơn giá (vnd) | J9: Thành tiền (vnd) | K9: Thành tiền (vnd) | L9: NGỌC HIẾU | O9: Hùng Nguyên | R9: APEC
L10: Phạm vi | M10: Đơn giá trước VAT (VNĐ/KG) | N10: Thành Tiền | O10: Phạm vi | P10: Đơn giá trước VAT (VNĐ/KG) | Q10: Thành Tiền | R10: Phạm vi | S10: Đơn giá trước VAT (VNĐ/KG) | T10: Thành Tiền
A11: Tổng | B11: Main-Material / Vật tư chính thép đen | H11: N/A | I11: N/A | J11: ='DT03 (TM)'!G6 -> 5.7151444e+10 | K11: ='Tổng hợp'!J19 -> 4.7616213e+10 | Q11: =SUM(Q12:Q13) -> 47939240 | U11: =J11-K11-Q11-N11 -> 9.4872916e+09
A12: I95-VTC01-008 | B12: =VLOOKUP(A12,'25-VPI-I-095'!L:N,3,0) -> PL12X2000X12000 | C12: Thép tấm 12x2000x12000 SS400 | D12: =VLOOKUP(A12,'25-VPI-I-095'!L:R,4,0) -> SS400 | E12: SS400 | F12: 24 | G12: =VLOOKUP(A12,'25-VPI-I-095'!L:DI,91,0) -> 0 | H12: N/A | I12: N/A | J12: N/A | K12: N/A | L12: X | M12: #N/A | N12: #N/A | O12: V | P12: 13363.64 | Q12: 30212517 | R12: V | S12: =14800/1.1 -> 13454.545 | T12: =VLOOKUP(D12,'[164]DA 95'!$B$20:$N$31,13,0) -> #N/A | U12: Chọn Hùng Nguyên
A13: I95-VTC01-121 | B13: =VLOOKUP(A13,'25-VPI-I-095'!L:N,3,0) -> PL8X1500X4600 | C13: Thép tấm 8x1500x4600 SS400 | D13: =VLOOKUP(A13,'25-VPI-I-095'!L:R,4,0) -> SS400 | E13: SS400 | F13: =3*1.5*4.6 -> 20.7 | G13: =VLOOKUP(A13,'25-VPI-I-095'!L:DI,91,0) -> 0 | H13: N/A | I13: N/A | J13: N/A | K13: N/A | L13: V | M13: =15100/1.1 -> 13727.273 | N13: #N/A | O13: V | P13: 13636.36 | Q13: 17726723 | R13: V | S13: 13727.273 | T13: =VLOOKUP(D13,'[164]DA 95'!$B$20:$N$31,13,0) -> #N/A | U13: Chọn Hùng Nguyên
B14: Xếp hạng | M14: 3 | P14: 1 | S14: 2
A15: Ghi chú: Tiếp tục công tác mua sắm để đảm báo tiến độ
A16: NGƯỜI ĐỀ NGHỊ/ RECOMMENDATION BY: | F16: NGƯỜI KIỂM TRA/ DEPARTMENT HEAD CHECK BY: | N16: APPROVED BY: PHÊ DUYỆT
N17: Nguyễn Quang Vinh | Q17: Hoàng Ngọc Bằng | T17: Đoàn Văn Toàn

Sheet hOÀNG hÀ bổ sung
A1: BID ANALYSIS - GIẢI TRÌNH MUA SẮM/ĐẤU THẦU
A3: Project | B3: PROJECT No/ Dự án: 25-VPI-I-095
A4: Dự án
A5: Subject | B5: Cung cấp vật tư phụ kiện / đóng kiện hoàng hà 26-1-2026 / Tách
A6: Chủ đề
A8: No. | B8: CONTENT | C8: Phạm vi công việc | I8: Dự toán | K8: Đã mua | L8: Đơn vị cung cấp chào giá (vnđ) | O8: Lựa chọn | P8: Ghi chú
A9: Item | B9: Description/ Chi tiết | C9: Profile/ Vật tư | D9: Grade/ Mác vật liệu | E9: Grade/ Mác vật liệu mua | F9: Số lượng Mua | H9: Khối lượng/ Số lượng | I9: Đơn giá (vnd) | J9: Thành tiền (vnd) | K9: Thành tiền (vnd) | L9: HOÀNG HÀ
L10: Phạm vi | M10: Đơn giá (VND) | N10: Thành Tiền (Chưa có VAT)
A11: Tổng | B11: Bolt-Material / Vật tư bulong, phụ kiện | H11: N/A | I11: N/A | J11: ='Tổng hợp'!K23 -> 9.374355e+09 | K11: ='Tổng hợp'!J23+'Tổng hợp'!J22-'Vật tư bạt trần toàn'!M11 -> 21764911718 | N11: =SUM(N12:N13) -> 11840000 | P11: =J11-K11-N11 -> -1.2402397e+10
A12: I95-VPK-096 | B12: =VLOOKUP(A12,'25-VPI-I-095'!L:N,3,0) -> UBOLT_DN40_M10(4N+2W) | C12: Ubolt làm theo bản vẽ | E12: Mạ kẽm | F12: 80 | G12: T4E2P | H12: =VLOOKUP(A12,'25-VPI-I-095'!L:DG,95,0) -> 80 | I12: N/A | J12: N/A | K12: N/A | L12: V | M12: 45000 | N12: =M12*F12 -> 3600000 | O12: HOÀNG HÀ | Q12: =G12-H12 -> #VALUE!
A13: I95-VPK-099 | B13: =VLOOKUP(A13,'25-VPI-I-095'!L:N,3,0) -> LÒ SO SPRING_D3 | C13: Loò xo làm theo bản vẻ | D13: D3 | E13: Inox 304 | F13: 80 | G13: cái | H13: =VLOOKUP(A13,'25-VPI-I-095'!L:DG,95,0) -> 80 | I13: N/A | J13: N/A | K13: N/A | L13: V | M13: 103000 | N13: =M13*F13 -> 8240000 | O13: HOÀNG HÀ | Q13: =G13-H13 -> #VALUE!
B14: Xếp hạng | M14: 1
A15: Ghi chú: PTM tiến hàng mua sắm để đảm bảo tiến độ
A16: NGƯỜI ĐỀ NGHỊ/ RECOMMENDATION BY: | D16: NGƯỜI KIỂM TRA/ DEPARTMENT HEAD CHECK BY: | J16: APPROVED BY: PHÊ DUYỆT
I17: Nguyễn Quang Vinh | L17: Hoàng Ngọc Bằng | O17: Đoàn Văn Toàn

Sheet Kẹp sàn VSAB
A1: BID ANALYSIS - GIẢI TRÌNH MUA SẮM/ĐẤU THẦU
A3: Project | B3: PROJECT No/ Dự án: 25-VPI-I-095
A4: Dự án
A5: Subject | B5: Cung cấp vật tư kẹp sàn grating 26-2-2026
A6: Chủ đề
A8: No. | B8: CONTENT | C8: Phạm vi công việc | G8: Dự toán | J8: Đã mua | K8: Đơn vị cung cấp chào giá (vnđ) | N8: Đơn vị cung cấp chào giá (vnđ) | Q8: Đơn vị cung cấp chào giá (vnđ) | T8: Lựa chọn | U8: Ghi chú
A9: Item | B9: Description/ Chi tiết | C9: Profile/ Vật tư | D9: Grade/ Mác vật liệu | E9: Grade/ Mác vật liệu mua | F9: Số lượng Mua (Bộ) | G9: Khối lượng/ Số lượng | H9: Đơn giá (vnd) | I9: Thành tiền (vnd) | J9: Thành tiền (vnd) | K9: WINWIN HD JOINT STOCK COMPANY | N9: CÔNG TY TNHH CKTEC | Q9: CÔNG TY CỔ PHẦN AMECC GT
K10: Phạm vi | L10: Đơn giá (VND) | M10: Thành Tiền (Chưa có VAT) | N10: Phạm vi | O10: Đơn giá (VND) | P10: Thành Tiền (Chưa có VAT) | Q10: Phạm vi | R10: Đơn giá (VND) | S10: Thành Tiền (Chưa có VAT)
A11: Tổng | B11: Gratting-Material / Vật tư gratting | G11: N/A | H11: N/A | I11: ='[165]Tổng hợp'!K21 -> 6.7325298e+09 | J11: 3.4811383e+09 | M11: =SUM(M12:M15) -> 113400000 | P11: =SUM(P12:P15) -> 104328000 | S11: =SUM(S12:S15) -> 106596000 | U11: =I11-J11-P11 -> 3.1470635e+09
A12: I95-VTC03-001 | B12: GRATING 32X5-KHÔNG RĂNG CƯA-MUA THEO BẢN VẼ | C12: Kẹp sàn | D12: SS400-HDG | E12: SS400-HDG | F12: 4056 | G12: N/A | H12: N/A | I12: N/A | J12: N/A | K12: V | L12: 25000 | M12: =L12*F12 -> 101400000 | N12: V | O12: 23000 | P12: =O12*F12 -> 93288000 | Q12: V | R12: 23500 | S12: =R12*F12 -> 95316000 | T12: CÔNG TY TNHH CKTEC
A13: I95-VTC03-002 | B13: GRATING 44X5-KHÔNG RĂNG CƯA-MUA THEO BẢN VẼ | C13: N/A | D13: SS400-HDG | E13: SS400-HDG | F13: N/A | G13: N/A | H13: N/A | I13: N/A | J13: N/A | K13: N/A | L13: N/A | M13: N/A | N13: N/A | O13: N/A | P13: N/A | Q13: N/A | R13: N/A | S13: N/A | T13: N/A
A14: I95-VTC03-003 | B14: GRATING 32X5-CÓ RĂNG CƯA-MUA THEO BẢN VẼ | C14: Kẹp sàn | D14: SS400-HDG | E14: SS400-HDG | F14: 480 | G14: N/A | H14: N/A | I14: N/A | J14: N/A | K14: V | L14: 25000 | M14: =L14*F14 -> 12000000 | N14: V | O14: 23000 | P14: =O14*F14 -> 11040000 | Q14: V | R14: 23500 | S14: =R14*F14 -> 11280000 | T14: CÔNG TY TNHH CKTEC
A15: I95-VTC03-004 | B15: GRATING 44X5-CÓ RĂNG CƯA-MUA THEO BẢN VẼ | C15: N/A | D15: SS400-HDG | E15: SS400-HDG | F15: N/A | G15: N/A | H15: N/A | I15: N/A | J15: N/A | K15: N/A | L15: N/A | M15: N/A | N15: N/A | O15: N/A | P15: N/A | Q15: N/A | R15: N/A | S15: N/A | T15: N/A
B16: Xếp hạng | L16: 3 | O16: 1 | R16: 2
A17: Ghi chú: PTM tiến hàng mua sắm để đảm bảo tiến độ
A18: NGƯỜI ĐỀ NGHỊ/ RECOMMENDATION BY: | D18: NGƯỜI KIỂM TRA/ DEPARTMENT HEAD CHECK BY: | I18: APPROVED BY: PHÊ DUYỆT
K19: Nguyễn Quang Vinh | O19: Hoàng Ngọc Bằng | S19: Đoàn Văn Toàn

Sheet WINWIN grating
A1: BID ANALYSIS - GIẢI TRÌNH MUA SẮM/ĐẤU THẦU | Z1: WINWIN HD JOINT STOCK COMPANY
Z2: Add: 10/207 Quang Trung Street - Thanh Dong Ward - Hải Phong City Tel: 0981.862.886 / Email: Winwinhd.jsc@gmail.com / Website: Winwinhd.vn | AJ2: CÔNG TY TNHH SX TM CƠ KHÍ KHANG THỊNH
A3: Project | B3: PROJECT No/ Dự án: 25-VPI-I-095 | Z3: BẢNG BÁO GIÁ / QUOTATION | AJ3: Địa chỉ: 558 Xô Viết Nghệ Tĩnh, Phường Thạnh Mỹ Tây, TP Hồ Chí Minh, Việt Nam
A4: Dự án | Z4: Khách hàng: CÔNG TY CỔ PHẦN CÔNG NGHIỆP NẶNG IBS | AJ4: Website: www.cokhikhangthinh.com – Email: info@cokhikhangthinh.com
A5: Subject | B5: Cung cấp vật tư sàn grating 6-2-2026 | Z5: Bảng báo giá số: 29126 - IBSWWHD | AJ5: Hotline: 0902.6446.86 – Zalo: 0902.6446.86 Mr Hưởng
A6: Chủ đề | Z6: Ngày báo giá: 29.01.2026 | AJ6: BẢNG BÁO GIÁ
Z7: Lần sửa đổi / Rev.: 00
A8: No. | B8: CONTENT | C8: Phạm vi công việc | G8: Dự toán | J8: Đã mua | K8: Đơn vị cung cấp chào giá (vnđ) | N8: Đơn vị cung cấp chào giá (vnđ) | Q8: Đơn vị cung cấp chào giá (vnđ) | T8: Lựa chọn | U8: Ghi chú | AK8: Kính gửi | AL8: CÔNG TY CỔ PHẦN CÔNG NGHIỆP NẶNG IBS
A9: Item | B9: Description/ Chi tiết | C9: Profile/ Vật tư | D9: Grade/ Mác vật liệu | E9: Grade/ Mác vật liệu mua | F9: Số lượng Mua (M) | G9: Khối lượng/ Số lượng | H9: Đơn giá (vnd) | I9: Thành tiền (vnd) | J9: Thành tiền (vnd) | K9: WINWIN HD JOINT STOCK COMPANY | N9: CÔNG TY TNHH SX TM CƠ KHÍ KHANG THỊNH | Q9: CÔNG TY CỔ PHẦN AMECC GT | AK9: Người liên hệ | AL9: Mr Đức | AS9: =[166]Sheet1!$I$8 -> Ngày báo giá | AT9: =TODAY() -> 46086
K10: Phạm vi | L10: Đơn giá (VND) | M10: Thành Tiền (Chưa có VAT) | N10: Phạm vi | O10: Đơn giá (VND) | P10: Thành Tiền (Chưa có VAT) | Q10: Phạm vi | R10: Đơn giá (VND) | S10: Thành Tiền (Chưa có VAT) | Z10: Stt | AA10: Mô tả | AB10: Đơn vị | AC10: Số lượng / Quantity | AD10: Số lượng | AE10: Đơn giá (đ/kg/bộ/bậc) | AF10: Tổng giá (Vnđ) | AG10: Ghi chú | AK10: Địa chỉ | AL10: Km 6 Quốc lộ 5, Phường Hùng Vương, Quận Hồng Bàng, Thành phố Hải Phòng, Việt Nam
A11: Tổng | B11: Gratting-Material / Vật tư gratting | G11: N/A | H11: N/A | I11: ='[165]Tổng hợp'!K21 -> 6.7325298e+09 | M11: =SUM(M12:M15) -> 3.4811383e+09 | P11: =SUM(P12:P15) -> 3232898000 | S11: =SUM(S12:S15) -> 3.5335804e+09 | Z11: 1 | AA11: GRATING 32X5-KHÔNG RĂNG CƯA-MẠ KẼM NÓNG | AB11: Kg | AD11: 67640 | AE11: 37000 | AF11: =AE11*AD11 -> 2502680000
A12: I95-VTC03-001 | B12: GRATING 32X5-KHÔNG RĂNG CƯA-MUA THEO BẢN VẼ | C12: GRATING 32X5-KHÔNG RĂNG CƯA-MẠ KẼM NÓNG | D12: SS400-HDG | E12: SS400-HDG | F12: 67640.06 | G12: N/A | H12: N/A | I12: N/A | J12: N/A | K12: V | L12: 37000 | M12: =L12*F12 -> 2502682220 | N12: V | O12: Danh mục/bản vẽ | P12: 2242492000 | Q12: V | R12: 37000 | S12: =R12*F12 -> 2502682220 | U12: - Chưa có giá trị phần kẹp sàn | Z12: 2 | AA12: GRATING 44X5-KHÔNG RĂNG CƯA-MẠ KẼM NÓNG | AB12: Kg | AD12: 11801 | AE12: 37000 | AF12: =AE12*AD12 -> 436637000
A13: I95-VTC03-002 | B13: GRATING 44X5-KHÔNG RĂNG CƯA-MUA THEO BẢN VẼ | C13: GRATING 44X5-KHÔNG RĂNG CƯA-MẠ KẼM NÓNG | D13: SS400-HDG | E13: SS400-HDG | F13: 11800.88 | G13: N/A | H13: N/A | I13: N/A | J13: N/A | K13: V | L13: 37000 | M13: =L13*F13 -> 4.3663256e+08 | N13: V | O13: Danh mục/bản vẽ | P13: 414348000 | Q13: V | R13: 41000 | S13: =R13*F13 -> 4.8383608e+08 | Z13: 3 | AA13: GRATING 32X5-CÓ RĂNG CƯA-MẠ KẼM NÓNG | AB13: Kg | AD13: 11432 | AE13: 38000 | AF13: =AE13*AD13 -> 434416000 | AJ13: KÝ | AK13: SẢN PHẨM | AL13: QUY CÁCH | AM13: KÍCH THƯỚC | AP13: UNIT | AQ13: SỐ LƯỢNG | AR13: ĐƠN GIÁ | AS13: ĐƠN GIÁ | AT13: GHI CHÚ
A14: I95-VTC03-003 | B14: GRATING 32X5-CÓ RĂNG CƯA-MUA THEO BẢN VẼ | C14: GRATING 32X5-CÓ RĂNG CƯA-MẠ KẼM NÓNG | D14: SS400-HDG | E14: SS400-HDG | F14: 11432.44 | G14: N/A | H14: N/A | I14: N/A | J14: N/A | K14: V | L14: 38000 | M14: =L14*F14 -> 434432720 | N14: V | O14: Danh mục/bản vẽ | P14: 474826000 | Q14: V | R14: 38000 | S14: =R14*F14 -> 434432720 | Z14: 4 | AA14: GRATING 44X5-CÓ RĂNG CƯA-MẠ KẼM NÓNG | AB14: Kg | AD14: 2619 | AE14: 41000 | AF14: =AE14*AD14 -> 107379000 | AJ14: HIỆU | AM14: BEARING | AO14: CROSS | AS14: TRƯỚC THUẾ
A15: I95-VTC03-004 | B15: GRATING 44X5-CÓ RĂNG CƯA-MUA THEO BẢN VẼ | C15: GRATING 44X5-CÓ RĂNG CƯA-MẠ KẼM NÓNG | D15: SS400-HDG | E15: SS400-HDG | F15: 2619.2889 | G15: N/A | H15: N/A | I15: N/A | J15: N/A | K15: V | L15: 41000 | M15: =L15*F15 -> 1.0739084e+08 | N15: V | O15: Danh mục/bản vẽ | P15: 101232000 | Q15: V | R15: 43000 | S15: =R15*F15 -> 1.1262942e+08 | Z15: 5 | AA15: Kẹp sàn loại SY | AB15: Bộ | AD15: =4056+480 -> 4536 | AE15: 24000 | AK15: ITEM | AL15: SPEC. | AM15: L | AO15: W | AP15: DVT | AQ15: SL | AR15: PRICE | AS15: EX.VAT | AT15: REMARKS
B16: Xếp hạng | L16: 1 | AA16: Tổng / Total | AF16: =SUM(AF11:AF15) -> 3481112000 | AM16: mm | AO16: mm
A17: Ghi chú: PTM tiến hàng mua sắm để đảm bảo tiến độ | AA17: VAT 10% | AF17: =AF16*10% -> 348111200 | AJ17: I95-VTC03-001-U1 (LA PHẲNG)
A18: NGƯỜI ĐỀ NGHỊ/ RECOMMENDATION BY: | D18: NGƯỜI KIỂM TRA/ DEPARTMENT HEAD CHECK BY: | I18: APPROVED BY: PHÊ DUYỆT | AA18: Tổng cộng | AF18: =AF17+AF16 -> 3829223200 | AJ18: 1 | AK18: V17565-PW-GR1 | AL18: THANH LA : FB 32x5 - BƯỚC 30- THANH XOẮN 6x6 BƯỚC 100 - (MM) | AM18: 1405 | AN18: x | AO18: 1300 | AP18: Tấm | AQ18: 14 | AR18: 2995000 | AS18: 41930000 | AT18: THEO BẢN VẼ
K19: Nguyễn Quang Vinh | O19: Hoàng Ngọc Bằng | S19: Đoàn Văn Toàn | Z19: Ghi chú / Note: | AJ19: 2 | AK19: V17565-PW-GR2 | AL19: THANH LA : FB 32x5 - BƯỚC 30- THANH XOẮN 6x6 BƯỚC 100 - (MM) | AM19: 886 | AN19: x | AO19: 1234 | AP19: Tấm | AQ19: 1 | AR19: 1830000 | AS19: 1830000 | AT19: THEO BẢN VẼ
AJ20: 3 | AK20: V17565-PW-GR3 | AL20: THANH LA : FB 32x5 - BƯỚC 30- THANH XOẮN 6x6 BƯỚC 100 - (MM) | AM20: 1688 | AN20: x | AO20: 1300 | AP20: Tấm | AQ20: 14 | AR20: 3809000 | AS20: 53326000 | AT20: THEO BẢN VẼ
AJ21: 4 | AK21: V17565-PW-GR4 | AL21: THANH LA : FB 32x5 - BƯỚC 30- THANH XOẮN 6x6 BƯỚC 100 - (MM) | AM21: 1329 | AN21: x | AO21: 1118 | AP21: Tấm | AQ21: 1 | AR21: 2449000 | AS21: 2449000 | AT21: THEO BẢN VẼ
AJ22: 5 | AK22: V17565-PW-GR5 | AL22: THANH LA : FB 32x5 - BƯỚC 30- THANH XOẮN 6x6 BƯỚC 100 - (MM) | AM22: 965 | AN22: x | AO22: 1118 | AP22: Tấm | AQ22: 1 | AR22: 1802000 | AS22: 1802000 | AT22: THEO BẢN VẼ
AJ23: 6 | AK23: V17565-PW-GR6 | AL23: THANH LA : FB 32x5 - BƯỚC 30- THANH XOẮN 6x6 BƯỚC 100 - (MM) | AM23: 761 | AN23: x | AO23: 1234 | AP23: Tấm | AQ23: 1 | AR23: 1585000 | AS23: 1585000 | AT23: THEO BẢN VẼ
AJ24: 7 | AK24: V17565-PW-GR7 | AL24: THANH LA : FB 32x5 - BƯỚC 30- THANH XOẮN 6x6 BƯỚC 100 - (MM) | AM24: 1329 | AN24: x | AO24: 1063 | AP24: Tấm | AQ24: 1 | AR24: 2332000 | AS24: 2332000 | AT24: THEO BẢN VẼ
AJ25: 8 | AK25: V17565-PW-GR8 | AL25: THANH LA : FB 32x5 - BƯỚC 30- THANH XOẮN 6x6 BƯỚC 100 - (MM) | AM25: 965 | AN25: x | AO25: 1063 | AP25: Tấm | AQ25: 1 | AR25: 1716000 | AS25: 1716000 | AT25: THEO BẢN VẼ
AJ26: 9 | AK26: V17565-PW-GR9 | AL26: THANH LA : FB 32x5 - BƯỚC 30- THANH XOẮN 6x6 BƯỚC 100 - (MM) | AM26: 927 | AN26: x | AO26: 1197 | AP26: Tấm | AQ26: 1 | AR26: 1854000 | AS26: 1854000 | AT26: THEO BẢN VẼ
AJ27: 10 | AK27: V17565-PW-GR10 | AL27: THANH LA : FB 32x5 - BƯỚC 30- THANH XOẮN 6x6 BƯỚC 100 - (MM) | AM27: 1329 | AN27: x | AO27: 1197 | AP27: Tấm | AQ27: 1 | AR27: 2618000 | AS27: 2618000 | AT27: THEO BẢN VẼ
AJ28: 11 | AK28: V17565-PW-GR53 | AL28: THANH LA : FB 32x5 - BƯỚC 30- THANH XOẮN 6x6 BƯỚC 100 - (MM) | AM28: 1203 | AN28: x | AO28: 1000 | AP28: Tấm | AQ28: 5 | AR28: 1996000 | AS28: 9980000 | AT28: THEO BẢN VẼ
AJ29: 12 | AK29: V17565-PW-GR54 | AL29: THANH LA : FB 32x5 - BƯỚC 30- THANH XOẮN 6x6 BƯỚC 100 - (MM) | AM29: 1203 | AN29: x | AO29: 1000 | AP29: Tấm | AQ29: 3 | AR29: 1996000 | AS29: 5988000 | AT29: THEO BẢN VẼ
AJ30: 13 | AK30: V17565-PW-GR55 | AL30: THANH LA : FB 32x5 - BƯỚC 30- THANH XOẮN 6x6 BƯỚC 100 - (MM) | AM30: 1203 | AN30: x | AO30: 573 | AP30: Tấm | AQ30: 1 | AR30: 1166000 | AS30: 1166000 | AT30: THEO BẢN VẼ
Z31: XÁC NHẬN ĐẶT HÀNG CỦA KHÁCH HÀNG | AE31: CÔNG TY CỔ PHẦN WINWIN HD | AJ31: 14 | AK31: V17565-PW-GR56 | AL31: THANH LA : FB 32x5 - BƯỚC 30- THANH XOẮN 6x6 BƯỚC 100 - (MM) | AM31: 1458 | AN31: x | AO31: 1103 | AP31: Tấm | AQ31: 1 | AR31: 2644000 | AS31: 2644000 | AT31: THEO BẢN VẼ
AJ32: 15 | AK32: V17565-PW-GR57 | AL32: THANH LA : FB 32x5 - BƯỚC 30- THANH XOẮN 6x6 BƯỚC 100 - (MM) | AM32: 1163 | AN32: x | AO32: 1080 | AP32: Tấm | AQ32: 1 | AR32: 2083000 | AS32: 2083000 | AT32: THEO BẢN VẼ
AJ33: 16 | AK33: V17565-PW-GR58 | AL33: THANH LA : FB 32x5 - BƯỚC 30- THANH XOẮN 6x6 BƯỚC 100 - (MM) | AM33: 1163 | AN33: x | AO33: 1080 | AP33: Tấm | AQ33: 1 | AR33: 2083000 | AS33: 2083000 | AT33: THEO BẢN VẼ
AJ34: 17 | AK34: V17565-PW-GR59 | AL34: THANH LA : FB 32x5 - BƯỚC 30- THANH XOẮN 6x6 BƯỚC 100 - (MM) | AM34: 1048 | AN34: x | AO34: 1080 | AP34: Tấm | AQ34: 2 | AR34: 1885000 | AS34: 3770000 | AT34: THEO BẢN VẼ
AJ35: 18 | AK35: V17565-PW-GR60 | AL35: THANH LA : FB 32x5 - BƯỚC 30- THANH XOẮN 6x6 BƯỚC 100 - (MM) | AM35: 1458 | AN35: x | AO35: 1103 | AP35: Tấm | AQ35: 1 | AR35: 2644000 | AS35: 2644000 | AT35: THEO BẢN VẼ
AJ36: 19 | AK36: V17565-PW-GR61 | AL36: THANH LA : FB 32x5 - BƯỚC 30- THANH XOẮN 6x6 BƯỚC 100 - (MM) | AM36: 790 | AN36: x | AO36: 1002 | AP36: Tấm | AQ36: 7 | AR36: 1340000 | AS36: 9380000 | AT36: THEO BẢN VẼ
AJ37: 20 | AK37: V17565-PW-GR62 | AL37: THANH LA : FB 32x5 - BƯỚC 30- THANH XOẮN 6x6 BƯỚC 100 - (MM) | AM37: 714 | AN37: x | AO37: 1002 | AP37: Tấm | AQ37: 7 | AR37: 1218000 | AS37: 8526000 | AT37: THEO BẢN VẼ
AJ38: 21 | AK38: V17565-PW-GR63 | AL38: THANH LA : FB 32x5 - BƯỚC 30- THANH XOẮN 6x6 BƯỚC 100 - (MM) | AM38: 1559 | AN38: x | AO38: 750 | AP38: Tấm | AQ38: 2 | AR38: 1940000 | AS38: 3880000 | AT38: THEO BẢN VẼ
AJ39: 22 | AK39: V17565-PW-GR64 | AL39: THANH LA : FB 32x5 - BƯỚC 30- THANH XOẮN 6x6 BƯỚC 100 - (MM) | AM39: 1254 | AN39: x | AO39: 750 | AP39: Tấm | AQ39: 1 | AR39: 1572000 | AS39: 1572000 | AT39: THEO BẢN VẼ
AJ40: 23 | AK40: V17565-PW-GR65 | AL40: THANH LA : FB 32x5 - BƯỚC 30- THANH XOẮN 6x6 BƯỚC 100 - (MM) | AM40: 1254 | AN40: x | AO40: 750 | AP40: Tấm | AQ40: 1 | AR40: 1572000 | AS40: 1572000 | AT40: THEO BẢN VẼ
AJ41: 24 | AK41: V17565-PW-GR66 | AL41: THANH LA : FB 32x5 - BƯỚC 30- THANH XOẮN 6x6 BƯỚC 100 - (MM) | AM41: 1453 | AN41: x | AO41: 1000 | AP41: Tấm | AQ41: 13 | AR41: 2395000 | AS41: 31135000 | AT41: THEO BẢN VẼ
AJ42: 25 | AK42: V17565-PW-GR67 | AL42: THANH LA : FB 32x5 - BƯỚC 30- THANH XOẮN 6x6 BƯỚC 100 - (MM) | AM42: 1453 | AN42: x | AO42: 946 | AP42: Tấm | AQ42: 1 | AR42: 2304000 | AS42: 2304000 | AT42: THEO BẢN VẼ
AJ43: 26 | AK43: V17565-PW-GR68 | AL43: THANH LA : FB 32x5 - BƯỚC 30- THANH XOẮN 6x6 BƯỚC 100 - (MM) | AM43: 1184 | AN43: x | AO43: 1000 | AP43: Tấm | AQ43: 6 | AR43: 1966000 | AS43: 11796000 | AT43: THEO BẢN VẼ
... AJ300: 283 | AK300: V17565-PW-GR336 | AL300: THANH LA : FB 32x5 - BƯỚC 30- THANH XOẮN 6x6 BƯỚC 100 - (MM) | AM300: 1360 | AN300: x | AO300: 271 | AP300: Tấm | AQ300: 1 | AR300: 687000 | AS300: 687000 | AT300: THEO BẢN VẼ
AJ301: I95-VTC03-001-U2 (LA PHẲNG)
AJ302: 1 | AK302: V17565-PW-GR1 | AL302: THANH LA : FB 32x5 - BƯỚC 30- THANH XOẮN 6x6 BƯỚC 100 - (MM) | AM302: 1405 | AN302: x | AO302: 1300 | AP302: Tấm | AQ302: 14 | AR302: 2995000 | AS302: 41930000 | AT302: THEO BẢN VẼ
AJ303: 2 | AK303: V17565-PW-GR2 | AL303: THANH LA : FB 32x5 - BƯỚC 30- THANH XOẮN 6x6 BƯỚC 100 - (MM) | AM303: 886 | AN303: x | AO303: 1234 | AP303: Tấm | AQ303: 1 | AR303: 1830000 | AS303: 1830000 | AT303: THEO BẢN VẼ
AJ304: 3 | AK304: V17565-PW-GR3 | AL304: THANH LA : FB 32x5 - BƯỚC 30- THANH XOẮN 6x6 BƯỚC 100 - (MM) | AM304: 1688 | AN304: x | AO304: 1300 | AP304: Tấm | AQ304: 14 | AR304: 3809000 | AS304: 53326000 | AT304: THEO BẢN VẼ
AJ305: 4 | AK305: V17565-PW-GR4 | AL305: THANH LA : FB 32x5 - BƯỚC 30- THANH XOẮN 6x6 BƯỚC 100 - (MM) | AM305: 1329 | AN305: x | AO305: 1118 | AP305: Tấm | AQ305: 1 | AR305: 2449000 | AS305: 2449000 | AT305: THEO BẢN VẼ
AJ306: 5 | AK306: V17565-PW-GR5 | AL306: THANH LA : FB 32x5 - BƯỚC 30- THANH XOẮN 6x6 BƯỚC 100 - (MM) | AM306: 965 | AN306: x | AO306: 1118 | AP306: Tấm | AQ306: 1 | AR306: 1802000 | AS306: 1802000 | AT306: THEO BẢN VẼ
AJ307: 6 | AK307: V17565-PW-GR6 | AL307: THANH LA : FB 32x5 - BƯỚC 30- THANH XOẮN 6x6 BƯỚC 100 - (MM) | AM307: 761 | AN307: x | AO307: 1234 | AP307: Tấm | AQ307: 1 | AR307: 1585000 | AS307: 1585000 | AT307: THEO BẢN VẼ
AJ308: 7 | AK308: V17565-PW-GR7 | AL308: THANH LA : FB 32x5 - BƯỚC 30- THANH XOẮN 6x6 BƯỚC 100 - (MM) | AM308: 1329 | AN308: x | AO308: 1063 | AP308: Tấm | AQ308: 1 | AR308: 2332000 | AS308: 2332000 | AT308: THEO BẢN VẼ
AJ309: 8 | AK309: V17565-PW-GR8 | AL309: THANH LA : FB 32x5 - BƯỚC 30- THANH XOẮN 6x6 BƯỚC 100 - (MM) | AM309: 965 | AN309: x | AO309: 1063 | AP309: Tấm | AQ309: 1 | AR309: 1716000 | AS309: 1716000 | AT309: THEO BẢN VẼ
AJ310: 9 | AK310: V17565-PW-GR9 | AL310: THANH LA : FB 32x5 - BƯỚC 30- THANH XOẮN 6x6 BƯỚC 100 - (MM) | AM310: 927 | AN310: x | AO310: 1197 | AP310: Tấm | AQ310: 1 | AR310: 1854000 | AS310: 1854000 | AT310: THEO BẢN VẼ
AJ311: 10 | AK311: V17565-PW-GR10 | AL311: THANH LA : FB 32x5 - BƯỚC 30- THANH XOẮN 6x6 BƯỚC 100 - (MM) | AM311: 1329 | AN311: x | AO311: 1197 | AP311: Tấm | AQ311: 1 | AR311: 2618000 | AS311: 2618000 | AT311: THEO BẢN VẼ
AJ312: 11 | AK312: V17565-PW-GR53 | AL312: THANH LA : FB 32x5 - BƯỚC 30- THANH XOẮN 6x6 BƯỚC 100 - (MM) | AM312: 1203 | AN312: x | AO312: 1000 | AP312: Tấm | AQ312: 5 | AR312: 1996000 | AS312: 9980000 | AT312: THEO BẢN VẼ
AJ313: 12 | AK313: V17565-PW-GR54 | AL313: THANH LA : FB 32x5 - BƯỚC 30- THANH XOẮN 6x6 BƯỚC 100 - (MM) | AM313: 1203 | AN313: x | AO313: 1000 | AP313: Tấm | AQ313: 3 | AR313: 1996000 | AS313: 5988000 | AT313: THEO BẢN VẼ
... AJ585: 284 | AK585: KẸP SÀN GRATING | AL585: CLIP M; CLIP L; BULONG M8x60MM (MẠ KẼM NHÚNG NÓNG LY TÂM) | AM585: 30 | AN585: x | AO585: 100 | AP585: Bộ | AQ585: 4056 | AR585: 21000 | AS585: 85176000 | AT585: THEO BẢN VẼ
AJ586: I95-VTC03-002 (LA PHẲNG)
AJ587: 284 | AK587: U1-TG1 | AL587: THANH LA : FB 44x5 - BƯỚC 30- THANH XOẮN 6x6 BƯỚC 100 - (MM) | AM587: 1063 | AN587: x | AO587: 305 | AP587: Tấm | AQ587: 242 | AR587: 803000 | AS587: 194326000 | AT587: THEO BẢN VẼ
AJ588: 285 | AK588: U1-GRT31 | AL588: THANH LA : FB 44x5 - BƯỚC 30- THANH XOẮN 6x6 BƯỚC 100 - (MM) | AM588: 1063 | AN588: x | AO588: 305 | AP588: Tấm | AQ588: 8 | AR588: 803000 | AS588: 6424000 | AT588: THEO BẢN VẼ
AJ589: 286 | AK589: U1-GRT32 | AL589: THANH LA : FB 44x5 - BƯỚC 30- THANH XOẮN 6x6 BƯỚC 100 - (MM) | AM589: 1063 | AN589: x | AO589: 305 | AP589: Tấm | AQ589: 8 | AR589: 803000 | AS589: 6424000 | AT589: THEO BẢN VẼ
AJ590: 287 | AK590: U2-TG1 | AL590: THANH LA : FB 44x5 - BƯỚC 30- THANH XOẮN 6x6 BƯỚC 100 - (MM) | AM590: 1063 | AN590: x | AO590: 305 | AP590: Tấm | AQ590: 242 | AR590: 803000 | AS590: 194326000 | AT590: THEO BẢN VẼ
AJ591: 288 | AK591: U2-GRT31 | AL591: THANH LA : FB 44x5 - BƯỚC 30- THANH XOẮN 6x6 BƯỚC 100 - (MM) | AM591: 1063 | AN591: x | AO591: 305 | AP591: Tấm | AQ591: 8 | AR591: 803000 | AS591: 6424000 | AT591: THEO BẢN VẼ
AJ592: 289 | AK592: U2-GRT32 | AL592: THANH LA : FB 44x5 - BƯỚC 30- THANH XOẮN 6x6 BƯỚC 100 - (MM) | AM592: 1063 | AN592: x | AO592: 305 | AP592: Tấm | AQ592: 8 | AR592: 803000 | AS592: 6424000 | AT592: THEO BẢN VẼ
AJ593: I95-VTC03-003 (LA RĂNG CƯA)
AJ594: 290 | AK594: V17565-PW-GR11 | AL594: THANH LA : FB 32x5 - BƯỚC 30- THANH XOẮN 6x6 BƯỚC 100 - (MM) | AM594: 1347 | AN594: x | AO594: 1423 | AP594: Tấm | AQ594: 1 | AR594: 3142000 | AS594: 3142000 | AT594: THEO BẢN VẼ
AJ595: 291 | AK595: V17565-PW-GR12 | AL595: THANH LA : FB 32x5 - BƯỚC 30- THANH XOẮN 6x6 BƯỚC 100 - (MM) | AM595: 1365 | AN595: x | AO595: 1692 | AP595: Tấm | AQ595: 1 | AR595: 3773000 | AS595: 3773000 | AT595: THEO BẢN VẼ
AJ596: 292 | AK596: V17565-PW-GR13 | AL596: THANH LA : FB 32x5 - BƯỚC 30- THANH XOẮN 6x6 BƯỚC 100 - (MM) | AM596: 1368 | AN596: x | AO596: 3029 | AP596: Tấm | AQ596: 1 | AR596: 6722000 | AS596: 6722000 | AT596: THEO BẢN VẼ
AJ597: 293 | AK597: V17565-PW-GR14 | AL597: THANH LA : FB 32x5 - BƯỚC 30- THANH XOẮN 6x6 BƯỚC 100 - (MM) | AM597: 1137 | AN597: x | AO597: 2234 | AP597: Tấm | AQ597: 1 | AR597: 4163000 | AS597: 4163000 | AT597: THEO BẢN VẼ
AJ598: 294 | AK598: V17565-PW-GR15 | AL598: THANH LA : FB 32x5 - BƯỚC 30- THANH XOẮN 6x6 BƯỚC 100 - (MM) | AM598: 1137 | AN598: x | AO598: 1640 | AP598: Tấm | AQ598: 1 | AR598: 3069000 | AS598: 3069000 | AT598: THEO BẢN VẼ
AJ599: 295 | AK599: V17565-PW-GR16 | AL599: THANH LA : FB 32x5 - BƯỚC 30- THANH XOẮN 6x6 BƯỚC 100 - (MM) | AM599: 1178 | AN599: x | AO599: 1578 | AP599: Tấm | AQ599: 1 | AR599: 3057000 | AS599: 3057000 | AT599: THEO BẢN VẼ
AJ600: 296 | AK600: V17565-PW-GR17 | AL600: THANH LA : FB 32x5 - BƯỚC 30- THANH XOẮN 6x6 BƯỚC 100 - (MM) | AM600: 1178 | AN600: x | AO600: 1576 | AP600: Tấm | AQ600: 1 | AR600: 3053000 | AS600: 3053000 | AT600: THEO BẢN VẼ
AJ601: 297 | AK601: V17565-PW-GR18 | AL601: THANH LA : FB 32x5 - BƯỚC 30- THANH XOẮN 6x6 BƯỚC 100 - (MM) | AM601: 1181 | AN601: x | AO601: 1617 | AP601: Tấm | AQ601: 2 | AR601: 3139000 | AS601: 6278000 | AT601: THEO BẢN VẼ
AJ602: 298 | AK602: V17565-PW-GR19 | AL602: THANH LA : FB 32x5 - BƯỚC 30- THANH XOẮN 6x6 BƯỚC 100 - (MM) | AM602: 1178 | AN602: x | AO602: 1577 | AP602: Tấm | AQ602: 2 | AR602: 3055000 | AS602: 6110000 | AT602: THEO BẢN VẼ
AJ603: 299 | AK603: V17565-PW-GR20 | AL603: THANH LA : FB 32x5 - BƯỚC 30- THANH XOẮN 6x6 BƯỚC 100 - (MM) | AM603: 1368 | AN603: x | AO603: 3029 | AP603: Tấm | AQ603: 1 | AR603: 6722000 | AS603: 6722000 | AT603: THEO BẢN VẼ
AJ604: 300 | AK604: V17565-PW-GR21 | AL604: THANH LA : FB 32x5 - BƯỚC 30- THANH XOẮN 6x6 BƯỚC 100 - (MM) | AM604: 1137 | AN604: x | AO604: 2165 | AP604: Tấm | AQ604: 1 | AR604: 4036000 | AS604: 4036000 | AT604: THEO BẢN VẼ
AJ605: 301 | AK605: V17565-PW-GR22 | AL605: THANH LA : FB 32x5 - BƯỚC 30- THANH XOẮN 6x6 BƯỚC 100 - (MM) | AM605: 1137 | AN605: x | AO605: 1650 | AP605: Tấm | AQ605: 1 | AR605: 3087000 | AS605: 3087000 | AT605: THEO BẢN VẼ
... AJ690: 386 | AK690: KẸP SÀN GRATING | AL690: CLIP M; CLIP L; BULONG M8x60MM (MẠ KẼM NHÚNG NÓNG LY TÂM) | AM690: 30 | AN690: x | AO690: 100 | AP690: Bộ | AQ690: 480 | AR690: 21000 | AS690: 10080000 | AT690: THEO BẢN VẼ
AJ691: I95-VTC03-004 (LA RĂNG CƯA)
AJ692: 387 | AK692: U1-GRT2 | AL692: THANH LA : FB 44x5 - BƯỚC 30- THANH XOẮN 6x6 BƯỚC 100 - (MM) | AM692: 1061 | AO692: 343 | AP692: Tấm | AQ692: 36 | AR692: 894000 | AS692: 32184000 | AT692: THEO BẢN VẼ
AJ693: 388 | AK693: U1-GRT3 | AL693: THANH LA : FB 44x5 - BƯỚC 30- THANH XOẮN 6x6 BƯỚC 100 - (MM) | AM693: 1061 | AO693: 343 | AP693: Tấm | AQ693: 2 | AR693: 894000 | AS693: 1788000 | AT693: THEO BẢN VẼ
AJ694: 389 | AK694: U1-GRT4 | AL694: THANH LA : FB 44x5 - BƯỚC 30- THANH XOẮN 6x6 BƯỚC 100 - (MM) | AM694: 1061 | AO694: 35 | AP694: Tấm | AQ694: 18 | AR694: 875000 | AS694: 15750000 | AT694: THEO BẢN VẼ
AJ695: 390 | AK695: U2-GRT2 | AL695: THANH LA : FB 44x5 - BƯỚC 30- THANH XOẮN 6x6 BƯỚC 100 - (MM) | AM695: 1061 | AO695: 343 | AP695: Tấm | AQ695: 36 | AR695: 894000 | AS695: 32184000 | AT695: THEO BẢN VẼ
AJ696: 391 | AK696: U2-GRT3 | AL696: THANH LA : FB 44x5 - BƯỚC 30- THANH XOẮN 6x6 BƯỚC 100 - (MM) | AM696: 1061 | AO696: 343 | AP696: Tấm | AQ696: 2 | AR696: 894000 | AS696: 1788000 | AT696: THEO BẢN VẼ
AJ697: 392 | AK697: U2-GRT4 | AL697: THANH LA : FB 44x5 - BƯỚC 30- THANH XOẮN 6x6 BƯỚC 100 - (MM) | AM697: 1061 | AO697: 35 | AP697: Tấm | AQ697: 18 | AR697: 875000 | AS697: 15750000 | AT697: THEO BẢN VẼ
AJ698: 393 | AK698: U1-GRT29 | AL698: THANH LA : FB 44x5 - BƯỚC 30- THANH XOẮN 6x6 BƯỚC 100 - (MM) | AM698: 1061 | AO698: 343 | AP698: Tấm | AQ698: 1 | AR698: 894000 | AS698: 894000 | AT698: THEO BẢN VẼ
AJ699: 394 | AK699: U2-GRT29 | AL699: THANH LA : FB 44x5 - BƯỚC 30- THANH XOẮN 6x6 BƯỚC 100 - (MM) | AM699: 1061 | AO699: 343 | AP699: Tấm | AQ699: 1 | AR699: 894000 | AS699: 894000 | AT699: THEO BẢN VẼ
AQ700: 1
AJ701: TỔNG CỘNG TRƯỚC THUẾ | AR701: =SUM(AS18:AS700) -> 3328154000
AJ702: THUẾ VAT 10% | AR702: =AR701*10% -> 332815400
AJ703: TỔNG CỘNG SAU THUẾ | AR703: =AR701+AR702 -> 3660969400
AK704: I. Thông số kỹ thuật | AP704: II. Điều kiện thương mại
AK705: 1. Nguyên vật liệu - Thép SS400 | AP705: 1. Báo giá có hiệu lực trong vòng 03 ngày kể từ ngày phát hành.
AK706: 2. Loại hình vật tư - La phẳng, la răng cưa | AP706: 2. Đơn giá đã bao gồm chi phí vận chuyển.
AK707: 3. Chiều L - Chiều thanh chịu lực- thanh la | AP707: 3. Địa diểm giao hàng : Phường Hùng Vương, Quận Hồng Bàng, Hải Phòng
AK708: 4. Chiều W - Chiều thanh liên kết - thanh xoắn | AP708: 4. Thời gian thực hiện : 90 ngày kể từ ngày nhận tạm ứng
AK709: 5. Phương sản xuất - Hàn Mig | AP709: 5. Phương thức thanh toán: Tạm ứng 30% khi ký hợp đồng, thanh toán phần còn lại khi có thông báo giao hàng hoặc trước khi nhận hàng.
AK710: 6. Hoàn thành sản phẩm - Mạ kẽm nhúng nóng theo tiêu chuẩn ASTM A123 hoặc tương đương
AK711: 7. Dung sai kích thước +/-5mm, Dung sai độ dày la +/- 0.2 mm
...

Sheet XALACO2
A1: BID ANALYSIS - GIẢI TRÌNH MUA SẮM/ĐẤU THẦU
A3: Project | B3: PROJECT No/ Dự án: 25-VPI-I-095
A4: Dự án
A5: Subject | B5: Cung cấp vật tư chính kéo giãn của XALACO
A6: Chủ đề
A8: No. | B8: CONTENT | C8: Phạm vi công việc | I8: Dự toán | L8: Đã mua | M8: Đơn vị cung cấp chào giá phần còn lại (VNĐ) | P8: Ghi chú
A9: Item | B9: Description/ Chi tiết | C9: Profile/ Vật tư | D9: Grade/ Mác vật liệu | E9: Grade/ Mác vật liệu mua | F9: Số lượng Mua (M2) | G9: Số lượng PR (M2) | H9: Số lượng Mua (Tấm) | I9: Khối lượng/ Số lượng | J9: Đơn giá (vnd) | K9: Thành tiền (vnd) | L9: Thành tiền (vnd) | M9: XALACO
M10: Phạm vi | N10: Đơn giá trước VAT (VNĐ/TẤM) | O10: Thành Tiền
A11: Tổng | B11: Main-Material / Vật tư chính thép đen | I11: N/A | J11: N/A | K11: ='DT03 (TM)'!G6 -> 5.7151444e+10 | L11: ='Tổng hợp'!J19 -> 4.7616213e+10 | O11: =SUM(O12:O17) -> 89770000 | P11: =K11-L11-O11 -> 9.4454609e+09
A12: I95-VTC01-102 | B12: =VLOOKUP(A12,'25-VPI-I-095'!L:N,3,0) -> EXPANDED_METAL_3/4"_#16_FLATTENED | C12: Lưới kéo giãn 1.2x1219x1632 | D12: =VLOOKUP(A12,'25-VPI-I-095'!L:R,4,0) -> SS400-MẠ KẼM | E12: SS400 | F12: =H12*1.1219*1.632 -> 73.237632 | G12: =VLOOKUP(A12,'25-VPI-I-095'!L6:DF319,89,0) -> 0 | H12: 40 | I12: N/A | J12: N/A | K12: N/A | L12: N/A | M12: V | N12: 338875 | O12: =N12*H12 -> 13555000 | P12: Chọn XALACO
A13: I95-VTC01-102 | B13: =VLOOKUP(A13,'25-VPI-I-095'!L:N,3,0) -> EXPANDED_METAL_3/4"_#16_FLATTENED | C13: Lưới kéo giãn 1.2x1219x2337 | D13: =VLOOKUP(A13,'25-VPI-I-095'!L:R,4,0) -> SS400-MẠ KẼM | E13: SS400 | F13: =H13*1.1219*2.337 -> 104.87521 | H13: 40 | I13: N/A | J13: N/A | K13: N/A | L13: N/A | M13: V | N13: 485250 | O13: =N13*H13 -> 19410000 | P13: Chọn XALACO
A14: I95-VTC01-102 | B14: =VLOOKUP(A14,'25-VPI-I-095'!L:N,3,0) -> EXPANDED_METAL_3/4"_#16_FLATTENED | C14: Lưới kéo giãn 1.2x1219x2438 | D14: =VLOOKUP(A14,'25-VPI-I-095'!L:R,4,0) -> SS400-MẠ KẼM | E14: SS400 | F14: =H14*1.1219*2.438 -> 246.1673 | H14: 90 | I14: N/A | J14: N/A | K14: N/A | L14: N/A | M14: V | N14: 506250 | O14: =N14*H14 -> 45562500 | P14: Chọn XALACO
A15: I95-VTC01-102 | B15: =VLOOKUP(A15,'25-VPI-I-095'!L:N,3,0) -> EXPANDED_METAL_3/4"_#16_FLATTENED | C15: Lưới kéo giãn 1.2x1219x2750 | D15: =VLOOKUP(A15,'25-VPI-I-095'!L:R,4,0) -> SS400-MẠ KẼM | E15: SS400 | F15: =H15*1.1219*2.75 -> 12.3409 | H15: 4 | I15: N/A | J15: N/A | K15: N/A | L15: N/A | M15: V | N15: 571125 | O15: =N15*H15 -> 2284500 | P15: Chọn XALACO
A16: I95-VTC01-102 | B16: =VLOOKUP(A16,'25-VPI-I-095'!L:N,3,0) -> EXPANDED_METAL_3/4"_#16_FLATTENED | C16: Lưới kéo giãn 1.2x1219x2850 | D16: =VLOOKUP(A16,'25-VPI-I-095'!L:R,4,0) -> SS400-MẠ KẼM | E16: SS400 | F16: =H16*1.1219*2.85 -> 6.39483 | H16: 2 | I16: N/A | J16: N/A | K16: N/A | L16: N/A | M16: V | N16: 591750 | O16: =N16*H16 -> 1183500 | P16: Chọn XALACO
A17: I95-VTC01-102 | B17: =VLOOKUP(A17,'25-VPI-I-095'!L:N,3,0) -> EXPANDED_METAL_3/4"_#16_FLATTENED | C17: Lưới kéo giãn 1.2x1219x3120 | D17: =VLOOKUP(A17,'25-VPI-I-095'!L:R,4,0) -> SS400-MẠ KẼM | E17: SS400 | F17: =H17*1.1219*3.12 -> 42.003936 | H17: 12 | I17: N/A | J17: N/A | K17: N/A | L17: N/A | M17: V | N17: 647875 | O17: =N17*H17 -> 7774500 | P17: Chọn XALACO
B18: Xếp hạng | N18: 1
A19: Ghi chú: Tiếp tục công tác mua sắm để đảm báo tiến độ
A20: NGƯỜI ĐỀ NGHỊ/ RECOMMENDATION BY: | D20: NGƯỜI KIỂM TRA/ DEPARTMENT HEAD CHECK BY: | K20: APPROVED BY: PHÊ DUYỆT
K21: Nguyễn Quang Vinh | M21: Hoàng Ngọc Bằng | O21: Đoàn Văn Toàn

Sheet Đạt phát 095 24-2 
A1: BID ANALYSIS - GIẢI TRÌNH MUA SẮM/ĐẤU THẦU
A3: Project | B3: PROJECT No/ Dự án: 25-VPI-I-095
A4: Dự án
A5: Subject | B5: Cung cấp vật tư chính thép hình tấm đạt phát 24-2-2026
A6: Chủ đề
A8: No. | B8: CONTENT | C8: Phạm vi công việc | G8: Dự toán | J8: Đã mua | K8: Đơn vị cung cấp chào giá phần còn lại (VNĐ) | N8: Đơn vị cung cấp chào giá phần còn lại (VNĐ) | Q8: Đơn vị cung cấp chào giá phần còn lại (VNĐ) | T8: Ghi chú
A9: Item | B9: Description/ Chi tiết | C9: Profile/ Vật tư | D9: Grade/ Mác vật liệu | E9: Số lượng Mua (M) | F9: Số lượng PR (M) | G9: Khối lượng/ Số lượng | H9: Đơn giá (vnd) | I9: Thành tiền (vnd) | J9: Thành tiền (vnd) | K9: NGỌC HIẾU | N9: Hùng Nguyên | Q9: ĐẠT PHÁT
K10: Phạm vi | L10: Đơn giá trước VAT (VNĐ/KG) | M10: Thành Tiền | N10: Phạm vi | O10: Đơn giá trước VAT (VNĐ/KG) | P10: Thành Tiền | Q10: Phạm vi | R10: Đơn giá trước VAT (VNĐ/KG) | S10: Thành Tiền
A11: Tổng | B11: Main-Material / Vật tư chính thép đen | G11: N/A | H11: N/A | I11: ='DT03 (TM)'!G6 -> 5.7151444e+10 | J11: ='Tổng hợp'!J19+'Tổng hợp'!J24+'Ngọc hiếu 095 24-2'!M11 -> 5.1739565e+10 | S11: =SUM(S12:S15) -> 2.4006797e+08 | T11: =I11-J11-P11-M11-S11 -> 5.1718113e+09
A12: I95-VTC01-004 | B12: =VLOOKUP(A12,'25-VPI-I-095'!L:N,3,0) -> PL25x2000x12000 | C12: Thép tấm 25x2000x12000 | D12: Q355B | E12: 48 | F12: =VLOOKUP(A12,'25-VPI-I-095'!L:DF,97,0) -> 48 | G12: N/A | H12: N/A | I12: N/A | J12: N/A | K12: X | L12: #N/A | M12: N//A | N12: X | O12: 14818.18 | P12: N//A | Q12: X | R12: 14636.364 | S12: 1.3787455e+08 | T12: Chọn ĐẠT PHÁT
A13: Tổng | B13: Packing-Material / Vật tư đóng kiện | G13: N/A | H13: N/A | J13: ='Tổng hợp'!J26 -> 0 | T13: =I13-J13-P13-M13 -> 0
A14: I95-VDK-014 | B14: =VLOOKUP(A14,'25-VPI-I-095'!L:N,3,0) -> PL10X2000X12000 | C14: Thép tấm 10x2000x6000 | D14: SS400 | E14: 48 | F14: =VLOOKUP(A14,'25-VPI-I-095'!L:DF,97,0) -> 55.80349 | G14: N/A | H14: N/A | I14: N/A | J14: N/A | K14: X | L14: #N/A | M14: N//A | N14: V | O14: 13363.64 | P14: N//A | Q14: X | R14: 13363.636 | S14: 50354182 | T14: Chọn ĐẠT PHÁT
A15: I95-VDK-010 | B15: =VLOOKUP(A15,'25-VPI-I-095'!L:N,3,0) -> H300X150X6.5X9-12000L | C15: Thép H300x150x6.5x9x12000 | D15: SS400 | E15: =7*12 -> 84 | F15: =VLOOKUP(A15,'25-VPI-I-095'!L:DF,97,0) -> 81.29712 | G15: N/A | H15: N/A | I15: N/A | J15: N/A | K15: V | L15: =19000/1.1 -> 17272.727 | M15: N//A | N15: X | O15: #N/A | P15: N//A | Q15: X | R15: 16818.182 | S15: 51839242 | T15: Chọn ĐẠT PHÁT
B16: Xếp hạng | L16: 1 | O16: 2 | R16: 3
A17: Ghi chú: Tiếp tục công tác mua sắm để đảm báo tiến độ
A18: NGƯỜI ĐỀ NGHỊ/ RECOMMENDATION BY: | D18: NGƯỜI KIỂM TRA/ DEPARTMENT HEAD CHECK BY: | M18: APPROVED BY: PHÊ DUYỆT
M19: Nguyễn Quang Vinh | P19: Hoàng Ngọc Bằng | S19: Đoàn Văn Toàn

Sheet Ngọc hiếu 095 24-2
A1: BID ANALYSIS - GIẢI TRÌNH MUA SẮM/ĐẤU THẦU
A3: Project | B3: PROJECT No/ Dự án: 25-VPI-I-095
A4: Dự án
A5: Subject | B5: Cung cấp vật tư chính thép hình Ngọc Hiếu 24-2-2026
A6: Chủ đề
A8: No. | B8: CONTENT | C8: Phạm vi công việc | G8: Dự toán | J8: Đã mua | K8: Đơn vị cung cấp chào giá phần còn lại (VNĐ) | N8: Đơn vị cung cấp chào giá phần còn lại (VNĐ) | Q8: Đơn vị cung cấp chào giá phần còn lại (VNĐ) | T8: Ghi chú
A9: Item | B9: Description/ Chi tiết | C9: Profile/ Vật tư | D9: Grade/ Mác vật liệu | E9: Số lượng Mua (M) | F9: Số lượng PR (M) | G9: Khối lượng/ Số lượng | H9: Đơn giá (vnd) | I9: Thành tiền (vnd) | J9: Thành tiền (vnd) | K9: NGỌC HIẾU | N9: Hùng Nguyên | Q9: APEC
K10: Phạm vi | L10: Đơn giá trước VAT (VNĐ/KG) | M10: Thành Tiền | N10: Phạm vi | O10: Đơn giá trước VAT (VNĐ/KG) | P10: Thành Tiền | Q10: Phạm vi | R10: Đơn giá trước VAT (VNĐ/KG) | S10: Thành Tiền
A11: Tổng | B11: Main-Material / Vật tư chính thép đen | G11: N/A | H11: N/A | I11: ='DT03 (TM)'!G6 -> 5.7151444e+10 | J11: ='Tổng hợp'!J19+'Tổng hợp'!J24-M11 -> 4.9967481e+10 | M11: =SUM(M12:M24) -> 886042100 | T11: =I11-J11-P11-M11 -> 6.2979213e+09
A12: I95-VTC01-114 | B12: =VLOOKUP(A12,'25-VPI-I-095'!L:N,3,0) -> L65X65X6-12000L | C12: Thép V65*65*6*12000 | D12: =VLOOKUP(A12,'25-VPI-I-095'!L:R,4,0) -> SS400 | E12: 24 | F12: =VLOOKUP(A12,'25-VPI-I-095'!L:DF,97,0) -> 0 | G12: N/A | H12: N/A | I12: N/A | J12: N/A | K12: V | L12: 14181.82 | M12: 2013818 | N12: X | O12: #N/A | P12: N//A | Q12: X | R12: #N/A | S12: N//A | T12: Chọn Ngọc Hiếu
A13: Tổng | B13: Packing-Material / Vật tư đóng kiện | G13: N/A | H13: N/A | J13: ='Tổng hợp'!J26 -> 0 | T13: =I13-J13-P13-M13 -> 0
A14: I95-VDK-004 | B14: =VLOOKUP(A14,'25-VPI-I-095'!L:N,3,0) -> C100X50X5X7.5-12000L | C14: Thép U100*48*5,3**12000 TQ | D14: =VLOOKUP(A14,'25-VPI-I-095'!L:R,4,0) -> SS400 | E14: 1272 | F14: =VLOOKUP(A14,'25-VPI-I-095'!L:DF,97,0) -> 6.76076 | G14: N/A | H14: N/A | I14: N/A | J14: N/A | K14: V | L14: 14000 | M14: 178080000 | N14: V | O14: 17363.64 | P14: N//A | Q14: X | R14: #N/A | S14: N//A | T14: Chọn Ngọc Hiếu
A15: I95-VDK-005 | B15: =VLOOKUP(A15,'25-VPI-I-095'!L:N,3,0) -> H100X100X6X8-12000L | C15: Thép H100*100*6*8*12000 | D15: =VLOOKUP(A15,'25-VPI-I-095'!L:R,4,0) -> SS400 | E15: 108 | F15: =E15/12 ( 3 cây) | G15: N/A | H15: N/A | I15: N/A | J15: N/A | K15: V | L15: 16909.09 | M15: 30859089 | N15: V | O15: 17500 | P15: N//A | Q15: X | R15: #N/A | S15: N//A | T15: Chọn Ngọc Hiếu
A16: I95-VDK-006 | B16: =VLOOKUP(A16,'25-VPI-I-095'!L:N,3,0) -> H125X125X6.5X9-12000L | C16: Thép H125*125*6,5*9*12000 | D16: =VLOOKUP(A16,'25-VPI-I-095'!L:R,4,0) -> SS400 | E16: 300 | F16: =E16/12 -> 25 | G16: N/A | H16: N/A | I16: N/A | J16: N/A | K16: V | L16: 16909.09 | M16: 119716357 | N16: V | O16: 17500 | P16: N//A | Q16: X | R16: #N/A | S16: N//A | T16: Chọn Ngọc Hiếu
A17: I95-VDK-007 | B17: =VLOOKUP(A17,'25-VPI-I-095'!L:N,3,0) -> H150X150X7X10-12000L | C17: Thép H150*150*7*10*12000 | D17: =VLOOKUP(A17,'25-VPI-I-095'!L:R,4,0) -> SS400 | E17: 96 | F17: =E17/12 -> 8 | G17: N/A | H17: N/A | I17: N/A | J17: N/A | K17: V | L17: 16545.45 | M17: 49404714 | N17: V | O17: 17500 | P17: N//A | Q17: X | R17: #N/A | S17: N//A | T17: Chọn Ngọc Hiếu
A18: I95-VDK-008 | B18: =VLOOKUP(A18,'25-VPI-I-095'!L:N,3,0) -> H150X75X5X7-12000L | C18: Thép I150*75*5*7*12000 | D18: =VLOOKUP(A18,'25-VPI-I-095'!L:R,4,0) -> SS400 | E18: 144 | F18: =E18/12 -> 12 | G18: N/A | H18: N/A | I18: N/A | J18: N/A | K18: V | L18: 17454.55 | M18: 35188373 | N18: X | O18: #N/A | P18: N//A | Q18: X | R18: #N/A | S18: N//A | T18: Chọn Ngọc Hiếu
A19: I95-VDK-009 | B19: =VLOOKUP(A19,'25-VPI-I-095'!L:N,3,0) -> H200X100X5.5X8-12000L | C19: Thép I200*100*5,5*8*12000 | D19: =VLOOKUP(A19,'25-VPI-I-095'!L:R,4,0) -> SS400 | E19: 252 | F19: =E19/12 -> 21 | G19: N/A | H19: N/A | I19: N/A | J19: N/A | K19: V | L19: 17272.73 | M19: 90975469 | N19: V | O19: 17363.64 | P19: N//A | Q19: X | R19: #N/A | S19: N//A | T19: Chọn Ngọc Hiếu
A20: I95-VDK-032 | B20: =VLOOKUP(A20,'25-VPI-I-095'!L:N,3,0) -> C125X65X6X8-12000L | C20: Thép U125*65*6*8*12000 | D20: =VLOOKUP(A20,'25-VPI-I-095'!L:R,4,0) -> SS400 | E20: 60 | F20: =VLOOKUP(A20,'25-VPI-I-095'!L:DF,97,0) -> -4.812 | G20: N/A | H20: N/A | I20: N/A | J20: N/A | K20: V | L20: 17090.91 | M20: 13741092 | N20: X | O20: #N/A | P20: N//A | Q20: X | R20: #N/A | S20: N//A | T20: Chọn Ngọc Hiếu
A21: I95-VDK-033 | B21: =VLOOKUP(A21,'25-VPI-I-095'!L:N,3,0) -> C75X40X5X7-12000L | C21: Thép U75*40*5*7*12000 | D21: =VLOOKUP(A21,'25-VPI-I-095'!L:R,4,0) -> SS400 | E21: 1368 | F21: =VLOOKUP(A21,'25-VPI-I-095'!L:DF,97,0) -> 2.8044 | G21: N/A | H21: N/A | I21: N/A | J21: N/A | K21: V | L21: 17272.73 | M21: 163520935 | N21: X | O21: #N/A | P21: N//A | Q21: X | R21: #N/A | S21: N//A | T21: Chọn Ngọc Hiếu
A22: I95-VDK-034 | B22: =VLOOKUP(A22,'25-VPI-I-095'!L:N,3,0) -> H100X50X5X7-12000L | C22: Thép I100*55*4,5*6000 | D22: =VLOOKUP(A22,'25-VPI-I-095'!L:R,4,0) -> SS400 | E22: =228/2 -> 114 | F22: =E22/6 -> 19 | G22: N/A | H22: N/A | I22: N/A | J22: N/A | K22: V | L22: 15636.36 | M22: 16042905 | N22: V | O22: 15454.55 | P22: N//A | Q22: X | R22: #N/A | S22: N//A | T22: Chọn Ngọc Hiếu
A23: I95-VDK-035 | B23: =VLOOKUP(A23,'25-VPI-I-095'!L:N,3,0) -> H194X150X6X9-12000L | C23: Thép I194*150*6*9*12000 | D23: =VLOOKUP(A23,'25-VPI-I-095'!L:R,4,0) -> SS400 | E23: 288 | F23: =VLOOKUP(A23,'25-VPI-I-095'!L:DF,97,0) -> -1.3584 | G23: N/A | H23: N/A | I23: N/A | J23: N/A | K23: V | L23: 16818.18 | M23: 144821348 | N23: V | O23: 17363.64 | P23: N//A | Q23: X | R23: #N/A | S23: N//A | T23: Chọn Ngọc Hiếu
A24: I95-VDK-036 | B24: =VLOOKUP(A24,'25-VPI-I-095'!L:N,3,0) -> L50X50X6-6000L | C24: Thép V50*50*6*6000 | D24: =VLOOKUP(A24,'25-VPI-I-095'!L:R,4,0) -> SS400 | E24: =1344/2 -> 672 | F24: =VLOOKUP(A24,'25-VPI-I-095'!L:DF,97,0) -> -2.9274 | G24: N/A | H24: N/A | I24: N/A | J24: N/A | K24: V | L24: 14000 | M24: 41678000 | N24: X | O24: 14136.36 | P24: N//A | Q24: X | R24: #N/A | S24: N//A | T24: Chọn Ngọc Hiếu
B25: Xếp hạng | L25: 1 | O25: 2 | R25: 3
A26: Ghi chú: Tiếp tục công tác mua sắm để đảm báo tiến độ
A27: NGƯỜI ĐỀ NGHỊ/ RECOMMENDATION BY: | E27: NGƯỜI KIỂM TRA/ DEPARTMENT HEAD CHECK BY: | M27: APPROVED BY: PHÊ DUYỆT
M28: Nguyễn Quang Vinh | P28: Hoàng Ngọc Bằng | S28: Đoàn Văn Toàn

Sheet Đại phát 31-1
A1: BID ANALYSIS - GIẢI TRÌNH MUA SẮM/ĐẤU THẦU
A3: Project | B3: PROJECT No/ Dự án: 25-VPI-I-095
A4: Dự án
A5: Subject | B5: Cung cấp vật tư chính thép đen ĐẠT PHÁT 31-1-2026
A6: Chủ đề
A8: No. | B8: CONTENT | C8: Phạm vi công việc | H8: Dự toán | K8: Đã mua | L8: Đơn vị cung cấp chào giá phần còn lại (VNĐ) | O8: Đơn vị cung cấp chào giá phần còn lại (VNĐ) | R8: Ghi chú
A9: Item | B9: Description/ Chi tiết | C9: Profile/ Vật tư | D9: Grade/ Mác vật liệu | E9: Grade/ Mác vật liệu mua | F9: Số lượng Mua (M) | G9: Số lượng PR (M) | H9: Khối lượng/ Số lượng | I9: Đơn giá (vnd) | J9: Thành tiền (vnd) | K9: Thành tiền (vnd) | L9: CÔNG TY TNHH SX và TM KIM KHÍ ĐẠT PHÁT | O9: Hùng Nguyên/ APEC
L10: Phạm vi | M10: Đơn giá trước VAT (VNĐ/KG) | N10: Thành Tiền | O10: Phạm vi | P10: Đơn giá trước VAT (VNĐ/KG) | Q10: Thành Tiền
A11: Tổng | B11: Main-Material / Vật tư chính thép đen | H11: N/A | I11: N/A | J11: ='DT03 (TM)'!G6 -> 5.7151444e+10 | K11: ='Tổng hợp'!J19+'Tổng hợp'!J24 -> 5.0853523e+10 | N11: =N12 -> 60288000 | R11: =J11-K11-Q11-N11 -> 6.2376333e+09
A12: I95-VTC01-023 | B12: PL20X2000X12000 | C12: Thép tấm Q355B 20x2000x12000 | D12: ASTM A75 GrB | E12: Q355B | F12: 24 | G12: 19.490933 | H12: N/A | I12: N/A | J12: N/A | K12: N/A | L12: V | M12: =16000/1.1 -> 14545.455 | N12: 60288000 | O12: X | P12: N/A | Q12: N/A | R12: Chọn ĐẠT PHÁT
B13: Xếp hạng | M13: 1 | P13: 2
A14: Ghi chú: Tiếp tục công tác mua sắm để đảm báo tiến độ
A15: NGƯỜI ĐỀ NGHỊ/ RECOMMENDATION BY: | D15: NGƯỜI KIỂM TRA/ DEPARTMENT HEAD CHECK BY: | J15: APPROVED BY: PHÊ DUYỆT
J16: Nguyễn Quang Vinh | M16: Hoàng Ngọc Bằng | P16: Đoàn Văn Toàn

Sheet Hùng nguyên 29-1
A1: BID ANALYSIS - GIẢI TRÌNH MUA SẮM/ĐẤU THẦU
A3: Project | B3: PROJECT No/ Dự án: 25-VPI-I-095
A4: Dự án
A5: Subject | B5: Cung cấp vật tư chính thép đen Hùng Nguyên 29-1-2026
A6: Chủ đề
A8: No. | B8: CONTENT | C8: Phạm vi công việc | H8: Dự toán | K8: Đã mua | L8: Đơn vị cung cấp chào giá phần còn lại (VNĐ) | O8: Đơn vị cung cấp chào giá phần còn lại (VNĐ) | R8: Ghi chú
A9: Item | B9: Description/ Chi tiết | C9: Profile/ Vật tư | D9: Grade/ Mác vật liệu | E9: Grade/ Mác vật liệu mua | F9: Số lượng Mua (M) | G9: Số lượng PR (M) | H9: Khối lượng/ Số lượng | I9: Đơn giá (vnd) | J9: Thành tiền (vnd) | K9: Thành tiền (vnd) | L9: NGỌC HIẾU | O9: Hùng Nguyên
L10: Phạm vi | M10: Đơn giá trước VAT (VNĐ/KG) | N10: Thành Tiền | O10: Phạm vi | P10: Đơn giá trước VAT (VNĐ/KG) | Q10: Thành Tiền
A11: Tổng | B11: Main-Material / Vật tư chính thép đen | H11: N/A | I11: N/A | J11: ='DT03 (TM)'!G6 -> 5.7151444e+10 | K11: ='Tổng hợp'!J19+'Tổng hợp'!J24-Q11 -> 5.0689355e+10 | Q11: =SUM(Q12:Q13) -> 1.6416721e+08 | R11: =J11-K11-Q11-N11 -> 6.2979213e+09
A12: I95-VTC01-023 | B12: H200X200X8X12-12000L | C12: H200X200X8X12-12000L | D12: SS400 | E12: SS400 | F12: =7*12 -> 84 | G12: 0 | H12: N/A | I12: N/A | J12: N/A | K12: N/A | L12: X | M12: =19400/1.1 -> 17636.364 | N12: #N/A | O12: V | P12: =19200/1.1 -> 17454.545 | Q12: 73162492 | R12: Chọn Hùng Nguyên
A13: I95-VTC01-084 | B13: H194X150X6X9-12000L | C13: H194X150X6X9-12000L | D13: =VLOOKUP(A13,'25-VPI-I-095'!L:R,4,0) -> SS400 | E13: SS400 | F13: =15*12 -> 180 | G13: 0 | H13: N/A | I13: N/A | J13: N/A | K13: N/A | L13: V | M13: =18600/1.1 -> 16909.091 | N13: #N/A | O13: V | P13: =18600/1.1 -> 16909.091 | Q13: 91004722
B14: Xếp hạng | M14: 2 | P14: 1
A15: Ghi chú: Tiếp tục công tác mua sắm để đảm báo tiến độ
A16: NGƯỜI ĐỀ NGHỊ/ RECOMMENDATION BY: | D16: NGƯỜI KIỂM TRA/ DEPARTMENT HEAD CHECK BY: | J16: APPROVED BY: PHÊ DUYỆT
J17: Nguyễn Quang Vinh | M17: Hoàng Ngọc Bằng | P17: Đoàn Văn Toàn

Sheet Hùng nguyên 26-1
A1: BID ANALYSIS - GIẢI TRÌNH MUA SẮM/ĐẤU THẦU
A3: Project | B3: PROJECT No/ Dự án: 25-VPI-I-095
A4: Dự án
A5: Subject | B5: Cung cấp vật tư chính thép đen Hùng Nguyên 26-1-2026
A6: Chủ đề
A8: No. | B8: CONTENT | C8: Phạm vi công việc | H8: Dự toán | K8: Đã mua | L8: Đơn vị cung cấp chào giá phần còn lại (VNĐ) | O8: Đơn vị cung cấp chào giá phần còn lại (VNĐ) | R8: Đơn vị cung cấp chào giá phần còn lại (VNĐ) | U8: Ghi chú
A9: Item | B9: Description/ Chi tiết | C9: Profile/ Vật tư | D9: Grade/ Mác vật liệu | E9: Grade/ Mác vật liệu mua | F9: Số lượng Mua (M) | G9: Số lượng PR (M) | H9: Khối lượng/ Số lượng | I9: Đơn giá (vnd) | J9: Thành tiền (vnd) | K9: Thành tiền (vnd) | L9: NGỌC HIẾU | O9: Hùng Nguyên | R9: APEC
L10: Phạm vi | M10: Đơn giá trước VAT (VNĐ/KG) | N10: Thành Tiền | O10: Phạm vi | P10: Đơn giá trước VAT (VNĐ/KG) | Q10: Thành Tiền | R10: Phạm vi | S10: Đơn giá trước VAT (VNĐ/KG) | T10: Thành Tiền
A11: Tổng | B11: Main-Material / Vật tư chính thép đen | H11: N/A | I11: N/A | J11: ='DT03 (TM)'!G6 -> 5.7151444e+10 | K11: ='Tổng hợp'!J19+'Tổng hợp'!J24 -> 5.0853523e+10 | Q11: =SUM(Q12:Q13) -> 185676739 | U11: =J11-K11-Q11-N11 -> 6.1122446e+09
A12: I95-VTC01-001 I95-VDK-014 | B12: PL10x2000X12000 | C12: Thép tấm 10x2000x12000 | D12: SS400 | E12: SS400 | F12: 120 | G12: 118 | H12: N/A | I12: N/A | J12: N/A | K12: N/A | L12: X | M12: 13636.36 | N12: #N/A | O12: V | P12: 13318.18 | Q12: 125457256 | R12: X | S12: =VLOOKUP(C12,'[164]DA 95'!$B$20:$N$31,13,0) -> #N/A | T12: =VLOOKUP(D12,'[164]DA 95'!$B$20:$N$31,13,0) -> #N/A | U12: Chọn Hùng Nguyên
A13: I95-VDK-017 | B13: PL6X2000X12000 | C13: Thép tấm 6x2000x12000 | D13: =VLOOKUP(A13,'25-VPI-I-095'!L:R,4,0) -> SS400 | E13: SS400 | F13: 96 | G13: 100.29197 | H13: N/A | I13: N/A | J13: N/A | K13: N/A | L13: V | M13: 13636.36 | N13: #N/A | O13: V | P13: 13318.18 | Q13: 60219483 | R13: V | S13: =15000/1.1 -> 13636.364 | T13: =VLOOKUP(D13,'[164]DA 95'!$B$20:$N$31,13,0) -> #N/A | U13: Chọn Hùng Nguyên
B14: Xếp hạng | M14: 2 | P14: 1 | S14: 3
A15: Ghi chú: Tiếp tục công tác mua sắm để đảm báo tiến độ
A16: NGƯỜI ĐỀ NGHỊ/ RECOMMENDATION BY: | F16: NGƯỜI KIỂM TRA/ DEPARTMENT HEAD CHECK BY: | N16: APPROVED BY: PHÊ DUYỆT
N17: Nguyễn Quang Vinh | Q17: Hoàng Ngọc Bằng | T17: Đoàn Văn Toàn

Sheet Vật tư bạt trần toàn
A1: BID ANALYSIS - GIẢI TRÌNH MUA SẮM/ĐẤU THẦU
A3: Project | B3: PROJECT No/ Dự án: 25-VPI-I-095
A4: Dự án
A5: Subject | B5: Cung cấp vật tư bạt đóng kiện Trần Toàn 26-1-2026
A6: Chủ đề
A8: No. | B8: CONTENT | C8: Phạm vi công việc | G8: Dự toán | J8: Đã mua | K8: Đơn vị cung cấp chào giá (vnđ) | N8: Lựa chọn | O8: Ghi chú
A9: Item | B9: Description/ Chi tiết | C9: Profile/ Vật tư | D9: Grade/ Mác vật liệu | E9: Đơn vị | F9: Số lượng Mua (M2) | G9: Khối lượng/ Số lượng | H9: Đơn giá (vnd) | I9: Thành tiền (vnd) | J9: Thành tiền (vnd) | K9: Trần Toàn
K10: Phạm vi | L10: Đơn giá (VND) | M10: Thành Tiền (Chưa có VAT)
A11: Tổng | B11: Packing-Material / Vật tư đóng kiện | G11: N/A | H11: N/A | M11: =SUM(M12:M104) -> 559330930 | O11: =I11-J11-M11 -> -559330930
A12: I95-VDK-027 | B12: I95-BAT-BC10 HÌNH CHỮ NHẬT12346 X 3761 = 2 Tấm | C12: Bạt I95 - BC10 ( 12346 X 3761 ) x 2 tấm | D12: bạt da 2 lớp chống nước, khuyên cách nhau 500-mua theo bản vẽ | E12: m2 | F12: 92.87 | G12: N/A | H12: N/A | I12: N/A | J12: N/A | K12: V | L12: 50500 | M12: =L12*F12 -> 4689935 | N12: Trần Toàn | O12: Chưa có trong dự toán
A13: I95-VDK-027 | B13: I95-BAT-SC10A HÌNH CHỮ NHẬT26691 X 3761 = 2 Tấm | C13: Bạt I95 - SC10A ( 26691 x 3761 ) x 2 tấm | D13: bạt da 2 lớp chống nước, khuyên cách nhau 500-mua theo bản vẽ | E13: m2 | F13: 200.77 | G13: N/A | H13: N/A | I13: N/A | J13: N/A | K13: V | L13: 50500 | M13: =L13*F13 -> 10138885 | N13: Trần Toàn | O13: Chưa có trong dự toán
A14: I95-VDK-027 | B14: I95-BAT-SC10C HÌNH CHỮ NHẬT26691 X 3761 = 2 Tấm | C14: Bạt I95 - SC10C ( 26691 x 3761 ) x 2 tấm | D14: bạt da 2 lớp chống nước, khuyên cách nhau 500-mua theo bản vẽ | E14: m2 | F14: 200.77 | G14: N/A | H14: N/A | I14: N/A | J14: N/A | K14: V | L14: 50500 | M14: =L14*F14 -> 10138885 | N14: Trần Toàn | O14: Chưa có trong dự toán
A15: I95-VDK-027 | B15: I95-BAT-BC20 HÌNH CHỮ NHẬT13338 X 4994 = 2 Tấm | C15: Bạt I95 - BC20 ( 13338 X 4994 ) x 2 tấm | D15: bạt da 2 lớp chống nước, khuyên cách nhau 500-mua theo bản vẽ | E15: m2 | F15: 133.22 | G15: N/A | H15: N/A | I15: N/A | J15: N/A | K15: V | L15: 50500 | M15: =L15*F15 -> 6727610 | N15: Trần Toàn | O15: Chưa có trong dự toán
A16: I95-VDK-027 | B16: I95-BAT-SC20A HÌNH CHỮ NHẬT30362 X 5038 = 2 Tấm | C16: Bạt I95 - SC20A ( 30362 x 5038 ) x 2 tấm | D16: bạt da 2 lớp chống nước, khuyên cách nhau 500-mua theo bản vẽ | E16: m2 | F16: 305.93 | G16: N/A | H16: N/A | I16: N/A | J16: N/A | K16: V | L16: 50500 | M16: =L16*F16 -> 15449465 | N16: Trần Toàn | O16: Chưa có trong dự toán
A17: I95-VDK-027 | B17: I95-BAT-SC20C HÌNH CHỮ NHẬT30362 X 5038 = 2 Tấm | C17: Bạt I95 - SC20C ( 30362 x 5038 ) x 2 tấm | D17: bạt da 2 lớp chống nước, khuyên cách nhau 500-mua theo bản vẽ | E17: m2 | F17: 305.93 | G17: N/A | H17: N/A | I17: N/A | J17: N/A | K17: V | L17: 50500 | M17: =L17*F17 -> 15449465 | N17: Trần Toàn | O17: Chưa có trong dự toán
A18: I95-VDK-027 | B18: I95-BAT-BC301 HÌNH CHỮ NHẬT12003 X 4072 = 2 Tấm | C18: Bạt I95 - BC301 ( 12003 x 4072 ) x 2 tấm | D18: bạt da 2 lớp chống nước, khuyên cách nhau 500-mua theo bản vẽ | E18: m2 | F18: 97.75 | G18: N/A | H18: N/A | I18: N/A | J18: N/A | K18: V | L18: 50500 | M18: =L18*F18 -> 4936375 | N18: Trần Toàn | O18: Chưa có trong dự toán
A19: I95-VDK-027 | B19: I95-BAT-SC30A1 HÌNH CHỮ NHẬT29384 X 3919 = 2 Tấm | C19: Bạt I95 - SC30A1 ( 29384 x 3919 ) x 2 tấm | D19: bạt da 2 lớp chống nước, khuyên cách nhau 500-mua theo bản vẽ | E19: m2 | F19: 230.31 | G19: N/A | H19: N/A | I19: N/A | J19: N/A | K19: V | L19: 50500 | M19: =L19*F19 -> 11630655 | N19: Trần Toàn | O19: Chưa có trong dự toán
A20: I95-VDK-027 | B20: I95-BAT-SC30C1 HÌNH CHỮ NHẬT29384 X 3919 = 2 Tấm | C20: Bạt I95 - SC30C1 ( 29384 x 3919 ) x 2 tấm | D20: bạt da 2 lớp chống nước, khuyên cách nhau 500-mua theo bản vẽ | E20: m2 | F20: 230.31 | G20: N/A | H20: N/A | I20: N/A | J20: N/A | K20: V | L20: 50500 | M20: =L20*F20 -> 11630655 | N20: Trần Toàn | O20: Chưa có trong dự toán
A21: I95-VDK-027 | B21: I95-BAT-BC401 HÌNH CHỮ NHẬT11902 X 4126 = 2 Tấm | C21: Bạt I95 -BC401 ( 11902 x 4126 ) x 2 tấm | D21: bạt da 2 lớp chống nước, khuyên cách nhau 500-mua theo bản vẽ | E21: m2 | F21: 98.22 | G21: N/A | H21: N/A | I21: N/A | J21: N/A | K21: V | L21: 50500 | M21: =L21*F21 -> 4960110 | N21: Trần Toàn | O21: Chưa có trong dự toán
A22: I95-VDK-027 | B22: I95-BAT-SC40A1 HÌNH CHỮ NHẬT29340 X 3926 = 2 Tấm | C22: Bạt I95 - SC40A1 ( 29340 x 3926 ) x 2 tấm | D22: bạt da 2 lớp chống nước, khuyên cách nhau 500-mua theo bản vẽ | E22: m2 | F22: 230.38 | G22: N/A | H22: N/A | I22: N/A | J22: N/A | K22: V | L22: 50500 | M22: =L22*F22 -> 11634190 | N22: Trần Toàn | O22: Chưa có trong dự toán
A23: I95-VDK-027 | B23: I95-BAT-SC40C1 HÌNH CHỮ NHẬT29340 X 3926 = 2 Tấm | C23: Bạt I95 - SC40C1 ( 29340 x 3926 ) x 2 tấm | D23: bạt da 2 lớp chống nước, khuyên cách nhau 500-mua theo bản vẽ | E23: m2 | F23: 230.38 | G23: N/A | H23: N/A | I23: N/A | J23: N/A | K23: V | L23: 50500 | M23: =L23*F23 -> 11634190 | N23: Trần Toàn | O23: Chưa có trong dự toán
... A104: I95-VDK-027 | B104: I95-BAT-RFR19 HÌNH CHỮ NHẬT4650 X 2602 = 2 Tấm | C104: Bạt I95 - RFR19 ( 4650 x 2602 ) x 2 tấm | D104: bạt da 2 lớp chống nước, khuyên cách nhau 500-mua theo bản vẽ | E104: m2 | F104: 24.2 | G104: N/A | H104: N/A | I104: N/A | J104: N/A | K104: V | L104: 50500 | M104: =L104*F104 -> 1222100 | N104: Trần Toàn | O104: Chưa có trong dự toán
B105: Xếp hạng | L105: 1
A106: Ghi chú: PTM tiến hàng mua sắm để đảm bảo tiến độ
A107: NGƯỜI ĐỀ NGHỊ/ RECOMMENDATION BY: | D107: NGƯỜI KIỂM TRA/ DEPARTMENT HEAD CHECK BY: | I107: APPROVED BY: PHÊ DUYỆT
H108: Nguyễn Quang Vinh | K108: Hoàng Ngọc Bằng | N108: Đoàn Văn Toàn

Sheet hOÀNG hÀ 26-1 
A1: BID ANALYSIS - GIẢI TRÌNH MUA SẮM/ĐẤU THẦU
A3: Project | B3: PROJECT No/ Dự án: 25-VPI-I-095
A4: Dự án
A5: Subject | B5: Cung cấp vật tư phụ kiện / đóng kiện hoàng hà 26-1-2026
A6: Chủ đề
A8: No. | B8: CONTENT | C8: Phạm vi công việc | I8: Dự toán | K8: Đã mua | L8: Đơn vị cung cấp chào giá (vnđ) | O8: Lựa chọn | P8: Ghi chú
A9: Item | B9: Description/ Chi tiết | C9: Profile/ Vật tư | D9: Grade/ Mác vật liệu | E9: Grade/ Mác vật liệu mua | F9: Số lượng Mua | H9: Khối lượng/ Số lượng | I9: Đơn giá (vnd) | J9: Thành tiền (vnd) | K9: Thành tiền (vnd) | L9: HOÀNG HÀ
L10: Phạm vi | M10: Đơn giá (VND) | N10: Thành Tiền (Chưa có VAT)
A11: Tổng | B11: Bolt-Material / Vật tư bulong, phụ kiện | H11: N/A | I11: N/A | J11: ='Tổng hợp'!K23 -> 9.374355e+09 | K11: ='Tổng hợp'!J23+'Tổng hợp'!J22-'Vật tư bạt trần toàn'!M11 -> 21764911718 | N11: =SUM(N12:N16) -> 14650000 | P11: =J11-K11-N11 -> -1.2405207e+10
A12: I95-VPK-028 | B12: =VLOOKUP(A12,'25-VPI-I-095'!L:N,3,0) -> VÍT TỰ KHOAN M5X10 | C12: Vít tự khoan đầu bằng | D12: M4.8*13 | E12: Inox 410 | F12: 7000 | G12: cái | H12: =VLOOKUP(A12,'25-VPI-I-095'!L:DG,95,0) -> 7000 | I12: N/A | J12: N/A | K12: N/A | L12: V | M12: 350 | N12: =M12*F12 -> 2450000 | O12: HOÀNG HÀ | Q12: =G12-H12 -> #VALUE!
A13: I95-VPK-096 | B13: =VLOOKUP(A13,'25-VPI-I-095'!L:N,3,0) -> UBOLT_DN40_M10(4N+2W) | C13: Ubolt làm theo bản vẽ | E13: Mạ kẽm | F13: 80 | G13: T4E2P | H13: =VLOOKUP(A13,'25-VPI-I-095'!L:DG,95,0) -> 80 | I13: N/A | J13: N/A | K13: N/A | L13: V | M13: 45000 | N13: =M13*F13 -> 3600000 | O13: HOÀNG HÀ | Q13: =G13-H13 -> #VALUE!
A14: I95-VPK-097 | B14: =VLOOKUP(A14,'25-VPI-I-095'!L:N,3,0) -> WASHER M16-ISO7089-140HV-HDG | C14: Long đen phẳng | D14: M16 | E14: Mạ kẽm nhúng nóng | F14: 80 | G14: cái | H14: =VLOOKUP(A14,'25-VPI-I-095'!L:DG,95,0) -> 80 | I14: N/A | J14: N/A | K14: N/A | L14: V | M14: 700 | N14: =M14*F14 -> 56000 | O14: HOÀNG HÀ | Q14: =G14-H14 -> #VALUE!
A15: I95-VPK-098 | B15: =VLOOKUP(A15,'25-VPI-I-095'!L:N,3,0) -> NUT M16-ISO4032-HDG | C15: Ecu | D15: M16 | E15: Mạ kẽm nhúng nóng | F15: 80 | G15: cái | H15: =VLOOKUP(A15,'25-VPI-I-095'!L:DG,95,0) -> 80 | I15: N/A | J15: N/A | K15: N/A | L15: V | M15: 3800 | N15: =M15*F15 -> 304000 | O15: HOÀNG HÀ | Q15: =G15-H15 -> #VALUE!
A16: I95-VPK-099 | B16: =VLOOKUP(A16,'25-VPI-I-095'!L:N,3,0) -> LÒ SO SPRING_D3 | C16: Loò xo làm theo bản vẻ | D16: D3 | E16: Inox 304 | F16: 80 | G16: cái | H16: =VLOOKUP(A16,'25-VPI-I-095'!L:DG,95,0) -> 80 | I16: N/A | J16: N/A | K16: N/A | L16: V | M16: 103000 | N16: =M16*F16 -> 8240000 | O16: HOÀNG HÀ | Q16: =G16-H16 -> #VALUE!
A17: Tổng | B17: Packing-Material / Vật tư đóng kiện | J17: ='Tổng hợp'!K19 -> 5.7151444e+10 | K17: ='Tổng hợp'!J19+'Tổng hợp'!J24 -> 5.0853523e+10 | N17: =SUM(N18:N24) -> 72902300 | P17: =J17-K17-N17 -> 6.225019e+09
A18: I95-VDK-019 | B18: =VLOOKUP(A18,'25-VPI-I-095'!L:N,3,0) -> BOLT-M12x40-ISO4017/ISO4032(1B+1N) | C18: Bu lông ren ren suốt | D18: M12*40 | E18: Mạ kẽm 8.8 | F18: 4100 | G18: TE | H18: =VLOOKUP(A18,'25-VPI-I-095'!L:DG,95,0) -> 4100 | I18: N/A | J18: N/A | K18: N/A | L18: V | M18: 2800 | N18: =M18*F18 -> 11480000 | O18: HOÀNG HÀ | Q18: =G18-H18 -> #VALUE!
A19: I95-VDK-020 | B19: =VLOOKUP(A19,'25-VPI-I-095'!L:N,3,0) -> BOLT-M16x50-ISO4017/ISO4032(1B+1N) | C19: Bu lông ren ren suốt | D19: M16*50 | E19: Mạ kẽm 8.8 | F19: 1700 | G19: TE | H19: =VLOOKUP(A19,'25-VPI-I-095'!L:DG,95,0) -> 1700 | I19: N/A | J19: N/A | K19: N/A | L19: V | M19: 6190 | N19: =M19*F19 -> 10523000 | O19: HOÀNG HÀ | Q19: =G19-H19 -> #VALUE!
A20: I95-VDK-021 | B20: =VLOOKUP(A20,'25-VPI-I-095'!L:N,3,0) -> BOLT-M16X60-ISO4017/ISO4032(1B+1N) | C20: Bu lông ren ren suốt | D20: M16*60 | E20: Mạ kẽm 8.8 | F20: 970 | G20: TE | H20: =VLOOKUP(A20,'25-VPI-I-095'!L:DG,95,0) -> 970 | I20: N/A | J20: N/A | K20: N/A | L20: V | M20: 6790 | N20: =M20*F20 -> 6586300 | O20: HOÀNG HÀ | Q20: =G20-H20 -> #VALUE!
A21: I95-VDK-022 | B21: =VLOOKUP(A21,'25-VPI-I-095'!L:N,3,0) -> BOLT-M16X90-ISO4017/ISO4032(1B+1N) | C21: Bu lông ren ren suốt | D21: M16*90 | E21: Mạ kẽm 8.8 | F21: 200 | G21: TE | H21: =VLOOKUP(A21,'25-VPI-I-095'!L:DG,95,0) -> 200 | I21: N/A | J21: N/A | K21: N/A | L21: V | M21: 8690 | N21: =M21*F21 -> 1738000 | O21: HOÀNG HÀ | Q21: =G21-H21 -> #VALUE!
A22: I95-VDK-023 | B22: =VLOOKUP(A22,'25-VPI-I-095'!L:N,3,0) -> dây Polyme belt 32 | C22: Dây chằng hàng | D22: D32 | E22: Vải | F22: 3000 | G22: Met | H22: =VLOOKUP(A22,'25-VPI-I-095'!L:DG,95,0) -> 3000 | I22: N/A | J22: N/A | K22: N/A | L22: V | M22: 4200 | N22: =M22*F22 -> 12600000 | O22: HOÀNG HÀ | Q22: =G22-H22 -> #VALUE!
A23: I95-VDK-025 | B23: =VLOOKUP(A23,'25-VPI-I-095'!L:N,3,0) -> dây cáp vải rộng 50 | C23: dây cáp vải rộng 50 | D23: D50 | E23: Vải | F23: 5000 | G23: Met | H23: =VLOOKUP(A23,'25-VPI-I-095'!L:DG,95,0) -> 5000 | I23: N/A | J23: N/A | K23: N/A | L23: V | M23: 5830 | N23: =M23*F23 -> 29150000 | O23: HOÀNG HÀ | Q23: =G23-H23 -> #VALUE!
A24: I95-VDK-031 | B24: =VLOOKUP(A24,'25-VPI-I-095'!L:N,3,0) -> VÍT TỰ KHOAN M5X20-MẠ KẼM | C24: VÍT TỰ KHOAN M5X20-MẠ KẼM | D24: M5*19 | E24: Mạ kẽm nhúng nóng | F24: 1500 | G24: cái | H24: =VLOOKUP(A24,'25-VPI-I-095'!L:DG,95,0) -> 1500 | I24: N/A | J24: N/A | K24: N/A | L24: V | M24: 550 | N24: =M24*F24 -> 825000 | O24: HOÀNG HÀ | Q24: =G24-H24 -> #VALUE!
B25: Xếp hạng | M25: 1
A26: Ghi chú: PTM tiến hàng mua sắm để đảm bảo tiến độ
A27: NGƯỜI ĐỀ NGHỊ/ RECOMMENDATION BY: | D27: NGƯỜI KIỂM TRA/ DEPARTMENT HEAD CHECK BY: | J27: APPROVED BY: PHÊ DUYỆT
I28: Nguyễn Quang Vinh | L28: Hoàng Ngọc Bằng | O28: Đoàn Văn Toàn

Sheet Kế hoạch thanh toán
A1: STT | B1: SUPPLIER | C1: SALE CONTRACT | D1: Dự án | E1: VALUE (CIF HAI PHONG PORT) Hoặc giá trước Thuế | F1: PAYMENTS | G1: SIGN DATE | H1: L/C | I1: ETD | J1: ETA | K1: DOCUMENT | L1: Kế hoạch thanh toán | M1: Deadline of L/C | N1: Notet
A2: 1 | B2: GLOBAL | C2: IBS-FY260115 | D2: DA 095 | E2: 1020.5 | F2: T/T | G2: 46038 | H2: N/A | I2: 46058 | J2: 46066 | K2: N/A | L2: Tháng 2 | M2: N/A | N2: Tính phương án lưu container
A3: 2 | B3: GLOBAL | C3: IBSHI-FENGYANG/2512-30 | D3: DA 095 | E3: 19507.84 | F3: LC 100% | G3: 46021 | H3: 46035 | I3: 46058 | J3: 46066 | K3: 46068 | L3: Tháng 2 | M3: 46083 | N3: Tính phương án lưu container
A4: 3 | B4: CENTERWAY | C4: CTWSO2025470ZY | D4: DA 095 | E4: 11753.2 | F4: LC 100% | G4: 45999 | H4: 46013 | I4: 46039 | J4: 46047 | K4: 46052 | L4: Tháng 2 | M4: 46069 | N4: Thanh toán trước tết
A5: 4 | B5: GNEE | C5: IBSHI-GNEE/2511-28 | D5: DA 095 | E5: 97932.26 | F5: LC 100% | G5: 45989 | H5: 46004 | I5: 46055 | J5: =I5+12 -> 46067 | K5: 46071 | L5: Tháng 2 | N5: Tính phương án lưu container
A6: 5 | B6: GNEE | C6: IBSHI-GNEE/2512-24 | D6: DA 095 | E6: 21340.3 | F6: DP | G6: 46015 | H6: N/A | I6: 46038 | J6: 46048 | K6: 46055 | L6: Tháng 2 | M6: N/A | N6: Thanh toán trước tết
A7: 6 | B7: JFE | C7: JFEBS-IBS-001 | D7: DA 095 | E7: 47822.4 | F7: LC 100% | G7: 46015 | H7: 46027 | I7: 46111 | J7: =I7+14 -> 46125 | K7: =J7+2 -> 46127 | L7: Tháng 4 | N7: Thanh toán sau tết
A8: 7 | B8: MCL | C8: 25MCL157S | D8: DA 095 | E8: 39892.1 | F8: DP | G8: 46013 | H8: N/A | I8: 46053 | J8: 46065 | K8: =J8+2 -> 46067 | L8: Tháng 2 | M8: N/A | N8: Tính phương án lưu container
B9: Số tiền cần thanh toán trong tháng 2 dự kiến: | F9: =SUM(E10:E154) -> 16129944088
B10: Đơn nhập khẩu quy ra VNĐ (Sum của các mục nhập khẩu phía trên trong tháng 2) | D10: DA 095 | E10: =26300*(SUM(E2:E6)+E8) -> 5035035060
A11: 8 | B11: Ngọc Hiếu đơn 1 | C11: Thép Hình/ Thép tấm | D11: DA 095 | E11: ='Ngọc hiếu 095 26-1'!M11 -> 1898049693 | K11: Hàng đang đi lấy | L11: Tháng 2 | M11: N/A
A12: 9 | B12: Hoàng Hà 1 | C12: Bu lông | D12: DA 095 | E12: ='Vật tư phụ Hoàng hà 2'!Q13 -> 99508400 | K12: Hàng đa giao ngày 20/1 | L12: Tháng 2
A13: 10 | B13: Hoàng Hà 2 | C13: Bu lông | D13: DA 095 | E13: ='hOÀNG hÀ 26-1 '!N11+'hOÀNG hÀ 26-1 '!N17 -> 87552300 | K13: Hàng sẽ giao ngày 6/2 | L13: Tháng 2
A14: 11 | B14: Hoàng Hà 3 | C14: Bu lông | D14: G07 | E14: 23000000 | K14: Hàng sẽ giao hàng ngày 2/2 | L14: Tháng 2
A15: 12 | B15: Trần Toàn | C15: Bạt | D15: DA 095 | E15: ='Vật tư bạt trần toàn'!M11 -> 559330930 | K15: Hàng sẽ giao trong tháng 2 | L15: Tháng 2
A16: 13 | B16: Xalaco 1 | C16: Bông bảo ôn (Phải thanh toán trước tết để xalaco nhập đợt 2) | D16: DA 095 | E16: 1.5589282e+09 | K16: Thanh toán tiền hàng giao đợt 1: 24/01/2026 và 26/01/2026 Đề nghị thanh toán xong trước ngày 07/02/2026 để giao lần 2 | L16: Tháng 2
A17: 14 | B17: Xalaco 2 | C17: Bông bảo ôn lần 2 | D17: DA 095 | E17: 2.7303998e+09 | K17: Dự kiến thanh toán và giao hàng vào tháng 2 , sau khi nhận tiền đợt 1 | L17: Tháng 2
A18: 15 | B18: Xalaco 3 | C18: Lưới | D18: DA 095 | E18: =XALACO2!O11 -> 89770000 | K18: Hàng sẽ giao trước 14/2 | L18: Tháng 2
A19: 16 | B19: Xalaco 4 | C19: Gioăng | D19: DA 078 | E19: 2.6782764e+08 | K19: Hàng đã giao | L19: Tháng 2
A20: 17 | B20: Kiên Dũng | C20: Gioăng | D20: DA 095 | E20: 10152000 | K20: Hàng sẽ giao trước ngày 9/2 | L20: Tháng 2
A21: 18 | B21: SUN COMMERCIAL | C21: Keo | D21: DA 095 | E21: ='Vật tư SUN COMMERCIAL'!K12 -> 9900000 | K21: Thanh toán xong mới có hàng | L21: Tháng 2
A22: 19 | B22: FUJIMOTO đơn 1 | C22: Vit | D22: DA 095 | E22: 7613000 | K22: Hàng sẽ giao ngày 24/2 | L22: Tháng 2
A23: 20 | B23: FUJIMOTO đơn 2 | C23: Vít | D23: DA 095 | E23: 7500000 | K23: Hàng sẽ giao ngày 24/2 | L23: Tháng 2
A24: 21 | B24: Hùng Nguyên trước đó | C24: Thép tấm | D24: All | E24: =1146425831-E25-E26 -> 814734821 | K24: Đa giao hàng từ lâu | L24: Tháng 2
A25: 22 | B25: Hùng Nguyên | C25: Thép tấm | D25: DA 095 | E25: 185676739 | K25: Hàng giao ngày 28/1 | L25: Tháng 2
A26: 23 | B26: Hùng Nguyên2 | C26: Thép tấm | D26: G07 | E26: 146014271 | K26: Hàng đã giao ngày 28/1 | L26: Tháng 2
A27: 24 | B27: Hùng Nguyên3 | C27: Thép hình | D27: DA 095 | E27: 73162492 | K27: Dự kiến lấy hàng 2/2 | L27: Tháng 2
A28: 25 | B28: Hùng Nguyên4 | C28: Thép hình | D28: DA 095 | E28: 93135268 | K28: Ngày 31/1 đi lấy hàng | L28: Tháng 2
A29: 26 | B29: Quang Thịnh Phát 1 | C29: Thép ống | D29: DA 095 | E29: 11745998 | K29: Hàng đã giao ngày 25/1 | L29: Tháng 2
A30: 27 | B30: VSAN | C30: Bu lông | D30: DA 095 | E30: 1150430610 | K30: Hàng đã giao ngày 30/1 | L30: Tháng 2
A31: 28 | B31: VSAN 2 | C31: Bu lông | D31: DA 095 | E31: 44484000 | K31: Hàng sẽ giao trước 14/2 | L31: Tháng 2
A32: 29 | B32: VSAN 3 | C32: Bu lông | D32: DA 095 | E32: 302139706 | K32: Hàng sẽ giao trước 14/2 | L32: Tháng 2
A33: 30 | B33: Hoàng Anh Minh | C33: Gỗ | D33: DA 097/100/90 | E33: 205858000 | K33: Đã giao | L33: Tháng 2
A34: 31 | B34: WINWIN | C34: Tạm ứng sàn 30% | D34: DA 095 | E34: =3589976000*0.2 -> 717995200 | K34: Tạm ứng/ giá có thể thay đổi | L34: Tháng 2

Sheet VSAN 27-1
A1: BID ANALYSIS - GIẢI TRÌNH MUA SẮM/ĐẤU THẦU
A3: Project | B3: PROJECT No/ Dự án: 25-VPI-I-095
A4: Dự án
A5: Subject | B5: Cung cấp vật tư phụ kiện VSAN 27-1-2026
A6: Chủ đề
A8: No. | B8: CONTENT | C8: Phạm vi công việc | I8: Dự toán | K8: Đã mua | L8: Đơn vị cung cấp chào giá (vnđ) | O8: Lựa chọn | P8: Ghi chú
A9: Item | B9: Description/ Chi tiết | C9: Profile/ Vật tư | D9: Grade/ Mác vật liệu | E9: Grade/ Mác vật liệu mua | F9: Số lượng Mua | H9: Khối lượng/ Số lượng | I9: Đơn giá (vnd) | J9: Thành tiền (vnd) | K9: Thành tiền (vnd) | L9: VSAN
L10: Phạm vi | M10: Đơn giá (VND) | N10: Thành Tiền (Chưa có VAT)
A11: Tổng | B11: Bolt-Material / Vật tư bulong, phụ kiện | H11: N/A | I11: N/A | J11: ='Tổng hợp'!K23 -> 9.374355e+09 | K11: ='Tổng hợp'!J23+'Tổng hợp'!J22 -> 22324242648 | N11: =SUM(N12:N25) -> 325180800 | P11: =J11-K11-N11 -> -1.3275068e+10
A12: I95-VPK-104 | B12: =VLOOKUP(A12,'25-VPI-I-095'!L:N,3,0) -> BOLT-1 1/2"x4 1/4"LG-A193-B7-HDG | C12: BOLT-1 1/2"x4 1/4"LG-A193-B7-HDG | D12: A193-B7 | E12: bolt full thread | F12: CÁI | G12: 80 | H12: =VLOOKUP(A12,'25-VPI-I-095'!L:DG,95,0) -> 80 | I12: N/A | J12: N/A | K12: N/A | L12: V | M12: 229600 | N12: 18368000 | O12: VSAN | Q12: =G12-H12 -> 0
A13: I95-VPK-105 | B13: =VLOOKUP(A13,'25-VPI-I-095'!L:N,3,0) -> BOLT-1 1/8"x4 1/2"LG(1B+1N+1W+1DTIW)-A490-GEOMET | C13: BOLT-1 1/8"x4 1/2"LG(1B+1N+1W+1DTIW)-A490-GEOMET | D13: A490/A563/F436/F959 | E13: bolt full thread | F13: BỘ | G13: 424 | H13: =VLOOKUP(A13,'25-VPI-I-095'!L:DG,95,0) -> 424 | I13: N/A | J13: N/A | K13: N/A | L13: V | M13: 239000 | N13: 101336000 | O13: VSAN | Q13: =G13-H13 -> 0
A14: I95-VPK-106 | B14: =VLOOKUP(A14,'25-VPI-I-095'!L:N,3,0) -> BOLT-1 1/8"x4"LG(1B+1N+1W+1DTIW)-A490-GEOMET | C14: BOLT-1 1/8"x4"LG(1B+1N+1W+1DTIW)-A490-GEOMET | D14: A490/A563/F436/F959 | E14: bolt full thread | F14: BỘ | G14: 494 | H14: =VLOOKUP(A14,'25-VPI-I-095'!L:DG,95,0) -> 494 | I14: N/A | J14: N/A | K14: N/A | L14: V | M14: 228000 | N14: 112632000 | O14: VSAN | Q14: =G14-H14 -> 0
A15: I95-VPK-107 | B15: =VLOOKUP(A15,'25-VPI-I-095'!L:N,3,0) -> BOLT-3/4"x2 1/2"LG(1B+1N)-A193B7-HDG | C15: BOLT-3/4"x2 1/2"LG(1B+1N)-A193B7-HDG | D15: A193-B7/A194-7 | E15: bolt full thread | F15: BỘ | G15: 28 | H15: =VLOOKUP(A15,'25-VPI-I-095'!L:DG,95,0) -> 28 | I15: N/A | J15: N/A | K15: N/A | L15: V | M15: 60000 | N15: 1680000 | O15: VSAN | Q15: =G15-H15 -> 0
A16: I95-VPK-108 | B16: =VLOOKUP(A16,'25-VPI-I-095'!L:N,3,0) -> BOLT-3/4"x2 3/4"LG-FULL THREAD-A193B7-HDG | C16: BOLT-3/4"x2 3/4"LG-FULL THREAD-A193B7-HDG | D16: A193-B7/A194-7 | E16: bolt full thread | F16: BỘ | G16: 62 | H16: =VLOOKUP(A16,'25-VPI-I-095'!L:DG,95,0) -> 62 | I16: N/A | J16: N/A | K16: N/A | L16: V | M16: 62400 | N16: 3868800 | O16: VSAN | Q16: =G16-H16 -> 0
A17: I95-VPK-109 | B17: =VLOOKUP(A17,'25-VPI-I-095'!L:N,3,0) -> BOLT-3/4"x3 1/2"LG(1B+1N)-A193B7-HDG | C17: BOLT-3/4"x3 1/2"LG(1B+1N)-A193B7-HDG | D17: A193-B7/A194-7 | E17: bolt full thread | F17: BỘ | G17: 194 | H17: =VLOOKUP(A17,'25-VPI-I-095'!L:DG,95,0) -> 194 | I17: N/A | J17: N/A | K17: N/A | L17: V | M17: 65000 | N17: 12610000 | O17: VSAN | Q17: =G17-H17 -> 0
A18: I95-VPK-110 | B18: =VLOOKUP(A18,'25-VPI-I-095'!L:N,3,0) -> BOLT-5/8"x1 3/4"LG-A193-B7-HDG | C18: BOLT-5/8"x1 3/4"LG-A193-B7-HDG | D18: A193-B7 | E18: bolt full thread | F18: CÁI | G18: 582 | H18: =VLOOKUP(A18,'25-VPI-I-095'!L:DG,95,0) -> 582 | I18: N/A | J18: N/A | K18: N/A | L18: V | M18: 29000 | N18: 16878000 | O18: VSAN | Q18: =G18-H18 -> 0
A19: I95-VPK-111 | B19: =VLOOKUP(A19,'25-VPI-I-095'!L:N,3,0) -> BOLT-5/8"x3"LG(1B+1N)-A193B7-HDG | C19: BOLT-5/8"x3"LG(1B+1N)-A193B7-HDG | D19: A193-B7/A194-7 | E19: bolt full thread | F19: BỘ | G19: 1004 | H19: =VLOOKUP(A19,'25-VPI-I-095'!L:DG,95,0) -> 1004 | I19: N/A | J19: N/A | K19: N/A | L19: V | M19: 39000 | N19: 39156000 | O19: VSAN | Q19: =G19-H19 -> 0
A20: I95-VPK-112 | B20: =VLOOKUP(A20,'25-VPI-I-095'!L:N,3,0) -> BOLT-5/8"x3"LG-A193-B7-HDG | C20: BOLT-5/8"x3"LG-A193-B7-HDG | D20: A193-B7 | E20: bolt full thread | F20: CÁI | G20: 160 | H20: =VLOOKUP(A20,'25-VPI-I-095'!L:DG,95,0) -> 160 | I20: N/A | J20: N/A | K20: N/A | L20: V | M20: 24800 | N20: 3968000 | O20: VSAN | Q20: =G20-H20 -> 0
A21: I95-VPK-113 | B21: =VLOOKUP(A21,'25-VPI-I-095'!L:N,3,0) -> NUT-1 1/2"-A194-2H-HDG | C21: NUT-1 1/2"-A194-2H-HDG | D21: A194-2H | F21: CÁI | G21: 80 | H21: =VLOOKUP(A21,'25-VPI-I-095'!L:DG,95,0) -> 80 | I21: N/A | J21: N/A | K21: N/A | L21: V | M21: 74400 | N21: 5952000 | O21: VSAN | Q21: =G21-H21 -> 0
A22: I95-VPK-114 | B22: =VLOOKUP(A22,'25-VPI-I-095'!L:N,3,0) -> NUT-3/4"-A194GR7-HDG | C22: NUT-3/4"-A194GR7-HDG | D22: A194-7 | F22: CÁI | G22: 124 | H22: =VLOOKUP(A22,'25-VPI-I-095'!L:DG,95,0) -> 124 | I22: N/A | J22: N/A | K22: N/A | L22: V | M22: 16800 | N22: 2083200 | O22: VSAN | Q22: =G22-H22 -> 0
A23: I95-VPK-115 | B23: =VLOOKUP(A23,'25-VPI-I-095'!L:N,3,0) -> NUT-5/8"-A194-2H-HDG | C23: NUT-5/8"-A194-2H-HDG | D23: A194-2H | F23: CÁI | G23: 740 | H23: =VLOOKUP(A23,'25-VPI-I-095'!L:DG,95,0) -> 740 | I23: N/A | J23: N/A | K23: N/A | L23: V | M23: 6800 | N23: 5032000 | O23: VSAN | Q23: =G23-H23 -> 0
A24: I95-VPK-116 | B24: =VLOOKUP(A24,'25-VPI-I-095'!L:N,3,0) -> WASHER-1 1/2"x3"OD-F436-HDG | C24: WASHER-1 1/2"x3"OD-F436-HDG | D24: F436 | F24: CÁI | G24: 80 | H24: =VLOOKUP(A24,'25-VPI-I-095'!L:DG,95,0) -> 80 | I24: N/A | J24: N/A | K24: N/A | L24: V | M24: 16800 | N24: 1344000 | O24: VSAN | Q24: =G24-H24 -> 0
A25: I95-VPK-117 | B25: =VLOOKUP(A25,'25-VPI-I-095'!L:N,3,0) -> WASHER-3/4"-SUS304 | C25: WASHER-3/4"-SUS304 | D25: SUS304 | F25: CÁI | G25: 62 | H25: =VLOOKUP(A25,'25-VPI-I-095'!L:DG,95,0) -> 62 | I25: N/A | J25: N/A | K25: N/A | L25: V | M25: 4400 | N25: 272800 | O25: VSAN | Q25: =G25-H25 -> 0
B26: Xếp hạng | M26: 1
A27: Ghi chú: PTM tiến hàng mua sắm để đảm bảo tiến độ
A28: NGƯỜI ĐỀ NGHỊ/ RECOMMENDATION BY: | D28: NGƯỜI KIỂM TRA/ DEPARTMENT HEAD CHECK BY: | J28: APPROVED BY: PHÊ DUYỆT
I29: Nguyễn Quang Vinh | L29: Hoàng Ngọc Bằng | O29: Đoàn Văn Toàn

Sheet VSAN 26-1
A1: BID ANALYSIS - GIẢI TRÌNH MUA SẮM/ĐẤU THẦU
A3: Project | B3: PROJECT No/ Dự án: 25-VPI-I-095
A4: Dự án
A5: Subject | B5: Cung cấp vật tư phụ kiện VSAN 28-1-2026
A6: Chủ đề
A8: No. | B8: CONTENT | C8: Phạm vi công việc | H8: Dự toán | K8: Đã mua | L8: Đơn vị cung cấp chào giá (vnđ) | O8: Đơn vị cung cấp chào giá (vnđ) | R8: Đơn vị cung cấp chào giá (vnđ) | U8: Lựa chọn | V8: Ghi chú
A9: Item | B9: Description/ Chi tiết | C9: Profile/ Vật tư | D9: Grade/ Mác vật liệu | E9: Grade/ Mác vật liệu mua | F9: Số lượng Mua | H9: Khối lượng/ Số lượng | I9: Đơn giá (vnd) | J9: Thành tiền (vnd) | K9: Thành tiền (vnd) | L9: VSAN | O9: HSC | R9: FUJIMOTO offer
L10: Phạm vi | M10: Đơn giá (VND) | N10: Thành Tiền (Chưa có VAT) | O10: Phạm vi | P10: Đơn giá (USD) Giá CIF | Q10: Thành Tiền (USD | R10: Phạm vi | S10: Đơn giá (VND) | T10: Tiến độ
A11: Tổng | B11: Bolt-Material / Vật tư bulong, phụ kiện | H11: N/A | I11: N/A | J11: ='Tổng hợp'!K23 -> 9.374355e+09 | K11: ='Tổng hợp'!J23+'Tổng hợp'!J22 -> 22324242648 | N11: =SUM(N12:N87) -> 1797978240 | V11: =J11-K11-N11 -> -1.4747866e+10
A12: I95-VPK-019 | B12: =VLOOKUP(A12,'25-VPI-I-095'!L:N,3,0) -> NUT-3/4"-A563-BLACK | C12: NUT-3/4"-A563-BLACK | D12: A-563 HEX NUT | F12: cái | G12: 1150 | H12: =VLOOKUP(A12,'25-VPI-I-095'!L:DG,95,0) -> 2032 | I12: N/A | J12: N/A | K12: N/A | L12: V | M12: 8800 | N12: 10120000 | O12: V | P12: 0.34 | Q12: N/A | R12: V | S12: 8700 | T12: 45 days , Plain no coating , | U12: VSAN | W12: =G12-H12 -> -882
A13: I95-VPK-034 | B13: =VLOOKUP(A13,'25-VPI-I-095'!L:N,3,0) -> BOLT-1"x6"LG(1B+1N+2W)-A193B8 | C13: BOLT-1"x6"LG(1B+1N+2W)-A193B8 | D13: A193B8 | E13: bolt full thread | F13: BỘ | G13: 80 | H13: =VLOOKUP(A13,'25-VPI-I-095'!L:DG,95,0) -> 80 | I13: N/A | J13: N/A | K13: N/A | L13: V | M13: 344000 | N13: 27520000 | O13: V | P13: 15.61 | Q13: N/A | R13: V | S13: 226000 | T13: 45 days , Plain , giá bộ, đổi qua hex bolt, hex nut ss304 thông thường, ren suốt | U13: VSAN | W13: =G13-H13 -> 0
A14: I95-VPK-035 | B14: =VLOOKUP(A14,'25-VPI-I-095'!L:N,3,0) -> BOLT-1/2"x 1 3/8"LG-A325-BLACK | C14: BOLT-1/2"x 1 3/8"LG-A325-BLACK | D14: A325 | E14: bolt full thread | F14: CÁI | G14: 634 | H14: =VLOOKUP(A14,'25-VPI-I-095'!L:DG,95,0) -> 634 | I14: N/A | J14: N/A | K14: N/A | L14: V | M14: 9600 | N14: 6086400 | O14: V | P14: 0.37 | Q14: N/A | R14: V | S14: 24000 | T14: 60 days , black oxided , | U14: VSAN | W14: =G14-H14 -> 0
A15: I95-VPK-036 | B15: =VLOOKUP(A15,'25-VPI-I-095'!L:N,3,0) -> BOLT-1/2"x1 1/2"-A325-HDG | C15: BOLT-1/2"x1 1/2"-A325-HDG | D15: A325-HDG | E15: bolt full thread | F15: CÁI | G15: 318 | H15: =VLOOKUP(A15,'25-VPI-I-095'!L:DG,95,0) -> 318 | I15: N/A | J15: N/A | K15: N/A | L15: V | M15: 12000 | N15: 3816000 | O15: V | P15: 0.42 | Q15: N/A | R15: V | S15: 39000 | T15: 60 days , HDG , | U15: VSAN | W15: =G15-H15 -> 0
A16: I95-VPK-037 | B16: =VLOOKUP(A16,'25-VPI-I-095'!L:N,3,0) -> BOLT-1/2"x1 1/2"LG-A307(1B+1N+1W)-HDG | C16: BOLT-1/2"x1 1/2"LG-A307(1B+1N+1W)-HDG | D16: A307-A563-F436 | E16: bolt full thread | F16: BỘ | G16: 512 | H16: =VLOOKUP(A16,'25-VPI-I-095'!L:DG,95,0) -> 512 | I16: N/A | J16: N/A | K16: N/A | L16: V | M16: 14400 | N16: 7372800 | O16: V | P16: 0.6 | Q16: N/A | R16: V | S16: 18000 | T16: 15 days , HDG/Geomet , giá bộ với đai ốc geomet, long đền nhúng, bolt nhúng nóng | U16: VSAN | W16: =G16-H16 -> 0
A17: I95-VPK-038 | B17: =VLOOKUP(A17,'25-VPI-I-095'!L:N,3,0) -> BOLT-1/2"x1 3/4"LG-A307(1B+1N+1W)-HDG | C17: BOLT-1/2"x1 3/4"LG-A307(1B+1N+1W)-HDG | D17: A307-A563-F436 | E17: bolt full thread | F17: BỘ | G17: 44 | H17: =VLOOKUP(A17,'25-VPI-I-095'!L:DG,95,0) -> 44 | I17: N/A | J17: N/A | K17: N/A | L17: V | M17: 15200 | N17: 668800 | O17: V | P17: 0.62 | Q17: N/A | R17: V | S17: 19000 | T17: 15 days , HDG/Geomet , giá bộ với đai ốc geomet, long đền nhúng, bolt nhúng nóng | U17: VSAN | W17: =G17-H17 -> 0
A18: I95-VPK-039 | B18: =VLOOKUP(A18,'25-VPI-I-095'!L:N,3,0) -> BOLT-1/2"x3 1/4"LG(1B+1N+1W)-A307-HDG | C18: BOLT-1/2"x3 1/4"LG(1B+1N+1W)-A307-HDG | D18: A307-A563-F436 | E18: bolt full thread | F18: BỘ | G18: 32 | H18: =VLOOKUP(A18,'25-VPI-I-095'!L:DG,95,0) -> 32 | I18: N/A | J18: N/A | K18: N/A | L18: V | M18: 22400 | N18: 716800 | O18: V | P18: 0.87 | Q18: N/A | R18: V | S18: 28000 | T18: 45 days , HDG/Geomet , giá bộ với đai ốc geomet, long đền nhúng, bolt nhúng nóng | U18: VSAN | W18: =G18-H18 -> 0
A19: I95-VPK-040 | B19: =VLOOKUP(A19,'25-VPI-I-095'!L:N,3,0) -> BOLT-1/2"x3 1/4"LG-A307(1B+1N+1W)-HDG | C19: BOLT-1/2"x3 1/4"LG-A307(1B+1N+1W)-HDG | D19: A307-A563-F436 | E19: bolt full thread | F19: BỘ | G19: 32 | H19: =VLOOKUP(A19,'25-VPI-I-095'!L:DG,95,0) -> 32 | I19: N/A | J19: N/A | K19: N/A | L19: V | M19: 22400 | N19: 716800 | O19: V | P19: 0.87 | Q19: N/A | R19: V | S19: 28000 | T19: 45 days , HDG/Geomet , giá bộ với đai ốc geomet, long đền nhúng, bolt nhúng nóng | U19: VSAN | W19: =G19-H19 -> 0
A20: I95-VPK-041 | B20: =VLOOKUP(A20,'25-VPI-I-095'!L:N,3,0) -> BOLT-3/4" x 2"LG-A193-A479-TP310S | C20: BOLT-3/4" x 2"LG-A193-A479-TP310S | D20: A193-A479-TP310S | E20: bolt full thread | F20: CÁI | G20: 20 | H20: =VLOOKUP(A20,'25-VPI-I-095'!L:DG,95,0) -> 20 | I20: N/A | J20: N/A | K20: N/A | L20: V | M20: 952400 | N20: 20222000 | O20: V | P20: 8.87 | Q20: N/A | R20: X | S20: N/A | T20: N/A | U20: VSAN | W20: =G20-H20 -> 0
A21: I95-VPK-042 | B21: =VLOOKUP(A21,'25-VPI-I-095'!L:N,3,0) -> BOLT-3/4"x 1 3/4"LG-A307-BLACK | C21: BOLT-3/4"x 1 3/4"LG-A307-BLACK | D21: A307 | E21: bolt full thread | F21: CÁI | G21: 856 | H21: =VLOOKUP(A21,'25-VPI-I-095'!L:DG,95,0) -> 856 | I21: N/A | J21: N/A | K21: N/A | L21: V | M21: 16800 | N21: 14380800 | O21: V | P21: 0.74 | Q21: N/A | R21: V | S21: 20000 | T21: Giao sẵn 350pcs, còn lại 45 days , black oxided , | U21: VSAN | W21: =G21-H21 -> 0
A22: I95-VPK-043 | B22: =VLOOKUP(A22,'25-VPI-I-095'!L:N,3,0) -> BOLT-3/4"x 1 3/4"LG-A325-BLACK | C22: BOLT-3/4"x 1 3/4"LG-A325-BLACK | D22: A325 | E22: bolt full thread | F22: CÁI | G22: 238 | H22: =VLOOKUP(A22,'25-VPI-I-095'!L:DG,95,0) -> 238 | I22: N/A | J22: N/A | K22: N/A | L22: V | M22: 20000 | N22: 4760000 | O22: V | P22: 0.84 | Q22: N/A | R22: V | S22: 25000 | T22: 60 days , black oxided , | U22: VSAN | W22: =G22-H22 -> 0
A23: I95-VPK-044 | B23: =VLOOKUP(A23,'25-VPI-I-095'!L:N,3,0) -> BOLT-3/4"x 2 1/2"LG-A325-HDG | C23: BOLT-3/4"x 2 1/2"LG-A325-HDG | D23: A325-HDG | E23: bolt full thread | F23: CÁI | G23: 1004 | H23: =VLOOKUP(A23,'25-VPI-I-095'!L:DG,95,0) -> 1004 | I23: N/A | J23: N/A | K23: N/A | L23: V | M23: 25600 | N23: 25702400 | O23: V | P23: 1.04 | Q23: N/A | R23: V | S23: 18000 | T23: 30 days , HDG , | U23: VSAN | W23: =G23-H23 -> 0
A24: I95-VPK-045 | B24: =VLOOKUP(A24,'25-VPI-I-095'!L:N,3,0) -> BOLT-3/4"x 2"LG-A193-A479-TP309S | C24: BOLT-3/4"x 2"LG-A193-A479-TP309S | D24: A193-A479-TP309S | E24: bolt full thread | F24: CÁI | G24: 40 | H24: =VLOOKUP(A24,'25-VPI-I-095'!L:DG,95,0) -> 40 | I24: N/A | J24: N/A | K24: N/A | L24: V | M24: 952400 | N24: 40444000 | O24: V | P24: 8.87 | Q24: N/A | R24: X | S24: N/A | T24: N/A | U24: VSAN | W24: =G24-H24 -> 0
A25: I95-VPK-046 | B25: =VLOOKUP(A25,'25-VPI-I-095'!L:N,3,0) -> BOLT-3/4"x 2"LG-A193-A479-TP310S | C25: BOLT-3/4"x 2"LG-A193-A479-TP310S | D25: A193-A479-TP310S | E25: bolt full thread | F25: CÁI | G25: 20 | H25: =VLOOKUP(A25,'25-VPI-I-095'!L:DG,95,0) -> 20 | I25: N/A | J25: N/A | K25: N/A | L25: V | M25: 952400 | N25: 20222000 | O25: V | P25: 8.87 | Q25: N/A | R25: X | S25: N/A | T25: N/A | U25: VSAN | W25: =G25-H25 -> 0
A26: I95-VPK-047 | B26: =VLOOKUP(A26,'25-VPI-I-095'!L:N,3,0) -> BOLT-3/4"x 2"LG-A193B8 | C26: BOLT-3/4"x 2"LG-A193B8 | D26: A193B8 | E26: bolt full thread | F26: CÁI | G26: 160 | H26: =VLOOKUP(A26,'25-VPI-I-095'!L:DG,95,0) -> 160 | I26: N/A | J26: N/A | K26: N/A | L26: V | M26: 73600 | N26: 11776000 | O26: V | P26: 4.28 | Q26: N/A | R26: V | S26: 48000 | T26: 45 days , Plain , | U26: VSAN | W26: =G26-H26 -> 0
A27: I95-VPK-048 | B27: =VLOOKUP(A27,'25-VPI-I-095'!L:N,3,0) -> BOLT-3/4"x 2"LG-A325-HDG | C27: BOLT-3/4"x 2"LG-A325-HDG | D27: A325-HDG | E27: bolt full thread | F27: CÁI | G27: 80 | H27: =VLOOKUP(A27,'25-VPI-I-095'!L:DG,95,0) -> 80 | I27: N/A | J27: N/A | K27: N/A | L27: V | M27: 24000 | N27: 1920000 | O27: V | P27: 0.99 | Q27: N/A | R27: V | S27: 12000 | T27: có sẵn đủ , HDG , | U27: VSAN | W27: =G27-H27 -> 0
A28: I95-VPK-049 | B28: =VLOOKUP(A28,'25-VPI-I-095'!L:N,3,0) -> BOLT-3/4"x1 1/2"LG-A307-BLACK | C28: BOLT-3/4"x1 1/2"LG-A307-BLACK | D28: A307 | E28: bolt full thread | F28: CÁI | G28: 132 | H28: =VLOOKUP(A28,'25-VPI-I-095'!L:DG,95,0) -> 132 | I28: N/A | J28: N/A | K28: N/A | L28: V | M28: 16000 | N28: 2112000 | O28: V | P28: 0.61 | Q28: N/A | R28: V | S28: 15000 | T28: Giao sẵn 40pcs, còn lại 45 days , HDG , | U28: VSAN | W28: =G28-H28 -> 0
A29: I95-VPK-050 | B29: =VLOOKUP(A29,'25-VPI-I-095'!L:N,3,0) -> BOLT-3/4"x1 3/4"LG-A307-BLACK | C29: BOLT-3/4"x1 3/4"LG-A307-BLACK | D29: A307 | E29: bolt full thread | F29: CÁI | G29: 546 | H29: =VLOOKUP(A29,'25-VPI-I-095'!L:DG,95,0) -> 546 | I29: N/A | J29: N/A | K29: N/A | L29: V | M29: 16800 | N29: 9172800 | O29: V | P29: 0.74 | Q29: N/A | R29: V | S29: 20000 | T29: Giao sẵn 350pcs, còn lại 45 days , HDG , | U29: VSAN | W29: =G29-H29 -> 0
A30: I95-VPK-051 | B30: =VLOOKUP(A30,'25-VPI-I-095'!L:N,3,0) -> BOLT-3/4"x2 1/2"LG(1B+1N+2W)-A325N-HDG | C30: BOLT-3/4"x2 1/2"LG(1B+1N+2W)-A325N-HDG | D30: A325N/A563/F436 | E30: bolt full thread | F30: BỘ | G30: 132 | H30: =VLOOKUP(A30,'25-VPI-I-095'!L:DG,95,0) -> 132 | I30: N/A | J30: N/A | K30: N/A | L30: V | M30: 42400 | N30: 5596800 | O30: V | P30: 1.48 | Q30: N/A | R30: V | S30: 45000 | T30: có sẵn đủ , HDG , Bộ gồm 1 bolt+1 nut+ 2 flat washer | U30: VSAN | W30: =G30-H30 -> 0
A31: I95-VPK-052 | B31: =VLOOKUP(A31,'25-VPI-I-095'!L:N,3,0) -> BOLT-3/4"x2"LG-A307-BLACK | C31: BOLT-3/4"x2"LG-A307-BLACK | D31: A307 | E31: bolt full thread | F31: CÁI | G31: 260 | H31: =VLOOKUP(A31,'25-VPI-I-095'!L:DG,95,0) -> 260 | I31: N/A | J31: N/A | K31: N/A | L31: V | M31: 20000 | N31: 5200000 | O31: V | P31: 0.58 | Q31: N/A | R31: V | S31: 22000 | T31: 15 days , black oxided , | U31: VSAN | W31: =G31-H31 -> 0
A32: I95-VPK-053 | B32: =VLOOKUP(A32,'25-VPI-I-095'!L:N,3,0) -> BOLT-3/4"x3 3/4"LG(1B+1N+2W)-A25N-HDG | C32: BOLT-3/4"x3 3/4"LG(1B+1N+2W)-A25N-HDG | D32: A325N/A563/F436 | E32: bolt full thread | F32: BỘ | G32: 142 | H32: =VLOOKUP(A32,'25-VPI-I-095'!L:DG,95,0) -> 142 | I32: N/A | J32: N/A | K32: N/A | L32: V | M32: 56800 | N32: 8065600 | O32: V | P32: 1.76 | Q32: N/A | R32: V | S32: 55000 | T32: 60 days , HDG , Bộ gồm 1 bolt+1 nut+ 2 flat washer | U32: VSAN | W32: =G32-H32 -> 0
A33: I95-VPK-054 | B33: =VLOOKUP(A33,'25-VPI-I-095'!L:N,3,0) -> BOLT-3/8"x1 1/2"LG(1B+1N+2W)-A307-HDG | C33: BOLT-3/8"x1 1/2"LG(1B+1N+2W)-A307-HDG | D33: A307/A563/F436 | E33: bolt full thread | F33: BỘ | G33: 2772 | H33: =VLOOKUP(A33,'25-VPI-I-095'!L:DG,95,0) -> 2772 | I33: N/A | J33: N/A | K33: N/A | L33: V | M33: 9600 | N33: 26611200 | O33: V | P33: 0.61 | Q33: N/A | R33: V | S33: 87000 | T33: 15 days , HDG , giá bộ với đai ốc geomet, long đền nhúng, bolt nhúng nóng | U33: VSAN | W33: =G33-H33 -> 0
A34: I95-VPK-055 | B34: =VLOOKUP(A34,'25-VPI-I-095'!L:N,3,0) -> BOLT-5/8"x1 3/4"LG(1B+1N+1W+1TW)-A325N-HDG | C34: BOLT-5/8"x1 3/4"LG(1B+1N+1W+1TW)-A325N-HDG | D34: A325N/A563/F436 | E34: bolt full thread | F34: BỘ | G34: 6 | H34: =VLOOKUP(A34,'25-VPI-I-095'!L:DG,95,0) -> 6 | I34: N/A | J34: N/A | K34: N/A | L34: V | M34: 48000 | N34: 288000 | O34: V | P34: 1.06 | Q34: N/A | R34: V | S34: 28000 | T34: 60 days , HDG , Bộ gồm 1 bolt+1 nut+ 1 flat washer ++1 tapper washer DIN434 M16 | U34: VSAN | W34: =G34-H34 -> 0
A35: I95-VPK-056 | B35: =VLOOKUP(A35,'25-VPI-I-095'!L:N,3,0) -> BOLT-5/8"x1 3/4"LG(1B+1N+2W)-A325N-HDG | C35: BOLT-5/8"x1 3/4"LG(1B+1N+2W)-A325N-HDG | D35: A325N/A563/F436 | E35: bolt full thread | F35: BỘ | G35: 396 | H35: =VLOOKUP(A35,'25-VPI-I-095'!L:DG,95,0) -> 396 | I35: N/A | J35: N/A | K35: N/A | L35: V | M35: 26400 | N35: 10454400 | O35: V | P35: 0.94 | Q35: N/A | R35: V | S35: 27000 | T35: 60 days , HDG , Bộ gồm 1 bolt+1 nut+ 2 flat washer | U35: VSAN | W35: =G35-H35 -> 0
A36: I95-VPK-057 | B36: =VLOOKUP(A36,'25-VPI-I-095'!L:N,3,0) -> BOLT-5/8"x2 1/4"LG(1B+1N+1W+1TW)-A325N-HDG | C36: BOLT-5/8"x2 1/4"LG(1B+1N+1W+1TW)-A325N-HDG | D36: A325N/A563/F436 | E36: bolt full thread | F36: BỘ | G36: 820 | H36: =VLOOKUP(A36,'25-VPI-I-095'!L:DG,95,0) -> 820 | I36: N/A | J36: N/A | K36: N/A | L36: V | M36: 42400 | N36: 34768000 | O36: V | P36: 1.13 | Q36: N/A | R36: V | S36: 29000 | T36: 60 days , HDG , Bộ gồm 1 bolt+1 nut+ 1 flat washer ++1 tapper washer DIN434 M16 | U36: VSAN | W36: =G36-H36 -> 0
A37: I95-VPK-058 | B37: =VLOOKUP(A37,'25-VPI-I-095'!L:N,3,0) -> BOLT-5/8"x2 1/4"LG(1B+1N+2W)-A325N-HDG | C37: BOLT-5/8"x2 1/4"LG(1B+1N+2W)-A325N-HDG | D37: A325N/A563/F436 | E37: bolt full thread | F37: BỘ | G37: 36 | H37: =VLOOKUP(A37,'25-VPI-I-095'!L:DG,95,0) -> 36 | I37: N/A | J37: N/A | K37: N/A | L37: V | M37: 28800 | N37: 1036800 | O37: V | P37: 1.22 | Q37: N/A | R37: V | S37: 27000 | T37: 60 days , HDG , Bộ gồm 1 bolt+1 nut+ 2 flat washer | U37: VSAN | W37: =G37-H37 -> 0
... A60: I95-VPK-081 | B60: =VLOOKUP(A60,'25-VPI-I-095'!L:N,3,0) -> BOLT-7/8"x4"LG(1B+1N+2W)-A325N-HDG | C60: BOLT-7/8"x4"LG(1B+1N+2W)-A325N-HDG | D60: A325N/A563/F436 | E60: bolt full thread | F60: BỘ | G60: 54 | H60: =VLOOKUP(A60,'25-VPI-I-095'!L:DG,95,0) -> 54 | I60: N/A | J60: N/A | K60: N/A | L60: V | M60: 77600 | N60: 4190400 | O60: V | P60: 2.72 | Q60: N/A | R60: V | S60: 95000 | T60: 60 days , HDG , Bộ gồm 1 bolt+1 nut+ 2 flat washer | U60: VSAN | W60: =G60-H60 -> 0
A61: I95-VPK-082 | B61: =VLOOKUP(A61,'25-VPI-I-095'!L:N,3,0) -> NUT-1/2"-A563-BLACK | C61: NUT-1/2"-A563-BLACK | D61: A563 | F61: CÁI | G61: 634 | H61: =VLOOKUP(A61,'25-VPI-I-095'!L:DG,95,0) -> 634 | I61: N/A | J61: N/A | K61: N/A | L61: V | M61: 3360 | N61: 2130240 | O61: V | P61: 0.07 | Q61: N/A | R61: V | S61: 5200 | T61: 15 ngày có đủ , black oxided , Offer A194 2H thay vì A563black | U61: VSAN | W61: =G61-H61 -> 0
A62: I95-VPK-083 | B62: =VLOOKUP(A62,'25-VPI-I-095'!L:N,3,0) -> NUT-1/2"-A563DH-HDG | C62: NUT-1/2"-A563DH-HDG | D62: A563DH-HDG | F62: CÁI | G62: 318 | H62: =VLOOKUP(A62,'25-VPI-I-095'!L:DG,95,0) -> 318 | I62: N/A | J62: N/A | K62: N/A | L62: V | M62: 4000 | N62: 1272000 | O62: V | P62: 0.14 | Q62: N/A | R62: V | S62: 5000 | T62: có sẵn đủ , HDG , | U62: VSAN | W62: =G62-H62 -> 0
A63: I95-VPK-084 | B63: =VLOOKUP(A63,'25-VPI-I-095'!L:N,3,0) -> NUT-3/4"-A194-A479-TP309S | C63: NUT-3/4"-A194-A479-TP309S | D63: A194-A479-TP309S | E63: 310S | F63: CÁI | G63: 40 | H63: =VLOOKUP(A63,'25-VPI-I-095'!L:DG,95,0) -> 40 | I63: N/A | J63: N/A | K63: N/A | L63: V | M63: 64000 | N63: 2560000 | O63: V | P63: 4.69 | Q63: N/A | R63: X | S63: N/A | T63: N/A | U63: VSAN | W63: =G63-H63 -> 0
A64: I95-VPK-085 | B64: =VLOOKUP(A64,'25-VPI-I-095'!L:N,3,0) -> NUT-3/4"-A194-A479-TP310S | C64: NUT-3/4"-A194-A479-TP310S | D64: A194-A479-TP310S | F64: CÁI | G64: 40 | H64: =VLOOKUP(A64,'25-VPI-I-095'!L:DG,95,0) -> 40 | I64: N/A | J64: N/A | K64: N/A | L64: V | M64: 64000 | N64: 2560000 | O64: V | P64: 4.69 | Q64: N/A | R64: X | S64: N/A | T64: N/A | U64: VSAN | W64: =G64-H64 -> 0
A65: I95-VPK-086 | B65: =VLOOKUP(A65,'25-VPI-I-095'!L:N,3,0) -> NUT-3/4"-A194-GR8 | C65: NUT-3/4"-A194-GR8 | D65: A194-GR8 | F65: CÁI | G65: 160 | H65: =VLOOKUP(A65,'25-VPI-I-095'!L:DG,95,0) -> 160 | I65: N/A | J65: N/A | K65: N/A | L65: V | M65: 20000 | N65: 3200000 | O65: V | P65: 2.86 | Q65: N/A | R65: V | S65: 19000 | T65: có sẵn đủ , Plain , | U65: VSAN | W65: =G65-H65 -> 0
A66: I95-VPK-087 | B66: =VLOOKUP(A66,'25-VPI-I-095'!L:N,3,0) -> NUT-3/4"-A563-HDG | C66: NUT-3/4"-A563-HDG | D66: A563-HDG | F66: CÁI | G66: 1084 | H66: =VLOOKUP(A66,'25-VPI-I-095'!L:DG,95,0) -> 1084 | I66: N/A | J66: N/A | K66: N/A | L66: V | M66: 11200 | N66: 12140800 | O66: V | P66: 0.1 | Q66: N/A | R66: V | S66: 12000 | T66: có sẵn đủ , HDG , marking 2H DH | U66: VSAN | W66: =G66-H66 -> 0
A67: I95-VPK-088 | B67: =VLOOKUP(A67,'25-VPI-I-095'!L:N,3,0) -> WASHER-1/2"-F436-BLACK | C67: WASHER-1/2"-F436-BLACK | D67: F436 | F67: CÁI | G67: 634 | H67: =VLOOKUP(A67,'25-VPI-I-095'!L:DG,95,0) -> 634 | I67: N/A | J67: N/A | K67: N/A | L67: V | M67: 1200 | N67: 760800 | O67: V | P67: 0.06 | Q67: N/A | R67: V | S67: 3500 | T67: 15 ngày có đủ , black oxided , | U67: VSAN | W67: =G67-H67 -> 0
A68: I95-VPK-089 | B68: =VLOOKUP(A68,'25-VPI-I-095'!L:N,3,0) -> WASHER-1/2"-F436-HDG | C68: WASHER-1/2"-F436-HDG | D68: F436-HDG | F68: CÁI | G68: 318 | H68: =VLOOKUP(A68,'25-VPI-I-095'!L:DG,95,0) -> 318 | I68: N/A | J68: N/A | K68: N/A | L68: V | M68: 1600 | N68: 508800 | O68: V | P68: 0.065 | Q68: N/A | R68: V | S68: 3500 | T68: có sẵn đủ , HDG , | U68: VSAN | W68: =G68-H68 -> 0
A69: I95-VPK-090 | B69: =VLOOKUP(A69,'25-VPI-I-095'!L:N,3,0) -> WASHER-3/4"-A240-TP304 | C69: WASHER-3/4"-A240-TP304 | D69: A240-TP304 | E69: bản vẽ | F69: CÁI | G69: 318 | H69: =VLOOKUP(A69,'25-VPI-I-095'!L:DG,95,0) -> 318 | I69: N/A | J69: N/A | K69: N/A | L69: V | M69: 3600 | N69: 1144800 | O69: V | P69: 0.27 | Q69: N/A | R69: V | S69: 3000 | T69: có sẵn đủ , Plain , | U69: VSAN | W69: =G69-H69 -> 0
A70: I95-VPK-091 | B70: =VLOOKUP(A70,'25-VPI-I-095'!L:N,3,0) -> WASHER-3/4"-A240-TP309S | C70: WASHER-3/4"-A240-TP309S | D70: A240-TP309S | E70: bản vẽ | F70: CÁI | G70: 80 | H70: =VLOOKUP(A70,'25-VPI-I-095'!L:DG,95,0) -> 80 | I70: N/A | J70: N/A | K70: N/A | L70: V | M70: 120000 | N70: 9600000 | O70: V | P70: 1.24 | Q70: N/A | R70: X | S70: N/A | T70: N/A | U70: VSAN | W70: =G70-H70 -> 0
A71: I95-VPK-092 | B71: =VLOOKUP(A71,'25-VPI-I-095'!L:N,3,0) -> WASHER-3/4"-A240-TP310S | C71: WASHER-3/4"-A240-TP310S | D71: A240-TP310S | E71: bản vẽ | F71: CÁI | G71: 80 | H71: =VLOOKUP(A71,'25-VPI-I-095'!L:DG,95,0) -> 80 | I71: N/A | J71: N/A | K71: N/A | L71: V | M71: 120000 | N71: 9600000 | O71: V | P71: 1.24 | Q71: N/A | R71: X | S71: N/A | T71: N/A | U71: VSAN | W71: =G71-H71 -> 0
A72: I95-VPK-093 | B72: =VLOOKUP(A72,'25-VPI-I-095'!L:N,3,0) -> WASHER-3/4"-F436-HDG | C72: WASHER-3/4"-F436-HDG | D72: F436-HDG | F72: CÁI | G72: 952 | H72: =VLOOKUP(A72,'25-VPI-I-095'!L:DG,95,0) -> 952 | I72: N/A | J72: N/A | K72: N/A | L72: V | M72: 2800 | N72: 2665600 | O72: V | P72: 0.11 | Q72: N/A | R72: V | S72: 6800 | T72: có sẵn đủ , HDG , | U72: VSAN | W72: =G72-H72 -> 0
A73: I95-VPK-094 | B73: =VLOOKUP(A73,'25-VPI-I-095'!L:N,3,0) -> STUD BOLT FULL THREAD-5/8"DIAx7 1/4"LG( 1 STUD+2 NUT)-A193B8 | C73: STUD BOLT FULL THREAD-5/8"DIAx7 1/4"LG( 1 STUD+2 NUT)-A193B8 | D73: A193B8/A194-8 | E73: bản vẽ | F73: BỘ | G73: 344 | H73: =VLOOKUP(A73,'25-VPI-I-095'!L:DG,95,0) -> 344 | I73: N/A | J73: N/A | K73: N/A | L73: V | M73: 96000 | N73: 33024000 | O73: V | P73: 6.51 | Q73: N/A | R73: V | S73: 84000 | T73: 45-60 days , Plain , Tồn 190 bộ giao trong 15 days | U73: VSAN | W73: =G73-H73 -> 0
A74: I95-VPK-104 | B74: =VLOOKUP(A74,'25-VPI-I-095'!L:N,3,0) -> BOLT-1 1/2"x4 1/4"LG-A193-B7-HDG | C74: BOLT-1 1/2"x4 1/4"LG-A193-B7-HDG | D74: A193-B7 | E74: bolt full thread | F74: CÁI | G74: 80 | H74: =VLOOKUP(A74,'25-VPI-I-095'!L:DG,95,0) -> 80 | I74: N/A | J74: N/A | K74: N/A | L74: V | M74: 229600 | N74: 18368000 | O74: V | P74: N/A | Q74: N/A | R74: X | S74: N/A | T74: N/A | U74: VSAN
A75: I95-VPK-105 | B75: =VLOOKUP(A75,'25-VPI-I-095'!L:N,3,0) -> BOLT-1 1/8"x4 1/2"LG(1B+1N+1W+1DTIW)-A490-GEOMET | C75: BOLT-1 1/8"x4 1/2"LG(1B+1N+1W+1DTIW)-A490-GEOMET | D75: A490/A563/F436/F959 | E75: bolt full thread | F75: BỘ | G75: 424 | H75: =VLOOKUP(A75,'25-VPI-I-095'!L:DG,95,0) -> 424 | I75: N/A | J75: N/A | K75: N/A | L75: V | M75: 239000 | N75: 101336000 | O75: V | P75: N/A | Q75: N/A | R75: X | S75: N/A | T75: N/A | U75: VSAN
A76: I95-VPK-106 | B76: =VLOOKUP(A76,'25-VPI-I-095'!L:N,3,0) -> BOLT-1 1/8"x4"LG(1B+1N+1W+1DTIW)-A490-GEOMET | C76: BOLT-1 1/8"x4"LG(1B+1N+1W+1DTIW)-A490-GEOMET | D76: A490/A563/F436/F959 | E76: bolt full thread | F76: BỘ | G76: 494 | H76: =VLOOKUP(A76,'25-VPI-I-095'!L:DG,95,0) -> 494 | I76: N/A | J76: N/A | K76: N/A | L76: V | M76: 228000 | N76: 112632000 | O76: V | P76: N/A | Q76: N/A | R76: X | S76: N/A | T76: N/A | U76: VSAN
A77: I95-VPK-107 | B77: =VLOOKUP(A77,'25-VPI-I-095'!L:N,3,0) -> BOLT-3/4"x2 1/2"LG(1B+1N)-A193B7-HDG | C77: BOLT-3/4"x2 1/2"LG(1B+1N)-A193B7-HDG | D77: A193-B7/A194-7 | E77: bolt full thread | F77: BỘ | G77: 28 | H77: =VLOOKUP(A77,'25-VPI-I-095'!L:DG,95,0) -> 28 | I77: N/A | J77: N/A | K77: N/A | L77: V | M77: 60000 | N77: 1680000 | O77: V | P77: N/A | Q77: N/A | R77: X | S77: N/A | T77: N/A | U77: VSAN
A78: I95-VPK-108 | B78: =VLOOKUP(A78,'25-VPI-I-095'!L:N,3,0) -> BOLT-3/4"x2 3/4"LG-FULL THREAD-A193B7-HDG | C78: BOLT-3/4"x2 3/4"LG-FULL THREAD-A193B7-HDG | D78: A193-B7/A194-7 | E78: bolt full thread | F78: BỘ | G78: 62 | H78: =VLOOKUP(A78,'25-VPI-I-095'!L:DG,95,0) -> 62 | I78: N/A | J78: N/A | K78: N/A | L78: V | M78: 62400 | N78: 3868800 | O78: V | P78: N/A | Q78: N/A | R78: X | S78: N/A | T78: N/A | U78: VSAN
A79: I95-VPK-109 | B79: =VLOOKUP(A79,'25-VPI-I-095'!L:N,3,0) -> BOLT-3/4"x3 1/2"LG(1B+1N)-A193B7-HDG | C79: BOLT-3/4"x3 1/2"LG(1B+1N)-A193B7-HDG | D79: A193-B7/A194-7 | E79: bolt full thread | F79: BỘ | G79: 194 | H79: =VLOOKUP(A79,'25-VPI-I-095'!L:DG,95,0) -> 194 | I79: N/A | J79: N/A | K79: N/A | L79: V | M79: 65000 | N79: 12610000 | O79: V | P79: N/A | Q79: N/A | R79: X | S79: N/A | T79: N/A | U79: VSAN
A80: I95-VPK-110 | B80: =VLOOKUP(A80,'25-VPI-I-095'!L:N,3,0) -> BOLT-5/8"x1 3/4"LG-A193-B7-HDG | C80: BOLT-5/8"x1 3/4"LG-A193-B7-HDG | D80: A193-B7 | E80: bolt full thread | F80: CÁI | G80: 582 | H80: =VLOOKUP(A80,'25-VPI-I-095'!L:DG,95,0) -> 582 | I80: N/A | J80: N/A | K80: N/A | L80: V | M80: 29000 | N80: 16878000 | O80: V | P80: N/A | Q80: N/A | R80: X | S80: N/A | T80: N/A | U80: VSAN
A81: I95-VPK-111 | B81: =VLOOKUP(A81,'25-VPI-I-095'!L:N,3,0) -> BOLT-5/8"x3"LG(1B+1N)-A193B7-HDG | C81: BOLT-5/8"x3"LG(1B+1N)-A193B7-HDG | D81: A193-B7/A194-7 | E81: bolt full thread | F81: BỘ | G81: 1004 | H81: =VLOOKUP(A81,'25-VPI-I-095'!L:DG,95,0) -> 1004 | I81: N/A | J81: N/A | K81: N/A | L81: V | M81: 39000 | N81: 39156000 | O81: V | P81: N/A | Q81: N/A | R81: X | S81: N/A | T81: N/A | U81: VSAN
A82: I95-VPK-112 | B82: =VLOOKUP(A82,'25-VPI-I-095'!L:N,3,0) -> BOLT-5/8"x3"LG-A193-B7-HDG | C82: BOLT-5/8"x3"LG-A193-B7-HDG | D82: A193-B7 | E82: bolt full thread | F82: CÁI | G82: 160 | H82: =VLOOKUP(A82,'25-VPI-I-095'!L:DG,95,0) -> 160 | I82: N/A | J82: N/A | K82: N/A | L82: V | M82: 24800 | N82: 3968000 | O82: V | P82: N/A | Q82: N/A | R82: X | S82: N/A | T82: N/A | U82: VSAN
A83: I95-VPK-113 | B83: =VLOOKUP(A83,'25-VPI-I-095'!L:N,3,0) -> NUT-1 1/2"-A194-2H-HDG | C83: NUT-1 1/2"-A194-2H-HDG | D83: A194-2H | F83: CÁI | G83: 80 | H83: =VLOOKUP(A83,'25-VPI-I-095'!L:DG,95,0) -> 80 | I83: N/A | J83: N/A | K83: N/A | L83: V | M83: 74400 | N83: 5952000 | O83: V | P83: N/A | Q83: N/A | R83: X | S83: N/A | T83: N/A | U83: VSAN
A84: I95-VPK-114 | B84: =VLOOKUP(A84,'25-VPI-I-095'!L:N,3,0) -> NUT-3/4"-A194GR7-HDG | C84: NUT-3/4"-A194GR7-HDG | D84: A194-7 | F84: CÁI | G84: 124 | H84: =VLOOKUP(A84,'25-VPI-I-095'!L:DG,95,0) -> 124 | I84: N/A | J84: N/A | K84: N/A | L84: V | M84: 16800 | N84: 2083200 | O84: V | P84: N/A | Q84: N/A | R84: X | S84: N/A | T84: N/A | U84: VSAN
A85: I95-VPK-115 | B85: =VLOOKUP(A85,'25-VPI-I-095'!L:N,3,0) -> NUT-5/8"-A194-2H-HDG | C85: NUT-5/8"-A194-2H-HDG | D85: A194-2H | F85: CÁI | G85: 740 | H85: =VLOOKUP(A85,'25-VPI-I-095'!L:DG,95,0) -> 740 | I85: N/A | J85: N/A | K85: N/A | L85: V | M85: 6800 | N85: 5032000 | O85: V | P85: N/A | Q85: N/A | R85: X | S85: N/A | T85: N/A | U85: VSAN
A86: I95-VPK-116 | B86: =VLOOKUP(A86,'25-VPI-I-095'!L:N,3,0) -> WASHER-1 1/2"x3"OD-F436-HDG | C86: WASHER-1 1/2"x3"OD-F436-HDG | D86: F436 | F86: CÁI | G86: 80 | H86: =VLOOKUP(A86,'25-VPI-I-095'!L:DG,95,0) -> 80 | I86: N/A | J86: N/A | K86: N/A | L86: V | M86: 16800 | N86: 1344000 | O86: V | P86: N/A | Q86: N/A | R86: X | S86: N/A | T86: N/A | U86: VSAN
A87: I95-VPK-117 | B87: =VLOOKUP(A87,'25-VPI-I-095'!L:N,3,0) -> WASHER-3/4"-SUS304 | C87: WASHER-3/4"-SUS304 | D87: SUS304 | F87: CÁI | G87: 62 | H87: =VLOOKUP(A87,'25-VPI-I-095'!L:DG,95,0) -> 62 | I87: N/A | J87: N/A | K87: N/A | L87: V | M87: 4400 | N87: 272800 | O87: V | P87: N/A | Q87: N/A | R87: X | S87: N/A | T87: N/A | U87: VSAN
B88: Xếp hạng | M88: 1
A89: Ghi chú: PTM tiến hàng mua sắm để đảm bảo tiến độ
A90: NGƯỜI ĐỀ NGHỊ/ RECOMMENDATION BY: | D90: NGƯỜI KIỂM TRA/ DEPARTMENT HEAD CHECK BY: | J90: APPROVED BY: PHÊ DUYỆT
I91: Nguyễn Quang Vinh | L91: Hoàng Ngọc Bằng | U91: Đoàn Văn Toàn

Sheet Vật tư gasket Kien dung
A1: BID ANALYSIS - GIẢI TRÌNH MUA SẮM/ĐẤU THẦU
A3: Project | B3: PROJECT No/ Dự án: 25-VPI-I-095
A4: Dự án
A5: Subject | B5: Cung cấp vật tư gasket Kiên Dũng 26-1-2026
A6: Chủ đề
A8: No. | B8: CONTENT | C8: Phạm vi công việc | G8: Dự toán | J8: Đã mua | K8: Đơn vị cung cấp chào giá (vnđ) | N8: Lựa chọn | O8: Ghi chú
A9: Item | B9: Description/ Chi tiết | C9: Profile/ Vật tư | D9: Grade/ Mác vật liệu | E9: Grade/ Mác vật liệu mua | F9: Số lượng Mua (M) | G9: Khối lượng/ Số lượng | H9: Đơn giá (vnd) | I9: Thành tiền (vnd) | J9: Thành tiền (vnd) | K9: Kiên Dũng
K10: Phạm vi | L10: Đơn giá (VND) | M10: Thành Tiền (Chưa có VAT)
A11: Tổng | B11: Bolt-Material / Vật tư bulong, phụ kiện | G11: N/A | H11: N/A | I11: ='Tổng hợp'!K23 -> 9.374355e+09 | J11: ='Tổng hợp'!J23+'Tổng hợp'!J22 -> 22324242648 | M11: =SUM(M12:M17) -> 10152000 | O11: =I11-J11-M11 -> -1.296004e+10
A12: I95-VPK-118 | B12: 2_1/2"_GASKET_#150_SORF-ASME B16.21 | C12: 2_1/2"_GASKET_#150_SORF-ASME B16.21-THICK 3mm | D12: "Spitmaan" Style AF 120 Non-Metallic Blue | E12: Vật liệu: AF 120 | F12: 64 | G12: N/A | H12: N/A | I12: N/A | J12: N/A | K12: V | L12: 28000 | M12: =L12*F12 -> 1792000 | N12: Kiên Dũng | P12: =CONCATENATE(C12," = ",F12," Cái ",E12) -> 2_1/2"_GASKET_#150_SORF-ASME B16.21-THICK 3mm = 64 Cái Vật liệu: AF 120
A13: I95-VPK-119 | B13: 3"_GASKET_#150_SORF-ASME B16.21 | C13: 3"_GASKET_#150_SORF-ASME B16.21-THICK 3mm | D13: "Spitmaan" Style AF 120 Non-Metallic Blue | E13: Vật liệu: AF 120 | F13: 164 | G13: N/A | H13: N/A | I13: N/A | J13: N/A | K13: V | L13: 30000 | M13: =L13*F13 -> 4920000 | N13: Kiên Dũng | P13: =CONCATENATE(C13," = ",F13," Cái ",E13) -> 3"_GASKET_#150_SORF-ASME B16.21-THICK 3mm = 164 Cái Vật liệu: AF 120
A14: I95-VPK-120 | B14: 4"_GASKET_#150_SORF-ASME B16.21 | C14: 4"_GASKET_#150_SORF-ASME B16.21-THICK 3mm | D14: "Spitmaan" Style AF 120 Non-Metallic Blue | E14: Vật liệu: AF 120 | F14: 18 | G14: N/A | H14: N/A | I14: N/A | J14: N/A | K14: V | L14: 52000 | M14: =L14*F14 -> 936000 | N14: Kiên Dũng | P14: =CONCATENATE(C14," = ",F14," Cái ",E14) -> 4"_GASKET_#150_SORF-ASME B16.21-THICK 3mm = 18 Cái Vật liệu: AF 120
A15: I95-VPK-121 | B15: 6"_GASKET_#150_SORF-ASME B16.21 | C15: 6"_GASKET_#150_SORF-ASME B16.21-THICK 3mm | D15: "Spitmaan" Style AF 120 Non-Metallic Blue | E15: Vật liệu: AF 120 | F15: 14 | G15: N/A | H15: N/A | I15: N/A | J15: N/A | K15: V | L15: 66000 | M15: =L15*F15 -> 924000 | N15: Kiên Dũng | P15: =CONCATENATE(C15," = ",F15," Cái ",E15) -> 6"_GASKET_#150_SORF-ASME B16.21-THICK 3mm = 14 Cái Vật liệu: AF 120
A16: I95-VPK-122 | B16: 8"_GASKET_#150_SORF-ASME B16.21 | C16: 8"_GASKET_#150_SORF-ASME B16.21-THICK 3mm | D16: "Spitmaan" Style AF 120 Non-Metallic Blue | E16: Vật liệu: AF 120 | F16: 8 | G16: N/A | H16: N/A | I16: N/A | J16: N/A | K16: V | L16: 115000 | M16: =L16*F16 -> 920000 | N16: Kiên Dũng | P16: =CONCATENATE(C16," = ",F16," Cái ",E16) -> 8"_GASKET_#150_SORF-ASME B16.21-THICK 3mm = 8 Cái Vật liệu: AF 120
A17: I95-VPK-123 | B17: GASKET PL3XOD711XID635 | C17: GASKET PL3 X OD711 X ID635 | D17: "Spitmaan" Style AF 120 Non-Metallic Blue | E17: Vật liệu: AF 120 | F17: 2 | G17: N/A | H17: N/A | I17: N/A | J17: N/A | K17: V | L17: 330000 | M17: =L17*F17 -> 660000 | N17: Kiên Dũng | P17: =CONCATENATE(C17," = ",F17," Cái ",E17) -> GASKET PL3 X OD711 X ID635 = 2 Cái Vật liệu: AF 120
B18: Xếp hạng | L18: 1
A19: Ghi chú: PTM tiến hàng mua sắm để đảm bảo tiến độ
A20: NGƯỜI ĐỀ NGHỊ/ RECOMMENDATION BY: | D20: NGƯỜI KIỂM TRA/ DEPARTMENT HEAD CHECK BY: | I20: APPROVED BY: PHÊ DUYỆT
H21: Nguyễn Quang Vinh | K21: Hoàng Ngọc Bằng | N21: Đoàn Văn Toàn

Sheet Vật tư vit 095-FUJIMOTO SANGYO 
A1: BID ANALYSIS - GIẢI TRÌNH MUA SẮM/ĐẤU THẦU
A3: Project | B3: PROJECT No/ Dự án: 25-VPI-I-095
A4: Dự án
A5: Subject | B5: Cung cấp vật tư vít FUJIMOTO SANGYO VIETNAM CO., LTD
A6: Chủ đề
A8: No. | B8: CONTENT | F8: Dự toán | I8: Đã mua | J8: Đơn vị cung cấp chào giá (vnđ) | M8: Đơn vị cung cấp chào giá (vnđ) | P8: Lựa chọn | Q8: Ghi chú
A9: Item | B9: Description/ Chi tiết | C9: ĐVT | D9: Số lượng (PR) (Cái( | E9: Số lượng mua (Cái) | F9: Khối lượng/ Số lượng | G9: Đơn giá (vnd) | H9: Thành tiền (vnd) | I9: Thành tiền (vnd) | J9: FUJIMOTO SANGYO VIETNAM CO., LTD | M9: VSAN/ HOÀNG HÀ
J10: Phạm vi | K10: Đơn giá (VND) | L10: Thành Tiền (Chưa có VAT) | M10: Phạm vi | N10: Đơn giá (VND) | O10: Thành Tiền (Chưa có VAT)
A11: Tổng | F11: N/A | G11: N/A | H11: ='Tổng hợp'!K23 -> 9.374355e+09 | I11: ='Tổng hợp'!J23+'Tổng hợp'!J22 -> 22324242648 | L11: =SUM(L12:L12) -> 7500000 | O11: =SUM(O12:O12) -> 0 | Q11: =H11-I11-L11 -> -1.2957388e+10
A12: I95-VPK-029 | B12: Vít tự khoan đầu lục giác 6.3x38 Din7504K . Mạ Dacromet | C12: Cái | D12: 1304 | E12: 2500 | F12: N/A | G12: N/A | J12: V | K12: 3000 | L12: =K12*E12 -> 7500000 | M12: X | N12: N/A | O12: N/A | P12: FUJIMOTO SANGYO VIETNAM CO., LTD
B13: Xếp hạng | K13: 1 | N13: 2
A14: Ghi chú: PTM tiến hàng mua sắm để đảm bảo tiến độ
A15: NGƯỜI ĐỀ NGHỊ/ RECOMMENDATION BY: | C15: NGƯỜI KIỂM TRA/ DEPARTMENT HEAD CHECK BY: | H15: APPROVED BY: PHÊ DUYỆT
G16: Nguyễn Quang Vinh | J16: Hoàng Ngọc Bằng | P16: Đoàn Văn Toàn

Sheet Vật tư SUN COMMERCIAL
A1: BID ANALYSIS - GIẢI TRÌNH MUA SẮM/ĐẤU THẦU
A3: Project | B3: PROJECT No/ Dự án: 25-VPI-I-095
A4: Dự án
A5: Subject | B5: Cung cấp vật tư keo dính chống cháy chịu nhiệt SUN COMMERCIAL 27-1-2026
A6: Chủ đề
A8: No. | B8: CONTENT | E8: Dự toán | H8: Đã mua | I8: Đơn vị cung cấp chào giá (vnđ) | L8: Lựa chọn | M8: Ghi chú
A9: Item | B9: Description/ Chi tiết | C9: ĐVT | D9: Số lượng | E9: Khối lượng/ Số lượng | F9: Đơn giá (vnd) | G9: Thành tiền (vnd) | H9: Thành tiền (vnd) | I9: SUN COMMERCIAL
I10: Phạm vi | J10: Đơn giá (VND/TUÝP) | K10: Thành Tiền (Chưa có 8% VAT)
A11: Tổng | E11: N/A | F11: N/A | G11: ='Tổng hợp'!K23 -> 9.374355e+09 | H11: ='Tổng hợp'!J23+'Tổng hợp'!J22 -> 22324242648 | K11: =SUM(K12:K12) -> 9900000 | M11: =G11-H11-K11 -> -1.2959788e+10
A12: I95-VPK-027 | B12: Keo tạo gioăng - 81409, 11 oz,permatex® #26 high temp. Rtv siliconegasket maker | C12: Cái | D12: 33 | E12: N/A | F12: N/A | I12: V | J12: 300000 | K12: =J12*D12 -> 9900000 | L12: SUN COMMERCIAL
B13: Xếp hạng | J13: 1
A14: Ghi chú: PTM tiến hàng mua sắm để đảm bảo tiến độ
A15: NGƯỜI ĐỀ NGHỊ/ RECOMMENDATION BY: | C15: NGƯỜI KIỂM TRA/ DEPARTMENT HEAD CHECK BY: | G15: APPROVED BY: PHÊ DUYỆT
F16: Nguyễn Quang Vinh | I16: Hoàng Ngọc Bằng | L16: Đoàn Văn Toàn

Sheet Vật tư keo 095
A1: BID ANALYSIS - GIẢI TRÌNH MUA SẮM/ĐẤU THẦU
A3: Project | B3: PROJECT No/ Dự án: 25-VPI-I-095
A4: Dự án
A5: Subject | B5: Cung cấp vật tư keo dính chống cháy chịu nhiệt
A6: Chủ đề
A8: No. | B8: CONTENT | E8: Dự toán | H8: Đã mua | I8: Đơn vị cung cấp chào giá (vnđ) | L8: Lựa chọn | M8: Ghi chú
A9: Item | B9: Description/ Chi tiết | C9: ĐVT | D9: Số lượng | E9: Khối lượng/ Số lượng | F9: Đơn giá (vnd) | G9: Thành tiền (vnd) | H9: Thành tiền (vnd) | I9: VSAN
I10: Phạm vi | J10: Đơn giá (VND) | K10: Thành Tiền (Chưa có VAT)
A11: Tổng | E11: N/A | F11: N/A | G11: ='Tổng hợp'!K23 -> 9.374355e+09 | H11: ='Tổng hợp'!J23+'Tổng hợp'!J22 -> 22324242648 | K11: =SUM(K12:K12) -> 71520000 | M11: =G11-H11-K11 -> -1.3021408e+10
A12: I95-VPK-027 | B12: HIGH TEMPERATURE ADHESIVE -20 ĐỘ C ĐẾN 1250 ĐỘ C | C12: Cái | D12: 24 | E12: N/A | F12: N/A | I12: V | J12: 2980000 | K12: =J12*D12 -> 71520000 | L12: VSAN
B13: Xếp hạng | J13: 1
A14: Ghi chú: PTM tiến hàng mua sắm để đảm bảo tiến độ
A15: NGƯỜI ĐỀ NGHỊ/ RECOMMENDATION BY: | C15: NGƯỜI KIỂM TRA/ DEPARTMENT HEAD CHECK BY: | G15: APPROVED BY: PHÊ DUYỆT
F16: Nguyễn Quang Vinh | I16: Hoàng Ngọc Bằng | L16: Đoàn Văn Toàn

Sheet Vật tư phụ VSAN 4
A1: BID ANALYSIS - GIẢI TRÌNH MUA SẮM/ĐẤU THẦU
A3: Project | B3: PROJECT No/ Dự án: 25-VPI-I-095
A4: Dự án
A5: Subject | B5: Cung cấp vật tư phụ kiện bu lông/ đinh bảo ôn
A6: Chủ đề
A8: No. | B8: CONTENT | C8: Phạm vi công việc | H8: Dự toán | K8: Đã mua | L8: Đơn vị cung cấp chào giá (vnđ) | O8: Ghi chú
A9: Item | B9: Description/ Chi tiết | C9: Profile/ Vật tư | D9: Grade/ Mác vật liệu | E9: Số lượng PR | F9: ĐVT | G9: Số lượng mua | H9: Khối lượng/ Số lượng | I9: Đơn giá (vnd) | J9: Thành tiền (vnd) | K9: Thành tiền (vnd) | L9: VSAN
L10: Phạm vi | M10: Đơn giá (VND) | N10: Thành Tiền (Không có VAT)
A11: Tổng | B11: Vật tư phụ kiện | H11: N/A | I11: N/A | J11: ='DT03 (TM)'!G19 -> 8.3322017e+09 | K11: ='Tổng hợp'!J22+'Tổng hợp'!J23 -> 22324242648 | N11: =SUM(N13:N18) -> 40440000 | O11: =J11-K11-N11 -> -1.4032481e+10
A12: Insulation-Material / Vật tư bảo ôn
A13: I95-VTC04-054 | B13: =VLOOKUP(A13,'25-VPI-I-095'!L:N,3,0) -> STUD-RB12X200-REN M12X1.75- 38mm-SUS304 | C13: ROUND WASHER OD76XID14X2.6mm-SUS304 | D13: =VLOOKUP(A13,'25-VPI-I-095'!L:R,4,0) -> JIS G4303-SUS304 | E13: =VLOOKUP(A13,'25-VPI-I-095'!L:DH,91,0) -> 0 | F13: Cái | G13: 28 | H13: N/A | I13: N/A | L13: V | M13: 35000 | N13: =M13*G13 -> 980000 | O13: Chọn mua VSAN
A14: I95-VTC04-055 | B14: =VLOOKUP(A14,'25-VPI-I-095'!L:N,3,0) -> STUD-RB12X534-REN M12X1.75- 38mm-SUS309S | C14: STUD-RB10X152-REN M10X1.5- 32mm-SUS304 | D14: =VLOOKUP(A14,'25-VPI-I-095'!L:R,4,0) -> SUS309S | E14: =VLOOKUP(A14,'25-VPI-I-095'!L:DH,91,0) -> 0 | F14: Cái | G14: 28 | H14: N/A | I14: N/A | L14: V | M14: 185000 | N14: =M14*G14 -> 5180000
A15: Bolt-Material / Vật tư bulong, phụ kiện
A16: I95-VPK-030 | B16: =VLOOKUP(A16,'25-VPI-I-095'!L:N,3,0) -> BOLT-M36X130-A193-B7-HDG | C16: CLEVIS PIN Ø12x52-DIN 1444-MẠ ĐIỆN PHÂN | D16: =VLOOKUP(A16,'25-VPI-I-095'!L:R,4,0) -> A193B7-HDG | E16: =VLOOKUP(A16,'25-VPI-I-095'!L:DH,91,0) -> 0 | F16: Cái | G16: 105 | H16: N/A | I16: N/A | L16: V | M16: 224000 | N16: =M16*G16 -> 23520000
A17: I95-VPK-031 | B17: =VLOOKUP(A17,'25-VPI-I-095'!L:N,3,0) -> NUT-M36-A194-7-HDG | C17: COTTER PIN Ø3.2x25L-DIN 94- MẠ ĐIỆN PHÂN | D17: =VLOOKUP(A17,'25-VPI-I-095'!L:R,4,0) -> A194-7-HDG | E17: =VLOOKUP(A17,'25-VPI-I-095'!L:DH,91,0) -> 0 | F17: Cái | G17: 105 | H17: N/A | I17: N/A | L17: V | M17: 72000 | N17: =M17*G17 -> 7560000
A18: I95-VPK-032 | B18: =VLOOKUP(A18,'25-VPI-I-095'!L:N,3,0) -> WASHER-M36-F436M-HDG | C18: EYE BOLT M14+2NUT+1WASHER-xEM BẢN VẼ | D18: =VLOOKUP(A18,'25-VPI-I-095'!L:R,4,0) -> F436-HDG | E18: =VLOOKUP(A18,'25-VPI-I-095'!L:DH,91,0) -> 0 | F18: Cái | G18: 200 | H18: N/A | I18: N/A | L18: V | M18: 16000 | N18: =M18*G18 -> 3200000
B19: Đơn giá tổng hợp
A20: II | B20: Khối lượng dự kiến giao (Kg )/ Estimated weight (Kg):
A21: 1 | B21: … | C21: kg
A22: 2 | B22: …
A23: III | B23: Tiến độ/ Schedule | C23: Bắt đầu/ Start | D23: Kết thúc/ Finish
A24: 1 | B24: ….
A26: IV | B26: Nhân lực/ ManPower
A27: 1 | B27: Thợ Pha cắt / Thợ sắt / Thợ hàn / …
B28: ….
A29: V | B29: Yêu cầu kỹ thuật: Tham chiếu các tài liệu đính kèm/ Technical requirement – refer to document attached
B30: Xếp hạng | M30: 1
A31: Ghi chú:Phòng Thương Mại tiếp tục công tác mua sắm để đảm báo tiến độ
A32: NGƯỜI ĐỀ NGHỊ/ RECOMMENDATION BY: | C32: NGƯỜI KIỂM TRA/ DEPARTMENT HEAD CHECK BY: | G32: APPROVED BY: PHÊ DUYỆT
G33: Nguyễn Quang Vinh | I33: Hoàng Ngọc Bằng | L33: Đoàn Văn Toàn

Sheet Vật tư phụ Hoàng hà 2
A1: BID ANALYSIS - GIẢI TRÌNH MUA SẮM/ĐẤU THẦU
A3: Project | B3: PROJECT No/ Dự án: 25-VPI-I-095
A4: Dự án
A5: Subject | B5: Cung cấp vật tư phụ kiện bu lông/ đinh bảo ôn
A6: Chủ đề
A8: No. | B8: CONTENT | C8: Phạm vi công việc | H8: Dự toán | K8: Đã mua | L8: Đơn vị cung cấp chào giá (vnđ) | O8: Đơn vị cung cấp chào giá (vnđ) | R8: Ghi chú
A9: Item | B9: Description/ Chi tiết | C9: Profile/ Vật tư | D9: Grade/ Mác vật liệu | E9: Số lượng PR | F9: ĐVT | G9: Số lượng mua | H9: Khối lượng/ Số lượng | I9: Đơn giá (vnd) | J9: Thành tiền (vnd) | K9: Thành tiền (vnd) | L9: VSAN | O9: Hoàng Hà
L10: Phạm vi | M10: Đơn giá (VND) | N10: Thành Tiền (Không có VAT) | O10: Phạm vi | P10: Đơn giá (VND) | Q10: Thành Tiền (Không có VAT)
A11: Tổng | B11: Vật tư phụ kiện | G11: =SUM(G13:G13) -> 7426 | H11: N/A | I11: N/A | J11: ='DT03 (TM)'!G19 -> 8.3322017e+09 | K11: ='Tổng hợp'!J22+'Tổng hợp'!J23 -> 22324242648 | Q11: =SUM(Q13:Q13) -> 99508400 | R11: =J11-K11-Q11 -> -1.4091549e+10
A12: Insulation-Material / Vật tư bảo ôn
A13: I95-VTC04-009 | B13: =VLOOKUP(A13,'25-VPI-I-095'!L:N,3,0) -> ROUND WASHER OD76XID14X2.6mm-SUS304 | C13: ROUND WASHER OD76XID14X2.6mm-SUS304 | D13: =VLOOKUP(A13,'25-VPI-I-095'!L:R,4,0) -> JIS G4303-SUS304 | E13: =VLOOKUP(A13,'25-VPI-I-095'!L:DH,87,0) -> 0 | F13: Cái | G13: 7426 | H13: N/A | I13: N/A | J13: N/A | L13: V | M13: 14060 | N13: 104409560 | O13: V | P13: 13400 | Q13: =P13*G13 -> 99508400 | R13: Chọn HOÀNG HÀ
B14: Đơn giá tổng hợp
A15: II | B15: Khối lượng dự kiến giao (Kg )/ Estimated weight (Kg):
A16: 1 | B16: … | C16: kg
A17: 2 | B17: …
A18: III | B18: Tiến độ/ Schedule | C18: Bắt đầu/ Start | D18: Kết thúc/ Finish
A19: 1 | B19: ….
A21: IV | B21: Nhân lực/ ManPower
A22: 1 | B22: Thợ Pha cắt / Thợ sắt / Thợ hàn / …
B23: ….
A24: V | B24: Yêu cầu kỹ thuật: Tham chiếu các tài liệu đính kèm/ Technical requirement – refer to document attached
B25: Xếp hạng | M25: 2 | P25: 1
A26: Ghi chú:Phòng Thương Mại tiếp tục công tác mua sắm để đảm báo tiến độ
A27: NGƯỜI ĐỀ NGHỊ/ RECOMMENDATION BY: | C27: NGƯỜI KIỂM TRA/ DEPARTMENT HEAD CHECK BY: | G27: APPROVED BY: PHÊ DUYỆT
G28: Nguyễn Quang Vinh | I28: Hoàng Ngọc Bằng | L28: Đoàn Văn Toàn

Sheet Vật tư phụ VSAN 3
A1: BID ANALYSIS - GIẢI TRÌNH MUA SẮM/ĐẤU THẦU
A3: Project | B3: PROJECT No/ Dự án: 25-VPI-I-095
A4: Dự án
A5: Subject | B5: Cung cấp vật tư phụ kiện bu lông/ đinh bảo ôn
A6: Chủ đề
A8: No. | B8: CONTENT | C8: Phạm vi công việc | H8: Dự toán | K8: Đã mua | L8: Đơn vị cung cấp chào giá (vnđ) | O8: Ghi chú
A9: Item | B9: Description/ Chi tiết | C9: Profile/ Vật tư | D9: Grade/ Mác vật liệu | E9: Số lượng PR | F9: ĐVT | G9: Số lượng mua | H9: Khối lượng/ Số lượng | I9: Đơn giá (vnd) | J9: Thành tiền (vnd) | K9: Thành tiền (vnd) | L9: VSAN
L10: Phạm vi | M10: Đơn giá (VND) | N10: Thành Tiền (Không có VAT)
A11: Tổng | B11: Vật tư phụ kiện | G11: =SUM(G13:G31) -> 30997 | H11: N/A | I11: N/A | J11: ='DT03 (TM)'!G19 -> 8.3322017e+09 | K11: ='Tổng hợp'!M23+'Tổng hợp'!J23 -> 9.374355e+09 | N11: =SUM(N13:N31) -> 276252460 | O11: =J11-K11-N11 -> -1.3184058e+09
A12: Insulation-Material / Vật tư bảo ôn
A13: I95-VTC04-009 | B13: =VLOOKUP(A13,'25-VPI-I-095'!L:N,3,0) -> ROUND WASHER OD76XID14X2.6mm-SUS304 | C13: ROUND WASHER OD76XID14X2.6mm-SUS304 | D13: =VLOOKUP(A13,'25-VPI-I-095'!L:R,4,0) -> JIS G4303-SUS304 | E13: =VLOOKUP(A13,'25-VPI-I-095'!L:DH,91,0) -> 0 | F13: Cái | G13: 7426 | H13: N/A | I13: N/A | L13: V | M13: 14060 | N13: 104409560
A14: I95-VTC04-020 | B14: =VLOOKUP(A14,'25-VPI-I-095'!L:N,3,0) -> STUD-RB10X152-REN M10X1.5- 32mm-SUS304 | C14: STUD-RB10X152-REN M10X1.5- 32mm-SUS304 | D14: =VLOOKUP(A14,'25-VPI-I-095'!L:R,4,0) -> JIS G4303-SUS304 | E14: =VLOOKUP(A14,'25-VPI-I-095'!L:DH,91,0) -> 0 | F14: Cái | G14: 20 | H14: N/A | I14: N/A | L14: V | M14: 17100 | N14: 342000
A15: I95-VTC04-021 | B15: =VLOOKUP(A15,'25-VPI-I-095'!L:N,3,0) -> STUD-RB10X171-REN M10X1.5- 32mm-SUS304 | C15: STUD-RB10X171-REN M10X1.5- 32mm-SUS304 | D15: =VLOOKUP(A15,'25-VPI-I-095'!L:R,4,0) -> JIS G4303-SUS304 | E15: =VLOOKUP(A15,'25-VPI-I-095'!L:DH,91,0) -> 0 | F15: Cái | G15: 5 | H15: N/A | I15: N/A | L15: V | M15: 18620 | N15: 93100
A16: I95-VTC04-040 | B16: =VLOOKUP(A16,'25-VPI-I-095'!L:N,3,0) -> STUD-RB10X152-REN M10X1.5- 32mm-SUS309S | C16: STUD-RB10X152-REN M10X1.5- 32mm-SUS309S | D16: =VLOOKUP(A16,'25-VPI-I-095'!L:R,4,0) -> JIS.G4303_SUS309S | E16: =VLOOKUP(A16,'25-VPI-I-095'!L:DH,91,0) -> 0 | F16: Cái | G16: 25 | H16: N/A | I16: N/A | L16: V | M16: 64600 | N16: 1615000
A17: I95-VTC04-041 | B17: =VLOOKUP(A17,'25-VPI-I-095'!L:N,3,0) -> STUD-RB10X241-REN M10X1.5- 32mm-SUS309S | C17: STUD-RB10X241-REN M10X1.5- 32mm-SUS309S | D17: =VLOOKUP(A17,'25-VPI-I-095'!L:R,4,0) -> JIS.G4303_SUS309S | E17: =VLOOKUP(A17,'25-VPI-I-095'!L:DH,91,0) -> 0 | F17: Cái | G17: 5 | H17: N/A | I17: N/A | L17: V | M17: 77520 | N17: 387600
A18: I95-VTC04-043 | B18: =VLOOKUP(A18,'25-VPI-I-095'!L:N,3,0) -> NUT M10-ISO4032-SUS309S | C18: NUT M10-ISO4032-SUS309S | D18: =VLOOKUP(A18,'25-VPI-I-095'!L:R,4,0) -> JIS G4303-SUS309S | E18: =VLOOKUP(A18,'25-VPI-I-095'!L:DH,91,0) -> 0 | F18: Cái | G18: 50 | H18: N/A | I18: N/A | L18: V | M18: 56600 | N18: 2830000
A19: I95-VTC04-047 | B19: =VLOOKUP(A19,'25-VPI-I-095'!L:N,3,0) -> STUD-RB10X286-REN M10X1.5- 32mm-SUS304 | C19: STUD-RB10X286-REN M10X1.5- 32mm-SUS304 | D19: =VLOOKUP(A19,'25-VPI-I-095'!L:R,4,0) -> JIS G4303-SUS304 | E19: =VLOOKUP(A19,'25-VPI-I-095'!L:DH,91,0) -> 0 | F19: Cái | G19: 30 | H19: N/A | I19: N/A | L19: V | M19: 28880 | N19: 866400
A20: I95-VTC04-050 | B20: =VLOOKUP(A20,'25-VPI-I-095'!L:N,3,0) -> STUD-3/8"DIA x 4"LENGTH-THREAD 2 1/4"-A479TP304 | C20: STUD-3/8"DIA x 4"LENGTH-THREAD 2 1/4"-A479TP304 | D20: =VLOOKUP(A20,'25-VPI-I-095'!L:R,4,0) -> A479-TP304 | E20: =VLOOKUP(A20,'25-VPI-I-095'!L:DH,91,0) -> 0 | F20: Cái | G20: 5700 | H20: N/A | I20: N/A | L20: V | M20: 12800 | N20: 72960000
A21: I95-VTC04-051 | B21: =VLOOKUP(A21,'25-VPI-I-095'!L:N,3,0) -> NUT-3/8"-A194-GR8 | C21: NUT-3/8"-A194-GR8 | D21: =VLOOKUP(A21,'25-VPI-I-095'!L:R,4,0) -> A194-GR8 | E21: =VLOOKUP(A21,'25-VPI-I-095'!L:DH,91,0) -> 0 | F21: Cái | G21: 11400 | H21: N/A | I21: N/A | L21: V | M21: 2400 | N21: 27360000
A22: I95-VTC04-052 | B22: =VLOOKUP(A22,'25-VPI-I-095'!L:N,3,0) -> 3/8" WASHER-1 1/2 "ODx1/8" THK-TP304 | C22: 3/8" WASHER-1 1/2 "ODx1/8" THK-TP304 | D22: =VLOOKUP(A22,'25-VPI-I-095'!L:R,4,0) -> TP304 | E22: =VLOOKUP(A22,'25-VPI-I-095'!L:DH,91,0) -> 0 | F22: Cái | G22: 5700 | H22: N/A | I22: N/A | L22: V | M22: 5600 | N22: 31920000
A23: I95-VTC04-053 | B23: =VLOOKUP(A23,'25-VPI-I-095'!L:N,3,0) -> STUD-RB10X351-REN M10X1.5- 32mm-SUS304 | C23: STUD-RB10X351-REN M10X1.5- 32mm-SUS304 | D23: =VLOOKUP(A23,'25-VPI-I-095'!L:R,4,0) -> JIS G4303-SUS304 | E23: =VLOOKUP(A23,'25-VPI-I-095'!L:DH,91,0) -> 0 | F23: Cái | G23: 40 | H23: N/A | I23: N/A | L23: V | M23: 45280 | N23: 1811200
A24: I95-VPK-019 | B24: =VLOOKUP(A24,'25-VPI-I-095'!L:N,3,0) -> NUT-3/4"-A563-BLACK | C24: NUT-3/4"-A563-BLACK | D24: =VLOOKUP(A24,'25-VPI-I-095'!L:R,4,0) -> A-563 HEX NUT | E24: =VLOOKUP(A24,'25-VPI-I-095'!L:DH,91,0) -> 0 | F24: Cái | G24: 100 | H24: N/A | I24: N/A | L24: V | M24: 15800 | N24: 1580000
A25: Bolt-Material / Vật tư bulong, phụ kiện | P25: =SUM(N26:N31) -> 30077600
A26: I95-VPK-013 | B26: =VLOOKUP(A26,'25-VPI-I-095'!L:N,3,0) -> CLEVIS PIN Ø12x52-DIN 1444-MẠ ĐIỆN PHÂN | C26: CLEVIS PIN Ø12x52-DIN 1444-MẠ ĐIỆN PHÂN | D26: =VLOOKUP(A26,'25-VPI-I-095'!L:R,4,0) -> JIS G3101-SS400-MG | E26: =VLOOKUP(A26,'25-VPI-I-095'!L:DH,91,0) -> 0 | F26: Cái | G26: 96 | H26: N/A | I26: N/A | L26: V | M26: 100000 | N26: 9600000
A27: I95-VPK-014 | B27: =VLOOKUP(A27,'25-VPI-I-095'!L:N,3,0) -> COTTER PIN Ø3.2x25L-DIN 94- MẠ ĐIỆN PHÂN | C27: COTTER PIN Ø3.2x25L-DIN 94- MẠ ĐIỆN PHÂN | D27: =VLOOKUP(A27,'25-VPI-I-095'!L:R,4,0) -> JIS G3101-SS400-MG | E27: =VLOOKUP(A27,'25-VPI-I-095'!L:DH,91,0) -> 0 | F27: Cái | G27: 96 | H27: N/A | I27: N/A | L27: V | M27: 5000 | N27: 480000
A28: I95-VPK-015 | B28: =VLOOKUP(A28,'25-VPI-I-095'!L:N,3,0) -> EYE BOLT M14+2NUT+1WASHER-xEM BẢN VẼ | C28: EYE BOLT M14+2NUT+1WASHER-xEM BẢN VẼ | D28: =VLOOKUP(A28,'25-VPI-I-095'!L:R,4,0) -> SS400 | E28: =VLOOKUP(A28,'25-VPI-I-095'!L:DH,91,0) -> 0 | F28: Cái | G28: 12 | H28: N/A | I28: N/A | L28: V | M28: 250000 | N28: 3000000
A29: I95-VPK-016 | B29: =VLOOKUP(A29,'25-VPI-I-095'!L:N,3,0) -> EYE BOLT M16x137(1 EYE BOLT+01 WASHER+ 01 HANDLE NUT) -xEM BẢN VẼ | C29: EYE BOLT M16x137(1 EYE BOLT+01 WASHER+ 01 HANDLE NUT) -xEM BẢN VẼ | D29: =VLOOKUP(A29,'25-VPI-I-095'!L:R,4,0) -> SS400 | E29: =VLOOKUP(A29,'25-VPI-I-095'!L:DH,91,0) -> 0 | F29: Cái | G29: 96 | H29: N/A | I29: N/A | L29: V | M29: 160000 | N29: 15360000
A30: I95-VPK-017 | B30: =VLOOKUP(A30,'25-VPI-I-095'!L:N,3,0) -> WASHER-M12-ISO7089-8-HDG | C30: WASHER-M12-ISO7089-8-HDG | D30: =VLOOKUP(A30,'25-VPI-I-095'!L:R,4,0) -> ZINC | E30: =VLOOKUP(A30,'25-VPI-I-095'!L:DH,91,0) -> 0 | F30: Cái | G30: 96 | H30: N/A | I30: N/A | L30: V | M30: 600 | N30: 57600
A31: I95-VPK-019 | B31: =VLOOKUP(A31,'25-VPI-I-095'!L:N,3,0) -> NUT-3/4"-A563-BLACK | C31: NUT-3/4"-A563-BLACK | D31: =VLOOKUP(A31,'25-VPI-I-095'!L:R,4,0) -> A-563 HEX NUT | E31: =VLOOKUP(A31,'25-VPI-I-095'!L:DH,91,0) -> 0 | F31: Cái | G31: 100 | H31: N/A | I31: N/A | L31: V | M31: 15800 | N31: 1580000
B32: Đơn giá tổng hợp
A33: II | B33: Khối lượng dự kiến giao (Kg )/ Estimated weight (Kg):
A34: 1 | B34: … | C34: kg
A35: 2 | B35: …
A36: III | B36: Tiến độ/ Schedule | C36: Bắt đầu/ Start | D36: Kết thúc/ Finish
A37: 1 | B37: ….
A39: IV | B39: Nhân lực/ ManPower
A40: 1 | B40: Thợ Pha cắt / Thợ sắt / Thợ hàn / …
B41: ….
A42: V | B42: Yêu cầu kỹ thuật: Tham chiếu các tài liệu đính kèm/ Technical requirement – refer to document attached
B43: Xếp hạng | M43: 1
A44: Ghi chú:Phòng Thương Mại tiếp tục công tác mua sắm để đảm báo tiến độ
A45: NGƯỜI ĐỀ NGHỊ/ RECOMMENDATION BY: | C45: NGƯỜI KIỂM TRA/ DEPARTMENT HEAD CHECK BY: | G45: APPROVED BY: PHÊ DUYỆT
G46: Nguyễn Quang Vinh | I46: Hoàng Ngọc Bằng | L46: Đoàn Văn Toàn

Sheet Vật tư Bảo Ôn
A1: BID ANALYSIS - GIẢI TRÌNH MUA SẮM/ĐẤU THẦU
A3: Project | B3: PROJECT No/ Dự án: 25-VPI-I-095
A4: Dự án
A5: Subject | B5: Cung cấp vật tư bông bảo ôn của dự án
A6: Chủ đề
A8: No. | B8: CONTENT | C8: Phạm vi công việc | G8: Dự toán | J8: Đơn vị cung cấp chào giá (vnđ) | M8: Ghi chú
A9: Item | B9: Description/ Chi tiết | C9: Khối lượng PR yêu cầu | D9: Khối lượng đặt mua | E9: Số lượng | F9: ĐVT | G9: Khối lượng/ Số lượng | H9: Đơn giá (vnd) | I9: Thành tiền (vnd) | J9: XALACO
J10: Phạm vi | K10: Đơn giá (VND) | L10: Thành Tiền (Không có VAT)
A11: Tổng | G11: N/A | H11: N/A | I11: ='DT03 (TM)'!G17 -> 1.1497242e+10 | L11: =SUM(L13:L16) -> 15086811438 | M11: =I11-L11 -> -3.5895689e+09
A12: Insulation-Material / Vật tư bảo ôn | M12: - Xalaco đơn vị cấp bông quen thuộc của nhà máy - Tổng giá trị vượt quá giá trí trong dự toán - Đơn giá đã đáp ứng dự toán ( thấp hơn dự toán) - Khối lượng theo PR -. theo thông tin từ sale, phần tính chi phí với khách hàng dựa trên khối lượng thực tế nên tổng chi phí có chênh so với dự toán cũng không ảnh hưởng gì
A13: I95-VTC04-004 | B13: Superwool Plus Blanket 3660x610x50mm Density 128kg/m3 Bông cuộn super wool plus (bông sợi khoáng) dày 50mm, tỷ trọng 128kg/m3 | C13: 1593 M3 | D13: =E13*3.66*0.61*0.05 -> 1593.0717 | E13: 14271 | F13: Roll | G13: N/A | H13: N/A | J13: V | K13: 969086 | L13: =K13*E13 -> 13829826306
A14: I95-VTC04-003 | B14: Superwool Plus Blanket 7320x610x25mm Density 128kg/m3 Bông cuộn super wool plus ( bông sợi khoáng) dày 25mm, tỷ trọng 128kg/m3 | C14: 134 M3 | D14: =E14*7.32*0.61*0.025 -> 133.956 | E14: 1200 | F14: Roll | G14: N/A | H14: N/A | J14: V | K14: 969086 | L14: =K14*E14 -> 1162903200
A15: I95-VTC04-002 | B15: Superwool Plus Blanket 14640x610x13mm Density 128kg/m3 Bông cuộn super wool plus ( bông sợi khoáng) dày 13mm , tỷ trọng 128kg/m3 | C15: 8 M3 | D15: =E15*14.64*0.61*0.013 -> 8.0105688 | E15: 69 | F15: Roll | G15: N/A | H15: N/A | J15: V | K15: 1300466 | L15: =K15*E15 -> 89732154
A16: I95-VTC04-001 | B16: Superwool Plus Paper 20000x610x3mm Density 200kg/m3 Bông cuộn Superwool Plus Paper dày 3mm, tỷ trọng 200kg/m3 | C16: 25 M2 | D16: =E16*20*0.61 -> 24.4 | E16: 2 | F16: Roll | G16: N/A | H16: N/A | J16: V | K16: 2174889 | L16: =K16*E16 -> 4349778
B17: Đơn giá tổng hợp
A18: II | B18: Khối lượng dự kiến giao (Kg )/ Estimated weight (Kg):
A19: 1 | B19: … | C19: kg
A20: 2 | B20: …
A21: III | B21: Tiến độ/ Schedule | C21: Bắt đầu/ Start | D21: Kết thúc/ Finish
A22: 1 | B22: ….
A24: IV | B24: Nhân lực/ ManPower
A25: 1 | B25: Thợ Pha cắt / Thợ sắt / Thợ hàn / …
B26: ….
A27: V | B27: Yêu cầu kỹ thuật: Tham chiếu các tài liệu đính kèm/ Technical requirement – refer to document attached
B28: Xếp hạng | K28: 1
A29: Ghi chú:Phòng Thương Mại tiếp tục công tác mua sắm để đảm báo tiến độ
A30: NGƯỜI ĐỀ NGHỊ/ RECOMMENDATION BY: | C30: NGƯỜI KIỂM TRA/ DEPARTMENT HEAD CHECK BY: | H30: APPROVED BY: PHÊ DUYỆT
F31: Nguyễn Quang Vinh | I31: Hoàng Ngọc Bằng | L31: Đoàn Văn Toàn

Sheet Đợt Centerway
A1: BID ANALYSIS - GIẢI TRÌNH MUA SẮM/ĐẤU THẦU
A3: Project | B3: PROJECT No/ Dự án: 25-VPI-I-095
A4: Dự án
A5: Subject | B5: Cung cấp vật tư chính phụ kiện
A6: Chủ đề
A8: No. | B8: CONTENT | C8: Phạm vi công việc | H8: Dự toán | K8: Đã mua | L8: Đơn vị cung cấp chào giá phần còn lại (VNĐ) | O8: Đơn vị cung cấp chào giá phần còn lại (VNĐ) | R8: Ghi chú
A9: Item | B9: Description/ Chi tiết | C9: Profile/ Vật tư | D9: Grade/ Mác vật liệu | E9: Grade/ Mác vật liệu mua | F9: Số lượng Mua (M) | G9: Số lượng PR (M) | H9: Khối lượng/ Số lượng | I9: Đơn giá (vnd) | J9: Thành tiền (vnd) | K9: Thành tiền (vnd) | L9: CENTERWAY STEEL CO.,LTD | O9: Tam Đa
L10: Phạm vi | M10: Đơn giá trước CIF (USD/PSC) | N10: Thành Tiền (26300VNĐ/USD) | O10: Phạm vi | P10: Đơn giá trước VAT (VNĐ/KG) | Q10: Thành Tiền
A11: Tổng | B11: VPK | C11: Bolt-Material / Vật tư bulong, phụ kiện | H11: N/A | I11: N/A | J11: ='DT03 (TM)'!G19 -> 8.3322017e+09 | K11: ='Vật tư phụ VSAN (2)'!M11 -> 4842086070 | N11: =SUM(N12:N24)*26300 -> 309109160 | R11: =J11-K11-Q11-N11 -> 3.1810065e+09
A12: I95-VPK-002 | B12: =VLOOKUP(A12,'25-VPI-I-095'!L:N,3,0) -> 2"_3000#_THREADED_COUPLING-ASME B16.11 | C12: 2"_3000#_THREADED_COUPLING-ASME B16.11 | D12: =VLOOKUP(A12,'25-VPI-I-095'!L:R,4,0) -> ASTM-A105 | E12: ASTM-A105 | F12: 20 | G12: =VLOOKUP(A12,'25-VPI-I-095'!L:DO,83,0) -> 46052 | H12: N/A | I12: N/A | J12: N/A | K12: N/A | L12: X | M12: 10.59837 | N12: =M12*F12 -> 211.96739 | O12: V | P12: 235000 | Q12: =VLOOKUP(A12,'[164]DA 95'!$B$20:$N$31,13,0) -> #N/A | R12: Chọn CENTERWAY
A13: I95-VPK-003 | B13: =VLOOKUP(A13,'25-VPI-I-095'!L:N,3,0) -> 3"_BLIND_FLANGE_#150_RF-ASME B16.5 | C13: 3"_BLIND_FLANGE_#150_RF-ASME B16.5 | D13: =VLOOKUP(A13,'25-VPI-I-095'!L:R,4,0) -> ASTM-A105 | E13: ASTM-A105 | F13: 96 | G13: =VLOOKUP(A13,'25-VPI-I-095'!L:DO,83,0) -> 46052 | H13: N/A | I13: N/A | J13: N/A | K13: N/A | L13: V | M13: 9.6983696 | N13: =M13*F13 -> 931.04348 | O13: V | P13: 265000 | Q13: =VLOOKUP(A13,'[164]DA 95'!$B$20:$N$31,13,0) -> #N/A | R13: Chọn CENTERWAY
A14: I95-VPK-004 | B14: =VLOOKUP(A14,'25-VPI-I-095'!L:N,3,0) -> 3"_FLANGE_#150_SORF-ASME B16.5 | C14: 3"_FLANGE_#150_SORF-ASME B16.5 | D14: =VLOOKUP(A14,'25-VPI-I-095'!L:R,4,0) -> ASTM-A105 | E14: ASTM-A105 | F14: 96 | G14: =VLOOKUP(A14,'25-VPI-I-095'!L:DO,83,0) -> 46052 | H14: N/A | I14: N/A | J14: N/A | K14: N/A | L14: V | M14: 7.6983696 | N14: =M14*F14 -> 739.04348 | O14: V | P14: 285000 | Q14: =VLOOKUP(A14,'[164]DA 95'!$B$20:$N$31,13,0) -> #N/A | R14: Chọn CENTERWAY
A15: I95-VPK-005 | B15: =VLOOKUP(A15,'25-VPI-I-095'!L:N,3,0) -> 3"_FLANGE_#150_SORF-ASME B16.5 | C15: 3"_FLANGE_#150_SORF-ASME B16.5 (FLANGE % C min 0.04%)) | D15: =VLOOKUP(A15,'25-VPI-I-095'!L:R,4,0) -> ASTM-A182-F304 | E15: ASTM-A182-F304 | F15: 336 | G15: =VLOOKUP(A15,'25-VPI-I-095'!L:DO,83,0) -> 46052 | H15: N/A | I15: N/A | J15: N/A | K15: N/A | L15: V | M15: 24.09837 | N15: =M15*F15 -> 8097.0522 | O15: V | P15: 598500 | Q15: =VLOOKUP(A15,'[164]DA 95'!$B$20:$N$31,13,0) -> #N/A | R15: Chọn CENTERWAY
A16: I95-VPK-008 | B16: =VLOOKUP(A16,'25-VPI-I-095'!L:N,3,0) -> 4"_BLIND_FLANGE_#150_RF-ASME B16.5 | C16: 4"_BLIND_FLANGE_#150_RF-ASME B16.5 | D16: =VLOOKUP(A16,'25-VPI-I-095'!L:R,4,0) -> ASTM-A105 | E16: ASTM-A105 | F16: 4 | G16: =VLOOKUP(A16,'25-VPI-I-095'!L:DO,83,0) -> 46052 | H16: N/A | I16: N/A | J16: N/A | K16: N/A | L16: V | M16: 12.99837 | N16: =M16*F16 -> 51.993478 | O16: V | P16: 365000 | Q16: =VLOOKUP(A16,'[164]DA 95'!$B$20:$N$31,13,0) -> #N/A | R16: Chọn CENTERWAY
A17: I95-VPK-009 | B17: =VLOOKUP(A17,'25-VPI-I-095'!L:N,3,0) -> 4"_FLANGE_#150_SORF-ASME B16.5 | C17: 4"_FLANGE_#150_SORF-ASME B16.5 | D17: =VLOOKUP(A17,'25-VPI-I-095'!L:R,4,0) -> ASTM-A105 | E17: ASTM-A105 | F17: 4 | G17: =VLOOKUP(A17,'25-VPI-I-095'!L:DO,83,0) -> 46052 | H17: N/A | I17: N/A | J17: N/A | K17: N/A | L17: V | M17: 9.7983696 | N17: =M17*F17 -> 39.193478 | O17: V | P17: 360000 | Q17: =VLOOKUP(A17,'[164]DA 95'!$B$20:$N$31,13,0) -> #N/A | R17: Chọn CENTERWAY
A18: I95-VPK-012 | B18: PL5X2000X12000 | C18: SQUARE_HEAD_PLUG_2"_3000#-ASME B16.11 | D18: =VLOOKUP(A18,'25-VPI-I-095'!L:R,4,0) -> ASTM-A105 | E18: ASTM-A105 | F18: 20 | G18: =VLOOKUP(A18,'25-VPI-I-095'!L:DO,83,0) -> 46052 | H18: N/A | I18: N/A | J18: N/A | K18: N/A | L18: V | M18: 7.3983696 | N18: =M18*F18 -> 147.96739 | O18: V | P18: 260000 | Q18: =VLOOKUP(A18,'[164]DA 95'!$B$20:$N$31,13,0) -> #N/A | R18: Chọn CENTERWAY
A19: I95-VPK-021 | B19: =VLOOKUP(A19,'25-VPI-I-095'!L:N,3,0) -> 2_1/2"_BLIND_FLANGE_#150_RF | C19: 2_1/2"_BLIND_FLANGE_#150_RF-ASME B16.5 | D19: =VLOOKUP(A19,'25-VPI-I-095'!L:R,4,0) -> A105 | E19: ASTM-A105 | F19: 64 | G19: =VLOOKUP(A19,'25-VPI-I-095'!L:DO,83,0) -> 46052 | H19: N/A | I19: N/A | J19: N/A | K19: N/A | L19: X | M19: 9.0983696 | N19: =M19*F19 -> 582.29565 | O19: V | P19: 235000 | Q19: =VLOOKUP(A19,'[164]DA 95'!$B$20:$N$31,13,0) -> #N/A | R19: Chọn CENTERWAY
A20: I95-VPK-022 | B20: =VLOOKUP(A20,'25-VPI-I-095'!L:N,3,0) -> 2_1/2"_FLANGE_#150_SORF | C20: 2_1/2"_FLANGE_#150_SORF-ASME B16.5 | D20: =VLOOKUP(A20,'25-VPI-I-095'!L:R,4,0) -> A105 | E20: ASTM-A105 | F20: 64 | G20: =VLOOKUP(A20,'25-VPI-I-095'!L:DO,83,0) -> 46052 | H20: N/A | I20: N/A | J20: N/A | K20: N/A | L20: X | M20: 7.1983696 | N20: =M20*F20 -> 460.69565 | O20: V | P20: 245000 | Q20: =VLOOKUP(A20,'[164]DA 95'!$B$20:$N$31,13,0) -> #N/A | R20: Chọn CENTERWAY
A21: I95-VPK-023 | B21: =VLOOKUP(A21,'25-VPI-I-095'!L:N,3,0) -> 3/4"_3000#_THREADED_COUPLING | C21: 3/4"_3000#_THREADED_COUPLING-ASME B16.11 | D21: =VLOOKUP(A21,'25-VPI-I-095'!L:R,4,0) -> A105 | E21: ASTM-A105 | F21: 8 | G21: =VLOOKUP(A21,'25-VPI-I-095'!L:DO,83,0) -> 46052 | H21: N/A | I21: N/A | J21: N/A | K21: N/A | L21: X | M21: 5.5983696 | N21: =M21*F21 -> 44.786957 | O21: V | P21: 75000 | Q21: =VLOOKUP(A21,'[164]DA 95'!$B$20:$N$31,13,0) -> #N/A | R21: Chọn CENTERWAY
A22: I95-VPK-024 | B22: =VLOOKUP(A22,'25-VPI-I-095'!L:N,3,0) -> 8"_BLIND_FLANGE_#150_RF | C22: 8"_BLIND_FLANGE_#150_RF-ASME B16.5 | D22: =VLOOKUP(A22,'25-VPI-I-095'!L:R,4,0) -> A105 | E22: ASTM-A105 | F22: 8 | G22: =VLOOKUP(A22,'25-VPI-I-095'!L:DO,83,0) -> 46052 | H22: N/A | I22: N/A | J22: N/A | K22: N/A | L22: X | M22: 30.59837 | N22: =M22*F22 -> 244.78696 | O22: V | P22: 890000 | Q22: =VLOOKUP(A22,'[164]DA 95'!$B$20:$N$31,13,0) -> #N/A | R22: Chọn CENTERWAY
A23: I95-VPK-025 | B23: =VLOOKUP(A23,'25-VPI-I-095'!L:N,3,0) -> 8"_FLANGE_#150_SORF | C23: 8"_FLANGE_#150_SORF-ASME B16.5 | D23: =VLOOKUP(A23,'25-VPI-I-095'!L:R,4,0) -> A105 | E23: ASTM-A105 | F23: 8 | G23: =VLOOKUP(A23,'25-VPI-I-095'!L:DO,83,0) -> 46052 | H23: N/A | I23: N/A | J23: N/A | K23: N/A | L23: X | M23: 19.69837 | N23: =M23*F23 -> 157.58696 | O23: V | P23: 1075000 | Q23: =VLOOKUP(A23,'[164]DA 95'!$B$20:$N$31,13,0) -> #N/A | R23: Chọn CENTERWAY
A24: I95-VPK-026 | B24: =VLOOKUP(A24,'25-VPI-I-095'!L:N,3,0) -> SQUARE_HEAD_PLUG_3/4"_3000# | C24: SQUARE_HEAD_PLUG_3/4"_3000#-ASME B16.11 | D24: =VLOOKUP(A24,'25-VPI-I-095'!L:R,4,0) -> A105 | E24: ASTM-A105 | F24: 8 | G24: =VLOOKUP(A24,'25-VPI-I-095'!L:DO,83,0) -> 46052 | H24: N/A | I24: N/A | J24: N/A | K24: N/A | L24: X | M24: 5.5983696 | N24: =M24*F24 -> 44.786957 | O24: V | P24: 85000 | Q24: =VLOOKUP(A24,'[164]DA 95'!$B$20:$N$31,13,0) -> #N/A | R24: Chọn CENTERWAY
B25: Xếp hạng | M25: 2 | P25: 1
A26: Ghi chú: Tiếp tục công tác mua sắm để đảm báo tiến độ
A27: NGƯỜI ĐỀ NGHỊ/ RECOMMENDATION BY: | E27: NGƯỜI KIỂM TRA/ DEPARTMENT HEAD CHECK BY: | K27: APPROVED BY: PHÊ DUYỆT
K28: Nguyễn Quang Vinh | N28: Hoàng Ngọc Bằng | Q28: Đoàn Văn Toàn

Sheet Đợt mới hùng nguyên
A1: BID ANALYSIS - GIẢI TRÌNH MUA SẮM/ĐẤU THẦU
A3: Project | B3: PROJECT No/ Dự án: 25-VPI-I-095
A4: Dự án
A5: Subject | B5: Cung cấp vật tư chính thép đen
A6: Chủ đề
A8: No. | B8: CONTENT | C8: Phạm vi công việc | H8: Dự toán | K8: Đã mua | L8: Đơn vị cung cấp chào giá phần còn lại (VNĐ) | O8: Đơn vị cung cấp chào giá phần còn lại (VNĐ) | R8: Đơn vị cung cấp chào giá phần còn lại (VNĐ) | U8: Ghi chú
A9: Item | B9: Description/ Chi tiết | C9: Profile/ Vật tư | D9: Grade/ Mác vật liệu | E9: Grade/ Mác vật liệu mua | F9: Số lượng Mua (M) | G9: Số lượng PR (M) | H9: Khối lượng/ Số lượng | I9: Đơn giá (vnd) | J9: Thành tiền (vnd) | K9: Thành tiền (vnd) | L9: NGỌC HIẾU | O9: Hùng Nguyên | R9: APEC
L10: Phạm vi | M10: Đơn giá trước VAT (VNĐ/KG) | N10: Thành Tiền | O10: Phạm vi | P10: Đơn giá trước VAT (VNĐ/KG) | Q10: Thành Tiền | R10: Phạm vi | S10: Đơn giá trước VAT (VNĐ/KG) | T10: Thành Tiền
A11: Tổng | B11: Main-Material / Vật tư chính thép đen | H11: N/A | I11: N/A | J11: ='DT03 (TM)'!G6 -> 5.7151444e+10 | K11: ='Tổng hợp'!J19 -> 4.7616213e+10 | Q11: =SUM(Q12:Q30) -> 1390458882 | U11: =J11-K11-Q11-N11 -> 8.144772e+09
A12: I95-VTC01-004 | B12: =VLOOKUP(A12,'25-VPI-I-095'!L:N,3,0) -> PL25x2000x12000 | C12: Thép tấm 25x2000x12000 | D12: =VLOOKUP(A12,'25-VPI-I-095'!L:R,4,0) -> A572-GR50 | E12: Q355B | F12: 72 | G12: =VLOOKUP(A12,'25-VPI-I-095'!L6:DF319,89,0) -> 0 | H12: N/A | I12: N/A | J12: N/A | K12: N/A | L12: X | M12: #N/A | N12: #N/A | O12: V | P12: 14772.73 | Q12: 208738675 | R12: V | S12: =16300/1.1 -> 14818.182 | T12: =VLOOKUP(D12,'[164]DA 95'!$B$20:$N$31,13,0) -> #N/A | U12: Chọn Hùng Nguyên
A13: I95-VTC01-008 | B13: =VLOOKUP(A13,'25-VPI-I-095'!L:N,3,0) -> PL12X2000X12000 | C13: Thép tấm 12x2000x12000 | D13: =VLOOKUP(A13,'25-VPI-I-095'!L:R,4,0) -> SS400 | E13: SS400 | F13: 168 | G13: =VLOOKUP(A13,'25-VPI-I-095'!L7:DF320,89,0) -> 0 | H13: N/A | I13: N/A | J13: N/A | K13: N/A | L13: V | M13: 13636.36 | N13: #N/A | O13: V | P13: 13590.91 | Q13: 215084305 | R13: X | S13: #N/A | T13: =VLOOKUP(D13,'[164]DA 95'!$B$20:$N$31,13,0) -> #N/A | U13: Chọn Hùng Nguyên
A14: I95-VTC01-009 | B14: =VLOOKUP(A14,'25-VPI-I-095'!L:N,3,0) -> PL16X2000X12000 | C14: Thép tấm 16x2000x12000 | D14: =VLOOKUP(A14,'25-VPI-I-095'!L:R,4,0) -> SS400 | E14: SS400 | F14: 264 | G14: =VLOOKUP(A14,'25-VPI-I-095'!L8:DF321,89,0) -> 0 | H14: N/A | I14: N/A | J14: N/A | K14: N/A | L14: V | M14: 13909.09 | N14: #N/A | O14: V | P14: 13909.09 | Q14: 461203170 | R14: V | S14: 14090.909 | T14: =VLOOKUP(D14,'[164]DA 95'!$B$20:$N$31,13,0) -> #N/A | U14: Chọn Hùng Nguyên
A15: I95-VTC01-010 | B15: =VLOOKUP(A15,'25-VPI-I-095'!L:N,3,0) -> PL20X2000X12000 | C15: Thép tấm 20x2000x12000 | D15: =VLOOKUP(A15,'25-VPI-I-095'!L:R,4,0) -> SS400 | E15: A36/Q235B/SS400 | F15: 72 | G15: =VLOOKUP(A15,'25-VPI-I-095'!L12:DF322,89,0) -> 0 | H15: N/A | I15: N/A | J15: N/A | K15: N/A | L15: V | M15: 13909.09 | N15: #N/A | O15: V | P15: 13909.09 | Q15: 157228353 | R15: X | S15: #N/A | T15: =VLOOKUP(D15,'[164]DA 95'!$B$20:$N$31,13,0) -> #N/A | U15: Chọn Hùng Nguyên
A16: I95-VTC01-036 | B16: =VLOOKUP(A16,'25-VPI-I-095'!L:N,3,0) -> PL6X2000X12000 | C16: Thép tấm 6x2000x6000 | D16: =VLOOKUP(A16,'25-VPI-I-095'!L:R,4,0) -> SS400 | E16: SS400 | F16: 12 | G16: =VLOOKUP(A16,'25-VPI-I-095'!L13:DF323,89,0) -> 0 | H16: N/A | I16: N/A | J16: N/A | K16: N/A | L16: V | M16: 13636.36 | N16: #N/A | O16: V | P16: 13590.91 | Q16: 7681582 | R16: V | S16: 14090.909 | T16: =VLOOKUP(D16,'[164]DA 95'!$B$20:$N$31,13,0) -> #N/A | U16: Chọn Hùng Nguyên
A17: I95-VTC01-047 | B17: =VLOOKUP(A17,'25-VPI-I-095'!L:N,3,0) -> PL25x2000x12000 | C17: Thép tấm 25x2000x12000 | D17: =VLOOKUP(A17,'25-VPI-I-095'!L:R,4,0) -> SS400 | E17: A36/Q235B | F17: 48 | G17: =VLOOKUP(A17,'25-VPI-I-095'!L14:DF324,89,0) -> 0 | H17: N/A | I17: N/A | J17: N/A | K17: N/A | L17: V | M17: 13909.09 | N17: #N/A | O17: V | P17: 13909.09 | Q17: 131023628 | R17: V | S17: 14090.909 | T17: =VLOOKUP(D17,'[164]DA 95'!$B$20:$N$31,13,0) -> #N/A | U17: Chọn Hùng Nguyên
A18: I95-VTC01-053 | B18: PL5X2000X12000 | C18: Thép tấm 5x2000x12000 | D18: =VLOOKUP(A18,'25-VPI-I-095'!L:R,4,0) -> SS400 | E18: SS400 | F18: 48 | G18: =VLOOKUP(A18,'25-VPI-I-095'!L15:DF325,89,0) -> 0 | H18: N/A | I18: N/A | J18: N/A | K18: N/A | L18: V | M18: 13636.36 | N18: #N/A | O18: V | P18: 13590.91 | Q18: 25605274 | R18: V | S18: 14090.909 | T18: =VLOOKUP(D18,'[164]DA 95'!$B$20:$N$31,13,0) -> #N/A | U18: Chọn Hùng Nguyên
A19: I95-VTC01-057 | B19: =VLOOKUP(A19,'25-VPI-I-095'!L:N,3,0) -> PL14X2000X12000 | C19: Thép tấm 14x2000x12000 | D19: =VLOOKUP(A19,'25-VPI-I-095'!L:R,4,0) -> A572-GR50 | E19: Q355B | F19: 24 | G19: =VLOOKUP(A19,'25-VPI-I-095'!L16:DF326,89,0) -> 0 | H19: N/A | I19: N/A | J19: N/A | K19: N/A | L19: X | M19: #N/A | N19: #N/A | O19: V | P19: 14181.82 | Q19: 37405968 | R19: V | S19: =16300/1.1 -> 14818.182 | T19: =VLOOKUP(D19,'[164]DA 95'!$B$20:$N$31,13,0) -> #N/A | U19: Chọn Hùng Nguyên
A20: I95-VTC01-057 | B20: =VLOOKUP(A20,'25-VPI-I-095'!L:N,3,0) -> PL14X2000X12000 | C20: Thép tấm 14x2000x6000 | D20: =VLOOKUP(A20,'25-VPI-I-095'!L:R,4,0) -> A572-GR50 | E20: Q355B | F20: 12 | H20: N/A | I20: N/A | J20: N/A | K20: N/A | L20: X | M20: #N/A | N20: #N/A | O20: V | P20: 14181.82 | Q20: 18702984 | R20: V | S20: =16300/1.1 -> 14818.182 | T20: =VLOOKUP(D20,'[164]DA 95'!$B$20:$N$31,13,0) -> #N/A | U20: Chọn Hùng Nguyên
A21: I95-VTC01-059 | B21: =VLOOKUP(A21,'25-VPI-I-095'!L:N,3,0) -> PL30X2000X6000 | C21: Thép tấm 30x2000x6000 | D21: =VLOOKUP(A21,'25-VPI-I-095'!L:R,4,0) -> A572-GR50 | E21: Q355B | F21: 12 | G21: =VLOOKUP(A21,'25-VPI-I-095'!L19:DF328,89,0) -> 0 | H21: N/A | I21: N/A | J21: N/A | K21: N/A | L21: X | M21: #N/A | N21: #N/A | O21: V | P21: 14772.73 | Q21: 41747735 | R21: V | S21: =16300/1.1 -> 14818.182 | T21: =VLOOKUP(D21,'[164]DA 95'!$B$20:$N$31,13,0) -> #N/A | U21: Chọn Hùng Nguyên
A22: I95-VTC01-076 | B22: =VLOOKUP(A22,'25-VPI-I-095'!L:N,3,0) -> PL3X1500X6000 | C22: Thép tấm 3x1500x3000 | D22: =VLOOKUP(A22,'25-VPI-I-095'!L:R,4,0) -> SS400 | E22: SS400 | F22: 54 | G22: =VLOOKUP(A22,'25-VPI-I-095'!L20:DF334,89,0) -> 0 | H22: N/A | I22: N/A | J22: N/A | K22: N/A | L22: X | M22: #N/A | N22: #N/A | O22: V | P22: 14136.36 | Q22: 17977209 | R22: X | S22: #N/A | T22: =VLOOKUP(D22,'[164]DA 95'!$B$20:$N$31,13,0) -> #N/A | U22: Chọn Hùng Nguyên
A23: I95-VTC01-093 | B23: =VLOOKUP(A23,'25-VPI-I-095'!L:N,3,0) -> PL14X2000X12000 | C23: Thép tấm 14x2000x12000 | D23: =VLOOKUP(A23,'25-VPI-I-095'!L:R,4,0) -> SS400 | E23: SS400 | F23: 24 | G23: =VLOOKUP(A23,'25-VPI-I-095'!L21:DF335,89,0) -> 0 | H23: N/A | I23: N/A | J23: N/A | K23: N/A | L23: X | M23: #N/A | N23: #N/A | O23: V | P23: 13909.09 | Q23: 36686616 | R23: X | S23: #N/A | T23: =VLOOKUP(D23,'[164]DA 95'!$B$20:$N$31,13,0) -> #N/A | U23: Chọn Hùng Nguyên
A24: I95-VTC01-094 | B24: =VLOOKUP(A24,'25-VPI-I-095'!L:N,3,0) -> PL8X2000X6000 | C24: Thép tấm 8x2000x6000 | D24: =VLOOKUP(A24,'25-VPI-I-095'!L:R,4,0) -> SS400 | E24: SS400 | F24: 12 | G24: =VLOOKUP(A24,'25-VPI-I-095'!L22:DF337,89,0) -> 0 | H24: N/A | I24: N/A | J24: N/A | K24: N/A | L24: X | M24: #N/A | N24: #N/A | O24: V | P24: 13590.91 | Q24: 10242110 | R24: V | S24: 14090.909 | T24: =VLOOKUP(D24,'[164]DA 95'!$B$20:$N$31,13,0) -> #N/A | U24: Chọn Hùng Nguyên
A25: I95-VTC01-105 | B25: =VLOOKUP(A25,'25-VPI-I-095'!L:N,3,0) -> CPL6X1500X6000 | C25: Thép tấm nhám 6x1500x6000 | D25: =VLOOKUP(A25,'25-VPI-I-095'!L:R,4,0) -> SS400 | E25: QHWB/Q235B | F25: 9 | G25: =VLOOKUP(A25,'25-VPI-I-095'!L23:DF341,89,0) -> 0 | H25: N/A | I25: N/A | J25: N/A | K25: N/A | L25: X | M25: #N/A | N25: #N/A | O25: V | P25: 13590.91 | Q25: 6128141 | R25: V | S25: 14090.909 | T25: =VLOOKUP(D25,'[164]DA 95'!$B$20:$N$31,13,0) -> #N/A | U25: Chọn Hùng Nguyên
A26: I95-VTC01-051 | B26: =VLOOKUP(A26,'25-VPI-I-095'!L:N,3,0) -> L50X50X6-6000L | C26: Thép góc V50x50x6x6000 | D26: =VLOOKUP(A26,'25-VPI-I-095'!L:R,4,0) -> SS400 | E26: SS400 | F26: 108 | G26: =VLOOKUP(A26,'25-VPI-I-095'!L24:DF342,89,0) -> 0 | H26: N/A | I26: N/A | J26: N/A | K26: N/A | L26: X | M26: #N/A | N26: #N/A | O26: V | P26: 14090.91 | Q26: 6741655 | R26: V | S26: 14090.91 | T26: =VLOOKUP(D26,'[164]DA 95'!$B$20:$N$31,13,0) -> #N/A | U26: Chọn Hùng Nguyên
A27: I95-VTC01-079 | B27: =VLOOKUP(A27,'25-VPI-I-095'!L:N,3,0) -> RB13-6000L | C27: Thép tròn trơn phi 14x6000 | D27: =VLOOKUP(A27,'25-VPI-I-095'!L:R,4,0) -> SS400 | E27: SS400/CB240 | F27: 30 | G27: =VLOOKUP(A27,'25-VPI-I-095'!L25:DF343,89,0) -> 0 | H27: N/A | I27: N/A | J27: N/A | K27: N/A | L27: X | M27: #N/A | N27: #N/A | O27: V | P27: 15272.73 | Q27: 553636 | R27: X | S27: #N/A | T27: =VLOOKUP(D27,'[164]DA 95'!$B$20:$N$31,13,0) -> #N/A | U27: Chọn Hùng Nguyên
A28: I95-VTC01-080 | B28: =VLOOKUP(A28,'25-VPI-I-095'!L:N,3,0) -> RB19-6000L | C28: Thép tròn trơn phi 20x6000 | D28: =VLOOKUP(A28,'25-VPI-I-095'!L:R,4,0) -> SS400 | E28: SS400/CB240 | F28: 24 | G28: =VLOOKUP(A28,'25-VPI-I-095'!L26:DF344,89,0) -> 0 | H28: N/A | I28: N/A | J28: N/A | K28: N/A | L28: X | M28: #N/A | N28: #N/A | O28: V | P28: 15272.73 | Q28: 903840 | R28: X | S28: #N/A | T28: =VLOOKUP(D28,'[164]DA 95'!$B$20:$N$31,13,0) -> #N/A | U28: Chọn Hùng Nguyên
A29: I95-VTC01-081 | B29: =VLOOKUP(A29,'25-VPI-I-095'!L:N,3,0) -> RB38-6000L | C29: Thép tròn trơn phi 38x6000 | D29: =VLOOKUP(A29,'25-VPI-I-095'!L:R,4,0) -> SS400 | E29: S45C | F29: 42 | G29: =VLOOKUP(A29,'25-VPI-I-095'!L27:DF345,89,0) -> 0 | H29: N/A | I29: N/A | J29: N/A | K29: N/A | L29: X | M29: #N/A | N29: #N/A | O29: V | P29: 15272.73 | Q29: 5710321 | R29: X | S29: #N/A | T29: =VLOOKUP(D29,'[164]DA 95'!$B$20:$N$31,13,0) -> #N/A | U29: Chọn Hùng Nguyên
A30: I95-VTC01-095 | B30: =VLOOKUP(A30,'25-VPI-I-095'!L:N,3,0) -> RB44-6000L | C30: Thép tròn trơn phi 44x6000 | D30: =VLOOKUP(A30,'25-VPI-I-095'!L:R,4,0) -> SS400 | E30: S45C | F30: 6 | G30: =VLOOKUP(A30,'25-VPI-I-095'!L33:DF350,89,0) -> 0 | H30: N/A | I30: N/A | J30: N/A | K30: N/A | L30: X | M30: #N/A | N30: #N/A | O30: V | P30: 15272.73 | Q30: 1093680 | R30: X | S30: #N/A | T30: =VLOOKUP(D30,'[164]DA 95'!$B$20:$N$31,13,0) -> #N/A | U30: Chọn Hùng Nguyên
B31: Xếp hạng | M31: 2 | P31: 1 | S31: 3
A32: Ghi chú: Tiếp tục công tác mua sắm để đảm báo tiến độ
A33: NGƯỜI ĐỀ NGHỊ/ RECOMMENDATION BY: | F33: NGƯỜI KIỂM TRA/ DEPARTMENT HEAD CHECK BY: | N33: APPROVED BY: PHÊ DUYỆT
N34: Nguyễn Quang Vinh | Q34: Hoàng Ngọc Bằng | T34: Đoàn Văn Toàn

Sheet Ngọc hiếu 095 23-1-2026
A1: BID ANALYSIS - GIẢI TRÌNH MUA SẮM/ĐẤU THẦU
A3: Project | B3: PROJECT No/ Dự án: 25-VPI-I-095
A4: Dự án
A5: Subject | B5: Cung cấp vật tư chính thép hình
A6: Chủ đề
A8: No. | B8: CONTENT | C8: Phạm vi công việc | G8: Dự toán | J8: Đã mua | K8: Đơn vị cung cấp chào giá phần còn lại (VNĐ) | N8: Đơn vị cung cấp chào giá phần còn lại (VNĐ) | Q8: Đơn vị cung cấp chào giá phần còn lại (VNĐ) | T8: Ghi chú
A9: Item | B9: Description/ Chi tiết | C9: Profile/ Vật tư | D9: Grade/ Mác vật liệu | E9: Số lượng Mua (M) | F9: Số lượng PR (M) | G9: Khối lượng/ Số lượng | H9: Đơn giá (vnd) | I9: Thành tiền (vnd) | J9: Thành tiền (vnd) | K9: NGỌC HIẾU | N9: Hùng Nguyên | Q9: APEC
K10: Phạm vi | L10: Đơn giá trước VAT (VNĐ/KG) | M10: Thành Tiền | N10: Phạm vi | O10: Đơn giá trước VAT (VNĐ/KG) | P10: Thành Tiền | Q10: Phạm vi | R10: Đơn giá trước VAT (VNĐ/KG) | S10: Thành Tiền
A11: Tổng | B11: Main-Material / Vật tư chính thép đen | G11: N/A | H11: N/A | I11: ='DT03 (TM)'!G6 -> 5.7151444e+10 | J11: ='Tổng hợp'!J19 -> 4.7616213e+10 | M11: =SUM(M12:M22) -> 350328560 | T11: =I11-J11-P11-M11 -> 9.1849023e+09
A12: I95-VTC01-028 | B12: =VLOOKUP(A12,'25-VPI-I-095'!L:N,3,0) -> L100X100X7-12000L | C12: Thép V100*100*7*12000 | D12: =VLOOKUP(A12,'25-VPI-I-095'!L:R,4,0) -> SS400 | E12: 84 | F12: =VLOOKUP(A12,'25-VPI-I-095'!L6:DF319,87,0) -> 0 | G12: N/A | H12: N/A | I12: N/A | J12: N/A | K12: V | L12: 13909.09 | M12: 12504272 | N12: V | O12: 14090.91 | P12: N//A | Q12: V | R12: 14363.636 | S12: =VLOOKUP(D12,'[164]DA 95'!$B$20:$N$31,13,0) -> #N/A | T12: Chọn Ngọc Hiếu
A13: I95-VTC01-030 | B13: =VLOOKUP(A13,'25-VPI-I-095'!L:N,3,0) -> L90X90X6-12000L | C13: Thép V90*90*6*12000 | D13: =VLOOKUP(A13,'25-VPI-I-095'!L:R,4,0) -> SS400 | E13: 24 | F13: =VLOOKUP(A13,'25-VPI-I-095'!L7:DF320,87,0) -> 0 | G13: N/A | H13: N/A | I13: N/A | J13: N/A | K13: V | L13: 13909.09 | M13: 2767909 | N13: V | O13: 14090.91 | P13: N//A | Q13: V | R13: 14545.455 | S13: =VLOOKUP(D13,'[164]DA 95'!$B$20:$N$31,13,0) -> #N/A | T13: Chọn Ngọc Hiếu
A14: I95-VTC01-034 | B14: =VLOOKUP(A14,'25-VPI-I-095'!L:N,3,0) -> C200X90X8X13.5-12000L | C14: Thép U200*90*8*13,5*12000 | D14: =VLOOKUP(A14,'25-VPI-I-095'!L:R,4,0) -> SS400 | E14: 156 | F14: =VLOOKUP(A14,'25-VPI-I-095'!L8:DF321,87,0) -> 0 | G14: N/A | H14: N/A | I14: N/A | J14: N/A | K14: V | L14: 17272.73 | M14: 81648195 | N14: X | O14: #N/A | P14: N//A | Q14: V | R14: 17727.273 | S14: =VLOOKUP(D14,'[164]DA 95'!$B$20:$N$31,13,0) -> #N/A | T14: Chọn Ngọc Hiếu
A15: I95-VTC01-052 | B15: =VLOOKUP(A15,'25-VPI-I-095'!L:N,3,0) -> L100X100X10-12000L | C15: Thép V100*100*10*12000 | D15: =VLOOKUP(A15,'25-VPI-I-095'!L:R,4,0) -> SS400 | E15: 264 | F15: =VLOOKUP(A15,'25-VPI-I-095'!L10:DF322,87,0) -> 0 | G15: N/A | H15: N/A | I15: N/A | J15: N/A | K15: V | L15: 13909.09 | M15: 54718360 | N15: V | O15: 14090.91 | P15: N//A | Q15: V | R15: 14363.636 | S15: =VLOOKUP(D15,'[164]DA 95'!$B$20:$N$31,13,0) -> #N/A | T15: Chọn Ngọc Hiếu
A16: I95-VTC01-061 | B16: =VLOOKUP(A16,'25-VPI-I-095'!L:N,3,0) -> L75x75x6-12000L | C16: Thép V75*75*6*12000 | D16: =VLOOKUP(A16,'25-VPI-I-095'!L:R,4,0) -> SS400 | E16: 672 | F16: =VLOOKUP(A16,'25-VPI-I-095'!L11:DF323,87,0) -> 0 | G16: N/A | H16: N/A | I16: N/A | J16: N/A | K16: V | L16: 13909.09 | M16: 64023541 | N16: V | O16: 14090.91 | P16: N//A | Q16: V | R16: 14363.636 | S16: =VLOOKUP(D16,'[164]DA 95'!$B$20:$N$31,13,0) -> #N/A | T16: Chọn Ngọc Hiếu
A17: I95-VTC01-079 | B17: =VLOOKUP(A17,'25-VPI-I-095'!L:N,3,0) -> RB13-6000L | C17: Thép tròn D14*6000 | D17: =VLOOKUP(A17,'25-VPI-I-095'!L:R,4,0) -> SS400 | E17: 36 | F17: =VLOOKUP(A17,'25-VPI-I-095'!L12:DF324,87,0) -> 0 | G17: N/A | H17: N/A | I17: N/A | J17: N/A | K17: V | L17: 14181.82 | M17: 609818 | N17: V | O17: 15272.73 | P17: N//A | Q17: X | R17: #N/A | S17: =VLOOKUP(D17,'[164]DA 95'!$B$20:$N$31,13,0) -> #N/A | T17: Chọn Ngọc Hiếu
A18: I95-VTC01-083 | B18: =VLOOKUP(A18,'25-VPI-I-095'!L:N,3,0) -> C250X90X9X13-12000L | C18: Thép U250*90*9*13*12000 | D18: =VLOOKUP(A18,'25-VPI-I-095'!L:R,4,0) -> SS400 | E18: 96 | F18: =VLOOKUP(A18,'25-VPI-I-095'!L13:DF325,87,0) -> 0 | G18: N/A | H18: N/A | I18: N/A | J18: N/A | K18: V | L18: 17272.73 | M18: 57380009 | N18: X | O18: #N/A | P18: N//A | Q18: V | R18: 17727.273 | S18: =VLOOKUP(D18,'[164]DA 95'!$B$20:$N$31,13,0) -> #N/A | T18: Chọn Ngọc Hiếu
A19: I95-VTC01-088 | B19: =VLOOKUP(A19,'25-VPI-I-095'!L:N,3,0) -> C100X50X5X7.5-12000L | C19: Thép U100*50*5*7,5*12000 | D19: =VLOOKUP(A19,'25-VPI-I-095'!L:R,4,0) -> SS400 | E19: 216 | F19: =VLOOKUP(A19,'25-VPI-I-095'!L14:DF326,87,0) -> 0 | G19: N/A | H19: N/A | I19: N/A | J19: N/A | K19: V | L19: 17090.91 | M19: 34557820 | N19: V | O19: 17500 | P19: N//A | Q19: V | R19: 17727.273 | S19: =VLOOKUP(D19,'[164]DA 95'!$B$20:$N$31,13,0) -> #N/A | T19: Chọn Ngọc Hiếu
A20: I95-VTC01-114 | B20: =VLOOKUP(A20,'25-VPI-I-095'!L:N,3,0) -> L65X65X6-12000L | C20: Thép V65*65*6*12000 | D20: =VLOOKUP(A20,'25-VPI-I-095'!L:R,4,0) -> SS400 | E20: 240 | F20: =VLOOKUP(A20,'25-VPI-I-095'!L15:DF327,87,0) -> 0 | G20: N/A | H20: N/A | I20: N/A | J20: N/A | K20: V | L20: 13909.09 | M20: 19723090 | N20: V | O20: 14090.91 | P20: N//A | Q20: V | R20: 14545.455 | S20: =VLOOKUP(D20,'[164]DA 95'!$B$20:$N$31,13,0) -> #N/A | T20: Chọn Ngọc Hiếu
A21: I95-VTC01-029 | B21: =VLOOKUP(A21,'25-VPI-I-095'!L:N,3,0) -> L120X120X8-12000L | C21: Thép V120*120*8*12000 | D21: =VLOOKUP(A21,'25-VPI-I-095'!L:R,4,0) -> SS400 | E21: 96 | F21: =VLOOKUP(A21,'25-VPI-I-095'!L16:DF328,87,0) -> 0 | G21: N/A | H21: N/A | I21: N/A | J21: N/A | K21: V | L21: 15000 | M21: 21165000 | N21: V | O21: #N/A | P21: N//A | Q21: V | R21: 15636.364 | S21: =VLOOKUP(D21,'[164]DA 95'!$B$20:$N$31,13,0) -> #N/A | T21: Chọn Ngọc Hiếu
A22: I95-VTC01-021 | B22: =VLOOKUP(A22,'25-VPI-I-095'!L:N,3,0) -> C150X75X6.5X10-12000L | C22: Thép U150*75*6,5*10*6000 | D22: =VLOOKUP(A22,'25-VPI-I-095'!L:R,4,0) -> SS400 | E22: 0 | F22: =VLOOKUP(A22,'25-VPI-I-095'!L17:DF329,87,0) -> 0 | G22: N/A | H22: N/A | I22: N/A | J22: N/A | K22: V | L22: 17090.91 | M22: 1230546 | N22: V | O22: #N/A | P22: N//A | Q22: X | R22: #N/A | S22: =VLOOKUP(D22,'[164]DA 95'!$B$20:$N$31,13,0) -> #N/A | T22: Chọn Ngọc Hiếu
B23: Xếp hạng | L23: 1 | O23: 2 | R23: 3
A24: Ghi chú: Tiếp tục công tác mua sắm để đảm báo tiến độ
A25: NGƯỜI ĐỀ NGHỊ/ RECOMMENDATION BY: | E25: NGƯỜI KIỂM TRA/ DEPARTMENT HEAD CHECK BY: | M25: APPROVED BY: PHÊ DUYỆT
M26: Nguyễn Quang Vinh | P26: Hoàng Ngọc Bằng | S26: Đoàn Văn Toàn

Sheet Quang thịnh Phát lần3
A1: BID ANALYSIS - GIẢI TRÌNH MUA SẮM/ĐẤU THẦU
A3: Project | B3: PROJECT No/ Dự án: 25-VPI-I-095
A4: Dự án
A5: Subject | B5: Cung cấp vật tư chính thép ống ngày 23-1-2026
A6: Chủ đề
A8: No. | B8: CONTENT | C8: Phạm vi công việc | H8: Dự toán | K8: Đã mua | L8: Đơn vị cung cấp chào giá phần còn lại (VNĐ) | O8: Đơn vị cung cấp chào giá phần còn lại (VNĐ) | R8: Ghi chú
A9: Item | B9: Description/ Chi tiết | C9: Profile/ Vật tư | D9: Grade/ Mác vật liệu | E9: Số lượng Mua (M) | F9: Khối lượng Mua (M) | G9: Số lượng PR (M) | H9: Khối lượng/ Số lượng | I9: Đơn giá (vnd) | J9: Thành tiền (vnd) | K9: Thành tiền (vnd) | L9: QUANG THỊNH PHÁT | O9: TITAN
L10: Phạm vi | M10: Đơn giá trước VAT (VNĐ/KG) | N10: Thành Tiền | O10: Phạm vi | P10: Đơn giá trước VAT (VNĐ/KG) | Q10: Thành Tiền
A11: Tổng | B11: Main-Material / Vật tư chính thép đen | H11: N/A | I11: N/A | J11: ='DT03 (TM)'!G6 -> 5.7151444e+10 | K11: ='Tổng hợp'!J19 -> 4.7616213e+10 | N11: =SUM(N12:N13) -> 11745998 | R11: =J11-K11-Q11-N11 -> 9.5234849e+09
A12: I95-VTC01-104 | B12: =VLOOKUP(A12,'25-VPI-I-095'!L:N,3,0) -> CHS48.3X5.1-6000L | C12: Thép ống đen 48,3 x 5,08 x 6.000 mm | D12: =VLOOKUP(A12,'25-VPI-I-095'!L:R,4,0) -> A53-GRB | E12: 21 | F12: =E12*6 -> 126 | G12: 122.54732 | H12: N/A | I12: N/A | J12: N/A | K12: N/A | L12: V | M12: 15.727,27 | N12: 10725998 | O12: V | P12: =19500/1.1 -> 17727.273 | Q12: N//A | R12: Chọn Quang Thịnh Phát
A13: I95-VTC01-122 | B13: =VLOOKUP(A13,'25-VPI-I-095'!L:N,3,0) -> CHS60.3X3.9-6000L | C13: Thép ống đen 60,3 x 3,96 x 6.000 mm | D13: =VLOOKUP(A13,'25-VPI-I-095'!L:R,4,0) -> A53-GRB | E13: 2 | F13: =E13*6 -> 12 | G13: 9 | H13: N/A | I13: N/A | J13: N/A | K13: N/A | L13: V | M13: 15.454,55 | N13: 1020000 | O13: V | P13: =17350/1.1 -> 15772.727 | Q13: N//A | R13: Chọn Quang Thịnh Phát
B14: Xếp hạng | M14: 1 | P14: 2
A15: Ghi chú: Tiếp tục công tác mua sắm để đảm báo tiến độ
A16: NGƯỜI ĐỀ NGHỊ/ RECOMMENDATION BY: | E16: NGƯỜI KIỂM TRA/ DEPARTMENT HEAD CHECK BY: | K16: APPROVED BY: PHÊ DUYỆT
K17: Nguyễn Quang Vinh | N17: Hoàng Ngọc Bằng | Q17: Đoàn Văn Toàn

Sheet QUang thịnh Phát lần 2
A1: BID ANALYSIS - GIẢI TRÌNH MUA SẮM/ĐẤU THẦU
A3: Project | B3: PROJECT No/ Dự án: 25-VPI-I-095
A4: Dự án
A5: Subject | B5: Cung cấp vật tư chính thép ống
A6: Chủ đề
A8: No. | B8: CONTENT | C8: Phạm vi công việc | H8: Dự toán | K8: Đã mua | L8: Đơn vị cung cấp chào giá phần còn lại (VNĐ) | O8: Đơn vị cung cấp chào giá phần còn lại (VNĐ) | R8: Ghi chú
A9: Item | B9: Description/ Chi tiết | C9: Profile/ Vật tư | D9: Grade/ Mác vật liệu | E9: Số lượng Mua (M) | F9: Khối lượng Mua (M) | G9: Số lượng PR (M) | H9: Khối lượng/ Số lượng | I9: Đơn giá (vnd) | J9: Thành tiền (vnd) | K9: Thành tiền (vnd) | L9: QUANG THỊNH PHÁT | O9: TITAN
L10: Phạm vi | M10: Đơn giá trước VAT (VNĐ/KG) | N10: Thành Tiền | O10: Phạm vi | P10: Đơn giá trước VAT (VNĐ/KG) | Q10: Thành Tiền
A11: Tổng | B11: Main-Material / Vật tư chính thép đen | H11: N/A | I11: N/A | J11: ='DT03 (TM)'!G6 -> 5.7151444e+10 | K11: ='Tổng hợp'!J19 -> 4.7616213e+10 | N11: =SUM(N12:N14) -> 431823652 | R11: =J11-K11-Q11-N11 -> 9.1034072e+09
A12: I95-VTC01-067 | B12: =VLOOKUP(A12,'25-VPI-I-095'!L:N,3,0) -> CHS88.9X5.49-6000L | C12: Thép ống đen 88,9 x 5,5 x 6.000 mm | D12: =VLOOKUP(A12,'25-VPI-I-095'!L:R,4,0) -> SS400 | E12: =6*2 -> 12 | F12: 136 | G12: 11.5 | H12: N/A | I12: N/A | J12: N/A | K12: N/A | L12: V | M12: 15636.36 | N12: 2126545 | O12: V | P12: =19500/1.1 -> 17727.273 | Q12: N//A | R12: Chọn Quang Thịnh Phát
A13: I95-VTC01-103 | B13: =VLOOKUP(A13,'25-VPI-I-095'!L:N,3,0) -> CHS48.3X3.6-6000L | C13: Thép ống đen 48,3 x 3,68 x 6.000 mm | D13: =VLOOKUP(A13,'25-VPI-I-095'!L:R,4,0) -> A53-GRB | E13: =6*664 -> 3984 | F13: 16132 | G13: 3977.8561 | H13: N/A | I13: N/A | J13: N/A | K13: N/A | L13: V | M13: 15363.64 | N13: 247846240 | O13: V | P13: =17350/1.1 -> 15772.727 | Q13: N//A | R13: Chọn Quang Thịnh Phát
A14: I95-VTC01-104 | B14: =VLOOKUP(A14,'25-VPI-I-095'!L:N,3,0) -> CHS48.3X5.1-6000L | C14: Thép ống đen 48,3 x 5,08 x 6.000 mm | D14: =VLOOKUP(A14,'25-VPI-I-095'!L:R,4,0) -> A53-GRB | E14: =6*358 -> 2148 | F14: 11630 | G14: 2145.5473 | H14: N/A | I14: N/A | J14: N/A | K14: N/A | L14: V | M14: 15636.36 | N14: 181850867 | O14: V | P14: =17950/1.1 -> 16318.182 | Q14: N//A | R14: Chọn Quang Thịnh
B15: Xếp hạng | M15: 1 | P15: 2
A16: Ghi chú: Tiếp tục công tác mua sắm để đảm báo tiến độ
A17: NGƯỜI ĐỀ NGHỊ/ RECOMMENDATION BY: | E17: NGƯỜI KIỂM TRA/ DEPARTMENT HEAD CHECK BY: | K17: APPROVED BY: PHÊ DUYỆT
K18: Nguyễn Quang Vinh | N18: Hoàng Ngọc Bằng | Q18: Đoàn Văn Toàn

Sheet Giải tình hoàng hà
A1: BID ANALYSIS - GIẢI TRÌNH MUA SẮM/ĐẤU THẦU
A3: Project | B3: PROJECT No/ Dự án: 25-VPI-I-095
A4: Dự án
A5: Subject | B5: Cung cấp vật tư chính thép trắng
A6: Chủ đề
A8: No. | B8: CONTENT | C8: Phạm vi công việc | G8: Dự toán | J8: Đã mua | K8: Đơn vị cung cấp chào giá phần còn lại (VNĐ) | N8: Đơn vị cung cấp chào giá phần còn lại (VNĐ) | Q8: Đơn vị cung cấp chào giá phần còn lại (USD) | T8: Ghi chú
A9: Item | B9: Description/ Chi tiết | C9: Profile/ Vật tư | D9: Grade/ Mác vật liệu | E9: Số lượng Mua (M2) | F9: Số lượng PR (M2) | G9: Khối lượng/ Số lượng | H9: Đơn giá (vnd) | I9: Thành tiền (vnd) | J9: Thành tiền (vnd) | K9: HOÀNG HÀ | N9: VSAN | Q9: XALACO
K10: Phạm vi | L10: Đơn giá trước VAT (VNĐ/TẤM) | M10: Thành Tiền | N10: Phạm vi | O10: Đơn giá trước VAT (VNĐ/TẤM) | P10: Thành Tiền | Q10: Phạm vi | R10: Đơn giá trước VAT (VNĐ/TẤM) | S10: Thành Tiền
A11: Tổng | B11: Main-Material / Vật tư chính thép trắng | I11: ='DT03 (TM)'!G12 -> 6.2338967e+09 | J11: ='Tổng hợp'!J20 -> 1.1194758e+10 | M11: =M12 -> 259200000 | T11: =I11-J11-M11 -> -5.2200611e+09
A12: I95-VTC02-037 | B12: =VLOOKUP(A12,'25-VPI-I-095'!L:N,3,0) -> 40 MESH( ROD 0.254mmx 0.381x0.381) | C12: 1M*30M (Mua 54 tấm) | D12: Inox 304 Lưới 40 mesh | E12: =54*30 -> 1620 | F12: 1600 | G12: N/A | H12: N/A | I12: N/A | J12: N/A | K12: V | L12: 4800000 | M12: 259200000 | N12: X | O12: =30*179200 -> 5376000 | P12: N/A | Q12: V | R12: =30*214380 -> 6431400 | S12: N/A | T12: Chọn HOÀNG HÀ
A14: IV | B14: Nhân lực/ ManPower
A15: 1 | B15: Thợ Pha cắt / Thợ sắt / Thợ hàn / …
B16: ….
B17: Xếp hạng | L17: 1 | O17: 2 | R17: 3
A18: Ghi chú: Tổng giá trị phần thép trắng tấm đang vượt quá dự toán ' Tiếp tục công tác mua sắm để đảm báo tiến độ/ Phần giá trị tăng sẽ báo sale để điều chỉnh cách tính tiền với khách hàng
A19: NGƯỜI ĐỀ NGHỊ/ RECOMMENDATION BY: | C19: NGƯỜI KIỂM TRA/ DEPARTMENT HEAD CHECK BY: | M19: APPROVED BY: PHÊ DUYỆT
M20: Nguyễn Quang Vinh | P20: Hoàng Ngọc Bằng | S20: Đoàn Văn Toàn

Sheet Giải tình Global lần 3
A1: BID ANALYSIS - GIẢI TRÌNH MUA SẮM/ĐẤU THẦU
A3: Project | B3: PROJECT No/ Dự án: 25-VPI-I-095
A4: Dự án
A5: Subject | B5: Cung cấp vật tư chính thép đen GLOBAL ngày 16-1
A6: Chủ đề
A8: No. | B8: CONTENT | C8: Phạm vi công việc | G8: Dự toán | J8: Đã mua | K8: Đơn vị cung cấp chào giá phần còn lại (USD) | N8: Đơn vị cung cấp chào giá phần còn lại (USD) | Q8: Đơn vị cung cấp chào giá phần còn lại (USD) | T8: Ghi chú
A9: Item | B9: Description/ Chi tiết | C9: Profile/ Vật tư | D9: Grade/ Mác vật liệu | E9: Số lượng Mua (M2) | F9: Số lượng PR (M2) | G9: Khối lượng/ Số lượng | H9: Đơn giá (vnd) | I9: Thành tiền (vnd) | J9: Thành tiền (vnd) | K9: GLOBAL | N9: GNEE | Q9: HÙNG NGUYÊN
K10: Phạm vi | L10: Đơn giá CIF (USD/KG) | M10: Thành Tiền | N10: Phạm vi | O10: Đơn giá CIF (USD/KG) | P10: Thành Tiền | Q10: Phạm vi | R10: Đơn giá (USD/KG) | S10: Thành Tiền
A11: Tổng | B11: ='Tổng hợp'!B19 -> Main-Material / Vật tư chính thép đen | I11: ='DT03 (TM)'!G6 -> 5.7151444e+10 | J11: ='Tổng hợp'!J19 -> 4.7616213e+10 | M11: =SUM(M12:M12)*26300 -> 26852300 | P11: =SUM(P12:P12)*26300 -> 0 | T11: =I11-J11-P11-M11-S11 -> 9.5083786e+09
A12: I95-VTC01-020 | B12: =VLOOKUP(A12,'25-VPI-I-095'!L:N,3,0) -> PL65X2000X6000 | C12: PL65X2000X1000 | D12: A572-GR50 | E12: 2 | F12: 2 | G12: N/A | H12: N/A | I12: N/A | K12: V | L12: 1 | M12: 1021 | N12: X | O12: N/A | P12: N/A | Q12: X | R12: N/A | S12: N/A | T12: Chọn GLOBAL
A14: IV | B14: Nhân lực/ ManPower
A15: 1 | B15: Thợ Pha cắt / Thợ sắt / Thợ hàn / …
B16: ….
B17: Xếp hạng | L17: 1 | O17: 2 | R17: 3
A18: Ghi chú: Tiếp tục công tác mua sắm để đảm báo tiến độ.
A19: NGƯỜI ĐỀ NGHỊ/ RECOMMENDATION BY: | C19: NGƯỜI KIỂM TRA/ DEPARTMENT HEAD CHECK BY: | M19: APPROVED BY: PHÊ DUYỆT
M20: Nguyễn Quang Vinh | P20: Hoàng Ngọc Bằng | S20: Đoàn Văn Toàn

Sheet Giải tình Global lần 2
A1: BID ANALYSIS - GIẢI TRÌNH MUA SẮM/ĐẤU THẦU
A3: Project | B3: PROJECT No/ Dự án: 25-VPI-I-095
A4: Dự án
A5: Subject | B5: Cung cấp vật tư chính thép trắng
A6: Chủ đề
A8: No. | B8: CONTENT | C8: Phạm vi công việc | G8: Dự toán | J8: Đã mua | K8: Đơn vị cung cấp chào giá phần còn lại (USD) | N8: Đơn vị cung cấp chào giá phần còn lại (USD) | Q8: Đơn vị cung cấp chào giá phần còn lại (USD) | T8: Ghi chú
A9: Item | B9: Description/ Chi tiết | C9: Profile/ Vật tư | D9: Grade/ Mác vật liệu | E9: Số lượng Mua (M2) | F9: Số lượng PR (M2) | G9: Khối lượng/ Số lượng | H9: Đơn giá (vnd) | I9: Thành tiền (vnd) | J9: Thành tiền (vnd) | K9: GLOBAL | N9: ĐÔNG NAM/ THỊNH PHÁT | Q9: EYANG
K10: Phạm vi | L10: Đơn giá (USD/KG) | M10: Thành Tiền | N10: Phạm vi | O10: Đơn giá (USD/KG) | P10: Thành Tiền | Q10: Phạm vi | R10: Đơn giá (USD/KG) | S10: Thành Tiền
A11: Tổng | B11: Main-Material / Vật tư chính thép trắng | I11: ='DT03 (TM)'!G12 -> 6.2338967e+09 | J11: ='Tổng hợp'!J20 -> 1.1194758e+10 | M11: =SUM(M12:M12)*26300 -> 6067410 | P11: =SUM(P12:P12)*26300 -> 0 | T11: =I11-J11-P11-M11-S11 -> -4.9669285e+09
A12: I95-VTC02-015 | B12: =VLOOKUP(A12,'25-VPI-I-095'!L:N,3,0) -> PL2X1220X2440 | C12: PL2X1220X2440 | D12: JIS.G4312_SUH409 | E12: =4*1.22*2.44 -> 11.9072 | F12: 10 | G12: N/A | H12: N/A | I12: N/A | K12: V | L12: 1.25 | M12: 230.7 | N12: X | O12: N/A | P12: N/A | Q12: V | R12: 1.25 | S12: N/A | T12: Chọn GLOBAL
A14: IV | B14: Nhân lực/ ManPower
A15: 1 | B15: Thợ Pha cắt / Thợ sắt / Thợ hàn / …
B16: ….
B17: Xếp hạng | L17: 1 | O17: 3 | R17: 2
A18: Ghi chú: Tổng giá trị phần thép trắng tấm đang vượt quá dự toán ' Tiếp tục công tác mua sắm để đảm báo tiến độ/ Phần giá trị tăng sẽ báo sale để điều chỉnh cách tính tiền với khách hàng
A19: NGƯỜI ĐỀ NGHỊ/ RECOMMENDATION BY: | C19: NGƯỜI KIỂM TRA/ DEPARTMENT HEAD CHECK BY: | M19: APPROVED BY: PHÊ DUYỆT
M20: Nguyễn Quang Vinh | P20: Hoàng Ngọc Bằng | S20: Đoàn Văn Toàn

Sheet Giải tình GNEE 2-12
A1: BID ANALYSIS - GIẢI TRÌNH MUA SẮM/ĐẤU THẦU
A3: Project | B3: PROJECT No/ Dự án: 25-VPI-I-095
A4: Dự án
A5: Subject | B5: Cung cấp vật tư chính thép đen
A6: Chủ đề
A8: No. | B8: CONTENT | C8: Phạm vi công việc | G8: Dự toán | J8: Đã mua | K8: Đơn vị cung cấp chào giá phần còn lại (USD) | N8: Đơn vị cung cấp chào giá phần còn lại (USD) | Q8: Ghi chú
A9: Item | B9: Description/ Chi tiết | C9: Profile/ Vật tư | D9: Grade/ Mác vật liệu | E9: Số lượng Mua (M2) | F9: Số lượng PR (M2) | G9: Khối lượng/ Số lượng | H9: Đơn giá (vnd) | I9: Thành tiền (vnd) | J9: Thành tiền (vnd) | K9: MCL/ YUXIN TIANJIN | N9: GNEE
K10: Phạm vi | L10: Đơn giá (USD/KG) | M10: Thành Tiền (Không có VAT) | N10: Phạm vi | O10: Đơn giá (USD/KG) | P10: Thành Tiền
A11: Tổng | B11: Main-Material / Vật tư chính thép đen | G11: N/A | H11: N/A | I11: ='DT03 (TM)'!G6 -> 5.7151444e+10 | J11: ='Tổng hợp'!J19-P11 -> 4.5040595e+10 | M11: =SUM(M12:M16) -> 0 | P11: =SUM(P12:P20)*26300 -> 2.5756184e+09 | Q11: =I11-J11-P11-M11 -> 9.5352309e+09
A12: I95-VTC01-017 | B12: =VLOOKUP(A12,'25-VPI-I-095'!L:N,3,0) -> PL38X2000X12000 | C12: 38*2000*12000 | D12: A572-GR50 PLATE | E12: 24 | F12: =VLOOKUP(A12,'25-VPI-I-095'!L:BA,25,0) -> 24 | G12: N/A | H12: N/A | I12: N/A | K12: X | L12: N/A | M12: N/A | N12: V | O12: 0.72859562 | P12: 5216.1618 | Q12: Chọn GNEE
A13: I95-VTC01-020 | B13: =VLOOKUP(A13,'25-VPI-I-095'!L:N,3,0) -> PL65X2000X6000 | C13: 65*2000*1000 | D13: A572-GR50 PLATE | E13: 2 | F13: =VLOOKUP(A13,'25-VPI-I-095'!L:BA,25,0) -> 2 | G13: N/A | H13: N/A | I13: N/A | K13: X | L13: N/A | M13: N/A | N13: V | O13: 0.72059562 | P13: 735.36783 | Q13: Chọn GNEE
A14: I95-VTC01-054 | B14: =VLOOKUP(A14,'25-VPI-I-095'!L:N,3,0) -> PL12X2000X1000 | C14: 12*2000*1000 | D14: SM490 PLATE | E14: 2 | F14: =VLOOKUP(A14,'25-VPI-I-095'!L:BA,25,0) -> 2 | G14: N/A | H14: N/A | I14: N/A | K14: X | L14: N/A | M14: N/A | N14: V | O14: 0.72059562 | P14: 135.76022 | Q14: Chọn GNEE
A15: I95-VTC01-055 | B15: =VLOOKUP(A15,'25-VPI-I-095'!L:N,3,0) -> PL25X2000X2000 | C15: 25*2000*1000 | D15: SM490 PLATE | E15: 2 | F15: =VLOOKUP(A15,'25-VPI-I-095'!L:BA,25,0) -> 2 | G15: N/A | H15: N/A | I15: N/A | K15: X | L15: N/A | M15: N/A | N15: V | O15: 0.72059562 | P15: 282.83378 | Q15: Chọn GNEE
A16: I95-VTC01-056 | B16: =VLOOKUP(A16,'25-VPI-I-095'!L:N,3,0) -> PL38X2000X3000 | C16: 38*2000*1000 | D16: SM490 PLATE | E16: 2 | F16: =VLOOKUP(A16,'25-VPI-I-095'!L:BA,25,0) -> 1 | G16: N/A | H16: N/A | I16: N/A | K16: X | L16: N/A | M16: N/A | N16: V | O16: 0.72859562 | P16: 434.68015 | Q16: Chọn GNEE
A17: I95-VTC01-107 | B17: =VLOOKUP(A17,'25-VPI-I-095'!L:N,3,0) -> PL10X2000X12000 | C17: 10*2000*12000 | D17: SA387 GR11CL2 PLATE | E17: 96 | F17: =VLOOKUP(A17,'25-VPI-I-095'!L:BA,25,0) -> 91 | G17: N/A | H17: N/A | I17: N/A | K17: X | L17: N/A | M17: N/A | N17: V | O17: 1.4115956 | P17: 10637.785 | Q17: Chọn GNEE
A18: I95-VTC01-108 | B18: =VLOOKUP(A18,'25-VPI-I-095'!L:N,3,0) -> PL12X2000X12000 | C18: 12*2000*12000 | D18: SA387 GR11CL2 PLATE | E18: 168 | F18: =VLOOKUP(A18,'25-VPI-I-095'!L:BA,25,0) -> 160 | G18: N/A | H18: N/A | I18: N/A | K18: X | L18: N/A | M18: N/A | N18: V | O18: 1.4115956 | P18: 22339.348 | Q18: Chọn GNEE
A19: I95-VTC01-109 | B19: =VLOOKUP(A19,'25-VPI-I-095'!L:N,3,0) -> PL6X1500X6000 | C19: 6*2000*12000 | D19: SA387 GR11CL2 PLATE | E19: 48 | F19: =VLOOKUP(A19,'25-VPI-I-095'!L:BA,25,0) -> 38 | G19: N/A | H19: N/A | I19: N/A | K19: X | L19: N/A | M19: N/A | N19: V | O19: 1.5355956 | P19: 3471.6746 | Q19: Chọn GNEE
A20: I95-VTC01-110 | B20: =VLOOKUP(A20,'25-VPI-I-095'!L:N,3,0) -> PL8X2000X12000 | C20: 8*2000*12000 | D20: SA387 GR11CL2 PLATE | E20: 576 | F20: =VLOOKUP(A20,'25-VPI-I-095'!L:BA,25,0) -> 555 | G20: N/A | H20: N/A | I20: N/A | K20: X | L20: N/A | M20: N/A | N20: V | O20: 1.5115956 | P20: 54678.646 | Q20: Chọn GNEE
A22: IV | B22: Nhân lực/ ManPower
A23: 1 | B23: Thợ Pha cắt / Thợ sắt / Thợ hàn / …
B24: ….
A25: V | B25: Yêu cầu kỹ thuật: Tham chiếu các tài liệu đính kèm/ Technical requirement – refer to document attached
B26: Xếp hạng | L26: 2 | O26: 1
A27: Ghi chú: Tiếp tục công tác mua sắm để đảm báo tiến độ
A28: NGƯỜI ĐỀ NGHỊ/ RECOMMENDATION BY: | C28: NGƯỜI KIỂM TRA/ DEPARTMENT HEAD CHECK BY: | J28: APPROVED BY: PHÊ DUYỆT
J29: Nguyễn Quang Vinh | M29: Hoàng Ngọc Bằng | P29: Đoàn Văn Toàn

Sheet Tân thành
A1: BID ANALYSIS - GIẢI TRÌNH MUA SẮM/ĐẤU THẦU
A3: Project | B3: PROJECT No/ Dự án: 25-VPI-I-095
A4: Dự án
A5: Subject | B5: Cung cấp vật tư chính thép ống đúc A106
A6: Chủ đề
A8: No. | B8: CONTENT | C8: Phạm vi công việc | G8: Dự toán | J8: Đã mua | K8: Đơn vị cung cấp chào giá phần còn lại (VNĐ) | N8: Đơn vị cung cấp chào giá phần còn lại (VNĐ) | Q8: Ghi chú
A9: Item | B9: Description/ Chi tiết | C9: Profile/ Vật tư | D9: Grade/ Mác vật liệu | E9: Số lượng Mua (M) | F9: Số lượng PR (M) | G9: Khối lượng/ Số lượng | H9: Đơn giá (vnd) | I9: Thành tiền (vnd) | J9: Thành tiền (vnd) | K9: Tân Thành | N9: Gnee
K10: Phạm vi | L10: Đơn giá trước VAT (VNĐ/KG) | M10: Thành Tiền | N10: Phạm vi | O10: Đơn giá Tính 26300 VNĐ/USD giá CIF (VNĐ/KG) | P10: Thành Tiền
A11: Tổng | B11: Main-Material / Vật tư chính thép đen | G11: N/A | H11: N/A | I11: ='DT03 (TM)'!G6 -> 5.7151444e+10 | J11: ='Tổng hợp'!J19-M11 -> 4.7567459e+10 | M11: =SUM(M12:M16) -> 48754543 | Q11: =I11-J11-P11-M11 -> 9.5352309e+09
A12: I95-VTC01-067 | B12: =VLOOKUP(A12,'25-VPI-I-095'!L:N,3,0) -> CHS88.9X5.49-6000L | C12: Thép ống Ø89 x 5.49 x 6m | D12: A106 | E12: 23.5 | F12: =E12+2.5 -> 26 | G12: N/A | H12: N/A | I12: N/A | J12: N/A | K12: V | L12: 16909.09 | M12: 4717636.1 | N12: V | O12: =0.811636796727484*26300 -> 21346.048 | P12: N//A | Q12: Chọn Tân Thành
A13: I95-VTC01-068 | B13: =VLOOKUP(A13,'25-VPI-I-095'!L:N,3,0) -> CHS114.3x6-6000L | C13: Thép ống Ø114.3 x 6.02 x 6m | D13: A106 | E13: 90 | F13: 87 | G13: N/A | H13: N/A | I13: N/A | J13: N/A | K13: V | L13: 16909.09 | M13: 23757271 | N13: V | O13: =0.811636796727484*26300 -> 21346.048 | P13: N//A | Q13: Chọn Tân Thành
A14: I95-VTC01-069 | B14: =VLOOKUP(A14,'25-VPI-I-095'!L:N,3,0) -> CHS114.3x8.6-6000L | C14: Thép ống Ø114.3 x 8.56 x 6m | D14: A106 | E14: 36 | F14: 36 | G14: N/A | H14: N/A | I14: N/A | J14: N/A | K14: V | L14: 16909.09 | M14: 13121454 | N14: V | O14: =0.811636796727484*26300 -> 21346.048 | P14: N//A | Q14: Chọn Tân Thành
A15: I95-VTC01-070 | B15: =VLOOKUP(A15,'25-VPI-I-095'!L:N,3,0) -> CHS168.3X7.1-6000L | C15: Thép ống Ø168 x 7.11 x 6m | D15: A106 | E15: 6 | F15: 6 | G15: N/A | H15: N/A | I15: N/A | J15: N/A | K15: V | L15: 16909.09 | M15: 2739272.6 | N15: V | O15: =0.811636796727484*26300 -> 21346.048 | P15: N//A | Q15: Chọn Tân Thành
A16: I95-VTC01-089 | B16: =VLOOKUP(A16,'25-VPI-I-095'!L:N,3,0) -> CHS168.3X21.9-6000L | C16: Thép ống Ø168 x 22 x 3m | D16: A106 | E16: 3 | F16: =3-0.66312 -> 2.33688 | G16: N/A | H16: N/A | I16: N/A | J16: N/A | K16: V | L16: 17818.18 | M16: 4418908.6 | N16: X | O16: N//A | P16: N//A | Q16: Chọn Tân Thành
B17: Xếp hạng | L17: 1 | O17: 2
A18: Ghi chú: Tiếp tục công tác mua sắm để đảm báo tiến độ
A19: NGƯỜI ĐỀ NGHỊ/ RECOMMENDATION BY: | D19: NGƯỜI KIỂM TRA/ DEPARTMENT HEAD CHECK BY: | J19: APPROVED BY: PHÊ DUYỆT
J20: Nguyễn Quang Vinh | M20: Hoàng Ngọc Bằng | P20: Đoàn Văn Toàn

Sheet Quang thịnh
A1: BID ANALYSIS - GIẢI TRÌNH MUA SẮM/ĐẤU THẦU
A3: Project | B3: PROJECT No/ Dự án: 25-VPI-I-095
A4: Dự án
A5: Subject | B5: Cung cấp vật tư chính thép hình
A6: Chủ đề
A8: No. | B8: CONTENT | C8: Phạm vi công việc | G8: Dự toán | J8: Đã mua | K8: Đơn vị cung cấp chào giá phần còn lại (VNĐ) | N8: Đơn vị cung cấp chào giá phần còn lại (VNĐ) | Q8: Ghi chú
A9: Item | B9: Description/ Chi tiết | C9: Profile/ Vật tư | D9: Grade/ Mác vật liệu | E9: Số lượng Mua (M) | F9: Số lượng PR (M) | G9: Khối lượng/ Số lượng | H9: Đơn giá (vnd) | I9: Thành tiền (vnd) | J9: Thành tiền (vnd) | K9: QUANG THỊNH | N9: Hùng Nguyên
K10: Phạm vi | L10: Đơn giá trước VAT (VNĐ/KG) | M10: Thành Tiền | N10: Phạm vi | O10: Đơn giá trước VAT (VNĐ/KG) | P10: Thành Tiền
A11: Tổng | B11: Main-Material / Vật tư chính thép đen | G11: N/A | H11: N/A | I11: ='DT03 (TM)'!G6 -> 5.7151444e+10 | J11: ='Tổng hợp'!J19 -> 4.7616213e+10 | M11: =SUM(M12:M13) -> 161743930 | Q11: =I11-J11-P11-M11 -> 9.373487e+09
A12: I95-VTC01-103 | B12: =VLOOKUP(A12,'25-VPI-I-095'!L:N,3,0) -> CHS48.3X3.6-6000L | C12: Thép ống đen 48,3 x 3,68 x 6.000 mm | D12: SS400/A53 | E12: 1662 | F12: =VLOOKUP(A12,'25-VPI-I-095'!L6:DF319,89,0) -> 0 | G12: N/A | H12: N/A | I12: N/A | J12: N/A | K12: V | L12: 15454.55 | M12: 104009122 | N12: V | O12: =17350/1.1 -> 15772.727 | P12: N//A | Q12: Chọn Quang Thịnh
A13: I95-VTC01-104 | B13: =VLOOKUP(A13,'25-VPI-I-095'!L:N,3,0) -> CHS48.3X5.1-6000L | C13: Thép ống đen 48,3 x 5,08 x 6.000 mm | D13: SS400/A53 | E13: 678 | F13: =VLOOKUP(A13,'25-VPI-I-095'!L7:DF320,89,0) -> 0 | G13: N/A | H13: N/A | I13: N/A | J13: N/A | K13: V | L13: 15727.27 | M13: 57734808 | N13: V | O13: =17950/1.1 -> 16318.182 | P13: N//A | Q13: Chọn Quang Thịnh
B14: Xếp hạng | L14: 1 | O14: 2
A15: Ghi chú: Tiếp tục công tác mua sắm để đảm báo tiến độ
A16: NGƯỜI ĐỀ NGHỊ/ RECOMMENDATION BY: | E16: NGƯỜI KIỂM TRA/ DEPARTMENT HEAD CHECK BY: | J16: APPROVED BY: PHÊ DUYỆT
J17: Nguyễn Quang Vinh | M17: Hoàng Ngọc Bằng | P17: Đoàn Văn Toàn

Sheet Ngọc hiếu 095 26-1
A1: BID ANALYSIS - GIẢI TRÌNH MUA SẮM/ĐẤU THẦU
A3: Project | B3: PROJECT No/ Dự án: 25-VPI-I-095
A4: Dự án
A5: Subject | B5: Cung cấp vật tư chính thép hình
A6: Chủ đề
A8: No. | B8: CONTENT | C8: Phạm vi công việc | G8: Dự toán | J8: Đã mua | K8: Đơn vị cung cấp chào giá phần còn lại (VNĐ) | N8: Đơn vị cung cấp chào giá phần còn lại (VNĐ) | Q8: Đơn vị cung cấp chào giá phần còn lại (VNĐ) | T8: Ghi chú
A9: Item | B9: Description/ Chi tiết | C9: Profile/ Vật tư | D9: Grade/ Mác vật liệu | E9: Số lượng Mua (M) | F9: Số lượng PR (M) | G9: Khối lượng/ Số lượng | H9: Đơn giá (vnd) | I9: Thành tiền (vnd) | J9: Thành tiền (vnd) | K9: NGỌC HIẾU | N9: Hùng Nguyên | Q9: APEC
K10: Phạm vi | L10: Đơn giá trước VAT (VNĐ/KG) | M10: Thành Tiền | N10: Phạm vi | O10: Đơn giá trước VAT (VNĐ/KG) | P10: Thành Tiền | Q10: Phạm vi | R10: Đơn giá trước VAT (VNĐ/KG) | S10: Thành Tiền
A11: Tổng | B11: Main-Material / Vật tư chính thép đen | G11: N/A | H11: N/A | I11: ='DT03 (TM)'!G6 -> 5.7151444e+10 | J11: ='Tổng hợp'!J19+'Tổng hợp'!J24-'Vật tư bạt trần toàn'!M11 -> 5.0294192e+10 | M11: =SUM(M12:M29) -> 1898049693 | T11: =I11-J11-P11-M11 -> 4.9592026e+09
A12: I95-VTC01-022 | B12: =VLOOKUP(A12,'25-VPI-I-095'!L:N,3,0) -> C200X80X7.5X11-12000L | C12: Thép U200*80*7,5*11*12000 = 11 Cây | D12: =VLOOKUP(A12,'25-VPI-I-095'!L:R,4,0) -> SS400 | E12: 132 | F12: =VLOOKUP(A12,'25-VPI-I-095'!L:DF,95,0)+E12 -> 8520 | G12: N/A | H12: N/A | I12: N/A | J12: N/A | K12: V | L12: 17090.91 | M12: 55494185 | N12: V | O12: 17636.36 | P12: N//A | Q12: X | R12: #N/A | S12: N//A | T12: Chọn Ngọc Hiếu
A13: I95-VTC01-031 | B13: =VLOOKUP(A13,'25-VPI-I-095'!L:N,3,0) -> L150X150X12-12000L | C13: Thép V150*150*12*12000 = 8 Cây | D13: =VLOOKUP(A13,'25-VPI-I-095'!L:R,4,0) -> SS400 | E13: 96 | F13: =VLOOKUP(A13,'25-VPI-I-095'!L:DF,95,0)+E13 -> 1572 | G13: N/A | H13: N/A | I13: N/A | J13: N/A | K13: V | L13: 15727.27 | M13: 41221175 | N13: X | O13: #N/A | P13: N//A | Q13: X | R13: #N/A | S13: N//A | T13: Chọn Ngọc Hiếu
A14: I95-VTC01-032 | B14: =VLOOKUP(A14,'25-VPI-I-095'!L:N,3,0) -> L100X100X12-12000L | C14: Thép V100*100*13*12000 = 1 Cây | D14: =VLOOKUP(A14,'25-VPI-I-095'!L:R,4,0) -> SS400 | E14: 12 | F14: =VLOOKUP(A14,'25-VPI-I-095'!L:DF,95,0)+E14 -> 132 | G14: N/A | H14: N/A | I14: N/A | J14: N/A | K14: V | L14: 14545.45 | M14: 3330908 | N14: X | O14: #N/A | P14: N//A | Q14: X | R14: #N/A | S14: N//A | T14: Chọn Ngọc Hiếu
A15: I95-VTC01-051 | B15: =VLOOKUP(A15,'25-VPI-I-095'!L:N,3,0) -> L50X50X6-6000L | C15: Thép V50*50*6*6000 = 5 Cây | D15: =VLOOKUP(A15,'25-VPI-I-095'!L:R,4,0) -> SS400 | E15: 30 | F15: =VLOOKUP(A15,'25-VPI-I-095'!L:DF,95,0)+E15 -> 318 | G15: N/A | H15: N/A | I15: N/A | J15: N/A | K15: V | L15: 14000 | M15: 1862000 | N15: V | O15: 14090.91 | P15: N//A | Q15: X | R15: #N/A | S15: N//A | T15: Chọn Ngọc Hiếu
A16: I95-VTC01-123 | B16: =VLOOKUP(A16,'25-VPI-I-095'!L:N,3,0) -> C75X40X5X7-12000L | C16: Thép U75*40*5*7*12000 = 22 Cây | D16: =VLOOKUP(A16,'25-VPI-I-095'!L:R,4,0) -> SS400 | E16: 264 | F16: =VLOOKUP(A16,'25-VPI-I-095'!L:DF,95,0)+E16 -> 528 | G16: N/A | H16: N/A | I16: N/A | J16: N/A | K16: V | L16: 17272.73 | M16: 31557278 | N16: X | O16: #N/A | P16: N//A | Q16: X | R16: #N/A | S16: N//A | T16: Chọn Ngọc Hiếu
A17: I95-VTC01-125 | B17: =VLOOKUP(A17,'25-VPI-I-095'!L:N,3,0) -> RB16-6000L | C17: Thép tròn D16*6000 = 5 Cây | D17: =VLOOKUP(A17,'25-VPI-I-095'!L:R,4,0) -> SS400 | E17: 30 | F17: =VLOOKUP(A17,'25-VPI-I-095'!L:DF,95,0)+E17 -> 60 | G17: N/A | H17: N/A | I17: N/A | J17: N/A | K17: V | L17: 14545.45 | M17: 683636 | N17: V | O17: 15000 | P17: N//A | Q17: X | R17: #N/A | S17: N//A | T17: Chọn Ngọc Hiếu
A18: Tổng | B18: Packing-Material / Vật tư đóng kiện | G18: N/A | H18: N/A | J18: ='Tổng hợp'!J26 -> 0 | T18: =I18-J18-P18-M18 -> 0
A19: I95-VDK-002 | B19: =VLOOKUP(A19,'25-VPI-I-095'!L:N,3,0) -> L75X75X6 | C19: Thép V75*75*6*12000 = 78 Cây | D19: =VLOOKUP(A19,'25-VPI-I-095'!L:R,4,0) -> SS400 | E19: 936 | F19: =VLOOKUP(A19,'25-VPI-I-095'!L:DF,95,0)+E19 -> 1884 | G19: N/A | H19: N/A | I19: N/A | J19: N/A | K19: V | L19: 14000 | M19: 89768000 | N19: V | O19: 14090.91 | P19: N//A | Q19: X | R19: #N/A | S19: N//A | T19: Chọn Ngọc Hiếu
A20: I95-VDK-004 | B20: =VLOOKUP(A20,'25-VPI-I-095'!L:N,3,0) -> C100X50X5X7.5-12000L | C20: Thép U100*48*5,3**12000 TQ = 319 Cây | D20: =VLOOKUP(A20,'25-VPI-I-095'!L:R,4,0) -> SS400 | E20: 3828 | F20: =VLOOKUP(A20,'25-VPI-I-095'!L:DF,95,0)+E20 -> 8928 | G20: N/A | H20: N/A | I20: N/A | J20: N/A | K20: V | L20: 13909.09 | M20: 532439965 | N20: V | O20: 14272.73 | P20: N//A | Q20: X | R20: #N/A | S20: N//A | T20: Chọn Ngọc Hiếu
A21: I95-VDK-005 | B21: =VLOOKUP(A21,'25-VPI-I-095'!L:N,3,0) -> H100X100X6X8-12000L | C21: Thép H100*100*6*8*12000 = 32 Cây | D21: =VLOOKUP(A21,'25-VPI-I-095'!L:R,4,0) -> SS400 | E21: 384 | F21: =VLOOKUP(A21,'25-VPI-I-095'!L:DF,95,0)+E21 -> 876 | G21: N/A | H21: N/A | I21: N/A | J21: N/A | K21: V | L21: 16727.27 | M21: 108559982 | N21: V | O21: 17454.55 | P21: N//A | Q21: X | R21: #N/A | S21: N//A | T21: Chọn Ngọc Hiếu
A22: I95-VDK-006 | B22: =VLOOKUP(A22,'25-VPI-I-095'!L:N,3,0) -> H125X125X6.5X9-12000L | C22: Thép H125*125*6,5*9*12000 = 26 Cây | D22: =VLOOKUP(A22,'25-VPI-I-095'!L:R,4,0) -> SS400 | E22: 312 | F22: =VLOOKUP(A22,'25-VPI-I-095'!L:DF,95,0)+E22 -> 924 | G22: N/A | H22: N/A | I22: N/A | J22: N/A | K22: V | L22: 16727.27 | M22: 123162889 | N22: V | O22: 17454.55 | P22: N//A | Q22: X | R22: #N/A | S22: N//A | T22: Chọn Ngọc Hiếu
A23: I95-VDK-007 | B23: =VLOOKUP(A23,'25-VPI-I-095'!L:N,3,0) -> H150X150X7X10-12000L | C23: Thép H150*150*7*10*12000 = 28 Cây | D23: =VLOOKUP(A23,'25-VPI-I-095'!L:R,4,0) -> SS400 | E23: 336 | F23: =VLOOKUP(A23,'25-VPI-I-095'!L:DF,95,0)+E23 -> 768 | G23: N/A | H23: N/A | I23: N/A | J23: N/A | K23: V | L23: 16363.64 | M23: 171000038 | N23: V | O23: 17454.55 | P23: N//A | Q23: X | R23: #N/A | S23: N//A | T23: Chọn Ngọc Hiếu
A24: I95-VDK-008 | B24: =VLOOKUP(A24,'25-VPI-I-095'!L:N,3,0) -> H150X75X5X7-12000L | C24: Thép I150*75*5*7*12000 = 54 Cây | D24: =VLOOKUP(A24,'25-VPI-I-095'!L:R,4,0) -> SS400 | E24: 648 | F24: =VLOOKUP(A24,'25-VPI-I-095'!L:DF,95,0)+E24 -> 1440 | G24: N/A | H24: N/A | I24: N/A | J24: N/A | K24: V | L24: 15363.64 | M24: 139378942 | N24: V | O24: 17454.55 | P24: N//A | Q24: X | R24: #N/A | S24: N//A | T24: Chọn Ngọc Hiếu
A25: I95-VDK-009 | B25: =VLOOKUP(A25,'25-VPI-I-095'!L:N,3,0) -> H200X100X5.5X8-12000L | C25: Thép I200*100*5,5*8*12000 = 26 Cây | D25: =VLOOKUP(A25,'25-VPI-I-095'!L:R,4,0) -> SS400 | E25: 312 | F25: =VLOOKUP(A25,'25-VPI-I-095'!L:DF,95,0)+E25 -> 876 | G25: N/A | H25: N/A | I25: N/A | J25: N/A | K25: V | L25: 16181.82 | M25: 105521648 | N25: V | O25: 17454.55 | P25: N//A | Q25: X | R25: #N/A | S25: N//A | T25: Chọn Ngọc Hiếu
A26: I95-VDK-010 | B26: =VLOOKUP(A26,'25-VPI-I-095'!L:N,3,0) -> H300X150X6.5X9-12000L | C26: Thép I300*150*6,5*9*12000 = 22 Cây | D26: =VLOOKUP(A26,'25-VPI-I-095'!L:R,4,0) -> SS400 | E26: =2*132 -> 264 | F26: =VLOOKUP(A26,'25-VPI-I-095'!L:DF,95,0)+E26 -> 528 | G26: N/A | H26: N/A | I26: N/A | J26: N/A | K26: V | L26: 17454.55 | M26: =2*84549840 -> 169099680 | N26: V | O26: 17454.55 | P26: N//A | Q26: X | R26: #N/A | S26: N//A | T26: Chọn Ngọc Hiếu
A27: I95-VDK-011 | B27: =VLOOKUP(A27,'25-VPI-I-095'!L:N,3,0) -> L50X50X4-6000L | C27: Thép V50*50*4*6000 = 1115 Cây | D27: =VLOOKUP(A27,'25-VPI-I-095'!L:R,4,0) -> SS400 | E27: 6690 | F27: =VLOOKUP(A27,'25-VPI-I-095'!L:DF,95,0)+E27 -> 10794 | G27: N/A | H27: N/A | I27: N/A | J27: N/A | K27: V | L27: 14000 | M27: 286594000 | N27: V | O27: 14090.91 | P27: N//A | Q27: X | R27: #N/A | S27: N//A | T27: Chọn Ngọc Hiếu
A28: I95-VDK-012 | B28: =VLOOKUP(A28,'25-VPI-I-095'!L:N,3,0) -> L60X60X5-6000L | C28: Thép V60*60*5*12000 = 22 Cây | D28: =VLOOKUP(A28,'25-VPI-I-095'!L:R,4,0) -> SS400 | E28: 264 | F28: =VLOOKUP(A28,'25-VPI-I-095'!L:DF,95,0)+E28 -> 528 | G28: N/A | H28: N/A | I28: N/A | J28: N/A | K28: V | L28: 14000 | M28: 16814000 | N28: V | O28: 14090.91 | P28: N//A | Q28: X | R28: #N/A | S28: N//A | T28: Chọn Ngọc Hiếu
A29: I95-VDK-018 | B29: =VLOOKUP(A29,'25-VPI-I-095'!L:N,3,0) -> PL1.5X1220X2440 | C29: Thép tấm 1,5*1250*2500 = 36 Cây | D29: =VLOOKUP(A29,'25-VPI-I-095'!L:R,4,0) -> SS400 | E29: 112.5 | F29: =VLOOKUP(A29,'25-VPI-I-095'!L:DF,95,0)+E29 -> 225 | G29: N/A | H29: N/A | I29: N/A | J29: N/A | K29: V | L29: 16272.73 | M29: 21561367 | N29: X | O29: #N/A | P29: N//A | Q29: X | R29: #N/A | S29: N//A | T29: Chọn Ngọc Hiếu
B30: Xếp hạng | L30: 1 | O30: 2 | R30: 3
A31: Ghi chú: Tiếp tục công tác mua sắm để đảm báo tiến độ
A32: NGƯỜI ĐỀ NGHỊ/ RECOMMENDATION BY: | E32: NGƯỜI KIỂM TRA/ DEPARTMENT HEAD CHECK BY: | M32: APPROVED BY: PHÊ DUYỆT
M33: Nguyễn Quang Vinh | P33: Hoàng Ngọc Bằng | S33: Đoàn Văn Toàn

Sheet Ngọc hiếu 095 24-12
A1: BID ANALYSIS - GIẢI TRÌNH MUA SẮM/ĐẤU THẦU
A3: Project | B3: PROJECT No/ Dự án: 25-VPI-I-095
A4: Dự án
A5: Subject | B5: Cung cấp vật tư chính thép hình
A6: Chủ đề
A8: No. | B8: CONTENT | C8: Phạm vi công việc | G8: Dự toán | J8: Đã mua | K8: Đơn vị cung cấp chào giá phần còn lại (VNĐ) | N8: Đơn vị cung cấp chào giá phần còn lại (VNĐ) | Q8: Đơn vị cung cấp chào giá phần còn lại (VNĐ) | T8: Ghi chú
A9: Item | B9: Description/ Chi tiết | C9: Profile/ Vật tư | D9: Grade/ Mác vật liệu | E9: Số lượng Mua (M) | F9: Số lượng PR (M) | G9: Khối lượng/ Số lượng | H9: Đơn giá (vnd) | I9: Thành tiền (vnd) | J9: Thành tiền (vnd) | K9: NGỌC HIẾU | N9: Hùng Nguyên | Q9: APEC
K10: Phạm vi | L10: Đơn giá trước VAT (VNĐ/KG) | M10: Thành Tiền | N10: Phạm vi | O10: Đơn giá trước VAT (VNĐ/KG) | P10: Thành Tiền | Q10: Phạm vi | R10: Đơn giá trước VAT (VNĐ/KG) | S10: Thành Tiền
A11: Tổng | B11: Main-Material / Vật tư chính thép đen | G11: N/A | H11: N/A | I11: ='DT03 (TM)'!G6 -> 5.7151444e+10 | J11: ='Tổng hợp'!J19 -> 4.7616213e+10 | M11: =SUM(M12:M22) -> 350328560 | T11: =I11-J11-P11-M11 -> 9.1849023e+09
A12: I95-VTC01-028 | B12: =VLOOKUP(A12,'25-VPI-I-095'!L:N,3,0) -> L100X100X7-12000L | C12: Thép V100*100*7*12000 | D12: =VLOOKUP(A12,'25-VPI-I-095'!L:R,4,0) -> SS400 | E12: 84 | F12: =VLOOKUP(A12,'25-VPI-I-095'!L6:DF319,87,0) -> 0 | G12: N/A | H12: N/A | I12: N/A | J12: N/A | K12: V | L12: 13909.09 | M12: 12504272 | N12: V | O12: 14090.91 | P12: N//A | Q12: V | R12: 14363.636 | S12: =VLOOKUP(D12,'[164]DA 95'!$B$20:$N$31,13,0) -> #N/A | T12: Chọn Ngọc Hiếu
A13: I95-VTC01-030 | B13: =VLOOKUP(A13,'25-VPI-I-095'!L:N,3,0) -> L90X90X6-12000L | C13: Thép V90*90*6*12000 | D13: =VLOOKUP(A13,'25-VPI-I-095'!L:R,4,0) -> SS400 | E13: 24 | F13: =VLOOKUP(A13,'25-VPI-I-095'!L7:DF320,87,0) -> 0 | G13: N/A | H13: N/A | I13: N/A | J13: N/A | K13: V | L13: 13909.09 | M13: 2767909 | N13: V | O13: 14090.91 | P13: N//A | Q13: V | R13: 14545.455 | S13: =VLOOKUP(D13,'[164]DA 95'!$B$20:$N$31,13,0) -> #N/A | T13: Chọn Ngọc Hiếu
A14: I95-VTC01-034 | B14: =VLOOKUP(A14,'25-VPI-I-095'!L:N,3,0) -> C200X90X8X13.5-12000L | C14: Thép U200*90*8*13,5*12000 | D14: =VLOOKUP(A14,'25-VPI-I-095'!L:R,4,0) -> SS400 | E14: 156 | F14: =VLOOKUP(A14,'25-VPI-I-095'!L8:DF321,87,0) -> 0 | G14: N/A | H14: N/A | I14: N/A | J14: N/A | K14: V | L14: 17272.73 | M14: 81648195 | N14: X | O14: #N/A | P14: N//A | Q14: V | R14: 17727.273 | S14: =VLOOKUP(D14,'[164]DA 95'!$B$20:$N$31,13,0) -> #N/A | T14: Chọn Ngọc Hiếu
A15: I95-VTC01-052 | B15: =VLOOKUP(A15,'25-VPI-I-095'!L:N,3,0) -> L100X100X10-12000L | C15: Thép V100*100*10*12000 | D15: =VLOOKUP(A15,'25-VPI-I-095'!L:R,4,0) -> SS400 | E15: 264 | F15: =VLOOKUP(A15,'25-VPI-I-095'!L10:DF322,87,0) -> 0 | G15: N/A | H15: N/A | I15: N/A | J15: N/A | K15: V | L15: 13909.09 | M15: 54718360 | N15: V | O15: 14090.91 | P15: N//A | Q15: V | R15: 14363.636 | S15: =VLOOKUP(D15,'[164]DA 95'!$B$20:$N$31,13,0) -> #N/A | T15: Chọn Ngọc Hiếu
A16: I95-VTC01-061 | B16: =VLOOKUP(A16,'25-VPI-I-095'!L:N,3,0) -> L75x75x6-12000L | C16: Thép V75*75*6*12000 | D16: =VLOOKUP(A16,'25-VPI-I-095'!L:R,4,0) -> SS400 | E16: 672 | F16: =VLOOKUP(A16,'25-VPI-I-095'!L11:DF323,87,0) -> 0 | G16: N/A | H16: N/A | I16: N/A | J16: N/A | K16: V | L16: 13909.09 | M16: 64023541 | N16: V | O16: 14090.91 | P16: N//A | Q16: V | R16: 14363.636 | S16: =VLOOKUP(D16,'[164]DA 95'!$B$20:$N$31,13,0) -> #N/A | T16: Chọn Ngọc Hiếu
A17: I95-VTC01-079 | B17: =VLOOKUP(A17,'25-VPI-I-095'!L:N,3,0) -> RB13-6000L | C17: Thép tròn D14*6000 | D17: =VLOOKUP(A17,'25-VPI-I-095'!L:R,4,0) -> SS400 | E17: 36 | F17: =VLOOKUP(A17,'25-VPI-I-095'!L12:DF324,87,0) -> 0 | G17: N/A | H17: N/A | I17: N/A | J17: N/A | K17: V | L17: 14181.82 | M17: 609818 | N17: V | O17: 15272.73 | P17: N//A | Q17: X | R17: #N/A | S17: =VLOOKUP(D17,'[164]DA 95'!$B$20:$N$31,13,0) -> #N/A | T17: Chọn Ngọc Hiếu
A18: I95-VTC01-083 | B18: =VLOOKUP(A18,'25-VPI-I-095'!L:N,3,0) -> C250X90X9X13-12000L | C18: Thép U250*90*9*13*12000 | D18: =VLOOKUP(A18,'25-VPI-I-095'!L:R,4,0) -> SS400 | E18: 96 | F18: =VLOOKUP(A18,'25-VPI-I-095'!L13:DF325,87,0) -> 0 | G18: N/A | H18: N/A | I18: N/A | J18: N/A | K18: V | L18: 17272.73 | M18: 57380009 | N18: X | O18: #N/A | P18: N//A | Q18: V | R18: 17727.273 | S18: =VLOOKUP(D18,'[164]DA 95'!$B$20:$N$31,13,0) -> #N/A | T18: Chọn Ngọc Hiếu
A19: I95-VTC01-088 | B19: =VLOOKUP(A19,'25-VPI-I-095'!L:N,3,0) -> C100X50X5X7.5-12000L | C19: Thép U100*50*5*7,5*12000 | D19: =VLOOKUP(A19,'25-VPI-I-095'!L:R,4,0) -> SS400 | E19: 216 | F19: =VLOOKUP(A19,'25-VPI-I-095'!L14:DF326,87,0) -> 0 | G19: N/A | H19: N/A | I19: N/A | J19: N/A | K19: V | L19: 17090.91 | M19: 34557820 | N19: V | O19: 17500 | P19: N//A | Q19: V | R19: 17727.273 | S19: =VLOOKUP(D19,'[164]DA 95'!$B$20:$N$31,13,0) -> #N/A | T19: Chọn Ngọc Hiếu
A20: I95-VTC01-114 | B20: =VLOOKUP(A20,'25-VPI-I-095'!L:N,3,0) -> L65X65X6-12000L | C20: Thép V65*65*6*12000 | D20: =VLOOKUP(A20,'25-VPI-I-095'!L:R,4,0) -> SS400 | E20: 240 | F20: =VLOOKUP(A20,'25-VPI-I-095'!L15:DF327,87,0) -> 0 | G20: N/A | H20: N/A | I20: N/A | J20: N/A | K20: V | L20: 13909.09 | M20: 19723090 | N20: V | O20: 14090.91 | P20: N//A | Q20: V | R20: 14545.455 | S20: =VLOOKUP(D20,'[164]DA 95'!$B$20:$N$31,13,0) -> #N/A | T20: Chọn Ngọc Hiếu
A21: I95-VTC01-029 | B21: =VLOOKUP(A21,'25-VPI-I-095'!L:N,3,0) -> L120X120X8-12000L | C21: Thép V120*120*8*12000 | D21: =VLOOKUP(A21,'25-VPI-I-095'!L:R,4,0) -> SS400 | E21: 96 | F21: =VLOOKUP(A21,'25-VPI-I-095'!L16:DF328,87,0) -> 0 | G21: N/A | H21: N/A | I21: N/A | J21: N/A | K21: V | L21: 15000 | M21: 21165000 | N21: V | O21: #N/A | P21: N//A | Q21: V | R21: 15636.364 | S21: =VLOOKUP(D21,'[164]DA 95'!$B$20:$N$31,13,0) -> #N/A | T21: Chọn Ngọc Hiếu
A22: I95-VTC01-021 | B22: =VLOOKUP(A22,'25-VPI-I-095'!L:N,3,0) -> C150X75X6.5X10-12000L | C22: Thép U150*75*6,5*10*6000 | D22: =VLOOKUP(A22,'25-VPI-I-095'!L:R,4,0) -> SS400 | E22: 0 | F22: =VLOOKUP(A22,'25-VPI-I-095'!L17:DF329,87,0) -> 0 | G22: N/A | H22: N/A | I22: N/A | J22: N/A | K22: V | L22: 17090.91 | M22: 1230546 | N22: V | O22: #N/A | P22: N//A | Q22: X | R22: #N/A | S22: =VLOOKUP(D22,'[164]DA 95'!$B$20:$N$31,13,0) -> #N/A | T22: Chọn Ngọc Hiếu
B23: Xếp hạng | L23: 1 | O23: 2 | R23: 3
A24: Ghi chú: Tiếp tục công tác mua sắm để đảm báo tiến độ
A25: NGƯỜI ĐỀ NGHỊ/ RECOMMENDATION BY: | E25: NGƯỜI KIỂM TRA/ DEPARTMENT HEAD CHECK BY: | M25: APPROVED BY: PHÊ DUYỆT
M26: Nguyễn Quang Vinh | P26: Hoàng Ngọc Bằng | S26: Đoàn Văn Toàn

Sheet Giải tình JFE
A1: BID ANALYSIS - GIẢI TRÌNH MUA SẮM/ĐẤU THẦU
A3: Project | B3: PROJECT No/ Dự án: 25-VPI-I-095
A4: Dự án
A5: Subject | B5: Cung cấp vật tư chính thép hình của JFE
A6: Chủ đề
A8: No. | B8: CONTENT | C8: Phạm vi công việc | H8: Dự toán | K8: Đã mua | L8: Đơn vị cung cấp chào giá phần còn lại (USD) | O8: Đơn vị cung cấp chào giá phần còn lại (VNĐ) | R8: Đơn vị cung cấp chào giá phần còn lại (VNĐ) | U8: Ghi chú
A9: Item | B9: Description/ Chi tiết | C9: Profile/ Vật tư | D9: Grade/ Mác vật liệu | E9: Số lượng Mua (M) | F9: Khối lượng Mua (Kg) | G9: Số lượng PR (M) | H9: Khối lượng/ Số lượng | I9: Đơn giá (vnd) | J9: Thành tiền (vnd) | K9: Thành tiền (vnd) | L9: JFE | O9: NGỌC HIẾU/APEC | R9: HÙNG NGUYÊN
L10: Phạm vi | M10: Đơn giá (USD/KG) | N10: Thành Tiền (CIF HAI PHONG) 26300USD/KG | O10: Phạm vi | P10: Đơn giá trước VAT (VNĐ/KG) | Q10: Thành Tiền (Không có VAT) | R10: Phạm vi | S10: Đơn giá trước VAT (VNĐ/KG) | T10: Thành Tiền (Không có VAT)
A11: Tổng | B11: Main-Material / Vật tư chính thép đen | H11: N/A | I11: N/A | J11: ='DT03 (TM)'!G6 -> 5.7151444e+10 | K11: ='Tổng hợp'!J19 -> 4.7616213e+10 | N11: =SUM(N12:N12)*(26300) -> 1257729120 | Q11: =SUM(Q12:Q12)*26300 -> 0 | U11: =J11-K11-Q11-N11 -> 8.2775018e+09
A12: I95-VTC01-022 | B12: =VLOOKUP(A12,'25-VPI-I-095'!L:N,3,0) -> C200X80X7.5X11-12000L | C12: C200X80X7.5X11-12000L | D12: SS400 | E12: =270*12 -> 3240 | F12: =E12*24.6 -> 79704 | G12: =VLOOKUP(A12,'25-VPI-I-095'!L:DG,87,0) -> 0 | H12: N/A | I12: N/A | J12: N/A | L12: V | M12: 0.6 | N12: =M12*E12*24.6 -> 47822.4 | O12: V | P12: =18800/1.1 -> 17090.909 | Q12: N/A | R12: V | S12: =19200/1.1 -> 17454.545 | T12: N/A | U12: Chọn JFE
A13: Ghi chú: Tiếp tục công tác mua sắm để đảm báo tiến độ
A14: NGƯỜI ĐỀ NGHỊ/ RECOMMENDATION BY: | E14: NGƯỜI KIỂM TRA/ DEPARTMENT HEAD CHECK BY: | N14: APPROVED BY: PHÊ DUYỆT
N15: Nguyễn Quang Vinh | Q15: Hoàng Ngọc Bằng | T15: Đoàn Văn Toàn

Sheet Giải tình gnee né
A1: BID ANALYSIS - GIẢI TRÌNH MUA SẮM/ĐẤU THẦU
A3: Project | B3: PROJECT No/ Dự án: 25-VPI-I-095
A4: Dự án
A5: Subject | B5: Cung cấp vật tư chính thép trắng
A6: Chủ đề
A8: No. | B8: CONTENT | C8: Phạm vi công việc | H8: Dự toán | K8: Đã mua | L8: Đơn vị cung cấp chào giá phần còn lại (USD) | O8: Đơn vị cung cấp chào giá phần còn lại (USD) | R8: Ghi chú
A9: Item | B9: Description/ Chi tiết | C9: Profile/ Vật tư | D9: Grade/ Mác vật liệu | E9: Grade/ Mác vật liệu PR | F9: Số lượng Mua (M2M) | G9: Số lượng PR (M2/M) | H9: Khối lượng/ Số lượng | I9: Đơn giá (vnd) | J9: Thành tiền (vnd) | K9: Thành tiền (vnd) | L9: GNEE | O9: GLOBAL
L10: Phạm vi | M10: Đơn giá (USD/KG) | N10: Thành Tiền (Giá CIF HAI PHONG) 26300VNĐ/KG | O10: Phạm vi | P10: Đơn giá (USD/KG) | Q10: Thành Tiền (Giá CIF HAI PHONG) 26300VNĐ/KG
A11: Tổng | B11: Main-Material / Vật tư chính thép trắng | J11: ='DT03 (TM)'!G12 -> 6.2338967e+09 | K11: ='Tổng hợp'!J20 -> 1.1194758e+10 | N11: =SUM(N12:N17)*26300 -> 5.6361778e+08 | Q11: =SUM(Q12:Q17)*26300 -> 0 | R11: =J11-K11-Q11-N11 -> -5.5244789e+09
A12: I95-VTC02-021 | B12: =VLOOKUP(A12,'25-VPI-I-095'!L:N,3,0) -> PL12X1500X6000 | C12: 12*1500*6000 | D12: SUS310S PLATE | E12: =VLOOKUP(A12,'25-VPI-I-095'!L:R,4,0) -> SUS310S | F12: 27 | G12: =VLOOKUP(A12,'25-VPI-I-095'!L:DF,87,0) -> 0 | H12: N/A | I12: N/A | J12: N/A | L12: V | M12: 5.009 | N12: 12950.269 | O12: V | P12: 5.009 | Q12: N/A | R12: Chọn GNEE GNEE đồng ý thanh toán theo hình thức 100% DP AT SIGHT
A13: I95-VTC02-022 | B13: =VLOOKUP(A13,'25-VPI-I-095'!L:N,3,0) -> PL6X1500X6000 | C13: 6*1500*6000 | D13: SUS310S PLATE | E13: =VLOOKUP(A13,'25-VPI-I-095'!L:R,4,0) -> SUS310S | F13: 9 | G13: =VLOOKUP(A13,'25-VPI-I-095'!L:DF,87,0) -> 0 | H13: N/A | I13: N/A | J13: N/A | L13: V | M13: 5.019 | N13: 2162.6871 | O13: V | P13: 5.019 | Q13: N/A
A14: I95-VTC02-039 | B14: =VLOOKUP(A14,'25-VPI-I-095'!L:N,3,0) -> PL1X1220X2440 | C14: 1*1220*2440 | D14: SUH409 PLATE | E14: =VLOOKUP(A14,'25-VPI-I-095'!L:R,4,0) -> SUH409 | F14: 306.6104 | G14: =VLOOKUP(A14,'25-VPI-I-095'!L:DF,87,0) -> 46058 | H14: N/A | I14: N/A | J14: N/A | L14: V | M14: 1.395 | N14: 3290.3865 | O14: V | P14: 1.395 | Q14: N/A
A15: I95-VTC02-040 | B15: =VLOOKUP(A15,'25-VPI-I-095'!L:N,3,0) -> PL1X1220X2440 | C15: 1*1220*2440 | D15: SUS304 PLATE | E15: =VLOOKUP(A15,'25-VPI-I-095'!L:R,4,0) -> SUS304 | F15: 38.6984 | G15: =VLOOKUP(A15,'25-VPI-I-095'!L:DF,87,0) -> 46058 | H15: N/A | I15: N/A | J15: N/A | L15: V | M15: 2.257 | N15: 692.4476 | O15: V | P15: 2.257 | Q15: N/A
A16: I95-VTC02-041 | B16: =VLOOKUP(A16,'25-VPI-I-095'!L:N,3,0) -> PL1X1220X2440 | C16: 1*1220*2440 | D16: SUS309S PLATE | E16: =VLOOKUP(A16,'25-VPI-I-095'!L:R,4,0) -> SUS309S | F16: 65.4896 | G16: =VLOOKUP(A16,'25-VPI-I-095'!L:DF,87,0) -> 46058 | H16: N/A | I16: N/A | J16: N/A | L16: V | M16: 4.428 | N16: 2318.5008 | O16: V | P16: 4.428 | Q16: N/A
A17: I95-VTC02-042 | B17: =VLOOKUP(A17,'25-VPI-I-095'!L:N,3,0) -> RB12-6000L | C17: 12*6000 | D17: SUS304 ROUND BAR | E17: =VLOOKUP(A17,'25-VPI-I-095'!L:R,4,0) -> SUS304 | F17: 6 | G17: =VLOOKUP(A17,'25-VPI-I-095'!L:DF,87,0) -> 46058 | H17: N/A | I17: N/A | J17: N/A | L17: V | M17: 2.971 | N17: 16.0434 | O17: V | P17: 2.971 | Q17: N/A
A19: IV | B19: Nhân lực/ ManPower
A20: 1 | B20: Thợ Pha cắt / Thợ sắt / Thợ hàn / …
B21: ….
A22: V | B22: Yêu cầu kỹ thuật: Tham chiếu các tài liệu đính kèm/ Technical requirement – refer to document attached
B23: Xếp hạng | M23: 2
A24: Ghi chú: Tổng giá trị phần thép trắng tấm đang vượt quá dự toán ' Tiếp tục công tác mua sắm để đảm báo tiến độ/ Phần giá trị tăng sẽ báo sale để điều chỉnh cách tính tiền với khách hàng
A25: NGƯỜI ĐỀ NGHỊ/ RECOMMENDATION BY: | C25: NGƯỜI KIỂM TRA/ DEPARTMENT HEAD CHECK BY: | K25: APPROVED BY: PHÊ DUYỆT
K26: Nguyễn Quang Vinh | N26: Hoàng Ngọc Bằng | Q26: Đoàn Văn Toàn

Sheet Giải tình Global đợt 2
A1: BID ANALYSIS - GIẢI TRÌNH MUA SẮM/ĐẤU THẦU
A3: Project | B3: PROJECT No/ Dự án: 25-VPI-I-095
A4: Dự án
A5: Subject | B5: Cung cấp vật tư chính thép tấm của GLOBAL ASIA MATERIAL CO., LIMITED
A6: Chủ đề
A8: No. | B8: CONTENT | C8: Phạm vi công việc | G8: Dự toán | J8: Đã mua | K8: Đơn vị cung cấp chào giá phần còn lại (USD) | N8: Đơn vị cung cấp chào giá phần còn lại (VNĐ) | Q8: Ghi chú
A9: Item | B9: Description/ Chi tiết | C9: Profile/ Vật tư | D9: Grade/ Mác vật liệu | E9: Số lượng Mua (M) | F9: Số lượng PR (M) | G9: Khối lượng/ Số lượng | H9: Đơn giá (vnd) | I9: Thành tiền (vnd) | J9: Thành tiền (vnd) | K9: GLOBAL ASIA MATERIAL CO., LIMITED | N9: GNEE
K10: Phạm vi | L10: Đơn giá (USD/KG) | M10: Thành Tiền (Giá CIF) 26300VNĐ/USD | N10: Phạm vi | O10: Đơn giá (USD/KG) | P10: Thành Tiền (Giá CIF) 26300VNĐ/USD
A11: Tổng | B11: Main-Material / Vật tư chính thép đen | G11: N/A | H11: N/A | I11: ='DT03 (TM)'!G6 -> 5.7151444e+10 | J11: ='Tổng hợp'!J19 -> 4.7616213e+10 | M11: =SUM(M12:M12)*26300 -> 513056192 | P11: =SUM(P12:P12)*26300 -> 0 | Q11: =I11-J11-M11 -> 9.0221747e+09
A12: I95-VTC01-119 | B12: =VLOOKUP(A12,'25-VPI-I-095'!L:N,3,0) -> PL6X1500X6000 | C12: PL6x2100x11000 | D12: A387_GR11_CL2 | E12: =11*2.1*11 -> 254.1 | F12: =VLOOKUP(A12,'25-VPI-I-095'!L:DG,89,0) -> 254.1 | G12: N/A | H12: N/A | I12: N/A | J12: N/A | K12: V | L12: 1.63 | M12: 19507.84 | N12: N/A | O12: N/A | P12: N/A | Q12: Chọn GLOBAL ASIA MATERIAL CO., LIMITED
B13: Xếp hạng | L13: 1 | O13: 2
A14: Ghi chú: Tiếp tục công tác mua sắm để đảm báo tiến độ
A15: NGƯỜI ĐỀ NGHỊ/ RECOMMENDATION BY: | E15: NGƯỜI KIỂM TRA/ DEPARTMENT HEAD CHECK BY: | J15: APPROVED BY: PHÊ DUYỆT
J16: Nguyễn Quang Vinh | L16: Hoàng Ngọc Bằng | O16: Đoàn Văn Toàn

Sheet Giải tình MCL đợt 6
A1: BID ANALYSIS - GIẢI TRÌNH MUA SẮM/ĐẤU THẦU
A3: Project | B3: PROJECT No/ Dự án: 25-VPI-I-095
A4: Dự án
A5: Subject | B5: Cung cấp vật tư chính thép hình của MCL
A6: Chủ đề
A8: No. | B8: CONTENT | C8: Phạm vi công việc | G8: Dự toán | J8: Đã mua | K8: Đơn vị cung cấp chào giá phần còn lại (USD) | N8: Đơn vị cung cấp chào giá phần còn lại (USD) | Q8: Đơn vị cung cấp chào giá phần còn lại (VNĐ) | T8: Đơn vị cung cấp chào giá phần còn lại (VNĐ) | W8: Ghi chú
A9: Item | B9: Description/ Chi tiết | C9: Profile/ Vật tư | D9: Grade/ Mác vật liệu | E9: Số lượng Mua (M) | F9: Số lượng PR (M) | G9: Khối lượng/ Số lượng | H9: Đơn giá (vnd) | I9: Thành tiền (vnd) | J9: Thành tiền (vnd) | K9: MCL | N9: GNEE | Q9: NGỌC HIẾU/APEC | T9: HÙNG NGUYÊN
K10: Phạm vi | L10: Đơn giá (USD/KG) | M10: Thành Tiền (CIF HAI PHONG) | N10: Phạm vi | O10: Đơn giá (USD/KG) | P10: Thành Tiền (Không có VAT) | Q10: Phạm vi | R10: Đơn giá trước VAT (VNĐ/KG) | S10: Thành Tiền (Không có VAT) | T10: Phạm vi | U10: Đơn giá trước VAT (VNĐ/KG) | V10: Thành Tiền (Không có VAT)
A11: Tổng | B11: Main-Material / Vật tư chính thép đen | G11: N/A | H11: N/A | I11: ='DT03 (TM)'!G6 -> 5.7151444e+10 | J11: ='Tổng hợp'!J19 -> 4.7616213e+10 | M11: =SUM(M12:M18)*(26300) -> 1.0491906e+09 | S11: =SUM(S12:S18)*26300 -> 0 | W11: =I11-J11-S11-M11 -> 8.4860403e+09
A12: I95-VTC01-023 | B12: =VLOOKUP(A12,'25-VPI-I-095'!L:N,3,0) -> H200X200X8X12-12000L | C12: H200X200X8X12-12000L | D12: SS400 | E12: 204 | F12: =VLOOKUP(A12,'25-VPI-I-095'!L:DG,87,0) -> 0 | G12: N/A | H12: N/A | I12: N/A | K12: V | L12: 0.598 | M12: 6087.64 | N12: V | O12: 0.6776368 | P12: N/A | Q12: V | R12: =19000/1.1 -> 17272.727 | S12: N/A | T12: V | U12: =19200/1.1 -> 17454.545 | V12: N/A | W12: Chọn MCL
A13: I95-VTC01-024 | B13: =VLOOKUP(A13,'25-VPI-I-095'!L:N,3,0) -> H294X200X8X12-12000L | C13: H294X200X8X12-12000L | D13: SS400 | E13: 96 | F13: =VLOOKUP(A13,'25-VPI-I-095'!L:DG,87,0) -> 0 | G13: N/A | H13: N/A | I13: N/A | K13: V | L13: 0.598 | M13: 3203.486 | N13: V | O13: 0.6776368 | P13: N/A | Q13: V | R13: =19000/1.1 -> 17272.727 | S13: N/A | T13: X | U13: =19200/1.1 -> 17454.545 | V13: N/A | W13: Chọn MCL
A14: I95-VTC01-065 | B14: =VLOOKUP(A14,'25-VPI-I-095'!L:N,3,0) -> H500X200X10X16-12000L | C14: H500X200X10X16-12000L | D14: SS400 | E14: 48 | F14: =VLOOKUP(A14,'25-VPI-I-095'!L:DG,87,0) -> 0 | G14: N/A | H14: N/A | I14: N/A | K14: V | L14: 0.598 | M14: 2528.942 | N14: V | O14: 0.6776368 | P14: N/A | Q14: V | R14: =19000/1.1 -> 17272.727 | S14: N/A | T14: V | U14: =19200/1.1 -> 17454.545 | V14: N/A | W14: Chọn MCL
A15: I95-VTC01-084 | B15: =VLOOKUP(A15,'25-VPI-I-095'!L:N,3,0) -> H194X150X6X9-12000L | C15: H194X150X6X9-12000L | D15: SS400 | E15: 912 | F15: =VLOOKUP(A15,'25-VPI-I-095'!L:DG,87,0) -> 0 | G15: N/A | H15: N/A | I15: N/A | K15: V | L15: 0.598 | M15: 16306.862 | N15: V | O15: 0.6776368 | P15: N/A | Q15: V | R15: =19000/1.1 -> 17272.727 | S15: N/A | T15: V | U15: =19200/1.1 -> 17454.545 | V15: N/A | W15: Chọn MCL
A16: I95-VTC01-085 | B16: =VLOOKUP(A16,'25-VPI-I-095'!L:N,3,0) -> H244X175X7X11-12000L | C16: H244X175X7X11-12000L | D16: SS400 | E16: 420 | F16: =VLOOKUP(A16,'25-VPI-I-095'!L:DG,87,0) -> 0 | G16: N/A | H16: N/A | I16: N/A | K16: V | L16: 0.598 | M16: 10950.576 | N16: V | O16: 0.6776368 | P16: N/A | Q16: V | R16: =19000/1.1 -> 17272.727 | S16: N/A | T16: V | U16: =19200/1.1 -> 17454.545 | V16: N/A | W16: Chọn MCL
A17: I95-VTC01-115 | B17: =VLOOKUP(A17,'25-VPI-I-095'!L:N,3,0) -> H200X100X5.5X8-12000L | C17: H200X100X5.5X8-12000L | D17: SS400 | E17: 24 | F17: =VLOOKUP(A17,'25-VPI-I-095'!L:DG,87,0) -> 46085 | G17: N/A | H17: N/A | I17: N/A | K17: V | L17: 0.598 | M17: 300.196 | N17: V | O17: 0.6776368 | P17: N/A | Q17: V | R17: =19000/1.1 -> 17272.727 | S17: N/A | T17: V | U17: =19200/1.1 -> 17454.545 | V17: N/A | W17: Chọn MCL
A18: I95-VTC01-116 | B18: =VLOOKUP(A18,'25-VPI-I-095'!L:N,3,0) -> H250X250X9X14-6000L | C18: H250X250X9X14-12000L | D18: SS400 | E18: 12 | F18: =VLOOKUP(A18,'25-VPI-I-095'!L:DG,87,0) -> 46085 | G18: N/A | H18: N/A | I18: N/A | K18: V | L18: 0.598 | M18: 515.476 | N18: V | O18: 0.6776368 | P18: N/A | Q18: V | R18: =19000/1.1 -> 17272.727 | S18: N/A | T18: V | U18: =19200/1.1 -> 17454.545 | V18: N/A | W18: Chọn MCL
A20: IV | B20: Nhân lực/ ManPower
A21: 1 | B21: Thợ Pha cắt / Thợ sắt / Thợ hàn / …
B22: ….
A23: V | B23: Yêu cầu kỹ thuật: Tham chiếu các tài liệu đính kèm/ Technical requirement – refer to document attached
B24: Xếp hạng | L24: 1 | O24: 2 | R24: 3 | U24: 4
A25: Ghi chú: Tiếp tục công tác mua sắm để đảm báo tiến độ
A26: NGƯỜI ĐỀ NGHỊ/ RECOMMENDATION BY: | E26: NGƯỜI KIỂM TRA/ DEPARTMENT HEAD CHECK BY: | M26: APPROVED BY: PHÊ DUYỆT
M27: Nguyễn Quang Vinh | S27: Hoàng Ngọc Bằng | V27: Đoàn Văn Toàn

Sheet Vật tư phụ VSAN (2)
A1: BID ANALYSIS - GIẢI TRÌNH MUA SẮM/ĐẤU THẦU
A3: Project | B3: PROJECT No/ Dự án: 25-VPI-I-095
A4: Dự án
A5: Subject | B5: Cung cấp vật tư phụ kiện bu lông/ đinh bảo ôn
A6: Chủ đề
A8: No. | B8: CONTENT | C8: Phạm vi công việc | H8: Dự toán | K8: Đơn vị cung cấp chào giá (vnđ) | N8: Ghi chú
A9: Item | B9: Description/ Chi tiết | C9: Profile/ Vật tư | D9: Grade/ Mác vật liệu | E9: Mặt hàng | F9: ĐVT | G9: Số lượng | H9: Khối lượng/ Số lượng | I9: Đơn giá (vnd) | J9: Thành tiền (vnd) | K9: VSAN
K10: Phạm vi | L10: Đơn giá (VND) | M10: Thành Tiền (Không có VAT)
A11: Tổng | G11: =SUM(G13:G64) -> 305786 | H11: N/A | I11: N/A | J11: ='DT03 (TM)'!G19 -> 8.3322017e+09 | M11: =SUM(M13:M64) -> 4842086070
A12: Insulation-Material / Vật tư bảo ôn
A13: I95-VTC04-005 | B13: NUT (%C min 0.04%)-phải lắp vào được stud M10 | C13: NUT M10-ISO4032-SUS304 | D13: JIS G4303-SUS304 | E13: =VLOOKUP(A13,'25-VPI-I-095'!L:BW,25,0) -> 0 | F13: Cái | G13: 52105 | H13: N/A | I13: N/A | K13: V | L13: 1520 | M13: =L13*G13 -> 79199600
A14: I95-VTC04-006 | B14: NUT (%C min 0.04%)-phải lắp vào được stud M12 | C14: NUT M12-ISO4032-SUS304 | D14: JIS G4303-SUS304 | E14: =VLOOKUP(A14,'25-VPI-I-095'!L:BW,25,0) -> 0 | F14: Cái | G14: 47960 | H14: N/A | I14: N/A | K14: V | L14: 2130 | M14: =L14*G14 -> 102154800
A15: I95-VTC04-007 | B15: NUT-phải lắp vào được stud M12 | C15: NUT M12-ISO4032-SUS309S | D15: JIS G4303-SUS309S | E15: =VLOOKUP(A15,'25-VPI-I-095'!L:BW,25,0) -> 0 | F15: Cái | G15: 21423 | H15: N/A | I15: N/A | K15: V | L15: 9880 | M15: =L15*G15 -> 211659240
A16: I95-VTC04-008 | B16: WASHER TRÒN | C16: ROUND WASHER OD76XID11X2mm-SUH409 | D16: JIS G4312-SUH409 | E16: =VLOOKUP(A16,'25-VPI-I-095'!L:BW,25,0) -> 0 | F16: Cái | G16: 52105 | H16: N/A | I16: N/A | K16: V | L16: 8970 | M16: =L16*G16 -> 467381850
A17: I95-VTC04-009 | B17: WASHER TRÒN( % C min 0.04%) | C17: ROUND WASHER OD76XID14X2.6mm-SUS304 | D17: JIS G4303-SUS304 | E17: =VLOOKUP(A17,'25-VPI-I-095'!L:BW,25,0) -> 0 | F17: Cái | G17: 7426 | H17: N/A | I17: N/A | K17: V | L17: 14060 | M17: =L17*G17 -> 104409560
A18: I95-VTC04-010 | B18: WASHER TRÒN | C18: ROUND WASHER OD76XID14X2.6mm-SUS309S | D18: JIS G4303-SUS309S | E18: =VLOOKUP(A18,'25-VPI-I-095'!L:BW,25,0) -> 0 | F18: Cái | G18: 21423 | H18: N/A | I18: N/A | K18: V | L18: 27360 | M18: =L18*G18 -> 586133280
A19: I95-VTC04-011 | B19: WASHER VUÔNG( % C min 0.04%) | C19: SQUARE WASHER 76X76XID14X2.6mm-SUS304 | D19: JIS G4303-SUS304 | E19: =VLOOKUP(A19,'25-VPI-I-095'!L:BW,25,0) -> 0 | F19: Cái | G19: 40400 | H19: N/A | I19: N/A | K19: V | L19: 17480 | M19: =L19*G19 -> 706192000
A20: I95-VTC04-012 | B20: ĐINH HÀN( % C min 0.04%) | C20: STUD-RB10X108-REN M10X1.5- 32mm-SUS304 | D20: JIS G4303-SUS304 | E20: =VLOOKUP(A20,'25-VPI-I-095'!L:BW,25,0) -> 0 | F20: Cái | G20: 21 | H20: N/A | I20: N/A | K20: V | L20: 14360 | M20: =L20*G20 -> 301560
A21: I95-VTC04-013 | B21: ĐINH HÀN( % C min 0.04%) | C21: STUD-RB10X111-REN M10X1.5- 32mm-SUS304 | D21: JIS G4303-SUS304 | E21: =VLOOKUP(A21,'25-VPI-I-095'!L:BW,25,0) -> 0 | F21: Cái | G21: 2105 | H21: N/A | I21: N/A | K21: V | L21: 14520 | M21: =L21*G21 -> 30564600
A22: I95-VTC04-014 | B22: ĐINH HÀN( % C min 0.04%) | C22: STUD-RB10X114-REN M10X1.5- 35mm-SUS304 | D22: JIS G4303-SUS304 | E22: =VLOOKUP(A22,'25-VPI-I-095'!L:BW,25,0) -> 0 | F22: Cái | G22: 586 | H22: N/A | I22: N/A | K22: V | L22: 14740 | M22: =L22*G22 -> 8637640
A23: I95-VTC04-015 | B23: ĐINH HÀN( % C min 0.04%) | C23: STUD-RB10X117-REN M10X1.5- 32mm-SUS304 | D23: JIS G4303-SUS304 | E23: =VLOOKUP(A23,'25-VPI-I-095'!L:BW,25,0) -> 0 | F23: Cái | G23: 954 | H23: N/A | I23: N/A | K23: V | L23: 14970 | M23: =L23*G23 -> 14281380
A24: I95-VTC04-016 | B24: ĐINH HÀN( % C min 0.04%) | C24: STUD-RB10X133-REN M10X1.5- 32mm-SUS304 | D24: JIS G4303-SUS304 | E24: =VLOOKUP(A24,'25-VPI-I-095'!L:BW,25,0) -> 0 | F24: Cái | G24: 10217 | H24: N/A | I24: N/A | K24: V | L24: 15960 | M24: =L24*G24 -> 163063320
... A57: I95-VTC04-049 | B57: ĐINH HÀN( % C min 0.04%) | C57: STUD-RB10X374-REN M10X1.5- 32mm-SUS304 | D57: JIS G4303-SUS304 | E57: =VLOOKUP(A57,'25-VPI-I-095'!L:BW,25,0) -> 0 | F57: Cái | G57: 38 | H57: N/A | I57: N/A | K57: V | L57: 33820 | M57: =L57*G57 -> 1285160
A58: Bolt-Material / Vật tư bulong, phụ kiện | E58: =VLOOKUP(A58,'25-VPI-I-095'!L:BW,25,0) -> #N/A | O58: =SUM(M59:M64) -> 99973200
A59: I95-VPK-013 | B59: CHỐT-MUA THEO BV | C59: CLEVIS PIN Ø12x52-DIN 1444-MẠ ĐIỆN PHÂN | D59: JIS G3101-SS400-MG | E59: =VLOOKUP(A59,'25-VPI-I-095'!L:BW,25,0) -> 96 | F59: Cái | G59: 296 | H59: N/A | I59: N/A | K59: V | L59: 100000 | M59: =L59*G59 -> 29600000
A60: I95-VPK-014 | B60: GIỮ CHỐT-MUA THEO BV | C60: COTTER PIN Ø3.2x25L-DIN 94- MẠ ĐIỆN PHÂN | D60: JIS G3101-SS400-MG | E60: =VLOOKUP(A60,'25-VPI-I-095'!L:BW,25,0) -> 96 | F60: Cái | G60: 296 | H60: N/A | I60: N/A | K60: V | L60: 5000 | M60: =L60*G60 -> 1480000
A61: I95-VPK-015 | B61: eye bolt-MẠ XEM BV | C61: EYE BOLT M14+2NUT+1WASHER-xEM BẢN VẼ | D61: SS400 | E61: =VLOOKUP(A61,'25-VPI-I-095'!L:BW,25,0) -> 12 | F61: Cái | G61: 36 | H61: N/A | I61: N/A | K61: V | L61: 250000 | M61: =L61*G61 -> 9000000
A62: I95-VPK-016 | B62: eye bolt-MẠ XEM BV | C62: EYE BOLT M16x137(1 EYE BOLT+01 WASHER+ 01 HANDLE NUT) -xEM BẢN VẼ | D62: SS400 | E62: =VLOOKUP(A62,'25-VPI-I-095'!L:BW,25,0) -> 96 | F62: Cái | G62: 296 | H62: N/A | I62: N/A | K62: V | L62: 160000 | M62: =L62*G62 -> 47360000
A63: I95-VPK-017 | B63: ĐỆM | C63: WASHER-M12-ISO7089-8-HDG | D63: ZINC | E63: =VLOOKUP(A63,'25-VPI-I-095'!L:BW,25,0) -> 96 | F63: Cái | G63: 296 | H63: N/A | I63: N/A | K63: V | L63: 600 | M63: =L63*G63 -> 177600
A64: I95-VPK-019 | B64: NUT-KHÔNG MẠ | C64: NUT-3/4"-A563-BLACK | D64: A-563 HEX NUT | E64: =VLOOKUP(A64,'25-VPI-I-095'!L:BW,25,0) -> 100 | F64: Cái | G64: 782 | H64: N/A | I64: N/A | K64: V | L64: 15800 | M64: =L64*G64 -> 12355600
B65: Đơn giá tổng hợp
A66: II | B66: Khối lượng dự kiến giao (Kg )/ Estimated weight (Kg):
A67: 1 | B67: … | C67: kg
A68: 2 | B68: …
A69: III | B69: Tiến độ/ Schedule | C69: Bắt đầu/ Start | D69: Kết thúc/ Finish
A70: 1 | B70: ….
A72: IV | B72: Nhân lực/ ManPower
A73: 1 | B73: Thợ Pha cắt / Thợ sắt / Thợ hàn / …
B74: ….
A75: V | B75: Yêu cầu kỹ thuật: Tham chiếu các tài liệu đính kèm/ Technical requirement – refer to document attached
B76: Xếp hạng | L76: 1
A77: Ghi chú:Phòng Thương Mại tiếp tục công tác mua sắm để đảm báo tiến độ
A78: NGƯỜI ĐỀ NGHỊ/ RECOMMENDATION BY: | C78: NGƯỜI KIỂM TRA/ DEPARTMENT HEAD CHECK BY: | G78: APPROVED BY: PHÊ DUYỆT
G79: Nguyễn Quang Vinh | I79: Hoàng Ngọc Bằng | K79: Đoàn Văn Toàn

Sheet Đợt mới ngọc hiếu 095
A1: BID ANALYSIS - GIẢI TRÌNH MUA SẮM/ĐẤU THẦU
A3: Project | B3: PROJECT No/ Dự án: 25-VPI-I-095
A4: Dự án
A5: Subject | B5: Cung cấp vật tư chính thép hình
A6: Chủ đề
A8: No. | B8: CONTENT | C8: Phạm vi công việc | G8: Dự toán | J8: Đã mua | K8: Đơn vị cung cấp chào giá phần còn lại (VNĐ) | N8: Đơn vị cung cấp chào giá phần còn lại (VNĐ) | Q8: Đơn vị cung cấp chào giá phần còn lại (VNĐ) | T8: Ghi chú
A9: Item | B9: Description/ Chi tiết | C9: Profile/ Vật tư | D9: Grade/ Mác vật liệu | E9: Số lượng Mua (M) | F9: Số lượng PR (M) | G9: Khối lượng/ Số lượng | H9: Đơn giá (vnd) | I9: Thành tiền (vnd) | J9: Thành tiền (vnd) | K9: NGỌC HIẾU | N9: Hùng Nguyên | Q9: APEC
K10: Phạm vi | L10: Đơn giá trước VAT (VNĐ/KG) | M10: Thành Tiền | N10: Phạm vi | O10: Đơn giá trước VAT (VNĐ/KG) | P10: Thành Tiền | Q10: Phạm vi | R10: Đơn giá trước VAT (VNĐ/KG) | S10: Thành Tiền
A11: Tổng | B11: Main-Material / Vật tư chính thép đen | G11: N/A | H11: N/A | I11: ='DT03 (TM)'!G6 -> 5.7151444e+10 | J11: ='Tổng hợp'!J19 -> 4.7616213e+10 | M11: =SUM(M12:M20) -> 2557532786 | T11: =I11-J11-P11-M11 -> 6.9776981e+09
A12: I95-VTC01-021 | B12: =VLOOKUP(A12,'25-VPI-I-095'!L:N,3,0) -> C150X75X6.5X10-12000L | C12: Thép U 150X75X6.5X10-12000L | D12: SS400 | E12: 120 | F12: =VLOOKUP(A12,'25-VPI-I-095'!L6:DF319,89,0) -> 0 | G12: N/A | H12: N/A | I12: N/A | J12: N/A | K12: V | L12: 17090.91 | M12: 36916366 | N12: V | O12: =19250/1.1 -> 17500 | P12: N//A | Q12: X | R12: #N/A | S12: =VLOOKUP(D12,'[164]DA 95'!$B$20:$N$31,13,0) -> #N/A | T12: Chọn Ngọc Hiếu
A13: I95-VTC01-022 | B13: =VLOOKUP(A13,'25-VPI-I-095'!L:N,3,0) -> C200X80X7.5X11-12000L | C13: Thép U200*80*7,5*11*12000 | D13: SS400 | E13: 3780 | F13: =VLOOKUP(A13,'25-VPI-I-095'!L7:DF320,89,0) -> 3240 | G13: N/A | H13: N/A | I13: N/A | J13: N/A | K13: V | L13: 17090.91 | M13: 1589249539 | N13: V | O13: =19250/1.1 -> 17500 | P13: N//A | Q13: X | R13: #N/A | S13: =VLOOKUP(D13,'[164]DA 95'!$B$20:$N$31,13,0) -> #N/A | T13: Chọn Ngọc Hiếu
A14: I95-VTC01-030 | B14: =VLOOKUP(A14,'25-VPI-I-095'!L:N,3,0) -> L90X90X6-12000L | C14: Thép V90*90*6*12000 | D14: SS400 | E14: 384 | F14: =VLOOKUP(A14,'25-VPI-I-095'!L8:DF321,89,0) -> 0 | G14: N/A | H14: N/A | I14: N/A | J14: N/A | K14: V | L14: 13909.09 | M14: 44230906 | N14: X | O14: N//A | P14: N//A | Q14: V | R14: 14090.909 | S14: N//A | T14: Chọn Ngọc Hiếu
A15: I95-VTC01-034 | B15: =VLOOKUP(A15,'25-VPI-I-095'!L:N,3,0) -> C200X90X8X13.5-12000L | C15: Thép U200*90*8*13,5*12000 | D15: SS400 | E15: 168 | F15: =VLOOKUP(A15,'25-VPI-I-095'!L12:DF322,89,0) -> 0 | G15: N/A | H15: N/A | I15: N/A | J15: N/A | K15: V | L15: 17090.91 | M15: 86992732 | N15: V | O15: 17500 | P15: N//A | Q15: X | R15: #N/A | S15: =VLOOKUP(D15,'[164]DA 95'!$B$20:$N$31,13,0) -> #N/A | T15: Chọn Ngọc Hiếu
A16: I95-VTC01-052 | B16: =VLOOKUP(A16,'25-VPI-I-095'!L:N,3,0) -> L100X100X10-12000L | C16: Thép V100*100*10*12000 | D16: SS400 | E16: 324 | F16: =VLOOKUP(A16,'25-VPI-I-095'!L13:DF323,89,0) -> 0 | G16: N/A | H16: N/A | I16: N/A | J16: N/A | K16: V | L16: 13909.09 | M16: 67153087 | N16: X | O16: N//A | P16: N//A | Q16: V | R16: 14090.909 | S16: N//A | T16: Chọn Ngọc Hiếu
A17: I95-VTC01-061 | B17: =VLOOKUP(A17,'25-VPI-I-095'!L:N,3,0) -> L75x75x6-12000L | C17: Thép V75*75*6*12000 | D17: SS400 | E17: 576 | F17: =VLOOKUP(A17,'25-VPI-I-095'!L14:DF324,89,0) -> 0 | G17: N/A | H17: N/A | I17: N/A | J17: N/A | K17: V | L17: 13909.09 | M17: 54885269 | N17: X | O17: N//A | P17: N//A | Q17: X | R17: #N/A | S17: =VLOOKUP(D17,'[164]DA 95'!$B$20:$N$31,13,0) -> #N/A | T17: Chọn Ngọc Hiếu
A18: I95-VTC01-062 | B18: =VLOOKUP(A18,'25-VPI-I-095'!L:N,3,0) -> L90x90x10-12000L | C18: Thép V90*90*10*12000 | D18: SS400 | E18: 456 | F18: =VLOOKUP(A18,'25-VPI-I-095'!L15:DF325,89,0) -> 0 | G18: N/A | H18: N/A | I18: N/A | J18: N/A | K18: V | L18: 15000 | M18: 90975000 | N18: X | O18: N//A | P18: N//A | Q18: V | R18: 14090.909 | S18: N//A | T18: Chọn Ngọc Hiếu
