Workbook
Name \0: #REF!
Name \a: #N/A
Name \a: #N/A
Name \a: #N/A
Name \a: #N/A
Name \a: #N/A
Name \a: #N/A
Name \a: #N/A
Name \a: #N/A
Name \a: #N/A
Name \a: #N/A
Name \a: #N/A
Name \a: #N/A
Name \a: #N/A
Name \a: #N/A
Name \a: #REF!
Name \a: #N/A
Name \a: #N/A
Name \a: #N/A
Name \a: #N/A
Name \a: #N/A
Name \a: #REF!
Name \b: #N/A
Name \c: #N/A
Name \d: #N/A
Name \e: #N/A
Name \f: #N/A
Name \g: #N/A
Name \h: #N/A
Name \h: #N/A
Name \h: #N/A
Name \h: #N/A
Name \h: #N/A
Name \h: #N/A
Name \h: #N/A
Name \h: #N/A
Name \h: #N/A
Name \h: #N/A
Name \h: #N/A
Name \h: #N/A
Name \h: #N/A
Name \h: #N/A
Name \h: #N/A
Name \h: #N/A
Name \h: #N/A
Name \h: #N/A
Name \h: #N/A
Name \h: [1]PP!$IC$5
Name \i: #N/A
Name \i: #N/A
Name \i: #N/A
Name \i: #N/A
Name \i: #N/A
Name \i: #N/A
Name \i: #N/A
Name \i: #N/A
Name \i: #N/A
Name \i: #N/A
Name \i: #N/A
Name \i: #N/A

Sheet Giải tình Hùng nguyên
A1: BID ANALYSIS - GIẢI TRÌNH MUA SẮM/ĐẤU THẦU
A3: Project | B3: PROJECT No/ Dự án: 25-WNC-I-097
A4: Dự án
A5: Subject | B5: Cung cấp vật tư chính thép tấm của Hùng Nguyên
A6: Chủ đề
A8: No. | B8: CONTENT | C8: Phạm vi công việc | H8: Dự toán | K8: Đã mua | L8: Đơn vị cung cấp chào giá phần còn lại (VNĐ) | O8: Đơn vị cung cấp chào giá phần còn lại (VNĐ) | R8: Ghi chú
A9: Item | B9: Description/ Chi tiết | C9: Profile/ Vật tư | D9: Grade/ Mác vật liệu | E9: Số lượng Mua cây) | F9: Số lượng Mua (M) | G9: Số lượng PR (M) | H9: Khối lượng/ Số lượng | I9: Đơn giá (vnd) | J9: Thành tiền (vnd) | K9: Thành tiền (vnd) | L9: HÙNG NGUYÊN | O9: APEC
L10: Phạm vi | M10: Đơn giá trước VAT (VNĐ/KG) | N10: Thành Tiền (Không có VAT) | O10: Phạm vi | P10: Đơn giá trước VAT (VNĐ/KG) | Q10: Thành Tiền (Không có VAT)
A11: Tổng | B11: Main-Material / Vật tư chính thép đen | H11: N/A | I11: N/A | J11: ='DT04 (TM) 1 '!L7 -> 3001944110 | K11: ='DT04 (TM) 1 '!Q7 -> 3.0852474e+09 | N11: =SUM(N12:N17) -> 422127444 | R11: =J11-K11-N11 -> -5.0543075e+08
A12: I97-VTC01-028 | B12: =VLOOKUP(A12,'25-WNC-I-097'!I:CX,3,0) -> PL3X1500X6000 | C12: Thép tấm 3x1500x6000 | D12: =VLOOKUP(A12,'25-WNC-I-097'!I:CX,4,0) -> SS400 | E12: 5 | F12: 45 | G12: =VLOOKUP(A12,'25-WNC-I-097'!I:CX,83,0) -> 0 | H12: N/A | I12: N/A | J12: N/A | L12: V | M12: 13954.55 | N12: 14788334 | O12: X | P12: N/A | Q12: N/A | R12: Chọn Hùng Nguyên
A13: I97-VTC01-030 | B13: =VLOOKUP(A13,'25-WNC-I-097'!I:CX,3,0) -> PL5X1500X6000 | C13: Thép tấm 5x1500x6000 | D13: =VLOOKUP(A13,'25-WNC-I-097'!I:CX,4,0) -> SS400 | E13: 5 | F13: 45 | G13: =VLOOKUP(A13,'25-WNC-I-097'!I:CX,83,0) -> 0 | H13: N/A | I13: N/A | J13: N/A | L13: V | M13: 13954.55 | N13: 24647224 | O13: X | P13: N/A | Q13: N/A | R13: Chọn Hùng Nguyên
A14: I97-VTC01-031 | B14: =VLOOKUP(A14,'25-WNC-I-097'!I:CX,3,0) -> PL6X1500X6000 | C14: Thép tấm 6x1500x6000 | D14: =VLOOKUP(A14,'25-WNC-I-097'!I:CX,4,0) -> SS400 | E14: 4 | F14: 36 | G14: =VLOOKUP(A14,'25-WNC-I-097'!I:CX,83,0) -> 0 | H14: N/A | I14: N/A | J14: N/A | L14: V | M14: 13363.64 | N14: 22659388 | O14: X | P14: 13636.364 | Q14: N/A | R14: Chọn Hùng Nguyên
A15: I97-VTC01-059 | B15: =VLOOKUP(A15,'25-WNC-I-097'!I:CX,3,0) -> PL4x2000x12000 | C15: Thép tấm 4x2000x12000 | D15: =VLOOKUP(A15,'25-WNC-I-097'!I:CX,4,0) -> SS400 | E15: 29 | F15: 696 | G15: =VLOOKUP(A15,'25-WNC-I-097'!I:CX,83,0) -> 0 | H15: N/A | I15: N/A | J15: N/A | L15: V | M15: 13363.64 | N15: 292054334 | O15: X | P15: 13454.545 | Q15: N/A | R15: Chọn Hùng Nguyên
A16: I97-VTC01-060 | B16: =VLOOKUP(A16,'25-WNC-I-097'!I:CX,3,0) -> PL12x2000x12000 | C16: Thép tấm 12x2000x6000 | D16: =VLOOKUP(A16,'25-WNC-I-097'!I:CX,4,0) -> SS400 | E16: 1 | F16: 12 | G16: =VLOOKUP(A16,'25-WNC-I-097'!I:CX,83,0) -> 0 | H16: N/A | I16: N/A | J16: N/A | L16: V | M16: 13363.64 | N16: 15106259 | O16: X | P16: 13363.636 | Q16: N/A | R16: Chọn Hùng Nguyên
A17: I97-VTC01-065 | B17: =VLOOKUP(A17,'25-WNC-I-097'!I:CX,3,0) -> PL6X2000X6000 | C17: Thép tấm 6x2000x6000 | D17: =VLOOKUP(A17,'25-WNC-I-097'!I:CX,4,0) -> SS400 | E17: 7 | F17: 84 | G17: =VLOOKUP(A17,'25-WNC-I-097'!I:CX,83,0) -> 0 | H17: N/A | I17: N/A | J17: N/A | L17: V | M17: 13363.64 | N17: 52871905 | O17: V | P17: 13363.636 | Q17: N/A | R17: Chọn Hùng Nguyên
B18: Xếp hạng | M18: 1 | P18: 2
A19: Ghi chú: Tiếp tục công tác mua sắm để đảm báo tiến độ
A20: NGƯỜI ĐỀ NGHỊ/ RECOMMENDATION BY: | C20: NGƯỜI KIỂM TRA/ DEPARTMENT HEAD CHECK BY: | H20: APPROVED BY: PHÊ DUYỆT
H21: Nguyễn Quang Vinh | N21: Hoàng Ngọc Bằng | Q21: Đoàn Văn Toàn

Sheet Giải tình Ngọc Hiếu 26-2
A1: BID ANALYSIS - GIẢI TRÌNH MUA SẮM/ĐẤU THẦU
A3: Project | B3: PROJECT No/ Dự án: 25-WNC-I-097
A4: Dự án
A5: Subject | B5: Cung cấp vật tư chính thép hình của Ngọc Hiếu ngày 12-2-2026
A6: Chủ đề
A8: No. | B8: CONTENT | C8: Phạm vi công việc | H8: Dự toán | K8: Đã mua | L8: Đơn vị cung cấp chào giá phần còn lại (VNĐ) | O8: Đơn vị cung cấp chào giá phần còn lại (VNĐ) | R8: Đơn vị cung cấp chào giá phần còn lại (VNĐ) | U8: Ghi chú
A9: Item | B9: Description/ Chi tiết | C9: Profile/ Vật tư | D9: Grade/ Mác vật liệu | E9: Số lượng Mua cây) | F9: Số lượng Mua (M) | G9: Số lượng PR (M) | H9: Khối lượng/ Số lượng | I9: Đơn giá (vnd) | J9: Thành tiền (vnd) | K9: Thành tiền (vnd) | L9: HÙNG NGUYÊN | O9: NGỌC HIẾU | R9: APEC
L10: Phạm vi | M10: Đơn giá trước VAT (VNĐ/KG) | N10: Thành Tiền (Không có VAT) | O10: Phạm vi | P10: Đơn giá trước VAT (VNĐ/KG) | Q10: Thành Tiền (Không có VAT) | R10: Phạm vi | S10: Đơn giá trước VAT (VNĐ/KG) | T10: Thành Tiền (Không có VAT)
A11: Tổng | B11: Main-Material / Vật tư chính thép đen | H11: N/A | I11: N/A | J11: ='DT04 (TM) 1 '!L7 -> 3001944110 | K11: ='DT04 (TM) 1 '!Q7 -> 3.0852474e+09 | Q11: =SUM(Q12:Q13) -> 2828000 | U11: =J11-K11-Q11 -> -86131310
A12: I97-VTC01-021 | B12: =VLOOKUP(A12,'25-WNC-I-097'!I:CX,3,0) -> L75X50X7-6000L | C12: Thép góc V75x75x7x6000 | D12: =VLOOKUP(A12,'25-WNC-I-097'!I:CX,4,0) -> SS400 | E12: 2 | F12: =E12*6 -> 12 | G12: =VLOOKUP(A12,'25-WNC-I-097'!I:CX,91,0) -> 0 | H12: N/A | I12: N/A | J12: N/A | L12: X | M12: N/A | N12: N/A | O12: V | P12: 14000 | Q12: 1344000 | R12: X | S12: N/A | T12: N/A | U12: Chọn NGỌC HIẾU
A13: I97-VTC01-051 | B13: =VLOOKUP(A13,'25-WNC-I-097'!I:CX,3,0) -> L50X50X6 | C13: Thép góc L50X50X6x6000 | D13: =VLOOKUP(A13,'25-WNC-I-097'!I:CX,4,0) -> SS400 | E13: 4 | F13: =E13*6 -> 24 | G13: =VLOOKUP(A13,'25-WNC-I-097'!I:CX,91,0) -> 0 | H13: N/A | I13: N/A | J13: N/A | L13: X | M13: N/A | N13: N/A | O13: V | P13: 14000 | Q13: 1484000 | R13: X | S13: N/A | T13: N/A | U13: Chọn NGỌC HIẾU
B14: Xếp hạng | M14: 3 | P14: 1 | S14: 2
A15: Ghi chú: Tiếp tục công tác mua sắm để đảm báo tiến độ
A16: NGƯỜI ĐỀ NGHỊ/ RECOMMENDATION BY: | C16: NGƯỜI KIỂM TRA/ DEPARTMENT HEAD CHECK BY: | K16: APPROVED BY: PHÊ DUYỆT
K17: Nguyễn Quang Vinh | Q17: Hoàng Ngọc Bằng | T17: Đoàn Văn Toàn

Sheet HT-ADH VN Vải bảo ôn
A1: BID ANALYSIS - GIẢI TRÌNH MUA SẮM/ĐẤU THẦU
A3: Project | B3: PROJECT No/ Dự án: 25-WNC-I-097
A4: Dự án
A5: Subject | B5: Cung cấp vật tư vải bảo ôn dự án 097 ngày 09-02-2026
A6: Chủ đề
A8: No. | B8: CONTENT | C8: Phạm vi công việc | F8: Dự toán | I8: Đã mua | J8: Đơn vị cung cấp chào giá phần còn lại (VNĐ) | M8: Đơn vị cung cấp chào giá phần còn lại (VNĐ) | P8: Lựa chọn | Q8: Ghi chú
A9: Item | B9: Description/ Chi tiết | C9: Profile/ Vật tư | D9: Số lượng Mua (Cuộn/50M2) | E9: Số lượng PR (M2) | F9: Khối lượng/ Số lượng | G9: Đơn giá (vnd) | H9: Thành tiền (vnd) | I9: Thành tiền (vnd) | J9: CÔNG TY TNHH SẢN XUẤT & THƯƠNG MẠI HT - ADH VIỆT NAM | M9: KIÊN DŨNG
J10: Phạm vi | K10: Đơn giá trước VAT (VNĐ/CUỘN) | L10: Thành Tiền Chưa có 8% VAT | M10: Phạm vi | N10: Đơn giá trước VAT (VNĐ/CUỘN) | O10: Thành Tiền Chưa có 8% VAT
A11: Tổng | B11: Insulation-Material / Vật tư bảo ôn | F11: N/A | G11: N/A | H11: ='Tổng hợp'!K23 -> 1.9069559e+08 | I11: ='Tổng hợp'!J23 -> 2.0585973e+08 | L11: =SUM(L12:L12) -> 54600000 | O11: =SUM(O12:O12) -> 54600000 | Q11: =H11-I11-L11 -> -69764139
A12: I97-VTC04-004 | B12: vải bảo ôn | C12: vải bảo ôn-WFF108H FIBERGLASS FABRIC HT800 (1mmx1mx50m) | D12: 21 | E12: 1050 | F12: N/A | G12: N/A | H12: N/A | I12: N/A | J12: V | K12: 2600000 | L12: =K12*D12 -> 54600000 | M12: V | N12: 2600000 | O12: 54600000 | P12: HT - ADH VIỆT NAM | Q12: Chọn HT - ADH VIỆT NAM vì hàng đang ở Bắc Ninh
B13: Xếp hạng | K13: 1 | N13: 2
A14: Ghi chú: Tiếp tục công tác mua sắm để đảm báo tiến độ
A15: NGƯỜI ĐỀ NGHỊ/ RECOMMENDATION BY: | D15: NGƯỜI KIỂM TRA/ DEPARTMENT HEAD CHECK BY: | H15: APPROVED BY: PHÊ DUYỆT
H16: Nguyễn Quang Vinh | L16: Hoàng Ngọc Bằng | O16: Đoàn Văn Toàn

Sheet CKTEC- tăng đơ
A1: BID ANALYSIS - GIẢI TRÌNH MUA SẮM/ĐẤU THẦU
A3: Project | B3: PROJECT No/ Dự án: 25-WNC-I-097
A4: Dự án
A5: Subject | B5: Cung cấp vật tư tăng đơ dự án 097 ngày 30-1-2026
A6: Chủ đề
A8: No. | B8: CONTENT | C8: Phạm vi công việc | F8: Dự toán | I8: Đã mua | J8: Đơn vị cung cấp chào giá phần còn lại (VNĐ) | M8: Ghi chú
A9: Item | B9: Description/ Chi tiết | C9: Profile/ Vật tư | D9: Số lượng Mua (Cây) | E9: Số lượng PR (Cây) | F9: Khối lượng/ Số lượng | G9: Đơn giá (vnd) | H9: Thành tiền (vnd) | I9: Thành tiền (vnd) | J9: CKTEC
J10: Phạm vi | K10: Đơn giá trước VAT (VNĐ/CÂY) | L10: Thành Tiền
A11: Tổng | B11: Vật tư chế tạo theo yêu cầu của sản xuất | F11: N/A | G11: N/A | L11: =SUM(L12:L14) -> 38400000 | M11: =-L11 -> -38400000
A12: I97 | B12: Tăng đơ M12x675 | C12: Tăng đơ M12x675 | D12: 20 | E12: 20 | F12: N/A | G12: N/A | H12: N/A | I12: N/A | J12: V | K12: 630000 | L12: 12600000 | M12: Chọn CKTEC
A13: I97 | B13: Tăng đơ M12x927 | C13: Tăng đơ M12x927 | D13: 20 | E13: 20 | F13: N/A | G13: N/A | H13: N/A | I13: N/A | J13: V | K13: 650000 | L13: 13000000 | M13: Chọn CKTEC
A14: I97 | B14: Tăng đơ M12x866 | C14: Tăng đơ M12x866 | D14: 20 | E14: 20 | F14: N/A | G14: N/A | H14: N/A | I14: N/A | J14: V | K14: 640000 | L14: 12800000 | M14: Chọn CKTEC
B15: Xếp hạng | K15: 1
A16: Ghi chú: Tiếp tục công tác mua sắm để đảm báo tiến độ
A17: NGƯỜI ĐỀ NGHỊ/ RECOMMENDATION BY: | D17: NGƯỜI KIỂM TRA/ DEPARTMENT HEAD CHECK BY: | H17: APPROVED BY: PHÊ DUYỆT
H18: Nguyễn Quang Vinh | J18: Hoàng Ngọc Bằng | L18: Đoàn Văn Toàn

Sheet Hùng nguyen 16-1
A1: BID ANALYSIS - GIẢI TRÌNH MUA SẮM/ĐẤU THẦU
A3: Project | B3: PROJECT No/ Dự án: 25-WNC-I-097
A4: Dự án
A5: Subject | B5: Cung cấp vật tư đóng kiện của Hùng Nguyên ngày 16-1-2026
A6: Chủ đề
A8: No. | B8: CONTENT | C8: Phạm vi công việc | G8: Dự toán | J8: Đã mua | K8: Đơn vị cung cấp chào giá phần còn lại (VNĐ) | N8: Đơn vị cung cấp chào giá phần còn lại (VNĐ) | Q8: Ghi chú
A9: Item | B9: Description/ Chi tiết | C9: Profile/ Vật tư | D9: Số lượng Mua (Tấm) | E9: Số lượng Mua (M) | F9: Số lượng PR (M) | G9: Khối lượng/ Số lượng | H9: Đơn giá (vnd) | I9: Thành tiền (vnd) | J9: Thành tiền (vnd) | K9: HÙNG NGUYÊN | N9: APEC
K10: Phạm vi | L10: Đơn giá trước VAT (VNĐ/KG) | M10: Thành Tiền | N10: Phạm vi | O10: Đơn giá trước VAT (VNĐ/KG) | P10: Thành Tiền
A11: Tổng | B11: ='25-WNC-I-097'!J310 -> Packing Material / Vật tư kiện | G11: N/A | H11: N/A | I11: ='DT04 (TM) 1 '!L28 -> 503250000 | J11: ='25-WNC-I-097'!BM310 -> 7.9502514e+08 | M11: =SUM(M12:M12) -> 11406767 | Q11: =I11-J11-P11-M11 -> -3.031819e+08
A12: I97-VDK-031 | B12: PL3x1500x6000 | C12: Thép tấm 3x2000x6000 SS400 | D12: 3 | E12: 36 | F12: 36 | G12: N/A | H12: N/A | I12: N/A | J12: N/A | K12: V | L12: 13454.55 | M12: 11406767 | N12: X | O12: N//A | P12: N//A | Q12: Chọn Hùng Nguyên
B13: Xếp hạng | L13: 1 | O13: 2
A14: Ghi chú: Tiếp tục công tác mua sắm để đảm báo tiến độ
A15: NGƯỜI ĐỀ NGHỊ/ RECOMMENDATION BY: | E15: NGƯỜI KIỂM TRA/ DEPARTMENT HEAD CHECK BY: | J15: APPROVED BY: PHÊ DUYỆT
J16: Nguyễn Quang Vinh | M16: Hoàng Ngọc Bằng | P16: Đoàn Văn Toàn

Sheet Quang thịnh lần 2
A1: BID ANALYSIS - GIẢI TRÌNH MUA SẮM/ĐẤU THẦU
A3: Project | B3: PROJECT No/ Dự án: 25-WNC-I-097
A4: Dự án
A5: Subject | B5: Cung cấp vật tư đóng kiện
A6: Chủ đề
A8: No. | B8: CONTENT | C8: Phạm vi công việc | G8: Dự toán | J8: Đã mua | K8: Đơn vị cung cấp chào giá phần còn lại (VNĐ) | N8: Đơn vị cung cấp chào giá phần còn lại (VNĐ) | Q8: Ghi chú
A9: Item | B9: Description/ Chi tiết | C9: Profile/ Vật tư | D9: Số lượng Mua (Cây) | E9: Số lượng Mua (M) | F9: Số lượng PR (M) | G9: Khối lượng/ Số lượng | H9: Đơn giá (vnd) | I9: Thành tiền (vnd) | J9: Thành tiền (vnd) | K9: QUANG THỊNH PHAT | N9: TITAN
K10: Phạm vi | L10: Đơn giá trước VAT (VNĐ/KG) | M10: Thành Tiền | N10: Phạm vi | O10: Đơn giá trước VAT (VNĐ/KG) | P10: Thành Tiền
A11: Tổng | B11: ='25-WNC-I-097'!J310 -> Packing Material / Vật tư kiện | G11: N/A | H11: N/A | I11: ='DT04 (TM) 1 '!L28 -> 503250000 | J11: ='25-WNC-I-097'!BM310+'Giải tình Huy hoàng'!N11 -> 9.5442614e+08 | M11: =SUM(M12:M12) -> 9259090 | Q11: =I11-J11-P11-M11 -> -4.6043523e+08
A12: I97-VDK-020 | B12: RHS100X50X4 | C12: Thép hộp đen 50 x 100 x 4,0 x 6.000 mm | D12: 11 | E12: 66 | F12: 64 | G12: N/A | H12: N/A | I12: N/A | J12: N/A | K12: V | L12: 15909.09 | M12: 9259090 | N12: V | O12: =18800/1.1 -> 17090.909 | P12: N//A | Q12: Chọn Quang Thịnh Phát
B13: Xếp hạng | L13: 1 | O13: 2
A14: Ghi chú: Tiếp tục công tác mua sắm để đảm báo tiến độ
A15: NGƯỜI ĐỀ NGHỊ/ RECOMMENDATION BY: | E15: NGƯỜI KIỂM TRA/ DEPARTMENT HEAD CHECK BY: | J15: APPROVED BY: PHÊ DUYỆT
J16: Nguyễn Quang Vinh | M16: Hoàng Ngọc Bằng | P16: Đoàn Văn Toàn

Sheet Giải tình IPC
A1: BID ANALYSIS - GIẢI TRÌNH MUA SẮM/ĐẤU THẦU
A3: Project | B3: PROJECT No/ Dự án: 25-WNC-I-097
A4: Dự án
A5: Subject | B5: Cung cấp vật tư chính thép hình của IPC
A6: Chủ đề
A8: No. | B8: CONTENT | C8: Phạm vi công việc | H8: Dự toán | K8: Đã mua | L8: Đơn vị cung cấp chào giá phần còn lại (VNĐ) | O8: Đơn vị cung cấp chào giá phần còn lại (VNĐ) | R8: Đơn vị cung cấp chào giá phần còn lại (VNĐ) | U8: Lựa chọn | V8: Ghi chú
A9: Item | B9: Description/ Chi tiết | C9: Profile/ Vật tư | D9: Grade/ Mác vật liệu | E9: Số lượng Mua cây) | F9: Số lượng Mua (M) | G9: Số lượng PR (M) | H9: Khối lượng/ Số lượng | I9: Đơn giá (vnd) | J9: Thành tiền (vnd) | K9: Thành tiền (vnd) | L9: HÙNG NGUYÊN | O9: IPC | R9: APEC
L10: Phạm vi | M10: Đơn giá trước VAT (VNĐ/KG) | N10: Thành Tiền (Không có VAT) | O10: Phạm vi | P10: Đơn giá trước VAT (VNĐ/KG) | Q10: Thành Tiền (Không có VAT) | R10: Phạm vi | S10: Đơn giá trước VAT (VNĐ/KG) | T10: Thành Tiền (Không có VAT)
A11: Tổng | B11: Main-Material / Vật tư chính thép đen | H11: N/A | I11: N/A | J11: ='DT04 (TM) 1 '!L7 -> 3001944110 | K11: ='DT04 (TM) 1 '!Q7-Q11 -> 3.0739647e+09 | Q11: =SUM(Q12:Q12) -> 11282727 | V11: =J11-K11-Q11 -> -83303310
A12: I97-VTC01-054 | B12: =VLOOKUP(A12,'25-WNC-I-097'!I:CX,3,0) -> L125X75X10 | C12: L130x130x10x12000 | D12: =VLOOKUP(A12,'25-WNC-I-097'!I:CX,4,0) -> SS400 | E12: 3 | F12: 36 | G12: 33.0578 | H12: N/A | I12: N/A | J12: N/A | L12: X | M12: N/A | N12: N/A | O12: V | P12: 15909.09 | Q12: 11282727 | R12: X | S12: N/A | T12: N/A | U12: Chọn IPC | V12: - Vượt quá dự toán
B13: Xếp hạng | M13: 3 | P13: 1 | S13: 2
A14: Ghi chú: Tiếp tục công tác mua sắm để đảm báo tiến độ
A15: NGƯỜI ĐỀ NGHỊ/ RECOMMENDATION BY: | C15: NGƯỜI KIỂM TRA/ DEPARTMENT HEAD CHECK BY: | K15: APPROVED BY: PHÊ DUYỆT
K16: Nguyễn Quang Vinh | Q16: Hoàng Ngọc Bằng | T16: Đoàn Văn Toàn

Sheet Vật tư Đóng kiện trần toàn
A1: BID ANALYSIS - GIẢI TRÌNH MUA SẮM/ĐẤU THẦU
A3: Project | B3: PROJECT No/ Dự án: 25-WNC-I-097
A4: Dự án
A5: Subject | B5: Cung cấp vật tư đóng kiện dự án 097
A6: Chủ đề
A8: No. | B8: CONTENT | C8: Phạm vi công việc | G8: Dự toán | J8: Đã mua | K8: Đơn vị cung cấp chào giá (vnđ) | N8: Lựa chọn | O8: Ghi chú
A9: Item | B9: Description/ Chi tiết | C9: Profile/ Vật tư | D9: Grade/ Mác vật liệu | E9: ĐVT | F9: Số lượng | G9: Khối lượng/ Số lượng | H9: Đơn giá (vnd) | I9: Thành tiền (vnd) | J9: Thành tiền (vnd) | K9: TRẦN TOÀN
K10: Phạm vi | L10: Đơn giá (VND) | M10: Thành Tiền (Không có VAT)
A11: Tổng | B11: Vật tư đóng kiện | G11: N/A | H11: N/A | I11: ='Tổng hợp'!K25 -> 503250000 | J11: ='Tổng hợp'!J25 -> 7.9502514e+08 | M11: =SUM(M12:M12) -> 4810428 | O11: =I11-J11-M11 -> -2.9658556e+08
A12: I97-VDK-018 | B12: BẠT DA KÍCH THƯỚC 7000X4200- SỐ LƯỢNG 05 TẤM | C12: Bạt Da I97- VDK-018 ( 7000mm x 4200mm ) x 3 tấm | D12: BẠT DA CHỐNG NƯỚC 2 LỚP-KHUYÊN @500 | E12: M2 | F12: 88.2 | G12: N/A | H12: N/A | I12: N/A | K12: V | L12: 50500 | M12: 4810428 | N12: Trần Toàn | O12: - Đã vượt dự toán - Giá trị vượt dự toán chưa có phần vật tư tận dụng
B13: Xếp hạng | L13: 1
A14: Ghi chú: PTM tiếp tục triển khai công tác mua hàng
A15: NGƯỜI ĐỀ NGHỊ/ RECOMMENDATION BY: | C15: NGƯỜI KIỂM TRA/ DEPARTMENT HEAD CHECK BY: | I15: APPROVED BY: PHÊ DUYỆT
H16: Nguyễn Quang Vinh | K16: Hoàng Ngọc Bằng | N16: Đoàn Văn Toàn

Sheet Giải tình Hoàng Hà vit 26-1
A1: BID ANALYSIS - GIẢI TRÌNH MUA SẮM/ĐẤU THẦU
A3: Project | B3: PROJECT No/ Dự án: 25-WNC-I-097
A4: Dự án
A5: Subject | B5: Cung cấp vật tư đóng kiện Hoàng Hà 26-1
A6: Chủ đề
A8: No. | B8: CONTENT | C8: Phạm vi công việc | H8: Dự toán | K8: Đã mua | L8: Đơn vị cung cấp chào giá (vnđ) | O8: Ghi chú
A9: Item | B9: Description/ Chi tiết | C9: Profile/ Vật tư | D9: Grade/ Mác vật liệu | E9: Số lượng Mua | F9: Số lượng PR | G9: Đơn vị | H9: Khối lượng/ Số lượng | I9: Đơn giá (vnd) | J9: Thành tiền (vnd) | K9: Thành tiền (vnd) | L9: HOÀNG HÀ
L10: Phạm vi | M10: Đơn giá (VND) | N10: Thành Tiền (Không có VAT)
A11: Tổng | B11: Packing Material / Vật tư kiện | H11: N/A | I11: N/A | J11: ='DT04 (TM) 1 '!L28 -> 503250000 | K11: ='Tổng hợp'!J25 -> 7.9502514e+08 | N11: =SUM(N12:N12) -> 473000 | O11: =J11-K11-N11 -> -2.9224814e+08
A12: I97-VDK-032 | B12: BULONG | C12: BOLT-M24X60(1B+1N)-ISO4017-8.8-MẠ KẼM | D12: BOLT-M24X60(1B+1N)-ISO4017-8.8-MẠ KẼMM24x60Mạ kẽm | E12: 22 | F12: 22 | G12: Cái | H12: N/A | I12: N/A | J12: N/A | K12: N/A | L12: V | M12: 21500 | N12: =M12*F12 -> 473000 | O12: HOÀNG Hà
B13: Xếp hạng | M13: 1
A14: Ghi chú: Giá trị mua hàng đã vượt quá dự toán ' Tiếp tục công tác mua sắm để đảm báo tiến độ
A15: NGƯỜI ĐỀ NGHỊ/ RECOMMENDATION BY: | C15: NGƯỜI KIỂM TRA/ DEPARTMENT HEAD CHECK BY: | G15: APPROVED BY: PHÊ DUYỆT
G16: Nguyễn Quang Vinh | J16: Hoàng Ngọc Bằng | M16: Đoàn Văn Toàn

Sheet Giải tình Hoàng Hà vit
A1: BID ANALYSIS - GIẢI TRÌNH MUA SẮM/ĐẤU THẦU
A3: Project | B3: PROJECT No/ Dự án: 25-WNC-I-097
A4: Dự án
A5: Subject | B5: Cung cấp vật tư đóng kiện
A6: Chủ đề
A8: No. | B8: CONTENT | C8: Phạm vi công việc | H8: Dự toán | K8: Đã mua | L8: Đơn vị cung cấp chào giá (vnđ) | O8: Ghi chú
A9: Item | B9: Description/ Chi tiết | C9: Profile/ Vật tư | D9: Grade/ Mác vật liệu | E9: Số lượng Mua | F9: Số lượng PR | G9: Đơn vị | H9: Khối lượng/ Số lượng | I9: Đơn giá (vnd) | J9: Thành tiền (vnd) | K9: Thành tiền (vnd) | L9: HOÀNG HÀ
L10: Phạm vi | M10: Đơn giá (VND) | N10: Thành Tiền (Không có VAT)
A11: Tổng | B11: Packing Material / Vật tư kiện | H11: N/A | I11: N/A | J11: ='DT04 (TM) 1 '!L28 -> 503250000 | K11: ='Tổng hợp'!J25+159401000 -> 9.5442614e+08 | N11: =SUM(N12:N12) -> 1620000 | O11: =J11-K11-N11 -> -4.5279614e+08
A12: I97-VDK-030 | B12: VÍT BẮN TÔN M4X40 | C12: M5.5*38 | D12: Mạ cầu vồng | E12: 300 | F12: 300 | G12: Cái | H12: N/A | I12: N/A | J12: N/A | L12: V | M12: 540 | N12: 1620000 | O12: HOÀNG Hà
B13: Xếp hạng | M13: 1
A14: Ghi chú: Giá trị mua hàng đã vượt quá dự toán ' Tiếp tục công tác mua sắm để đảm báo tiến độ
A15: NGƯỜI ĐỀ NGHỊ/ RECOMMENDATION BY: | C15: NGƯỜI KIỂM TRA/ DEPARTMENT HEAD CHECK BY: | G15: APPROVED BY: PHÊ DUYỆT
G16: Nguyễn Quang Vinh | J16: Hoàng Ngọc Bằng | M16: Đoàn Văn Toàn

Sheet Giải tình Huy hoàng
A1: BID ANALYSIS - GIẢI TRÌNH MUA SẮM/ĐẤU THẦU
A3: Project | B3: PROJECT No/ Dự án: 25-WNC-I-097
A4: Dự án
A5: Subject | B5: Cung cấp vật tư đóng kiện
A6: Chủ đề
A8: No. | B8: CONTENT | C8: Phạm vi công việc | H8: Dự toán | K8: Đã mua | L8: Đơn vị cung cấp chào giá (vnđ) | O8: Ghi chú
A9: Item | B9: Description/ Chi tiết | C9: Profile/ Vật tư | D9: Grade/ Mác vật liệu | E9: Số lượng Mua | F9: Số lượng PR | G9: Đơn vị | H9: Khối lượng/ Số lượng | I9: Đơn giá (vnd) | J9: Thành tiền (vnd) | K9: Thành tiền (vnd) | L9: HOÀNG ANH MINH
L10: Phạm vi | M10: Đơn giá (VND) | N10: Thành Tiền (Không có VAT)
A11: Tổng | B11: Packing Material / Vật tư kiện | H11: N/A | I11: N/A | J11: ='DT04 (TM) 1 '!L28 -> 503250000 | K11: ='Tổng hợp'!J25 -> 7.9502514e+08 | N11: =SUM(N12:N16) -> 159401000 | O11: =J11-K11-N11 -> -4.5117614e+08
A12: I97-VDK-005 | B12: GỖ 100X100X2500 | C12: Gỗ thanh 2500*100*100 | D12: gỗ khử trùng-ISPM15 | E12: 510 | F12: 510 | G12: m | H12: N/A | I12: N/A | J12: N/A | L12: V | M12: 77000 | N12: =M12*E12 -> 39270000 | O12: Chọn HUY HOÀNG MINH
A13: I97-VDK-006 | B13: GỖ 100X20X2500 | C13: Gỗ thanh 2500*100*20 | D13: gỗ khử trùng-ISPM15 | E13: 270 | F13: 270 | G13: m | H13: N/A | I13: N/A | J13: N/A | L13: V | M13: 18000 | N13: =M13*E13 -> 4860000 | O13: Chọn HUY HOÀNG MINH
A14: I97-VDK-007 | B14: GỖ 100X50X2500 | C14: Gỗ thanh 2500*100*50 | D14: gỗ khử trùng-ISPM15 | E14: 301 | F14: 301 | G14: m | H14: N/A | I14: N/A | J14: N/A | L14: V | M14: 41000 | N14: =M14*E14 -> 12341000 | O14: Chọn HUY HOÀNG MINH
A15: I97-VDK-028 | B15: GỖ VÁN ÉP PL15X1220X2440 | C15: Gỗ tấm 2440*1220*15 | D15: gỗ ÉP khử trùng-ISPM15 | E15: 151 | F15: =450/2.44/1.22 -> 151.16904 | G15: Tấm | H15: N/A | I15: N/A | J15: N/A | L15: V | M15: 270000 | N15: =M15*E15 -> 40770000 | O15: Chọn HUY HOÀNG MINH
A16: I97-VDK-029 | B16: GỖ VÁN ÉP PL10X1220X2440 | C16: Gỗ tấm 2440*1220*10 | D16: gỗ ÉP khử trùng-ISPM15 | E16: 336 | F16: =1000/2.44/1.22 -> 335.9312 | G16: Tấm | H16: N/A | I16: N/A | J16: N/A | L16: V | M16: 185000 | N16: =M16*E16 -> 62160000 | O16: Chọn HUY HOÀNG MINH
B17: Xếp hạng | M17: 1
A18: Ghi chú: Giá trị mua hàng đã vượt quá dự toán ' Tiếp tục công tác mua sắm để đảm báo tiến độ
A19: NGƯỜI ĐỀ NGHỊ/ RECOMMENDATION BY: | C19: NGƯỜI KIỂM TRA/ DEPARTMENT HEAD CHECK BY: | G19: APPROVED BY: PHÊ DUYỆT
G20: Nguyễn Quang Vinh | J20: Hoàng Ngọc Bằng | M20: Đoàn Văn Toàn

Sheet Giải tình Ngọc Hiếu
A1: BID ANALYSIS - GIẢI TRÌNH MUA SẮM/ĐẤU THẦU
A3: Project | B3: PROJECT No/ Dự án: 25-WNC-I-097
A4: Dự án
A5: Subject | B5: Cung cấp vật tư chính thép hình của Ngọc Hiếu
A6: Chủ đề
A8: No. | B8: CONTENT | C8: Phạm vi công việc | H8: Dự toán | K8: Đã mua | L8: Đơn vị cung cấp chào giá phần còn lại (VNĐ) | O8: Đơn vị cung cấp chào giá phần còn lại (VNĐ) | R8: Đơn vị cung cấp chào giá phần còn lại (VNĐ) | U8: Ghi chú
A9: Item | B9: Description/ Chi tiết | C9: Profile/ Vật tư | D9: Grade/ Mác vật liệu | E9: Số lượng Mua cây) | F9: Số lượng Mua (M) | G9: Số lượng PR (M) | H9: Khối lượng/ Số lượng | I9: Đơn giá (vnd) | J9: Thành tiền (vnd) | K9: Thành tiền (vnd) | L9: HÙNG NGUYÊN | O9: NGỌC HIẾU/APEC | R9: APEC
L10: Phạm vi | M10: Đơn giá trước VAT (VNĐ/KG) | N10: Thành Tiền (Không có VAT) | O10: Phạm vi | P10: Đơn giá trước VAT (VNĐ/KG) | Q10: Thành Tiền (Không có VAT) | R10: Phạm vi | S10: Đơn giá trước VAT (VNĐ/KG) | T10: Thành Tiền (Không có VAT)
A11: Tổng | B11: Main-Material / Vật tư chính thép đen | H11: N/A | I11: N/A | J11: ='DT04 (TM) 1 '!L7 -> 3001944110 | K11: ='DT04 (TM) 1 '!Q7 -> 3.0852474e+09 | Q11: =SUM(Q12:Q20) -> 280781112 | U11: =J11-K11-Q11 -> -3.6408442e+08
A12: I97-VTC01-001 | B12: =VLOOKUP(A12,'25-WNC-I-097'!I:CX,3,0) -> C100X50X5X7.5-12000L | C12: Thép U100*50*5*7,5*12000 | D12: =VLOOKUP(A12,'25-WNC-I-097'!I:CX,4,0) -> SS400 | E12: 3 | F12: 36 | G12: =VLOOKUP(A12,'25-WNC-I-097'!I:CX,83,0) -> 0 | H12: N/A | I12: N/A | J12: N/A | L12: V | M12: 17500 | N12: N/A | O12: V | P12: 17090.91 | Q12: 5759637 | R12: V | S12: 17090.909 | T12: N/A | U12: Chọn NGỌC HIẾU
A13: I97-VTC01-002 | B13: =VLOOKUP(A13,'25-WNC-I-097'!I:CX,3,0) -> C125X65X6X8-12000L | C13: Thép U125*65*6*8*12000 | D13: =VLOOKUP(A13,'25-WNC-I-097'!I:CX,4,0) -> SS400 | E13: 20 | F13: 240 | G13: =VLOOKUP(A13,'25-WNC-I-097'!I:CX,83,0) -> 0 | H13: N/A | I13: N/A | J13: N/A | L13: X | M13: N/A | N13: N/A | O13: V | P13: 17090.91 | Q13: 54964367 | R13: V | S13: 17454.545 | T13: N/A | U13: Chọn NGỌC HIẾU
A14: I97-VTC01-003 | B14: =VLOOKUP(A14,'25-WNC-I-097'!I:CX,3,0) -> C200X90X8X13.5-12000L | C14: Thép U200*90*8*13,5*12000 | D14: =VLOOKUP(A14,'25-WNC-I-097'!I:CX,4,0) -> SS400 | E14: 4 | F14: 48 | G14: =VLOOKUP(A14,'25-WNC-I-097'!I:CX,83,0) -> 0 | H14: N/A | I14: N/A | J14: N/A | L14: X | M14: N/A | N14: N/A | O14: V | P14: 17272.73 | Q14: 25114549 | R14: X | S14: N/A | T14: N/A | U14: Chọn NGỌC HIẾU
A15: I97-VTC01-041 | B15: =VLOOKUP(A15,'25-WNC-I-097'!I:CX,3,0) -> C150X75X6.5X10 | C15: Thép U150*75*6,5*10*12000 | D15: =VLOOKUP(A15,'25-WNC-I-097'!I:CX,4,0) -> SS400 | E15: 39 | F15: 468 | G15: =VLOOKUP(A15,'25-WNC-I-097'!I:CX,83,0) -> 0 | H15: N/A | I15: N/A | J15: N/A | L15: X | M15: N/A | N15: N/A | O15: V | P15: 17090.91 | Q15: 148776372 | R15: X | S15: N/A | T15: N/A | U15: Chọn NGỌC HIẾU
A16: I97-VTC01-044 | B16: =VLOOKUP(A16,'25-WNC-I-097'!I:CX,3,0) -> C250X90X9X13 | C16: Thép U250*90*9*13*12000 | D16: =VLOOKUP(A16,'25-WNC-I-097'!I:CX,4,0) -> SS400 | E16: 5 | F16: 60 | G16: =VLOOKUP(A16,'25-WNC-I-097'!I:CX,83,0) -> 0 | H16: N/A | I16: N/A | J16: N/A | L16: X | M16: N/A | N16: N/A | O16: V | P16: 17272.73 | Q16: 35858187 | R16: X | S16: N/A | T16: N/A | U16: Chọn NGỌC HIẾU
A17: I97-VTC01-017 | B17: =VLOOKUP(A17,'25-WNC-I-097'!I:CX,3,0) -> L50X50X5-6000L | C17: Thép V50*50*5*6000 | D17: =VLOOKUP(A17,'25-WNC-I-097'!I:CX,4,0) -> SS400 | E17: 2 | F17: 12 | G17: =VLOOKUP(A17,'25-WNC-I-097'!I:CX,83,0) -> 0 | H17: N/A | I17: N/A | J17: N/A | L17: V | M17: 14090.91 | N17: N/A | O17: V | P17: 13909.09 | Q17: 625909 | R17: V | S17: 13727.273 | T17: N/A | U17: Chọn NGỌC HIẾU
A18: I97-VTC01-051 | B18: =VLOOKUP(A18,'25-WNC-I-097'!I:CX,3,0) -> L50X50X6 | C18: Thép V50*50*6*6000 | D18: =VLOOKUP(A18,'25-WNC-I-097'!I:CX,4,0) -> SS400 | E18: 9 | F18: 54 | G18: =VLOOKUP(A18,'25-WNC-I-097'!I:CX,83,0) -> 0 | H18: N/A | I18: N/A | J18: N/A | L18: V | M18: 14090.91 | N18: N/A | O18: V | P18: 13909.09 | Q18: 3324273 | R18: V | S18: 13727.273 | T18: N/A | U18: Chọn NGỌC HIẾU
A19: I97-VTC01-053 | B19: =VLOOKUP(A19,'25-WNC-I-097'!I:CX,3,0) -> L75X75X6 | C19: Thép V75*75*6*6000 | D19: =VLOOKUP(A19,'25-WNC-I-097'!I:CX,4,0) -> SS400 | E19: 11 | F19: 66 | G19: =VLOOKUP(A19,'25-WNC-I-097'!I:CX,83,0) -> 0 | H19: N/A | I19: N/A | J19: N/A | L19: V | M19: 14090.91 | N19: N/A | O19: V | P19: 13909.09 | Q19: 6286909 | R19: V | S19: 13727.273 | T19: N/A | U19: Chọn NGỌC HIẾU
A20: I97-VTC01-023 | B20: =VLOOKUP(A20,'25-WNC-I-097'!I:CX,3,0) -> RB12-6000L | C20: Thép tròn D12*6000 | D20: =VLOOKUP(A20,'25-WNC-I-097'!I:CX,4,0) -> SS400 | E20: 1 | F20: 6 | G20: =VLOOKUP(A20,'25-WNC-I-097'!I:CX,83,0) -> 0 | H20: N/A | I20: N/A | J20: N/A | L20: V | M20: 15272.73 | N20: N/A | O20: V | P20: 14181.82 | Q20: 70909 | R20: V | S20: 15000 | T20: N/A | U20: Chọn NGỌC HIẾU
B21: Xếp hạng | M21: 3 | P21: 1 | S21: 2
A22: Ghi chú: Tiếp tục công tác mua sắm để đảm báo tiến độ
A23: NGƯỜI ĐỀ NGHỊ/ RECOMMENDATION BY: | C23: NGƯỜI KIỂM TRA/ DEPARTMENT HEAD CHECK BY: | K23: APPROVED BY: PHÊ DUYỆT
K24: Nguyễn Quang Vinh | Q24: Hoàng Ngọc Bằng | T24: Đoàn Văn Toàn

Sheet Giải tình MCL đợt 2
A1: BID ANALYSIS - GIẢI TRÌNH MUA SẮM/ĐẤU THẦU
A3: Project | B3: PROJECT No/ Dự án: 25-WNC-I-097
A4: Dự án
A5: Subject | B5: Cung cấp vật tư chính thép hình của MCL
A6: Chủ đề
A8: No. | B8: CONTENT | C8: Phạm vi công việc | G8: Dự toán | J8: Đã mua | K8: Đơn vị cung cấp chào giá phần còn lại (USD) | N8: Đơn vị cung cấp chào giá phần còn lại (USD) | Q8: Đơn vị cung cấp chào giá phần còn lại (VNĐ) | T8: Đơn vị cung cấp chào giá phần còn lại (VNĐ) | W8: Ghi chú
A9: Item | B9: Description/ Chi tiết | C9: Profile/ Vật tư | D9: Grade/ Mác vật liệu | E9: Số lượng Mua (M2) | F9: Số lượng PR (M2) | G9: Khối lượng/ Số lượng | H9: Đơn giá (vnd) | I9: Thành tiền (vnd) | J9: Thành tiền (vnd) | K9: MCL | N9: GNEE | Q9: NGỌC HIẾU/APEC | T9: HÙNG NGUYÊN
K10: Phạm vi | L10: Đơn giá (USD/KG) | M10: Thành Tiền (Không có VAT) | N10: Phạm vi | O10: Đơn giá (USD/KG) | P10: Thành Tiền (Không có VAT) | Q10: Phạm vi | R10: Đơn giá trước VAT (VNĐ/KG) | S10: Thành Tiền (Không có VAT) | T10: Phạm vi | U10: Đơn giá trước VAT (VNĐ/KG) | V10: Thành Tiền (Không có VAT)
A11: Tổng | B11: Main-Material / Vật tư chính thép đen | G11: N/A | H11: N/A | I11: ='DT04 (TM) 1 '!L7 -> 3001944110 | J11: ='DT04 (TM) 1 '!Q7 -> 3.0852474e+09 | M11: =SUM(M12:M12)*(26300) -> 91134234 | S11: =SUM(S12:S12)*26300 -> 0 | W11: =I11-J11-S11-M11 -> -1.7443754e+08
A12: I97-VTC01-013 | B12: H300X300X10X15-12000L | C12: H300X300X10X15-12000L | D12: SS400 | E12: 60 | F12: 63 | G12: N/A | H12: N/A | I12: N/A | K12: V | L12: 0.621 | M12: 3465.18 | N12: V | O12: 0.6776368 | P12: N/A | Q12: V | R12: =19300/1.1 -> 17545.455 | S12: N/A | T12: V | U12: 17636.36 | V12: N/A | W12: Chọn MCL
A14: IV | B14: Nhân lực/ ManPower
A15: 1 | B15: Thợ Pha cắt / Thợ sắt / Thợ hàn / …
B16: ….
A17: V | B17: Yêu cầu kỹ thuật: Tham chiếu các tài liệu đính kèm/ Technical requirement – refer to document attached
B18: Xếp hạng | L18: 1 | O18: 2 | R18: 3 | U18: 4
A19: Ghi chú: Tiếp tục công tác mua sắm để đảm báo tiến độ
A20: NGƯỜI ĐỀ NGHỊ/ RECOMMENDATION BY: | C20: NGƯỜI KIỂM TRA/ DEPARTMENT HEAD CHECK BY: | M20: APPROVED BY: PHÊ DUYỆT
M21: Nguyễn Quang Vinh | S21: Hoàng Ngọc Bằng | V21: Đoàn Văn Toàn

Sheet Vật tư kẹp sàn
A1: BID ANALYSIS - GIẢI TRÌNH MUA SẮM/ĐẤU THẦU
A3: Project | B3: PROJECT No/ Dự án: 25-WNC-I-097
A4: Dự án
A5: Subject | B5: Cung cấp vật tư kẹp sàn dự án 097
A6: Chủ đề
A8: No. | B8: CONTENT | C8: Phạm vi công việc | F8: Dự toán | I8: Đơn vị cung cấp chào giá (VNĐ) | L8: Đơn vị cung cấp chào giá (USD) | O8: Lựa chọn | P8: Ghi chú
A9: Item | B9: Description/ Chi tiết | C9: Profile/ Vật tư | D9: Grade/ Mác vật liệu | E9: Số lượng PR (PSC) | F9: Khối lượng/ Số lượng | G9: Đơn giá (vnd) | H9: Thành tiền (vnd) | I9: VSAN | L9: WINWIN
E10: Số lượng (cây) | I10: Phạm vi | J10: Đơn giá (VNĐ) | K10: Thành Tiền (VNĐ) | L10: Phạm vi | M10: Đơn giá (VNĐ) | N10: Thành Tiền (VNĐ)
A11: Tổng | B11: Main-Material / Vật tư chính thép đen | F11: N/A | G11: N/A | K11: =SUM(K12:K12) -> 5405000
A12: 1 | B12: Kẹp sàn A30 | C12: kẹp trên + kẹp dưới + bulong + đai ốc vuông (Toàn bộ mạ kẽm nhúng nóng HDG) | E12: 235 | F12: N/A | G12: N/A | H12: N/A | I12: V | J12: 23000 | K12: 5405000 | L12: X | M12: N/A | N12: N/A | O12: VSAN
B13: Xếp hạng | J13: 1 | L13: 2
A14: Ghi Chú: PTM tiến hành đặt hàng để kịp tiến độ
A15: NGƯỜI ĐỀ NGHỊ/ RECOMMENDATION BY: | C15: NGƯỜI KIỂM TRA/ DEPARTMENT HEAD CHECK BY: | H15: APPROVED BY: PHÊ DUYỆT
H16: Nguyễn Quang Vinh | J16: Hoàng Ngọc Bằng | M16: Đoàn Văn Toàn

Sheet Vật tư U180
A1: BID ANALYSIS - GIẢI TRÌNH MUA SẮM/ĐẤU THẦU
A3: Project | B3: PROJECT No/ Dự án: 25-WNC-I-097
A4: Dự án
A5: Subject | B5: Cung cấp vật tư chính dự án 097
A6: Chủ đề
A8: No. | B8: CONTENT | C8: Phạm vi công việc | F8: Dự toán | I8: Đơn vị cung cấp chào giá (VNĐ) | L8: Đơn vị cung cấp chào giá (USD) | O8: Lựa chọn | P8: Ghi chú
A9: Item | B9: Description/ Chi tiết | C9: Profile/ Vật tư | D9: Grade/ Mác vật liệu | E9: Số lượng PR (PSC) | F9: Khối lượng/ Số lượng | G9: Đơn giá (vnd) | H9: Thành tiền (vnd) | I9: TRUNG HẢI | L9: NGỌC HIẾU/HÙNG NGUYÊN/APEC…
E10: Số lượng (cây) | I10: Phạm vi | J10: Đơn giá (VNĐ) | K10: Thành Tiền (VNĐ) | L10: Phạm vi | M10: Đơn giá (VNĐ) | N10: Thành Tiền (VNĐ)
A11: Tổng | B11: Main-Material / Vật tư chính thép đen | F11: N/A | G11: N/A | K11: =SUM(K12:K14) -> 66506200
A12: I97-VTC01-042 | B12: Thép hình C C180X90X7.5X12.5 | C12: Thép sấn U U180x90x10 | D12: SS400 | E12: 145 | F12: N/A | G12: N/A | H12: N/A | I12: V | J12: 19100 | K12: 66506200 | L12: X | M12: N/A | N12: N/A | O12: TRUNG HẢI
B13: Đơn giá tổng hợp
A14: II | B14: Khối lượng dự kiến giao (Kg )/ Estimated weight (Kg):
A15: 1 | B15: … | C15: kg
A16: 2 | B16: …
A17: III | B17: Tiến độ/ Schedule | C17: Bắt đầu/ Start | D17: Kết thúc/ Finish
A18: 1 | B18: ….
A20: IV | B20: Nhân lực/ ManPower
A21: 1 | B21: Thợ Pha cắt / Thợ sắt / Thợ hàn / …
B22: ….
A23: V | B23: Yêu cầu kỹ thuật: Tham chiếu các tài liệu đính kèm/ Technical requirement – refer to document attached
B24: Xếp hạng | J24: 1 | L24: 2
A25: Ghi Chú: PTM tiến hành đặt hàng để kịp tiến độ
A26: NGƯỜI ĐỀ NGHỊ/ RECOMMENDATION BY: | C26: NGƯỜI KIỂM TRA/ DEPARTMENT HEAD CHECK BY: | H26: APPROVED BY: PHÊ DUYỆT
H27: Nguyễn Quang Vinh | J27: Hoàng Ngọc Bằng | M27: Đoàn Văn Toàn

Sheet Vật tư U80
A1: BID ANALYSIS - GIẢI TRÌNH MUA SẮM/ĐẤU THẦU
A3: Project | B3: PROJECT No/ Dự án: 25-WNC-I-097
A4: Dự án
A5: Subject | B5: Cung cấp vật tư chính dự án 097
A6: Chủ đề
A8: No. | B8: CONTENT | C8: Phạm vi công việc | F8: Dự toán | I8: Đơn vị cung cấp chào giá (USD) | L8: Đơn vị cung cấp chào giá (USD) | O8: Lựa chọn | P8: Ghi chú
A9: Item | B9: Description/ Chi tiết | C9: Profile/ Vật tư | D9: Grade/ Mác vật liệu | E9: Số lượng PR (PSC) | F9: Khối lượng/ Số lượng | G9: Đơn giá (vnd) | H9: Thành tiền (vnd) | I9: MCL | L9: GNEE
E10: Số lượng (cây) | I10: Phạm vi | J10: Đơn giá (USD) | K10: Thành Tiền (CIF) | L10: Phạm vi | M10: Đơn giá (USD) | N10: Thành Tiền (CIF)
A11: Tổng | B11: Main-Material / Vật tư chính thép đen | F11: N/A | G11: N/A | H11: ='DT04 (TM) 1 '!L7 -> 3001944110 | K11: =SUM(K12:K14) -> 5225.472 | N11: =SUM(N12:N14) -> 6955.6838
A12: I97-VTC01-040 | B12: Thép hình C C80x45x5.5x7.5-12000L | C12: C80x45x6x8-12000L | D12: SS400 | E12: 56 | F12: N/A | G12: N/A | H12: N/A | I12: V | J12: 0.9 | K12: =8.64*12*E12*J12 -> 5225.472 | L12: V | M12: 1.198 | N12: =8.64*12*E12*M12 -> 6955.6838 | O12: MCL | P12: - Vật tư thép tấm PL6 (84m2) đã cấp cho sản xuất cắt để đưa đi sấn. Nhưng phôi cắt không đảm bảo công tác sấn. => Để đảm bảo chất lượng dự án GE, yêu cầu PTM tiến hành mua thép U80x6x8x12m (56 cây)
B13: Đơn giá tổng hợp
A14: II | B14: Khối lượng dự kiến giao (Kg )/ Estimated weight (Kg):
A15: 1 | B15: … | C15: kg
A16: 2 | B16: …
A17: III | B17: Tiến độ/ Schedule | C17: Bắt đầu/ Start | D17: Kết thúc/ Finish
A18: 1 | B18: ….
A20: IV | B20: Nhân lực/ ManPower
A21: 1 | B21: Thợ Pha cắt / Thợ sắt / Thợ hàn / …
B22: ….
A23: V | B23: Yêu cầu kỹ thuật: Tham chiếu các tài liệu đính kèm/ Technical requirement – refer to document attached
B24: Xếp hạng | J24: 1 | L24: 2
A25: Ghi Chú: PTM tiến hành đặt hàng để kịp tiến độ
A26: NGƯỜI ĐỀ NGHỊ/ RECOMMENDATION BY: | C26: NGƯỜI KIỂM TRA/ DEPARTMENT HEAD CHECK BY: | H26: APPROVED BY: PHÊ DUYỆT
H27: Nguyễn Quang Vinh | J27: Hoàng Ngọc Bằng | M27: Đoàn Văn Toàn

Sheet Hùng nguyen kien
A1: BID ANALYSIS - GIẢI TRÌNH MUA SẮM/ĐẤU THẦU
A3: Project | B3: PROJECT No/ Dự án: 25-WNC-I-097
A4: Dự án
A5: Subject | B5: Cung cấp vật tư đóng kiện
A6: Chủ đề
A8: No. | B8: CONTENT | C8: Phạm vi công việc | G8: Dự toán | J8: Đã mua | K8: Đơn vị cung cấp chào giá phần còn lại (VNĐ) | N8: Đơn vị cung cấp chào giá phần còn lại (VNĐ) | Q8: Ghi chú
A9: Item | B9: Description/ Chi tiết | C9: Profile/ Vật tư | D9: Số lượng Mua (Cây) | E9: Số lượng Mua (M) | F9: Số lượng PR (M) | G9: Khối lượng/ Số lượng | H9: Đơn giá (vnd) | I9: Thành tiền (vnd) | J9: Thành tiền (vnd) | K9: HÙNG NGUYÊN/NGỌC HIÊÚ | N9: TITAN
K10: Phạm vi | L10: Đơn giá trước VAT (VNĐ/KG) | M10: Thành Tiền | N10: Phạm vi | O10: Đơn giá trước VAT (VNĐ/KG) | P10: Thành Tiền
A11: Tổng | B11: ='25-WNC-I-097'!J310 -> Packing Material / Vật tư kiện | G11: N/A | H11: N/A | I11: ='DT04 (TM) 1 '!L28 -> 503250000 | J11: ='25-WNC-I-097'!BM310 -> 7.9502514e+08 | M11: =SUM(M12:M12) -> 92972969 | Q11: =I11-J11-P11-M11 -> -3.847481e+08
A12: I97-VDK-024 | B12: C150X75X6.5X10 | C12: C150X75X6.5X10x12000mm | D12: 29 | E12: =D12*12 -> 348 | F12: 338.1294 | G12: N/A | H12: N/A | I12: N/A | J12: N/A | K12: V | L12: 14363.64 | M12: 92972969 | N12: V | O12: =17000/1.1 -> 15454.545 | P12: N//A | Q12: Chọn Hùng Nguyên
B13: Xếp hạng | L13: 1 | O13: 2
A14: Ghi chú: Tiếp tục công tác mua sắm để đảm báo tiến độ
A15: NGƯỜI ĐỀ NGHỊ/ RECOMMENDATION BY: | E15: NGƯỜI KIỂM TRA/ DEPARTMENT HEAD CHECK BY: | J15: APPROVED BY: PHÊ DUYỆT
J16: Nguyễn Quang Vinh | M16: Hoàng Ngọc Bằng | P16: Đoàn Văn Toàn

Sheet DT04 (TM) 1 
D1: CÔNG TY CỔ PHẦN CÔNG NGHIỆP NẶNG IBS IBS HEAVY INDUSTRY JOINT STOCK COMPANY Add.: KM6, Quốc lộ 5, Phường Hồng Bàng, Thành phố Hải Phòng
A2: BẢNG DỰ TOÁN CHI TIẾT VẬT TƯ
L3: Mẫu số: QT30-DT04 | M3: Mua sắm/ Ordered, Puchased (Đến hiện tại/ Up to now)
A4: STT | B4: Nhóm vật tư | C4: Mã vật tư | D4: Danh mục vật tư | E4: Đơn vị tính | F4: Mác vật liệu | G4: Quy cách | J4: Khối lượng/ Số lượng | K4: Đơn giá (vnd) | L4: Thành tiền (vnd) | M4: Hàng mua thêm | O4: Hàng tồn | Q4: Tổng Giá trị đã mua/ Total Cost (VND) | R4: Đânh giá
G5: Dài | H5: Rộng | I5: Dày | M5: Khối lượng/ Weight (Kg) | N5: Số lượng/ Q'ty (M/M2//PSC) | O5: Khối lượng/ Weight (Kg/N/A) Materials available at the factory | P5: Số lượng/ Q'ty (M/M2/PSC) Materials available at the factory
A6: A | B6: VTC | D6: Vật tư chính | J6: =SUBTOTAL(9,J7:J20) -> 0 | L6: =SUM(L7:L22) -> 6.3904488e+09 | R6: =IF(L6>Q6," OKE MUA TIẾP","BÁO CÁO BOM") -> OKE MUA TIẾP
A7: 1 | B7: VTC01 | D7: Thép carbon các loại | E7: kg | L7: =L8+L9 -> 3001944110 | M7: ='Tổng hợp'!F20 -> 186779.34 | N7: ='Tổng hợp'!G20 -> 8152.1214 | O7: ='Tổng hợp'!H20 -> 3634.4786 | P7: ='Tổng hợp'!I20 -> 304.2928 | Q7: ='Tổng hợp'!J20 -> 3.0852474e+09 | R7: =IF(L7>Q7," OKE MUA TIẾP","BÁO CÁO BOM") -> BÁO CÁO BOM
A8: 1.1 | B8: VTC0101 | D8: Thép tấm carbon | E8: kg | L8: ='[116]Dự toán vật tư'!G7 -> 7.8006665e+08
A9: 1.2 | B9: VTC0102 | D9: Thép hình carbon | E9: kg | L9: ='[116]Dự toán vật tư'!G8 -> 2221877460
A10: 1.3 | B10: VTC0103 | D10: Thép ống carbon | E10: kg
A11: 1.4 | B11: VTC0104 | D11: Thép carbon khác
A12: 2 | B12: VTC02 | D12: Thép Hợp kim các loại | E12: kg | M12: ='Tổng hợp'!F21 -> 0 | N12: ='Tổng hợp'!G21 -> 0 | O12: ='Tổng hợp'!H21 -> 0 | P12: ='Tổng hợp'!I21 -> 0 | Q12: ='Tổng hợp'!J21 -> 0 | R12: =IF(L12>Q12," OKE MUA TIẾP","BÁO CÁO BOM") -> BÁO CÁO BOM
A13: 2.1 | B13: VTC0201 | D13: Thép tấm hợp kim | E13: kg
A14: 2.2 | B14: VTC0202 | D14: Thép hình hợp kim
A15: 2.3 | B15: VTC0203 | D15: Thép ống hợp kim
A16: 2.4 | B16: VTC0204 | D16: Thép hợp kim khác
A17: 3 | B17: VTC03 | D17: Tấm sàn, grating … | E17: kg | L17: ='[116]Dự toán vật tư'!G9 -> 195865000 | M17: ='Tổng hợp'!F22 -> 3622 | N17: ='Tổng hợp'!G22 -> 470 | O17: ='Tổng hợp'!H22 -> 0 | P17: ='Tổng hợp'!I22 -> 0 | Q17: ='Tổng hợp'!J22 -> 165851000 | R17: =IF(L17>Q17," OKE MUA TIẾP","BÁO CÁO BOM") -> OKE MUA TIẾP | S17: ='Sàn winwin'!G27 -> 160446000
A20: 4 | B20: VTC04 | D20: Vât tư bảo ôn | E20: kg | L20: ='[116]Dự toán vật tư'!G10 -> 1.9069559e+08 | M20: ='Tổng hợp'!F23 -> 0 | N20: ='Tổng hợp'!G23 -> 90.8928 | O20: ='Tổng hợp'!H23 -> 0 | P20: ='Tổng hợp'!I23 -> 0 | Q20: ='Tổng hợp'!J23 -> 2.0585973e+08 | R20: =IF(L20>Q20," OKE MUA TIẾP","BÁO CÁO BOM") -> BÁO CÁO BOM
A23: B | B23: VPK | D23: Vật tư phụ kiện, bu lông… | L23: ='[116]Dự toán vật tư'!G12 -> 213600000 | M23: ='Tổng hợp'!F24 -> 0 | N23: ='Tổng hợp'!G24 -> 49585 | O23: ='Tổng hợp'!H24 -> 0 | P23: ='Tổng hợp'!I24 -> 0 | Q23: ='Tổng hợp'!J24 -> 202484525 | R23: =IF(L23>Q23," OKE MUA TIẾP","BÁO CÁO BOM") -> OKE MUA TIẾP
A24: 1 | B24: VPK01 | D24: Phụ kiện
A25: 2 | B25: VPK02 | D25: Phụ kiện khác
A28: C | B28: VDK | D28: Vật tư đóng kiện | L28: ='[116]Dự toán vật tư'!G14 -> 503250000 | M28: ='Tổng hợp'!F25 -> 23146.8 | N28: ='Tổng hợp'!G25 -> 12576.902 | O28: ='Tổng hợp'!H25 -> 939.96862 | P28: ='Tổng hợp'!I25 -> 139.834 | Q28: ='Tổng hợp'!J25 -> 7.9502514e+08 | R28: =IF(L28>Q28," OKE MUA TIẾP","BÁO CÁO BOM") -> BÁO CÁO BOM
A29: 1 | B29: VDK01 | D29: Thép đen các loại | L29: ='[116]Dự toán vật tư'!G15 -> 347225000
A30: 2 | B30: VDK02 | D30: Vật tư phụ kiện, bu lông… | L30: ='[116]Dự toán vật tư'!G16 -> 69445000
A31: 3 | B31: VDK03 | D31: Vật tư phụ các loại | L31: ='[116]Dự toán vật tư'!G17 -> 86580000
A34: D | B34: VBP | D34: Vật tư làm biện pháp | L34: ='[116]Dự toán vật tư'!G18 -> 67000000 | R34: =IF(L34>Q34," OKE MUA TIẾP","BÁO CÁO BOM") -> OKE MUA TIẾP
A35: 1 | B35: VBP01 | D35: Thép đen các loại | L35: ='[116]Dự toán vật tư'!G19 -> 60000000
A38: 2 | B38: VBP02 | D38: Vật tư phụ kiện, bu lông… | L38: ='[116]Dự toán vật tư'!G20 -> 7000000
A41: E | B41: VTH | D41: Vật tư tiêu hao | L41: ='[116]Dự toán vật tư'!G21 -> 307343625 | R41: =IF(L41>Q41," OKE MUA TIẾP","BÁO CÁO BOM") -> OKE MUA TIẾP
A42: 1 | B42: VTH01 | D42: Vật tư hàn | L42: ='[116]Dự toán vật tư'!G22 -> 141900000
A43: 1.1 | B43: VTH0101 | D43: Dây hàn
A45: 1.2 | B45: VTH0102 | D45: Que hàn
A47: 1.3 | B47: VTH0103 | D47: Thuốc hàn
A49: 2 | B49: VTH02 | D49: Khí công nghiệp | L49: ='[116]Dự toán vật tư'!G23 -> 145490625
A50: 2.1 | B50: VTH0201 | D50: Khí Ôxy
A52: 2.2 | B52: VTH0202 | D52: Khí CO2
A54: 2.3 | B54: VTH0203 | D54: Khí Gas
A56: 2.4 | B56: VTH0204 | D56: Khí Argon
A58: 2.5 | B58: VTH0205 | D58: Khí công nghiệp khác
A61: 3 | B61: VTH03 | D61: Vật tư phụ các loại | L61: ='[116]Dự toán vật tư'!G24 -> 19953000
A64: F | B64: VLS | D64: Vật tư làm sạch và sơn | L64: ='[116]Dự toán vật tư'!G25 -> 887932697 | R64: =IF(L64>Q64," OKE MUA TIẾP","BÁO CÁO BOM") -> OKE MUA TIẾP
A70: G | B70: VTP | D70: Vật tư dự phòng | L70: ='[116]Dự toán vật tư'!G30 -> 2.3986905e+08 | R70: =IF(L70>Q70," OKE MUA TIẾP","BÁO CÁO BOM") -> OKE MUA TIẾP
D71: TỔNG CỘNG (A+B+C+D) | L71: =L70+L64+L41+L34+L28+L23+L6 -> 8.6094442e+09 | Q71: =Q70+Q64+Q41+Q34+Q28+Q23+Q6 -> 9.9750966e+08 | R71: =IF(L71>Q71," OKE MUA TIẾP","BÁO CÁO BOM") -> OKE MUA TIẾP
J73: Ngày…...tháng…...năm 2025
J74: PHỎNG THƯƠNG MẠI

Sheet Vật tư sơn 097
A1: BID ANALYSIS - GIẢI TRÌNH MUA SẮM/ĐẤU THẦU
A3: Project | B3: PROJECT No/ Dự án: 25-WNC-I-097
A4: Dự án
A5: Subject | B5: Cung cấp vật tư sơn
A6: Chủ đề
A8: No. | B8: CONTENT | C8: Phạm vi công việc | G8: Dự toán | J8: Đã mua | K8: Đơn vị cung cấp chào giá (vnđ) | N8: Lựa chọn | O8: Ghi chú
A9: Item | B9: Description/ Chi tiết | C9: Profile/ Vật tư | D9: Grade/ Mác vật liệu | E9: ĐVT | F9: Số lượng | G9: Khối lượng/ Số lượng | H9: Đơn giá (vnd) | I9: Thành tiền (vnd) | J9: Thành tiền (vnd) | K9: CTY CP TM VÀ CN NGUYÊN HANH
K10: Phạm vi | L10: Đơn giá (VND) | M10: Thành Tiền (Không có VAT)
A11: Tổng | G11: N/A | H11: N/A | I11: N/A | J11: 81840000 | M11: =SUM(M12:M18) -> 358940000 | O11: =-J11-M11 -> -440780000
A12: 1 | B12: Sơn Interzinc 52 | C12: EPA142 | D12: Grey | E12: lít | F12: 640 | G12: N/A | H12: N/A | K12: V | L12: 350000 | M12: 224000000 | N12: Nguyên Hanh | O12: - Chưa có số liệu dự toán để so sánh
A13: 2 | B13: Sơn Intergard 475HS | C13: EVA010 | D13: Off White | E13: lít | F13: 520 | G13: N/A | H13: N/A | K13: V | L13: 118000 | M13: 61360000 | N13: Nguyên Hanh
A14: 3 | B14: Sơn Interthane 990 | C14: PHD704 | D14: Ral 7035 | E14: lít | F14: 320 | G14: N/A | H14: N/A | K14: V | L14: 172900 | M14: 55328000 | N14: Nguyên Hanh
A15: 4 | B15: Sơn Intergard 345 | C15: AAD704 | D15: Ral 7035 | E15: lít | F15: 20 | G15: N/A | H15: N/A | K15: V | L15: 208600 | M15: 4172000 | N15: Nguyên Hanh
A16: 5 | B16: Dung môi GTA220 | C16: GTA220 | D16: Clear | E16: lít | F16: 80 | G16: N/A | H16: N/A | K16: V | L16: 64000 | M16: 5120000 | N16: Nguyên Hanh
A17: 6 | B17: Dung môi GTA007 | C17: GTA007 | D17: Clear | E17: lít | F17: 80 | G17: N/A | H17: N/A | K17: V | L17: 64000 | M17: 5120000 | N17: Nguyên Hanh
A18: 7 | B18: Dung môi GTA733 | C18: GTA733 | D18: Clear | E18: lít | F18: 60 | G18: N/A | H18: N/A | K18: V | L18: 64000 | M18: 3840000 | N18: Nguyên Hanh
B19: Đơn giá tổng hợp
A20: II | B20: Khối lượng dự kiến giao (Kg )/ Estimated weight (Kg):
A21: 1 | B21: … | C21: kg
A22: 2 | B22: …
A23: III | B23: Tiến độ/ Schedule | C23: Bắt đầu/ Start | D23: Kết thúc/ Finish
A24: 1 | B24: ….
A26: IV | B26: Nhân lực/ ManPower
A27: 1 | B27: Thợ Pha cắt / Thợ sắt / Thợ hàn / …
B28: ….
A29: V | B29: Yêu cầu kỹ thuật: Tham chiếu các tài liệu đính kèm/ Technical requirement – refer to document attached
B30: Xếp hạng | L30: 1
A31: Ghi chú: PTM tiến hàng mua sắm đẻ đảm bảo tiến độ
A32: NGƯỜI ĐỀ NGHỊ/ RECOMMENDATION BY: | C32: NGƯỜI KIỂM TRA/ DEPARTMENT HEAD CHECK BY: | F32: APPROVED BY: PHÊ DUYỆT
E33: Nguyễn Quang Vinh | H33: Hoàng Ngọc Bằng | K33: Đoàn Văn Toàn

Sheet 25-WNC-I-097
I1: THEO DÕI VẬT TƯ DỰ ÁN/ MATERIAL CONTROL LOG | N1: Hướng dẫn cập nhật thông tin: | R1: Thời gian nộp bảng cập nhật: | CY1: DỰ TOÁN
I2: Tên dự án/ Project no.:25-WNC-I-097 | N2: - Chữ tô màu xanh: | P2: Chưa cập nhật | R2: - Trong ngày khi có biến động.
I3: Cập nhật ngày/ Update to: | K3: =TODAY() -> 46086 | N3: - Chữ tô màu đỏ: | P3: Đã cập nhật mới | R3: - Báo cáo hàng tuần vào 16:30 mỗi chiều thứ 2. | AV3: =SUBTOTAL(9,AV7:AV1406) -> 0
B4: Đánh giá (Thiếu/ Đủ/ Thừa) | I4: Item/ STT | J4: Description/ Chi tiết | K4: Profile/ Vật tư | L4: Grade/ Mác vật liệu | M4: Unit/ Đơn vị | N4: U.Weight/ Đ.Trọng (Kg/m2,m,pcs) | O4: Net Quantity/Số lượng tinh | Q4: Current Ordered/Dự trù lần 0 (Ngày 16/8/2025) | S4: Current Ordered/Dự trù lần 1 (Ngày 26/8/2025) | U4: Current Ordered/Dự trù lần 2 (Ngày 2/10/2025) | W4: Current Ordered/Dự trù lần 3 (Ngày 10/10/2025) | Y4: Current Ordered/Dự trù lần 4 (Ngày 18/10/2025) | AA4: Current Ordered/Dự trù lần 5 (Ngày 23/10/2025) | AC4: Current Ordered/Dự trù lần 6 (Ngày 1/11/2025) | AE4: Current Ordered/Dự trù lần 7 (Ngày 7/11/2025) | AG4: Current Ordered/Dự trù lần 8 (Ngày 16/12/2025) | AI4: Current Ordered/Dự trù lần 9 (Ngày 23/12/2025) | AK4: Current Ordered/Dự trù lần 10 (Ngày 10/1/2026) | AM4: Current Ordered/Dự trù lần 11 (Ngày 22/1/2026) | AO4: Current Ordered/Dự trù lần 12 (Ngày 07/2/2026) | AQ4: Total Ordered/Tổng dự trù | AS4: Remarks/ Ghi chú | AT4: Tận dụng tồn kho/ Remain | AY4: Khối lượng phải mua sắm/ total order | BA4: Ngày bàn giao vật tư/ Material avaiable for hand over date | BB4: VẬT TƯ TRONG NƯỚC | BO4: ĐÃ MUA TRONG NƯỚC | BQ4: QC Nghiệm thu | BU4: Mua sắm nước ngoài/ Oversea purchase | CM4: ĐÃ MUA NHẬP KHẨU | CO4: Nghiệm thu | CS4: TỔNG ĐÃ MUA TRONG VÀ NGOÀI NƯỚC | CU4: So sánh với số lượng vật tư PR | CX4: Remarks/ Ghi chú
O5: Q.Ty/ S.Lượng | P5: Weight/ K.Lượng (Kg) | Q5: Q.Ty/ S.Lượng | R5: Weight/ K.Lượng (Kg) | S5: Q.Ty/ S.Lượng | T5: Weight/ K.Lượng (Kg) | U5: Q.Ty/ S.Lượng | V5: Weight/ K.Lượng (Kg) | W5: Q.Ty/ S.Lượng | X5: Weight/ K.Lượng (Kg) | Y5: Q.Ty/ S.Lượng | Z5: Weight/ K.Lượng (Kg) | AA5: Q.Ty/ S.Lượng | AB5: Weight/ K.Lượng (Kg) | AC5: Q.Ty/ S.Lượng | AD5: Weight/ K.Lượng (Kg) | AE5: Q.Ty/ S.Lượng | AF5: Weight/ K.Lượng (Kg) | AG5: Q.Ty/ S.Lượng | AH5: Weight/ K.Lượng (Kg) | AI5: Q.Ty/ S.Lượng | AJ5: Weight/ K.Lượng (Kg) | AK5: Q.Ty/ S.Lượng | AL5: Weight/ K.Lượng (Kg) | AM5: Q.Ty/ S.Lượng | AN5: Weight/ K.Lượng (Kg) | AO5: Q.Ty/ S.Lượng | AP5: Weight/ K.Lượng (Kg) | AQ5: Q.Ty/ S.Lượng | AR5: Weight/ K.Lượng (Kg) | AT5: Report No. | AU5: Q.Ty/ S.Lượng | AV5: Weight/ K.Lượng (Kg) | AW5: Ngày nghiệm thu ACC | AX5: Remarks/ Ghi chú | AY5: Q.Ty/ S.Lượng | AZ5: Weight/ K.Lượng (Kg) | BB5: Số Hợp đồng / Contract No | BC5: Nhà cung cấp/ Vendor | BD5: Profile/ Vật tư | BE5: Grade/ Mác vật liệu | BF5: Contract weight ( K.Lượng theo HĐ) | BG5: Ngày ký HD/ Contract date | BH5: S.Lượng giao hàng thực tế/ Handover Q'ty | BI5: K.Lượng giao hàng thực tế// Handover weight | BJ5: Đơn giá / Unit Price (Not VAT) | BK5: Tổng tiền cả VAT (VNĐ) | BL5: VAT | BM5: Tổng tiền (VNĐ) | BN5: Bàn giao sản xuất/ Handover to Product | BO5: Q.Ty/ S.Lượng | BP5: Weight/ K.Lượng (Kg) | BQ5: Report No. | BR5: Inspection date | BS5: Khối lượng nghiệm thu đạt/ Weight Acc. Inspection | BT5: Results | BU5: Số Hợp đồng / Contract No | BV5: Nhà cung cấp/ Vendor | BW5: Profile/ Vật tư | BX5: Grade/ Mác vật liệu | BY5: Weight/ Khối lượng (Kg) | BZ5: Ngày ký HD/ Contract date | CA5: Số lượng giao hàng thực tế/ Handover Q'ty | CB5: Khối lượng giao hàng thực tế/ Handover Q'ty | CC5: Đơn giá / Unit Price | CD5: Thành tiền Hợp đồng/ total | CE5: Ngày mở L/C/ LC issued date | CF5: Hàng đi từ cảng nước ngoài/ Export Port | CG5: Hàng Đến cảng HP (CIF)/ HaiPhong CIF | CH5: Ngày thanh toán / Payment date | CI5: Thủ tục hải quan, vận chuyển/ Paper work, local transportaion date | CJ5: Ngày hàng về / Arived | CK5: Ngày mời nghiệm thu / invice QC date | CL5: Bàn giao sản xuất/ Handover to Product | CM5: Q.Ty/ S.Lượng | CN5: Weight/ K.Lượng (Kg) | CO5: Report No. | CP5: Inspection date | CQ5: Khối lượng nghiệm thu đạt/ Weight Acc. Inspection | CR5: Results | CS5: Q.Ty/ S.Lượng | CT5: Weight/ K.Lượng (Kg) | CU5: Q.Ty/ S.Lượng | CV5: Weight/ K.Lượng (Kg) | CW5: Đánh giá (Thiếu/ Đủ/ Thừa) | CY5: STT | CZ5: Chi tiết vật liệu | DB5: ĐVT | DC5: Định mức | DD5: Số lượng | DE5: Khối lượng | DF5: Đơn giá (VNĐ)
C6: Số lượng cần (M/M2) | D6: Xin chuyển đổi | E6: Đã đặt hàng | G6: Xin chuyển đổi | I6: 1 | J6: =I6+1 -> 2 | K6: =J6+1 -> 3 | L6: =K6+1 -> 4 | M6: =L6+1 -> 5 | N6: =M6+1 -> 6 | O6: =N6+1 -> 7 | P6: =O6+1 -> 8 | Q6: =P6+1 -> 9 | ... CX6: =CW6+1 -> 94
F7: Xin chuyển đổi | I7: VTC01 | J7: Main-Material / Vật tư chính thép đen | AQ7: =SUM(AQ8:AQ121) -> 7442.1193 | AR7: =SUM(AR8:AR121) -> 178328.59 | AS7: =SUM(AS8:AS121) -> 0 | AT7: =SUM(AT8:AT121) -> 0 | AU7: =SUM(AU8:AU121) -> 304.2928 | AV7: =SUM(AV8:AV121) -> 3634.4786 | AW7: =SUM(AW8:AW121) -> 0 | AX7: =SUM(AX8:AX121) -> 0 | ... CX7: =SUM(CX8:CX121) -> 0 | CY7: I
A8: =IF(I8=I7,"ok","Hiện") -> Hiện | B8: =CONCATENATE(CW8," Thiếu ít") -> Thiếu Thiếu ít | C8: =CU8 -> 1.3252 | E8: Thép U100x50x5x7.5x12000 | F8: Ngọc hiếu | I8: I97-VTC01-001 | J8: Thép hình C | K8: C100X50X5X7.5-12000L | L8: SS400 | M8: m | N8: 9.36 | O8: 90.232 | P8: 844 | Q8: 99.2552 | R8: 929.02867 | U8: 142.07 | V8: 1329.7752 | W8: 0 | X8: 0 | Y8: 0 | Z8: 0 | AG8: 0 | AH8: 0 | AK8: 0 | AL8: 0 | AM8: 0 | AN8: 0 | AO8: 0 | AP8: 0 | AQ8: =Q8+S8+U8+W8+Y8+AA8+AC8+AE8+AG8+AI8+AK8+AM8+AO8 -> 241.3252 | AR8: =R8+T8+V8+X8+Z8+AB8+AD8+AF8+AH8+AJ8+AL8+AN8+AP8 -> 2258.8039 | AS8: REV02-IBS REV | AY8: =IF(AQ8>AU8,AQ8-AU8,"0") -> 241.3252 | AZ8: =IF(AR8>AV8,AR8-AV8,"0") -> 2258.8039 | BA8: 45892 | BB8: 200825/HN-IBS | BC8: Hùng Nguyên | BD8: Thép U100x50x5x7.5x12000 = 9 Tấm/ Cây | BE8: A36/SS400 | BF8: 1010.88 | BG8: 45889 | BH8: 108 | BI8: 1010.88 | BJ8: 17636.36 | BK8: =BJ8*BI8*1.1 -> 19611068 | BL8: =(BK8-BM8)/BM8 -> 0.1 | BM8: =BJ8*BI8*1 -> 17828244 | BN8: 45892 | BO8: =SUMIF($I:$I,I8,$BH:$BH) -> 240 | BP8: =SUMIF($I:$I,I8,$BI:$BI) -> 2246.44 | CM8: =SUMIF($I:$I,I8,$CA:$CA) -> 0 | CN8: =SUMIF($I:$I,I8,$CB:$CB) -> 0 | CS8: =BO8+CM8 -> 240 | CT8: =BP8+CN8 -> 2246.44 | CU8: =AY8-CS8 -> 1.3252 | CV8: =AZ8-CT8 -> 12.363872 | CW8: =IF(CU8<0,"Thừa",IF(CU8=0,"Đủ","Thiếu")) -> Thiếu
A9: =IF(I9=I8,"ok","Hiện") -> ok | I9: I97-VTC01-001 | J9: Thép hình C | K9: C100X50X5X7.5-12000L | L9: SS400 | M9: m | BB9: 1912-2025/HĐKT/NH-IBS | BC9: Ngọc Hiếu | BD9: Thép U100*50*5*7,5*12000 ( 3 cây) | BE9: SS400 | BF9: 337 | BG9: 46010 | BH9: 36 | BI9: 337 | BJ9: 17090.91 | BK9: =BJ9*BI9*(1+BL9) -> 6335600.3 | BL9: 0.1 | BM9: =BJ9*BI9 -> 5759636.7 | BN9: 46029
A10: =IF(I10=I9,"ok","Hiện") -> ok | I10: I97-VTC01-001 | J10: Thép hình C | K10: C100X50X5X7.5-12000L | L10: SS400 | M10: m | BB10: I97-1010/HN-IBS | BC10: Hùng Nguyên | BD10: Thép U100x50x5x7.5x12000 = 8 CâySS400 | BF10: 898.56 | BG10: 45940 | BH10: 96 | BI10: 898.56 | BJ10: 17681.82 | BK10: =BJ10*BI10*1.1 -> 17476994 | BL10: =(BK10-BM10)/BM10 -> 0.1 | BM10: =BJ10*BI10*1 -> 15888176 | BN10: 45947
A11: =IF(I11=I10,"ok","Hiện") -> Hiện | B11: =CW11 -> Thừa | C11: =CU11 -> -4.91265 | E11: Thép U125x65x6x8x12000 thừa chuyển sang dự án 100 | F11: Ngọc hiếu | I11: I97-VTC01-002 | J11: Thép hình C | K11: C125X65X6X8-12000L | L11: SS400 | M11: m | N11: 13.4 | O11: 296.402 | P11: 3980.4 | Q11: 326.0422 | R11: 4368.9655 | U11: 629.04515 | V11: 8429.205 | W11: 0 | X11: 0 | Y11: 0 | Z11: 0 | AG11: 0 | AH11: 0 | AK11: 0 | AL11: 0 | AM11: 0 | AN11: 0 | AO11: 0 | AP11: 0 | AQ11: =Q11+S11+U11+W11+Y11+AA11+AC11+AE11+AG11+AI11+AK11+AM11+AO11 -> 955.08735 | AR11: =R11+T11+V11+X11+Z11+AB11+AD11+AF11+AH11+AJ11+AL11+AN11+AP11 -> 12798.17 | AS11: REV02-IBS REV | AY11: =IF(AQ11>AU11,AQ11-AU11,"0") -> 955.08735 | AZ11: =IF(AR11>AV11,AR11-AV11,"0") -> 12798.17 | BA11: 45892 | BB11: 200825/HN-IBS | BC11: Hùng Nguyên | BD11: Thép U125x65x6x8x12000 = 28 Tấm/ Cây | BE11: A36/SS400 | BF11: 4502.4 | BG11: 45889 | BH11: 336 | BI11: 4502.4 | BJ11: 17636.36 | BK11: =BJ11*BI11*1.1 -> 87346542 | BL11: =(BK11-BM11)/BM11 -> 0.1 | BM11: =BJ11*BI11*1 -> 79405947 | BN11: 45892 | BO11: =SUMIF($I:$I,I11,$BH:$BH) -> 960 | BP11: =SUMIF($I:$I,I11,$BI:$BI) -> 12864.4 | CM11: =SUMIF($I:$I,I11,$CA:$CA) -> 0 | CN11: =SUMIF($I:$I,I11,$CB:$CB) -> 0 | CS11: =BO11+CM11 -> 960 | CT11: =BP11+CN11 -> 12864.4 | CU11: =AY11-CS11 -> -4.91265 | CV11: =AZ11-CT11 -> -66.22951 | CW11: =IF(CU11<0,"Thừa",IF(CU11=0,"Đủ","Thiếu")) -> Thừa
A12: =IF(I12=I11,"ok","Hiện") -> ok | I12: I97-VTC01-002 | J12: Thép hình C | K12: C125X65X6X8-12000L | L12: SS400 | M12: m | BB12: 1912-2025/HĐKT/NH-IBS | BC12: Ngọc Hiếu | BD12: Thép U125*65*6*8*12000 ( 20 cây) | BE12: SS400 | BF12: 3216 | BG12: 46010 | BH12: 240 | BI12: 3216 | BJ12: 17090.91 | BK12: =BJ12*BI12*(1+BL12) -> 60460803 | BL12: 0.1 | BM12: =BJ12*BI12 -> 54964367 | BN12: 46029
A13: =IF(I13=I12,"ok","Hiện") -> ok | I13: I97-VTC01-002 | J13: Thép hình C | K13: C125X65X6X8-12000L | L13: SS400 | M13: m | BB13: 1510-2025/HĐKT/NH-IBS | BC13: Ngọc Hiếu | BD13: Thép U125*65*6*8*12000 = 32 Cây | BF13: 5146 | BG13: 45945 | BH13: 384 | BI13: 5146 | BJ13: 17545.45 | BK13: =BJ13*BI13*1.1 -> 99317774 | BL13: =(BK13-BM13)/BM13 -> 0.1 | BM13: =BJ13*BI13*1 -> 90288886 | BN13: 45954
A14: =IF(I14=I13,"ok","Hiện") -> Hiện | B14: =CW14 -> Thừa | C14: =CU14 -> -1.8881 | E14: Thép U200x90x8x13.5x12000 Hàng thiếu dùng dự án 100 | F14: Ngọc hiếu | I14: I97-VTC01-003 | J14: Thép hình C | K14: C200X90X8X13.5-12000L | L14: SS400 | M14: m | N14: 30.34 | O14: 71.076 | P14: 2167.8 | Q14: 78.1836 | R14: 2372.0904 | U14: 111.9283 | V14: 3395.9046 | W14: 0 | X14: 0 | Y14: 0 | Z14: 0 | AG14: 0 | AH14: 0 | AK14: 0 | AL14: 0 | AM14: 0 | AN14: 0 | AO14: 0 | AP14: 0 | AQ14: =Q14+S14+U14+W14+Y14+AA14+AC14+AE14+AG14+AI14+AK14+AM14+AO14 -> 190.1119 | AR14: =R14+T14+V14+X14+Z14+AB14+AD14+AF14+AH14+AJ14+AL14+AN14+AP14 -> 5767.995 | AS14: REV02-IBS REV | AY14: =IF(AQ14>AU14,AQ14-AU14,"0") -> 190.1119 | AZ14: =IF(AR14>AV14,AR14-AV14,"0") -> 5767.995 | BA14: 45892 | BB14: 200825/HN-IBS | BC14: Hùng Nguyên | BD14: Thép U200x90x8x13.5x12000 = 6 Tấm/ Cây | BE14: A36/SS400 | BF14: 2181.6 | BG14: 45889 | BH14: 72 | BI14: 2181.6 | BJ14: 17636.36 | BK14: =BJ14*BI14*1.1 -> 42323031 | BL14: =(BK14-BM14)/BM14 -> 0.1 | BM14: =BJ14*BI14*1 -> 38475483 | BN14: 45892 | BO14: =SUMIF($I:$I,I14,$BH:$BH) -> 192 | BP14: =SUMIF($I:$I,I14,$BI:$BI) -> 5819.36 | CM14: =SUMIF($I:$I,I14,$CA:$CA) -> 0 | CN14: =SUMIF($I:$I,I14,$CB:$CB) -> 0 | CS14: =BO14+CM14 -> 192 | CT14: =BP14+CN14 -> 5819.36 | CU14: =AY14-CS14 -> -1.8881 | CV14: =AZ14-CT14 -> -51.364954 | CW14: =IF(CU14<0,"Thừa",IF(CU14=0,"Đủ","Thiếu")) -> Thừa
A15: =IF(I15=I14,"ok","Hiện") -> ok | I15: I97-VTC01-003 | J15: Thép hình C | K15: C200X90X8X13.5-12000L | L15: SS400 | M15: m | BB15: 1912-2025/HĐKT/NH-IBS | BC15: Ngọc Hiếu | BD15: Thép U200*90*8*13,5*12000 ( 4 cây) | BE15: SS400 | BF15: 1454 | BG15: 46010 | BH15: 48 | BI15: 1454 | BJ15: 17272.73 | BK15: =BJ15*BI15*(1+BL15) -> 27626004 | BL15: 0.1 | BM15: =BJ15*BI15 -> 25114549 | BN15: 46036
A16: =IF(I16=I15,"ok","Hiện") -> ok | I16: I97-VTC01-003 | J16: Thép hình C | K16: C200X90X8X13.5-12000L | L16: SS400 | M16: m | BB16: I97-1010/HN-IBS | BC16: Hùng Nguyên | BD16: Thép U200x90x8x13.5x12000 = 6 CâySS400 | BF16: 2183.76 | BG16: 45940 | BH16: 72 | BI16: 2183.76 | BJ16: 17681.82 | BK16: =BJ16*BI16*1.1 -> 42474136 | BL16: =(BK16-BM16)/BM16 -> 0.1 | BM16: =BJ16*BI16*1 -> 38612851 | BN16: 45947
A17: =IF(I17=I16,"ok","Hiện") -> Hiện | B17: =CW17 -> Thừa | C17: =CU17 -> -0.8026 | D17: Dùng 3m hàng tồn của 102 | I17: I97-VTC01-004 | J17: Thép ống | K17: CHS33.7X2.6-6000L | L17: SS400 | M17: m | N17: 2.0267531 | O17: 4.934 | P17: 10 | Q17: 5.4274 | R17: 11 | U17: 7.77 | V17: 15.747872 | W17: 0 | X17: 0 | Y17: 0 | Z17: 0 | AG17: 0 | AH17: 0 | AK17: 0 | AL17: 0 | AM17: 0 | AN17: 0 | AO17: 0 | AP17: 0 | AQ17: =Q17+S17+U17+W17+Y17+AA17+AC17+AE17+AG17+AI17+AK17+AM17+AO17 -> 13.1974 | AR17: =R17+T17+V17+X17+Z17+AB17+AD17+AF17+AH17+AJ17+AL17+AN17+AP17 -> 26.747872 | AS17: REV02-IBS REV | AU17: 2 | AV17: =AU17*N17 -> 4.0535063 | AX17: Đã mời ngày 14/10 | AY17: =IF(AQ17>AU17,AQ17-AU17,"0") -> 11.1974 | AZ17: =IF(AR17>AV17,AR17-AV17,"0") -> 22.694366 | BA17: 45892 | BB17: Báo giá ngày 22/8/2025 | BC17: TITAN/190 | BD17: Thép ống đen 33,5 x 2,6 x 6.000 mm | BE17: STK R400 | BF17: 12 | BG17: 45891 | BH17: 6 | BI17: 12 | BJ17: 18500 | BK17: =BJ17*BI17*1.1 -> 244200 | BL17: =(BK17-BM17)/BM17 -> 0.1 | BM17: =BJ17*BI17*1 -> 222000 | BN17: 45903 | BO17: =SUMIF($I:$I,I17,$BH:$BH) -> 12 | BP17: =SUMIF($I:$I,I17,$BI:$BI) -> 24 | CM17: =SUMIF($I:$I,I17,$CA:$CA) -> 0 | CN17: =SUMIF($I:$I,I17,$CB:$CB) -> 0 | CS17: =BO17+CM17 -> 12 | CT17: =BP17+CN17 -> 24 | CU17: =AY17-CS17 -> -0.8026 | CV17: =AZ17-CT17 -> -1.3056344 | CW17: =IF(CU17<0,"Thừa",IF(CU17=0,"Đủ","Thiếu")) -> Thừa
A18: =IF(I18=I17,"ok","Hiện") -> ok | I18: I97-VTC01-004 | J18: Thép ống | K18: CHS33.7X2.6-6000L | L18: SS400 | BB18: Báo giá ngày 10/10/2025 | BC18: TITAN/190 | BD18: Thép ống đen 33.700 x 2.600 x 6000.0 mm = 1Cây | BF18: 12 | BG18: 45940 | BH18: 6 | BI18: 12 | BJ18: 16818.182 | BK18: =BJ18*BI18*1.1 -> 222000 | BL18: =(BK18-BM18)/BM18 -> 0.1 | BM18: =BJ18*BI18*1 -> 201818.18 | BN18: 45953
A19: =IF(I19=I18,"ok","Hiện") -> Hiện | B19: =CW19 -> Thừa | C19: =CU19 -> -0.7746 | I19: I97-VTC01-005 | J19: Thép ống | K19: CHS42.4X4-6000L | L19: SS400 | M19: m | N19: 3.9633806 | O19: 17.914 | P19: 71 | Q19: 19.7054 | R19: 78.1 | U19: 27.52 | V19: 109.07223 | W19: 0 | X19: 0 | Y19: 0 | Z19: 0 | AG19: 0 | AH19: 0 | AK19: 0 | AL19: 0 | AM19: 0 | AN19: 0 | AO19: 0 | AP19: 0 | AQ19: =Q19+S19+U19+W19+Y19+AA19+AC19+AE19+AG19+AI19+AK19+AM19+AO19 -> 47.2254 | AR19: =R19+T19+V19+X19+Z19+AB19+AD19+AF19+AH19+AJ19+AL19+AN19+AP19 -> 187.17223 | AS19: REV02-IBS REV | AY19: =IF(AQ19>AU19,AQ19-AU19,"0") -> 47.2254 | AZ19: =IF(AR19>AV19,AR19-AV19,"0") -> 187.17223 | BA19: 45892 | BB19: Báo giá ngày 22/8/2025 | BC19: TITAN/190 | BD19: Thép ống đen 42,2 x 4,0 x 6.000 mm | BE19: STK R400 | BF19: 90 | BG19: 45891 | BH19: 24 | BI19: 90 | BJ19: 18500 | BK19: =BJ19*BI19*1.1 -> 1831500 | BL19: =(BK19-BM19)/BM19 -> 0.1 | BM19: =BJ19*BI19*1 -> 1665000 | BN19: 45903 | BO19: =SUMIF($I:$I,I19,$BH:$BH) -> 48 | BP19: =SUMIF($I:$I,I19,$BI:$BI) -> 180 | CM19: =SUMIF($I:$I,I19,$CA:$CA) -> 0 | CN19: =SUMIF($I:$I,I19,$CB:$CB) -> 0 | CS19: =BO19+CM19 -> 48 | CT19: =BP19+CN19 -> 180 | CU19: =AY19-CS19 -> -0.7746 | CV19: =AZ19-CT19 -> 7.172234 | CW19: =IF(CU19<0,"Thừa",IF(CU19=0,"Đủ","Thiếu")) -> Thừa
A20: =IF(I20=I19,"ok","Hiện") -> ok | I20: I97-VTC01-005 | J20: Thép ống | K20: CHS42.4X4-6000L | L20: SS400 | BB20: Báo giá ngày 10/10/2025 | BC20: TITAN/190 | BD20: Thép ống đen 42.200 x 4.00 x 6000.0 mm = 4Cây | BF20: 90 | BG20: 45940 | BH20: 24 | BI20: 90 | BJ20: 16818.182 | BK20: =BJ20*BI20*1.1 -> 1665000 | BL20: =(BK20-BM20)/BM20 -> 0.1 | BM20: =BJ20*BI20*1 -> 1513636.4 | BN20: 45953
A21: =IF(I21=I20,"ok","Hiện") -> Hiện | B21: =CW21 -> Thừa | C21: =CU21 -> -96 | D21: CHS48.3x3.6-6000L / ASTM-A53-GR.B (Dự án 078 thừa 243m) | I21: I97-VTC01-006 | J21: Thép ống | K21: CHS48.3X3.7-6000L | L21: SS400 | M21: m | N21: 4.0427427 | O21: 85.348 | P21: 345.04 | Q21: 93.8828 | R21: 379.544 | U21: 134.41 | V21: 543.38504 | W21: 0 | X21: 0 | Y21: 0 | Z21: 0 | AG21: 0 | AH21: 0 | AK21: 0 | AL21: 0 | AM21: 0 | AN21: 0 | AO21: 0 | AP21: 0 | AQ21: =Q21+S21+U21+W21+Y21+AA21+AC21+AE21+AG21+AI21+AK21+AM21+AO21 -> 228.2928 | AR21: =R21+T21+V21+X21+Z21+AB21+AD21+AF21+AH21+AJ21+AL21+AN21+AP21 -> 922.92904 | AS21: REV02-IBS REV | AU21: 228.2928 | AV21: 922.92904 | AX21: Hàng tồn dự án 078/ Nhập Gnee | AY21: =IF(AQ21>AU21,AQ21-AU21,"0") -> 0 | AZ21: =IF(AR21>AV21,AR21-AV21,"0") -> 0 | BA21: 45892 | BB21: Báo giá ngày 22/8/2025 | BC21: TITAN/190 | BD21: Thép ống đen 48,3 x 3,7 x 6.000 mm | BE21: STK R400 | BF21: 391 | BG21: 45891 | BH21: 96 | BI21: 391 | BJ21: 18500 | BK21: =BJ21*BI21*1.1 -> 7956850 | BL21: =(BK21-BM21)/BM21 -> 0.1 | BM21: =BJ21*BI21*1 -> 7233500 | BN21: 45903 | BO21: =SUMIF($I:$I,I21,$BH:$BH) -> 96 | BP21: =SUMIF($I:$I,I21,$BI:$BI) -> 391 | CM21: =SUMIF($I:$I,I21,$CA:$CA) -> 0 | CN21: =SUMIF($I:$I,I21,$CB:$CB) -> 0 | CS21: =BO21+CM21 -> 96 | CT21: =BP21+CN21 -> 391 | CU21: =AY21-CS21 -> -96 | CV21: =AZ21-CT21 -> -391 | CW21: =IF(CU21<0,"Thừa",IF(CU21=0,"Đủ","Thiếu")) -> Thừa
A22: =IF(I22=I21,"ok","Hiện") -> Hiện | B22: =CW22 -> Thừa | C22: =CU22 -> -3.0628 | I22: I97-VTC01-007 | J22: Thép ống | K22: CHS50X3.5-6000L | L22: SS400 | M22: m | N22: 4.5487106 | O22: 5.584 | P22: 25.4 | Q22: 6.1424 | R22: 27.94 | U22: 8.7948 | V22: 40.005 | W22: 0 | X22: 0 | Y22: 0 | Z22: 0 | AG22: 0 | AH22: 0 | AK22: 0 | AL22: 0 | AM22: 0 | AN22: 0 | AO22: 0 | AP22: 0 | AQ22: =Q22+S22+U22+W22+Y22+AA22+AC22+AE22+AG22+AI22+AK22+AM22+AO22 -> 14.9372 | AR22: =R22+T22+V22+X22+Z22+AB22+AD22+AF22+AH22+AJ22+AL22+AN22+AP22 -> 67.945 | AS22: REV02-IBS REV | AY22: =IF(AQ22>AU22,AQ22-AU22,"0") -> 14.9372 | AZ22: =IF(AR22>AV22,AR22-AV22,"0") -> 67.945 | BA22: 45892 | BB22: Báo giá ngày 22/8/2025 | BC22: TITAN/190 | BD22: Thép ống đen 50,0 x 3,5 x 6.000 mm | BE22: STK R400 | BF22: 48 | BG22: 45891 | BH22: 12 | BI22: 48 | BJ22: 18500 | BK22: =BJ22*BI22*1.1 -> 976800 | BL22: =(BK22-BM22)/BM22 -> 0.1 | BM22: =BJ22*BI22*1 -> 888000 | BN22: 45903 | BO22: =SUMIF($I:$I,I22,$BH:$BH) -> 18 | BP22: =SUMIF($I:$I,I22,$BI:$BI) -> 72 | CM22: =SUMIF($I:$I,I22,$CA:$CA) -> 0 | CN22: =SUMIF($I:$I,I22,$CB:$CB) -> 0 | CS22: =BO22+CM22 -> 18 | CT22: =BP22+CN22 -> 72 | CU22: =AY22-CS22 -> -3.0628 | CV22: =AZ22-CT22 -> -4.055 | CW22: =IF(CU22<0,"Thừa",IF(CU22=0,"Đủ","Thiếu")) -> Thừa
A23: =IF(I23=I22,"ok","Hiện") -> ok | I23: I97-VTC01-007 | J23: Thép ống | K23: CHS50X3.5-6000L | L23: SS400 | M23: m | BB23: Báo giá ngày 10/10/2025 | BC23: TITAN/190 | BD23: Thép ống đen 50.00 x 3.500 x 6000.0 mm = 1Cây | BF23: 24 | BG23: 45940 | BH23: 6 | BI23: 24 | BJ23: 16818.182 | BK23: =BJ23*BI23*1.1 -> 444000 | BL23: =(BK23-BM23)/BM23 -> 0.1 | BM23: =BJ23*BI23*1 -> 403636.36 | BN23: 45953
A24: =IF(I24=I23,"ok","Hiện") -> Hiện | B24: =CW24 -> Đủ | C24: =CU24 -> 0 | F24: ELBOW 90˚ LR ( DN32 ) Ø42.2 x 3.56mmB 16.9A234WPB | G24: Tam Đa | I24: I97-VTC01-008 | J24: elbow | K24: ELBOW 42.4x4-90 độ LONG-DIN2605-TYPE3 | L24: SS400 | M24: cái | N24: 0 | O24: 18 | P24: 0 | Q24: 20 | U24: 28 | V24: 0 | W24: 0 | X24: 0 | Y24: 0 | Z24: 0 | AG24: 0 | AH24: 0 | AK24: 0 | AL24: 0 | AM24: 0 | AN24: 0 | AO24: 0 | AP24: 0 | AQ24: =Q24+S24+U24+W24+Y24+AA24+AC24+AE24+AG24+AI24+AK24+AM24+AO24 -> 48 | AR24: =R24+T24+V24+X24+Z24+AB24+AD24+AF24+AH24+AJ24+AL24+AN24+AP24 -> 0 | AS24: REV02-IBS REV | AY24: =IF(AQ24>AU24,AQ24-AU24,"0") -> 48 | AZ24: =IF(AR24>AV24,AR24-AV24,"0") -> 0 | BA24: 45892 | BB24: Báo giá ngày 20/8/2025 | BC24: Tam Đa | BD24: ELBOW 42.4x4-90 độ LONG-DIN2605-TYPE3 | BF24: N/A | BG24: 45889 | BH24: 20 | BI24: N/A | BJ24: 26000 | BK24: =BJ24*BH24*1.1 -> 572000 | BL24: =(BK24-BM24)/BM24 -> 0.1 | BM24: =BJ24*BH24*1 -> 520000 | BN24: 45911 | BO24: =SUMIF($I:$I,I24,$BH:$BH) -> 48 | BP24: =SUMIF($I:$I,I24,$BI:$BI) -> 0 | CM24: =SUMIF($I:$I,I24,$CA:$CA) -> 0 | CN24: =SUMIF($I:$I,I24,$CB:$CB) -> 0 | CS24: =BO24+CM24 -> 48 | CT24: =BP24+CN24 -> 0 | CU24: =AY24-CS24 -> 0 | CV24: =AZ24-CT24 -> 0 | CW24: =IF(CU24<0,"Thừa",IF(CU24=0,"Đủ","Thiếu")) -> Đủ
A25: =IF(I25=I24,"ok","Hiện") -> ok | I25: I97-VTC01-008 | J25: elbow | K25: ELBOW 42.4x4-90 độ LONG-DIN2605-TYPE3 | L25: SS400 | M25: cái | BB25: ? | BC25: Tam Đa | BD25: ELBOW 90˚ LRDN32B 16.9Ø42.2 x 3.56mmA234WPB = 28PCS | BF25: N/A | BG25: ? | BH25: 28 | BI25: N/A | BJ25: 26000 | BK25: =BJ25*BH25*1.1 -> 800800 | BL25: =(BK25-BM25)/BM25 -> 0.1 | BM25: =BJ25*BH25*1 -> 728000 | BN25: 45968
A26: =IF(I26=I25,"ok","Hiện") -> Hiện | B26: =CW26 -> Đủ | C26: =CU26 -> 0 | F26: ELBOW 45˚ LR ( DN40 ) Ø48.3 x 3.68mmB 16.9A234WPB | G26: Tam Đa | I26: I97-VTC01-009 | J26: elbow | K26: ELBOW 48.3X4-45 độ LONG-DIN2605-TYPE3 | L26: SS400 | M26: cái | N26: 0 | O26: 32 | P26: 0 | Q26: 36 | U26: 49 | V26: 0 | W26: 0 | X26: 0 | Y26: 0 | Z26: 0 | AG26: 0 | AH26: 0 | AK26: 0 | AL26: 0 | AM26: 0 | AN26: 0 | AO26: 0 | AP26: 0 | AQ26: =Q26+S26+U26+W26+Y26+AA26+AC26+AE26+AG26+AI26+AK26+AM26+AO26 -> 85 | AR26: =R26+T26+V26+X26+Z26+AB26+AD26+AF26+AH26+AJ26+AL26+AN26+AP26 -> 0 | AS26: REV02-IBS REV | AY26: =IF(AQ26>AU26,AQ26-AU26,"0") -> 85 | AZ26: =IF(AR26>AV26,AR26-AV26,"0") -> 0 | BA26: 45892 | BB26: Báo giá ngày 20/8/2025 | BC26: Tam Đa | BD26: ELBOW 48.3X4-45 độ LONG-DIN2605-TYPE3 | BF26: N/A | BG26: 45889 | BH26: 36 | BI26: N/A | BJ26: 18000 | BK26: =BJ26*BH26*1.1 -> 712800 | BL26: =(BK26-BM26)/BM26 -> 0.1 | BM26: =BJ26*BH26*1 -> 648000 | BN26: 45911 | BO26: =SUMIF($I:$I,I26,$BH:$BH) -> 85 | BP26: =SUMIF($I:$I,I26,$BI:$BI) -> 0 | CM26: =SUMIF($I:$I,I26,$CA:$CA) -> 0 | CN26: =SUMIF($I:$I,I26,$CB:$CB) -> 0 | CS26: =BO26+CM26 -> 85 | CT26: =BP26+CN26 -> 0 | CU26: =AY26-CS26 -> 0 | CV26: =AZ26-CT26 -> 0 | CW26: =IF(CU26<0,"Thừa",IF(CU26=0,"Đủ","Thiếu")) -> Đủ
A27: =IF(I27=I26,"ok","Hiện") -> ok | I27: I97-VTC01-009 | J27: elbow | K27: ELBOW 48.3X4-45 độ LONG-DIN2605-TYPE3 | L27: SS400 | M27: cái | BB27: ? | BC27: Tam Đa | BD27: ELBOW 45˚ LRDN40B 16.9Ø48.3 x 3.68mmA234WPB = 49PCS | BF27: N/A | BH27: 49 | BI27: N/A | BJ27: 18000 | BK27: =BJ27*BH27*1.1 -> 970200 | BL27: =(BK27-BM27)/BM27 -> 0.1 | BM27: =BJ27*BH27*1 -> 882000 | BN27: 45968
A28: =IF(I28=I27,"ok","Hiện") -> Hiện | B28: =CW28 -> Đủ | C28: =CU28 -> 0 | F28: ELBOW 90˚ LR ( DN40 ) Ø48.3 x 3.68mmB 16.9A234WPB | G28: Tam Đa | I28: I97-VTC01-010 | J28: elbow | K28: ELBOW 48.3X4-90 độ LONG-DIN2605-TYPE3 | L28: SS400 | M28: cái | N28: 0 | O28: 32 | P28: 0 | Q28: 36 | U28: 49 | V28: 0 | W28: 0 | X28: 0 | Y28: 0 | Z28: 0 | AG28: 0 | AH28: 0 | AK28: 0 | AL28: 0 | AM28: 0 | AN28: 0 | AO28: 0 | AP28: 0 | AQ28: =Q28+S28+U28+W28+Y28+AA28+AC28+AE28+AG28+AI28+AK28+AM28+AO28 -> 85 | AR28: =R28+T28+V28+X28+Z28+AB28+AD28+AF28+AH28+AJ28+AL28+AN28+AP28 -> 0 | AS28: REV02-IBS REV | AY28: =IF(AQ28>AU28,AQ28-AU28,"0") -> 85 | AZ28: =IF(AR28>AV28,AR28-AV28,"0") -> 0 | BA28: 45892 | BB28: Báo giá ngày 20/8/2025 | BC28: Tam Đa | BD28: ELBOW 48.3X4-90 độ LONG-DIN2605-TYPE3 | BF28: N/A | BG28: 45889 | BH28: 36 | BI28: N/A | BJ28: 32000 | BK28: =BJ28*BH28*1.1 -> 1267200 | BL28: =(BK28-BM28)/BM28 -> 0.1 | BM28: =BJ28*BH28*1 -> 1152000 | BN28: 45911 | BO28: =SUMIF($I:$I,I28,$BH:$BH) -> 85 | BP28: =SUMIF($I:$I,I28,$BI:$BI) -> 0 | CM28: =SUMIF($I:$I,I28,$CA:$CA) -> 0 | CN28: =SUMIF($I:$I,I28,$CB:$CB) -> 0 | CS28: =BO28+CM28 -> 85 | CT28: =BP28+CN28 -> 0 | CU28: =AY28-CS28 -> 0 | CV28: =AZ28-CT28 -> 0 | CW28: =IF(CU28<0,"Thừa",IF(CU28=0,"Đủ","Thiếu")) -> Đủ
A29: =IF(I29=I28,"ok","Hiện") -> ok | I29: I97-VTC01-010 | J29: elbow | K29: ELBOW 48.3X4-90 độ LONG-DIN2605-TYPE3 | L29: SS400 | M29: cái | BB29: ? | BC29: Tam Đa | BD29: ELBOW 90˚ LRDN40B 16.9Ø48.3 x 3.68mmA234WPB = 49PCS | BF29: N/A | BH29: 49 | BI29: N/A | BJ29: 32000 | BK29: =BJ29*BH29*1.1 -> 1724800 | BL29: =(BK29-BM29)/BM29 -> 0.1 | BM29: =BJ29*BH29*1 -> 1568000 | BN29: 45968
A30: =IF(I30=I29,"ok","Hiện") -> Hiện | B30: =CW30 -> Thừa | C30: =CU30 -> -4.52 | E30: Thép H100x100x6x8x12000 | I30: I97-VTC01-011 | J30: thép hình H | K30: H100X100X6X8-12000L | L30: SS400 | M30: m | N30: 17.2 | O30: 7.284 | P30: 123.4 | Q30: 12 | R30: 206.4 | U30: 7.48 | V30: 128.656 | W30: 0 | X30: 0 | Y30: 0 | Z30: 0 | AG30: 0 | AH30: 0 | AK30: 0 | AL30: 0 | AM30: 0 | AN30: 0 | AO30: 0 | AP30: 0 | AQ30: =Q30+S30+U30+W30+Y30+AA30+AC30+AE30+AG30+AI30+AK30+AM30+AO30 -> 19.48 | AR30: =R30+T30+V30+X30+Z30+AB30+AD30+AF30+AH30+AJ30+AL30+AN30+AP30 -> 335.056 | AS30: REV02-IBS REV | AY30: =IF(AQ30>AU30,AQ30-AU30,"0") -> 19.48 | AZ30: =IF(AR30>AV30,AR30-AV30,"0") -> 335.056 | BA30: 45892 | BB30: 200825/HN-IBS | BC30: Hùng Nguyên | BD30: Thép H100x100x6x8x12000 = 1 Tấm/ Cây | BE30: A36/SS400 | BF30: 206.4 | BG30: 45889 | BH30: 12 | BI30: 206.4 | BJ30: 17636.36 | BK30: =BJ30*BI30*1.1 -> 4004159.2 | BL30: =(BK30-BM30)/BM30 -> 0.1 | BM30: =BJ30*BI30*1 -> 3640144.7 | BN30: 45892 | BO30: =SUMIF($I:$I,I30,$BH:$BH) -> 24 | BP30: =SUMIF($I:$I,I30,$BI:$BI) -> 409.2 | CM30: =SUMIF($I:$I,I30,$CA:$CA) -> 0 | CN30: =SUMIF($I:$I,I30,$CB:$CB) -> 0 | CS30: =BO30+CM30 -> 24 | CT30: =BP30+CN30 -> 409.2 | CU30: =AY30-CS30 -> -4.52 | CV30: =AZ30-CT30 -> -74.144 | CW30: =IF(CU30<0,"Thừa",IF(CU30=0,"Đủ","Thiếu")) -> Thừa
A31: =IF(I31=I30,"ok","Hiện") -> ok | I31: I97-VTC01-011 | J31: thép hình H | K31: H100X100X6X8-12000L | L31: SS400 | M31: m | BB31: 03.10.2025/APEC-IBS | BC31: APEC 2 | BD31: H100X100X6X8x12000mm = 12 m Cây/ Tấm SS400 | BE31: SS400 | BF31: 202.8 | BG31: 45933 | BH31: =1*12 -> 12 | BI31: 202.8 | BJ31: 17636.364 | BK31: =BJ31*BI31*1.1 -> 3934320 | BL31: =(BK31-BM31)/BM31 -> 0.1 | BM31: =BJ31*BI31*1 -> 3576654.5 | BN31: 45940
A32: =IF(I32=I31,"ok","Hiện") -> Hiện | B32: =CW32 -> Thừa | C32: =CU32 -> -4.38 | E32: Thép I194x150x6x9x12000 | I32: I97-VTC01-012 | J32: thép hình H | K32: H194X150X6X9-6000L | L32: SS400 | M32: m | N32: 30.6 | O32: 2.85 | P32: 85.2 | Q32: 6 | R32: 183.6 | U32: 1.62 | V32: 49.572 | W32: 0 | X32: 0 | Y32: 0 | Z32: 0 | AG32: 0 | AH32: 0 | AK32: 0 | AL32: 0 | AM32: 0 | AN32: 0 | AO32: 0 | AP32: 0 | AQ32: =Q32+S32+U32+W32+Y32+AA32+AC32+AE32+AG32+AI32+AK32+AM32+AO32 -> 7.62 | AR32: =R32+T32+V32+X32+Z32+AB32+AD32+AF32+AH32+AJ32+AL32+AN32+AP32 -> 233.172 | AS32: REV02-IBS REV | AY32: =IF(AQ32>AU32,AQ32-AU32,"0") -> 7.62 | AZ32: =IF(AR32>AV32,AR32-AV32,"0") -> 233.172 | BA32: 45892 | BB32: 200825/HN-IBS | BC32: Hùng Nguyên | BD32: Thép I194x150x6x9x12000 = 1 Tấm/ Cây | BE32: A36/SS400 | BF32: 367.2 | BG32: 45889 | BH32: 12 | BI32: 367.2 | BJ32: 17636.36 | BK32: =BJ32*BI32*1.1 -> 7123678.5 | BL32: =(BK32-BM32)/BM32 -> 0.1 | BM32: =BJ32*BI32*1 -> 6476071.4 | BN32: 45892 | BO32: =SUMIF($I:$I,I32,$BH:$BH) -> 12 | BP32: =SUMIF($I:$I,I32,$BI:$BI) -> 367.2 | CM32: =SUMIF($I:$I,I32,$CA:$CA) -> 0 | CN32: =SUMIF($I:$I,I32,$CB:$CB) -> 0 | CS32: =BO32+CM32 -> 12 | CT32: =BP32+CN32 -> 367.2 | CU32: =AY32-CS32 -> -4.38 | CV32: =AZ32-CT32 -> -134.028 | CW32: =IF(CU32<0,"Thừa",IF(CU32=0,"Đủ","Thiếu")) -> Thừa
A33: =IF(I33=I32,"ok","Hiện") -> Hiện | B33: =CONCATENATE(CW33," thiếu ít đủ") -> Thiếu thiếu ít đủ | C33: =CU33 -> 3 | E33: Thép H300x300x10x15x12000 | F33: đặt MCL | I33: I97-VTC01-013 | J33: thép hình H | K33: H300X300X10X15-12000L | L33: SS400 | M33: m | N33: 94 | O33: 61.4 | P33: 5711.2 | Q33: 72 | R33: 6768 | U33: 171 | V33: 16074 | W33: 0 | X33: 0 | Y33: 0 | Z33: 0 | AG33: 0 | AH33: 0 | AK33: 0 | AL33: 0 | AM33: 0 | AN33: 0 | AO33: 0 | AP33: 0 | AQ33: =Q33+S33+U33+W33+Y33+AA33+AC33+AE33+AG33+AI33+AK33+AM33+AO33 -> 243 | AR33: =R33+T33+V33+X33+Z33+AB33+AD33+AF33+AH33+AJ33+AL33+AN33+AP33 -> 22842 | AS33: REV02-IBS REV | AY33: =IF(AQ33>AU33,AQ33-AU33,"0") -> 243 | AZ33: =IF(AR33>AV33,AR33-AV33,"0") -> 22842 | BA33: 45892 | BB33: 200825/HN-IBS | BC33: Hùng Nguyên | BD33: Thép H300x300x10x15x12000 = 6 Tấm/ Cây | BE33: A36/SS400 | BF33: 6768 | BG33: 45889 | BH33: 72 | BI33: 6768 | BJ33: 17636.36 | BK33: =BJ33*BI33*1.1 -> 1.3129917e+08 | BL33: =(BK33-BM33)/BM33 -> 0.1 | BM33: =BJ33*BI33*1 -> 1.1936288e+08 | BN33: 45892 | BO33: =SUMIF($I:$I,I33,$BH:$BH) -> 180 | BP33: =SUMIF($I:$I,I33,$BI:$BI) -> 16812 | BU33: 25MCL145S | BV33: MCL | BW33: H300X300X10X15-12000L | BX33: SS400 | BY33: 5580 | BZ33: 45988 | CA33: 60 | CB33: 5580 | CC33: 0.621 | CD33: =CC33*CB33 -> 3465.18 | CL33: 46047 | CM33: =SUMIF($I:$I,I33,$CA:$CA) -> 60 | CN33: =SUMIF($I:$I,I33,$CB:$CB) -> 5580 | CS33: =BO33+CM33 -> 240 | CT33: =BP33+CN33 -> 22392 | CU33: =AY33-CS33 -> 3 | CV33: =AZ33-CT33 -> 450 | CW33: =IF(CU33<0,"Thừa",IF(CU33=0,"Đủ","Thiếu")) -> Thiếu
A34: =IF(I34=I33,"ok","Hiện") -> ok | I34: I97-VTC01-013 | J34: thép hình H | K34: H300X300X10X15-12000L | L34: SS400 | M34: m | BB34: 03.10.2025/APEC-IBS | BC34: APEC 2 | BD34: H300X300X10X15x12000mm = 108 m Cây/ Tấm SS400 | BE34: SS400/A36 | BF34: 10044 | BG34: 45933 | BH34: =9*12 -> 108 | BI34: 10044 | BJ34: 17636.364 | BK34: =BJ34*BI34*1.1 -> 1.948536e+08 | BL34: =(BK34-BM34)/BM34 -> 0.1 | BM34: =BJ34*BI34*1 -> 1.7713964e+08 | BN34: 45940
A35: =IF(I35=I34,"ok","Hiện") -> Hiện | B35: =CW35 -> Thừa | C35: =CU35 -> -9.12 | D35: Thép góc V150x150x10x12000 | E35: Thép góc V150x150x10x12000 | I35: I97-VTC01-014 | J35: thép hình L | K35: L150X100X10-12000L | L35: SS400 | M35: m | N35: 19 | O35: 32.48 | P35: 616 | Q35: 36 | R35: 684 | U35: 50.88 | V35: 966.72 | W35: 0 | X35: 0 | Y35: 0 | Z35: 0 | AG35: 0 | AH35: 0 | AK35: 0 | AL35: 0 | AM35: 0 | AN35: 0 | AO35: 0 | AP35: 0 | AQ35: =Q35+S35+U35+W35+Y35+AA35+AC35+AE35+AG35+AI35+AK35+AM35+AO35 -> 86.88 | AR35: =R35+T35+V35+X35+Z35+AB35+AD35+AF35+AH35+AJ35+AL35+AN35+AP35 -> 1650.72 | AS35: REV02-IBS REV | AY35: =IF(AQ35>AU35,AQ35-AU35,"0") -> 86.88 | AZ35: =IF(AR35>AV35,AR35-AV35,"0") -> 1650.72 | BA35: 45892 | BB35: 200825/HN-IBS | BC35: Hùng Nguyên | BD35: Thép góc V150x150x10x12000 = 3 Tấm/ Cây | BE35: SS400 | BF35: 829.98 | BG35: 45889 | BH35: 36 | BI35: 829.98 | BJ35: 17636.36 | BK35: =BJ35*BI35*1.1 -> 16101609 | BL35: =(BK35-BM35)/BM35 -> 0.1 | BM35: =BJ35*BI35*1 -> 14637826 | BN35: 45892 | BO35: =SUMIF($I:$I,I35,$BH:$BH) -> 96 | BP35: =SUMIF($I:$I,I35,$BI:$BI) -> 2209.98 | CM35: =SUMIF($I:$I,I35,$CA:$CA) -> 0 | CN35: =SUMIF($I:$I,I35,$CB:$CB) -> 0 | CS35: =BO35+CM35 -> 96 | CT35: =BP35+CN35 -> 2209.98 | CU35: =AY35-CS35 -> -9.12 | CV35: =AZ35-CT35 -> -559.26 | CW35: =IF(CU35<0,"Thừa",IF(CU35=0,"Đủ","Thiếu")) -> Thừa
A36: =IF(I36=I35,"ok","Hiện") -> ok | I36: I97-VTC01-014 | J36: thép hình L | K36: L150X100X10-12000L | L36: SS400 | M36: m | BB36: 1510-2025/HĐKT/NH-IBS | BC36: Ngọc Hiếu | BD36: Thép V150*150*10*12000 = 5 Cây | BF36: 1380 | BG36: 45945 | BH36: 60 | BI36: 1380 | BJ36: 15818.18 | BK36: =BJ36*BI36*1.1 -> 24011997 | BL36: =(BK36-BM36)/BM36 -> 0.1 | BM36: =BJ36*BI36*1 -> 21829088 | BN36: 45954
A37: =IF(I37=I36,"ok","Hiện") -> Hiện | B37: =CW37 -> Thừa | C37: =CU37 -> -6 | E37: Thép góc V150x150x10x12000 | I37: I97-VTC01-015 | J37: thép hình L | K37: L150X150X10-6000L | L37: SS400 | M37: m | N37: 23 | O37: 1.828 | P37: 42 | Q37: 6 | R37: 138 | U37: 0 | V37: 0 | W37: 0 | X37: 0 | Y37: 0 | Z37: 0 | AG37: 0 | AH37: 0 | AK37: 0 | AL37: 0 | AM37: 0 | AN37: 0 | AO37: 0 | AP37: 0 | AQ37: =Q37+S37+U37+W37+Y37+AA37+AC37+AE37+AG37+AI37+AK37+AM37+AO37 -> 6 | AR37: =R37+T37+V37+X37+Z37+AB37+AD37+AF37+AH37+AJ37+AL37+AN37+AP37 -> 138 | AY37: =IF(AQ37>AU37,AQ37-AU37,"0") -> 6 | AZ37: =IF(AR37>AV37,AR37-AV37,"0") -> 138 | BA37: 45892 | BB37: 200825/HN-IBS | BC37: Hùng Nguyên | BD37: Thép góc V150x150x10x12000 = 1 Tấm/ Cây | BE37: SS400 | BF37: 276.66 | BG37: 45889 | BH37: 12 | BI37: 276.66 | BJ37: 16818.18 | BK37: =BJ37*BI37*1.1 -> 5118209.4 | BL37: =(BK37-BM37)/BM37 -> 0.1 | BM37: =BJ37*BI37*1 -> 4652917.7 | BN37: 45892 | BO37: =SUMIF($I:$I,I37,$BH:$BH) -> 12 | BP37: =SUMIF($I:$I,I37,$BI:$BI) -> 276.66 | CM37: =SUMIF($I:$I,I37,$CA:$CA) -> 0 | CN37: =SUMIF($I:$I,I37,$CB:$CB) -> 0 | CS37: =BO37+CM37 -> 12 | CT37: =BP37+CN37 -> 276.66 | CU37: =AY37-CS37 -> -6 | CV37: =AZ37-CT37 -> -138.66 | CW37: =IF(CU37<0,"Thừa",IF(CU37=0,"Đủ","Thiếu")) -> Thừa
A38: =IF(I38=I37,"ok","Hiện") -> Hiện | B38: =CW38 -> Thừa | C38: =CU38 -> -3.09 | D38: Thép góc V50x50x5x6000 | E38: Thép góc V50x50x5x6000 | I38: I97-VTC01-016 | J38: thép hình L | K38: L50X30X5-6000L | L38: SS400 | M38: m | N38: 2.9583875 | O38: 12.304 | P38: 36.4 | Q38: 18 | R38: 53.250975 | U38: 14.91 | V38: 44.109558 | W38: 0 | X38: 0 | Y38: 0 | Z38: 0 | AG38: 0 | AH38: 0 | AK38: 0 | AL38: 0 | AM38: 0 | AN38: 0 | AO38: 0 | AP38: 0 | AQ38: =Q38+S38+U38+W38+Y38+AA38+AC38+AE38+AG38+AI38+AK38+AM38+AO38 -> 32.91 | AR38: =R38+T38+V38+X38+Z38+AB38+AD38+AF38+AH38+AJ38+AL38+AN38+AP38 -> 97.360533 | AS38: REV02-IBS REV | AY38: =IF(AQ38>AU38,AQ38-AU38,"0") -> 32.91 | AZ38: =IF(AR38>AV38,AR38-AV38,"0") -> 97.360533 | BA38: 45892 | BB38: 200825/HN-IBS | BC38: Hùng Nguyên | BD38: Thép góc V50x50x5x6000 = 3 Tấm/ Cây | BE38: SS400 | BF38: 67.95 | BG38: 45889 | BH38: 18 | BI38: 67.95 | BJ38: 14181.82 | BK38: =BJ38*BI38*1.1 -> 1060020.1 | BL38: =(BK38-BM38)/BM38 -> 0.1 | BM38: =BJ38*BI38*1 -> 963654.67 | BN38: 45892 | BO38: =SUMIF($I:$I,I38,$BH:$BH) -> 36 | BP38: =SUMIF($I:$I,I38,$BI:$BI) -> 135.60112 | CM38: =SUMIF($I:$I,I38,$CA:$CA) -> 0 | CN38: =SUMIF($I:$I,I38,$CB:$CB) -> 0 | CS38: =BO38+CM38 -> 36 | CT38: =BP38+CN38 -> 135.60112 | CU38: =AY38-CS38 -> -3.09 | CV38: =AZ38-CT38 -> -38.240589 | CW38: =IF(CU38<0,"Thừa",IF(CU38=0,"Đủ","Thiếu")) -> Thừa
A39: =IF(I39=I38,"ok","Hiện") -> ok | I39: I97-VTC01-016 | J39: thép hình L | K39: L50X30X5-6000L | L39: SS400 | M39: m | BB39: 03.10.2025/APEC-IBS | BC39: APEC 2 | BD39: L50X50x5x6000mm = 18 m Cây/ Tấm SS400 | BE39: SS400 | BF39: 67.651123 | BG39: 45933 | BH39: =3*6 -> 18 | BI39: 67.651123 | BJ39: 13818.182 | BK39: =BJ39*BI39*1.1 -> 1028297.1 | BL39: =(BK39-BM39)/BM39 -> 0.1 | BM39: =BJ39*BI39*1 -> 934815.51 | BN39: 45940
A40: =IF(I40=I39,"ok","Hiện") -> Hiện | B40: =CW40 -> Thừa | C40: =CU40 -> -4.24 | E40: Thép góc V50x50x5x6000 | F40: Ngọc hiếu | I40: I97-VTC01-017 | J40: thép hình L | K40: L50X50X5-6000L | L40: SS400 | M40: m | N40: 3.7583957 | O40: 20.844 | P40: 78.34 | Q40: 24 | R40: 90.201497 | U40: 31.76 | V40: 119.36665 | W40: 0 | X40: 0 | Y40: 0 | Z40: 0 | AG40: 0 | AH40: 0 | AK40: 0 | AL40: 0 | AM40: 0 | AN40: 0 | AO40: 0 | AP40: 0 | AQ40: =Q40+S40+U40+W40+Y40+AA40+AC40+AE40+AG40+AI40+AK40+AM40+AO40 -> 55.76 | AR40: =R40+T40+V40+X40+Z40+AB40+AD40+AF40+AH40+AJ40+AL40+AN40+AP40 -> 209.56814 | AS40: REV02-IBS REV | AY40: =IF(AQ40>AU40,AQ40-AU40,"0") -> 55.76 | AZ40: =IF(AR40>AV40,AR40-AV40,"0") -> 209.56814 | BA40: 45892 | BB40: 200825/HN-IBS | BC40: Hùng Nguyên | BD40: Thép góc V50x50x5x6000 = 4 Tấm/ Cây | BE40: SS400 | BF40: 90.6 | BG40: 45889 | BH40: 24 | BI40: 90.6 | BJ40: 14181.82 | BK40: =BJ40*BI40*1.1 -> 1413360.2 | BL40: =(BK40-BM40)/BM40 -> 0.1 | BM40: =BJ40*BI40*1 -> 1284872.9 | BN40: 45892 | BO40: =SUMIF($I:$I,I40,$BH:$BH) -> 60 | BP40: =SUMIF($I:$I,I40,$BI:$BI) -> 225.8015 | CM40: =SUMIF($I:$I,I40,$CA:$CA) -> 0 | CN40: =SUMIF($I:$I,I40,$CB:$CB) -> 0 | CS40: =BO40+CM40 -> 60 | CT40: =BP40+CN40 -> 225.8015 | CU40: =AY40-CS40 -> -4.24 | CV40: =AZ40-CT40 -> -16.233353 | CW40: =IF(CU40<0,"Thừa",IF(CU40=0,"Đủ","Thiếu")) -> Thừa
A41: =IF(I41=I40,"ok","Hiện") -> ok | I41: I97-VTC01-017 | J41: thép hình L | K41: L50X50X5-6000L | L41: SS400 | M41: m | BB41: 1912-2025/HĐKT/NH-IBS | BC41: Ngọc Hiếu | BD41: Thép V50*50*5*6000 ( 2 cây) | BE41: SS400 | BF41: 45 | BG41: 46010 | BH41: 12 | BI41: 45 | BJ41: 13909.09 | BK41: =BJ41*BI41*(1+BL41) -> 688499.96 | BL41: 0.1 | BM41: =BJ41*BI41 -> 625909.05 | BN41: 46029
A42: =IF(I42=I41,"ok","Hiện") -> ok | I42: I97-VTC01-017 | J42: thép hình L | K42: L50X50X5-6000L | L42: SS400 | M42: m | BB42: 03.10.2025/APEC-IBS | BC42: APEC 2 | BD42: L50X50X5x6000mm = 24 m Cây/ Tấm SS400 | BE42: SS400 | BF42: 90.201497 | BG42: 45933 | BH42: =4*6 -> 24 | BI42: 90.201497 | BJ42: 13818.182 | BK42: =BJ42*BI42*1.1 -> 1371062.8 | BL42: =(BK42-BM42)/BM42 -> 0.1 | BM42: =BJ42*BI42*1 -> 1246420.7 | BN42: 45940
A43: =IF(I43=I42,"ok","Hiện") -> Hiện | B43: =CW43 -> Đủ | C43: =CU43 -> 0 | D43: Thép góc V50x50x5x6000 | I43: I97-VTC01-018 | J43: thép hình L | K43: L60X40X5-6000L | L43: SS400 | M43: m | N43: 3.7727273 | O43: 1.76 | P43: 6.64 | Q43: 6 | R43: 22.636364 | U43: 0 | V43: 0 | W43: 0 | X43: 0 | Y43: 0 | Z43: 0 | AG43: 0 | AH43: 0 | AK43: 0 | AL43: 0 | AM43: 0 | AN43: 0 | AO43: 0 | AP43: 0 | AQ43: =Q43+S43+U43+W43+Y43+AA43+AC43+AE43+AG43+AI43+AK43+AM43+AO43 -> 6 | AR43: =R43+T43+V43+X43+Z43+AB43+AD43+AF43+AH43+AJ43+AL43+AN43+AP43 -> 22.636364 | AY43: =IF(AQ43>AU43,AQ43-AU43,"0") -> 6 | AZ43: =IF(AR43>AV43,AR43-AV43,"0") -> 22.636364 | BA43: 45892 | BB43: 200825/HN-IBS | BC43: Hùng Nguyên | BD43: Thép góc V63x63x5x6000 = 1 tờ SS400 | BE43: SS400 | BF43: 28.85 | BG43: 45889 | BH43: 6 | BI43: 28.85 | BJ43: 14181.82 | BK43: =BJ43*BI43*1.1 -> 450060.06 | BL43: =(BK43-BM43)/BM43 -> 0.1 | BM43: =BJ43*BI43*1 -> 409145.51 | BN43: 45892 | BO43: =SUMIF($I:$I,I43,$BH:$BH) -> 6 | BP43: =SUMIF($I:$I,I43,$BI:$BI) -> 28.85 | CM43: =SUMIF($I:$I,I43,$CA:$CA) -> 0 | CN43: =SUMIF($I:$I,I43,$CB:$CB) -> 0 | CS43: =BO43+CM43 -> 6 | CT43: =BP43+CN43 -> 28.85 | CU43: =AY43-CS43 -> 0 | CV43: =AZ43-CT43 -> -6.2136364 | CW43: =IF(CU43<0,"Thừa",IF(CU43=0,"Đủ","Thiếu")) -> Đủ
A44: =IF(I44=I43,"ok","Hiện") -> Hiện | B44: =CW44 -> Thừa | C44: =CU44 -> -6.02 | D44: Thép góc V63x63x8x6000 | I44: I97-VTC01-019 | J44: thép hình L | K44: L65X65X8-6000L | L44: SS400 | M44: m | N44: 7.66 | O44: 29.152 | P44: 219.6 | Q44: 36 | R44: 275.76 | U44: 41.98 | V44: 321.5668 | W44: 0 | X44: 0 | Y44: 0 | Z44: 0 | AG44: 0 | AH44: 0 | AK44: 0 | AL44: 0 | AM44: 0 | AN44: 0 | AO44: 0 | AP44: 0 | AQ44: =Q44+S44+U44+W44+Y44+AA44+AC44+AE44+AG44+AI44+AK44+AM44+AO44 -> 77.98 | AR44: =R44+T44+V44+X44+Z44+AB44+AD44+AF44+AH44+AJ44+AL44+AN44+AP44 -> 597.3268 | AS44: REV02-IBS REV | AY44: =IF(AQ44>AU44,AQ44-AU44,"0") -> 77.98 | AZ44: =IF(AR44>AV44,AR44-AV44,"0") -> 597.3268 | BA44: 45892 | BB44: 290825/2025/NH-IBS | BC44: Ngọc Hiếu | BD44: Thép V63*63*8*12000 | BE44: SS400 | BF44: 269 | BG44: 45898 | BH44: =3*12 -> 36 | BI44: 269 | BJ44: 15454.55 | BK44: =BJ44*BI44*1.1 -> 4573001.3 | BL44: =(BK44-BM44)/BM44 -> 0.1 | BM44: =BJ44*BI44*1 -> 4157273.9 | BN44: 45898 | BO44: =SUMIF($I:$I,I44,$BH:$BH) -> 84 | BP44: =SUMIF($I:$I,I44,$BI:$BI) -> 628 | CM44: =SUMIF($I:$I,I44,$CA:$CA) -> 0 | CN44: =SUMIF($I:$I,I44,$CB:$CB) -> 0 | CS44: =BO44+CM44 -> 84 | CT44: =BP44+CN44 -> 628 | CU44: =AY44-CS44 -> -6.02 | CV44: =AZ44-CT44 -> -30.6732 | CW44: =IF(CU44<0,"Thừa",IF(CU44=0,"Đủ","Thiếu")) -> Thừa
A45: =IF(I45=I44,"ok","Hiện") -> ok | I45: I97-VTC01-019 | J45: thép hình L | K45: L65X65X8-6000L | L45: SS400 | M45: m | BB45: 1510-2025/HĐKT/NH-IBS | BC45: Ngọc Hiếu | BD45: Thép V63*63*8*12000 = 4 Cây | BF45: 359 | BG45: 45945 | BH45: 48 | BI45: 359 | BJ45: 15454.55 | BK45: =BJ45*BI45*1.1 -> 6103001.8 | BL45: =(BK45-BM45)/BM45 -> 0.1 | BM45: =BJ45*BI45*1 -> 5548183.5 | BN45: 45954
A46: =IF(I46=I45,"ok","Hiện") -> Hiện | B46: =CW46 -> Thừa | C46: =CU46 -> -1.77 | E46: Thép góc V70x70x7x6000 | I46: I97-VTC01-020 | J46: thép hình L | K46: L70X70X7-6000L | L46: SS400 | M46: m | N46: 7.3676957 | O46: 21.768 | P46: 160.38 | Q46: 24 | R46: 176.8247 | U46: 34.23 | V46: 252.19622 | W46: 0 | X46: 0 | Y46: 0 | Z46: 0 | AG46: 0 | AH46: 0 | AK46: 0 | AL46: 0 | AM46: 0 | AN46: 0 | AO46: 0 | AP46: 0 | AQ46: =Q46+S46+U46+W46+Y46+AA46+AC46+AE46+AG46+AI46+AK46+AM46+AO46 -> 58.23 | AR46: =R46+T46+V46+X46+Z46+AB46+AD46+AF46+AH46+AJ46+AL46+AN46+AP46 -> 429.02092 | AS46: REV02-IBS REV | AY46: =IF(AQ46>AU46,AQ46-AU46,"0") -> 58.23 | AZ46: =IF(AR46>AV46,AR46-AV46,"0") -> 429.02092 | BA46: 45892 | BB46: 200825/HN-IBS | BC46: Hùng Nguyên | BD46: Thép góc V70x70x7x6000 = 4 Tấm/ Cây | BE46: SS400 | BF46: 177.6 | BG46: 45889 | BH46: 24 | BI46: 177.6 | BJ46: 14181.82 | BK46: =BJ46*BI46*1.1 -> 2770560.4 | BL46: =(BK46-BM46)/BM46 -> 0.1 | BM46: =BJ46*BI46*1 -> 2518691.2 | BN46: 45892 | BO46: =SUMIF($I:$I,I46,$BH:$BH) -> 60 | BP46: =SUMIF($I:$I,I46,$BI:$BI) -> 443.6 | CM46: =SUMIF($I:$I,I46,$CA:$CA) -> 0 | CN46: =SUMIF($I:$I,I46,$CB:$CB) -> 0 | CS46: =BO46+CM46 -> 60 | CT46: =BP46+CN46 -> 443.6 | CU46: =AY46-CS46 -> -1.77 | CV46: =AZ46-CT46 -> -14.579079 | CW46: =IF(CU46<0,"Thừa",IF(CU46=0,"Đủ","Thiếu")) -> Thừa
A47: =IF(I47=I46,"ok","Hiện") -> ok | I47: I97-VTC01-020 | J47: thép hình L | K47: L70X70X7-6000L | L47: SS400 | M47: m | BB47: 1510-2025/HĐKT/NH-IBS | BC47: Ngọc Hiếu | BD47: Thép V70*70*7*6000 = 6 Cây | BF47: 266 | BG47: 45945 | BH47: 36 | BI47: 266 | BJ47: 13909.09 | BK47: =BJ47*BI47*1.1 -> 4069799.7 | BL47: =(BK47-BM47)/BM47 -> 0.1 | BM47: =BJ47*BI47*1 -> 3699817.9 | BN47: 45954
A48: =IF(I48=I47,"ok","Hiện") -> Hiện | B48: =CW48 -> Đủ | C48: =CU48 -> 0 | D48: Thép góc V75x75x7x6000 | E48: Thép góc V75x75x7x6000 | F48: Ngọc hiếu/ hàng đã về | I48: I97-VTC01-021 | J48: thép hình L | K48: L75X50X7-6000L | L48: SS400 | M48: m | N48: 6.5090262 | O48: 15.732 | P48: 102.4 | Q48: 18 | R48: 117.16247 | U48: 24.08 | V48: 156.73735 | W48: 0 | X48: 0 | Y48: 0 | Z48: 0 | AG48: 0 | AH48: 0 | AK48: 0 | AL48: 0 | AM48: 0 | AN48: 0 | AO48: 11.92 | AP48: 77.587592 | AQ48: =Q48+S48+U48+W48+Y48+AA48+AC48+AE48+AG48+AI48+AK48+AM48+AO48 -> 54 | AR48: =R48+T48+V48+X48+Z48+AB48+AD48+AF48+AH48+AJ48+AL48+AN48+AP48 -> 351.48741 | AS48: REV12-IBS REV | AY48: =IF(AQ48>AU48,AQ48-AU48,"0") -> 54 | AZ48: =IF(AR48>AV48,AR48-AV48,"0") -> 351.48741 | BA48: 45892 | BB48: 200825/HN-IBS | BC48: Hùng Nguyên | BD48: Thép góc V75x75x7x6000 = 3 Tấm/ Cây | BE48: SS400 | BF48: 143.22 | BG48: 45889 | BH48: 18 | BI48: 143.22 | BJ48: 14181.82 | BK48: =BJ48*BI48*1.1 -> 2234232.3 | BL48: =(BK48-BM48)/BM48 -> 0.1 | BM48: =BJ48*BI48*1 -> 2031120.3 | BN48: 45892 | BO48: =SUMIF($I:$I,I48,$BH:$BH) -> 54 | BP48: =SUMIF($I:$I,I48,$BI:$BI) -> 430.18 | CM48: =SUMIF($I:$I,I48,$CA:$CA) -> 0 | CN48: =SUMIF($I:$I,I48,$CB:$CB) -> 0 | CS48: =BO48+CM48 -> 54 | CT48: =BP48+CN48 -> 430.18 | CU48: =AY48-CS48 -> 0 | CV48: =AZ48-CT48 -> -78.692586 | CW48: =IF(CU48<0,"Thừa",IF(CU48=0,"Đủ","Thiếu")) -> Đủ
A49: =IF(I49=I48,"ok","Hiện") -> ok | I49: I97-VTC01-021 | J49: thép hình L | K49: L75X50X7-6000L | L49: SS400 | M49: m | BB49: Báo giá ngày 12/2/2026 | BC49: Ngọc Hiếu | BD49: Thép góc V75x75x7x6000 = 2 Tấm/ Cây | BE49: SS400 | BF49: 96 | BG49: 46065 | BH49: 12 | BI49: 96 | BJ49: 14000 | BK49: =BJ49*BI49*1.1 -> 1478400 | BL49: =(BK49-BM49)/BM49 -> 0.1 | BM49: =BJ49*BI49*1 -> 1344000 | BN49: 46065
A50: =IF(I50=I49,"ok","Hiện") -> ok | I50: I97-VTC01-021 | J50: thép hình L | K50: L75X50X7-6000L | L50: SS400 | BB50: Báo giá ngày 16/10/2025 | BC50: Hùng Nguyên | BD50: Thép góc V75x75x7x6000 = 4 Tấm/ Cây | BF50: 190.96 | BG50: 45946 | BH50: 24 | BI50: 190.96 | BJ50: 14181.82 | BK50: =BJ50*BI50*1.1 -> 2978976.4 | BL50: =(BK50-BM50)/BM50 -> 0.1 | BM50: =BJ50*BI50*1 -> 2708160.3 | BN50: 45947
A51: =IF(I51=I50,"ok","Hiện") -> Hiện | B51: =CW51 -> Đủ | C51: =CU51 -> 0 | I51: I97-VTC01-022 | J51: thép hình L | K51: L90X90X10-2000L | L51: SS400 | M51: m | N51: 13.3 | O51: 0.36 | P51: 4.8 | Q51: 2 | R51: 26.6 | U51: 0 | V51: 0 | W51: 0 | X51: 0 | Y51: 0 | Z51: 0 | AG51: 0 | AH51: 0 | AK51: 0 | AL51: 0 | AM51: 0 | AN51: 0 | AO51: 0 | AP51: 0 | AQ51: =Q51+S51+U51+W51+Y51+AA51+AC51+AE51+AG51+AI51+AK51+AM51+AO51 -> 2 | AR51: =R51+T51+V51+X51+Z51+AB51+AD51+AF51+AH51+AJ51+AL51+AN51+AP51 -> 26.6 | AU51: 2 | AV51: 26.6 | AX51: hàng tồn | AY51: =IF(AQ51>AU51,AQ51-AU51,"0") -> 0 | AZ51: =IF(AR51>AV51,AR51-AV51,"0") -> 0 | BA51: 45892 | BO51: =SUMIF($I:$I,I51,$BH:$BH) -> 0 | BP51: =SUMIF($I:$I,I51,$BI:$BI) -> 0 | CM51: =SUMIF($I:$I,I51,$CA:$CA) -> 0 | CN51: =SUMIF($I:$I,I51,$CB:$CB) -> 0 | CS51: =BO51+CM51 -> 0 | CT51: =BP51+CN51 -> 0 | CU51: =AY51-CS51 -> 0 | CV51: =AZ51-CT51 -> 0 | CW51: =IF(CU51<0,"Thừa",IF(CU51=0,"Đủ","Thiếu")) -> Đủ
A52: =IF(I52=I51,"ok","Hiện") -> Hiện | B52: =CW52 -> Đủ | C52: =CU52 -> 0 | E52: Thép tròn trơn phi 12x6000 | F52: Ngọc hiếu | I52: I97-VTC01-023 | J52: thép tròn | K52: RB12-6000L | L52: SS400 | M52: m | N52: 0.88206145 | O52: 16.144 | P52: 14.24 | Q52: 18 | R52: 15.877106 | U52: 30 | V52: 26.461843 | W52: 0 | X52: 0 | Y52: 0 | Z52: 0 | AG52: 0 | AH52: 0 | AK52: 0 | AL52: 0 | AM52: 0 | AN52: 0 | AO52: 0 | AP52: 0 | AQ52: =Q52+S52+U52+W52+Y52+AA52+AC52+AE52+AG52+AI52+AK52+AM52+AO52 -> 48 | AR52: =R52+T52+V52+X52+Z52+AB52+AD52+AF52+AH52+AJ52+AL52+AN52+AP52 -> 42.338949 | AS52: REV02-IBS REV | AY52: =IF(AQ52>AU52,AQ52-AU52,"0") -> 48 | AZ52: =IF(AR52>AV52,AR52-AV52,"0") -> 42.338949 | BA52: 45892 | BB52: 200825/HN-IBS | BC52: Hùng Nguyên | BD52: Thép tròn trơn phi 12x6000 = 3 Tấm/ Cây | BE52: SS400/CB240 | BF52: 15.98 | BG52: 45889 | BH52: 18 | BI52: 15.98 | BJ52: 15181.82 | BK52: =BJ52*BI52*1.1 -> 266866.03 | BL52: =(BK52-BM52)/BM52 -> 0.1 | BM52: =BJ52*BI52*1 -> 242605.48 | BN52: 45892 | BO52: =SUMIF($I:$I,I52,$BH:$BH) -> 48 | BP52: =SUMIF($I:$I,I52,$BI:$BI) -> 42.29 | CM52: =SUMIF($I:$I,I52,$CA:$CA) -> 0 | CN52: =SUMIF($I:$I,I52,$CB:$CB) -> 0 | CS52: =BO52+CM52 -> 48 | CT52: =BP52+CN52 -> 42.29 | CU52: =AY52-CS52 -> 0 | CV52: =AZ52-CT52 -> 0.048949455 | CW52: =IF(CU52<0,"Thừa",IF(CU52=0,"Đủ","Thiếu")) -> Đủ
A53: =IF(I53=I52,"ok","Hiện") -> ok | I53: I97-VTC01-023 | J53: thép tròn | K53: RB12-6000L | L53: SS400 | M53: m | BB53: 1912-2025/HĐKT/NH-IBS | BC53: Ngọc Hiếu | BD53: Thép tròn D12*6000 ( 1 cây) | BE53: SS400 | BF53: 5 | BG53: 46010 | BH53: 6 | BI53: 5 | BJ53: 14181.82 | BK53: =BJ53*BI53*(1+BL53) -> 78000.01 | BL53: 0.1 | BM53: =BJ53*BI53 -> 70909.1 | BN53: 46029
A54: =IF(I54=I53,"ok","Hiện") -> ok | I54: I97-VTC01-023 | J54: thép tròn | K54: RB12-6000L | L54: SS400 | BB54: I97-1010/HN-IBS | BC54: Hùng Nguyên | BD54: Thép tròn trơn phi 12x6000 = 4 CâySS400 | BF54: 21.31 | BG54: 45940 | BH54: 24 | BI54: 21.31 | BJ54: 15727.27 | BK54: =BJ54*BI54*1.1 -> 368662.94 | BL54: =(BK54-BM54)/BM54 -> 0.1 | BM54: =BJ54*BI54*1 -> 335148.12 | BN54: 45947
A55: =IF(I55=I54,"ok","Hiện") -> Hiện | B55: =CONCATENATE(CW55," Hàng tồn") -> Thiếu Hàng tồn | C55: =CU55 -> 1 | E55: Thép tròn trơn phi 20x6000 | I55: I97-VTC01-024 | J55: thép tròn | K55: RB20-6000L | L55: SS400 | M55: m | N55: 2.47 | O55: 7.796 | P55: 19.4 | Q55: 12 | R55: 29.64 | U55: 13 | V55: 32.11 | W55: 0 | X55: 0 | Y55: 0 | Z55: 0 | AG55: 0 | AH55: 0 | AK55: 0 | AL55: 0 | AM55: 0 | AN55: 0 | AO55: 0 | AP55: 0 | AQ55: =Q55+S55+U55+W55+Y55+AA55+AC55+AE55+AG55+AI55+AK55+AM55+AO55 -> 25 | AR55: =R55+T55+V55+X55+Z55+AB55+AD55+AF55+AH55+AJ55+AL55+AN55+AP55 -> 61.75 | AS55: REV02-IBS REV | AY55: =IF(AQ55>AU55,AQ55-AU55,"0") -> 25 | AZ55: =IF(AR55>AV55,AR55-AV55,"0") -> 61.75 | BA55: 45892 | BB55: 200825/HN-IBS | BC55: Hùng Nguyên | BD55: Thép tròn trơn phi 20x6000 = 2 Tấm/ Cây | BE55: SS400/CB240 | BF55: 29.59 | BG55: 45889 | BH55: 12 | BI55: 29.59 | BJ55: 15181.82 | BK55: =BJ55*BI55*1.1 -> 494153.06 | BL55: =(BK55-BM55)/BM55 -> 0.1 | BM55: =BJ55*BI55*1 -> 449230.05 | BN55: 45892 | BO55: =SUMIF($I:$I,I55,$BH:$BH) -> 24 | BP55: =SUMIF($I:$I,I55,$BI:$BI) -> 59.18 | CM55: =SUMIF($I:$I,I55,$CA:$CA) -> 0 | CN55: =SUMIF($I:$I,I55,$CB:$CB) -> 0 | CS55: =BO55+CM55 -> 24 | CT55: =BP55+CN55 -> 59.18 | CU55: =AY55-CS55 -> 1 | CV55: =AZ55-CT55 -> 2.57 | CW55: =IF(CU55<0,"Thừa",IF(CU55=0,"Đủ","Thiếu")) -> Thiếu
A56: =IF(I56=I55,"ok","Hiện") -> ok | I56: I97-VTC01-024 | J56: thép tròn | K56: RB20-6000L | L56: SS400 | M56: m | BB56: I97-1010/HN-IBS | BC56: Hùng Nguyên | BD56: Thép tròn trơn phi 20x6000 = 2 CâySS400 | BF56: 29.59 | BG56: 45940 | BH56: 12 | BI56: 29.59 | BJ56: 15727.27 | BK56: =BJ56*BI56*1.1 -> 511906.91 | BL56: =(BK56-BM56)/BM56 -> 0.1 | BM56: =BJ56*BI56*1 -> 465369.92 | BN56: 45947
A57: =IF(I57=I56,"ok","Hiện") -> Hiện | B57: =CW57 -> Đủ | C57: =CU57 -> 0 | I57: I97-VTC01-025 | J57: tôn tấm | K57: PL1X1250X2500 | L57: SS400 | M57: m2 | N57: 7.85 | O57: 3.8369427 | P57: 30.12 | Q57: 6.25 | R57: 49.0625 | U57: 6.25 | V57: 49.0625 | W57: 0 | X57: 0 | Y57: 0 | Z57: 0 | AG57: 0 | AH57: 0 | AK57: 0 | AL57: 0 | AM57: 0 | AN57: 0 | AO57: 0 | AP57: 0 | AQ57: =Q57+S57+U57+W57+Y57+AA57+AC57+AE57+AG57+AI57+AK57+AM57+AO57 -> 12.5 | AR57: =R57+T57+V57+X57+Z57+AB57+AD57+AF57+AH57+AJ57+AL57+AN57+AP57 -> 98.125 | AS57: REV02-IBS REV | AY57: =IF(AQ57>AU57,AQ57-AU57,"0") -> 12.5 | AZ57: =IF(AR57>AV57,AR57-AV57,"0") -> 98.125 | BA57: 45892 | BB57: 22.08.2025/APEC-IBS | BC57: APEC | BD57: Thép tấm 1x1250x2500mm | BE57: SPHC/ | BF57: 49.06 | BG57: 45891 | BH57: =2*1.25*2.5 -> 6.25 | BI57: 49.06 | BJ57: 16363.64 | BK57: =BJ57*BI57*1.1 -> 883080.2 | BL57: =(BK57-BM57)/BM57 -> 0.1 | BM57: =BJ57*BI57*1 -> 802800.18 | BN57: 45897 | BO57: =SUMIF($I:$I,I57,$BH:$BH) -> 12.5 | BP57: =SUMIF($I:$I,I57,$BI:$BI) -> 98.1225 | CM57: =SUMIF($I:$I,I57,$CA:$CA) -> 0 | CN57: =SUMIF($I:$I,I57,$CB:$CB) -> 0 | CS57: =BO57+CM57 -> 12.5 | CT57: =BP57+CN57 -> 98.1225 | CU57: =AY57-CS57 -> 0 | CV57: =AZ57-CT57 -> 0.0025 | CW57: =IF(CU57<0,"Thừa",IF(CU57=0,"Đủ","Thiếu")) -> Đủ
A58: =IF(I58=I57,"ok","Hiện") -> ok | I58: I97-VTC01-025 | J58: tôn tấm | K58: PL1X1250X2500 | L58: SS400 | M58: m2 | BB58: 03.10.2025/APEC-IBS | BC58: APEC 2 | BD58: PL1X1250X2500mm = 6.25 m2 Cây/ Tấm SS400 | BE58: Q235B | BF58: 49.0625 | BG58: 45933 | BH58: =1.25*2.5*2 -> 6.25 | BI58: 49.0625 | BJ58: 16818.182 | BK58: =BJ58*BI58*1.1 -> 907656.25 | BL58: =(BK58-BM58)/BM58 -> 0.1 | BM58: =BJ58*BI58*1 -> 825142.05 | BN58: 45940
A59: =IF(I59=I58,"ok","Hiện") -> Hiện | B59: =CW59 -> Đủ | C59: =CU59 -> 0 | I59: I97-VTC01-026 | J59: tôn tấm | K59: PL1.5X1250X2500 | L59: SS400 | M59: m2 | N59: 11.775 | O59: 0.62845011 | P59: 7.4 | Q59: 3.125 | R59: 36.796875 | U59: 0 | V59: 0 | W59: 0 | X59: 0 | Y59: 0 | Z59: 0 | AG59: 0 | AH59: 0 | AK59: 0 | AL59: 0 | AM59: 0 | AN59: 0 | AO59: 0 | AP59: 0 | AQ59: =Q59+S59+U59+W59+Y59+AA59+AC59+AE59+AG59+AI59+AK59+AM59+AO59 -> 3.125 | AR59: =R59+T59+V59+X59+Z59+AB59+AD59+AF59+AH59+AJ59+AL59+AN59+AP59 -> 36.796875 | AY59: =IF(AQ59>AU59,AQ59-AU59,"0") -> 3.125 | AZ59: =IF(AR59>AV59,AR59-AV59,"0") -> 36.796875 | BA59: 45892 | BB59: 22.08.2025/APEC-IBS | BC59: APEC | BD59: Thép tấm 1.5x1250x2500mm | BE59: Q235B/SS400 | BF59: 36.8 | BG59: 45891 | BH59: =1*1.25*2.5 -> 3.125 | BI59: 36.8 | BJ59: 16363.64 | BK59: =BJ59*BI59*1.1 -> 662400.15 | BL59: =(BK59-BM59)/BM59 -> 0.1 | BM59: =BJ59*BI59*1 -> 602181.95 | BN59: 45897 | BO59: =SUMIF($I:$I,I59,$BH:$BH) -> 3.125 | BP59: =SUMIF($I:$I,I59,$BI:$BI) -> 36.8 | CM59: =SUMIF($I:$I,I59,$CA:$CA) -> 0 | CN59: =SUMIF($I:$I,I59,$CB:$CB) -> 0 | CS59: =BO59+CM59 -> 3.125 | CT59: =BP59+CN59 -> 36.8 | CU59: =AY59-CS59 -> 0 | CV59: =AZ59-CT59 -> -0.003125 | CW59: =IF(CU59<0,"Thừa",IF(CU59=0,"Đủ","Thiếu")) -> Đủ
A60: =IF(I60=I59,"ok","Hiện") -> Hiện | B60: =CW60 -> Thừa | C60: =CU60 -> -9.375 | D60: bàn giao 3 tờ sang cho 102 | I60: I97-VTC01-027 | J60: tôn tấm | K60: PL2X1250X2500 | L60: SS400 | M60: m2 | N60: 15.7 | O60: 2.0025478 | P60: 31.44 | Q60: 3.125 | R60: 49.0625 | U60: 3.125 | V60: 49.0625 | W60: 0 | X60: 0 | Y60: 0 | Z60: 0 | AG60: 0 | AH60: 0 | AK60: 0 | AL60: 0 | AM60: 0 | AN60: 0 | AO60: 0 | AP60: 0 | AQ60: =Q60+S60+U60+W60+Y60+AA60+AC60+AE60+AG60+AI60+AK60+AM60+AO60 -> 6.25 | AR60: =R60+T60+V60+X60+Z60+AB60+AD60+AF60+AH60+AJ60+AL60+AN60+AP60 -> 98.125 | AS60: REV02-IBS REV | AY60: =IF(AQ60>AU60,AQ60-AU60,"0") -> 6.25 | AZ60: =IF(AR60>AV60,AR60-AV60,"0") -> 98.125 | BA60: 45892 | BB60: 22.08.2025/APEC-IBS | BC60: APEC | BD60: Thép tấm 2x1250x2500mm | BE60: SPHC/ | BF60: 49.06 | BG60: 45891 | BH60: =1*1.25*2.5 -> 3.125 | BI60: 49.06 | BJ60: 15272.73 | BK60: =BJ60*BI60*1.1 -> 824208.15 | BL60: =(BK60-BM60)/BM60 -> 0.1 | BM60: =BJ60*BI60*1 -> 749280.13 | BN60: 45897 | BO60: =SUMIF($I:$I,I60,$BH:$BH) -> 15.625 | BP60: =SUMIF($I:$I,I60,$BI:$BI) -> 245.31 | CM60: =SUMIF($I:$I,I60,$CA:$CA) -> 0 | CN60: =SUMIF($I:$I,I60,$CB:$CB) -> 0 | CS60: =BO60+CM60 -> 15.625 | CT60: =BP60+CN60 -> 245.31 | CU60: =AY60-CS60 -> -9.375 | CV60: =AZ60-CT60 -> -147.185 | CW60: =IF(CU60<0,"Thừa",IF(CU60=0,"Đủ","Thiếu")) -> Thừa
A61: =IF(I61=I60,"ok","Hiện") -> ok | I61: I97-VTC01-027 | J61: tôn tấm | K61: PL2X1250X2500 | L61: SS400 | M61: m2 | BB61: 03.10.2025/APEC-IBS | BC61: APEC 2 | BD61: PL2X1250X2500mm = 12.5 m2 Cây/ Tấm SS400 | BE61: SS400 | BF61: 196.25 | BG61: 45933 | BH61: =1.25*2.5*4 -> 12.5 | BI61: 196.25 | BJ61: 15909.091 | BK61: =BJ61*BI61*1.1 -> 3434375 | BL61: =(BK61-BM61)/BM61 -> 0.1 | BM61: =BJ61*BI61*1 -> 3122159.1 | BN61: 45940
A62: =IF(I62=I61,"ok","Hiện") -> Hiện | B62: =CONCATENATE(CW62," Thiếu ít") -> Thiếu Thiếu ít | C62: =CU62 -> 2.12 | I62: I97-VTC01-028 | J62: tôn tấm | K62: PL3X1500X6000 | L62: SS400 | M62: m2 | N62: 23.55 | O62: 5.044586 | P62: 118.8 | Q62: 6.25 | R62: 147.1875 | U62: 97.87 | V62: 2304.8385 | W62: 0 | X62: 0 | Y62: 0 | Z62: 0 | AG62: 0 | AH62: 0 | AK62: 0 | AL62: 0 | AM62: 0 | AN62: 0 | AO62: 0 | AP62: 0 | AQ62: =Q62+S62+U62+W62+Y62+AA62+AC62+AE62+AG62+AI62+AK62+AM62+AO62 -> 104.12 | AR62: =R62+T62+V62+X62+Z62+AB62+AD62+AF62+AH62+AJ62+AL62+AN62+AP62 -> 2452.026 | AS62: REV02-IBS REV | AY62: =IF(AQ62>AU62,AQ62-AU62,"0") -> 104.12 | AZ62: =IF(AR62>AV62,AR62-AV62,"0") -> 2452.026 | BA62: 45892 | BB62: 22.08.2025/APEC-IBS | BC62: APEC | BD62: Thép tấm 3x2000x6000mm | BE62: Q235B/SS400 | BF62: 282.6 | BG62: 45891 | BH62: 12 | BI62: 282.6 | BJ62: 13090.91 | BK62: =BJ62*BI62*1.1 -> 4069440.3 | BL62: =(BK62-BM62)/BM62 -> 0.1 | BM62: =BJ62*BI62*1 -> 3699491.2 | BN62: 45897 | BO62: =SUMIF($I:$I,I62,$BH:$BH) -> 102 | BP62: =SUMIF($I:$I,I62,$BI:$BI) -> 2402.1 | CM62: =SUMIF($I:$I,I62,$CA:$CA) -> 0 | CN62: =SUMIF($I:$I,I62,$CB:$CB) -> 0 | CS62: =BO62+CM62 -> 102 | CT62: =BP62+CN62 -> 2402.1 | CU62: =AY62-CS62 -> 2.12 | CV62: =AZ62-CT62 -> 49.926 | CW62: =IF(CU62<0,"Thừa",IF(CU62=0,"Đủ","Thiếu")) -> Thiếu
A63: =IF(I63=I62,"ok","Hiện") -> ok | I63: I97-VTC01-028 | J63: tôn tấm | K63: PL3X1500X6000 | L63: SS400 | M63: m2 | BB63: I97-1912/HN-IBS | BC63: Hùng Nguyên | BD63: Thép tấm 3x1500x6000 | BE63: SS400 | BF63: 1059.75 | BG63: 46010 | BH63: 45 | BI63: 1059.75 | BJ63: 13954.55 | BK63: =BJ63*BI63*(1+BL63) -> 16267168 | BL63: 0.1 | BM63: =BJ63*BI63 -> 14788334 | BN63: 46018
A64: =IF(I64=I63,"ok","Hiện") -> ok | I64: I97-VTC01-028 | J64: tôn tấm | K64: PL3X1500X6000 | L64: SS400 | M64: m2 | BB64: I97-1010/HN-IBS | BC64: Hùng Nguyên | BD64: Thép tấm 3x1500x6000 = 5 CâySS400 | BF64: 1059.75 | BG64: 45940 | BH64: 45 | BI64: 1059.75 | BJ64: 14181.82 | BK64: =BJ64*BI64*1.1 -> 16532102 | BL64: =(BK64-BM64)/BM64 -> 0.1 | BM64: =BJ64*BI64*1 -> 15029184 | BN64: 45947
A65: =IF(I65=I64,"ok","Hiện") -> Hiện | B65: =CW65 -> Thừa | C65: =CU65 -> -3 | D65: Khổ 2m | I65: I97-VTC01-029 | J65: tôn tấm | K65: PL4X1500X6000 | L65: SS400 | M65: m2 | N65: 31.4 | O65: 33.649682 | P65: 1056.6 | Q65: 45 | R65: 1413 | U65: 0 | V65: 0 | W65: 0 | X65: 0 | Y65: 0 | Z65: 0 | AG65: 0 | AH65: 0 | AK65: 0 | AL65: 0 | AM65: 0 | AN65: 0 | AO65: 0 | AP65: 0 | AQ65: =Q65+S65+U65+W65+Y65+AA65+AC65+AE65+AG65+AI65+AK65+AM65+AO65 -> 45 | AR65: =R65+T65+V65+X65+Z65+AB65+AD65+AF65+AH65+AJ65+AL65+AN65+AP65 -> 1413 | AY65: =IF(AQ65>AU65,AQ65-AU65,"0") -> 45 | AZ65: =IF(AR65>AV65,AR65-AV65,"0") -> 1413 | BA65: 45892 | BB65: 200825/HN-IBS | BC65: Hùng Nguyên | BD65: PL4x2000x12000 = 2 tờ SS400 | BE65: Q235B/SS400 | BF65: 1507.2 | BG65: 45889 | BH65: 48 | BI65: 1507.2 | BJ65: 13090.91 | BK65: =BJ65*BI65*1.1 -> 21703682 | BL65: =(BK65-BM65)/BM65 -> 0.1 | BM65: =BJ65*BI65*1 -> 19730620 | BN65: 45892 | BO65: =SUMIF($I:$I,I65,$BH:$BH) -> 48 | BP65: =SUMIF($I:$I,I65,$BI:$BI) -> 1507.2 | CM65: =SUMIF($I:$I,I65,$CA:$CA) -> 0 | CN65: =SUMIF($I:$I,I65,$CB:$CB) -> 0 | CS65: =BO65+CM65 -> 48 | CT65: =BP65+CN65 -> 1507.2 | CU65: =AY65-CS65 -> -3 | CV65: =AZ65-CT65 -> -94.2 | CW65: =IF(CU65<0,"Thừa",IF(CU65=0,"Đủ","Thiếu")) -> Thừa
A66: =IF(I66=I65,"ok","Hiện") -> Hiện | B66: =CW66 -> Thừa | C66: =CU66 -> -2.94 | D66: Khổ 1,5 | F66: Hùng Nguyên | I66: I97-VTC01-030 | J66: tôn tấm | K66: PL5X1500X6000 | L66: SS400 | M66: m2 | N66: 39.25 | O66: 6.1849682 | P66: 242.76 | Q66: 9 | R66: 353.25 | U66: 78.06 | V66: 3063.855 | W66: 0 | X66: 0 | Y66: 0 | Z66: 0 | AG66: 0 | AH66: 0 | AK66: 0 | AL66: 0 | AM66: 0 | AN66: 0 | AO66: 0 | AP66: 0 | AQ66: =Q66+S66+U66+W66+Y66+AA66+AC66+AE66+AG66+AI66+AK66+AM66+AO66 -> 87.06 | AR66: =R66+T66+V66+X66+Z66+AB66+AD66+AF66+AH66+AJ66+AL66+AN66+AP66 -> 3417.105 | AS66: REV02-IBS REV | AY66: =IF(AQ66>AU66,AQ66-AU66,"0") -> 87.06 | AZ66: =IF(AR66>AV66,AR66-AV66,"0") -> 3417.105 | BA66: 45892 | BB66: 200825/HN-IBS | BC66: Hùng Nguyên | BD66: PL5x1500x6000 = 1 tờ SS400 | BE66: Q235B/SS400 | BF66: 353.25 | BG66: 45889 | BH66: 9 | BI66: 353.25 | BJ66: 13909.09 | BK66: =BJ66*BI66*1.1 -> 5404724.6 | BL66: =(BK66-BM66)/BM66 -> 0.1 | BM66: =BJ66*BI66*1 -> 4913386 | BN66: 45892 | BO66: =SUMIF($I:$I,I66,$BH:$BH) -> 90 | BP66: =SUMIF($I:$I,I66,$BI:$BI) -> 3532.5 | CM66: =SUMIF($I:$I,I66,$CA:$CA) -> 0 | CN66: =SUMIF($I:$I,I66,$CB:$CB) -> 0 | CS66: =BO66+CM66 -> 90 | CT66: =BP66+CN66 -> 3532.5 | CU66: =AY66-CS66 -> -2.94 | CV66: =AZ66-CT66 -> -115.395 | CW66: =IF(CU66<0,"Thừa",IF(CU66=0,"Đủ","Thiếu")) -> Thừa
A67: =IF(I67=I66,"ok","Hiện") -> ok | I67: I97-VTC01-030 | J67: tôn tấm | K67: PL5X1500X6000 | L67: SS400 | M67: m2 | BB67: I97-1912/HN-IBS | BC67: Hùng Nguyên | BD67: Thép tấm 5x1500x6000 | BE67: SS400 | BF67: 1766.25 | BG67: 46010 | BH67: 45 | BI67: 1766.25 | BJ67: 13954.55 | BK67: =BJ67*BI67*(1+BL67) -> 27111946 | BL67: 0.1 | BM67: =BJ67*BI67 -> 24647224 | BN67: 46018
A68: =IF(I68=I67,"ok","Hiện") -> ok | I68: I97-VTC01-030 | J68: tôn tấm | K68: PL5X1500X6000 | L68: SS400 | M68: m2 | BB68: 03.10.2025/APEC-IBS | BC68: APEC 2 | BD68: PL5X1500X6000mm = 36 m2 Cây/ Tấm SS400 | BE68: Q235B | BF68: 1413 | BG68: 45933 | BH68: =4*9 -> 36 | BI68: 1413 | BJ68: 14090.909 | BK68: =BJ68*BI68*1.1 -> 21901500 | BL68: =(BK68-BM68)/BM68 -> 0.1 | BM68: =BJ68*BI68*1 -> 19910455 | BN68: 45940
A69: =IF(I69=I68,"ok","Hiện") -> Hiện | B69: =CONCATENATE(CW69," Thiếu ít") -> Thiếu Thiếu ít | C69: =CU69 -> 3.54 | D69: Khổ 1,5 | I69: I97-VTC01-031 | J69: tôn tấm | K69: PL6X1500X6000 | L69: SS400 | M69: m2 | N69: 47.1 | O69: 6.5138004 | P69: 306.8 | Q69: 9 | R69: 423.9 | U69: 84.54 | V69: 3981.834 | W69: 0 | X69: 0 | Y69: 0 | Z69: 0 | AG69: 0 | AH69: 0 | AK69: 0 | AL69: 0 | AM69: 0 | AN69: 0 | AO69: 0 | AP69: 0 | AQ69: =Q69+S69+U69+W69+Y69+AA69+AC69+AE69+AG69+AI69+AK69+AM69+AO69 -> 93.54 | AR69: =R69+T69+V69+X69+Z69+AB69+AD69+AF69+AH69+AJ69+AL69+AN69+AP69 -> 4405.734 | AS69: REV02-IBS REV | AY69: =IF(AQ69>AU69,AQ69-AU69,"0") -> 93.54 | AZ69: =IF(AR69>AV69,AR69-AV69,"0") -> 4405.734 | BA69: 45892 | BB69: 200825/HN-IBS | BC69: Hùng Nguyên | BD69: PL6x1500x6000 = 1 tờ SS400 | BE69: Q235B/SS400 | BF69: 423.9 | BG69: 45889 | BH69: 9 | BI69: 423.9 | BJ69: 13909.09 | BK69: =BJ69*BI69*1.1 -> 6485669.6 | BL69: =(BK69-BM69)/BM69 -> 0.1 | BM69: =BJ69*BI69*1 -> 5896063.3 | BN69: 45892 | BO69: =SUMIF($I:$I,I69,$BH:$BH) -> 90 | BP69: =SUMIF($I:$I,I69,$BI:$BI) -> 4239 | CM69: =SUMIF($I:$I,I69,$CA:$CA) -> 0 | CN69: =SUMIF($I:$I,I69,$CB:$CB) -> 0 | CS69: =BO69+CM69 -> 90 | CT69: =BP69+CN69 -> 4239 | CU69: =AY69-CS69 -> 3.54 | CV69: =AZ69-CT69 -> 166.734 | CW69: =IF(CU69<0,"Thừa",IF(CU69=0,"Đủ","Thiếu")) -> Thiếu
A70: =IF(I70=I69,"ok","Hiện") -> ok | I70: I97-VTC01-031 | J70: tôn tấm | K70: PL6X1500X6000 | L70: SS400 | M70: m2 | BB70: I97-1912/HN-IBS | BC70: Hùng Nguyên | BD70: Thép tấm 6x1500x6000 | BE70: SS400 | BF70: 1695.6 | BG70: 46010 | BH70: 36 | BI70: 1695.6 | BJ70: 13363.64 | BK70: =BJ70*BI70*(1+BL70) -> 24925327 | BL70: 0.1 | BM70: =BJ70*BI70 -> 22659388 | BN70: 46018
A71: =IF(I71=I70,"ok","Hiện") -> ok | I71: I97-VTC01-031 | J71: tôn tấm | K71: PL6X1500X6000 | L71: SS400 | M71: m2 | BB71: I97-1010/HN-IBS | BC71: Hùng Nguyên | BD71: Thép tấm 6x1500x6000 = 5 CâySS400 | BF71: 2119.5 | BG71: 45940 | BH71: 45 | BI71: 2119.5 | BJ71: 13909.09 | BK71: =BJ71*BI71*1.1 -> 32428348 | BL71: =(BK71-BM71)/BM71 -> 0.1 | BM71: =BJ71*BI71*1 -> 29480316 | BN71: 45947
A72: =IF(I72=I71,"ok","Hiện") -> Hiện | B72: =CW72 -> Thừa | C72: =CU72 -> -3 | D72: Khổ 2m | I72: I97-VTC01-032 | J72: tôn tấm | K72: PL8X1500X6000 | L72: SS400 | M72: m2 | N72: 62.8 | O72: 5.4735669 | P72: 343.74 | Q72: 9 | R72: 565.2 | U72: 15 | V72: 942 | W72: 0 | X72: 0 | Y72: 0 | Z72: 0 | AG72: 0 | AH72: 0 | AK72: 0 | AL72: 0 | AM72: 0 | AN72: 0 | AO72: 0 | AP72: 0 | AQ72: =Q72+S72+U72+W72+Y72+AA72+AC72+AE72+AG72+AI72+AK72+AM72+AO72 -> 24 | AR72: =R72+T72+V72+X72+Z72+AB72+AD72+AF72+AH72+AJ72+AL72+AN72+AP72 -> 1507.2 | AS72: REV02-IBS REV | AY72: =IF(AQ72>AU72,AQ72-AU72,"0") -> 24 | AZ72: =IF(AR72>AV72,AR72-AV72,"0") -> 1507.2 | BA72: 45892 | BB72: 200825/HN-IBS | BC72: Hùng Nguyên | BD72: PL8x2000x4500 = 1 tờ SS400 | BE72: Q235B/SS400 | BF72: 565.2 | BG72: 45889 | BH72: 9 | BI72: 565.2 | BJ72: 13090.91 | BK72: =BJ72*BI72*1.1 -> 8138880.6 | BL72: =(BK72-BM72)/BM72 -> 0.1 | BM72: =BJ72*BI72*1 -> 7398982.3 | BN72: 45892 | BO72: =SUMIF($I:$I,I72,$BH:$BH) -> 27 | BP72: =SUMIF($I:$I,I72,$BI:$BI) -> 1695.6 | CM72: =SUMIF($I:$I,I72,$CA:$CA) -> 0 | CN72: =SUMIF($I:$I,I72,$CB:$CB) -> 0 | CS72: =BO72+CM72 -> 27 | CT72: =BP72+CN72 -> 1695.6 | CU72: =AY72-CS72 -> -3 | CV72: =AZ72-CT72 -> -188.4 | CW72: =IF(CU72<0,"Thừa",IF(CU72=0,"Đủ","Thiếu")) -> Thừa
A73: =IF(I73=I72,"ok","Hiện") -> ok | I73: I97-VTC01-032 | J73: tôn tấm | K73: PL8X1500X6000 | L73: SS400 | M73: m2 | BB73: I97-1010/HN-IBS | BC73: Hùng Nguyên | BD73: Thép tấm 8x1500x6000 = 2 CâySS400 | BF73: 1130.4 | BG73: 45940 | BH73: 18 | BI73: 1130.4 | BJ73: 13909.09 | BK73: =BJ73*BI73*1.1 -> 17295119 | BL73: =(BK73-BM73)/BM73 -> 0.1 | BM73: =BJ73*BI73*1 -> 15722835 | BN73: 45947
A74: =IF(I74=I73,"ok","Hiện") -> Hiện | B74: =CONCATENATE(CW74," Hàng tồn") -> Thiếu Hàng tồn | C74: =CU74 -> 2 | D74: Khổ 1,5 | I74: I97-VTC01-033 | J74: tôn tấm | K74: PL10X1500X6000 | L74: SS400 | M74: m2 | N74: 78.5 | O74: 7.8996178 | P74: 620.12 | Q74: 9 | R74: 706.5 | U74: 20 | V74: 1570 | W74: 0 | X74: 0 | Y74: 0 | Z74: 0 | AG74: 0 | AH74: 0 | AK74: 0 | AL74: 0 | AM74: 0 | AN74: 0 | AO74: 0 | AP74: 0 | AQ74: =Q74+S74+U74+W74+Y74+AA74+AC74+AE74+AG74+AI74+AK74+AM74+AO74 -> 29 | AR74: =R74+T74+V74+X74+Z74+AB74+AD74+AF74+AH74+AJ74+AL74+AN74+AP74 -> 2276.5 | AS74: REV02-IBS REV | AY74: =IF(AQ74>AU74,AQ74-AU74,"0") -> 29 | AZ74: =IF(AR74>AV74,AR74-AV74,"0") -> 2276.5 | BA74: 45892 | BB74: 200825/HN-IBS | BC74: Hùng Nguyên | BD74: PL10x1500x6000 = 1 tờ SS400 | BE74: Q235B/SS400 | BF74: 706.5 | BG74: 45889 | BH74: 9 | BI74: 706.5 | BJ74: 13909.09 | BK74: =BJ74*BI74*1.1 -> 10809449 | BL74: =(BK74-BM74)/BM74 -> 0.1 | BM74: =BJ74*BI74*1 -> 9826772.1 | BN74: 45892 | BO74: =SUMIF($I:$I,I74,$BH:$BH) -> 27 | BP74: =SUMIF($I:$I,I74,$BI:$BI) -> 2119.5 | CM74: =SUMIF($I:$I,I74,$CA:$CA) -> 0 | CN74: =SUMIF($I:$I,I74,$CB:$CB) -> 0 | CS74: =BO74+CM74 -> 27 | CT74: =BP74+CN74 -> 2119.5 | CU74: =AY74-CS74 -> 2 | CV74: =AZ74-CT74 -> 157 | CW74: =IF(CU74<0,"Thừa",IF(CU74=0,"Đủ","Thiếu")) -> Thiếu
A75: =IF(I75=I74,"ok","Hiện") -> ok | I75: I97-VTC01-033 | J75: tôn tấm | K75: PL10X1500X6000 | L75: SS400 | M75: m2 | BB75: I97-1010/HN-IBS | BC75: Hùng Nguyên | BD75: Thép tấm 10x1500x6000 = 2 CâySS400 | BF75: 1413 | BG75: 45940 | BH75: 18 | BI75: 1413 | BJ75: 13909.09 | BK75: =BJ75*BI75*1.1 -> 21618899 | BL75: =(BK75-BM75)/BM75 -> 0.1 | BM75: =BJ75*BI75*1 -> 19653544 | BN75: 45947
A76: =IF(I76=I75,"ok","Hiện") -> Hiện | B76: =CW76 -> Đủ | C76: =CU76 -> 0 | D76: Khổ 2m | E76: Đã mời | I76: I97-VTC01-034 | J76: tôn tấm | K76: PL12X1500X2000 | L76: SS400 | M76: m2 | N76: 94.2 | O76: 0.59532909 | P76: 56.08 | Q76: 3 | R76: 282.6 | U76: 0 | V76: 0 | W76: 0 | X76: 0 | Y76: 0 | Z76: 0 | AG76: 0 | AH76: 0 | AK76: 0 | AL76: 0 | AM76: 0 | AN76: 0 | AO76: 0 | AP76: 0 | AQ76: =Q76+S76+U76+W76+Y76+AA76+AC76+AE76+AG76+AI76+AK76+AM76+AO76 -> 3 | AR76: =R76+T76+V76+X76+Z76+AB76+AD76+AF76+AH76+AJ76+AL76+AN76+AP76 -> 282.6 | AU76: 3 | AV76: 282.6 | AX76: Hàng tận dungj | AY76: =IF(AQ76>AU76,AQ76-AU76,"0") -> 0 | AZ76: =IF(AR76>AV76,AR76-AV76,"0") -> 0 | BA76: 45892 | BO76: =SUMIF($I:$I,I76,$BH:$BH) -> 0 | BP76: =SUMIF($I:$I,I76,$BI:$BI) -> 0 | CM76: =SUMIF($I:$I,I76,$CA:$CA) -> 0 | CN76: =SUMIF($I:$I,I76,$CB:$CB) -> 0 | CS76: =BO76+CM76 -> 0 | CT76: =BP76+CN76 -> 0 | CU76: =AY76-CS76 -> 0 | CV76: =AZ76-CT76 -> 0 | CW76: =IF(CU76<0,"Thừa",IF(CU76=0,"Đủ","Thiếu")) -> Đủ
A77: =IF(I77=I76,"ok","Hiện") -> Hiện | B77: =CW77 -> Đủ | C77: =CU77 -> 0 | D77: Pl16x2m | E77: Đã mời | I77: I97-VTC01-035 | J77: tôn tấm | K77: PL15X1500X2000 | L77: SS400 | M77: m2 | N77: 117.26667 | O77: 1.2 | P77: 140.72 | Q77: 3 | R77: 351.8 | U77: 0 | V77: 0 | W77: 0 | X77: 0 | Y77: 0 | Z77: 0 | AG77: 0 | AH77: 0 | AK77: 0 | AL77: 0 | AM77: 0 | AN77: 0 | AO77: 0 | AP77: 0 | AQ77: =Q77+S77+U77+W77+Y77+AA77+AC77+AE77+AG77+AI77+AK77+AM77+AO77 -> 3 | AR77: =R77+T77+V77+X77+Z77+AB77+AD77+AF77+AH77+AJ77+AL77+AN77+AP77 -> 351.8 | AU77: 3 | AV77: 351.8 | AX77: Hàng tận dungj | AY77: =IF(AQ77>AU77,AQ77-AU77,"0") -> 0 | AZ77: =IF(AR77>AV77,AR77-AV77,"0") -> 0 | BA77: 45892 | BO77: =SUMIF($I:$I,I77,$BH:$BH) -> 0 | BP77: =SUMIF($I:$I,I77,$BI:$BI) -> 0 | CM77: =SUMIF($I:$I,I77,$CA:$CA) -> 0 | CN77: =SUMIF($I:$I,I77,$CB:$CB) -> 0 | CS77: =BO77+CM77 -> 0 | CT77: =BP77+CN77 -> 0 | CU77: =AY77-CS77 -> 0 | CV77: =AZ77-CT77 -> 0 | CW77: =IF(CU77<0,"Thừa",IF(CU77=0,"Đủ","Thiếu")) -> Đủ
A78: =IF(I78=I77,"ok","Hiện") -> Hiện | B78: =CW78 -> Thừa | C78: =CU78 -> -22 | E78: Dùng cùng dự án 090 | I78: I97-VTC01-036 | J78: tôn tấm | K78: PL25X2000X1000 | L78: SS400 | M78: m2 | N78: 196.25 | O78: 0.50017834 | P78: 98.16 | Q78: 2 | R78: 392.5 | U78: 0 | V78: 0 | W78: 0 | X78: 0 | Y78: 0 | Z78: 0 | AG78: 0 | AH78: 0 | AK78: 0 | AL78: 0 | AM78: 0 | AN78: 0 | AO78: 0 | AP78: 0 | AQ78: =Q78+S78+U78+W78+Y78+AA78+AC78+AE78+AG78+AI78+AK78+AM78+AO78 -> 2 | AR78: =R78+T78+V78+X78+Z78+AB78+AD78+AF78+AH78+AJ78+AL78+AN78+AP78 -> 392.5 | AY78: =IF(AQ78>AU78,AQ78-AU78,"0") -> 2 | AZ78: =IF(AR78>AV78,AR78-AV78,"0") -> 392.5 | BA78: 45892 | BB78: 22.08.2025/APEC-IBS | BC78: APEC | BD78: Thép tấm 25x2000x12000mm | BE78: SS400/ | BF78: 4710 | BG78: 45891 | BH78: 24 | BI78: 4710 | BJ78: 14090.91 | BK78: =BJ78*BI78*1.1 -> 73005005 | BL78: =(BK78-BM78)/BM78 -> 0.1 | BM78: =BJ78*BI78*1 -> 66368186 | BN78: 45897 | BO78: =SUMIF($I:$I,I78,$BH:$BH) -> 24 | BP78: =SUMIF($I:$I,I78,$BI:$BI) -> 4710 | CM78: =SUMIF($I:$I,I78,$CA:$CA) -> 0 | CN78: =SUMIF($I:$I,I78,$CB:$CB) -> 0 | CS78: =BO78+CM78 -> 24 | CT78: =BP78+CN78 -> 4710 | CU78: =AY78-CS78 -> -22 | CV78: =AZ78-CT78 -> -4317.5 | CW78: =IF(CU78<0,"Thừa",IF(CU78=0,"Đủ","Thiếu")) -> Thừa
A79: =IF(I79=I78,"ok","Hiện") -> Hiện | B79: =CW79 -> Thừa | C79: =CU79 -> -4.4 | I79: I97-VTC01-037 | J79: tôn tấm | K79: PL50X2000X3800 | L79: SS400 | M79: m2 | N79: 392.5 | O79: 2.3745223 | P79: 932 | Q79: 7.6 | R79: 2983 | U79: 0 | V79: 0 | W79: 0 | X79: 0 | Y79: 0 | Z79: 0 | AG79: 0 | AH79: 0 | AK79: 0 | AL79: 0 | AM79: 0 | AN79: 0 | AO79: 0 | AP79: 0 | AQ79: =Q79+S79+U79+W79+Y79+AA79+AC79+AE79+AG79+AI79+AK79+AM79+AO79 -> 7.6 | AR79: =R79+T79+V79+X79+Z79+AB79+AD79+AF79+AH79+AJ79+AL79+AN79+AP79 -> 2983 | AY79: =IF(AQ79>AU79,AQ79-AU79,"0") -> 7.6 | AZ79: =IF(AR79>AV79,AR79-AV79,"0") -> 2983 | BA79: 45892 | BB79: 22.08.2025/APEC-IBS | BC79: APEC | BD79: Thép tấm 50x2000x6000mm | BE79: A36/Q235B | BF79: 4710 | BG79: 45891 | BH79: 12 | BI79: 4710 | BJ79: 14909.09 | BK79: =BJ79*BI79*1.1 -> 77243995 | BL79: =(BK79-BM79)/BM79 -> 0.1 | BM79: =BJ79*BI79*1 -> 70221814 | BN79: 45897 | BO79: =SUMIF($I:$I,I79,$BH:$BH) -> 12 | BP79: =SUMIF($I:$I,I79,$BI:$BI) -> 4710 | CM79: =SUMIF($I:$I,I79,$CA:$CA) -> 0 | CN79: =SUMIF($I:$I,I79,$CB:$CB) -> 0 | CS79: =BO79+CM79 -> 12 | CT79: =BP79+CN79 -> 4710 | CU79: =AY79-CS79 -> -4.4 | CV79: =AZ79-CT79 -> -1727 | CW79: =IF(CU79<0,"Thừa",IF(CU79=0,"Đủ","Thiếu")) -> Thừa
A80: =IF(I80=I79,"ok","Hiện") -> Hiện | B80: =CW80 -> Đủ | C80: =CU80 -> 0 | I80: I97-VTC01-038 | J80: bậc thang | K80: LADDER RUNG LSP25-457L | L80: SS400 | M80: cái | N80: 0 | O80: 24 | P80: 0 | Q80: 24 | R80: 0 | U80: 36 | V80: 0 | W80: 0 | X80: 0 | Y80: 0 | Z80: 0 | AG80: 0 | AH80: 0 | AK80: 0 | AL80: 0 | AM80: 0 | AN80: 0 | AO80: 0 | AP80: 0 | AQ80: =Q80+S80+U80+W80+Y80+AA80+AC80+AE80+AG80+AI80+AK80+AM80+AO80 -> 60 | AR80: =R80+T80+V80+X80+Z80+AB80+AD80+AF80+AH80+AJ80+AL80+AN80+AP80 -> 0 | AS80: REV02-IBS REV | AY80: =IF(AQ80>AU80,AQ80-AU80,"0") -> 60 | AZ80: =IF(AR80>AV80,AR80-AV80,"0") -> 0 | BA80: 45892 | BB80: Báo giá ngày 22/8/2025 | BC80: WINWWIN | BD80: Bậc thang dập lỗ nổi - thép đen (LSP 25) -L=457 mm | BF80: N/A | BG80: 45889 | BH80: 24 | BI80: N/A | BJ80: 350000 | BK80: =BJ80*BH80*1.1 -> 9240000 | BL80: =(BK80-BM80)/BM80 -> 0.1 | BM80: =BJ80*BH80*1 -> 8400000 | BN80: 45910 | BO80: =SUMIF($I:$I,I80,$BH:$BH) -> 60 | BP80: =SUMIF($I:$I,I80,$BI:$BI) -> 0 | CM80: =SUMIF($I:$I,I80,$CA:$CA) -> 0 | CN80: =SUMIF($I:$I,I80,$CB:$CB) -> 0 | CS80: =BO80+CM80 -> 60 | CT80: =BP80+CN80 -> 0 | CU80: =AY80-CS80 -> 0 | CV80: =AZ80-CT80 -> 0 | CW80: =IF(CU80<0,"Thừa",IF(CU80=0,"Đủ","Thiếu")) -> Đủ
A81: =IF(I81=I80,"ok","Hiện") -> ok | I81: I97-VTC01-038 | J81: bậc thang | K81: LADDER RUNG LSP25-457L | L81: SS400 | M81: cái | BB81: Báo giá ngày 2/10/2025 | BC81: WINWWIN | BD81: Bậc thang dập lỗ nổi - thép đen (LSP 25) -L=457 mm | BF81: N/A | BG81: 45932 | BH81: 36 | BI81: N/A | BJ81: 350000 | BK81: =BJ81*BH81*1.1 -> 13860000 | BL81: =(BK81-BM81)/BM81 -> 0.1 | BM81: =BJ81*BH81*1 -> 12600000 | BN81: 45947 | BO81: =SUMIF($K:$K,K81,$BH:$BH) -> 60
A82: =IF(I82=I81,"ok","Hiện") -> Hiện | B82: =CW82 -> Đủ | C82: =CU82 -> 0 | I82: I97-VTC01-039 | J82: bậc thang | K82: LADDER RUNG LSP25-560L | L82: SS400 | M82: cái | N82: 0 | O82: 64 | P82: 0 | Q82: 64 | R82: 0 | U82: 96 | V82: 0 | W82: 0 | X82: 0 | Y82: 0 | Z82: 0 | AG82: 0 | AH82: 0 | AK82: 0 | AL82: 0 | AM82: 0 | AN82: 0 | AO82: 0 | AP82: 0 | AQ82: =Q82+S82+U82+W82+Y82+AA82+AC82+AE82+AG82+AI82+AK82+AM82+AO82 -> 160 | AR82: =R82+T82+V82+X82+Z82+AB82+AD82+AF82+AH82+AJ82+AL82+AN82+AP82 -> 0 | AS82: REV02-IBS REV | AY82: =IF(AQ82>AU82,AQ82-AU82,"0") -> 160 | AZ82: =IF(AR82>AV82,AR82-AV82,"0") -> 0 | BA82: 45892 | BB82: Báo giá ngày 22/8/2025 | BC82: WINWWIN | BD82: Bậc thang dập lỗ nổi - thép đen (LSP 25) -L=560 mm | BF82: N/A | BG82: 45889 | BH82: 64 | BI82: N/A | BJ82: 350000 | BK82: =BJ82*BH82*1.1 -> 24640000 | BL82: =(BK82-BM82)/BM82 -> 0.1 | BM82: =BJ82*BH82*1 -> 22400000 | BN82: 45910 | BO82: =SUMIF($I:$I,I82,$BH:$BH) -> 160 | BP82: =SUMIF($I:$I,I82,$BI:$BI) -> 0 | CM82: =SUMIF($I:$I,I82,$CA:$CA) -> 0 | CN82: =SUMIF($I:$I,I82,$CB:$CB) -> 0 | CS82: =BO82+CM82 -> 160 | CT82: =BP82+CN82 -> 0 | CU82: =AY82-CS82 -> 0 | CV82: =AZ82-CT82 -> 0 | CW82: =IF(CU82<0,"Thừa",IF(CU82=0,"Đủ","Thiếu")) -> Đủ
A83: =IF(I83=I82,"ok","Hiện") -> ok | I83: I97-VTC01-039 | J83: bậc thang | K83: LADDER RUNG LSP25-560L | L83: SS400 | M83: cái | BB83: Báo giá ngày 2/10/2025 | BC83: WINWWIN | BD83: Bậc thang dập lỗ nổi - thép đen (LSP 25) -L=560 mm | BF83: N/A | BG83: 45932 | BH83: 96 | BI83: N/A | BJ83: 350000 | BK83: =BJ83*BH83*1.1 -> 36960000 | BL83: =(BK83-BM83)/BM83 -> 0.1 | BM83: =BJ83*BH83*1 -> 33600000 | BN83: 45947 | BO83: =SUMIF($K:$K,K83,$BH:$BH) -> 160
A84: =IF(I84=I83,"ok","Hiện") -> Hiện | B84: =CW84 -> Thừa | C84: =CU84 -> -672 | I84: I97-VTC01-040 | J84: thepa hình C | K84: C80x45x5.5x7.5-12000L | L84: SS400 | M84: m | N84: 8.23 | O84: 787.43 | P84: 6488 | U84: 842.5501 | V84: 6934.1873 | W84: 0 | X84: 0 | Y84: 0 | Z84: 0 | AE84: -842.5501 | AF84: -6934.1873 | AG84: 0 | AH84: 0 | AK84: 0 | AL84: 0 | AM84: 0 | AN84: 0 | AO84: 0 | AP84: 0 | AQ84: =Q84+S84+U84+W84+Y84+AA84+AC84+AE84+AG84+AI84+AK84+AM84+AO84 -> 0 | AR84: =R84+T84+V84+X84+Z84+AB84+AD84+AF84+AH84+AJ84+AL84+AN84+AP84 -> 0 | AS84: REV07-IBS REV(PTM chuyển PL6) | AY84: =IF(AQ84>AU84,AQ84-AU84,"0") -> 0 | AZ84: =IF(AR84>AV84,AR84-AV84,"0") -> 0 | BO84: =SUMIF($I:$I,I84,$BH:$BH) -> 0 | BP84: =SUMIF($I:$I,I84,$BI:$BI) -> 0 | BU84: 25MCL139S | BV84: MCL | BW84: UPN80（80x45x6x8） | BY84: 5806 | BZ84: 45978 | CA84: =56*12 -> 672 | CB84: 5806 | CC84: 0.9 | CD84: =CC84*CB84 -> 5225.4 | CL84: 46021 | CM84: =SUMIF($I:$I,I84,$CA:$CA) -> 672 | CN84: =SUMIF($I:$I,I84,$CB:$CB) -> 5806 | CS84: =BO84+CM84 -> 672 | CT84: =BP84+CN84 -> 5806 | CU84: =AY84-CS84 -> -672 | CV84: =AZ84-CT84 -> -5806 | CW84: =IF(CU84<0,"Thừa",IF(CU84=0,"Đủ","Thiếu")) -> Thừa
A85: =IF(I85=I84,"ok","Hiện") -> Hiện | B85: =CW85 -> Thừa | C85: =CU85 -> -3.42065 | I85: I97-VTC01-041 | J85: thepa hình C | K85: C150X75X6.5X10 | L85: SS400 | M85: m | N85: 18.6 | O85: 748.205 | P85: 13928.5 | U85: 800.57935 | V85: 14890.776 | W85: 0 | X85: 0 | Y85: 0 | Z85: 0 | AG85: 0 | AH85: 0 | AK85: 0 | AL85: 0 | AM85: 0 | AN85: 0 | AO85: 0 | AP85: 0 | AQ85: =Q85+S85+U85+W85+Y85+AA85+AC85+AE85+AG85+AI85+AK85+AM85+AO85 -> 800.57935 | AR85: =R85+T85+V85+X85+Z85+AB85+AD85+AF85+AH85+AJ85+AL85+AN85+AP85 -> 14890.776 | AS85: REV02-IBS REV | AY85: =IF(AQ85>AU85,AQ85-AU85,"0") -> 800.57935 | AZ85: =IF(AR85>AV85,AR85-AV85,"0") -> 14890.776 | BB85: ? | BC85: Hùng Nguyên | BD85: Thép U150*75*6.5*10*12000 = 28 Cây | BF85: 6249.6 | BG85: ? | BH85: =28*12 -> 336 | BI85: 6249.6 | BJ85: =19200/1.1 -> 17454.545 | BK85: =BJ85*BI85*1.1 -> 119992320 | BL85: =(BK85-BM85)/BM85 -> 0.1 | BM85: =BJ85*BI85*1 -> 1.0908393e+08 | BN85: 45961 | BO85: =SUMIF($I:$I,I85,$BH:$BH) -> 804 | BP85: =SUMIF($I:$I,I85,$BI:$BI) -> 14954.6 | CM85: =SUMIF($I:$I,I85,$CA:$CA) -> 0 | CN85: =SUMIF($I:$I,I85,$CB:$CB) -> 0 | CS85: =BO85+CM85 -> 804 | CT85: =BP85+CN85 -> 14954.6 | CU85: =AY85-CS85 -> -3.42065 | CV85: =AZ85-CT85 -> -63.82409 | CW85: =IF(CU85<0,"Thừa",IF(CU85=0,"Đủ","Thiếu")) -> Thừa
A86: =IF(I86=I85,"ok","Hiện") -> ok | I86: I97-VTC01-041 | J86: thepa hình C | K86: C150X75X6.5X10 | L86: SS400 | M86: m | BB86: 1912-2025/HĐKT/NH-IBS | BC86: Ngọc Hiếu | BD86: Thép U150*75*6,5*10*12000 ( 39 cây) | BE86: SS400 | BF86: 8705 | BG86: 46010 | BH86: 468 | BI86: 8705 | BJ86: 17090.91 | BK86: =BJ86*BI86*(1+BL86) -> 1.6365401e+08 | BL86: 0.1 | BM86: =BJ86*BI86 -> 1.4877637e+08 | BN86: 46029
A87: =IF(I87=I86,"ok","Hiện") -> Hiện | B87: =CONCATENATE(CW87," dùng hàng sấn/ Ms Khanh") -> Thiếu dùng hàng sấn/ Ms Khanh | C87: =CU87 -> 85.09735 | E87: hàng sấn | I87: I97-VTC01-042 | J87: thepa hình C | K87: C180X90X7.5X12.5 | L87: SS400 | M87: m | N87: 27.137642 | O87: 135.605 | P87: 3680 | U87: 145.09735 | V87: 3937.6 | W87: 0 | X87: 0 | Y87: 0 | Z87: 0 | AG87: 0 | AH87: 0 | AK87: 0 | AL87: 0 | AM87: 0 | AN87: 0 | AO87: 0 | AP87: 0 | AQ87: =Q87+S87+U87+W87+Y87+AA87+AC87+AE87+AG87+AI87+AK87+AM87+AO87 -> 145.09735 | AR87: =R87+T87+V87+X87+Z87+AB87+AD87+AF87+AH87+AJ87+AL87+AN87+AP87 -> 3937.6 | AS87: REV02-IBS REV | AY87: =IF(AQ87>AU87,AQ87-AU87,"0") -> 145.09735 | AZ87: =IF(AR87>AV87,AR87-AV87,"0") -> 3937.6 | BB87: I97-1010/HN-IBS | BC87: Hùng Nguyên | BD87: Thép U180x75x7x10.5x12000 = 5 CâySS400 | BF87: 1284 | BG87: 45940 | BH87: 60 | BI87: 1284 | BJ87: 17681.82 | BK87: =BJ87*BI87*1.1 -> 24973803 | BL87: =(BK87-BM87)/BM87 -> 0.1 | BM87: =BJ87*BI87*1 -> 22703457 | BN87: 45947 | BO87: =SUMIF($I:$I,I87,$BH:$BH) -> 60 | BP87: =SUMIF($I:$I,I87,$BI:$BI) -> 1284 | CM87: =SUMIF($I:$I,I87,$CA:$CA) -> 0 | CN87: =SUMIF($I:$I,I87,$CB:$CB) -> 0 | CS87: =BO87+CM87 -> 60 | CT87: =BP87+CN87 -> 1284 | CU87: =AY87-CS87 -> 85.09735 | CV87: =AZ87-CT87 -> 2653.6 | CW87: =IF(CU87<0,"Thừa",IF(CU87=0,"Đủ","Thiếu")) -> Thiếu
A88: =IF(I88=I87,"ok","Hiện") -> Hiện | B88: =CW88 -> Thừa | C88: =CU88 -> -0.9082 | I88: I97-VTC01-043 | J88: thepa hình C | K88: C200X80X7.5X11 | L88: SS400 | M88: m | N88: 24.6 | O88: 290.74 | P88: 7151.5 | U88: 311.0918 | V88: 7652.8583 | W88: 0 | X88: 0 | Y88: 0 | Z88: 0 | AG88: 0 | AH88: 0 | AK88: 0 | AL88: 0 | AM88: 0 | AN88: 0 | AO88: 0 | AP88: 0 | AQ88: =Q88+S88+U88+W88+Y88+AA88+AC88+AE88+AG88+AI88+AK88+AM88+AO88 -> 311.0918 | AR88: =R88+T88+V88+X88+Z88+AB88+AD88+AF88+AH88+AJ88+AL88+AN88+AP88 -> 7652.8583 | AS88: REV02-IBS REV | AY88: =IF(AQ88>AU88,AQ88-AU88,"0") -> 311.0918 | AZ88: =IF(AR88>AV88,AR88-AV88,"0") -> 7652.8583 | BB88: 3110-2025/HĐKT/NH-IBS | BC88: Ngọc Hiếu | BD88: Thép U200*80*7,5*11*12000 (26 cây) | BF88: 7675 | BG88: 45961 | BH88: =26*12 -> 312 | BI88: 7675 | BJ88: 17545.45 | BK88: =BJ88*BI88*1.1 -> 1.4812746e+08 | BL88: =(BK88-BM88)/BM88 -> 0.1 | BM88: =BJ88*BI88*1 -> 1.3466133e+08 | BN88: 45961 | BO88: =SUMIF($I:$I,I88,$BH:$BH) -> 312 | BP88: =SUMIF($I:$I,I88,$BI:$BI) -> 7675 | CM88: =SUMIF($I:$I,I88,$CA:$CA) -> 0 | CN88: =SUMIF($I:$I,I88,$CB:$CB) -> 0 | CS88: =BO88+CM88 -> 312 | CT88: =BP88+CN88 -> 7675 | CU88: =AY88-CS88 -> -0.9082 | CV88: =AZ88-CT88 -> -22.14172 | CW88: =IF(CU88<0,"Thừa",IF(CU88=0,"Đủ","Thiếu")) -> Thừa
A89: =IF(I89=I88,"ok","Hiện") -> Hiện | B89: =CW89 -> Thừa | C89: =CU89 -> -1.09525 | I89: I97-VTC01-044 | J89: thepa hình C | K89: C250X90X9X13 | L89: SS400 | M89: m | N89: 34.6 | O89: 335.425 | P89: 11603 | U89: 358.90475 | V89: 12418.104 | W89: 0 | Y89: 0 | Z89: 0 | AG89: 0 | AH89: 0 | AK89: 0 | AL89: 0 | AM89: 0 | AN89: 0 | AO89: 0 | AP89: 0 | AQ89: =Q89+S89+U89+W89+Y89+AA89+AC89+AE89+AG89+AI89+AK89+AM89+AO89 -> 358.90475 | AR89: =R89+T89+V89+X89+Z89+AB89+AD89+AF89+AH89+AJ89+AL89+AN89+AP89 -> 12418.104 | AS89: REV02-IBS REV | AY89: =IF(AQ89>AU89,AQ89-AU89,"0") -> 358.90475 | AZ89: =IF(AR89>AV89,AR89-AV89,"0") -> 12418.104 | BB89: 1510-2025/HĐKT/NH-IBS | BC89: Ngọc Hiếu | BD89: Thép U250*90*9*13*12000 = 12 Cây | BF89: 4982 | BG89: 45945 | BH89: 144 | BI89: 4982 | BJ89: 17545.45 | BK89: =BJ89*BI89*1.1 -> 96152575 | BL89: =(BK89-BM89)/BM89 -> 0.1 | BM89: =BJ89*BI89*1 -> 87411432 | BN89: 45954 | BO89: =SUMIF($I:$I,I89,$BH:$BH) -> 360 | BP89: =SUMIF($I:$I,I89,$BI:$BI) -> 12455.6 | CM89: =SUMIF($I:$I,I89,$CA:$CA) -> 0 | CN89: =SUMIF($I:$I,I89,$CB:$CB) -> 0 | CS89: =BO89+CM89 -> 360 | CT89: =BP89+CN89 -> 12455.6 | CU89: =AY89-CS89 -> -1.09525 | CV89: =AZ89-CT89 -> -37.49565 | CW89: =IF(CU89<0,"Thừa",IF(CU89=0,"Đủ","Thiếu")) -> Thừa
A90: =IF(I90=I89,"ok","Hiện") -> ok | I90: I97-VTC01-044 | J90: thepa hình C | K90: C250X90X9X13 | L90: SS400 | M90: m | BB90: 1912-2025/HĐKT/NH-IBS | BC90: Ngọc Hiếu | BD90: Thép U250*90*9*13*12000 (5 cây) | BE90: SS400 | BF90: 2076 | BG90: 46010 | BH90: 60 | BI90: 2076 | BJ90: 17272.73 | BK90: =BJ90*BI90*(1+BL90) -> 39444006 | BL90: 0.1 | BM90: =BJ90*BI90 -> 35858187 | BN90: Hàng chưa vè (đã về 4 cây)
A91: =IF(I91=I90,"ok","Hiện") -> ok | I91: I97-VTC01-044 | J91: thepa hình C | K91: C250X90X9X13 | L91: SS400 | M91: m | BB91: ? | BC91: Hùng Nguyên | BD91: Thép U250*90*9*13*12000 = 13 Cây | BF91: 5397.6 | BG91: ? | BH91: =13*12 -> 156 | BI91: 5397.6 | BJ91: =19200/1.1 -> 17454.545 | BK91: =BJ91*BI91*1.1 -> 103633920 | BL91: =(BK91-BM91)/BM91 -> 0.1 | BM91: =BJ91*BI91*1 -> 94212655 | BN91: 45955
A92: =IF(I92=I91,"ok","Hiện") -> Hiện | B92: =CONCATENATE(CW92," tính đủ") -> Thiếu tính đủ | C92: =CU92 -> 0.0037 | I92: I97-VTC01-045 | J92: thepa hình C | K92: C300X90X9X13 | L92: SS400 | M92: m | N92: 38.1 | O92: 73.91 | P92: 2818 | U92: 79.0837 | V92: 3013.089 | W92: 0 | X92: 0 | Y92: 0 | Z92: 0 | AG92: 0 | AH92: 0 | AK92: 0 | AL92: 0 | AM92: 0 | AN92: 0 | AO92: 4.92 | AP92: 187.452 | AQ92: =Q92+S92+U92+W92+Y92+AA92+AC92+AE92+AG92+AI92+AK92+AM92+AO92 -> 84.0037 | AR92: =R92+T92+V92+X92+Z92+AB92+AD92+AF92+AH92+AJ92+AL92+AN92+AP92 -> 3200.541 | AS92: REV12-IBS REV | AY92: =IF(AQ92>AU92,AQ92-AU92,"0") -> 84.0037 | AZ92: =IF(AR92>AV92,AR92-AV92,"0") -> 3200.541 | BB92: 1510-2025/HĐKT/NH-IBS | BC92: Ngọc Hiếu | BD92: Thép U300*90*9*12*12000 = 7 Cây | BF92: 3200 | BG92: 45945 | BH92: 84 | BI92: 3200 | BJ92: 17545.45 | BK92: =BJ92*BI92*1.1 -> 61759984 | BL92: =(BK92-BM92)/BM92 -> 0.1 | BM92: =BJ92*BI92*1 -> 56145440 | BN92: 45954 | BO92: =SUMIF($I:$I,I92,$BH:$BH) -> 84 | BP92: =SUMIF($I:$I,I92,$BI:$BI) -> 3200 | CM92: =SUMIF($I:$I,I92,$CA:$CA) -> 0 | CN92: =SUMIF($I:$I,I92,$CB:$CB) -> 0 | CS92: =BO92+CM92 -> 84 | CT92: =BP92+CN92 -> 3200 | CU92: =AY92-CS92 -> 0.0037 | CV92: =AZ92-CT92 -> 0.54097 | CW92: =IF(CU92<0,"Thừa",IF(CU92=0,"Đủ","Thiếu")) -> Thiếu
A93: =IF(I93=I92,"ok","Hiện") -> Hiện | B93: =CW93 -> Thừa | C93: =CU93 -> -0.2672 | I93: I97-VTC01-046 | J93: thepa hình C | K93: C380X100X10.5X16 | L93: SS400 | M93: m | N93: 54.5 | O93: 67.04 | P93: 3652 | U93: 71.7328 | V93: 3909.4376 | W93: 0 | X93: 0 | Y93: 0 | Z93: 0 | AG93: 0 | AH93: 0 | AK93: 0 | AL93: 0 | AM93: 0 | AN93: 0 | AO93: 0 | AP93: 0 | AQ93: =Q93+S93+U93+W93+Y93+AA93+AC93+AE93+AG93+AI93+AK93+AM93+AO93 -> 71.7328 | AR93: =R93+T93+V93+X93+Z93+AB93+AD93+AF93+AH93+AJ93+AL93+AN93+AP93 -> 3909.4376 | AS93: REV02-IBS REV | AY93: =IF(AQ93>AU93,AQ93-AU93,"0") -> 71.7328 | AZ93: =IF(AR93>AV93,AR93-AV93,"0") -> 3909.4376 | BB93: 1510-2025/HĐKT/NH-IBS | BC93: Ngọc Hiếu | BD93: Thép U380*100*10,5*16*12000 = 6 Cây | BF93: 3924 | BG93: 45945 | BH93: 72 | BI93: 3924 | BJ93: 20909.09 | BK93: =BJ93*BI93*1.1 -> 90251996 | BL93: =(BK93-BM93)/BM93 -> 0.1 | BM93: =BJ93*BI93*1 -> 82047269 | BN93: 45954 | BO93: =SUMIF($I:$I,I93,$BH:$BH) -> 72 | BP93: =SUMIF($I:$I,I93,$BI:$BI) -> 3924 | CM93: =SUMIF($I:$I,I93,$CA:$CA) -> 0 | CN93: =SUMIF($I:$I,I93,$CB:$CB) -> 0 | CS93: =BO93+CM93 -> 72 | CT93: =BP93+CN93 -> 3924 | CU93: =AY93-CS93 -> -0.2672 | CV93: =AZ93-CT93 -> -14.5624 | CW93: =IF(CU93<0,"Thừa",IF(CU93=0,"Đủ","Thiếu")) -> Thừa
A94: =IF(I94=I93,"ok","Hiện") -> Hiện | B94: =CW94 -> Thừa | C94: =CU94 -> -2.74185 | I94: I97-VTC01-047 | J94: thép ống | K94: CHS114X6 | L94: SS400 | M94: m | N94: 15.763547 | O94: 3.045 | P94: 48 | U94: 3.25815 | V94: 51.36 | W94: 0 | X94: 0 | Y94: 0 | Z94: 0 | AG94: 0 | AH94: 0 | AK94: 0 | AL94: 0 | AM94: 0 | AN94: 0 | AO94: 0 | AP94: 0 | AQ94: =Q94+S94+U94+W94+Y94+AA94+AC94+AE94+AG94+AI94+AK94+AM94+AO94 -> 3.25815 | AR94: =R94+T94+V94+X94+Z94+AB94+AD94+AF94+AH94+AJ94+AL94+AN94+AP94 -> 51.36 | AS94: REV02-IBS REV | AY94: =IF(AQ94>AU94,AQ94-AU94,"0") -> 3.25815 | AZ94: =IF(AR94>AV94,AR94-AV94,"0") -> 51.36 | BB94: Báo giá ngày 10/10/2025 | BC94: TITAN/190 | BD94: Thép ống đen 114.00 x 6.00 x 6000.0 mm = 1Cây | BF94: 96 | BG94: 45940 | BH94: 6 | BI94: 96 | BJ94: 17727.273 | BK94: =BJ94*BI94*1.1 -> 1872000 | BL94: =(BK94-BM94)/BM94 -> 0.1 | BM94: =BJ94*BI94*1 -> 1701818.2 | BN94: 45953 | BO94: =SUMIF($I:$I,I94,$BH:$BH) -> 6 | BP94: =SUMIF($I:$I,I94,$BI:$BI) -> 96 | CM94: =SUMIF($I:$I,I94,$CA:$CA) -> 0 | CN94: =SUMIF($I:$I,I94,$CB:$CB) -> 0 | CS94: =BO94+CM94 -> 6 | CT94: =BP94+CN94 -> 96 | CU94: =AY94-CS94 -> -2.74185 | CV94: =AZ94-CT94 -> -44.64 | CW94: =IF(CU94<0,"Thừa",IF(CU94=0,"Đủ","Thiếu")) -> Thừa
A95: =IF(I95=I94,"ok","Hiện") -> Hiện | B95: =CW95 -> Thừa | C95: =CU95 -> -2.8028 | I95: I97-VTC01-048 | J95: thép ống | K95: CHS42.7X2.3 | L95: SS400 | M95: m | N95: 2.4022431 | O95: 131.96 | P95: 317 | U95: 141.1972 | V95: 339.19 | W95: 0 | X95: 0 | Y95: 0 | Z95: 0 | AG95: 0 | AH95: 0 | AK95: 0 | AL95: 0 | AM95: 0 | AN95: 0 | AO95: 0 | AP95: 0 | AQ95: =Q95+S95+U95+W95+Y95+AA95+AC95+AE95+AG95+AI95+AK95+AM95+AO95 -> 141.1972 | AR95: =R95+T95+V95+X95+Z95+AB95+AD95+AF95+AH95+AJ95+AL95+AN95+AP95 -> 339.19 | AS95: REV02-IBS REV | AY95: =IF(AQ95>AU95,AQ95-AU95,"0") -> 141.1972 | AZ95: =IF(AR95>AV95,AR95-AV95,"0") -> 339.19 | BB95: Báo giá ngày 10/10/2025 | BC95: TITAN/190 | BD95: Thép ống đen 42.700 x 2.300 x 6000.0 mm = 24Cây | BF95: 330 | BG95: 45940 | BH95: 144 | BI95: 330 | BJ95: 16818.182 | BK95: =BJ95*BI95*1.1 -> 6105000 | BL95: =(BK95-BM95)/BM95 -> 0.1 | BM95: =BJ95*BI95*1 -> 5550000 | BN95: 45953 | BO95: =SUMIF($I:$I,I95,$BH:$BH) -> 144 | BP95: =SUMIF($I:$I,I95,$BI:$BI) -> 330 | CM95: =SUMIF($I:$I,I95,$CA:$CA) -> 0 | CN95: =SUMIF($I:$I,I95,$CB:$CB) -> 0 | CS95: =BO95+CM95 -> 144 | CT95: =BP95+CN95 -> 330 | CU95: =AY95-CS95 -> -2.8028 | CV95: =AZ95-CT95 -> 9.19 | CW95: =IF(CU95<0,"Thừa",IF(CU95=0,"Đủ","Thiếu")) -> Thừa
A96: =IF(I96=I95,"ok","Hiện") -> Hiện | B96: =CW96 -> Đủ | C96: =CU96 -> 0 | F96: ELBOW 90˚ LR ( DN32 ) Ø42.2 x 2.6mmEN 10253P 235GH | I96: I97-VTC01-049 | J96: elbow | K96: ELBOW 42.4x2.6-90 độ LONG-DIN2605-TYPE3 | L96: SS400 | M96: cái | O96: 100 | P96: 0 | U96: 105 | V96: 0 | W96: 0 | X96: 0 | Y96: 0 | Z96: 0 | AG96: 0 | AH96: 0 | AK96: 0 | AL96: 0 | AM96: 0 | AN96: 0 | AO96: 0 | AP96: 0 | AQ96: =Q96+S96+U96+W96+Y96+AA96+AC96+AE96+AG96+AI96+AK96+AM96+AO96 -> 105 | AR96: =R96+T96+V96+X96+Z96+AB96+AD96+AF96+AH96+AJ96+AL96+AN96+AP96 -> 0 | AS96: REV02-IBS REV | AY96: =IF(AQ96>AU96,AQ96-AU96,"0") -> 105 | AZ96: =IF(AR96>AV96,AR96-AV96,"0") -> 0 | BB96: ? | BC96: Tam Đa | BD96: ELBOW 90˚ LRDN32EN 10253Ø42.2 x 2.6mmP 235GH = 105PCS | BF96: N/A | BH96: 105 | BI96: N/A | BJ96: 26500 | BK96: =BJ96*BH96*1.1 -> 3060750 | BL96: =(BK96-BM96)/BM96 -> 0.1 | BM96: =BJ96*BH96*1 -> 2782500 | BN96: 45968 | BO96: =SUMIF($I:$I,I96,$BH:$BH) -> 105 | BP96: =SUMIF($I:$I,I96,$BI:$BI) -> 0 | CM96: =SUMIF($I:$I,I96,$CA:$CA) -> 0 | CN96: =SUMIF($I:$I,I96,$CB:$CB) -> 0 | CS96: =BO96+CM96 -> 105 | CT96: =BP96+CN96 -> 0 | CU96: =AY96-CS96 -> 0 | CV96: =AZ96-CT96 -> 0 | CW96: =IF(CU96<0,"Thừa",IF(CU96=0,"Đủ","Thiếu")) -> Đủ
A97: =IF(I97=I96,"ok","Hiện") -> Hiện | B97: =CW97 -> Đủ | C97: =CU97 -> 0 | F97: Tổ hợp | I97: I97-VTC01-050 | J97: thép hình L | K97: L150X150X19 | L97: SS400 | M97: m | N97: 41.9 | O97: 74.54 | P97: 3123 | U97: 79.7578 | V97: 3341.8518 | W97: 0 | X97: 0 | Y97: -79.7578 | Z97: -3341.8518 | AG97: 0 | AH97: 0 | AK97: 0 | AL97: 0 | AM97: 0 | AN97: 0 | AO97: 0 | AP97: 0 | AQ97: =Q97+S97+U97+W97+Y97+AA97+AC97+AE97+AG97+AI97+AK97+AM97+AO97 -> 0 | AR97: =R97+T97+V97+X97+Z97+AB97+AD97+AF97+AH97+AJ97+AL97+AN97+AP97 -> 0 | AS97: REV04-IBS REV CHUYỂN TỔ HỢP | AY97: =IF(AQ97>AU97,AQ97-AU97,"0") -> 0 | AZ97: =IF(AR97>AV97,AR97-AV97,"0") -> 0 | BO97: =SUMIF($I:$I,I97,$BH:$BH) -> 0 | BP97: =SUMIF($I:$I,I97,$BI:$BI) -> 0 | CM97: =SUMIF($I:$I,I97,$CA:$CA) -> 0 | CN97: =SUMIF($I:$I,I97,$CB:$CB) -> 0 | CS97: =BO97+CM97 -> 0 | CT97: =BP97+CN97 -> 0 | CU97: =AY97-CS97 -> 0 | CV97: =AZ97-CT97 -> 0 | CW97: =IF(CU97<0,"Thừa",IF(CU97=0,"Đủ","Thiếu")) -> Đủ
A98: =IF(I98=I97,"ok","Hiện") -> Hiện | B98: =CW98 -> Đủ | C98: =CU98 -> 0 | D98: L50X50X6 | F98: Ngọc hiếu/ hàng đã về | I98: I97-VTC01-051 | J98: thép hình L | K98: L50X50X6 | L98: SS400 | M98: m | N98: 4.43 | O98: 89.88 | P98: 397 | U98: 96.1716 | V98: 426.04019 | W98: 0 | X98: 0 | Y98: 0 | Z98: 0 | AG98: 0 | AH98: 0 | AK98: 0 | AL98: 0 | AM98: 0 | AN98: 0 | AO98: 23.8284 | AP98: 105.55981 | AQ98: =Q98+S98+U98+W98+Y98+AA98+AC98+AE98+AG98+AI98+AK98+AM98+AO98 -> 120 | AR98: =R98+T98+V98+X98+Z98+AB98+AD98+AF98+AH98+AJ98+AL98+AN98+AP98 -> 531.6 | AS98: REV12-IBS REV | AY98: =IF(AQ98>AU98,AQ98-AU98,"0") -> 120 | AZ98: =IF(AR98>AV98,AR98-AV98,"0") -> 531.6 | BB98: 1510-2025/HĐKT/NH-IBS | BC98: Ngọc Hiếu | BD98: Thép V50*50*6*6000 = 7 Cây | BE98: SS400 | BF98: 188 | BG98: 45945 | BH98: 42 | BI98: 188 | BJ98: 13909.09 | BK98: =BJ98*BI98*1.1 -> 2876399.8 | BL98: =(BK98-BM98)/BM98 -> 0.1 | BM98: =BJ98*BI98*1 -> 2614908.9 | BN98: 45954 | BO98: =SUMIF($I:$I,I98,$BH:$BH) -> 120 | BP98: =SUMIF($I:$I,I98,$BI:$BI) -> 533 | CM98: =SUMIF($I:$I,I98,$CA:$CA) -> 0 | CN98: =SUMIF($I:$I,I98,$CB:$CB) -> 0 | CS98: =BO98+CM98 -> 120 | CT98: =BP98+CN98 -> 533 | CU98: =AY98-CS98 -> 0 | CV98: =AZ98-CT98 -> -1.4 | CW98: =IF(CU98<0,"Thừa",IF(CU98=0,"Đủ","Thiếu")) -> Đủ
A99: =IF(I99=I98,"ok","Hiện") -> ok | I99: I97-VTC01-051 | J99: thép hình L | K99: L50X50X6 | L99: SS400 | M99: m | BB99: Báo giá ngày 12/2/2026 | BC99: Ngọc Hiếu | BD99: Thép V50*50*6*6000 = 4 Cây | BE99: SS400 | BF99: 106 | BG99: 46065 | BH99: 24 | BI99: 106 | BJ99: 14000 | BK99: =BJ99*BI99*1.1 -> 1632400 | BL99: =(BK99-BM99)/BM99 -> 0.1 | BM99: =BJ99*BI99*1 -> 1484000 | BN99: 46065
A100: =IF(I100=I99,"ok","Hiện") -> ok | I100: I97-VTC01-051 | J100: thép hình L | K100: L50X50X6 | L100: SS400 | M100: m | BB100: 1912-2025/HĐKT/NH-IBS | BC100: Ngọc Hiếu | BD100: Thép V50*50*6*6000 ( 9 cây) | BE100: SS400 | BF100: 239 | BG100: 46010 | BH100: 54 | BI100: 239 | BJ100: 13909.09 | BK100: =BJ100*BI100*(1+BL100) -> 3656699.8 | BL100: 0.1 | BM100: =BJ100*BI100 -> 3324272.5 | BN100: 46036
...

Sheet Tổng hợp
A1: Item/ STT | B1: Total Ordered/Tổng dự trù | D1: Tận dụng tồn kho/ Remain | G1: Khối lượng phải mua sắm/ total order | I1: VẬT TƯ TRONG NƯỚC | L1: VẬT TƯ OVERSEA | O1: Khối lượng phải mua còn lại theo PR/ total order from PR | Q1: Khối lượng phải mua còn lại/ total order
B2: Q.Ty/S.Lượng (M/M2/Set) | C2: Weight/K.Lượng (Kg) | D2: Q.Ty/S.Lượng (M/M2/Set) | E2: Weight/K.Lượng (Kg) | F2: Đã nghiệm thu (Kg) | G2: Q.Ty/ S.Lượng | H2: Weight/ K.Lượng (Kg) | I2: S.Lượng giao hàng thực tế/ Handover Q'ty | J2: K.Lượng giao hàng thực tế// Handover weight | K2: Khối lượng nghiệm thu đạt/ Weight Acc. Inspection | L2: S.Lượng giao hàng thực tế/ Handover Q'ty | M2: K.Lượng giao hàng thực tế// Handover weight | N2: Khối lượng nghiệm thu đạt/ Weight Acc. Inspection | O2: Q.Ty/S.Lượng (M/M2/Set) | P2: Weight/ K.Lượng (Kg) | Q2: Q.Ty/S.Lượng (M/M2/Set) | R2: Weight/ K.Lượng (Kg)
A3: VTC01 | B3: Main-Material / Vật tư chính thép đen
A4: 1 | B4: ='25-WNC-I-097'!AQ7 -> 7442.1193 | C4: ='25-WNC-I-097'!AR7 -> 178328.59 | D4: ='25-WNC-I-097'!AU7 -> 304.2928 | E4: ='25-WNC-I-097'!AV7 -> 3634.4786 | F4: =E4 -> 3634.4786 | G4: ='25-WNC-I-097'!AY7 -> 7137.8265 | H4: ='25-WNC-I-097'!AZ7 -> 174694.12 | I4: ='25-WNC-I-097'!BO7 -> 7420.1214 | J4: ='25-WNC-I-097'!BP7 -> 175393.34 | K4: ='25-WNC-I-097'!BS7 -> 0 | L4: ='25-WNC-I-097'!CM7 -> 732 | M4: ='25-WNC-I-097'!CN7 -> 11386 | N4: ='25-WNC-I-097'!CQ7 -> 0 | O4: =B4-I4-L4 -> -710.00213 | P4: =C4-J4-M4 -> -8450.7401 | Q4: ='25-WNC-I-097'!CU7 -> -794.29493 | R4: ='25-WNC-I-097'!CV7 -> -12085.219
A5: VTC02 | B5: Main-Material / Vật tư chính thép trắng
A6: 1 | B6: ='25-WNC-I-097'!AQ122 -> 0 | C6: ='25-WNC-I-097'!AR122 -> 0 | D6: ='25-WNC-I-097'!AU122 -> 0 | E6: ='25-WNC-I-097'!AV122 -> 0 | F6: =E6 -> 0 | G6: ='25-WNC-I-097'!AY122 -> 0 | H6: ='25-WNC-I-097'!AZ122 -> 0 | I6: ='25-WNC-I-097'!BO122 -> 0 | J6: ='25-WNC-I-097'!BP122 -> 0 | K6: ='25-WNC-I-097'!BS122 -> 0 | L6: ='25-WNC-I-097'!CM122 -> 0 | M6: ='25-WNC-I-097'!CN122 -> 0 | N6: ='25-WNC-I-097'!CQ122 -> 0 | O6: =B6-I6-L6 -> 0 | P6: =C6-J6-M6 -> 0 | Q6: ='25-WNC-I-097'!CU122 -> 0 | R6: ='25-WNC-I-097'!CV122 -> 0
A7: VTC03 | B7: Gratting-Material / Vật tư gratting
A8: 1 | B8: ='25-WNC-I-097'!AQ125 -> 823.04681 | C8: ='25-WNC-I-097'!AR125 -> 2990.0076 | D8: ='25-WNC-I-097'!AU125 -> 0 | E8: ='25-WNC-I-097'!AV125 -> 0 | F8: =E8 -> 0 | G8: ='25-WNC-I-097'!AY125 -> 823.04681 | H8: ='25-WNC-I-097'!AZ125 -> 2990.0076 | I8: ='25-WNC-I-097'!BO125 -> 470 | J8: ='25-WNC-I-097'!BP125 -> 3622 | K8: ='25-WNC-I-097'!BS125 -> 0 | L8: ='25-WNC-I-097'!CM125 -> 0 | M8: ='25-WNC-I-097'!CN125 -> 0 | N8: ='25-WNC-I-097'!CQ125 -> 0 | O8: =B8-I8-L8 -> 353.04681 | P8: =C8-J8-M8 -> -631.9924 | Q8: ='25-WNC-I-097'!CU125 -> 353.04681 | R8: ='25-WNC-I-097'!CV125 -> -631.9924
A9: VTC04 | B9: Insulation-Material / Vật tư bảo ôn
A10: 1 | B10: ='25-WNC-I-097'!AQ130 -> 90.5 | C10: ='25-WNC-I-097'!AR130 -> 9050 | D10: ='25-WNC-I-097'!AU130 -> 0 | E10: ='25-WNC-I-097'!AV130 -> 0 | F10: =E10 -> 0 | G10: ='25-WNC-I-097'!AY130 -> 90.5 | H10: ='25-WNC-I-097'!AZ130 -> 9050 | I10: ='25-WNC-I-097'!BO130 -> 90.8928 | J10: ='25-WNC-I-097'!BP130 -> 0 | K10: ='25-WNC-I-097'!BS130 -> 0 | L10: ='25-WNC-I-097'!CM130 -> 0 | M10: ='25-WNC-I-097'!CN130 -> 0 | N10: ='25-WNC-I-097'!CQ130 -> 0 | O10: =B10-I10-L10 -> -0.3928 | P10: =C10-J10-M10 -> 9050 | Q10: ='25-WNC-I-097'!CU130 -> -0.3928 | R10: ='25-WNC-I-097'!CV130 -> 9050
A11: VPK | B11: Bolt-Material / Vật tư bulong, phụ kiện
A12: 1 | B12: ='25-WNC-I-097'!AQ137 -> 48970 | C12: ='25-WNC-I-097'!AR137 -> 0 | D12: ='25-WNC-I-097'!AU137 -> 0 | E12: ='25-WNC-I-097'!AV137 -> 0 | F12: =E12 -> 0 | G12: ='25-WNC-I-097'!AY137 -> 48970 | H12: ='25-WNC-I-097'!AZ137 -> 0 | I12: ='25-WNC-I-097'!BO137 -> 49585 | J12: ='25-WNC-I-097'!BP137 -> 0 | K12: ='25-WNC-I-097'!BS137 -> 0 | L12: ='25-WNC-I-097'!CM137 -> 0 | M12: ='25-WNC-I-097'!CN137 -> 0 | N12: ='25-WNC-I-097'!CQ137 -> 0 | O12: =B12-I12-L12 -> -615 | P12: =C12-J12-M12 -> 0 | Q12: ='25-WNC-I-097'!CU137 -> -615 | R12: ='25-WNC-I-097'!CV137 -> 0
A13: VTK | B13: Packing Material / Vật tư kiện
A14: 1 | B14: ='25-WNC-I-097'!AQ310 -> 12558.274 | C14: ='25-WNC-I-097'!AR310 -> 24635.757 | D14: ='25-WNC-I-097'!AU310 -> 139.834 | E14: ='25-WNC-I-097'!AV310 -> 939.96862 | F14: =E14 -> 939.96862 | G14: ='25-WNC-I-097'!AY310 -> 12418.44 | H14: ='25-WNC-I-097'!AZ310 -> 23695.789 | I14: ='25-WNC-I-097'!BO310 -> 12576.902 | J14: ='25-WNC-I-097'!BP310 -> 23146.8 | K14: ='25-WNC-I-097'!BS310 -> 0 | L14: ='25-WNC-I-097'!CM310 -> 0 | M14: ='25-WNC-I-097'!CN310 -> 0 | N14: ='25-WNC-I-097'!CQ310 -> 0 | O14: =B14-I14-L14 -> -18.6272 | P14: =C14-J14-M14 -> 1488.9572 | Q14: ='25-WNC-I-097'!CU310 -> -158.4612 | R14: ='25-WNC-I-097'!CV310 -> 548.98858
A17: STT/ No. | B17: Dự án/ Hạng mục/ Project/ Items | C17: Thiết kế, Dự toán/ Design, Estimation | F17: Mua sắm/ Ordered, Puchased (Đến hiện tại/ Up to now) | K17: Tổng Giá trị mua thêm/ Total Cost (VND)
F18: Hàng mua thêm | H18: Hàng tồn
C19: Khối lượng/ Weight (Kg) | D19: Số lượng/ Q'ty (M/M2//PSC) | E19: Tổng Giá trị/ Total Cost (VND) | F19: Khối lượng/ Weight (Kg) | G19: Số lượng/ Q'ty (M/M2//PSC) | H19: Khối lượng/ Weight (Kg/N/A) Materials available at the factory | I19: Số lượng/ Q'ty (M/M2/PSC) Materials available at the factory | J19: Tổng Giá trị mua thêm/ Total Cost (VND) | K19: DỰ TOÁN (VNĐ) | L19: GIÁ TRỊ ĐÃ ĐẶT HÀNG THÊM (VNĐ) | M19: Chênh lệch/ Diff. (VND) | N19: Ghi chú/ Remarks
A20: VTC01 | B20: Main-Material / Vật tư chính thép đen | C20: =C4 -> 178328.59 | D20: =B4 -> 7442.1193 | F20: =J4+M4 -> 186779.34 | G20: =I4+L4 -> 8152.1214 | H20: =E4 -> 3634.4786 | I20: =D4 -> 304.2928 | J20: ='25-WNC-I-097'!BM7+'25-WNC-I-097'!CD7*27000 -> 3.0852474e+09 | K20: ='DT04 (TM) 1 '!L7 -> 3001944110 | M20: =K20-J20-L20 -> -83303310 | N20: =IF(M20<0,"VƯỢT DỰ TOÁN","ĐẢM BẢO") -> VƯỢT DỰ TOÁN
A21: VTC02 | B21: Main-Material / Vật tư chính thép trắng | C21: =C6 -> 0 | D21: =B6 -> 0 | F21: =J6+M6 -> 0 | G21: =I6+L6 -> 0 | H21: =E6 -> 0 | I21: =D6 -> 0 | J21: ='25-WNC-I-097'!BM122+'25-WNC-I-097'!CD122*27000 -> 0 | M21: =K21-J21-L21 -> 0 | N21: =IF(M21<0,"VƯỢT DỰ TOÁN","ĐẢM BẢO") -> ĐẢM BẢO
A22: VTC03 | B22: Gratting-Material / Vật tư gratting | C22: =C8 -> 2990.0076 | D22: =B8 -> 823.04681 | F22: =J8+M8 -> 3622 | G22: =I8+L8 -> 470 | H22: =E8 -> 0 | I22: =D8 -> 0 | J22: ='25-WNC-I-097'!BM125+'25-WNC-I-097'!CD125*27000 -> 165851000 | K22: ='DT04 (TM) 1 '!L17 -> 195865000 | M22: =K22-J22-L22 -> 30014000 | N22: =IF(M22<0,"VƯỢT DỰ TOÁN","ĐẢM BẢO") -> ĐẢM BẢO
A23: VTC04 | B23: Insulation-Material / Vật tư bảo ôn | C23: =C10 -> 9050 | D23: =B10 -> 90.5 | F23: =J10+M10 -> 0 | G23: =I10+L10 -> 90.8928 | H23: =E10 -> 0 | I23: =D10 -> 0 | J23: ='25-WNC-I-097'!BM130+'25-WNC-I-097'!CD130*27000 -> 2.0585973e+08 | K23: ='DT04 (TM) 1 '!L20 -> 1.9069559e+08 | M23: =K23-J23-L23 -> -15164139 | N23: =IF(M23<0,"VƯỢT DỰ TOÁN","ĐẢM BẢO") -> VƯỢT DỰ TOÁN
A24: VPK | B24: Bolt-Material / Vật tư bulong, phụ kiện | C24: =C12 -> 0 | D24: =B12 -> 48970 | F24: =J12+M12 -> 0 | G24: =I12+L12 -> 49585 | H24: =E12 -> 0 | I24: =D12 -> 0 | J24: ='25-WNC-I-097'!BM137+'25-WNC-I-097'!CD137*27000 -> 202484525 | K24: ='DT04 (TM) 1 '!L23 -> 213600000 | M24: =K24-J24-L24 -> 11115475 | N24: =IF(M24<0,"VƯỢT DỰ TOÁN","ĐẢM BẢO") -> ĐẢM BẢO
A25: VTK | B25: Packing Material / Vật tư kiện | C25: =C14 -> 24635.757 | D25: =B14 -> 12558.274 | F25: =J14+M14 -> 23146.8 | G25: =I14+L14 -> 12576.902 | H25: =E14 -> 939.96862 | I25: =D14 -> 139.834 | J25: ='25-WNC-I-097'!BM310+'25-WNC-I-097'!CD310*27000 -> 7.9502514e+08 | K25: ='DT04 (TM) 1 '!L28 -> 503250000 | M25: =K25-J25-L25 -> -2.9177514e+08 | N25: =IF(M25<0,"VƯỢT DỰ TOÁN","ĐẢM BẢO") -> VƯỢT DỰ TOÁN

Sheet Quang thịnh
A1: BID ANALYSIS - GIẢI TRÌNH MUA SẮM/ĐẤU THẦU
A3: Project | B3: PROJECT No/ Dự án: 25-WNC-I-097
A4: Dự án
A5: Subject | B5: Cung cấp vật tư đóng kiện
A6: Chủ đề
A8: No. | B8: CONTENT | C8: Phạm vi công việc | G8: Dự toán | J8: Đã mua | K8: Đơn vị cung cấp chào giá phần còn lại (VNĐ) | N8: Đơn vị cung cấp chào giá phần còn lại (VNĐ) | Q8: Ghi chú
A9: Item | B9: Description/ Chi tiết | C9: Profile/ Vật tư | D9: Số lượng Mua (Cây) | E9: Số lượng Mua (M) | F9: Số lượng PR (M) | G9: Khối lượng/ Số lượng | H9: Đơn giá (vnd) | I9: Thành tiền (vnd) | J9: Thành tiền (vnd) | K9: QUANG THỊNH PHAT | N9: TITAN
K10: Phạm vi | L10: Đơn giá trước VAT (VNĐ/KG) | M10: Thành Tiền | N10: Phạm vi | O10: Đơn giá trước VAT (VNĐ/KG) | P10: Thành Tiền
A11: Tổng | B11: ='25-WNC-I-097'!J310 -> Packing Material / Vật tư kiện | G11: N/A | H11: N/A | I11: ='DT04 (TM) 1 '!L28 -> 503250000 | J11: ='25-WNC-I-097'!BM310 -> 7.9502514e+08 | M11: =SUM(M12:M18) -> 197997313 | Q11: =I11-J11-P11-M11 -> -4.8977245e+08
A12: I97-VDK-020 | B12: RHS100X50X4 | C12: Thép hộp đen 50 x 100 x 4,0 x 6.000 mm | D12: 97 | E12: 582 | F12: 577.7 | G12: N/A | H12: N/A | I12: N/A | J12: N/A | K12: V | L12: 15454.55 | M12: 79297296 | N12: V | O12: =18800/1.1 -> 17090.909 | P12: N//A | Q12: Chọn Quang Thịnh Phát
A13: I97-VDK-021 | B13: RHS150X75X4 | C13: Thép hộp đen 75 x 150 x 3,5 x 6.000 mm | D13: 35 | E13: 210 | F13: 208.767 | G13: N/A | H13: N/A | I13: N/A | J13: N/A | K13: V | L13: 16818.18 | M13: 42045450 | N13: V | O13: =18800/1.1 -> 17090.909 | P13: N//A | Q13: Chọn Quang Thịnh Phát
A14: I97-VDK-022 | B14: RHS50X25X2.5 | C14: Thép hộp đen 25 x 50 x 2,5 x 6.000 mm | D14: 41 | E14: 246 | F14: 1447.5996 | G14: N/A | H14: N/A | I14: N/A | J14: N/A | K14: V | L14: 15454.55 | M14: 10292730 | N14: V | O14: =17800/1.1 -> 16181.818 | P14: N//A | Q14: Chọn Quang Thịnh Phát
C15: Thép hộp đen 25 x 50 x 2,3 x 6.000 mm | D15: 124 | E15: 744 | G15: N/A | H15: N/A | I15: N/A | J15: N/A | K15: V | L15: 15454.55 | M15: 28838190 | N15: V | O15: =17800/1.1 -> 16181.818 | P15: N//A | Q15: Chọn Quang Thịnh Phát
C16: Thép hộp đen 25 x 50 x 2,0 x 6.000 mm | D16: 77 | E16: 462 | G16: N/A | H16: N/A | I16: N/A | J16: N/A | K16: V | L16: 15454.55 | M16: 15732732 | N16: V | O16: =17800/1.1 -> 16181.818 | P16: N//A | Q16: Chọn Quang Thịnh Phát
A17: I97-VDK-023 | B17: RHS60X30X3 | C17: Thép hộp đen 30 x 60 x 3,0 x 6.000 mm | D17: 34 | E17: 204 | F17: 367.5444 | G17: N/A | H17: N/A | I17: N/A | J17: N/A | K17: V | L17: 15454.55 | M17: 12286367 | N17: V | O17: =17800/1.1 -> 16181.818 | P17: N//A | Q17: Chọn Quang Thịnh Phát
C18: Thép hộp đen 30 x 60 x 2,8 x 6.000 mm | D18: 28 | E18: 168 | G18: N/A | H18: N/A | I18: N/A | J18: N/A | K18: V | L18: 15454.55 | M18: 9504548 | N18: V | O18: =17800/1.1 -> 16181.818 | P18: N//A | Q18: Chọn Quang Thịnh Phát
B19: Xếp hạng | L19: 1 | O19: 2
A20: Ghi chú: Tiếp tục công tác mua sắm để đảm báo tiến độ
A21: NGƯỜI ĐỀ NGHỊ/ RECOMMENDATION BY: | E21: NGƯỜI KIỂM TRA/ DEPARTMENT HEAD CHECK BY: | J21: APPROVED BY: PHÊ DUYỆT
J22: Nguyễn Quang Vinh | M22: Hoàng Ngọc Bằng | P22: Đoàn Văn Toàn

Sheet Sheet1
A1: I97-VTC03-001-LIST GRATTING ĐẶT HÀNG
H3: =+SUM(H5:H32) -> 160 | J3: =+SUM(J5:J32) -> 2897.1475
A4: No. | B4: ITEM | C4: GRARTING NAME | D4: SỐ LƯỢNG/ 1 UNIT | E4: SỐ LƯỢNG BỘ | F4: WIDTH(mm) | G4: Length(mm) | H4: TỔNG SỐ LƯỢNG( TẤM) | I4: UNIT WEIGHT(KG) | J4: T' WEIGHT(KG)
A5: 1 | B5: 325022 | C5: I97-022-130_022 | D5: 1 | E5: 5 | F5: 820 | G5: 899 | H5: =+D5*E5 -> 5 | I5: 18.7 | J5: =+I5*H5 -> 93.5 | K5: =CONCATENATE(C5," = ",H5," Tấm") -> I97-022-130_022 = 5 Tấm | N5: Đã về ngày 1710/2025
A6: 2 | B6: 325022 | C6: I97-022-130_023 | D6: 1 | E6: 5 | F6: 434.5 | G6: 700 | H6: =+D6*E6 -> 5 | I6: 7.7 | J6: =+I6*H6 -> 38.5 | K6: =CONCATENATE(C6," = ",H6," Tấm") -> I97-022-130_023 = 5 Tấm | N6: Đã về ngày 1710/2025
A7: 3 | B7: 325024 | C7: I97-024-131_9 | D7: 2 | E7: 5 | F7: 550 | G7: 974 | H7: =+D7*E7 -> 10 | I7: 15.26745 | J7: =+I7*H7 -> 152.6745 | K7: =CONCATENATE(C7," = ",H7," Tấm") -> I97-024-131_9 = 10 Tấm | N7: Đã về ngày 1710/2025
A8: 4 | B8: 325024 | C8: I97-024-131_10 | D8: 1 | E8: 5 | F8: 550 | G8: 715 | H8: =+D8*E8 -> 5 | I8: 11.207625 | J8: =+I8*H8 -> 56.038125 | K8: =CONCATENATE(C8," = ",H8," Tấm") -> I97-024-131_10 = 5 Tấm | N8: Đã về ngày 1710/2025
A9: 5 | B9: 325024 | C9: I97-024-131_11 | D9: 1 | E9: 5 | F9: 555 | G9: 665 | H9: =+D9*E9 -> 5 | I9: 10.423875 | J9: =+I9*H9 -> 52.119375 | K9: =CONCATENATE(C9," = ",H9," Tấm") -> I97-024-131_11 = 5 Tấm | N9: Đã về ngày 1710/2025
A10: 6 | B10: 325024 | C10: I97-024-131_12 | D10: 4 | E10: 5 | F10: 253 | G10: 550 | H10: =+D10*E10 -> 20 | I10: 3.965775 | J10: =+I10*H10 -> 79.3155 | K10: =CONCATENATE(C10," = ",H10," Tấm") -> I97-024-131_12 = 20 Tấm | N10: Đã về ngày 1710/2025
A11: 7 | B11: 325031 | C11: I97-031-110_005 | D11: 1 | E11: 5 | F11: 628 | G11: =378.5+6+164+60+245+60+51.5 -> 965 | H11: =+D11*E11 -> 5 | I11: 28.7 | J11: =+I11*H11 -> 143.5
A12: 8 | B12: 325031 | C12: I97-031-110_006 | D12: 1 | E12: 5 | F12: 488.5 | G12: 528.5 | H12: =+D12*E12 -> 5 | I12: 12.8 | J12: =+I12*H12 -> 64
A13: 9 | B13: 325031 | C13: I97-031-110_007 | D13: 1 | E13: 5 | F13: 559.5 | G13: 1185 | H13: =+D13*E13 -> 5 | I13: 24 | J13: =+I13*H13 -> 120
A14: 10 | B14: 325031 | C14: I97-031-110_008 | D14: 1 | E14: 5 | F14: 628 | G14: 803.5 | H14: =+D14*E14 -> 5 | I14: 20.4 | J14: =+I14*H14 -> 102
A15: 11 | B15: 325031 | C15: I97-031-110_009 | D15: 1 | E15: 5 | F15: 631.5 | G15: 691.5 | H15: =+D15*E15 -> 5 | I15: 15.5 | J15: =+I15*H15 -> 77.5
A16: 12 | B16: 325031 | C16: I97-031-110_010 | D16: 1 | E16: 5 | F16: 323.5 | G16: 441 | H16: =+D16*E16 -> 5 | I16: 5.9 | J16: =+I16*H16 -> 29.5
A17: 13 | B17: 325031 | C17: I97-031-110_011 | D17: 1 | E17: 5 | F17: 776.5 | G17: 1100 | H17: =+D17*E17 -> 5 | I17: 24 | J17: =+I17*H17 -> 120
A18: 14 | B18: 325031 | C18: I97-031-110_012 | D18: 1 | E18: 5 | F18: 724.5 | G18: 1110.5 | H18: =+D18*E18 -> 5 | I18: 26.7 | J18: =+I18*H18 -> 133.5
A19: 15 | B19: 325031 | C19: I97-031-110_013 | D19: 1 | E19: 5 | F19: 641.5 | G19: 1082 | H19: =+D19*E19 -> 5 | I19: 21.3 | J19: =+I19*H19 -> 106.5
A20: 16 | B20: 325031 | C20: I97-031-110_014 | D20: 1 | E20: 5 | F20: 1005.5 | G20: 1244 | H20: =+D20*E20 -> 5 | I20: 39.5 | J20: =+I20*H20 -> 197.5
A21: 17 | B21: 325031 | C21: I97-031-110_015 | D21: 1 | E21: 5 | F21: 649 | G21: 1122 | H21: =+D21*E21 -> 5 | I21: 24 | J21: =+I21*H21 -> 120
A22: 18 | B22: 325031 | C22: I97-031-110_037 | D22: 1 | E22: 5 | F22: 559.5 | G22: 1185 | H22: =+D22*E22 -> 5 | I22: 24 | J22: =+I22*H22 -> 120
A23: 19 | B23: 325031 | C23: I97-031-110_038 | D23: 1 | E23: 5 | F23: 628.5 | G23: 964.5 | H23: =+D23*E23 -> 5 | I23: 28.7 | J23: =+I23*H23 -> 143.5
... A32: 28 | B32: 325031 | C32: I97-031-110_047 | D32: 1 | E32: 5 | F32: 323.5 | G32: 441 | H32: =+D32*E32 -> 5 | I32: 5.9 | J32: =+I32*H32 -> 29.5

Sheet SO SÁNH
A1: ĐÁNH GIÁ PHẦN VIỆC ĐÃ VƯỢT QUÁ DỰ TOÁN
B2: STT | C2: THIẾT KẾ | G2: DỰ TOÁN | I2: =UPPER("Mua dự kiến") -> MUA DỰ KIẾN | K2: GIÁ TRỊ VƯỢT QUÁ
G3: KL | H3: Giá trị | I3: KL | J3: Giá trị (Chưa tính VAT)
A5: VTC04 | B5: Insulation-Material / Vật tư bảo ôn | C5: ='Tổng hợp'!D23 -> 90.5 | D5: M3 | E5: ='Tổng hợp'!C23 -> 9050 | F5: Kg | H5: ='DT04 (TM) 1 '!L20 -> 1.9069559e+08 | I5: ='Tổng hợp'!G23 -> 90.8928 | J5: ='Tổng hợp'!J23/1.08 -> 1.9061086e+08 | K5: =J5-H5 -> -84729.248
A6: VTC01 | B6: Main-Material / Vật tư chính thép đen | C6: ='Tổng hợp'!D20 -> 7442.1193 | D6: M/M2 | E6: ='Tổng hợp'!C20 -> 178328.59 | F6: Kg | H6: ='DT04 (TM) 1 '!L7 -> 3001944110 | J6: ='Tổng hợp'!J20/1.1+'25-WNC-I-097'!#REF!/1.1 -> #REF! | K6: =J6-H6 -> #REF!
A10: Ý kiến của sale: 101,343.39 kg x 20,975 = 2,125,677,643 VNĐ. Tổng giá trị vật tư bao gồm cả tai cẩu = 2,600,957,643 VNĐ.
A11: Kết luận:
A12: Nguồn Vốn:
A13: Ảnh Hưởng:
A14: Đề Nghị | B14: Cho Mua sắm tiếp theo để đáp ứng tiến độ

Sheet Sàn winwin
A1: CỘNG HÒA XÃ HỘI CHỦ NGHĨA VIỆT NAM
A2: Độc lập - Tự do - Hạnh phúc
A4: BIÊN BẢN QUYẾT TOÁN GIÁ TRỊ
A5: ( V/v: Cung cấp tấm sàn Grating Mạ Kẽm Nhúng Nóng và phụ kiện)
A7: Căn cứ hợp đồng nguyên tắc số: 01/2025-IBSWWHD ký ngày 01 tháng 01 năm 2025, báo giá số 110925 - IBSWWHD và Biên bản giao nhận hàng hóa ngày …... tháng ……. năm 2025 giữa Công ty Cổ phần Công Nghiệp Nặng IBS và Công ty Cổ phần WinWin HD.
A9: Hôm nay; ngày ………………….. tại Công ty Cổ phần WinWin HD chúng tôi gồm:
A10: Đại diện Bên Mua ( Bên A): CÔNG TY CỔ PHẦN CÔNG NGHIỆP NẶNG IBS
B11: Ông: | G11: Chức vụ: …………..
B12: Ông: | G12: Chức vụ: ………….
A13: Mã số thuế: 0801224033 | B13: Mã số thuế: | D13: 0107923145
B14: Địa chỉ: Km6, Quốc lộ 5, Phường Hồng Bàng, Thành phố Hải Phòng, Việt Nam
A15: Đại diện Bên Bán ( Bên B): CÔNG TY CỔ PHẦN WINWIN HD
B16: Ông: Hoàng Văn Trung | G16: Chức vụ: Giám Đốc
B17: Ông: | G17: Chức vụ:
B18: Mã số thuế: | D18: 0801351835
B19: Tài khoản số: | D19: 6666836566668 | E19: Tại Ngân hàng Cổ phần Quân Đội - Chi Nhánh Hải Dương
B20: Địa chỉ: Số nhà 10, Ngõ 207 Đường Quang Trung, Phường Thành Đông, Thành Phố Hải Phòng, Việt Nam.
A21: Hai bên cùng nhau quyết toán giá trị cung cấp Tấm sàn, Bậc cầu thang (Grating) mạ kẽm nhúng nóng của Công ty Cổ phần Winwin HD thực hiện cho Công ty Cổ phần Công Nghiệp Nặng IBS cụ thể như sau:
A24: STT | B24: Tên hàng hóa | E24: Khối lượng tổng (Kg/ bộ) | F24: Đơn giá (Đ/Kg, bộ) | G24: Thành tiền | H24: Ghi chú
A25: 1 | B25: Tấm sàn (Grating): Serrated bearing bar 32x3 -Pitch 34, Cross bar 6x6 - Pitch 38. | E25: =+'[117]Biên bản TH nghiệm thu.'!F24 -> 3622 | F25: 43000 | G25: =F25*E25 -> 155746000
A26: 2 | B26: Kẹp sàn Grating (loại SY) | E26: =+'[117]Biên bản TH nghiệm thu.'!E25 -> 235 | F26: 20000 | G26: =F26*E26 -> 4700000
A27: A | B27: Cộng | G27: =SUM(G25:G26) -> 160446000
A28: B | B28: Thuế VAT 10% | G28: =G27*10% -> 16044600
A29: C | B29: Tổng tiền | G29: =+G27+G28 -> 176490600
A30: Bằng chữ: Một trăm sáu mươi chín triệu không trăm linh tư nghìn đồng chẵn.
A31: Biên bản được lập thành 04 bản, mỗi bên giữ 02 bản làm cơ sở thanh quyết toán.
A33: CÔNG TY CỔ PHẦN CÔNG NGHIỆP NẶNG IBS | G33: CÔNG TY CỔ PHẦN WINWIN HD

Sheet VSAN
F1: CÔNG TY TNHH VSAN / VSAN COMPANY LTD
F2: STK: 31092.88888 Ngân hàng TMCP Á Châu (ACB) – CN Duyên Hải.
M3: Số: | N3: 97.2VSA2025
M4: Ngày : | N4: 07-10-2025
B5: Địa chỉ: Số 19/152 Phủ Thượng Đoạn, Phường Ngô Quyền, Thành phố Hải Phòng, Việt Nam.
B6: Điện thoại : (+84) 2256.25.38.39 - Email: vsanfasteners@gmail.com - website: www.vsanvina.com
B7: Add: No. 19/152 Phu Thuong Doan, Ngo Quyen Ward, Hai Phong City, Vietnam.
B8: Tel: (+84) 2256.25.38.39 - Email: vsanfasteners@gmail.com - website: www.vsanvina.com
B10: BẢNG BÁO GIÁ
B11: Kính gửi: CÔNG TY CỔ PHẦN CÔNG NGHIỆP NẶNG IBS
B12: Địa chỉ: Km6, Quốc lộ 5, Phường Hồng Bàng, Thành phố Hải Phòng, Việt Nam.
B13: ĐT: | L13: Fax:
B14: Công ty Chúng tôi xin gửi tới Quý Công ty lời chào trân trọng!
B15: Theo nhu cầu của Quý Công ty, chúng tôi xin báo giá hàng như sau:
C16: Yêu cầu | F16: Đề xuất | M16: 97.2
B17: Item | C17: Description/ Chi tiết | D17: Profile/ Vật tư | E17: Grade/ Mác vật liệu | F17: Mặt hàng | G17: Tiêu chuẩn | H17: Cấp bền | I17: Cấp bền/ lớp mạ/ Vật liệu | K17: ĐVT | L17: Số lượng | M17: Đơn giá (VND) | N17: Thành tiền (VND) | O17: Thuế VAT | P17: Tổng | Q17: % Thuế | R17: Ghi chú | S17: Số lượng đợt 97.2 chốt
B18: I97-VPK-003 | C18: nut | D18: Square nut-M8-DIN562 | E18: DIN562 | F18: Ecu vuông M8 | I18: HDG | K18: Cái | L18: 24 | M18: 2000 | N18: =M18*L18 -> 48000 | O18: =Q18*N18 -> 4800 | P18: =O18+N18 -> 52800 | Q18: 0.1 | S18: =VLOOKUP(B18,'[118]25-WNC-I-097'!$I:$P,8,0) -> 24 | T18: =L18-S18 -> 0 | U18: 24
B19: I97-VPK-004 | C19: tăng đơ | D19: TURNBUCKLE M12 | E19: STEEL-GALV | F19: Tăng đơ 12 | I19: HDG | K19: Cái | L19: 39 | M19: 150000 | N19: =M19*L19 -> 5850000 | O19: =Q19*N19 -> 585000 | P19: =O19+N19 -> 6435000 | Q19: 0.1 | S19: =VLOOKUP(B19,'[118]25-WNC-I-097'!$I:$P,8,0) -> 39 | T19: =L19-S19 -> 0 | U19: 39
B20: I97-VPK-006 | C20: bulong | D20: BOLT-M12X35-EN14399-4-8.8-HDG | E20: EN14399-4-8.8 | F20: Bulong M12x35 Gr10.9 | I20: EN14399-4-GR10.9 HDG | K20: Cái | L20: 112 | M20: 8000 | N20: =M20*L20 -> 896000 | O20: =Q20*N20 -> 89600 | P20: =O20+N20 -> 985600 | Q20: 0.1 | S20: =VLOOKUP(B20,'[118]25-WNC-I-097'!$I:$P,8,0) -> 112 | T20: =L20-S20 -> 0 | U20: 112
B21: I97-VPK-007 | C21: bulong | D21: BOLT-M12x35-ISO4017-8.8-HDG | E21: ISO4017-8.8 | F21: Bulong M12x40 | I21: Gr 8.8 ISO 4017 HDG | K21: Cái | L21: 95 | M21: 3140 | N21: =M21*L21 -> 298300 | O21: =Q21*N21 -> 29830 | P21: =O21+N21 -> 328130 | Q21: 0.1 | S21: =VLOOKUP(B21,'[118]25-WNC-I-097'!$I:$P,8,0) -> 95 | T21: =L21-S21 -> 0 | U21: 95
B22: I97-VPK-008 | C22: bulong | D22: BOLT-M12X40-EN14399-3-8.8-HDG | E22: EN14399-3-8.8 | F22: Bulong M12x40 Gr10.9 | I22: EN14399-4-GR10.9 HDG | K22: Cái | L22: 101 | M22: 9000 | N22: =M22*L22 -> 909000 | O22: =Q22*N22 -> 90900 | P22: =O22+N22 -> 999900 | Q22: 0.1 | S22: =VLOOKUP(B22,'[118]25-WNC-I-097'!$I:$P,8,0) -> 101 | T22: =L22-S22 -> 0 | U22: 101
B23: I97-VPK-009 | C23: bulong | D23: BOLT-M12X40-EN14399-4-10.9-HDG | E23: EN14399-4-10.9 | F23: Bulong M12x40 Gr10.9 | I23: EN14399-4-GR10.9 HDG | K23: Cái | L23: 27 | M23: 9000 | N23: =M23*L23 -> 243000 | O23: =Q23*N23 -> 24300 | P23: =O23+N23 -> 267300 | Q23: 0.1 | S23: =VLOOKUP(B23,'[118]25-WNC-I-097'!$I:$P,8,0) -> 27 | T23: =L23-S23 -> 0 | U23: 27
B24: I97-VPK-010 | C24: bulong | D24: BOLT-M12x40-ISO4017-8.8-HDG | E24: ISO4017-8.8 | F24: Bulong M12x40 | I24: Gr 8.8 ISO 4017 HDG | K24: Cái | L24: 228 | M24: 3140 | N24: =M24*L24 -> 715920 | O24: =Q24*N24 -> 71592 | P24: =O24+N24 -> 787512 | Q24: 0.1 | S24: =VLOOKUP(B24,'[118]25-WNC-I-097'!$I:$P,8,0) -> 228 | T24: =L24-S24 -> 0 | U24: 228
B25: I97-VPK-011 | C25: bulong | D25: BOLT-M12x45-ISO4017-8.8-HDG | E25: ISO4017-8.8 | F25: Bulong M12x50 | I25: Gr 8.8 ISO 4017 HDG | K25: Cái | L25: 408 | M25: 3640 | N25: =M25*L25 -> 1485120 | O25: =Q25*N25 -> 148512 | P25: =O25+N25 -> 1633632 | Q25: 0.1 | S25: =VLOOKUP(B25,'[118]25-WNC-I-097'!$I:$P,8,0) -> 408 | T25: =L25-S25 -> 0 | U25: 408
B26: I97-VPK-012 | C26: bulong | D26: BOLT-M12X50-ISO4017-8.8-HDG | E26: ISO4017-8.8 | F26: Bulong M12x50 | I26: Gr 8.8 ISO 4017 HDG | K26: Cái | L26: 136 | M26: 3640 | N26: =M26*L26 -> 495040 | O26: =Q26*N26 -> 49504 | P26: =O26+N26 -> 544544 | Q26: 0.1 | S26: =VLOOKUP(B26,'[118]25-WNC-I-097'!$I:$P,8,0) -> 136 | T26: =L26-S26 -> 0 | U26: 136
B27: I97-VPK-013 | C27: bulong | D27: BOLT-M16x40-ISO4017-8.8-HDG | E27: ISO4017-8.8 | F27: Bulong M16x40 | I27: Gr 8.8 ISO 4017 HDG | K27: Cái | L27: 15 | M27: 6310 | N27: =M27*L27 -> 94650 | O27: =Q27*N27 -> 9465 | P27: =O27+N27 -> 104115 | Q27: 0.1 | S27: =VLOOKUP(B27,'[118]25-WNC-I-097'!$I:$P,8,0) -> 15 | T27: =L27-S27 -> 0 | U27: 15
B28: I97-VPK-014 | C28: bulong | D28: BOLT-M16x45-ISO4017-8.8-HDG | E28: ISO4017-8.8 | F28: Bulong M16x50 | I28: Gr 8.8 ISO 4017 HDG | K28: Cái | L28: 254 | M28: 7210 | N28: =M28*L28 -> 1831340 | O28: =Q28*N28 -> 183134 | P28: =O28+N28 -> 2014474 | Q28: 0.1 | S28: =VLOOKUP(B28,'[118]25-WNC-I-097'!$I:$P,8,0) -> 254 | T28: =L28-S28 -> 0 | U28: 254
B29: I97-VPK-015 | C29: bulong | D29: BOLT-M16X50-EN14399-3-8.8-HDG | E29: EN14399-3-8.8 | F29: Bulong M16x50 Gr10.9 | I29: EN14399-4-GR10.9 HDG | K29: Cái | L29: 56 | M29: 45000 | N29: =M29*L29 -> 2520000 | O29: =Q29*N29 -> 252000 | P29: =O29+N29 -> 2772000 | Q29: 0.1 | S29: =VLOOKUP(B29,'[118]25-WNC-I-097'!$I:$P,8,0) -> 56 | T29: =L29-S29 -> 0 | U29: 56
... B84: I97-VPK-075 | C84: THANH REN | D84: Threaded rod-M20X110-DIN975-8.8-HDG | E84: DIN975-8.8-HDG | F84: Thanh ren M20x110 | I84: DIN975-8.8-HDG | K84: Cái | L84: 25 | M84: 29260 | N84: =M84*L84 -> 731500 | O84: =Q84*N84 -> 73150 | P84: =O84+N84 -> 804650 | Q84: 0.1 | S84: =VLOOKUP(B84,'[118]25-WNC-I-097'!$I:$P,8,0) -> 25 | T84: =L84-S84 -> 0 | U84: 25
B85: I97-VPK-076 | C85: NUT | D85: NUT-3/4"-10UNC 2B-A563GRB-HDG | E85: A563GRB-HDG | F85: Ecu 3/4'' | K85: Cái | L85: 185 | M85: 19320 | N85: =M85*L85 -> 3574200 | O85: =Q85*N85 -> 357420 | P85: =O85+N85 -> 3931620 | Q85: 0.1 | S85: =VLOOKUP(B85,'[118]25-WNC-I-097'!$I:$P,8,0) -> 185 | T85: =L85-S85 -> 0 | U85: 185
B86: I97-VPK-077 | C86: NUT | D86: NUT-M10-DIN929-8-HDG | E86: DIN929-8-HDG | F86: Ecu hàn M10 | I86: DIN929 -HDG | K86: Cái | L86: 330 | M86: 1740 | N86: =M86*L86 -> 574200 | O86: =Q86*N86 -> 57420 | P86: =O86+N86 -> 631620 | Q86: 0.1 | S86: =VLOOKUP(B86,'[118]25-WNC-I-097'!$I:$P,8,0) -> 330 | T86: =L86-S86 -> 0 | U86: 330
B87: I97-VPK-078 | C87: NUT | D87: NUT-M10-ISO4032-8-HDG | E87: ISO4032-8-HDG | F87: Ecu M20 | I87: ISO4032-8-HDG | K87: Cái | L87: 485 | M87: 810 | N87: =M87*L87 -> 392850 | O87: =Q87*N87 -> 39285 | P87: =O87+N87 -> 432135 | Q87: 0.1 | S87: =VLOOKUP(B87,'[118]25-WNC-I-097'!$I:$P,8,0) -> 485 | T87: =L87-S87 -> 0 | U87: 485
B88: I97-VPK-079 | C88: NUT | D88: NUT-M20-DIN929-8-HDG | E88: DIN929-8-HDG | F88: Ecu hàn M20 | I88: DIN929 -HDG | K88: Cái | L88: 25 | M88: 9660 | N88: =M88*L88 -> 241500 | O88: =Q88*N88 -> 24150 | P88: =O88+N88 -> 265650 | Q88: 0.1 | S88: =VLOOKUP(B88,'[118]25-WNC-I-097'!$I:$P,8,0) -> 25 | T88: =L88-S88 -> 0 | U88: 25
B89: I97-VPK-080 | C89: NUT | D89: NUT-M27-DIN929-8-HDG | E89: DIN929-8-HDG | F89: Ecu hàn M27 | I89: DIN929 -HDG | K89: Cái | L89: 90 | M89: 24750 | N89: =M89*L89 -> 2227500 | O89: =Q89*N89 -> 222750 | P89: =O89+N89 -> 2450250 | Q89: 0.1 | S89: =VLOOKUP(B89,'[118]25-WNC-I-097'!$I:$P,8,0) -> 0 | T89: =L89-S89 -> 90
B90: I97-VPK-081 | C90: NUT | D90: NUT-M8-DIN929-8-HDG | E90: DIN929-8-HDG | F90: Ecu hàn M8 | I90: DIN929 -HDG | K90: Cái | L90: 595 | M90: 780 | N90: =M90*L90 -> 464100 | O90: =Q90*N90 -> 46410 | P90: =O90+N90 -> 510510 | Q90: 0.1 | S90: =VLOOKUP(B90,'[118]25-WNC-I-097'!$I:$P,8,0) -> 70 | T90: =L90-S90 -> 525 | U90: 70
B91: I97-VPK-082 | C91: NUT | D91: NUT-M8-ISO4032-8-HDG | E91: ISO4032-8-HDG | F91: Ecu M8 | I91: Geomet | K91: Cái | L91: 70 | M91: 360 | N91: =M91*L91 -> 25200 | O91: =Q91*N91 -> 2520 | P91: =O91+N91 -> 27720 | Q91: 0.1 | S91: =VLOOKUP(B91,'[118]25-WNC-I-097'!$I:$P,8,0) -> 70 | T91: =L91-S91 -> 0 | U91: 70
B92: I97-VPK-083 | C92: WASHER | D92: TAPER WASHER-M10-DIN434-200HV-HDG | E92: DIN434-200HV-HDG | F92: Vòng đệm vuông vát M10 | I92: HDG | K92: Cái | L92: 165 | M92: 2210 | N92: =M92*L92 -> 364650 | O92: =Q92*N92 -> 36465 | P92: =O92+N92 -> 401115 | Q92: 0.1 | S92: =VLOOKUP(B92,'[118]25-WNC-I-097'!$I:$P,8,0) -> 165 | T92: =L92-S92 -> 0 | U92: 165
B93: I97-VPK-084 | C93: WASHER | D93: TAPER WASHER-M16-DIN434-200HV-HDG | E93: DIN434-200HV-HDG | F93: Vòng đệm vuông vát M16 | I93: HDG | K93: Cái | L93: 1245 | M93: 7850 | N93: =M93*L93 -> 9773250 | O93: =Q93*N93 -> 977325 | P93: =O93+N93 -> 10750575 | Q93: 0.1 | S93: =VLOOKUP(B93,'[118]25-WNC-I-097'!$I:$P,8,0) -> 1245 | T93: =L93-S93 -> 0 | U93: 1245
B94: I97-VPK-085 | C94: WASHER | D94: TAPER WASHER-M8-DIN434-200HV-HDG | E94: DIN434-200HV-HDG | F94: Vòng đệm vuông vát M8 | I94: Geomet | K94: Cái | L94: 530 | M94: 4790 | N94: =M94*L94 -> 2538700 | O94: =Q94*N94 -> 253870 | P94: =O94+N94 -> 2792570 | Q94: 0.1 | S94: =VLOOKUP(B94,'[118]25-WNC-I-097'!$I:$P,8,0) -> 530 | T94: =L94-S94 -> 0 | U94: 530
B95: I97-VPK-086 | C95: WASHER | D95: WASHER-M10-ISO7089-200HV-HDG | E95: ISO7089-200HV-HDG | F95: Vòng đệm phẳng M10 | I95: HDG | K95: Cái | L95: 1300 | M95: 230 | N95: =M95*L95 -> 299000 | O95: =Q95*N95 -> 29900 | P95: =O95+N95 -> 328900 | Q95: 0.1 | S95: =VLOOKUP(B95,'[118]25-WNC-I-097'!$I:$P,8,0) -> 1300 | T95: =L95-S95 -> 0 | U95: 1300
B96: I97-VPK-087 | C96: WASHER | D96: WASHER-M16-ISO7093-200HV-HDG | E96: ISO7093-200HV-HDG | F96: Vòng đệm phẳng M16 | I96: HDG | K96: Cái | L96: 265 | M96: 1410 | N96: =M96*L96 -> 373650 | O96: =Q96*N96 -> 37365 | P96: =O96+N96 -> 411015 | Q96: 0.1 | S96: =VLOOKUP(B96,'[118]25-WNC-I-097'!$I:$P,8,0) -> 265 | T96: =L96-S96 -> 0 | U96: 265
B97: I97-VPK-088 | C97: WASHER | D97: WASHER-M36-ISO7089-200HV-HDG | E97: ISO7089-200HV-HDG | F97: Vòng đệm phẳng M36 | I97: HDG | K97: Cái | L97: 25 | M97: 11510 | N97: =M97*L97 -> 287750 | O97: =Q97*N97 -> 28775 | P97: =O97+N97 -> 316525 | Q97: 0.1 | S97: =VLOOKUP(B97,'[118]25-WNC-I-097'!$I:$P,8,0) -> 25 | T97: =L97-S97 -> 0 | U97: 25
B98: I97-VPK-091 | C98: NUT | D98: NUT-M24-DIN929-8-HDG | E98: DIN929-8-HDG | S98: =VLOOKUP(B98,'[118]25-WNC-I-097'!$I:$P,8,0) -> 90 | T98: =L98-S98 -> -90 | U98: 90
N104: =M104*L104 -> 0 | O104: =Q104*N104 -> 0 | P104: =O104+N104 -> 0
B105: Cộng | L105: =SUM(L18:L104) -> 24019 | N105: =SUM(N18:N104) -> 110064670 | P105: =SUM(P18:P104) -> 121071137
B106: Ghi chú: | C106: (Giá trị báo giá chưa bao gồm chi phí thí nghiệm hàng hóa )
C107: ĐIỀU KIỆN GIAO HÀNG
C108: 1. Yêu cầu kỹ thuật: | E108: Hàng mới 100%.
C109: 2. Chứng từ:
C110: 3. Kiểm tra, nghiệm thu: | E110: + Giá chưa bao gồm chi phí thí nghiệm, nghiệm thu.
E111: + Giá trên chưa bao gồm chi phí lưu kho và CP tài chính lưu kho.
C112: 4. Điều kiện thương mại:
C113: - Thời gian giao hàng: | E113: Giao hàng trong vòng 35-40 ngày từ ngày tạm ứng đặt hàng. ( không kể ngày lễ và chủ nhật)
C114: - Địa điểm giao hàng: | E114: Giao tại kho khách hàng tại Hải Phòng
C115: - Phương thức giao nhận: | E115: Theo số lượng thực tế
C116: - Dung sai số lượng: | E116: 0%
C117: - Phương thức ghi hóa đơn: | E117: Theo số lượng thực tế
C118: - Đóng gói: | E118: Theo quy cách NCC
C119: - Marking: | E119: Theo quy cách NCC
C120: - Xuất xứ
C121: - Điều kiện thanh toán: | E121: + Khách hàng xác nhận đặt hàng qua mail hoặc gửi ký xác nhận gửi qua các phương tiện khác.
E122: + Thanh toán trong vòng 15 ngày sau khi giao hàng và hồ sơ thanh toán.
C123: 5. Hiệu lực báo giá: | E123: 03 ngày
C124: Rất mong nhận được đặt hàng của Quý đơn vị trong thời gian sớm nhất.
C125: Kính chúc Quý đơn vị luôn thành công và đạt hiệu quả kinh doanh cao nhất.
B126: XÁC NHẬN BÁO GIÁ | I126: CÔNG TY TNHH VSAN
B127: (Mail đặt hàng: vsanfasteners@gmail.com)

Sheet BG Gnee 2
B1: GNEE STEEL CO.,LIMITED
B2: FLAT/RM 1512 15/F LUCKY CENTRE NO.165-171 WAN CHAI ROAD WAN CHAI HK
A3: TEL: +86 15286968617 E-mail:alice@gescosteel.com
A4: QUOTATION SHEET
A5: QUOTATION NO.: GNEEYPH20240527-1
A6: DATE: MAY.27TH,2024
A7: TO:IBS
A8: SR NO. | B8: PRODUCT NAME | C8: SPECIFICATION (mm) | F8: UNIT WEIGHT (KG/PCS) | G8: QUANTITY | I8: FOB CHINA
E9: Số lượng (m/m2) | G9: QTY (PCS) | H9: WEIGHT (KG) | I9: UNIT PRICE（USD/KG) | J9: AMOUNT (USD) | K9: lead time
A10: A-8 | B10: HARDOX 450 PLATE | C10: 6*2000*6000 | E10: =G10*2*6 -> 36 | F10: 565.2 | G10: 3 | H10: =G10*F10 -> 1695.6 | I10: 3.16 | J10: =I10*H10 -> 5358.096 | K10: 20days
A11: A-15 | B11: NM400 PLATE | C11: 12*1500*3700 | E11: =G11*1.5*3.7 -> 5.55 | F11: 653.5 | G11: 1 | H11: =G11*F11 -> 653.5 | I11: 1.1 | J11: =I11*H11 -> 718.85 | K11: 20days
A12: A-20 | B12: HARDOX 500 PLATE | C12: 16*2000*6000 | E12: =G12*2*6 -> 12 | F12: 1507.2 | G12: 1 | H12: =G12*F12 -> 1507.2 | I12: 3.07 | J12: =I12*H12 -> 4627.104 | K12: 20days
A13: A-27 | B13: HARDOX 500 PLATE | C13: 22*2000*6000 | E13: =G13*2*6 -> 12 | F13: =22*2*6*7.85 -> 2072.4 | G13: 1 | H13: =G13*F13 -> 2072.4 | I13: 3.16 | J13: =I13*H13 -> 6548.784 | K13: 20days
A14: A-5 | B14: SA240-304 PLATE | C14: 2*1219*2438 | E14: =G14*1.219*2.438 -> 2.971922 | F14: 47.2 | G14: 1 | H14: =G14*F14 -> 47.2 | I14: 3.29 | J14: =I14*H14 -> 155.288
A15: A-64 | B15: SUS 304 ROUND BAR | C15: 40*6000 | E15: =G15*6 -> 12 | F15: 59.8 | G15: 2 | H15: =G15*F15 -> 119.6 | I15: 3.72 | J15: =I15*H15 -> 444.912
A16: A-46 | B16: Q235B PIPE | C16: 102*6*6000 | E16: =G16*6 -> 6 | F16: 85.2 | G16: 1 | H16: =G16*F16 -> 85.2 | I16: 0.91 | J16: =I16*H16 -> 77.532
A17: A-47 | B17: Q235B PIPE | C17: 108*5*6000 | E17: =G17*6 -> 126 | F17: 76.2 | G17: 21 | H17: =G17*F17 -> 1600.2 | I17: 0.91 | J17: =I17*H17 -> 1456.182
A18: A-48 | B18: Q235B PIPE | C18: 121*5*6000 | E18: =G18*6 -> 60 | F18: 85.8 | G18: 10 | H18: =G18*F18 -> 858 | I18: 0.91 | J18: =I18*H18 -> 780.78
A19: A-49 | B19: Q235B PIPE | C19: 140*6*6000 | E19: =G19*6 -> 150 | F19: 119 | G19: 25 | H19: =G19*F19 -> 2975 | I19: 0.91 | J19: =I19*H19 -> 2707.25
A20: A-50 | B20: Q235B PIPE | C20: 168*8*6000 | E20: =G20*6 -> 18 | F20: 189.4 | G20: 3 | H20: =G20*F20 -> 568.2 | I20: 0.91 | J20: =I20*H20 -> 517.062
A21: A-51 | B21: Q235B PIPE | C21: 194*8*6000 | E21: =G21*6 -> 6 | F21: 220.2 | G21: 1 | H21: =G21*F21 -> 220.2 | I21: 0.91 | J21: =I21*H21 -> 200.382
A22: A-52 | B22: Q235B PIPE | C22: 245*10*12000 | E22: =G22*12 -> 12 | F22: 695.5 | G22: 1 | H22: =G22*F22 -> 695.5 | I22: 0.91 | J22: =I22*H22 -> 632.905
A23: A-53 | B23: Q235B PIPE | C23: 32*4*6000 | E23: =G23*6 -> 6 | F23: 16.6 | G23: 1 | H23: =G23*F23 -> 16.6 | I23: 0.91 | J23: =I23*H23 -> 15.106
A24: A-54 | B24: Q235B PIPE | C24: 60*3.5*6000 | E24: =G24*6 -> 6 | F24: 29.3 | G24: 1 | H24: =G24*F24 -> 29.3 | I24: 0.91 | J24: =I24*H24 -> 26.663
A25: A-55 | B25: Q235B PIPE | C25: 60*6*6000 | E25: =G25*6 -> 6 | F25: 47.9 | G25: 1 | H25: =G25*F25 -> 47.9 | I25: 0.91 | J25: =I25*H25 -> 43.589
A26: A-57 | B26: Q235B PIPE | C26: 76*5*6000 | E26: =G26*6 -> 36 | F26: 52.6 | G26: 6 | H26: =G26*F26 -> 315.6 | I26: 0.91 | J26: =I26*H26 -> 287.196
A27: AMOUNT | G27: =SUM(G10:G26) -> 80 | H27: =SUM(H10:H26) -> 13507.2 | J27: =SUM(J10:J26) -> 24597.681
A28: SPECIFICATION:
A29: 1. SURFACE: | C29: SAFETY
A30: 2. PACKAGE: | C30: SEA WORTHY PACKING
A31: 3. QUALITY STANDARD OF MATERIAL: | C31: ACCORDANCE WITH ABOVE SPECIFICATION.
A32: TERMS:
A33: 1. INSPECTION: | C33: MILL QUALITY TEST.(ORIGINAL MTC WILL BE PROVIDED.)
A34: 2. TOLERANCE OF AMOUNT: | C34: QUANTITY AND AMOUNT ARE ALLOWED MORE OR LESS 10%.
A35: 3.TERMS OF PAYMENT: | C35: 100% LC AT SIGHT.
A36: 4. TIME OF DELIVERY: | C36: 20DAYS AFTER ORIGINAL LC
A37: 5. PORT OF LOADING: | C37: ANY PORT,CHINA
A38: 6. PORT OF DESTINATION: | C38: HAIPHONG,VIETNAM
A39: 7. TRANSPORTATION: | C39: CONTAINER
A40: 8. VALID PERIOD OF PRICE: | C40: 5DAYS
A41: 9. ORIGIN OF GOODS: | C41: CHINA.
A42: 10.NOTE | C42: 1. ABOVE PRICE IS BASED ON FINAL WEIGHT
C43: 2. ABOVE PRICE DOES NOT CONTAIN THIRD PARTY INSPECTION FEE.
A44: BANK INFORMATION:
A45: BENIFICIARY COMPANY: | C45: GNEE STEEL CO.,LIMITED
A46: COMPANY ADDRESS: | C46: FLAT/RM 1512 15/F LUCKY CENTRE NO.165-171 WAN CHAI ROAD WAN CHAI HK
A47: BENIFICIARY BANK: | C47: ZHEJIANG CHOUZHOU COMMERCIAL BANK
A48: BANK ADDRESS: | C48: YIWU LEYUAN EAST JIANGBIN ROAD YIWU CITY ZHEJIANG PROVINCE CHINA
A49: SWIFT NO.: | C49: CZCBCN2X
A50: ACCOUNT NUMBER: | C50: NRA15628142010500008718

Sheet Báo giá của GNEE
B1: GNEE STEEL CO.,LIMITED
B2: FLAT/RM 1512 15/F LUCKY CENTRE NO.165-171 WAN CHAI ROAD WAN CHAI HK
A3: TEL: +86 15286968617 E-mail:alice@gescosteel.com
A4: QUOTATION SHEET
A5: QUOTATION NO.: GNEEYPH20240513-1
A6: DATE: MAY.13TH,2024
A7: TO:IBS
A8: SR NO. | B8: PRODUCT NAME | C8: SPECIFICATION (mm) | F8: UNIT WEIGHT (KG/PCS) | G8: QUANTITY | I8: CIF HAIPHONG, VIETNAM
E9: Số lượng (m/m2) | G9: QTY (PCS) | H9: WEIGHT (KG) | I9: UNIT PRICE（USD/KG) | J9: AMOUNT (USD) | M9: lead time
A10: A-8 | B10: HARDOX 450 PLATE | C10: 6*2000*6000 | E10: =G10*2*6 -> 36 | F10: 565.2 | G10: 3 | H10: =G10*F10 -> 1695.6 | I10: 3.21 | J10: =I10*H10 -> 5442.876 | K10: GNEEYPH20240513-1 | L10: kt: 1500X6000-2 tờ; 1500x5400-1 tờ. | M10: 20days
A11: A-9 | B11: Q235B PLATE | C11: 6*1500*6000 | E11: =G11*1.5*6 -> 18 | F11: 423.9 | G11: 2 | H11: =G11*F11 -> 847.8 | I11: 0.68 | J11: =I11*H11 -> 576.504 | K11: GNEEYPH20240513-1 | M11: 20days
A12: A-11 | B12: Q235B PLATE | C12: 8*1500*6000 | E12: =G12*1.5*6 -> 9 | F12: 565.2 | G12: 1 | H12: =G12*F12 -> 565.2 | I12: 0.7 | J12: =I12*H12 -> 395.64 | K12: GNEEYPH20240513-1 | M12: 20days
A13: A-12 | B13: Q355B PLATE | C13: 8*2000*12000 | E13: =G13*2*12 -> 24 | F13: 1507.2 | G13: 1 | H13: =G13*F13 -> 1507.2 | I13: 0.72 | J13: =I13*H13 -> 1085.184 | K13: GNEEYPH20240513-1 | M13: 20days
A14: A-13 | B14: Q235B PLATE | C14: 10*1500*6000 | E14: =G14*1.5*6 -> 9 | F14: 706.5 | G14: 1 | H14: =G14*F14 -> 706.5 | I14: 0.69 | J14: =I14*H14 -> 487.485 | K14: GNEEYPH20240513-1 | M14: 20days
A15: A-14 | B15: Q355B PLATE | C15: 10*2000*10000 | E15: =G15*2*10 -> 20 | F15: 1570 | G15: 1 | H15: =G15*F15 -> 1570 | I15: 0.72 | J15: =I15*H15 -> 1130.4 | K15: GNEEYPH20240513-1 | M15: 20days
A16: A-15 | B16: NM400 PLATE | C16: 12*1500*3700 | E16: =G16*1.5*3.7 -> 5.55 | F16: 653.5 | G16: 1 | H16: =G16*F16 -> 653.5 | I16: 1.15 | J16: =I16*H16 -> 751.525 | K16: GNEEYPH20240513-1 | L16: 12*1500*4250 | M16: 20days
A17: A-17 | B17: Q355B PLATE | C17: 12*2000*12000 | E17: =G17*2*12 -> 24 | F17: 2260.8 | G17: 1 | H17: =G17*F17 -> 2260.8 | I17: 0.72 | J17: =I17*H17 -> 1627.776 | K17: GNEEYPH20240513-1 | M17: 45days
A18: A-20 | B18: HARDOX 500 PLATE | C18: 16*2000*6000 | E18: =G18*2*6 -> 12 | F18: 1507.2 | G18: 1 | H18: =G18*F18 -> 1507.2 | I18: 3.12 | J18: =I18*H18 -> 4702.464 | K18: GNEEYPH20240513-1 | L18: kt: 1500X6000-1 tờ; 1500x2500-1 tờ. | M18: 20days
A19: A-22 | B19: Q355B PLATE | C19: 16*2000*8000 | E19: =G19*2*8 -> 16 | F19: 2009.6 | G19: 1 | H19: =G19*F19 -> 2009.6 | I19: 0.78 | J19: =I19*H19 -> 1567.488 | K19: GNEEYPH20240513-1 | M19: 20days
A20: A-42 | B20: Q355 H BEAM | C20: 200*200*8*12*12000 | E20: =G20*12 -> 96 | F20: =50.5*12 -> 606 | G20: 8 | H20: =G20*F20 -> 4848 | I20: 0.75 | J20: =I20*H20 -> 3636 | K20: GNEEYPH20240513-1 | M20: 20days
A21: A-43 | B21: Q355 H BEAM | C21: 250*250*9*14*12000 | E21: =G21*12 -> 12 | F21: =72.4*12 -> 868.8 | G21: 1 | H21: =G21*F21 -> 868.8 | I21: 0.75 | J21: =I21*H21 -> 651.6 | K21: GNEEYPH20240513-1
A22: A-73 | B22: Q235B RHS | C22: 150*100*6*12000 | E22: =G22*12 -> 24 | F22: 269 | G22: 2 | H22: =G22*F22 -> 538 | I22: 0.75 | J22: =I22*H22 -> 403.5 | K22: GNEEYPH20240513-1 | M22: 20days
A23: A-74 | B23: Q235B RHS | C23: 200*100*6*6000 | E23: =G23*6 -> 30 | F23: 162.8 | G23: 5 | H23: =G23*F23 -> 814 | I23: 0.75 | J23: =I23*H23 -> 610.5 | K23: GNEEYPH20240513-1 | M23: 20days
A24: A-75 | B24: Q235B SHS | C24: 200*200*10*6000 | E24: =G24*6 -> 60 | F24: 358 | G24: 10 | H24: =G24*F24 -> 3580 | I24: 0.75 | J24: =I24*H24 -> 2685 | K24: GNEEYPH20240513-1 | M24: 20days
A25: A-76 | B25: Q355B SHS | C25: 200*200*8*12000 | E25: =G25*12 -> 48 | F25: 289.4 | G25: 4 | H25: =G25*F25 -> 1157.6 | I25: 0.77 | J25: =I25*H25 -> 891.352 | K25: GNEEYPH20240513-1
A26: A-77 | B26: Q235B SHS | C26: 300*300*6*6000 | E26: =G26*6 -> 54 | F26: 332.4 | G26: 9 | H26: =G26*F26 -> 2991.6 | I26: 0.75 | J26: =I26*H26 -> 2243.7 | K26: GNEEYPH20240513-1 | M26: 20days
A27: AMOUNT | G27: =SUM(G10:G26) -> 52 | H27: =SUM(H10:H26) -> 28121.4 | J27: =SUM(J10:J26) -> 28888.994
A28: SPECIFICATION:
A29: 1. SURFACE: | C29: SAFETY
A30: 2. PACKAGE: | C30: SEA WORTHY PACKING
A31: 3. QUALITY STANDARD OF MATERIAL: | C31: ACCORDANCE WITH ABOVE SPECIFICATION.
A32: TERMS:
A33: 1. INSPECTION: | C33: MILL QUALITY TEST.(ORIGINAL MTC WILL BE PROVIDED.)
A34: 2. TOLERANCE OF AMOUNT: | C34: QUANTITY AND AMOUNT ARE ALLOWED MORE OR LESS 10%.
A35: 3.TERMS OF PAYMENT: | C35: 100% LC AT SIGHT.
A36: 4. TIME OF DELIVERY: | C36: 20DAYS AFTER ORIGINAL LC
A37: 5. PORT OF LOADING: | C37: ANY PORT,CHINA
A38: 6. PORT OF DESTINATION: | C38: HAIPHONG,VIETNAM
A39: 7. TRANSPORTATION: | C39: CONTAINER
A40: 8. VALID PERIOD OF PRICE: | C40: 5DAYS
A41: 9. ORIGIN OF GOODS: | C41: CHINA.
A42: 10.NOTE | C42: 1. ABOVE PRICE IS BASED ON FINAL WEIGHT
C43: 2. ABOVE PRICE DOES NOT CONTAIN THIRD PARTY INSPECTION FEE.
A44: BANK INFORMATION:
A45: BENIFICIARY COMPANY: | C45: GNEE STEEL CO.,LIMITED
A46: COMPANY ADDRESS: | C46: FLAT/RM 1512 15/F LUCKY CENTRE NO.165-171 WAN CHAI ROAD WAN CHAI HK
A47: BENIFICIARY BANK: | C47: ZHEJIANG CHOUZHOU COMMERCIAL BANK
A48: BANK ADDRESS: | C48: YIWU LEYUAN EAST JIANGBIN ROAD YIWU CITY ZHEJIANG PROVINCE CHINA
A49: SWIFT NO.: | C49: CZCBCN2X
A50: ACCOUNT NUMBER: | C50: NRA15628142010500008718

Sheet Dieu kien giao hang
A2: ĐIỀU KIỆN GIAO HÀNG NHẬP KHẨU
A3: STT | B3: Nội dung | C3: Số ngày | D3: Giá trị cộng dồn
A4: 1 | B4: Ký HD | C4: 0
A5: 2 | B5: Tạm ứng | C5: 0
A6: 3 | B6: Mở LC | C6: 5 | D6: =+C6+D5+C5 -> 5
A7: 4 | B7: Giao Hàng CIF | C7: 20 | D7: =+C7+D6 -> 25
A8: 5 | B8: Vận chuyển quốc tế | C8: 5 | D8: =+C8+D7 -> 30
A9: 6 | B9: Ngày thanh toán | C9: 3 | D9: =+C9+D8 -> 33
A10: 6 | B10: Thủ tục hải quan + vận chuyển nội địa | C10: 3 | D10: =+C10+D9 -> 36
B11: Ngày hàng về | C11: 2 | D11: =+C11+D10 -> 38
B12: Ngày mời nghiệm thu QC | C12: 1 | D12: =+C12+D11 -> 39
A13: 7 | B13: Nghiệm thu | C13: 12 | D13: =+C13+D12 -> 51
A14: 7 | B14: Bàn giao | C14: 1 | D14: =+C14+D13 -> 52
A16: ĐIỀU KIỆN GIAO HÀNG TRONG NƯỚC (VTU CHÍNH)
A17: STT | B17: Nội dung | C17: Số ngày | D17: Giá trị cộng dồn
A18: 1 | B18: Ký HD | C18: 0
A19: 2 | B19: Tạm ứng | C19: 0
A20: 3 | B20: Mở LC | C20: 0 | D20: =+C20+D19+C19 -> 0
A21: 4 | B21: Giao Hàng tại xưởng | C21: 4 | D21: =+C21+D20 -> 4
A22: 5 | B22: Nghiệm thu | C22: 2 | D22: =+C22+D21 -> 6
A23: 6 | B23: Bàn giao | C23: 1 | D23: =+C23+D22 -> 7
A26: ĐIỀU KIỆN GIAO HÀNG TRONG NƯỚC (VTU Phụ)
A27: STT | B27: Nội dung | C27: Số ngày | D27: Giá trị cộng dồn
A28: 1 | B28: Ký HD | C28: 0
A29: 2 | B29: Tạm ứng | C29: 0
A30: 3 | B30: Mở LC | C30: 0 | D30: =+C30+D29+C29 -> 0
A31: 4 | B31: Giao Hàng tại xưởng | C31: 26 | D31: =+C31+D30 -> 26
A32: 5 | B32: Nghiệm thu | C32: 2 | D32: =+C32+D31 -> 28
A33: 6 | B33: Bàn giao | C33: 1 | D33: =+C33+D32 -> 29

Sheet PL01 Hung nguyen
A1: CÔNG TY TNHH THƯƠNG MẠI HÙNG NGUYÊN Trụ sở: Số 673 đường 5/2, P.Hùng Vương, Q.Hồng Bàng, Hải Phòng VPGD: Số 955 đường Hùng Vương, P.Hùng Vương, Q.Hồng Bàng, TP.Hải Phòng Điện thoại: 0225.3529.509 / E: hungnguyenthep@gmail.com
A3: PHỤ LỤC SỐ 01 THUỘC HỢP ĐỒNG MUA BÁN SỐ: 030224/HN-IBS ngày 03/02/2024
A4: Hôm nay ngày 03/02/2024, Công ty TNHH Thương Mại Hùng Nguyên (Bên Bán) và CÔNG TY CỔ PHẦN CÔNG NGHIỆP NẶNG IBS (Bên Mua) thống nhất lập phụ lục hợp đồng số: 01 thuộc Hợp đồng mua bán số: 030224/HN-IBS ngày 03/02/2024 với các điều khoản cụ thể như sau:
A5: Điều 1: Thông tin lô hàng đính kèm hợp đồng:
A6: STT | C6: Tên hàng hóa | D6: Mác thép | E6: Xuất xứ | F6: Số lượng (Cây,Tấm) | G6: Trọng lượng (KG) | H6: Đơn giá Có VAT (VNĐ/KG) | I6: Đơn giá Chưa VAT (VND/KG) | K6: Thành tiền Chưa VAT (VNĐ)
A7: (a) | C7: (b) | F7: (c) | G7: (d) | H7: (e) | I7: (f) | K7: (g = d x f)
A8: 1 | B8: A-01 | C8: Thép tấm 10x2000x12000 | D8: A36/SS400 | E8: Trung Quốc | F8: 14 | G8: =ROUND(10*2*12*7.85*F8,0) -> 26376 | H8: 16550 | I8: =+ROUND(H8/1.1,2) -> 15045.45 | K8: =+ROUND(G8*I8,0) -> 396838789
A9: 2 | B9: A-06 | C9: Thép tấm 6x2000x12000 | D9: A36/SS400 | E9: Trung Quốc | F9: 22 | G9: =ROUND(6*2*12*7.85*F9,0) -> 24869 | H9: 16550 | I9: =+ROUND(H9/1.1,2) -> 15045.45 | K9: =+ROUND(G9*I9,0) -> 374165296
A10: 3 | B10: A-17 | C10: Thép tấm 12x2000x6000 | D10: A36/SS400 | E10: Trung Quốc | F10: 1 | G10: =ROUND(12*2*6*7.85*F10,0) -> 1130 | H10: 16550 | I10: =+ROUND(H10/1.1,2) -> 15045.45 | K10: =+ROUND(G10*I10,0) -> 17001359
A11: 4 | B11: A-15 | C11: Thép tấm 10x2000x12000 | D11: Q355/A572 | E11: Trung Quốc | F11: 1.5 | G11: =ROUND(10*2*12*7.85*F11,0) -> 2826 | H11: 17550 | I11: =+ROUND(H11/1.1,2) -> 15954.55 | K11: =+ROUND(G11*I11,0) -> 45087558
A12: 5 | B12: A-16 | C12: Thép tấm 12x2000x6000 | D12: Q355/A572 | E12: Trung Quốc | F12: 1 | G12: =ROUND(12*2*6*7.85*F12,0) -> 1130 | H12: 17550 | I12: =+ROUND(H12/1.1,2) -> 15954.55 | K12: =+ROUND(G12*I12,0) -> 18028642
A13: 6 | B13: A-18 | C13: Thép tấm 16x2000x6000 | D13: Q355/A572 | E13: Trung Quốc | F13: 1 | G13: =ROUND(16*2*6*7.85*F13,0) -> 1507 | H13: 17550 | I13: =+ROUND(H13/1.1,2) -> 15954.55 | K13: =+ROUND(G13*I13,0) -> 24043507
A14: 7 | B14: A-19 | C14: Thép tấm 20x2000x12000 | D14: Q355/A572 | E14: Trung Quốc | F14: 5 | G14: =ROUND(20*2*12*7.85*F14,0) -> 18840 | H14: 17550 | I14: =+ROUND(H14/1.1,2) -> 15954.55 | K14: =+ROUND(G14*I14,0) -> 300583722
A15: 8 | B15: A-20 | C15: Thép tấm 22x2000x12000 | D15: Q355/A572 | E15: Trung Quốc | F15: 3.5 | G15: =ROUND(22*2*12*7.85*F15,0) -> 14507 | H15: 18050 | I15: =+ROUND(H15/1.1,2) -> 16409.09 | K15: =+ROUND(G15*I15,0) -> 238046669
A16: 9 | B16: A-21 | C16: Thép tấm 25x2000x6000 | D16: Q355/A572 | E16: Trung Quốc | F16: 1 | G16: =ROUND(25*2*6*7.85*F16,0) -> 2355 | H16: 18050 | I16: =+ROUND(H16/1.1,2) -> 16409.09 | K16: =+ROUND(G16*I16,0) -> 38643407
A17: 10 | B17: A-22 | C17: Thép tấm 28x2000x6000 | D17: Q355/A572 | E17: Trung Quốc | F17: 1 | G17: =ROUND(28*2*6*7.85*F17,0) -> 2638 | H17: 18050 | I17: =+ROUND(H17/1.1,2) -> 16409.09 | K17: =+ROUND(G17*I17,0) -> 43287179
A18: 11 | B18: A-23 | C18: Thép tấm 32x2000x6000 | D18: Q355/A572 | E18: Trung Quốc | F18: 1 | G18: =ROUND(32*2*6*7.85*F18,0) -> 3014 | H18: 18050 | I18: =+ROUND(H18/1.1,2) -> 16409.09 | K18: =+ROUND(G18*I18,0) -> 49456997
A19: 12 | B19: A-24 | C19: Thép U125x65x6x8x12000 | D19: SS400 | E19: Nhật Bản/ Hàn Quốc/ Thái Lan | F19: 9 | G19: =ROUND(13.4*12*F19,2) -> 1447.2 | H19: 24050 | I19: =+ROUND(H19/1.1,2) -> 21863.64 | K19: =+ROUND(G19*I19,0) -> 31641060
A20: 13 | B20: A-25 | C20: Thép U150x75x6.5x10x12000 | D20: SS400 | E20: Việt Nam | F20: 7 | G20: =ROUND(18.6*12*F20,2) -> 1562.4 | H20: 18550 | I20: =+ROUND(H20/1.1,2) -> 16863.64 | K20: =+ROUND(G20*I20,0) -> 26347751
A21: 14 | B21: A-26 | C21: Thép U180x68x7x12000 | D21: SS400 | E21: Trung Quốc | F21: 54 | G21: =ROUND(18.6*12*F21,2) -> 12052.8 | H21: 18550 | I21: =+ROUND(H21/1.1,2) -> 16863.64 | K21: =+ROUND(G21*I21,0) -> 203254080
A22: 15 | B22: A-27 | C22: Thép U200x80x7.5x11x12000 | D22: SS400 | E22: Nhật Bản/ Hàn Quốc/ Thái Lan | F22: 24 | G22: =ROUND(24.6*12*F22,2) -> 7084.8 | H22: 24050 | I22: =+ROUND(H22/1.1,2) -> 21863.64 | K22: =+ROUND(G22*I22,0) -> 154899517
A23: 16 | B23: A-28 | C23: Thép U200x90x8x13.5x12000 | D23: SS400 | E23: Nhật Bản/ Hàn Quốc/ Thái Lan | F23: 7 | G23: =ROUND(30.3*12*F23,2) -> 2545.2 | H23: 24550 | I23: =+ROUND(H23/1.1,2) -> 22318.18 | K23: =+ROUND(G23*I23,0) -> 56804232
A24: 17 | B24: A-29 | C24: Thép U250x90x9x13x12000 | D24: SS400 | E24: Nhật Bản/ Hàn Quốc/ Thái Lan | F24: 3 | G24: =ROUND(34.6*12*F24,2) -> 1245.6 | H24: 24550 | I24: =+ROUND(H24/1.1,2) -> 22318.18 | K24: =+ROUND(G24*I24,0) -> 27799525
A25: 18 | B25: A-30 | C25: Thép H150x150x7x10x12000 | D25: SS400 | E25: Việt Nam | F25: 2 | G25: =ROUND(31.5*12*F25,2) -> 756 | H25: 20850 | I25: =+ROUND(H25/1.1,2) -> 18954.55 | K25: =+ROUND(G25*I25,0) -> 14329640
A26: 19 | B26: A-31 | C26: Thép H194x150x6x9x12000 | D26: SS400 | E26: Việt Nam | F26: 1 | G26: =ROUND(30.6*12*F26,2) -> 367.2 | H26: 20950 | I26: =+ROUND(H26/1.1,2) -> 19045.45 | K26: =+ROUND(G26*I26,0) -> 6993489
A27: 20 | B27: A-32 | C27: Thép H244x175x7x11x12000 | D27: SS400 | E27: Việt Nam | F27: 11 | G27: =ROUND(44.1*12*F27,2) -> 5821.2 | H27: 20950 | I27: =+ROUND(H27/1.1,2) -> 19045.45 | K27: =+ROUND(G27*I27,0) -> 110867374
A28: 21 | B28: A-33 | C28: Thép I250x125x6x9x12000 | D28: SS400 | E28: Việt Nam | F28: 7.5 | G28: =ROUND(29.6*12*F28,20) -> 2664 | H28: 20850 | I28: =+ROUND(H28/1.1,2) -> 18954.55 | K28: =+ROUND(G28*I28,0) -> 50494921
A29: 22 | B29: A-34 | C29: Thép I300x150x6.5x9x12000 | D29: SS400 | E29: Việt Nam | F29: 5.5 | G29: =ROUND(36.7*12*F29,2) -> 2422.2 | H29: 20850 | I29: =+ROUND(H29/1.1,2) -> 18954.55 | K29: =+ROUND(G29*I29,0) -> 45911711
A30: 23 | B30: A-35 | C30: Thép góc L100x100x10x12000 | D30: SS400 | E30: Việt Nam | F30: 3 | G30: =ROUND(181.26*F30,0) -> 544 | H30: 17350 | I30: =+ROUND(H30/1.1,2) -> 15772.73 | K30: =+ROUND(G30*I30,0) -> 8580365
A31: 24 | B31: A-36 | C31: Thép góc L100x100x7x6000 | D31: SS400 | E31: Việt Nam | F31: 1 | G31: =64.44*F31 -> 64.44 | H31: 17350 | I31: =+ROUND(H31/1.1,2) -> 15772.73 | K31: =+ROUND(G31*I31,0) -> 1016395
A32: 25 | B32: A-37 | C32: Thép góc L130x130x10x12000 | D32: SS400 | E32: Trung Quốc | F32: 1 | G32: =238.5*F32 -> 238.5 | H32: 18550 | I32: =+ROUND(H32/1.1,2) -> 16863.64 | K32: =+ROUND(G32*I32,0) -> 4021978
A33: 26 | B33: A-38 | C33: Thép góc L150x150x10x12000 | D33: SS400 | E33: Việt Nam | F33: 3 | G33: =ROUND(276.66*F33,2) -> 829.98 | H33: 19550 | I33: =+ROUND(H33/1.1,2) -> 17772.73 | K33: =+ROUND(G33*I33,0) -> 14751010
A34: 27 | B34: A-39 | C34: Thép góc L65x65x6x6000 | D34: SS400 | E34: Việt Nam | F34: 1 | G34: =35.49*F34 -> 35.49 | H34: 17050 | I34: =+ROUND(H34/1.1,2) -> 15500 | K34: =+ROUND(G34*I34,0) -> 550095
A35: 28 | B35: A-41 | C35: Thép góc L75x75x6x6000 | D35: SS400 | E35: Việt Nam | F35: 7 | G35: 288.47 | H35: 17050 | I35: =+ROUND(H35/1.1,2) -> 15500 | K35: =+ROUND(G35*I35,0) -> 4471285
A36: 29 | B36: A-42 | C36: Thép góc L75x75x8x6000 | D36: SS400 | E36: Việt Nam | F36: 1 | G36: 54.19 | H36: 17050 | I36: =+ROUND(H36/1.1,2) -> 15500 | K36: =+ROUND(G36*I36,0) -> 839945
A37: 30 | B37: A-43 | C37: Thép góc L90x90x10x12000 | D37: SS400 | E37: Việt Nam | F37: 12 | G37: =ROUND(162.18*F37,2) -> 1946.16 | H37: 17350 | I37: =+ROUND(H37/1.1,2) -> 15772.73 | K37: =+ROUND(G37*I37,0) -> 30696256
A38: 31 | B38: A-44 | C38: Thép góc L90x90x6x12000 | D38: SS400 | E38: Việt Nam | F38: 6 | G38: 597.6 | H38: 17350 | I38: =+ROUND(H38/1.1,2) -> 15772.73 | K38: =+ROUND(G38*I38,0) -> 9425783
A39: 32 | B39: A-45 | C39: Thép góc L90x90x7x6000 | D39: SS400 | E39: Việt Nam | F39: 10 | G39: 577.65 | H39: 17350 | I39: =+ROUND(H39/1.1,2) -> 15772.73 | K39: =+ROUND(G39*I39,0) -> 9111117
A40: 33 | B40: A-55 | C40: Thép tròn D10x6000 | D40: SS400/CB240/S45C | E40: Việt Nam/ Trung Quốc | F40: 1 | G40: 3.699 | H40: 18850 | I40: =+ROUND(H40/1.1,2) -> 17136.36 | K40: =+ROUND(G40*I40,0) -> 63387
A41: 34 | B41: A-56 | C41: Thép tròn D12x6000 | D41: SS400/CB240/S45C | E41: Việt Nam/ Trung Quốc | F41: 1 | G41: 5.32656 | H41: 18850 | I41: =+ROUND(H41/1.1,2) -> 17136.36 | K41: =+ROUND(G41*I41,0) -> 91278
A42: 35 | B42: A-57 | C42: Thép tròn D14x6000 | D42: SS400/CB240/S45C | E42: Việt Nam/ Trung Quốc | F42: 1 | G42: 7.25004 | H42: 18850 | I42: =+ROUND(H42/1.1,2) -> 17136.36 | K42: =+ROUND(G42*I42,0) -> 124239
A43: 36 | B43: A-58 | C43: Thép tròn D16x6000 | D43: SS400/CB240/S45C | E43: Việt Nam/ Trung Quốc | F43: 1 | G43: 9.46944 | H43: 18850 | I43: =+ROUND(H43/1.1,2) -> 17136.36 | K43: =+ROUND(G43*I43,0) -> 162272
A44: 37 | B44: A-59 | C44: Thép tròn D20x6000 | D44: SS400/CB240/S45C | E44: Việt Nam/ Trung Quốc | F44: 1 | G44: 14.8 | H44: 18850 | I44: =+ROUND(H44/1.1,2) -> 17136.36 | K44: =+ROUND(G44*I44,0) -> 253618
A45: 38 | B45: A-60 | C45: Thép tròn D38x6000 | D45: SS400/CB240/S45C | E45: Việt Nam/ Trung Quốc | F45: 1 | G45: 53.41 | H45: 19250 | I45: =+ROUND(H45/1.1,2) -> 17500 | K45: =+ROUND(G45*I45,0) -> 934675
A46: Tổng: | F46: =SUBTOTAL(9,F8:F45) -> 234 | G46: =SUBTOTAL(9,G8:G45) -> 142431.04 | H46: Cộng tiền hàng: | K46: =SUBTOTAL(9,K8:K45) -> 2359620123
A47: Thuế GTGT: 10% | G47: Tiền thuế GTGT: | K47: =ROUND(K46*0.1,0) -> 235962012
A48: Tổng số tiền viết bằng số: | K48: =SUM(K46:K47) -> 2595582135
A49: Số tiền viết bằng chữ: | D49: =+_xll.VND(K48) -> #NAME?
A52: Điều 2: Các điều khoản khác. - Phụ lục Hợp đồng số 01 có hiệu lực kể từ ngày ký và là một phần không thể tách rời của đồng mua bán số 030224/HN-IBS ngày 03/02/2024 - Những điều khoản khác của Hợp đồng mua bán số: 030224/HN-IBS giữ nguyên giá trị hiệu lực, hai bên có trách nhiệm cùng nhau thực hiện. - Phụ lục Hợp đồng này được lập thành 04 bản, mỗi bên giữ 02 bản có giá trị như nhau.
C56: ĐẠI DIỆN BÊN BÁN | G56: ĐẠI DIỆN BÊN MUA

Sheet vogt 060_Plan_Khong su dung
A1: THEO DÕI VẬT TƯ DỰ ÁN/ MATERIAL CONTROL LOG
A2: Tên dự án/ Project no.: VOGT 060
A3: Cập nhật ngày/ Update to: | C3: =TODAY() -> 46086
A4: Item/ STT | B4: Description/ Chi tiết | C4: Profile/ Vật tư | D4: Grade/ Mác vật liệu | E4: Unit/ Đơn vị | F4: U.Weight/ Đ.Trọng (Kg/m2,m,pcs) | G4: Net Quantity/Số lượng tinh | I4: Previous Ordered/Đã dự trù | K4: Current Ordered/Dự trù lần 1 | M4: Total Ordered/Tổng dự trù | O4: Ngày vật tư đưa vào sử dụng/ Material avaiable for fabrication date | P4: Tận dụng tồn kho/ Remain | R4: Khối lượng phải mua sắm/ total order | T4: Mua sắm trong nước/ Local purchase | AB4: Mua sắm nước ngoài/ Oversea purchase | AM4: Remarks/ Ghi chú
G5: Q.Ty/ Số lượng | H5: Weight/ Khối lượng (Kg) | I5: Q.Ty/ Số lượng | J5: Weight/ Khối lượng (Kg) | K5: Q.Ty/Số lượng | L5: Weight/Khối lượng (Kg) | M5: Q.Ty/ Số lượng | N5: Weight/Khối lượng (Kg) | P5: Q.Ty/ Số lượng | Q5: Weight/Khối lượng (Kg) | R5: Q.Ty/ Số lượng | S5: Weight/Khối lượng (Kg) | T5: Q.Ty/ Số lượng | U5: Weight/ Khối lượng (Kg) | V5: Nhà cung cấp/ Vendor | W5: Ngày ký HD/ Contract date | X5: Ngày giao hàng/ Handover date | Y5: Ngày nghiệm thu, Bàn giao/ Inspection date | Z5: Kết quả nghiệm thu/ Results | AA5: Bàn giao sản xuất/ Handover to Product | AB5: Q.Ty/ Số lượng | AC5: Weight/ Khối lượng (Kg) | AD5: Nhà cung cấp/ Vendor | AE5: Ngày ký HD/ Contract date | AF5: Ngày mở L/C/ LC issued date | AG5: Hàng đi từ cảng nước ngoài/ Export Port | AH5: Hàng Đến cảng HP (CIF)/ HaiPhong CIF | AI5: Thủ tục hải quan, vận chuyển/ Paper work, local transportaion date | AJ5: Ngày nghiệm thu, Bàn giao/ Handover date | AK5: Kết quả nghiệm thu/ Results | AL5: Bàn giao sản xuất/ Handover to Product
A6: 1 | B6: 2 | C6: 3 | D6: 4 | E6: 5 | F6: 6 | G6: 7 | H6: 8 | I6: 9 | J6: 10 | K6: 11 | L6: 12 | M6: 13 | N6: 14 | AM6: 15
A7: A. | B7: Main-Material / Vật tư chính | H7: =SUM(H8:H86) -> 447323.94 | J7: =SUM(J8:J86) -> 2826 | L7: =SUM(L8:L86) -> 493509.35 | N7: =SUM(N8:N86) -> 496335.35 | U7: =SUM(U8:U86) -> 452389.54 | AC7: =SUM(AC8:AC86) -> 43945.809 | AM7: .
A8: A-1 | B8: TÔN TẤM | C8: PL10X2000X12000 | D8: SS400 | E8: m2 | F8: 78.5 | G8: =+H8/F8 -> 612.19898 | H8: =1259.98+46797.64 -> 48057.62 | I8: 36 | J8: 2826 | K8: 650 | L8: =+K8*F8 -> 51025 | M8: =+K8+I8 -> 686 | N8: =+L8+J8 -> 53851 | O8: 45316 | R8: =+M8-P8 -> 686 | S8: =+N8-Q8 -> 53851 | T8: =+R8 -> 686 | U8: =+S8 -> 53851 | V8: Hùng Nguyên | W8: 45324 | X8: =+W8+'Dieu kien giao hang'!$C$21 -> 45328 | Y8: =+X8+'Dieu kien giao hang'!$C$22 -> 45330
A9: A-2 | B9: TÔN TẤM-LINER INOX | C9: PL1.5x1220x2440 | D9: SUH409 | E9: m2 | F9: =+H9/G9 -> 11.895 | G9: 2220.0992 | H9: 26408.08 | K9: 2510 | L9: =+K9*F9 -> 29856.45 | M9: =+K9+I9 -> 2510 | N9: =+L9+J9 -> 29856.45 | O9: 45371 | R9: =+M9-P9 -> 2510 | S9: =+N9-Q9 -> 29856.45 | AB9: =+R9 -> 2510 | AC9: =+S9 -> 29856.45 | AD9: GNEE | AE9: 45323 | AF9: =+AE9+'Dieu kien giao hang'!$C$6 -> 45328 | AG9: =AF9+'Dieu kien giao hang'!$C$7 -> 45348 | AH9: =AG9+'Dieu kien giao hang'!$C$8 -> 45353 | AI9: =AH9+'Dieu kien giao hang'!$C$10 -> 45356 | AJ9: =AI9+'Dieu kien giao hang'!$C$13 -> 45368
A10: A-3 | B10: TÔN TẤM-LINER INOX | C10: PL2x1220x2440 | D10: SUH409 | E10: m2 | F10: =+H10/G10 -> 15.968596 | G10: 736.67591 | H10: 11763.68 | K10: 835 | L10: =+K10*F10 -> 13333.778 | M10: =+K10+I10 -> 835 | N10: =+L10+J10 -> 13333.778 | O10: 45371 | R10: =+M10-P10 -> 835 | S10: =+N10-Q10 -> 13333.778 | AB10: =+R10 -> 835 | AC10: =+S10 -> 13333.778 | AD10: GNEE | AE10: 45323 | AF10: =+AE10+'Dieu kien giao hang'!$C$6 -> 45328 | AG10: =AF10+'Dieu kien giao hang'!$C$7 -> 45348 | AH10: =AG10+'Dieu kien giao hang'!$C$8 -> 45353 | AI10: =AH10+'Dieu kien giao hang'!$C$10 -> 45356 | AJ10: =AI10+'Dieu kien giao hang'!$C$13 -> 45368
A11: A-4 | B11: TÔN TẤM | C11: PL3 | D11: SUH409 | E11: m2 | F11: =+H11/G11 -> 23.55 | G11: 2.2573248 | H11: 53.16 | K11: 3 | L11: =+K11*F11 -> 70.65 | M11: =+K11+I11 -> 3 | N11: =+L11+J11 -> 70.65 | O11: 45371 | R11: =+M11-P11 -> 3 | S11: =+N11-Q11 -> 70.65 | AB11: =+R11 -> 3 | AC11: =+S11 -> 70.65 | AD11: GNEE | AE11: 45323 | AF11: =+AE11+'Dieu kien giao hang'!$C$6 -> 45328 | AG11: =AF11+'Dieu kien giao hang'!$C$7 -> 45348 | AH11: =AG11+'Dieu kien giao hang'!$C$8 -> 45353 | AI11: =AH11+'Dieu kien giao hang'!$C$10 -> 45356 | AJ11: =AI11+'Dieu kien giao hang'!$C$13 -> 45368
A12: A-5 | B12: TÔN TẤM | C12: PL6 | D12: A-240 TP304 | E12: m2 | F12: =+H12/G12 -> 47.1 | G12: 0.072186837 | H12: 3.4 | K12: 1 | L12: =+K12*F12 -> 47.1 | M12: =+K12+I12 -> 1 | N12: =+L12+J12 -> 47.1 | O12: 45371 | R12: =+M12-P12 -> 1 | S12: =+N12-Q12 -> 47.1 | AB12: =+R12 -> 1 | AC12: =+S12 -> 47.1 | AD12: GNEE | AE12: 45323 | AF12: =+AE12+'Dieu kien giao hang'!$C$6 -> 45328 | AG12: =AF12+'Dieu kien giao hang'!$C$7 -> 45348 | AH12: =AG12+'Dieu kien giao hang'!$C$8 -> 45353 | AI12: =AH12+'Dieu kien giao hang'!$C$10 -> 45356 | AJ12: =AI12+'Dieu kien giao hang'!$C$13 -> 45368
A13: A-6 | B13: TÔN TẤM | C13: PL6x2000x12000 | D13: SS400 | E13: m2 | F13: =+H13/G13 -> 47.1 | G13: 1159.5244 | H13: 54613.6 | K13: =1.12*G13 -> 1298.6673 | L13: =+K13*F13 -> 61167.232 | M13: =+K13+I13 -> 1298.6673 | N13: =+L13+J13 -> 61167.232 | O13: 45338 | R13: =+M13-P13 -> 1298.6673 | S13: =+N13-Q13 -> 61167.232 | T13: =+R13 -> 1298.6673 | U13: =+S13 -> 61167.232 | V13: Hùng Nguyên | W13: 45324 | X13: =+W13+'Dieu kien giao hang'!$C$21 -> 45328 | Y13: =+X13+'Dieu kien giao hang'!$C$22 -> 45330
A14: A-7 | B14: TÔN TẤM CUỘN CẮT | C14: PL6X1500X7100 | D14: SS400 | E14: m2 | F14: =+H14/G14 -> 47.1 | G14: 216 | H14: 10173.6 | K14: =1.08*G14 -> 233.28 | L14: =+K14*F14 -> 10987.488 | M14: =+K14+I14 -> 233.28 | N14: =+L14+J14 -> 10987.488 | O14: 45338 | R14: =+M14-P14 -> 233.28 | S14: =+N14-Q14 -> 10987.488 | T14: =+R14 -> 233.28 | U14: =+S14 -> 10987.488 | V14: Hùng Nguyên | W14: 45324 | X14: =+W14+'Dieu kien giao hang'!$C$21 -> 45328 | Y14: =+X14+'Dieu kien giao hang'!$C$22 -> 45330
A15: A-8 | B15: TÔN TẤM CUỘN CẮT | C15: PL6x1500x9000 | D15: SS400 | E15: m2 | F15: =+H15/G15 -> 47.1 | G15: 408 | H15: 19216.8 | K15: =1.08*G15 -> 440.64 | L15: =+K15*F15 -> 20754.144 | M15: =+K15+I15 -> 440.64 | N15: =+L15+J15 -> 20754.144 | O15: 45338 | R15: =+M15-P15 -> 440.64 | S15: =+N15-Q15 -> 20754.144 | T15: =+R15 -> 440.64 | U15: =+S15 -> 20754.144 | V15: Hùng Nguyên | W15: 45324 | X15: =+W15+'Dieu kien giao hang'!$C$21 -> 45328 | Y15: =+X15+'Dieu kien giao hang'!$C$22 -> 45330
A16: A-9 | B16: TÔN TẤM CUỘN CẮT | C16: PL6X1500X11000 | D16: SS400 | E16: m2 | F16: =+H16/G16 -> 47.1 | G16: 720 | H16: 33912 | K16: =1.08*G16 -> 777.6 | L16: =+K16*F16 -> 36624.96 | M16: =+K16+I16 -> 777.6 | N16: =+L16+J16 -> 36624.96 | O16: 45338 | R16: =+M16-P16 -> 777.6 | S16: =+N16-Q16 -> 36624.96 | T16: =+R16 -> 777.6 | U16: =+S16 -> 36624.96 | V16: Hùng Nguyên | W16: 45324 | X16: =+W16+'Dieu kien giao hang'!$C$21 -> 45328 | Y16: =+X16+'Dieu kien giao hang'!$C$22 -> 45330
A17: A-10 | B17: TÔN TẤM CUỘN CẮT | C17: PL8X1500X7100 | D17: SS400 | E17: m2 | F17: =+H17/G17 -> 62.8 | G17: 232 | H17: 14569.6 | K17: =1.08*G17 -> 250.56 | L17: =+K17*F17 -> 15735.168 | M17: =+K17+I17 -> 250.56 | N17: =+L17+J17 -> 15735.168 | O17: 45338 | R17: =+M17-P17 -> 250.56 | S17: =+N17-Q17 -> 15735.168 | T17: =+R17 -> 250.56 | U17: =+S17 -> 15735.168 | V17: Hùng Nguyên | W17: 45324 | X17: =+W17+'Dieu kien giao hang'!$C$21 -> 45328 | Y17: =+X17+'Dieu kien giao hang'!$C$22 -> 45330
A18: A-11 | B18: TÔN TẤM CUỘN CẮT | C18: PL8X1500X9000 | D18: SS400 | E18: m2 | F18: =+H18/G18 -> 62.8 | G18: 140 | H18: 8792 | K18: =1.08*G18 -> 151.2 | L18: =+K18*F18 -> 9495.36 | M18: =+K18+I18 -> 151.2 | N18: =+L18+J18 -> 9495.36 | O18: 45338 | R18: =+M18-P18 -> 151.2 | S18: =+N18-Q18 -> 9495.36 | T18: =+R18 -> 151.2 | U18: =+S18 -> 9495.36 | V18: Hùng Nguyên | W18: 45324 | X18: =+W18+'Dieu kien giao hang'!$C$21 -> 45328 | Y18: =+X18+'Dieu kien giao hang'!$C$22 -> 45330
A19: A-12 | B19: TÔN TẤM CUỘN CẮT | C19: PL8X1500X11000 | D19: SS400 | E19: m2 | F19: =+H19/G19 -> 62.8 | G19: 240 | H19: 15072 | K19: =1.08*G19 -> 259.2 | L19: =+K19*F19 -> 16277.76 | M19: =+K19+I19 -> 259.2 | N19: =+L19+J19 -> 16277.76 | O19: 45338 | R19: =+M19-P19 -> 259.2 | S19: =+N19-Q19 -> 16277.76 | T19: =+R19 -> 259.2 | U19: =+S19 -> 16277.76 | V19: Hùng Nguyên | W19: 45324 | X19: =+W19+'Dieu kien giao hang'!$C$21 -> 45328 | Y19: =+X19+'Dieu kien giao hang'!$C$22 -> 45330
A20: A-13 | B20: TÔN TẤM | C20: PL8X2000X12000 | D20: SS400 | E20: m2 | F20: =+H20/G20 -> 62.8 | G20: 140 | H20: 8792 | K20: =1.12*G20 -> 156.8 | L20: =+K20*F20 -> 9847.04 | M20: =+K20+I20 -> 156.8 | N20: =+L20+J20 -> 9847.04 | O20: 45338 | R20: =+M20-P20 -> 156.8 | S20: =+N20-Q20 -> 9847.04 | T20: =+R20 -> 156.8 | U20: =+S20 -> 9847.04 | V20: Hùng Nguyên | W20: 45324 | X20: =+W20+'Dieu kien giao hang'!$C$21 -> 45328 | Y20: =+X20+'Dieu kien giao hang'!$C$22 -> 45330
A21: A-14 | B21: TÔN TẤM | C21: PL10 | D21: A-240 TP304 | E21: m2 | F21: =+H21/G21 -> 78.5 | G21: 0.41579618 | H21: 32.64 | K21: =1.12*G21 -> 0.46569172 | L21: =+K21*F21 -> 36.5568 | M21: =+K21+I21 -> 0.46569172 | N21: =+L21+J21 -> 36.5568 | O21: 45371 | R21: =+M21-P21 -> 0.46569172 | S21: =+N21-Q21 -> 36.5568 | AB21: =+R21 -> 0.46569172 | AC21: =+S21 -> 36.5568 | AD21: GNEE | AE21: 45323 | AF21: =+AE21+'Dieu kien giao hang'!$C$6 -> 45328 | AG21: =AF21+'Dieu kien giao hang'!$C$7 -> 45348 | AH21: =AG21+'Dieu kien giao hang'!$C$8 -> 45353 | AI21: =AH21+'Dieu kien giao hang'!$C$10 -> 45356 | AJ21: =AI21+'Dieu kien giao hang'!$C$13 -> 45368
A22: A-15 | B22: TÔN TẤM | C22: PL10x2000x12000 | D22: A572-GR.50 | E22: m2 | F22: =+H22/G22 -> 78.5 | G22: 48.524841 | H22: 3809.2 | K22: =1.12*G22 -> 54.347822 | L22: =+K22*F22 -> 4266.304 | M22: =+K22+I22 -> 54.347822 | N22: =+L22+J22 -> 4266.304 | O22: 45338 | R22: =+M22-P22 -> 54.347822 | S22: =+N22-Q22 -> 4266.304 | T22: =+R22 -> 54.347822 | U22: =+S22 -> 4266.304 | V22: Hùng Nguyên | W22: 45324 | X22: =+W22+'Dieu kien giao hang'!$C$21 -> 45328 | Y22: =+X22+'Dieu kien giao hang'!$C$22 -> 45330
A23: A-16 | B23: TÔN TẤM | C23: PL12x2000x12000 | D23: A572-GR.50 | E23: m2 | F23: =+H23/G23 -> 94.2 | G23: 1.0292994 | H23: 96.96 | K23: =1.12*G23 -> 1.1528153 | L23: =+K23*F23 -> 108.5952 | M23: =+K23+I23 -> 1.1528153 | N23: =+L23+J23 -> 108.5952 | O23: 45338 | R23: =+M23-P23 -> 1.1528153 | S23: =+N23-Q23 -> 108.5952 | T23: =+R23 -> 1.1528153 | U23: =+S23 -> 108.5952 | V23: Hùng Nguyên | W23: 45324 | X23: =+W23+'Dieu kien giao hang'!$C$21 -> 45328 | Y23: =+X23+'Dieu kien giao hang'!$C$22 -> 45330
A24: A-17 | B24: TÔN TẤM | C24: PL12x2000x12000 | D24: SS400 | E24: m2 | F24: =+H24/G24 -> 94.2 | G24: 8.8276008 | H24: 831.56 | K24: =1.12*G24 -> 9.886913 | L24: =+K24*F24 -> 931.3472 | M24: =+K24+I24 -> 9.886913 | N24: =+L24+J24 -> 931.3472 | O24: 45338 | R24: =+M24-P24 -> 9.886913 | S24: =+N24-Q24 -> 931.3472 | T24: =+R24 -> 9.886913 | U24: =+S24 -> 931.3472 | V24: Hùng Nguyên | W24: 45324 | X24: =+W24+'Dieu kien giao hang'!$C$21 -> 45328 | Y24: =+X24+'Dieu kien giao hang'!$C$22 -> 45330
A25: A-18 | B25: TÔN TẤM | C25: PL16x2000x12000 | D25: A572-GR.50 | E25: m2 | F25: =+H25/G25 -> 125.6 | G25: 12.253503 | H25: 1539.04 | K25: =1.12*G25 -> 13.723924 | L25: =+K25*F25 -> 1723.7248 | M25: =+K25+I25 -> 13.723924 | N25: =+L25+J25 -> 1723.7248 | O25: 45338 | R25: =+M25-P25 -> 13.723924 | S25: =+N25-Q25 -> 1723.7248 | T25: =+R25 -> 13.723924 | U25: =+S25 -> 1723.7248 | V25: Hùng Nguyên | W25: 45324 | X25: =+W25+'Dieu kien giao hang'!$C$21 -> 45328 | Y25: =+X25+'Dieu kien giao hang'!$C$22 -> 45330
A26: A-19 | B26: TÔN TẤM | C26: PL20x2000x12000 | D26: A572-GR.50 | E26: m2 | F26: =+H26/G26 -> 157 | G26: 208.2242 | H26: 32691.2 | K26: =1.12*G26 -> 233.21111 | L26: =+K26*F26 -> 36614.144 | M26: =+K26+I26 -> 233.21111 | N26: =+L26+J26 -> 36614.144 | O26: 45338 | R26: =+M26-P26 -> 233.21111 | S26: =+N26-Q26 -> 36614.144 | T26: =+R26 -> 233.21111 | U26: =+S26 -> 36614.144 | V26: Hùng Nguyên | W26: 45324 | X26: =+W26+'Dieu kien giao hang'!$C$21 -> 45328 | Y26: =+X26+'Dieu kien giao hang'!$C$22 -> 45330
A27: A-20 | B27: TÔN TẤM | C27: PL22x2000x12000 | D27: A572-GR.50 | E27: m2 | F27: =+H27/G27 -> 172.7 | G27: 148.54105 | H27: 25653.04 | K27: =1.12*G27 -> 166.36598 | L27: =+K27*F27 -> 28731.405 | M27: =+K27+I27 -> 166.36598 | N27: =+L27+J27 -> 28731.405 | O27: 45338 | R27: =+M27-P27 -> 166.36598 | S27: =+N27-Q27 -> 28731.405 | T27: =+R27 -> 166.36598 | U27: =+S27 -> 28731.405 | V27: Hùng Nguyên | W27: 45324 | X27: =+W27+'Dieu kien giao hang'!$C$21 -> 45328 | Y27: =+X27+'Dieu kien giao hang'!$C$22 -> 45330
A28: A-21 | B28: TÔN TẤM | C28: PL25 | D28: A572-GR.50 | E28: m2 | F28: =+H28/G28 -> 196.25 | G28: 4.485707 | H28: 880.32 | K28: =1.12*G28 -> 5.0239918 | L28: =+K28*F28 -> 985.9584 | M28: =+K28+I28 -> 5.0239918 | N28: =+L28+J28 -> 985.9584 | O28: 45338 | R28: =+M28-P28 -> 5.0239918 | S28: =+N28-Q28 -> 985.9584 | T28: =+R28 -> 5.0239918 | U28: =+S28 -> 985.9584 | V28: Hùng Nguyên | W28: 45324 | X28: =+W28+'Dieu kien giao hang'!$C$21 -> 45328 | Y28: =+X28+'Dieu kien giao hang'!$C$22 -> 45330
A29: A-22 | B29: TÔN TẤM | C29: PL28 | D29: A572-GR.50 | E29: m2 | F29: =+H29/G29 -> 219.8 | G29: 5.099909 | H29: 1120.96 | K29: =1.12*G29 -> 5.7118981 | L29: =+K29*F29 -> 1255.4752 | M29: =+K29+I29 -> 5.7118981 | N29: =+L29+J29 -> 1255.4752 | O29: 45338 | R29: =+M29-P29 -> 5.7118981 | S29: =+N29-Q29 -> 1255.4752 | T29: =+R29 -> 5.7118981 | U29: =+S29 -> 1255.4752 | V29: Hùng Nguyên | W29: 45324 | X29: =+W29+'Dieu kien giao hang'!$C$21 -> 45328 | Y29: =+X29+'Dieu kien giao hang'!$C$22 -> 45330
A30: A-23 | B30: TÔN TẤM | C30: PL32x2000x6000 | D30: A572-GR.50 | E30: m2 | F30: =+H30/G30 -> 251.2 | G30: 7.6261146 | H30: 1915.68 | K30: =1.12*G30 -> 8.5412484 | L30: =+K30*F30 -> 2145.5616 | M30: =+K30+I30 -> 8.5412484 | N30: =+L30+J30 -> 2145.5616 | O30: 45338 | R30: =+M30-P30 -> 8.5412484 | S30: =+N30-Q30 -> 2145.5616 | T30: =+R30 -> 8.5412484 | U30: =+S30 -> 2145.5616 | V30: Hùng Nguyên | W30: 45324 | X30: =+W30+'Dieu kien giao hang'!$C$21 -> 45328 | Y30: =+X30+'Dieu kien giao hang'!$C$22 -> 45330
A31: A-24 | B31: THÉP HÌNH C | C31: C125X65X6X8-12000L | D31: SS400 | E31: m | F31: =+H31/G31 -> 12.511673 | G31: 373.52 | H31: 4673.36 | K31: =1.06*G31 -> 395.9312 | L31: =+K31*F31 -> 4953.7616 | M31: =+K31+I31 -> 395.9312 | N31: =+L31+J31 -> 4953.7616 | O31: 45338 | R31: =+M31-P31 -> 395.9312 | S31: =+N31-Q31 -> 4953.7616 | T31: =+R31 -> 395.9312 | U31: =+S31 -> 4953.7616 | V31: Hùng Nguyên | W31: 45324 | X31: =+W31+'Dieu kien giao hang'!$C$21 -> 45328 | Y31: =+X31+'Dieu kien giao hang'!$C$22 -> 45330
A32: A-25 | B32: THÉP HÌNH C | C32: C150X75X6.5X10-12000L | D32: SS400 | E32: m | F32: =+H32/G32 -> 18.612228 | G32: 151.264 | H32: 2815.36 | K32: =1.06*G32 -> 160.33984 | L32: =+K32*F32 -> 2984.2816 | M32: =+K32+I32 -> 160.33984 | N32: =+L32+J32 -> 2984.2816 | O32: 45338 | R32: =+M32-P32 -> 160.33984 | S32: =+N32-Q32 -> 2984.2816 | T32: =+R32 -> 160.33984 | U32: =+S32 -> 2984.2816 | V32: Hùng Nguyên | W32: 45324 | X32: =+W32+'Dieu kien giao hang'!$C$21 -> 45328 | Y32: =+X32+'Dieu kien giao hang'!$C$22 -> 45330
A33: A-26 | B33: THÉP HÌNH C | C33: C180X75X7X10.5-12000L | D33: SS400 | E33: m | F33: =+H33/G33 -> 20.123097 | G33: 1508.4 | H33: 30353.68 | K33: =1.06*G33 -> 1598.904 | L33: =+K33*F33 -> 32174.901 | M33: =+K33+I33 -> 1598.904 | N33: =+L33+J33 -> 32174.901 | O33: 45338 | R33: =+M33-P33 -> 1598.904 | S33: =+N33-Q33 -> 32174.901 | T33: =+R33 -> 1598.904 | U33: =+S33 -> 32174.901 | V33: Hùng Nguyên | W33: 45324 | X33: =+W33+'Dieu kien giao hang'!$C$21 -> 45328 | Y33: =+X33+'Dieu kien giao hang'!$C$22 -> 45330
A34: A-27 | B34: THÉP HÌNH C | C34: C200X80X7.5X11-12000L | D34: SS400 | E34: m | F34: =+H34/G34 -> 22.773663 | G34: 550.896 | H34: 12545.92 | K34: =1.06*G34 -> 583.94976 | L34: =+K34*F34 -> 13298.675 | M34: =+K34+I34 -> 583.94976 | N34: =+L34+J34 -> 13298.675 | O34: 45338 | R34: =+M34-P34 -> 583.94976 | S34: =+N34-Q34 -> 13298.675 | T34: =+R34 -> 583.94976 | U34: =+S34 -> 13298.675 | V34: Hùng Nguyên | W34: 45324 | X34: =+W34+'Dieu kien giao hang'!$C$21 -> 45328 | Y34: =+X34+'Dieu kien giao hang'!$C$22 -> 45330
A35: A-28 | B35: THÉP HÌNH C | C35: C200X90X8X13.5-12000L | D35: SS400 | E35: m | F35: =+H35/G35 -> 30.341183 | G35: 152.88 | H35: 4638.56 | K35: =1.06*G35 -> 162.0528 | L35: =+K35*F35 -> 4916.8736 | M35: =+K35+I35 -> 162.0528 | N35: =+L35+J35 -> 4916.8736 | O35: 45338 | R35: =+M35-P35 -> 162.0528 | S35: =+N35-Q35 -> 4916.8736 | T35: =+R35 -> 162.0528 | U35: =+S35 -> 4916.8736 | V35: Hùng Nguyên | W35: 45324 | X35: =+W35+'Dieu kien giao hang'!$C$21 -> 45328 | Y35: =+X35+'Dieu kien giao hang'!$C$22 -> 45330
A36: A-29 | B36: THÉP HÌNH C | C36: C250X90X9X13-12000L | D36: SS400 | E36: m | F36: =+H36/G36 -> 34.594627 | G36: 66.408 | H36: 2297.36 | K36: =1.06*G36 -> 70.39248 | L36: =+K36*F36 -> 2435.2016 | M36: =+K36+I36 -> 70.39248 | N36: =+L36+J36 -> 2435.2016 | O36: 45338 | R36: =+M36-P36 -> 70.39248 | S36: =+N36-Q36 -> 2435.2016 | T36: =+R36 -> 70.39248 | U36: =+S36 -> 2435.2016 | V36: Hùng Nguyên | W36: 45324 | X36: =+W36+'Dieu kien giao hang'!$C$21 -> 45328 | Y36: =+X36+'Dieu kien giao hang'!$C$22 -> 45330
A37: A-30 | B37: THÉP HÌNH H | C37: H150X150X7X10-12000L | D37: SS400 | E37: m | F37: =+H37/G37 -> 24.855967 | G37: 19.44 | H37: 483.2 | K37: =1.06*G37 -> 20.6064 | L37: =+K37*F37 -> 512.192 | M37: =+K37+I37 -> 20.6064 | N37: =+L37+J37 -> 512.192 | O37: 45338 | R37: =+M37-P37 -> 20.6064 | S37: =+N37-Q37 -> 512.192 | T37: =+R37 -> 20.6064 | U37: =+S37 -> 512.192 | V37: Hùng Nguyên | W37: 45324 | X37: =+W37+'Dieu kien giao hang'!$C$21 -> 45328 | Y37: =+X37+'Dieu kien giao hang'!$C$22 -> 45330
A38: A-31 | B38: THÉP HÌNH H | C38: H194X150X6X9-12000L | D38: SS400 | E38: m | F38: =+H38/G38 -> 30.612113 | G38: 6.208 | H38: 190.04 | K38: =1.06*G38 -> 6.58048 | L38: =+K38*F38 -> 201.4424 | M38: =+K38+I38 -> 6.58048 | N38: =+L38+J38 -> 201.4424 | O38: 45338 | R38: =+M38-P38 -> 6.58048 | S38: =+N38-Q38 -> 201.4424 | T38: =+R38 -> 6.58048 | U38: =+S38 -> 201.4424 | V38: Hùng Nguyên | W38: 45324 | X38: =+W38+'Dieu kien giao hang'!$C$21 -> 45328 | Y38: =+X38+'Dieu kien giao hang'!$C$22 -> 45330
A39: A-32 | B39: THÉP HÌNH H | C39: H244X175X7X11-12000L | D39: SS400 | E39: m | F39: =+H39/G39 -> 44.14586 | G39: 234.856 | H39: 10367.92 | K39: =1.06*G39 -> 248.94736 | L39: =+K39*F39 -> 10989.995 | M39: =+K39+I39 -> 248.94736 | N39: =+L39+J39 -> 10989.995 | O39: 45338 | R39: =+M39-P39 -> 248.94736 | S39: =+N39-Q39 -> 10989.995 | T39: =+R39 -> 248.94736 | U39: =+S39 -> 10989.995 | V39: Hùng Nguyên | W39: 45324 | X39: =+W39+'Dieu kien giao hang'!$C$21 -> 45328 | Y39: =+X39+'Dieu kien giao hang'!$C$22 -> 45330
